Workbook
Name IQ_CH: 110000
Name IQ_CQ: 5000
Name IQ_CY: 10000
Name IQ_DAILY: 500000
Name IQ_FH: 100000
Name IQ_FQ: 500
Name IQ_FY: 1000
Name IQ_LTM: 2000
Name IQ_MONTH: 15000
Name IQ_NTM: 6000
Name IQ_WEEK: 50000
Name IQ_YTD: 3000

Sheet Data Template
A1: AllLife - Performance Data
I2: *Forecast | J2: *Forecast | K2: *Forecast | AL2: *Forecast | AM2: *Forecast | AN2: *Forecast | AP2: *Forecast | AQ2: *Forecast | AR2: *Forecast | AS2: *Forecast | DQ2: *Forecast | DR2: *Forecast | DT2: *Forecast | DU2: *Forecast | DW2: *Forecast | DX2: *Forecast | ED2: *Forecast | EE2: *Forecast | EF2: *Forecast | EG2: *Forecast | EH2: *Forecast | EI2: *Forecast | EJ2: *Forecast | EK2: *Forecast | EL2: *Forecast | EM2: *Forecast | EN2: *Forecast | EO2: *Forecast | ER2: *Forecast | ES2: *Forecast | ET2: *Forecast | EU2: *Forecast | EV2: *Forecast | EW2: *Forecast
B3: Financial Metrics | D3: 2018 | E3: 2019 | F3: 2020 | G3: 2021 | H3: 2022 | I3: 2023 | J3: 2024 | K3: 2025 | L3: Q1 2018 | M3: Q2 2018 | N3: Q3 2018 | O3: Q4 2018 | Q3: Q1 2019 | R3: Q2 2019 | S3: Q3 2019 | T3: Q4 2019 | V3: Q1 2020 | W3: Q2 2020 | X3: Q3 2020 | Y3: Q4 2020 | AA3: Q1 2021 | AB3: Q2 2021 | AC3: Q3 2021 | AD3: Q4 2021 | AF3: Q1 2022 | AG3: Q2 2022 | AH3: Q3 2022 | AI3: Q4 2022 | AK3: Q1 2023 | AL3: Q2 2023 | AM3: Q3 2023 | AN3: Q4 2023 | AP3: Q1 2024 | AQ3: Q2 2024 | AR3: Q3 2024 | AS3: Q4 2024 | AU3: Q1 2025 | AV3: Q2 2025 | AW3: Q3 2025 | AX3: Q4 2025 | AZ3: 43101 | BA3: 43132 | BB3: 43160 | BC3: 43191 | BD3: 43221 | BE3: 43252 | BF3: 43282 | BG3: 43313 | BH3: 43344 | BI3: 43374 | BJ3: 43405 | BK3: 43435 | BM3: 43466 | BN3: 43497 | BO3: 43525 | BP3: 43556 | BQ3: 43586 | BR3: 43617 | BS3: 43647 | BT3: 43678 | BU3: 43709 | BV3: 43739 | BW3: 43770 | BX3: 43800 | BZ3: 43831 | CA3: 43863 | CB3: 43895 | CC3: 43927 | CD3: 43959 | CE3: 43991 | CF3: 44023 | CG3: 44055 | CH3: 44087 | CI3: 44119 | CJ3: 44151 | CK3: 44183 | CM3: 44197 | CN3: 44228 | CO3: 44256 | CP3: 44287 | CQ3: 44317 | CR3: 44348 | CS3: 44378 | CT3: 44409 | CU3: 44440 | CV3: 44470 | CW3: 44501 | CX3: 44531 | CZ3: 44562 | DA3: 44593 | DB3: 44621 | DC3: 44652 | DD3: 44682 | DE3: 44713 | DF3: 44743 | DG3: 44774 | DH3: 44805 | DI3: 44835 | DJ3: 44866 | DK3: 44896 | DM3: 44927 | DN3: 44958 | DO3: 44986 | DP3: 45017 | DQ3: 45047 | DR3: 45078 | DS3: 45108 | DT3: 45139 | DU3: 45170 | DV3: 45200 | DW3: 45231 | DX3: 45261 | ED3: 45292 | EE3: 45323 | EF3: 45352 | EG3: 45383 | EH3: 45413 | EI3: 45444 | EJ3: 45474 | EK3: 45505 | EL3: 45536 | EM3: 45566 | EN3: 45597 | EO3: 45627 | ER3: 45658 | ES3: 45689 | ET3: 45717 | EU3: 45748 | EV3: 45778 | EW3: 45809
B4: TCTC - Ongoing Revenue (ZAR 000s) | D4: =+SUM(AZ4:BK4) -> 134869.4 | E4: =+SUM(BM4:BX4) -> 146663.24 | F4: =+SUM(V4:Y4) -> 160456.98 | G4: =SUM(AA4:AD4) -> 185124.63 | H4: =SUM(AF4:AI4) -> 186565.14 | I4: =SUM(AK4:AN4) -> 207679.22 | J4: =SUM(AP4:AR4) -> 136383.1 | K4: =SUM(AU4:AX4) -> 99566.261 | L4: =+SUM(AZ4:BB4) -> 33509.468 | M4: =+SUM(BC4:BE4) -> 33425.235 | N4: =+SUM(BF4:BH4) -> 34066.433 | O4: =+SUM(BI4:BK4) -> 33868.264 | Q4: =+SUM(BM4:BO4) -> 33357.508 | R4: =+SUM(BP4:BR4) -> 37922.455 | S4: =+SUM(BS4:BU4) -> 39427.697 | T4: =+SUM(BV4:BX4) -> 35955.581 | V4: =+SUM(BZ4:CB4) -> 40558.574 | W4: =SUM(CC4:CE4) -> 39979.771 | X4: =SUM(CF4:CH4) -> 41427.316 | Y4: =SUM(CI4:CK4) -> 38491.314 | AA4: =SUM(CM4:CO4) -> 44413.854 | AB4: =SUM(CP4:CR4) -> 45894.424 | AC4: =SUM(CS4:CU4) -> 47614.213 | AD4: =SUM(CV4:CX4) -> 47202.14 | AF4: =SUM(CZ4:DB4) -> 44137.427 | AG4: =SUM(DC4:DE4) -> 46840.714 | AH4: =SUM(DF4:DH4) -> 47806 | AI4: =SUM(DI4:DK4) -> 47781 | AK4: =SUM(DM4:DO4) -> 49335 | AL4: =SUM(DP4:DR4) -> 51066.572 | AM4: =SUM(DS4:DU4) -> 51541.196 | AN4: =SUM(DV4:DX4) -> 55736.452 | AP4: =SUM(ED4:EF4) -> 41147.953 | AQ4: =SUM(EG4:EI4) -> 47326.009 | AR4: =SUM(EJ4:EL4) -> 47909.135 | AS4: =SUM(EM4:EO4) -> 48048.681 | AU4: =SUM(ER4:ET4) -> 49322.044 | AV4: =SUM(EU4:EW4) -> 50244.217 | AZ4: 10410.986 | BA4: 11854.897 | BB4: 11243.584 | BC4: 11497.606 | BD4: 10633.45 | BE4: 11294.178 | BF4: 11076.425 | BG4: 11222.903 | BH4: 11767.104 | BI4: 11390.247 | BJ4: 11381.752 | BK4: 11096.264 | BM4: 10265.102 | BN4: 11590.803 | BO4: 11501.603 | BP4: 12315.045 | BQ4: 12975.809 | BR4: 12631.601 | BS4: 12979.747 | BT4: 13118.101 | BU4: 13329.849 | BV4: 11994.41 | BW4: 12245.072 | BX4: 11716.099 | BZ4: 13490.737 | CA4: 13589.184 | CB4: 13478.653 | CC4: 14030.541 | CD4: 13859.78 | CE4: 12089.451 | CF4: 14008.059 | CG4: 13522.225 | CH4: 13897.032 | CI4: 9970.7681 | CJ4: 14395.089 | CK4: 14125.457 | CM4: 14430.659 | CN4: 15369.368 | CO4: 14613.828 | CP4: 15173.655 | CQ4: 15042.082 | CR4: 15678.687 | CS4: 15966.386 | CT4: 16454.974 | CU4: 15192.852 | CV4: 16108.346 | CW4: 15728.164 | CX4: 15365.63 | CZ4: 14443.278 | DA4: 15020.234 | DB4: 14673.914 | DC4: 15861.641 | DD4: 15069.824 | DE4: 15909.249 | DF4: 16062 | DG4: 15879 | DH4: 15865 | DI4: 16030 | DJ4: 16144 | DK4: 15607 | DM4: 16726 | DN4: 16365 | DO4: 16244 | DP4: =[4]Ebitda!$AC$19/1000 -> 16851.439 | DQ4: =[4]Ebitda!$AD$19/1000 -> 16773.544 | DR4: =([4]Ebitda!$AN$3+[4]Ebitda!$AN$5)/1000 -> 17441.589 | DS4: =[4]Ebitda!$AH$19/1000 -> 17010.495 | DT4: =[4]Ebitda!$AI$19/1000 -> 16979.678 | DU4: =[4]Ebitda!$AJ$19/1000 -> 17551.023 | DV4: =[5]Ebitda!$AM$19/1000 -> 17857.57 | DW4: =[5]Ebitda!$AN$19/1000 -> 19027.73 | DX4: =[5]Ebitda!$AO$19/1000 -> 18851.152 | ED4: =[6]Ebitda!AU17/1000 -> 14030.138 | EE4: =[6]Ebitda!AV17/1000 -> 13471.702 | EF4: =[6]Ebitda!AW17/1000 -> 13646.112 | EG4: =[7]Ebitda!$AZ$15/1000 -> 15653.093 | EH4: =[7]Ebitda!$BA$17/1000 -> 15818.791 | EI4: =[7]Ebitda!$BB$17/1000 -> 15854.125 | EJ4: =[8]Ebitda!$BE$17/1000 -> 15907.698 | EK4: =[8]Ebitda!$BF$17/1000 -> 15960.613 | EL4: =[8]Ebitda!$BG$17/1000 -> 16040.824 | EM4: =[9]Ebitda!$BJ$17/1000 -> 16181.272 | EN4: =[9]Ebitda!$BK$17/1000 -> 16290.874 | EO4: =[9]Ebitda!$BL$17/1000 -> 15576.535 | ER4: =[10]Ebitda!$BO$17/1000 -> 16058.208 | ES4: =[10]Ebitda!$BP$17/1000 -> 16581.164 | ET4: =[10]Ebitda!$BQ$17/1000 -> 16682.673 | EU4: =[18]Ebitda!$BT$15/1000 -> 16748.072 | EV4: =[18]Ebitda!$BU$15/1000 -> 16748.072 | EW4: =[18]Ebitda!$BV$15/1000 -> 16748.072
B5: Monthly VIF sale - Upfront Revenue(ZAR 000s) | D5: =+SUM(AZ5:BK5) -> 0 | E5: =+SUM(BM5:BX5) -> 27136.427 | F5: =+SUM(V5:Y5) -> 47899.796 | G5: =SUM(AA5:AD5) -> 47926.852 | H5: =SUM(AF5:AI5) -> 55918.876 | I5: =SUM(AK5:AN5) -> 43662.339 | J5: =SUM(AP5:AR5) -> 34588 | K5: =SUM(AU5:AX5) -> 26842.131 | L5: =+SUM(AZ5:BB5) -> 0 | M5: =+SUM(BC5:BE5) -> 0 | N5: =+SUM(BF5:BH5) -> 0 | O5: =+SUM(BI5:BK5) -> 0 | Q5: =+SUM(BM5:BO5) -> 0 | R5: =+SUM(BP5:BR5) -> 0 | S5: =+SUM(BS5:BU5) -> 0 | T5: =+SUM(BV5:BX5) -> 27136.427 | V5: =+SUM(BZ5:CB5) -> 9859.4212 | W5: =SUM(CC5:CE5) -> 14245.215 | X5: =SUM(CF5:CH5) -> 12491.118 | Y5: =SUM(CI5:CK5) -> 11304.042 | AA5: =SUM(CM5:CO5) -> 10709.161 | AB5: =SUM(CP5:CR5) -> 12059.362 | AC5: =SUM(CS5:CU5) -> 12200.353 | AD5: =SUM(CV5:CX5) -> 12957.976 | AF5: =SUM(CZ5:DB5) -> 16738.68 | AG5: =SUM(DC5:DE5) -> 9607.1963 | AH5: =SUM(DF5:DH5) -> 19591 | AI5: =SUM(DI5:DK5) -> 9982 | AK5: =SUM(DM5:DO5) -> 8641 | AL5: =SUM(DP5:DR5) -> 10459.924 | AM5: =SUM(DS5:DU5) -> 11494.63 | AN5: =SUM(DV5:DX5) -> 13066.785 | AP5: =SUM(ED5:EF5) -> 11293 | AQ5: =SUM(EG5:EI5) -> 11245 | AR5: =SUM(EJ5:EL5) -> 12050 | AS5: =SUM(EM5:EO5) -> 13658 | AU5: =SUM(ER5:ET5) -> 12153.241 | AV5: =SUM(EU5:EW5) -> 14688.89 | BV5: 23473.09 | BW5: 3663.3374 | BZ5: 4090.5894 | CA5: 1813.5846 | CB5: 3955.2473 | CC5: 2210.1434 | CD5: 8734.2136 | CE5: 3300.8575 | CF5: 3719.0478 | CG5: 3951.4912 | CH5: 4820.5788 | CI5: 3791.5651 | CJ5: 3909.1293 | CK5: 3603.3479 | CM5: 4715.4433 | CN5: 2693.7971 | CO5: 3299.9204 | CP5: 4293.5872 | CQ5: 3850.4609 | CR5: 3915.3137 | CS5: 3577.4261 | CT5: 2993.1975 | CU5: 5629.7298 | CV5: 4519.9921 | CW5: 4245.2963 | CX5: 4192.6871 | CZ5: 3932.5675 | DA5: 2833.2192 | DB5: 9972.8934 | DC5: 3220.5149 | DD5: 3219.5049 | DE5: 3167.1766 | DF5: 6087 | DG5: 9684 | DH5: 3820 | DI5: 3694 | DJ5: 2769 | DK5: 3519 | DM5: 2662 | DN5: 2492 | DO5: 3487 | DP5: 3349.1021 | DQ5: 3516.0345 | DR5: 3594.7878 | DS5: 3488.5756 | DT5: 3914.8025 | DU5: 4091.2517 | DV5: 4037.131 | DW5: 3719.8039 | DX5: 5309.85 | ED5: 3785 | EE5: 3572 | EF5: 3936 | EG5: 4141 | EH5: 3552 | EI5: =EH5 -> 3552 | EJ5: 3954 | EK5: 4383 | EL5: 3713 | EM5: 4243 | EN5: 5036 | EO5: 4379 | ER5: ='[11]Income Statement'!$H$16 -> 3363.7391 | ES5: ='[11]Income Statement'!$J$16 -> 3316.0064 | ET5: ='[11]Income Statement'!$L$16 -> 5473.4956 | EU5: 4905.8004 | EV5: 4900.9314 | EW5: 4882.1577
B6: Once off VIF sales (ZAR 000s) | D6: =+SUM(AZ6:BK6) -> 57209.946 | E6: =+SUM(BM6:BX6) -> 21474.999 | F6: =+SUM(V6:Y6) -> 1726.995 | G6: =SUM(AA6:AD6) -> 0 | H6: =SUM(AF6:AI6) -> 0 | I6: =SUM(AK6:AN6) -> 0 | L6: =+SUM(AZ6:BB6) -> 0 | M6: =+SUM(BC6:BE6) -> 0 | N6: =+SUM(BF6:BH6) -> 0 | O6: =+SUM(BI6:BK6) -> 57209.946 | Q6: =+SUM(BM6:BO6) -> 0 | R6: =+SUM(BP6:BR6) -> 0 | S6: =+SUM(BS6:BU6) -> 16304.781 | T6: =+SUM(BV6:BX6) -> 5170.2178 | V6: =+SUM(BZ6:CB6) -> 1726.995 | W6: =SUM(CC6:CE6) -> 0 | X6: =SUM(CF6:CH6) -> 0 | Y6: =SUM(CI6:CK6) -> 0 | AA6: =SUM(CM6:CO6) -> 0 | AB6: =SUM(CP6:CR6) -> 0 | AC6: =SUM(CS6:CU6) -> 0 | AD6: =SUM(CV6:CX6) -> 0 | AF6: =SUM(CZ6:DB6) -> 0 | AG6: =SUM(DC6:DE6) -> 0 | AH6: =SUM(DF6:DH6) -> 0 | AI6: =SUM(DI6:DK6) -> 0 | AK6: =SUM(DM6:DO6) -> 0 | AL6: =SUM(DP6:DR6) -> 0 | AM6: =SUM(DS6:DU6) -> 0 | AN6: =SUM(DV6:DX6) -> 0 | BI6: =72128817.33/1000 -> 72128.817 | BK6: =-14918871/1000 -> -14918.871 | BT6: 14644.36 | BU6: 1660.4209 | BV6: 1617.6529 | BW6: 1853.4381 | BX6: 1699.1269 | BZ6: 1726.995 | CA6: 0 | CB6: 0 | CC6: 0 | CD6: 0 | CE6: 0 | CF6: 0 | CG6: 0 | CH6: 0 | CI6: 0 | CJ6: 0 | CK6: 0 | CM6: 0 | CN6: 0 | CO6: 0 | CP6: 0 | CQ6: 0 | CR6: 0 | CS6: 0 | CT6: 0 | CU6: 0 | CV6: 0 | CW6: 0 | CX6: 0 | CZ6: 0 | DA6: 0 | DB6: 0 | DC6: 0 | DD6: 0 | DE6: 0 | DF6: 0 | DG6: 0 | DH6: 0 | DI6: 0 | DJ6: 0 | DK6: 0 | DM6: 0 | DN6: 0 | DO6: 0 | DP6: 0 | DQ6: 0 | DR6: 0 | DS6: 0 | DT6: 0 | DU6: 0 | ED6: 0 | EE6: 0 | EF6: 0 | EG6: 0 | EH6: 0 | EI6: 0 | EJ6: 0 | EK6: 0 | EL6: 0 | EM6: 0 | EN6: 0 | EO6: 0 | ER6: 0 | ES6: 0 | ET6: 0 | EU6: 0 | EV6: 0 | EW6: 0
B7: Delta VIF | D7: =+SUM(AZ7:BK7) -> 0 | E7: =+SUM(BM7:BX7) -> 107018.78 | F7: =+SUM(V7:Y7) -> 119880.97 | G7: =SUM(AA7:AD7) -> 145366.77 | H7: =SUM(AF7:AI7) -> 39527.426 | I7: =SUM(AK7:AN7) -> 36587.411 | J7: =SUM(AP7:AR7) -> 38310.886 | K7: =SUM(AU7:AX7) -> 37880.787 | Q7: =+SUM(BM7:BO7) -> 22828.024 | R7: =+SUM(BP7:BR7) -> 28358.465 | S7: =+SUM(BS7:BU7) -> 29398.046 | T7: =+SUM(BV7:BX7) -> 26434.242 | V7: =+SUM(BZ7:CB7) -> 24514.658 | W7: =SUM(CC7:CE7) -> 29465 | X7: =SUM(CF7:CH7) -> 33026.305 | Y7: =SUM(CI7:CK7) -> 32875.011 | AA7: =SUM(CM7:CO7) -> 35967.079 | AB7: =SUM(CP7:CR7) -> 33255.955 | AC7: =SUM(CS7:CU7) -> 40801 | AD7: =SUM(CV7:CX7) -> 35342.734 | AF7: =SUM(CZ7:DB7) -> 27729.426 | AG7: =SUM(DC7:DE7) -> 17143 | AH7: =SUM(DF7:DH7) -> -6000 | AI7: =SUM(DI7:DK7) -> 655 | AK7: =SUM(DM7:DO7) -> 3635.3111 | AL7: =SUM(DP7:DR7) -> 8106.9327 | AM7: =SUM(DS7:DU7) -> 14296.767 | AN7: =SUM(DV7:DX7) -> 10548.4 | AP7: =SUM(ED7:EF7) -> 9147 | AQ7: =SUM(EG7:EI7) -> 15026.344 | AR7: =SUM(EJ7:EL7) -> 14137.542 | AS7: =SUM(EM7:EO7) -> 20311 | AU7: =SUM(ER7:ET7) -> 12809.787 | AV7: =SUM(EU7:EW7) -> 25071 | BM7: 5674.519 | BN7: 8706.5946 | BO7: 8446.9103 | BP7: 8316.6371 | BQ7: 9645.164 | BR7: 10396.664 | BS7: 8638.9051 | BT7: 10091.03 | BU7: 10668.111 | BV7: 11056.949 | BW7: 8663.1288 | BX7: 6714.1643 | BZ7: 6454.9826 | CA7: 8042.4827 | CB7: 10017.193 | CC7: 7910 | CD7: 11006 | CE7: 10549 | CF7: 11600.449 | CG7: 9198.2372 | CH7: 12227.619 | CI7: 11600.372 | CJ7: 12178.698 | CK7: 9095.941 | CM7: 10052.893 | CN7: 13763.029 | CO7: 12151.157 | CP7: 10501.664 | CQ7: 11523.951 | CR7: 11230.34 | CS7: 12497 | CT7: 16304 | CU7: 12000 | CV7: 12017.734 | CW7: 12125 | CX7: 11200 | CZ7: 8010.8711 | DA7: 10159.115 | DB7: 9559.4401 | DC7: 5645 | DD7: 6158 | DE7: 5340 | DF7: -4698 | DG7: -4640 | DH7: 3338 | DI7: -1492 | DJ7: 1547 | DK7: 600 | DM7: 1322.9111 | DN7: 1172.1853 | DO7: 1140.2147 | DP7: 2982.9376 | DQ7: 2662.639 | DR7: 2461.3561 | DS7: 4945.6533 | DT7: 4866.0736 | DU7: 4485.0405 | DV7: 4450.3997 | DW7: 3049 | DX7: 3049 | ED7: 3049 | EE7: 3049 | EF7: 3049 | EG7: 5315.5314 | EH7: 4998.2986 | EI7: 4712.514 | EJ7: 4712.514 | EK7: 4712.514 | EL7: 4712.514 | EM7: 4858 | EN7: 10595 | EO7: =EM7 -> 4858 | ER7: ='[11]Income Statement'!$I$77 -> 3365.934 | ES7: ='[11]Income Statement'!$K$77 -> 4405.9716 | ET7: ='[11]Income Statement'!$M$77 -> 5037.8815 | EU7: 9175 | EV7: 4483 | EW7: 11413
B8: EBITDA (ZAR 000s) | D8: =+SUM(AZ8:BK8) -> 141318.25 | E8: =+SUM(BM8:BX8) -> 169280.88 | F8: =+SUM(V8:Y8) -> 191021.35 | G8: =SUM(AA8:AD8) -> 224452.7 | H8: =SUM(AF8:AI8) -> 191679.54 | I8: =SUM(AK8:AN8) -> 213014.36 | J8: =SUM(AP8:AR8) -> 153264.87 | K8: =SUM(AU8:AX8) -> 100026.77 | L8: =+SUM(AZ8:BB8) -> 18410.82 | M8: =+SUM(BC8:BE8) -> 24515.412 | N8: =+SUM(BF8:BH8) -> 20216.882 | O8: =+SUM(BI8:BK8) -> 78175.132 | Q8: =+SUM(BM8:BO8) -> 24927.502 | R8: =+SUM(BP8:BR8) -> 31752.588 | S8: =+SUM(BS8:BU8) -> 49299.195 | T8: =+SUM(BV8:BX8) -> 63301.593 | V8: =+SUM(BZ8:CB8) -> 43295.169 | W8: =SUM(CC8:CE8) -> 49233.807 | X8: =SUM(CF8:CH8) -> 52106.48 | Y8: =SUM(CI8:CK8) -> 46385.893 | AA8: =SUM(CM8:CO8) -> 53086.324 | AB8: =SUM(CP8:CR8) -> 52539.559 | AC8: =SUM(CS8:CU8) -> 60966.573 | AD8: =SUM(CV8:CX8) -> 57860.24 | AF8: =SUM(CZ8:DB8) -> 51532.79 | AG8: =SUM(DC8:DE8) -> 41192.277 | AH8: =SUM(DF8:DH8) -> 56412 | AI8: =SUM(DI8:DK8) -> 42542.477 | AK8: =SUM(DM8:DO8) -> 42904.447 | AL8: =SUM(DP8:DR8) -> 50004.196 | AM8: =SUM(DS8:DU8) -> 59551.167 | AN8: =SUM(DV8:DX8) -> 60554.555 | AP8: =SUM(ED8:EF8) -> 54355.591 | AQ8: =SUM(EG8:EI8) -> 49357.338 | AR8: =SUM(EJ8:EL8) -> 49551.937 | AS8: =SUM(EM8:EO8) -> 50587.01 | AU8: =SUM(ER8:ET8) -> 52483.902 | AV8: =SUM(EU8:EW8) -> 47542.866 | AZ8: 5930.7867 | BA8: 6572.7671 | BB8: 5907.2662 | BC8: 8055.3498 | BD8: 6111.2928 | BE8: 10348.77 | BF8: 6493.3805 | BG8: 6520.0949 | BH8: 7203.4062 | BI8: 78608.336 | BJ8: 7441.2025 | BK8: -7874.4065 | BM8: 6429.8973 | BN8: 9801.674 | BO8: 8695.9309 | BP8: 9196.6638 | BQ8: 11169.834 | BR8: 11386.09 | BS8: 9807.3872 | BT8: 25891.931 | BU8: 13599.877 | BV8: 36428.679 | BW8: 16922.711 | BX8: 9950.2037 | BZ8: 15058.837 | CA8: 12351.402 | CB8: 15884.93 | CC8: 13545.177 | CD8: 22985.018 | CE8: 12703.612 | CF8: 17530.036 | CG8: 15406.669 | CH8: 19169.775 | CI8: 12722.42 | CJ8: 18210.959 | CK8: 15452.514 | CM8: 17131.694 | CN8: 19084.956 | CO8: 16869.675 | CP8: 17164.358 | CQ8: 17462.878 | CR8: 17912.323 | CS8: 18935.097 | CT8: 21289.772 | CU8: 20741.704 | CV8: 19471.829 | CW8: 18932.289 | CX8: 19456.121 | CZ8: 14496.621 | DA8: 15490.538 | DB8: 21545.632 | DC8: 14181.444 | DD8: 12891.174 | DE8: 14119.659 | DF8: 17341 | DG8: 22251 | DH8: 16820 | DI8: 14707.368 | DJ8: 13911.689 | DK8: 13923.419 | DM8: =13542565.6662154/1000 -> 13542.566 | DN8: =14620880.871786/1000 -> 14620.881 | DO8: =14741000/1000 -> 14741 | DP8: =[4]Ebitda!$AC$5/1000 -> 17467.201 | DQ8: =[4]Ebitda!$AD$5/1000 -> 16538.224 | DR8: =[4]Ebitda!$AE$5/1000 -> 15998.771 | DS8: =[4]Ebitda!$AH$5/1000 -> 18411.546 | DT8: =[4]Ebitda!$AI$5/1000 -> 21472.515 | DU8: =[4]Ebitda!$AJ$5/1000 -> 19667.106 | DV8: =[5]Ebitda!$AM$5/1000 -> 19348.067 | DW8: =[5]Ebitda!$AN$5/1000 -> 21858.421 | DX8: =[5]Ebitda!$AO$5/1000 -> 19348.067 | ED8: =[6]Ebitda!AU5/1000 -> 16127.929 | EE8: =[6]Ebitda!AV5/1000 -> 18700.643 | EF8: =[6]Ebitda!AW5/1000 -> 19527.019 | EG8: =[7]Ebitda!AZ5/1000 -> 16336.67 | EH8: =[7]Ebitda!BA5/1000 -> 16579.645 | EI8: =[7]Ebitda!BB5/1000 -> 16441.023 | EJ8: =[8]Ebitda!$BE$5/1000 -> 16474.6 | EK8: =[8]Ebitda!$BF$5/1000 -> 16507.895 | EL8: =[8]Ebitda!$BG$5/1000 -> 16569.441 | EM8: =[9]Ebitda!$BJ$5/1000 -> 16774.852 | EN8: =[9]Ebitda!$BK$5/1000 -> 16877.66 | EO8: =[9]Ebitda!$BL$5/1000 -> 16934.498 | ER8: =[10]Ebitda!$BO$5/1000 -> 14648.177 | ES8: =[10]Ebitda!$BP$5/1000 -> 16237.989 | ET8: =[10]Ebitda!$BQ$5/1000 -> 21597.736 | EU8: =[18]Ebitda!BT5/1000 -> 15926.623 | EV8: =[18]Ebitda!BU5/1000 -> 15888.089 | EW8: =[18]Ebitda!BV5/1000 -> 15728.154
B10: Operational Metrics | D10: 2018 | E10: 2019 | F10: 2020 | G10: 2021 | H10: 2022 | I10: 2023 | J10: =J3 -> 2024 | K10: =K3 -> 2025 | L10: Q1 2018 | M10: Q2 2018 | N10: Q3 2018 | O10: Q4 2018 | Q10: Q1 2019 | R10: Q2 2019 | S10: Q3 2019 | T10: Q4 2019 | V10: Q1 2020 | W10: Q2 2020 | X10: Q3 2020 | Y10: Q4 2020 | AP10: =AP3 -> Q1 2024 | AQ10: =AQ3 -> Q2 2024 | AR10: =AR3 -> Q3 2024 | AS10: =AS3 -> Q4 2024 | AZ10: 43101 | BA10: 43132 | BB10: 43160 | BC10: 43191 | BD10: 43221 | BE10: 43252 | BF10: 43282 | BG10: 43313 | BH10: 43344 | BI10: 43374 | BJ10: 43405 | BK10: 43435 | BM10: 43466 | BN10: 43497 | BO10: 43525 | BP10: 43556 | BQ10: 43586 | BR10: 43617 | BS10: 43647 | BT10: 43678 | BU10: 43709 | BV10: 43739 | BW10: 43770 | BX10: 43800 | BZ10: 43831 | CA10: 43863 | CB10: 43895 | CC10: 43927 | CD10: 43959 | CE10: 43991 | CF10: 44023 | CG10: 44055 | CH10: 44087 | CI10: 44119 | CJ10: 44151 | CK10: 44183 | CM10: 44197 | CN10: 44228 | CO10: 44256 | CP10: 44287 | CQ10: 44317 | CR10: 44348 | CS10: 44378 | CT10: 44409 | CU10: 44440 | CV10: 44470 | CW10: 44501 | CX10: 44531 | CZ10: 44562 | DA10: 44593 | DB10: 44621 | DC10: 44652 | DD10: 44682 | DE10: 44713 | DF10: 44743 | DG10: 44774 | DH10: 44805 | DI10: 44835 | DJ10: 44866 | DK10: 44896 | DM10: 44927 | DN10: 44958 | DO10: 44986 | DP10: 45017 | DQ10: 45047 | DR10: 45078 | DS10: 45108 | DT10: 45139 | DU10: 45170 | DV10: 45200 | DW10: 45231 | DX10: 45261 | ED10: =ED3 -> 45292 | EE10: =EE3 -> 45323 | EF10: =EF3 -> 45352 | EG10: =EG3 -> 45383 | EH10: =EH3 -> 45413 | EI10: =EI3 -> 45444 | EJ10: =EJ3 -> 45474 | EK10: =EK3 -> 45505 | ... EO10: =EO3 -> 45627 | ER10: =ER3 -> 45658 | ES10: =ES3 -> 45689 | ET10: =ET3 -> 45717 | EU10: =EU3 -> 45748 | EV10: =EV3 -> 45778 | EW10: =EW3 -> 45809
B11: HIV Inceptions (ZAR) | D11: =+SUM(AZ11:BK11) -> 2395.43 | E11: =+SUM(BM11:BX11) -> 3197.001 | F11: =+SUM(V11:Y11) -> 2841273.5 | G11: =SUM(AA11:AD11) -> 3749956 | H11: =SUM(AF11:AI11) -> 2196416 | I11: =SUM(AK11:AN11) -> 2136256.1 | J11: =SUM(AP11:AR11) -> 1257981.6 | K11: =SUM(AU11:AX11) -> 912711 | L11: =+SUM(AZ11:BB11) -> 515.294 | M11: =+SUM(BC11:BE11) -> 641.199 | N11: =+SUM(BF11:BH11) -> 627.314 | O11: =+SUM(BI11:BK11) -> 611.623 | Q11: =+SUM(BM11:BO11) -> 686.724 | R11: =+SUM(BP11:BR11) -> 751.36 | S11: =+SUM(BS11:BU11) -> 966.358 | T11: =+SUM(BV11:BX11) -> 792.559 | V11: =+SUM(BZ11:CB11) -> 557565 | W11: =SUM(CC11:CE11) -> 694085.04 | X11: =SUM(CF11:CH11) -> 899731 | Y11: =SUM(CI11:CK11) -> 689892.5 | AA11: =SUM(CM11:CO11) -> 1002461 | AB11: =SUM(CP11:CR11) -> 970260 | AC11: =SUM(CS11:CU11) -> 989011 | AD11: =SUM(CV11:CX11) -> 788224 | AF11: =SUM(CZ11:DB11) -> 649016 | AG11: =SUM(DC11:DE11) -> 517439 | AH11: =SUM(DF11:DH11) -> 595308 | AI11: =SUM(DI11:DK11) -> 434653 | AK11: =SUM(DM11:DO11) -> 439009 | AL11: =SUM(DP11:DR11) -> 461141 | AM11: =SUM(DS11:DU11) -> 609363.82 | AN11: =SUM(DV11:DX11) -> 626742.27 | AP11: =SUM(ED11:EF11) -> 376625.04 | AQ11: =SUM(EG11:EI11) -> 401740.59 | AR11: =SUM(EJ11:EL11) -> 479616 | AS11: =SUM(EM11:EO11) -> 554832.62 | AU11: =SUM(ER11:ET11) -> 476614 | AV11: =SUM(EU11:EW11) -> 436097 | AZ11: =134460/1000 -> 134.46 | BA11: =152399/1000 -> 152.399 | BB11: =228435/1000 -> 228.435 | BC11: =229032/1000 -> 229.032 | BD11: =200886/1000 -> 200.886 | BE11: =211281/1000 -> 211.281 | BF11: =210656/1000 -> 210.656 | BG11: =200174/1000 -> 200.174 | BH11: =216484/1000 -> 216.484 | BI11: =226882/1000 -> 226.882 | BJ11: =253025/1000 -> 253.025 | BK11: =131716/1000 -> 131.716 | BM11: =162790/1000 -> 162.79 | BN11: =252893/1000 -> 252.893 | BO11: =271041/1000 -> 271.041 | BP11: =260123/1000 -> 260.123 | BQ11: =228342/1000 -> 228.342 | BR11: =262895/1000 -> 262.895 | BS11: =276889/1000 -> 276.889 | BT11: =365251/1000 -> 365.251 | BU11: =324218/1000 -> 324.218 | BV11: =335571/1000 -> 335.571 | BW11: =261348/1000 -> 261.348 | BX11: =195640/1000 -> 195.64 | BZ11: 141030 | CA11: 182177 | CB11: 234358 | CC11: 203863.7 | CD11: 281613 | CE11: 208608.34 | CF11: 276459 | CG11: 309091 | CH11: 314181 | CI11: 307722.25 | CJ11: 267949 | CK11: 114221.25 | CM11: 323918 | CN11: 377398 | CO11: 301145 | CP11: 312546 | CQ11: 353619 | CR11: 304095 | CS11: 338444 | CT11: 336493 | CU11: 314074 | CV11: 260756 | CW11: 294016 | CX11: 233452 | CZ11: 184833 | DA11: 241996 | DB11: 222187 | DC11: 179701 | DD11: 158326 | DE11: 179412 | DF11: 183946 | DG11: 190892 | DH11: 220470 | DI11: 150983 | DJ11: 160400 | DK11: 123270 | DM11: 123790 | DN11: 170470 | DO11: 144749 | DP11: ='[12]Activity indicators'!$H$69 -> 172045 | DQ11: ='[12]Activity indicators'!$I$69 -> 163356 | DR11: ='[13]VIF @ POS May month'!$F$49+'[13]VIF @ POS May month'!$F$50 -> 125740 | DS11: ='[14]Activity indicators'!$K$69 -> 209409.82 | DT11: 205237 | DU11: 194717 | DV11: 193636 | DW11: 224192.27 | DX11: 208914 | ED11: 103722 | EE11: 131607 | EF11: 141296.04 | EG11: 127319.98 | EH11: 137210.31 | EI11: =EH11 -> 137210.31 | EJ11: 157011 | EK11: 154238 | EL11: 168367 | EM11: 178394.5 | EN11: 198043.63 | EO11: =EM11 -> 178394.5 | ER11: 121710 | ES11: 178083 | ET11: 176821 | EU11: 132047 | EV11: 135764 | EW11: 168286
B13: DIA Inceptions (ZAR) | D13: =+SUM(AZ13:BK13) -> 481.574 | E13: =+SUM(BM13:BX13) -> 660.61 | F13: =+SUM(V13:Y13) -> 682410.5 | G13: =SUM(AA13:AD13) -> 1016375.2 | H13: =SUM(AF13:AI13) -> 927350 | I13: =SUM(AK13:AN13) -> 1241115.2 | J13: =SUM(AP13:AR13) -> 900374.76 | K13: =SUM(AU13:AX13) -> 570535 | L13: =+SUM(AZ13:BB13) -> 62.98 | M13: =+SUM(BC13:BE13) -> 107.959 | N13: =+SUM(BF13:BH13) -> 149.495 | O13: =+SUM(BI13:BK13) -> 161.14 | Q13: =+SUM(BM13:BO13) -> 171.22 | R13: =+SUM(BP13:BR13) -> 200.23 | S13: =+SUM(BS13:BU13) -> 162.395 | T13: =+SUM(BV13:BX13) -> 126.765 | V13: =+SUM(BZ13:CB13) -> 196431 | W13: =SUM(CC13:CE13) -> 132082.5 | X13: =SUM(CF13:CH13) -> 173561 | Y13: =SUM(CI13:CK13) -> 180336 | AA13: =SUM(CM13:CO13) -> 205505.18 | AB13: =SUM(CP13:CR13) -> 252510 | AC13: =SUM(CS13:CU13) -> 264931 | AD13: =SUM(CV13:CX13) -> 293429 | AF13: =SUM(CZ13:DB13) -> 179385 | AG13: =SUM(DC13:DE13) -> 215236 | AH13: =SUM(DF13:DH13) -> 296474 | AI13: =SUM(DI13:DK13) -> 236255 | AK13: =SUM(DM13:DO13) -> 195575 | AL13: =SUM(DP13:DR13) -> 320065 | AM13: =SUM(DS13:DU13) -> 360053.87 | AN13: =SUM(DV13:DX13) -> 365421.33 | AP13: =SUM(ED13:EF13) -> 302571.76 | AQ13: =SUM(EG13:EI13) -> 281060.36 | AR13: =SUM(EJ13:EL13) -> 316742.64 | AS13: =SUM(EM13:EO13) -> 331896.49 | AU13: =SUM(ER13:ET13) -> 308205 | AV13: =SUM(EU13:EW13) -> 262330 | AZ13: 13.755 | BA13: 21.015 | BB13: 28.21 | BC13: =41885/1000 -> 41.885 | BD13: 30.615 | BE13: =35459/1000 -> 35.459 | BF13: =58215/1000 -> 58.215 | BG13: =53355/1000 -> 53.355 | BH13: =37925/1000 -> 37.925 | BI13: =54135/1000 -> 54.135 | BJ13: =59805/1000 -> 59.805 | BK13: =47200/1000 -> 47.2 | BM13: =50525/1000 -> 50.525 | BN13: =68165/1000 -> 68.165 | BO13: =52530/1000 -> 52.53 | BP13: =73765/1000 -> 73.765 | BQ13: =66495/1000 -> 66.495 | BR13: =59970/1000 -> 59.97 | BS13: =65235/1000 -> 65.235 | BT13: =42610/1000 -> 42.61 | BU13: =54550/1000 -> 54.55 | BV13: =55795/1000 -> 55.795 | BW13: =46020/1000 -> 46.02 | BX13: 24.95 | BZ13: 56710 | CA13: 60002 | CB13: 79719 | CC13: 39955 | CD13: 48100 | CE13: 44027.5 | CF13: 61686 | CG13: 60335 | CH13: 51540 | CI13: 80376 | CJ13: 68136 | CK13: 31824 | CM13: 52195.175 | CN13: 91660 | CO13: 61650 | CP13: 84895 | CQ13: 90655 | CR13: 76960 | CS13: 100565 | CT13: 72030 | CU13: 92336 | CV13: 99654 | CW13: 107745 | CX13: 86030 | CZ13: 56335 | DA13: 64720 | DB13: 58330 | DC13: 58240 | DD13: 71975 | DE13: 85021 | DF13: 100799 | DG13: 119645 | DH13: 76030 | DI13: 84870 | DJ13: 73560 | DK13: 77825 | DM13: 66550 | DN13: 64690 | DO13: 64335 | DP13: ='[12]Activity indicators'!$H$74 -> 99970 | DQ13: ='[12]Activity indicators'!$I$74 -> 114550 | DR13: ='[13]VIF @ POS May month'!$F$51 -> 105545 | DS13: ='[14]Activity indicators'!$K$74 -> 120489.57 | DT13: 120933.43 | DU13: 118630.87 | DV13: 109505 | DW13: 134109.33 | DX13: 121807 | ED13: 70070 | EE13: 120730.48 | EF13: 111771.29 | EG13: 94453.031 | EH13: 90084.326 | EI13: 96523 | EJ13: 104438.73 | EK13: 109184.35 | EL13: 103119.56 | EM13: 107593.81 | EN13: 116708.87 | EO13: =EM13 -> 107593.81 | ER13: 77695 | ES13: 103815 | ET13: 126695 | EU13: 80325 | EV13: 80290 | EW13: 101715
B15: HIV New policies (#) | D15: 5344 | E15: =+SUM(BM15:BX15) -> 7977 | F15: =+SUM(V15:Y15) -> 6955.7 | G15: =SUM(AA15:AD15) -> 7376 | H15: =SUM(AF15:AI15) -> 4085 | I15: =SUM(AK15:AN15) -> 3504 | J15: =SUM(AP15:AR15) -> 2665 | K15: =SUM(AU15:AX15) -> 1619 | L15: =+SUM(AZ15:BB15) -> 1195 | M15: =+SUM(BC15:BE15) -> 1450 | N15: =+SUM(BF15:BH15) -> 1382 | O15: =+SUM(BI15:BK15) -> 1317 | Q15: =+SUM(BM15:BO15) -> 1509 | R15: =+SUM(BP15:BR15) -> 1902 | S15: =+SUM(BS15:BU15) -> 2479 | T15: =+SUM(BV15:BX15) -> 2087 | V15: =+SUM(BZ15:CB15) -> 1387 | W15: =SUM(CC15:CE15) -> 1850.6 | X15: =SUM(CF15:CH15) -> 2078 | Y15: =SUM(CI15:CK15) -> 1640.1 | AA15: =SUM(CM15:CO15) -> 2039 | AB15: =SUM(CP15:CR15) -> 1840 | AC15: =SUM(CS15:CU15) -> 1979 | AD15: =SUM(CV15:CX15) -> 1518 | AF15: =SUM(CZ15:DB15) -> 1259 | AG15: =SUM(DC15:DE15) -> 967 | AH15: =SUM(DF15:DH15) -> 1028 | AI15: =SUM(DI15:DK15) -> 831 | AK15: =SUM(DM15:DO15) -> 647 | AL15: =SUM(DP15:DR15) -> 772 | AM15: =SUM(DS15:DU15) -> 1116 | AN15: =SUM(DV15:DX15) -> 969 | AP15: =SUM(ED15:EF15) -> 803 | AQ15: =SUM(EG15:EI15) -> 859 | AR15: =SUM(EJ15:EL15) -> 1003 | AS15: =SUM(EM15:EO15) -> 1080 | AU15: =SUM(ER15:ET15) -> 761 | AV15: =SUM(EU15:EW15) -> 858 | AZ15: 320 | BA15: 377 | BB15: 498 | BC15: 524 | BD15: 482 | BE15: 444 | BF15: 403 | BG15: 478 | BH15: 501 | BI15: 513 | BJ15: 519 | BK15: 285 | BM15: 385 | BN15: 537 | BO15: 587 | BP15: 608 | BQ15: 607 | BR15: 687 | BS15: 726 | BT15: 909 | BU15: 844 | BV15: 888 | BW15: 755 | BX15: 444 | BZ15: 377 | CA15: 446 | CB15: 564 | CC15: 591 | CD15: 720 | CE15: 539.6 | CF15: 657 | CG15: 674 | CH15: 747 | CI15: 730.95 | CJ15: 637.45 | CK15: 271.7 | CM15: 655 | CN15: 741 | CO15: 643 | CP15: 651 | CQ15: 670 | CR15: 519 | CS15: 671 | CT15: 671 | CU15: 637 | CV15: 506 | CW15: 531 | CX15: 481 | CZ15: 371 | DA15: 431 | DB15: 457 | DC15: 351 | DD15: 293 | DE15: 323 | DF15: 346 | DG15: 339 | DH15: 343 | DI15: 268 | DJ15: 308 | DK15: 255 | DM15: 175 | DN15: 224 | DO15: 248 | DP15: ='[12]Activity indicators'!$H$68 -> 315 | DQ15: ='[12]Activity indicators'!$I$68 -> 232 | DR15: ='[13]VIF @ POS May month'!$U$19+'[13]VIF @ POS May month'!$U$20 -> 225 | DS15: ='[14]Activity indicators'!$K$68 -> 351 | DT15: 395 | DU15: 370 | DV15: 293 | DW15: 353 | DX15: 323 | ED15: 225 | EE15: 246 | EF15: 332 | EG15: 208 | EH15: 308 | EI15: 343 | EJ15: 344 | EK15: 323 | EL15: 336 | EM15: 336 | EN15: 372 | EO15: =EN15 -> 372 | ER15: 265 | ES15: 373 | ET15: 123 | EU15: 255 | EV15: 277 | EW15: 326
B17: DIA New policies (#) | D17: 889 | E17: =+SUM(BM17:BX17) -> 1320 | F17: =+SUM(V17:Y17) -> 1388.56 | G17: =SUM(AA17:AD17) -> 1509 | H17: =SUM(AF17:AI17) -> 1423 | I17: =SUM(AK17:AN17) -> 1502 | J17: =SUM(AP17:AR17) -> 1108 | K17: =SUM(AU17:AX17) -> 738 | L17: =+SUM(AZ17:BB17) -> 117 | M17: =+SUM(BC17:BE17) -> 202 | N17: =+SUM(BF17:BH17) -> 276 | O17: =+SUM(BI17:BK17) -> 294 | Q17: =+SUM(BM17:BO17) -> 353 | R17: =+SUM(BP17:BR17) -> 373 | S17: =+SUM(BS17:BU17) -> 319 | T17: =+SUM(BV17:BX17) -> 275 | V17: =+SUM(BZ17:CB17) -> 501 | W17: =SUM(CC17:CE17) -> 240 | X17: =SUM(CF17:CH17) -> 347 | Y17: =SUM(CI17:CK17) -> 300.56 | AA17: =SUM(CM17:CO17) -> 300 | AB17: =SUM(CP17:CR17) -> 349 | AC17: =SUM(CS17:CU17) -> 417 | AD17: =SUM(CV17:CX17) -> 443 | AF17: =SUM(CZ17:DB17) -> 309 | AG17: =SUM(DC17:DE17) -> 331 | AH17: =SUM(DF17:DH17) -> 443 | AI17: =SUM(DI17:DK17) -> 340 | AK17: =SUM(DM17:DO17) -> 311 | AL17: =SUM(DP17:DR17) -> 397 | AM17: =SUM(DS17:DU17) -> 415 | AN17: =SUM(DV17:DX17) -> 379 | AP17: =SUM(ED17:EF17) -> 378 | AQ17: =SUM(EG17:EI17) -> 346 | AR17: =SUM(EJ17:EL17) -> 384 | AS17: =SUM(EM17:EO17) -> 372 | AU17: =SUM(ER17:ET17) -> 373 | AV17: =SUM(EU17:EW17) -> 365 | AZ17: 34 | BA17: 26 | BB17: 57 | BC17: 79 | BD17: 59 | BE17: 64 | BF17: 95 | BG17: 90 | BH17: 91 | BI17: 83 | BJ17: 108 | BK17: 103 | BM17: 106 | BN17: 130 | BO17: 117 | BP17: 124 | BQ17: 121 | BR17: 128 | BS17: 115 | BT17: 89 | BU17: 115 | BV17: 112 | BW17: 99 | BX17: 64 | BZ17: 163 | CA17: 156 | CB17: 182 | CC17: 73 | CD17: 87 | CE17: 80 | CF17: 100 | CG17: 138 | CH17: 109 | CI17: 133.96 | CJ17: 113.56 | CK17: 53.04 | CM17: 86 | CN17: 108 | CO17: 106 | CP17: 120 | CQ17: 115 | CR17: 114 | CS17: 140 | CT17: 125 | CU17: 152 | CV17: 144 | CW17: 170 | CX17: 129 | CZ17: 100 | DA17: 102 | DB17: 107 | DC17: 92 | DD17: 118 | DE17: 121 | DF17: 170 | DG17: 173 | DH17: 100 | DI17: 125 | DJ17: 103 | DK17: 112 | DM17: 111 | DN17: 92 | DO17: 108 | DP17: ='[12]Activity indicators'!$H$73 -> 150 | DQ17: ='[12]Activity indicators'!$I$73 -> 136 | DR17: ='[13]VIF @ POS May month'!$U$21 -> 111 | DS17: ='[14]Activity indicators'!$K$73 -> 151 | DT17: 130 | DU17: 134 | DV17: 108 | DW17: 145 | DX17: 126 | ED17: 88 | EE17: 151 | EF17: 139 | EG17: 110 | EH17: 113 | EI17: 123 | EJ17: 130 | EK17: 139 | EL17: 115 | EM17: 128 | EN17: 122 | EO17: =EN17 -> 122 | ER17: 92 | ES17: 119 | ET17: 162 | EU17: 125 | EV17: 107 | EW17: 133
B19: Average total charge to client (ZAR) | D19: =+AVERAGE(AZ19:BK19) -> 399 | E19: =+AVERAGE(BM19:BX19) -> 367.96693 | F19: =F23/F26*1000 -> 4112.3653 | G19: =G23/G26*1000 -> 4290.4568 | H19: =H23*4/H26*1000 -> 17780.386 | I19: =I23*4/I26*1000 -> 18244.682 | J19: =J23*4/J26*1000 -> 10607.898 | K19: =+AVERAGE(ER19:EW19) -> 304.11644 | L19: =+AVERAGE(AZ19:BB19) -> 399 | M19: =+AVERAGE(BC19:BE19) -> 399 | N19: =+AVERAGE(BF19:BH19) -> 399 | O19: =+AVERAGE(BI19:BK19) -> 399 | Q19: =+AVERAGE(BM19:BO19) -> 402.7963 | R19: =+AVERAGE(BP19:BR19) -> 351.84685 | S19: =+AVERAGE(BS19:BU19) -> 345.78221 | T19: =+AVERAGE(BV19:BX19) -> 371.44234 | V19: =AVERAGE(BZ19:CB19) -> 384.06149 | W19: =AVERAGE(CC19:CE19) -> 368.08252 | X19: =AVERAGE(CF19:CH19) -> 371.34744 | Y19: =AVERAGE(CI19:CK19) -> 358.27332 | AA19: =AA23/AA26*1000 -> 1100.0608 | AB19: =AB23/AB26*1000 -> 1100.4801 | AC19: =AC23/AC26*1000 -> 1145.7567 | AD19: =AD23/AD26*1000 -> 1093.9589 | AF19: =SUM(CZ19:DB19) -> 1044.1825 | AG19: =SUM(DC19:DE19) -> 1116.7748 | AH19: =SUM(DF19:DH19) -> 1163.012 | AI19: =SUM(DI19:DK19) -> 1158.9489 | AK19: =SUM(DM19:DO19)/3 -> 395.5284 | AL19: =SUM(DP19:DR19)/3 -> 405.58098 | AM19: =SUM(DS19:DU19)/3 -> 382.28978 | AN19: =SUM(DV19:DX19) -> 1203.5388 | AP19: =SUM(ED19:EF19) -> 851.14339 | AQ19: =SUM(EG19:EI19) -> 982.92776 | AR19: =SUM(EJ19:EL19) -> 944.68304 | AS19: =SUM(EM19:EO19) -> 932.6107 | AU19: =SUM(ER19:ET19) -> 922.94531 | AV19: =SUM(EU19:EW19) -> 901.75333 | AZ19: 399 | BA19: 399 | BB19: 399 | BC19: 399 | BD19: 399 | BE19: 399 | BF19: 399 | BG19: 399 | BH19: 399 | BI19: 399 | BJ19: 399 | BK19: 399 | BM19: 384.83996 | BN19: 423.96866 | BO19: 399.58027 | BP19: 370.93943 | BQ19: 343.78928 | BR19: 340.81186 | BS19: 340.50781 | BT19: 355.73882 | BU19: 341.1 | BV19: 359.7223 | BW19: 340.82596 | BX19: 413.77876 | BZ19: =BZ23/BZ26*1000 -> 385.86857 | CA19: =CA23/CA26*1000 -> 386.52856 | CB19: =CB23/CB26*1000 -> 379.78734 | CC19: =CC23/CC26*1000 -> 390.58352 | CD19: =CD23/CD26*1000 -> 382.3282 | CE19: =CE23/CE26*1000 -> 331.33583 | CF19: =CF23/CF26*1000 -> 380.12698 | CG19: =CG23/CG26*1000 -> 364.42153 | ... CK19: =CK23/CK26*1000 -> 353.64036 | CM19: =CM23/CM26*1000 -> 371.60813 | CN19: =CN23/CN26*1000 -> 387.12797 | CO19: =CO23/CO26*1000 -> 361.96136 | CP19: =CP23/CP26*1000 -> 372.64312 | CQ19: =CQ23/CQ26*1000 -> 367.47158 | CR19: =CR23/CR26*1000 -> 375.95164 | CS19: =CS23/CS26*1000 -> 384.2045 | CT19: =CT23/CT26*1000 -> 393.47141 | ... CX19: =CX23/CX26*1000 -> 356.11454 | CZ19: =CZ23/CZ26*1000 -> 339.17148 | DA19: =DA23/DA26*1000 -> 355.39075 | DB19: =DB23/DB26*1000 -> 349.62031 | DC19: =DC23/DC26*1000 -> 379.28363 | DD19: =DD23/DD26*1000 -> 358.76262 | DE19: =DE23/DE26*1000 -> 378.72852 | DF19: =DF23/DF26*1000 -> 385.40167 | DG19: =DG23/DG26*1000 -> 388.93379 | ... DK19: =DK23/DK26*1000 -> 380.44512 | DM19: =DM23/DM26*1000 -> 401.66178 | DN19: =DN23/DN26*1000 -> 394.49895 | DO19: =DO23/DO26*1000 -> 390.42446 | DP19: =DP23/DP26*1000 -> 401.53068 | DQ19: =DQ23/DQ26*1000 -> 398.48772 | DR19: =DR23/DR26*1000 -> 416.72455 | DS19: =DS23/DS26*1000 -> 385.33232 | DT19: =DT23/DT26*1000 -> 375.68152 | ... DX19: =DX23/DX26*1000 -> 414.01985 | ED19: =ED23/ED26*1000 -> 285.49036 | EE19: =EE23/EE26*1000 -> 281.24052 | EF19: =EF23/EF26*1000 -> 284.41251 | EG19: =EG23/EG26*1000 -> 326.76644 | EH19: =EH23/EH26*1000 -> 327.91856 | EI19: =EI23/EI26*1000 -> 328.24275 | EJ19: =EJ23/EJ26*1000 -> 319.64349 | EK19: =EK23/EK26*1000 -> 313.12511 | ... EO19: =EO23/EO26*1000 -> 311.02684 | ER19: =ER23/ER26*1000 -> 298.10291 | ES19: =ES23/ES26*1000 -> 312.95844 | ET19: =ET23/ET26*1000 -> 311.88396 | EU19: =EU23/EU26*1000 -> 304.80967 | EV19: =EV23/EV26*1000 -> 300.56481 | EW19: =EW23/EW26*1000 -> 296.37885
B21: Total acquisition costs (ZAR 000s) | D21: =+SUM(AZ21:BK21) -> -42499.175 | E21: =+SUM(BM21:BX21) -> -46676.361 | F21: =+SUM(V21:Y21) -> -47090.229 | G21: =SUM(AA21:AD21) -> -52779.98 | H21: =SUM(AF21:AI21) -> -48496.489 | I21: =SUM(AK21:AN21) -> -49332.693 | J21: =SUM(AP21:AR21) -> -46835.942 | K21: =SUM(AU21:AX21) -> -33338.441 | L21: =+SUM(AZ21:BB21) -> -11479.495 | M21: =+SUM(BC21:BE21) -> -12240.989 | N21: =+SUM(BF21:BH21) -> -9586.5556 | O21: =+SUM(BI21:BK21) -> -9192.1351 | Q21: =+SUM(BM21:BO21) -> -10830.349 | R21: =+SUM(BP21:BR21) -> -12013.834 | S21: =+SUM(BS21:BU21) -> -12804.914 | T21: =+SUM(BV21:BX21) -> -11027.264 | V21: =+SUM(BZ21:CB21) -> -11766.91 | W21: =SUM(CC21:CE21) -> -10772.689 | X21: =SUM(CF21:CH21) -> -12013.402 | Y21: =SUM(CI21:CK21) -> -12537.228 | AA21: =SUM(CM21:CO21) -> -13690.355 | AB21: =SUM(CP21:CR21) -> -13369.999 | AC21: =SUM(CS21:CU21) -> -13359.464 | AD21: =SUM(CV21:CX21) -> -12360.163 | AF21: =SUM(CZ21:DB21) -> -12357.843 | AG21: =SUM(DC21:DE21) -> -13010 | AH21: =SUM(DF21:DH21) -> -12077 | AI21: =SUM(DI21:DK21) -> -11051.646 | AK21: =SUM(DM21:DO21) -> -12018.626 | AL21: =SUM(DP21:DR21) -> -14101.137 | AM21: =SUM(DS21:DU21) -> -10270.93 | AN21: =SUM(DV21:DX21) -> -12942 | AP21: =SUM(ED21:EF21) -> -12333 | AQ21: =SUM(EG21:EI21) -> -17155 | AR21: =SUM(EJ21:EL21) -> -17347.942 | AS21: =SUM(EM21:EO21) -> -15794 | AU21: =SUM(ER21:ET21) -> -16394.441 | AV21: =SUM(EU21:EW21) -> -16944 | AZ21: -2967.1762 | BA21: -4357.1999 | BB21: -4155.1191 | BC21: -3813.7756 | BD21: -4367.771 | BE21: -4059.4421 | BF21: -2879.3968 | BG21: -3449.3055 | BH21: -3257.8533 | BI21: -3103.1857 | BJ21: -3429.5787 | BK21: -2659.3707 | BM21: -3344.5178 | BN21: -3489.0443 | BO21: -3996.7869 | BP21: -4193.0734 | BQ21: -4006.5454 | BR21: -3814.2148 | BS21: -4227.828 | BT21: -4181.0298 | BU21: -4396.0559 | BV21: -4229.8588 | BW21: -3927.3816 | BX21: -2870.0241 | BZ21: -3724.9206 | CA21: -4077.0996 | CB21: -3964.8903 | CC21: -3631.2696 | CD21: -3359.1488 | CE21: -3782.2705 | CF21: -4031.3257 | CG21: -3927.3256 | CH21: -4054.7504 | CI21: -4558.467 | CJ21: -4599.7951 | CK21: -3378.9654 | CM21: -4011.2174 | CN21: -4644.0826 | CO21: -5035.0545 | CP21: -4723.1568 | CQ21: -4482.0941 | CR21: -4164.748 | CS21: -4180.1363 | CT21: -4808.9423 | CU21: -4370.3851 | CV21: -4452.5731 | CW21: -4496.5891 | CX21: -3411.0007 | CZ21: -3900.2535 | DA21: -4089.3272 | DB21: -4368.262 | DC21: -4117 | DD21: -4303 | DE21: -4590 | DF21: -4177 | DG21: -4106 | DH21: -3794 | DI21: -3885.7787 | DJ21: -4162.6364 | DK21: -3003.2308 | DM21: -3590 | DN21: -3944 | DO21: -4484.6259 | DP21: ='[15]Income statement'!$H$25 -> -4291.569 | DQ21: ='[15]Income statement'!$I$25 -> -4633.5678 | DR21: -5176 | DS21: -3103 | DT21: -3413.3 | DU21: -3754.63 | DV21: -4720 | DW21: -4111 | DX21: -4111 | ED21: -4111 | EE21: -4111 | EF21: -4111 | EG21: -5686 | EH21: -5699 | EI21: -5770 | EJ21: -5770.2286 | EK21: -5770.4311 | EL21: -5807.2826 | EM21: -5954 | EN21: -5602 | EO21: -4238 | ER21: ='[11]Income Statement'!$H$48 -> -5159.4265 | ES21: ='[11]Income Statement'!$J$48 -> -6235.8957 | ET21: ='[11]Income Statement'!$L$48 -> -4999.119 | EU21: -5469 | EV21: -5827 | EW21: -5648
B23: Total charge to client (ZAR 000s) | D23: =+SUM(AZ23:BK23) -> 134869.4 | E23: =+SUM(BM23:BX23) -> 146663.24 | F23: =+SUM(V23:Y23) -> 164260.21 | G23: =SUM(AA23:AD23) -> 185124.63 | H23: =SUM(AF23:AI23) -> 186565.14 | I23: =SUM(AK23:AN23) -> 207679.22 | J23: =SUM(AP23:AR23) -> 136383.1 | K23: =SUM(AU23:AX23) -> 99566.261 | L23: =+SUM(AZ23:BB23) -> 33509.468 | M23: =+SUM(BC23:BE23) -> 33425.235 | N23: =+SUM(BF23:BH23) -> 34066.433 | O23: =+SUM(BI23:BK23) -> 33868.264 | Q23: =+SUM(BM23:BO23) -> 33357.508 | R23: =+SUM(BP23:BR23) -> 37922.455 | S23: =+SUM(BS23:BU23) -> 39427.697 | T23: =+SUM(BV23:BX23) -> 35955.581 | V23: =+SUM(BZ23:CB23) -> 40558.574 | W23: =SUM(CC23:CE23) -> 39979.771 | X23: =SUM(CF23:CH23) -> 41427.316 | Y23: =SUM(CI23:CK23) -> 42294.546 | AA23: =SUM(CM23:CO23) -> 44413.854 | AB23: =SUM(CP23:CR23) -> 45894.424 | AC23: =SUM(CS23:CU23) -> 47614.213 | AD23: =SUM(CV23:CX23) -> 47202.14 | AF23: =SUM(CZ23:DB23) -> 44137.427 | AG23: =SUM(DC23:DE23) -> 46840.714 | AH23: =SUM(DF23:DH23) -> 47806 | AI23: =SUM(DI23:DK23) -> 47781 | AK23: =SUM(DM23:DO23) -> 49335 | AL23: =SUM(DP23:DR23) -> 51066.572 | AM23: =SUM(DS23:DU23) -> 51541.196 | AN23: =SUM(DV23:DX23) -> 55736.452 | AP23: =SUM(ED23:EF23) -> 41147.953 | AQ23: =SUM(EG23:EI23) -> 47326.009 | AR23: =SUM(EJ23:EL23) -> 47909.135 | AS23: =SUM(EM23:EO23) -> 48048.681 | AU23: =SUM(ER23:ET23) -> 49322.044 | AV23: =SUM(EU23:EW23) -> 50244.217 | AZ23: =+AZ4 -> 10410.986 | BA23: =+BA4 -> 11854.897 | BB23: =+BB4 -> 11243.584 | BC23: =+BC4 -> 11497.606 | BD23: =+BD4 -> 10633.45 | BE23: =+BE4 -> 11294.178 | BF23: =+BF4 -> 11076.425 | BG23: =+BG4 -> 11222.903 | ... BK23: =+BK4 -> 11096.264 | BM23: =+BM4 -> 10265.102 | BN23: =+BN4 -> 11590.803 | BO23: =+BO4 -> 11501.603 | BP23: =+BP4 -> 12315.045 | BQ23: =+BQ4 -> 12975.809 | BR23: =+BR4 -> 12631.601 | BS23: =+BS4 -> 12979.747 | BT23: =+BT4 -> 13118.101 | ... BX23: =+BX4 -> 11716.099 | BZ23: =+BZ4 -> 13490.737 | CA23: =+CA4 -> 13589.184 | CB23: =+CB4 -> 13478.653 | CC23: =+CC4 -> 14030.541 | CD23: =+CD4 -> 13859.78 | CE23: =+CE4 -> 12089.451 | CF23: =+CF4 -> 14008.059 | CG23: =+CG4 -> 13522.225 | CH23: =+CH4 -> 13897.032 | CI23: 13774 | CJ23: =+CJ4 -> 14395.089 | CK23: =+CK4 -> 14125.457 | CM23: =+CM4 -> 14430.659 | CN23: =+CN4 -> 15369.368 | CO23: =+CO4 -> 14613.828 | CP23: =+CP4 -> 15173.655 | CQ23: =+CQ4 -> 15042.082 | CR23: =+CR4 -> 15678.687 | CS23: =+CS4 -> 15966.386 | CT23: =+CT4 -> 16454.974 | ... CX23: =+CX4 -> 15365.63 | CZ23: =+CZ4 -> 14443.278 | DA23: =+DA4 -> 15020.234 | DB23: =+DB4 -> 14673.914 | DC23: =+DC4 -> 15861.641 | DD23: =+DD4 -> 15069.824 | DE23: =+DE4 -> 15909.249 | DF23: =+DF4 -> 16062 | DG23: =+DG4 -> 15879 | ... DK23: =+DK4 -> 15607 | DM23: =+DM4 -> 16726 | DN23: =+DN4 -> 16365 | DO23: =+DO4 -> 16244 | DP23: =+DP4 -> 16851.439 | DQ23: =+DQ4 -> 16773.544 | DR23: =+DR4 -> 17441.589 | DS23: =+DS4 -> 17010.495 | DT23: =+DT4 -> 16979.678 | ... DX23: =+DX4 -> 18851.152 | ED23: =+ED4 -> 14030.138 | EE23: =+EE4 -> 13471.702 | EF23: =+EF4 -> 13646.112 | EG23: =+EG4 -> 15653.093 | EH23: =+EH4 -> 15818.791 | EI23: =+EI4 -> 15854.125 | EJ23: =+EJ4 -> 15907.698 | EK23: =+EK4 -> 15960.613 | ... EO23: =+EO4 -> 15576.535 | ER23: =+ER4 -> 16058.208 | ES23: =+ES4 -> 16581.164 | ET23: =+ET4 -> 16682.673 | EU23: =+EU4 -> 16748.072 | EV23: =+EV4 -> 16748.072 | EW23: =+EW4 -> 16748.072
B25: Impact Metrics | D25: 2018 | E25: 2019 | F25: 2020 | G25: 2021 | H25: 2022 | I25: 2023 | J25: =J10 -> 2024 | K25: =K10 -> 2025 | L25: Q1 2018 | M25: Q2 2018 | N25: Q3 2018 | O25: Q4 2018 | Q25: Q1 2019 | R25: Q2 2019 | S25: Q3 2019 | T25: Q4 2019 | V25: Q1 2020 | W25: Q2 2020 | X25: Q3 2020 | Y25: Q4 2020 | AP25: =AP3 -> Q1 2024 | AQ25: =AQ3 -> Q2 2024 | AR25: =AR3 -> Q3 2024 | AS25: =AS3 -> Q4 2024 | AZ25: 43101 | BA25: 43132 | BB25: 43160 | BC25: 43191 | BD25: 43221 | BE25: 43252 | BF25: 43282 | BG25: 43313 | BH25: 43344 | BI25: 43374 | BJ25: 43405 | BK25: 43435 | BM25: 43466 | BN25: 43497 | BO25: 43525 | BP25: 43556 | BQ25: 43586 | BR25: 43617 | BS25: 43647 | BT25: 43678 | BU25: 43709 | BV25: 43739 | BW25: 43770 | BX25: 43800 | BZ25: 43831 | CA25: 43863 | CB25: 43895 | CC25: 43927 | CD25: 43959 | CE25: 43991 | CF25: 44023 | CG25: 44055 | CH25: 44087 | CI25: 44119 | CJ25: 44151 | CK25: 44183 | CM25: 44197 | CN25: 44228 | CO25: 44256 | CP25: 44287 | CQ25: 44317 | CR25: 44348 | CS25: 44378 | CT25: 44409 | CU25: 44440 | CV25: 44470 | CW25: 44501 | CX25: 44531 | CZ25: 44562 | DA25: 44593 | DB25: 44621 | DC25: 44652 | DD25: 44682 | DE25: 44713 | DF25: 44743 | DG25: 44774 | DH25: 44805 | DI25: 44835 | DJ25: 44866 | DK25: 44896 | DM25: 44927 | DN25: 44958 | DO25: 44986 | DP25: 45017 | DQ25: 45047 | DR25: 45078 | DS25: 45108 | DT25: 45139 | DU25: 45170 | DV25: 45200 | DW25: 45231 | DX25: 45261 | ED25: =ED10 -> 45292 | EE25: =EE10 -> 45323 | EF25: =EF10 -> 45352 | EG25: =EG10 -> 45383 | EH25: =EH10 -> 45413 | EI25: =EI10 -> 45444 | EJ25: =EJ10 -> 45474 | EK25: =EK10 -> 45505 | ... EO25: =EO10 -> 45627 | ER25: =ER10 -> 45658 | ES25: =ES10 -> 45689 | ET25: =ET10 -> 45717 | EU25: =EU10 -> 45748 | EV25: =EV10 -> 45778 | EW25: =EW10 -> 45809
B26: Active Customers with policies outstanding | D26: 30916 | E26: =+T26 -> 34845 | F26: =+Y26 -> 39943 | G26: =AD26 -> 43148 | H26: =AF26 -> 41971 | I26: =AN26 -> 45532 | J26: =AR26 -> 51427 | K26: =AV26 -> 56509 | L26: =+BB26 -> 32255 | M26: =+BE26 -> 30850 | N26: =+BH26 -> 31309 | O26: =+BK26 -> 30916 | Q26: =+BO26 -> 31537 | R26: =+BR26 -> 32006 | S26: =+BU26 -> 33538 | T26: =+BX26 -> 34845 | V26: =+CB26 -> 35490 | W26: =CE26 -> 36487 | X26: =CH26 -> 37611 | Y26: =CK26 -> 39943 | AA26: =CO26 -> 40374 | AB26: =CR26 -> 41704 | AC26: =CS26 -> 41557 | AD26: =CX26 -> 43148 | AF26: =DB26 -> 41971 | AG26: =DE26 -> 42007 | AH26: =DH26 -> 40818 | AI26: =DK26 -> 41023 | AK26: =DO26 -> 41606 | AL26: =DR26 -> 41854 | AM26: =DU26 -> 45486 | AN26: =DX26 -> 45532 | AP26: =EF26 -> 47980 | AQ26: =EI26 -> 48300 | AR26: =EL26 -> 51427 | AS26: =EO26 -> 50081 | AU26: =ET26 -> 53490 | AV26: =EW26 -> 56509 | BB26: 32255 | BE26: 30850 | BH26: 31309 | BI26: 31111 | BJ26: 31069 | BK26: 30916 | BM26: 30817 | BN26: 31153 | BO26: 31537 | BP26: 31807 | BQ26: 31796 | BR26: 32006 | BS26: 32485 | BT26: 32783 | BU26: 33538 | BV26: 34162 | BW26: 34816 | BX26: 34845 | BZ26: 34962 | CA26: 35157 | CB26: 35490 | CC26: 35922 | CD26: 36251 | CE26: 36487 | CF26: 36851 | CG26: 37106 | CH26: 37611 | CI26: 38610 | CJ26: 39500 | CK26: 39943 | CM26: 38833 | CN26: 39701 | CO26: 40374 | CP26: 40719 | CQ26: 40934 | CR26: 41704 | CS26: 41557 | CT26: 41820 | CU26: 42652 | CV26: 42380 | CW26: 42517 | CX26: 43148 | CZ26: 42584 | DA26: 42264 | DB26: 41971 | DC26: 41820 | DD26: 42005 | DE26: 42007 | DF26: 41676 | DG26: 40827 | DH26: 40818 | DI26: 41554 | DJ26: 41106 | DK26: 41023 | DM26: 41642 | DN26: 41483 | DO26: 41606 | DP26: ='[12]Activity indicators'!$H$39 -> 41968 | DQ26: ='[12]Activity indicators'!$I$39 -> 42093 | DR26: 41854 | DS26: ='[14]Activity indicators'!$K$39 -> 44145 | DT26: 45197 | DU26: 45486 | DV26: 46547 | DW26: 46881 | DX26: 45532 | ED26: 49144 | EE26: 47901 | EF26: 47980 | EG26: 47903 | EH26: 48240 | EI26: 48300 | EJ26: 49767 | EK26: 50972 | EL26: 51427 | EM26: 51906 | EN26: 52578 | EO26: 50081 | ER26: 53868 | ES26: 52982 | ET26: 53490 | EU26: 54946 | EV26: 55722 | EW26: 56509
B28: Full time employees | D28: =+BK28 -> 112 | E28: =+T28 -> 142 | F28: =+Y28 -> 161 | G28: =AD28 -> 157 | H28: =AF28 -> 161 | I28: =AN28 -> 170 | J28: =AR28 -> 205 | K28: =AV28 -> 210 | L28: =+BB28 -> 116 | M28: =+BE28 -> 115 | N28: =+BH28 -> 116 | O28: =+BK28 -> 112 | Q28: =+BO28 -> 136 | R28: =+BR28 -> 137 | S28: =+BU28 -> 135 | T28: =+BX28 -> 142 | V28: =+CB28 -> 148 | W28: =CE28 -> 139 | X28: =CH28 -> 146 | Y28: =CK28 -> 161 | AA28: =CO28 -> 156 | AB28: =CR28 -> 160 | AC28: =CU28 -> 172 | AD28: =CX28 -> 157 | AF28: =DB28 -> 161 | AG28: =DE28 -> 145 | AH28: =DH28 -> 146 | AI28: =DK28 -> 154 | AK28: =DO28 -> 172 | AL28: =DR28 -> 176 | AM28: =DU28 -> 171 | AN28: =DX28 -> 170 | AP28: =EF28 -> 174 | AQ28: =EI28 -> 217 | AR28: =EL28 -> 205 | AS28: =EO28 -> 215 | AU28: =ET28 -> 246 | AV28: =EW28 -> 210 | AZ28: 120 | BA28: 118 | BB28: 116 | BC28: 114 | BD28: 110 | BE28: 115 | BF28: 120 | BG28: 115 | BH28: 116 | BI28: 115 | BJ28: 114 | BK28: 112 | BM28: 107 | BN28: 131 | BO28: 136 | BP28: 143 | BQ28: 136 | BR28: 137 | BS28: 138 | BT28: 141 | BU28: 135 | BV28: 132 | BW28: 132 | BX28: 142 | BZ28: 149 | CA28: 143 | CB28: 148 | CC28: 147 | CD28: 136 | CE28: 139 | CF28: 142 | CG28: 145 | CH28: 146 | CI28: 155 | CJ28: 152 | CK28: 161 | CM28: 162 | CN28: 152 | CO28: 156 | CP28: 153 | CQ28: 152 | CR28: 160 | CS28: 172 | CT28: 172 | CU28: 172 | CV28: 157 | CW28: 157 | CX28: 157 | CZ28: 161 | DA28: 161 | DB28: 161 | DC28: 145 | DD28: 145 | DE28: 145 | DF28: 146 | DG28: 146 | DH28: 146 | DI28: 154 | DJ28: 154 | DK28: 154 | DM28: 151 | DN28: 184 | DO28: 172 | DP28: 177 | DQ28: 167 | DR28: 176 | DS28: 193 | DT28: 184 | DU28: 171 | DV28: 174 | DW28: 178 | DX28: 170 | ED28: 173 | EE28: 176 | EF28: 174 | EG28: 183 | EH28: 186 | EI28: 217 | EJ28: 210 | EK28: 202 | EL28: 205 | EM28: 214 | EN28: 225 | EO28: 215 | ER28: 222 | ES28: 238 | ET28: 246 | EU28: 228 | EV28: 221 | EW28: 210
B30: Female Employees | D30: =+O30 -> 83 | E30: =+T30 -> 104 | F30: =+Y30 -> 119 | G30: =AD30 -> 104 | H30: =AF30 -> 114 | I30: =AN30 -> 130 | J30: =AR30 -> 154 | K30: =AV30 -> 162 | L30: =+BB30 -> 72 | M30: =+BE30 -> 71 | N30: =+BH30 -> 76 | O30: =+BK30 -> 83 | Q30: =+BO30 -> 104 | R30: =+BR30 -> 105 | S30: =+BU30 -> 102 | T30: =+BX30 -> 104 | V30: =+CB30 -> 107 | W30: =CE30 -> 100 | X30: =CH30 -> 103 | Y30: =CK30 -> 119 | AA30: =CO30 -> 117 | AB30: =CR30 -> 119 | AC30: =CU30 -> 124 | AD30: =CX30 -> 104 | AF30: =DB30 -> 114 | AG30: =DE30 -> 107 | AH30: =DH30 -> 110 | AI30: =DK30 -> 106 | AK30: =DO30 -> 119 | AL30: =DR30 -> 136 | AM30: =DU30 -> 135 | AN30: =DX30 -> 130 | AP30: =EF30 -> 127 | AQ30: =EI30 -> 166 | AR30: =EL30 -> 154 | AS30: =EO30 -> 161 | AU30: =ET30 -> 189 | AV30: =EW30 -> 162 | BB30: 72 | BE30: 71 | BH30: 76 | BK30: 83 | BO30: 104 | BR30: 105 | BU30: 102 | BX30: 104 | BZ30: 107 | CA30: 107 | CB30: 107 | CC30: 100 | CD30: 100 | CE30: 100 | CF30: 102 | CG30: 102 | CH30: 103 | CI30: =75+44 -> 119 | CJ30: =75+44 -> 119 | CK30: =75+44 -> 119 | CM30: 121 | CN30: 114 | CO30: 117 | CP30: 117 | CQ30: 120 | CR30: 119 | CS30: 124 | CT30: 124 | CU30: 124 | CV30: 104 | CW30: 104 | CX30: 104 | CZ30: 114 | DA30: 114 | DB30: 114 | DC30: 107 | DD30: 107 | DE30: 107 | DF30: 110 | DG30: 110 | DH30: 110 | DI30: 106 | DJ30: 106 | DK30: 106 | DM30: 105 | DN30: 129 | DO30: 119 | DP30: 138 | DQ30: 136 | DR30: 136 | DS30: 153 | DT30: 147 | DU30: 135 | DV30: 134 | DW30: 135 | DX30: 130 | ED30: 132 | EE30: 129 | EF30: 127 | EG30: 137 | EH30: 144 | EI30: 166 | EJ30: 154 | EK30: 157 | EL30: 154 | EM30: 160 | EN30: 167 | EO30: 161 | ER30: 169 | ES30: 177 | ET30: 189 | EU30: 178 | EV30: 171 | EW30: 162
B32: Female Employees in Senior management | D32: =+O32 -> 10 | E32: =+T32 -> 10 | F32: =+Y32 -> 10 | G32: =AD32 -> 10 | H32: =AF32 -> 9 | I32: =AN32 -> 4 | J32: =AR32 -> 5 | K32: =AV32 -> 6 | L32: =+BB32 -> 10 | M32: =+BE32 -> 11 | N32: =+BH32 -> 9 | O32: =+BK32 -> 10 | Q32: =+BO32 -> 11 | R32: =+BR32 -> 11 | S32: =+BU32 -> 11 | T32: =+BX32 -> 10 | V32: =+CB32 -> 9 | W32: =CE32 -> 10 | X32: =CH32 -> 10 | Y32: =CK32 -> 10 | AA32: =CO32 -> 10 | AB32: =CR32 -> 11 | AC32: =CU32 -> 10 | AD32: =CX32 -> 10 | AF32: =DB32 -> 9 | AG32: =DE32 -> 9 | AH32: =DH32 -> 9 | AI32: =DK32 -> 9 | AK32: =DO32 -> 9 | AL32: =DR32 -> 5 | AM32: =DU32 -> 4 | AN32: =DX32 -> 4 | AP32: =EF32 -> 9 | AQ32: =EI32 -> 6 | AR32: =EL32 -> 5 | AS32: =EO32 -> 5 | AU32: =ET32 -> 5 | AV32: =EW32 -> 6 | AZ32: 9 | BA32: 10 | BB32: 10 | BC32: 10 | BD32: 10 | BE32: 11 | BF32: 11 | BG32: 11 | BH32: 9 | BI32: 9 | BJ32: 9 | BK32: 10 | BM32: 10 | BN32: 11 | BO32: 11 | BP32: 11 | BQ32: 11 | BR32: 11 | BS32: 11 | BT32: 11 | BU32: 11 | BV32: 11 | BW32: 11 | BX32: 10 | BZ32: 10 | CA32: 9 | CB32: 9 | CC32: 9 | CD32: 9 | CE32: 10 | CF32: 10 | CG32: 10 | CH32: 10 | CI32: 10 | CJ32: 10 | CK32: 10 | CM32: 10 | CN32: 10 | CO32: 10 | CP32: 10 | CQ32: 10 | CR32: 11 | CS32: 11 | CT32: 10 | CU32: 10 | CV32: 10 | CW32: 10 | CX32: 10 | CZ32: 10 | DA32: 10 | DB32: 9 | DC32: 9 | DD32: 9 | DE32: 9 | DF32: 9 | DG32: 9 | DH32: 9 | DI32: 9 | DJ32: 9 | DK32: 9 | DM32: 9 | DN32: 9 | DO32: 9 | DP32: 5 | DQ32: 5 | DR32: 5 | DS32: 4 | DT32: 4 | DU32: 4 | DV32: 4 | DW32: 4 | DX32: 4 | ED32: 9 | EE32: 9 | EF32: 9 | EG32: 6 | EH32: 6 | EI32: 6 | EJ32: 5 | EK32: 5 | EL32: 5 | EM32: 5 | EN32: 5 | EO32: 5 | ER32: 5 | ES32: 5 | ET32: 5 | EU32: 5 | EV32: 5 | EW32: 6
B34: Females on Board of Directors | D34: =+O34 -> 1 | E34: =+T34 -> 1 | F34: =+Y34 -> 1 | G34: =AD34 -> 1 | H34: =AF34 -> 1 | I34: =AN34 -> 2 | J34: =AR34 -> 0 | K34: =AV34 -> 0 | L34: =+BB34 -> 1 | M34: =+BE34 -> 1 | N34: =+BH34 -> 1 | O34: =+BK34 -> 1 | Q34: =+BO34 -> 1 | R34: =+BR34 -> 1 | S34: =+BU34 -> 1 | T34: =+BX34 -> 1 | V34: =+CB34 -> 1 | W34: =CE34 -> 1 | X34: =CH34 -> 1 | Y34: =CK34 -> 1 | AA34: =CO34 -> 1 | AB34: =CR34 -> 1 | AC34: =CU34 -> 1 | AD34: =CX34 -> 1 | AF34: =DB34 -> 1 | AG34: =DE34 -> 1 | AH34: =DH34 -> 1 | AI34: =DK34 -> 0 | AK34: =DO34 -> 0 | AL34: =DR34 -> 1 | AM34: =DU34 -> 2 | AN34: =DX34 -> 2 | AP34: =EF34 -> 0 | AQ34: =EI34 -> 0 | AR34: =EL34 -> 0 | AS34: =EO34 -> 0 | AU34: =ET34 -> 0 | AV34: =EW34 -> 0 | AZ34: 1 | BA34: 1 | BB34: 1 | BC34: 1 | BD34: 1 | BE34: 1 | BF34: 1 | BG34: 1 | BH34: 1 | BI34: 1 | BJ34: 1 | BK34: 1 | BM34: 1 | BN34: 1 | BO34: 1 | BP34: 1 | BQ34: 1 | BR34: 1 | BS34: 1 | BT34: 1 | BU34: 1 | BV34: 1 | BW34: 1 | BX34: 1 | BZ34: 1 | CA34: 1 | CB34: 1 | CC34: 1 | CD34: 1 | CE34: 1 | CF34: 1 | CG34: 1 | CH34: 1 | CI34: 1 | CJ34: 1 | CK34: 1 | CM34: 1 | CN34: 1 | CO34: 1 | CP34: 1 | CQ34: 1 | CR34: 1 | CS34: 1 | CT34: 1 | CU34: 1 | CV34: 1 | CW34: 1 | CX34: 1 | CZ34: 1 | DA34: 1 | DB34: 1 | DC34: 1 | DD34: 1 | DE34: 1 | DF34: 1 | DG34: 1 | DH34: 1 | DI34: 1 | DJ34: 1 | DK34: 0 | DM34: 0 | DN34: 0 | DO34: 0 | DP34: 1 | DQ34: 1 | DR34: 1 | DS34: 1 | DT34: 2 | DU34: 2 | DV34: 2 | DW34: 2 | DX34: 2 | ED34: 0 | EE34: 0 | EF34: 0 | EG34: 0 | EH34: 0 | EI34: 0 | EJ34: 0 | EK34: 0 | EL34: 0 | EM34: 0 | EN34: 0 | EO34: 0 | ER34: 0 | ES34: 0 | ET34: 0 | EU34: 0 | EV34: 0 | EW34: 0
B36: Total employees in Senior management | F36: =+Y36 -> 15 | G36: =AD36 -> 14 | H36: =AF36 -> 13 | I36: =AN36 -> 12 | J36: =AR36 -> 13 | K36: =AV36 -> 12 | V36: =+CB36 -> 14 | W36: =CE36 -> 16 | X36: =CH36 -> 15 | Y36: =CK36 -> 15 | AA36: =CO36 -> 14 | AB36: =CR36 -> 15 | AC36: =CU36 -> 14 | AD36: =CX36 -> 14 | AF36: =DB36 -> 13 | AG36: =DE36 -> 14 | AH36: =DH36 -> 14 | AI36: =DK36 -> 14 | AK36: =DO36 -> 13 | AL36: =DR36 -> 11 | AM36: =DU36 -> 12 | AN36: =DX36 -> 12 | AP36: =EF36 -> 13 | AQ36: =EI36 -> 13 | AR36: =EL36 -> 13 | AS36: =EO36 -> 13 | AU36: =ET36 -> 13 | AV36: =EW36 -> 12 | BZ36: 15 | CA36: 14 | CB36: 14 | CC36: 14 | CD36: 14 | CE36: 16 | CF36: 16 | CG36: 15 | CH36: 15 | CI36: 15 | CJ36: 15 | CK36: 15 | CM36: 15 | CN36: 15 | CO36: 14 | CP36: 14 | CQ36: 14 | CR36: 15 | CS36: 15 | CT36: 14 | CU36: 14 | CV36: 14 | CW36: 14 | CX36: 14 | CZ36: 14 | DA36: 14 | DB36: 13 | DC36: 13 | DD36: 14 | DE36: 14 | DF36: 14 | DG36: 14 | DH36: 14 | DI36: 14 | DJ36: 14 | DK36: 14 | DM36: 13 | DN36: 13 | DO36: 13 | DP36: 11 | DQ36: 11 | DR36: 11 | DS36: 10 | DT36: 12 | DU36: 12 | DV36: 12 | DW36: 12 | DX36: 12 | ED36: 13 | EE36: 13 | EF36: 13 | EG36: 13 | EH36: 13 | EI36: 13 | EJ36: 13 | EK36: 13 | EL36: 13 | EM36: 13 | EN36: 13 | EO36: 13 | ER36: 13 | ES36: 13 | ET36: 13 | EU36: 13 | EV36: 12 | EW36: 12
B38: Total Board of Directors | F38: =+Y38 -> 10 | G38: =AD38 -> 10 | H38: =AF38 -> 8 | I38: =AN38 -> 3 | J38: =AR38 -> 4 | K38: =AV38 -> 4 | V38: =+CB38 -> 10 | W38: =CE38 -> 10 | X38: =CH38 -> 10 | Y38: =CK38 -> 10 | AA38: =CO38 -> 10 | AB38: =CR38 -> 10 | AC38: =CU38 -> 10 | AD38: =CX38 -> 10 | AF38: =DB38 -> 8 | AG38: =DE38 -> 8 | AH38: =DH38 -> 8 | AI38: =DK38 -> 4 | AK38: =DO38 -> 4 | AL38: =DR38 -> 4 | AM38: =DU38 -> 4 | AN38: =DX38 -> 3 | AP38: =EF38 -> 4 | AQ38: =EI38 -> 4 | AR38: =EL38 -> 4 | AS38: =EO38 -> 4 | AU38: =ET38 -> 4 | AV38: =EW38 -> 4 | BZ38: 10 | CA38: 10 | CB38: 10 | CC38: 10 | CD38: 10 | CE38: 10 | CF38: 10 | CG38: 10 | CH38: 10 | CI38: 10 | CJ38: 10 | CK38: 10 | CM38: 10 | CN38: 10 | CO38: 10 | CP38: 10 | CQ38: 10 | CR38: 10 | CS38: 10 | CT38: 10 | CU38: 10 | CV38: 10 | CW38: 10 | CX38: 10 | CZ38: 9 | DA38: 9 | DB38: 8 | DC38: 8 | DD38: 8 | DE38: 8 | DF38: 8 | DG38: 8 | DH38: 8 | DI38: 8 | DJ38: 8 | DK38: 4 | DM38: 4 | DN38: 4 | DO38: 4 | DP38: 4 | DQ38: 4 | DR38: 4 | DS38: 4 | DT38: 4 | DU38: 4 | DV38: 3 | DW38: 3 | DX38: 3 | ED38: 4 | EE38: 4 | EF38: 4 | EG38: 4 | EH38: 4 | EI38: 4 | EJ38: 4 | EK38: 4 | EL38: 4 | EM38: 4 | EN38: 4 | EO38: 4 | ER38: 4 | ES38: 4 | ET38: 4 | EU38: 4 | EV38: 4 | EW38: 4

Sheet P&L Breakdown
A1: AllLife P&L Breakdown
A2: All figures in ZAR 000s
AN3: *Forecast | AO3: *Forecast | AP3: *Forecast | AR3: *Forecast
E4: 2018 | F4: 2019 | G4: 2020 | H4: 2021 | I4: 2022 | J4: 2023 | K4: 2024 | L4: 2025 | N4: Q1 2018 | O4: Q2 2018 | P4: Q3 2018 | Q4: Q4 2018 | S4: Q1 2019 | T4: Q2 2019 | U4: Q3 2019 | V4: Q4 2019 | X4: Q1 2020 | Y4: Q2 2020 | Z4: Q3 2020 | AA4: Q4 2020 | AC4: Q1 2021 | AD4: Q2 2021 | AE4: Q3 2021 | AF4: Q4 2021 | AH4: Q1 2022 | AI4: Q2 2022 | AJ4: Q3 2022 | AK4: Q4 2022 | AM4: Q1 2023 | AN4: Q2 2023 | AO4: Q3 2023 | AP4: Q4 2023 | AR4: Q1 2024 | AS4: Q2 2024 | AT4: Q3 2024 | AU4: Q4 2024 | AW4: Q1 2025 | AX4: Q2 2025 | AY4: Q3 2025 | AZ4: Q4 2025
B6: Revenue | E6: =+SUM('Data Template'!D4:D6) -> 192079.35 | F6: =+SUM('Data Template'!E4:E7) -> 302293.44 | G6: =SUM(X6:AA6) -> 329964.74 | H6: =SUM(AC6:AF6) -> 378418.25 | I6: =SUM(AH6:AK6) -> 282011.44 | J6: =SUM(AM6:AP6) -> 287928.97 | K6: =SUM(AR6:AU6) -> 291299.66 | L6: =SUM(AW6:AZ6) -> 164289.18 | N6: =+SUM('Data Template'!L4:L6) -> 33509.468 | O6: =+SUM('Data Template'!M4:M6) -> 33425.235 | P6: =+SUM('Data Template'!N4:N6) -> 34066.433 | Q6: =+SUM('Data Template'!O4:O6) -> 91078.211 | S6: =+SUM('Data Template'!Q4:Q7) -> 56185.532 | T6: =+SUM('Data Template'!R4:R7) -> 66280.92 | U6: =+SUM('Data Template'!S4:S7) -> 85130.524 | V6: =+SUM('Data Template'!T4:T7) -> 94696.468 | X6: =+SUM('Data Template'!V4:V7) -> 76659.649 | Y6: =SUM('Data Template'!W4:W7) -> 83689.986 | Z6: =SUM('Data Template'!X4:X7) -> 86944.74 | AA6: =SUM('Data Template'!Y4:Y7) -> 82670.367 | AC6: =SUM('Data Template'!AA4:AA7) -> 91090.094 | AD6: =SUM('Data Template'!AB4:AB7) -> 91209.741 | AE6: =SUM('Data Template'!AC4:AC7) -> 100615.57 | AF6: =SUM('Data Template'!AD4:AD7) -> 95502.849 | AH6: =SUM('Data Template'!AF4:AF7) -> 88605.533 | AI6: =SUM('Data Template'!AG4:AG7) -> 73590.911 | AJ6: =SUM('Data Template'!AH4:AH7) -> 61397 | AK6: =SUM('Data Template'!AI4:AI7) -> 58418 | AM6: =SUM('Data Template'!AK4:AK7) -> 61611.311 | AN6: =SUM('Data Template'!AL4:AL7) -> 69633.429 | AO6: =SUM('Data Template'!AM4:AM7) -> 77332.593 | AP6: =SUM('Data Template'!AN4:AN7) -> 79351.636 | AR6: =SUM('Data Template'!AP4:AP7) -> 61587.953 | AS6: =SUM('Data Template'!AQ4:AQ7) -> 73597.353 | AT6: =SUM('Data Template'!AR4:AR7) -> 74096.677 | AU6: =SUM('Data Template'!AS4:AS7) -> 82017.681 | AW6: =SUM('Data Template'!AU4:AU7) -> 74285.073 | AX6: =SUM('Data Template'!AV4:AV7) -> 90004.106
B7: Reinsurance Premium | E7: -24829.113 | F7: -29078.358 | G7: =SUM(X7:AA7) -> -36049.421 | H7: =SUM(AC7:AF7) -> -44910.216 | I7: =SUM(AH7:AK7) -> -47738.436 | J7: =SUM(AM7:AP7) -> -52960.478 | K7: =SUM(AR7:AU7) -> -23326.284 | L7: =SUM(AW7:AZ7) -> -36924.213 | N7: -6007.0249 | O7: -6168.6069 | P7: -6266.4336 | Q7: -6387.048 | S7: -7230.4433 | T7: -7369.3937 | U7: -7469.2913 | V7: -7009.2298 | X7: -8490.33 | Y7: -8722.2739 | Z7: -9166.6182 | AA7: -9670.1993 | AC7: -10431.239 | AD7: -11310.689 | AE7: -11354 | AF7: -11814.289 | AH7: -11072.436 | AI7: -11922 | AJ7: -12126 | AK7: -12618 | AM7: -12607 | AN7: =-[4]Ebitda!$AF$25/1000 -> -13041.592 | AO7: =-[4]Ebitda!$AK$25/1000 -> -13200.632 | AP7: =-[5]Ebitda!$AP$25/1000 -> -14111.254 | AR7: =-[6]Ebitda!$AX$25/1000 -> -14588.499 | AS7: =-[7]Ebitda!$BC$25/1000 -> -12023.733 | AT7: =-[8]Ebitda!$BH$25/1000 -> -14251.263 | AU7: =[9]Ebitda!$BM$25/1000 -> 17537.212 | AW7: =-[10]Ebitda!$BR$25/1000 -> -18852.059 | AX7: =-[18]Ebitda!$BW$25/1000 -> -18072.154
B8: Vat Leakage | E8: -5600.6315 | F8: -7074.358 | G8: =SUM(X8:AA8) -> -5426.562 | H8: =SUM(AC8:AF8) -> -4252.2741 | I8: =SUM(AH8:AK8) -> -3075.3975 | J8: =SUM(AM8:AP8) -> -8254.1726 | K8: =SUM(AR8:AU8) -> -6889.3873 | L8: =SUM(AW8:AZ8) -> -8540.0995 | N8: -1871.6462 | O8: -1723.5156 | P8: -986.11263 | Q8: -1019.3571 | S8: -1277.9634 | T8: -1958.4923 | U8: -2130.005 | V8: -1707.8974 | X8: -1279.4038 | Y8: -1214.5275 | Z8: -1241.601 | AA8: -1691.0297 | AC8: -1303.9147 | AD8: -1155.2915 | AE8: -1106 | AF8: -687.06791 | AH8: -744.39754 | AI8: -686 | AJ8: -663 | AK8: -982 | AM8: -1545 | AN8: =[4]Ebitda!$AF$33/1000 -> -1687.4219 | AO8: =[4]Ebitda!$AK$33/1000 -> -2558.2851 | AP8: =[5]Ebitda!$AP$33/1000 -> -2463.4656 | AR8: =[6]Ebitda!$AX$33/1000 -> -2020.482 | AS8: =SUM('[16]Cash forecast Mgt Acc Format'!$BM$11:$BO$11) -> -1747.7865 | AT8: =SUM('[17]Cash forecast Mgt Acc Format'!$BP$11:$BR$11) -> -1871.1446 | AU8: =SUM('[17]Cash forecast Mgt Acc Format'!$BS$11:$BT$11) -> -1249.9742 | AW8: =[10]Ebitda!$BR$33/1000 -> -4217.0244 | AX8: =[18]Ebitda!$BW$33/1000 -> -4323.0751
B9: Other income | E9: 279.58491 | F9: 596.64531 | G9: =SUM(X9:AA9) -> 852.81359 | H9: =SUM(AC9:AF9) -> 420.50882 | I9: =SUM(AH9:AK9) -> 117 | J9: =SUM(AM9:AP9) -> 259 | K9: =SUM(AR9:AU9) -> 707 | L9: =SUM(AW9:AZ9) -> 35.00666 | N9: 135.35089 | O9: -113.20174 | P9: 132.43575 | Q9: 125.00001 | S9: 125.00001 | T9: 125.00001 | U9: 188.96628 | V9: 157.67901 | X9: 125.00001 | Y9: 546.64696 | Z9: 338.90001 | AA9: -157.73339 | AC9: 118.93449 | AD9: 293.57433 | AE9: 8 | AF9: 0 | AH9: 0 | AI9: 27 | AJ9: 90 | AK9: 0 | AM9: 100 | AN9: =59+54+46 -> 159 | AU9: 707 | AW9: ='[11]Income Statement'!$C$45 -> 15.00666 | AX9: 20
B10: Total Revenue | E10: =+SUM(E6:E9) -> 161929.19 | F10: =+SUM(F6:F9) -> 266737.37 | G10: =SUM(X10:AA10) -> 289341.57 | H10: =SUM(AC10:AF10) -> 329676.27 | I10: =SUM(AH10:AK10) -> 231314.61 | J10: =SUM(AM10:AP10) -> 226973.32 | K10: =SUM(AR10:AU10) -> 261790.99 | L10: =SUM(AW10:AZ10) -> 118859.87 | N10: =+SUM(N6:N9) -> 25766.147 | O10: =+SUM(O6:O9) -> 25419.911 | P10: =+SUM(P6:P9) -> 26946.322 | Q10: =+SUM(Q6:Q9) -> 83796.806 | S10: =+SUM(S6:S9) -> 47802.125 | T10: =+SUM(T6:T9) -> 57078.034 | U10: =+SUM(U6:U9) -> 75720.194 | V10: =+SUM(V6:V9) -> 86137.02 | X10: =+SUM(X6:X9) -> 67014.915 | Y10: =+SUM(Y6:Y9) -> 74299.832 | Z10: =+SUM(Z6:Z9) -> 76875.42 | AA10: =+SUM(AA6:AA9) -> 71151.405 | AC10: =+SUM(AC6:AC9) -> 79473.875 | AD10: =+SUM(AD6:AD9) -> 79037.335 | AE10: =+SUM(AE6:AE9) -> 88163.566 | AF10: =+SUM(AF6:AF9) -> 83001.492 | AH10: =+SUM(AH6:AH9) -> 76788.699 | AI10: =+SUM(AI6:AI9) -> 61009.911 | AJ10: =+SUM(AJ6:AJ9) -> 48698 | AK10: =+SUM(AK6:AK9) -> 44818 | AM10: =+SUM(AM6:AM9) -> 47559.311 | AN10: =+SUM(AN6:AN9) -> 55063.416 | AO10: =+SUM(AO6:AO9) -> 61573.676 | AP10: =+SUM(AP6:AP9) -> 62776.917 | AR10: =+SUM(AR6:AR9) -> 44978.972 | AS10: =+SUM(AS6:AS9) -> 59825.834 | AT10: =+SUM(AT6:AT9) -> 57974.269 | AU10: =+SUM(AU6:AU9) -> 99011.919 | AW10: =+SUM(AW6:AW9) -> 51230.996 | AX10: =+SUM(AX6:AX9) -> 67628.877 | AY10: =+SUM(AY6:AY9) -> 0 | AZ10: =+SUM(AZ6:AZ9) -> 0
B11: Operating costs | E11: -94194.354 | F11: -97456.494 | G11: =SUM(X11:AA11) -> -96456.013 | H11: =SUM(AC11:AF11) -> -105757.95 | I11: =SUM(AH11:AK11) -> -103879.18 | J11: =SUM(AM11:AP11) -> -107095.88 | K11: =SUM(AR11:AU11) -> -124689.91 | L11: =SUM(AW11:AZ11) -> -58652.46 | N11: -25417.455 | O11: -21543.637 | P11: -24424.929 | Q11: -22808.334 | S11: -22874.623 | T11: -25325.446 | U11: -26420.999 | V11: -22835.427 | X11: -23719.746 | Y11: -23201.756 | Z11: -24769 | AA11: -24765.512 | AC11: -26387.551 | AD11: -26497.776 | AE11: -27198 | AF11: -25674.62 | AH11: -25451.18 | AI11: -26451 | AJ11: -26337 | AK11: -25640 | AM11: -25466 | AN11: =[4]Ebitda!$AF$34/1000 -> -26973.647 | AO11: =[4]Ebitda!$AK$34/1000 -> -27140.409 | AP11: =[5]Ebitda!$AP$34/1000 -> -27515.823 | AR11: =[6]Ebitda!$AX$34/1000 -> -27140.409 | AS11: =[7]Ebitda!$BC$34/1000 -> -32595.168 | AT11: =[8]Ebitda!$BH$34/1000 -> -33133.509 | AU11: =[9]Ebitda!$BM$34/1000 -> -31820.825 | AW11: =[10]Ebitda!$BR$34/1000 -> -28336.46 | AX11: =-[18]Ebitda!$BW$34 -> -30316
B12: Operating profit | E12: =+E10+E11 -> 67734.832 | F12: =+F10+F11 -> 169280.88 | G12: =SUM(X12:AA12) -> 192885.56 | H12: =SUM(AC12:AF12) -> 223918.32 | I12: =SUM(AH12:AK12) -> 127435.43 | J12: =SUM(AM12:AP12) -> 119877.44 | K12: =SUM(AR12:AU12) -> 137101.08 | L12: =SUM(AW12:AZ12) -> 60207.413 | N12: =+N10+N11 -> 348.69256 | O12: =+O10+O11 -> 3876.274 | P12: =+P10+P11 -> 2521.393 | Q12: =+Q10+Q11 -> 60988.472 | S12: =+S10+S11 -> 24927.502 | T12: =+T10+T11 -> 31752.588 | U12: =+U10+U11 -> 49299.195 | V12: =+V10+V11 -> 63301.593 | X12: =+X10+X11 -> 43295.169 | Y12: =+Y10+Y11 -> 51098.076 | Z12: =+Z10+Z11 -> 52106.42 | AA12: =+AA10+AA11 -> 46385.893 | AC12: =+AC10+AC11 -> 53086.324 | AD12: =+AD10+AD11 -> 52539.559 | AE12: =+AE10+AE11 -> 60965.566 | AF12: =+AF10+AF11 -> 57326.872 | AH12: =+AH10+AH11 -> 51337.519 | AI12: =+AI10+AI11 -> 34558.911 | AJ12: =+AJ10+AJ11 -> 22361 | AK12: =+AK10+AK11 -> 19178 | AM12: =+AM10+AM11 -> 22093.311 | AN12: =+AN10+AN11 -> 28089.769 | AO12: =+AO10+AO11 -> 34433.267 | AP12: =+AP10+AP11 -> 35261.094 | AR12: =+AR10+AR11 -> 17838.563 | AS12: =+AS10+AS11 -> 27230.666 | AT12: =+AT10+AT11 -> 24840.759 | AU12: =+AU10+AU11 -> 67191.094 | AW12: =+AW10+AW11 -> 22894.536 | AX12: =+AX10+AX11 -> 37312.877 | AY12: =+AY10+AY11 -> 0 | AZ12: =+AZ10+AZ11 -> 0
B13: DAC Capitalised | E13: 73583.36 | F13: 0 | G13: =SUM(X13:AA13) -> 0 | H13: =SUM(AC13:AF13) -> 0 | I13: =SUM(AH13:AK13) -> 0 | J13: =SUM(AM13:AP13) -> 0 | K13: =SUM(AR13:AU13) -> 0 | N13: 18062.127 | O13: 20639.138 | P13: 17695.489 | Q13: 17186.606 | S13: 0 | T13: 0 | U13: 0 | V13: 0 | X13: 0 | Y13: 0 | Z13: 0 | AC13: 0 | AH13: 0 | AI13: 0 | AJ13: 0 | AK13: 0 | AM13: 0
B14: EBITDA | E14: =+E12+E13 -> 141318.19 | F14: =+F12+F13 -> 169280.88 | G14: =SUM(X14:AA14) -> 192885.56 | H14: =SUM(AC14:AF14) -> 223918.32 | I14: =SUM(AH14:AK14) -> 127435.43 | J14: =SUM(AM14:AP14) -> 119877.44 | K14: =SUM(AR14:AU14) -> 137101.08 | L14: =SUM(AW14:AZ14) -> 60207.413 | N14: =+N12+N13 -> 18410.82 | O14: =+O12+O13 -> 24515.412 | P14: =+P12+P13 -> 20216.882 | Q14: =+Q12+Q13 -> 78175.078 | S14: =+S12+S13 -> 24927.502 | T14: =+T12+T13 -> 31752.588 | U14: =+U12+U13 -> 49299.195 | V14: =+V12+V13 -> 63301.593 | X14: =+X12+X13 -> 43295.169 | Y14: =+Y12+Y13 -> 51098.076 | Z14: =+Z12+Z13 -> 52106.42 | AA14: =+AA12+AA13 -> 46385.893 | AC14: =+AC12+AC13 -> 53086.324 | AD14: =+AD12+AD13 -> 52539.559 | AE14: =+AE12+AE13 -> 60965.566 | AF14: =+AF12+AF13 -> 57326.872 | AH14: =+AH12+AH13 -> 51337.519 | AI14: =+AI12+AI13 -> 34558.911 | AJ14: =+AJ12+AJ13 -> 22361 | AK14: =+AK12+AK13 -> 19178 | AM14: =+AM12+AM13 -> 22093.311 | AN14: =+AN12+AN13 -> 28089.769 | AO14: =+AO12+AO13 -> 34433.267 | AP14: =+AP12+AP13 -> 35261.094 | AR14: =+AR12+AR13 -> 17838.563 | AS14: =+AS12+AS13 -> 27230.666 | AT14: =+AT12+AT13 -> 24840.759 | AU14: =+AU12+AU13 -> 67191.094 | AW14: =+AW12+AW13 -> 22894.536 | AX14: =+AX12+AX13 -> 37312.877 | AY14: =+AY12+AY13 -> 0 | AZ14: =+AZ12+AZ13 -> 0
B15: DAC Amortisation | E15: -176251.58 | F15: -85159.994 | G15: =SUM(X15:AA15) -> -82005.305 | H15: =SUM(AC15:AF15) -> -65072.471 | I15: =SUM(AH15:AK15) -> -4641 | J15: =SUM(AM15:AP15) -> -1591 | K15: =SUM(AR15:AU15) -> 0 | N15: -16304.719 | O15: -16599.248 | P15: -16262.815 | Q15: -127084.79 | S15: -6287.052 | T15: -2661.3724 | U15: -29396.44 | V15: -46815.13 | X15: -23579.305 | Y15: -12921 | Z15: -30959 | AA15: -14546 | AC15: -23207 | AD15: -17800.791 | AE15: -14085 | AF15: -9979.6793 | AH15: -16302 | AI15: 3639 | AJ15: 5326 | AK15: 2696 | AM15: -1591 | AW15: 0
B16: Depreciation | E16: -6325.0822 | F16: -5528.3976 | G16: =SUM(X16:AA16) -> -3682.1715 | H16: =SUM(AC16:AF16) -> -2942.6539 | I16: =SUM(AH16:AK16) -> -4011.7669 | J16: =SUM(AM16:AP16) -> -4960 | K16: =SUM(AR16:AU16) -> -6600 | L16: =SUM(AW16:AZ16) -> -3800.5684 | N16: -1490.2239 | O16: -1543.2878 | P16: -1504.1786 | Q16: -1787.3919 | S16: -1496.9262 | T16: -1469.7335 | U16: -1369.3875 | V16: -1192.3504 | X16: -1046.9058 | Y16: -870.11181 | Z16: -975.87857 | AA16: -789.27535 | AC16: -686.39277 | AD16: -694.93531 | AE16: -744 | AF16: -817.32584 | AH16: -898.76686 | AI16: -971 | AJ16: -1031 | AK16: -1111 | AM16: -1184 | AN16: -1376 | AO16: -1200 | AP16: -1200 | AR16: -1200 | AS16: =AR16 -> -1200 | AT16: -2100 | AU16: -2100 | AW16: ='[11]Income Statement'!$C$65+'[11]Income Statement'!$C$66+'[11]Income Statement'!$C$68 -> -1870.5684 | AX16: -1930
B17: Net Interest on Loans | E17: -25062.287 | F17: -25025.9 | G17: =SUM(X17:AA17) -> -22940.033 | H17: =SUM(AC17:AF17) -> -27349.305 | I17: =SUM(AH17:AK17) -> -35624.248 | J17: =SUM(AM17:AP17) -> -48909.572 | K17: =SUM(AR17:AU17) -> -56957.765 | L17: =SUM(AW17:AZ17) -> -19084.618 | N17: -5909.7876 | O17: -6339.4555 | P17: -6528.848 | Q17: -6284.1961 | S17: -5962.4836 | T17: -6102.3169 | U17: -6334.4674 | V17: -6626.6324 | X17: -6090.8651 | Y17: -5417.3066 | Z17: -5574.7958 | AA17: -5857.0654 | AC17: -6094.541 | AD17: -6616.4876 | AE17: -7030 | AF17: -7608.2767 | AH17: -7615.2477 | AI17: -8105 | AJ17: -9122 | AK17: -10782 | AM17: -10354 | AN17: =[4]Ebitda!$AF$21/1000 -> -12116.301 | AO17: =[4]Ebitda!$AK$21/1000 -> -12860.967 | AP17: =[5]Ebitda!$AP$21/1000 -> -13578.304 | AR17: =[6]Ebitda!$AX$21/1000 -> -13846.599 | AS17: =[7]Ebitda!$BC$21/1000 -> -15245.166 | AT17: -14485 | AU17: -13381 | AW17: =[10]Ebitda!$BR$21/1000 -> -14352.618 | AX17: -4732
B18: GAP Financing | E18: 31207.215 | F18: -56051.495 | G18: =SUM(X18:AA18) -> -75163.092 | H18: =SUM(AC18:AF18) -> -88866.185 | I18: =SUM(AH18:AK18) -> -87242.449 | J18: =SUM(AM18:AP18) -> -83894.215 | K18: =SUM(AR18:AU18) -> -85459.043 | L18: =SUM(AW18:AZ18) -> -44802.638 | N18: -3954.1065 | O18: -3929.3124 | P18: -4222.651 | Q18: 43313.285 | S18: -15014.086 | T18: -14201.553 | U18: -13742.225 | V18: -13093.631 | X18: -20422.194 | Y18: -19966.715 | Z18: -20828.736 | AA18: -13945.447 | AC18: -21768.431 | AD18: -22356.493 | AE18: -22831 | AF18: -21910.261 | AH18: -20429.449 | AI18: -21341 | AJ18: -22551 | AK18: -22921 | AM18: -23048 | AN18: =SUM('[12]Cell accounts'!$I$10:$K$11)/1000 -> -22311.87 | AO18: =[4]Ebitda!$AK$23/1000 -> -19310 | AP18: =[5]Ebitda!$AP$23/1000 -> -19224.345 | AR18: =[6]Ebitda!$AX$23/1000 -> -20596.772 | AS18: =[7]Ebitda!$BC$23/1000 -> -21602.024 | AT18: =[8]Ebitda!$BH$23/1000 -> -21602.024 | AU18: =[9]Ebitda!$BM$23/1000 -> -21658.222 | AW18: =[10]Ebitda!$BR$23/1000 -> -22597.638 | AX18: -22205
B19: PBT | E19: =+SUM(E14:E18) -> -35113.539 | F19: =+SUM(F14:F18) -> -2484.9075 | G19: =SUM(X19:AA19) -> 9094.9576 | H19: =SUM(AC19:AF19) -> 39687.706 | I19: =SUM(AH19:AK19) -> -4084.0339 | J19: =SUM(AM19:AP19) -> -19477.346 | K19: =SUM(AR19:AU19) -> -11915.727 | L19: =SUM(AW19:AZ19) -> -7480.4101 | N19: =+SUM(N14:N18) -> -9248.0168 | O19: =+SUM(O14:O18) -> -3895.8917 | P19: =+SUM(P14:P18) -> -8301.6113 | Q19: =+SUM(Q14:Q18) -> -13668.019 | S19: =+SUM(S14:S18) -> -3833.0455 | T19: =+SUM(T14:T18) -> 7317.6129 | U19: =+SUM(U14:U18) -> -1543.3241 | V19: =+SUM(V14:V18) -> -4426.1509 | X19: =+SUM(X14:X18) -> -7844.1005 | Y19: =+SUM(Y14:Y18) -> 11922.943 | Z19: =+SUM(Z14:Z18) -> -6231.9896 | AA19: =+SUM(AA14:AA18) -> 11248.105 | AC19: =+SUM(AC14:AC18) -> 1329.9591 | AD19: =+SUM(AD14:AD18) -> 5070.8513 | AE19: =+SUM(AE14:AE18) -> 16275.566 | AF19: =+SUM(AF14:AF18) -> 17011.33 | AH19: =+SUM(AH14:AH18) -> 6092.0555 | AI19: =+SUM(AI14:AI18) -> 7780.9106 | AJ19: =+SUM(AJ14:AJ18) -> -5017 | AK19: =+SUM(AK14:AK18) -> -12940 | AM19: =+SUM(AM14:AM18) -> -14083.689 | AN19: =+SUM(AN14:AN18) -> -7714.4026 | AO19: =+SUM(AO14:AO18) -> 1062.3002 | AP19: =+SUM(AP14:AP18) -> 1258.4448 | AR19: =+SUM(AR14:AR18) -> -17804.808 | AS19: =+SUM(AS14:AS18) -> -10816.525 | AT19: =+SUM(AT14:AT18) -> -13346.265 | AU19: =+SUM(AU14:AU18) -> 30051.871 | AW19: =+SUM(AW14:AW18) -> -15926.287 | AX19: =+SUM(AX14:AX18) -> 8445.877 | AY19: =+SUM(AY14:AY18) -> 0 | AZ19: =+SUM(AZ14:AZ18) -> 0
B20: Tax | E20: 0 | F20: 0 | G20: =SUM(X20:AA20) -> 0 | H20: =SUM(AC20:AF20) -> 0 | I20: =SUM(AH20:AK20) -> 0 | J20: =SUM(AM20:AP20) -> 0 | K20: =SUM(AR20:AU20) -> 0 | N20: 0 | O20: 0 | P20: 0 | Q20: 0 | S20: 0 | T20: 0 | U20: 0 | V20: 0 | X20: 0 | Y20: 0 | Z20: 0 | AC20: 0 | AD20: 0 | AE20: 0 | AH20: 0 | AI20: 0 | AJ20: 0 | AM20: 0
B21: PAT | E21: =+E19+E20 -> -35113.539 | F21: =+F19+F20 -> -2484.9075 | G21: =SUM(X21:AA21) -> 9094.9576 | H21: =SUM(AC21:AF21) -> 39687.706 | I21: =SUM(AH21:AK21) -> -4084.0339 | J21: =SUM(AM21:AP21) -> -19477.346 | K21: =SUM(AR21:AU21) -> -11915.727 | L21: =SUM(AW21:AZ21) -> -7480.4101 | N21: =+N19+N20 -> -9248.0168 | O21: =+O19+O20 -> -3895.8917 | P21: =+P19+P20 -> -8301.6113 | Q21: =+Q19+Q20 -> -13668.019 | S21: =+S19+S20 -> -3833.0455 | T21: =+T19+T20 -> 7317.6129 | U21: =+U19+U20 -> -1543.3241 | V21: =+V19+V20 -> -4426.1509 | X21: =+X19+X20 -> -7844.1005 | Y21: =+Y19+Y20 -> 11922.943 | Z21: =+Z19+Z20 -> -6231.9896 | AA21: =+AA19+AA20 -> 11248.105 | AC21: =+AC19+AC20 -> 1329.9591 | AD21: =+AD19+AD20 -> 5070.8513 | AE21: =+AE19+AE20 -> 16275.566 | AF21: =+AF19+AF20 -> 17011.33 | AH21: =+AH19+AH20 -> 6092.0555 | AI21: =+AI19+AI20 -> 7780.9106 | AJ21: =+AJ19+AJ20 -> -5017 | AK21: =+AK19+AK20 -> -12940 | AM21: =+AM19+AM20 -> -14083.689 | AN21: =+AN19+AN20 -> -7714.4026 | AO21: =+AO19+AO20 -> 1062.3002 | AP21: =+AP19+AP20 -> 1258.4448 | AR21: =+AR19+AR20 -> -17804.808 | AS21: =+AS19+AS20 -> -10816.525 | AT21: =+AT19+AT20 -> -13346.265 | AU21: =+AU19+AU20 -> 30051.871 | AW21: =+AW19+AW20 -> -15926.287 | AX21: =+AX19+AX20 -> 8445.877 | AY21: =+AY19+AY20 -> 0 | AZ21: =+AZ19+AZ20 -> 0

Sheet Current Data
B2: Key Performance Indicators
B4: Financial Metrics
F6: 2018 | H6: 2019 | L6: 2018 | N6: 2019 | R6: 2018 | T6: 2019
B7: Revenue (USD 000s)
B8: % change since last year
B9: EBITDA (USD 000s)
B10: % change since last year
B24: Monthly Historical Metrics
B26: Financial Metrics
F28: 2018 | G28: 2019 | I28: Q3 2018 | J28: Q4 2018 | K28: Q1 2019 | L28: Q2 2019 | M28: Q3 2019 | O28: 43101 | P28: 43132 | Q28: 43160 | R28: 43191 | S28: 43221 | T28: 43252 | U28: 43282 | V28: 43313 | W28: 43344 | X28: 43374 | Y28: 43405 | Z28: 43435 | AA28: 43466 | AB28: 43497 | AC28: 43525 | AD28: 43556 | AE28: 43586 | AF28: 43617 | AG28: 43647 | AH28: 43678 | AI28: 43709
B29: Revenue (USD 000s) | F29: 12197 | I29: =SUM(U29:W29) -> 2106.2771 | J29: =SUM(X29:Z29) -> 2043.1941 | K29: =33357.508/K33 -> 2380.7373 | L29: =L35/L$33 -> 2637.6803 | M29: =M35/M$33 -> 3793.1727 | U29: 690.11186 | V29: 710.77428 | W29: 705.39098 | X29: =10298.796/X33 -> 702.7976 | Y29: 700.36077 | Z29: 640.03576
B30: % change | F30: 0.35 | J30: =(J29-I29)/ABS(I29) -> -0.029949996 | K30: =(K29-J29)/ABS(J29) -> 0.16520365 | L30: =(L29-K29)/ABS(K29) -> 0.10792584 | M30: =(M29-L29)/ABS(L29) -> 0.43807142 | V30: =(V29-U29)/U29 -> 0.029940675 | W30: =(W29-V29)/V29 -> -0.0075738581 | X30: =(X29-W29)/W29 -> -0.0036765103 | Y30: =(Y29-X29)/X29 -> -0.0034673213 | Z30: =(Z29-Y29)/Y29 -> -0.086134202
B31: EBITDA (USD 000s) | F31: 11030 | I31: =SUM(U31:W31) -> -1191.4373 | J31: =SUM(X31:Z31) -> 1680.627 | K31: =25321.7534082514/K33 -> 1807.2226 | L31: =L37/L$33 -> 2150.8217 | M31: =M37/M$33 -> 3294.9587 | U31: -221.8915 | V31: -181.66642 | W31: -787.87938 | X31: =7872.063/X33 -> 537.19551 | Y31: 593.30089 | Z31: 550.13057
B32: % change | F32: 0.56 | J32: =(J31-I31)/ABS(I31) -> 2.4105878 | K32: =(K31-J31)/ABS(J31) -> 0.075326421 | L32: =(L31-K31)/ABS(K31) -> 0.19012553 | M32: =(M31-L31)/ABS(L31) -> 0.53195341 | V32: =(V31-U31)/U31 -> -0.18128262 | W32: =(W31-V31)/V31 -> 3.3369565 | X32: =(X31-W31)/W31 -> -1.6818246 | Y32: =(Y31-X31)/X31 -> 0.10444126 | Z32: =(Z31-Y31)/Y31 -> -0.072762942
B33: FX Rate | K33: =AVERAGE(AA33:AC33) -> 14.011419 | L33: =AVERAGE(AD33:AF33) -> 14.377199 | M33: =AVERAGE(AG33:AI33) -> 14.69284 | U33: 13.1676 | V33: 13.3598 | W33: 14.0777 | X33: 14.654 | Y33: 13.7761 | Z33: 14.3965 | AA33: 13.871648 | AB33: 13.781627 | AC33: 14.380983 | AD33: 14.145649 | AE33: 14.402048 | AF33: 14.5839 | AG33: 14.05693 | AH33: 15.150308 | AI33: 14.871281
B35: Revenue (ZAR 000s) | L35: 37922.455 | M35: 55732.478
B36: % change
B37: EBITDA (ZAR 000s) | L37: 30922.792 | M37: 48412.3
B38: % change
B40: Operational Metrics
F42: 2018 | G42: 2019 | I42: Q3 2018 | J42: Q4 2018 | K42: Q1 2019 | L42: Q2 2019 | M42: Q3 2019 | O42: 43101 | P42: 43132 | Q42: 43160 | R42: 43191 | S42: 43221 | T42: 43252 | U42: 43282 | V42: 43313 | W42: 43344 | X42: 43374 | Y42: 43405 | Z42: 43435 | AA42: 43466 | AB42: 43497 | AC42: 43525 | AD42: 43556 | AE42: 43586 | AF42: 43617 | AG42: 43647 | AH42: 43678 | AI42: 43709
B43: HIV Inceptions (USD) | F43: 156558 | I43: =SUM(U43:W43) -> 44234.778 | J43: =SUM(X43:Z43) -> 42510.471 | K43: =SUM(AA43:AC43) -> 44739.715 | L43: =L59/L$33 -> 46691.153 | M43: =M59/M$33 -> 59530.426 | U43: 15094.626 | V43: 15069.387 | W43: 14070.764 | X43: 15585.506 | Y43: 17706.753 | Z43: 9218.2128 | AA43: 10220.127 | AB43: 16593.832 | AC43: 17925.757
B44: % change | F44: -0.4 | J44: =(J43-I43)/I43 -> -0.038980787 | K44: =(K43-J43)/J43 -> 0.05243987 | L44: =(L43-K43)/K43 -> 0.043617581 | M44: =(M43-L43)/L43 -> 0.27498298 | V44: =(V43-U43)/U43 -> -0.0016720479 | W44: =(W43-V43)/V43 -> -0.066268313 | X44: =(X43-W43)/W43 -> 0.10765167 | Y44: =(Y43-X43)/X43 -> 0.13610385 | Z44: =(Z43-Y43)/Y43 -> -0.47939564 | AA44: =(AA43-Z43)/Z43 -> 0.10868852 | AB44: =(AB43-AA43)/AA43 -> 0.62364247 | AC44: =(AC43-AB43)/AB43 -> 0.080266257
B45: DIA Inceptions (USD) | F45: 33533 | I45: =SUM(U45:W45) -> 11097.431 | J45: =SUM(X45:Z45) -> 11303.464 | K45: =SUM(AA45:AC45) -> 11677.189 | L45: =L61/L$33 -> 16775.938 | M45: =M61/M$33 -> 18714.762 | U45: 4480.3153 | V45: 4072.6658 | W45: 2544.4497 | X45: 3689.7775 | Y45: 3538.7374 | Z45: 4074.9488 | AA45: 3314.6747 | AB45: 4807.1247 | AC45: 3555.3898
B46: % change | F46: -0.37 | J46: =(J45-I45)/I45 -> 0.018565818 | K46: =(K45-J45)/J45 -> 0.033062917 | L46: =(L45-K45)/K45 -> 0.4366418 | M46: =(M45-L45)/L45 -> 0.11557173 | V46: =(V45-U45)/U45 -> -0.090986802 | W46: =(W45-V45)/V45 -> -0.37523728 | X46: =(X45-W45)/W45 -> 0.4501279 | Y46: =(Y45-X45)/X45 -> -0.04093476 | Z46: =(Z45-Y45)/Y45 -> 0.15152619 | AA46: =(AA45-Z45)/Z45 -> -0.18657268 | AB46: =(AB45-AA45)/AA45 -> 0.45025538 | AC46: =(AC45-AB45)/AB45 -> -0.26039161
B47: HIV New policies (#) | F47: 5595 | I47: =SUM(U47:W47) -> 1364 | J47: =SUM(X47:Z47) -> 1295 | K47: =SUM(AA47:AC47) -> 1422 | L47: 1643 | M47: 2235 | U47: 398 | V47: 472 | W47: 494 | X47: 513 | Y47: 501 | Z47: 281 | AA47: 376 | AB47: 503 | AC47: 543
B48: % change | F48: -0.24 | J48: =(J47-I47)/I47 -> -0.05058651 | K48: =(K47-J47)/J47 -> 0.098069498 | L48: =(L47-K47)/K47 -> 0.15541491 | M48: =(M47-L47)/L47 -> 0.36031649 | V48: =(V47-U47)/U47 -> 0.18592965 | W48: =(W47-V47)/V47 -> 0.046610169 | X48: =(X47-W47)/W47 -> 0.038461538 | Y48: =(Y47-X47)/X47 -> -0.023391813 | Z48: =(Z47-Y47)/Y47 -> -0.43912176 | AA48: =(AA47-Z47)/Z47 -> 0.33807829 | AB48: =(AB47-AA47)/AA47 -> 0.33776596 | AC48: =(AC47-AB47)/AB47 -> 0.079522863
B49: DIA New policies (#) | F49: 852 | I49: =SUM(U49:W49) -> 230 | J49: =SUM(X49:Z49) -> 258 | K49: =SUM(AA49:AC49) -> 303 | L49: 570 | M49: 650 | U49: 80 | V49: 75 | W49: 75 | X49: 77 | Y49: 92 | Z49: 89 | AA49: 90 | AB49: 114 | AC49: 99
B50: % change | F50: -0.36 | J50: =(J49-I49)/I49 -> 0.12173913 | K50: =(K49-J49)/J49 -> 0.1744186 | L50: =(L49-K49)/K49 -> 0.88118812 | M50: =(M49-L49)/L49 -> 0.14035088 | V50: =(V49-U49)/U49 -> -0.0625 | W50: =(W49-V49)/V49 -> 0 | X50: =(X49-W49)/W49 -> 0.026666667 | Y50: =(Y49-X49)/X49 -> 0.19480519 | Z50: =(Z49-Y49)/Y49 -> -0.032608696 | AA50: =(AA49-Z49)/Z49 -> 0.011235955 | AB50: =(AB49-AA49)/AA49 -> 0.26666667 | AC50: =(AC49-AB49)/AB49 -> -0.13157895
B51: Average total charge to client (USD) | F51: 32 | I51: =AVERAGE(U51:W51) -> 34.268493 | J51: =AVERAGE(X51:Z51) -> 31.063076 | K51: =AVERAGE(AA51:AC51) -> 35.860288 | L51: =L63/L$33 -> 27.752276 | M51: =M63/M$33 -> 27.208202 | U51: 31.424841 | V51: 30.61598 | W51: 40.76466 | X51: 28.986919 | Y51: 32.780198 | Z51: 31.422111 | AA51: 34.427066 | AB51: 33.08519 | AC51: 40.068607
B52: % change | F52: -0.01 | J52: =(J51-I51)/I51 -> -0.093538324 | K52: =(K51-J51)/J51 -> 0.15443454 | L52: =(L51-K51)/K51 -> -0.2261 | M52: =(M51-L51)/L51 -> -0.019604669 | V52: =(V51-U51)/U51 -> -0.025739539 | W52: =(W51-V51)/V51 -> 0.33148311 | X52: =(X51-W51)/W51 -> -0.28892038 | Y52: =(Y51-X51)/X51 -> 0.13086177 | Z52: =(Z51-Y51)/Y51 -> -0.041430104 | AA52: =(AA51-Z51)/Z51 -> 0.095631854 | AB52: =(AB51-AA51)/AA51 -> -0.038977361 | AC52: =(AC51-AB51)/AB51 -> 0.21107383
B53: Total acquisition costs (USD 000s) | F53: 2933 | I53: =SUM(U53:W53) -> 354.62211 | J53: =SUM(X53:Z53) -> 264.74628 | K53: =10830.349/K33 -> 772.96587 | L53: =L65/L$33 -> 808.39439 | M53: =M65/M$33 -> 871.08349 | U53: 103.40307 | V53: 134.16971 | W53: 117.04933 | X53: 90.436806 | Y53: 112.55676 | Z53: 61.752722 | AA53: 135.15647 | AB53: 132.49894 | AC53: 140.39708
B54: % change | F54: -0.41 | J54: =(J53-I53)/I53 -> -0.25344112 | K54: =(K53-J53)/J53 -> 1.9196477 | L54: =(L53-K53)/K53 -> 0.045834513 | M54: =(M53-L53)/L53 -> 0.077547665 | V54: =(V53-U53)/U53 -> 0.2975408 | W54: =(W53-V53)/V53 -> -0.12760242 | X54: =(X53-W53)/W53 -> -0.2273616 | Y54: =(Y53-X53)/X53 -> 0.24459013 | Z54: =(Z53-Y53)/Y53 -> -0.4513637 | AA54: =(AA53-Z53)/Z53 -> 1.1886723 | AB54: =(AB53-AA53)/AA53 -> -0.019662613 | AC54: =(AC53-AB53)/AB53 -> 0.059609052
B55: Total charge to client (USD 000s) | F55: 9411 | I55: =SUM(U55:W55) -> 2550.1544 | J55: =SUM(X55:Z55) -> 2390.21 | K55: =SUM(AA55:AC55) -> 2380.8175 | L55: =L67/L$33 -> 2637.6803 | M55: =M67/M$33 -> 2683.4634 | U55: 852.31008 | V55: 851.07003 | W55: 846.7743 | X55: 788.45553 | Y55: 820.96726 | Z55: 780.78724 | AA55: 740.00593 | AB55: 841.03299 | AC55: 799.77863
B56: % change | F56: -0.16 | J56: =(J55-I55)/I55 -> -0.062719487 | K56: =(K55-J55)/J55 -> -0.0039295647 | L56: =(L55-K55)/K55 -> 0.10788848 | M56: =(M55-L55)/L55 -> 0.017357313 | V56: =(V55-U55)/U55 -> -0.0014549326 | W56: =(W55-V55)/V55 -> -0.0050474471 | X56: =(X55-W55)/W55 -> -0.068871684 | Y56: =(Y55-X55)/X55 -> 0.041234713 | Z56: =(Z55-Y55)/Y55 -> -0.048942291 | AA56: =(AA55-Z55)/Z55 -> -0.05223102 | AB56: =(AB55-AA55)/AA55 -> 0.13652195 | AC56: =(AC55-AB55)/AB55 -> -0.049052006
B59: HIV Inceptions (ZAR) | L59: 671288 | M59: 874671
B60: % change | M60: =(M59-L59)/L59 -> 0.30297428
B61: DIA Inceptions (ZAR) | L61: 241191 | M61: 274973
B62: % change | M62: =(M61-L61)/L61 -> 0.14006327
B63: Average total charge to client (ZAR) | L63: 399 | M63: 399.76575
B64: % change | M64: =(M63-L63)/L63 -> 0.0019191779
B65: Total acquisition costs (ZAR 000s) | L65: 11622.447 | M65: 12798.69
B66: % change | M66: =(M65-L65)/L65 -> 0.10120442
B67: Total charge to client (ZAR 000s) | L67: 37922.455 | M67: 39427.697
B68: % change | M68: =(M67-L67)/L67 -> 0.039692633
B71: Impact Metrics
F73: 2018 | G73: 2019 | I73: Q3 2018 | J73: Q4 2018 | K73: Q1 2019 | L73: Q2 2019 | M73: Q3 2019
B74: Customers | F74: =J74 -> 31328 | I74: 31513 | J74: 31328 | K74: 31467 | L74: 31425 | M74: 33359
B75: % change | F75: -0.06 | J75: =(J74-I74)/I74 -> -0.0058705931 | K75: =(K74-J74)/J74 -> 0.0044369254 | L75: =(L74-K74)/K74 -> -0.0013347316 | M75: =(M74-L74)/L74 -> 0.061543357
B76: Underserved customers | F76: =J76 -> 31328 | I76: =I74 -> 31513 | J76: =J74 -> 31328 | K76: =K74 -> 31467 | L76: =L74 -> 31425 | M76: =M74 -> 33359
B77: % change | F77: -0.06 | J77: =(J76-I76)/I76 -> -0.0058705931 | K77: =(K76-J76)/J76 -> 0.0044369254 | L77: =(L76-K76)/K76 -> -0.0013347316 | M77: =(M76-L76)/L76 -> 0.061543357
B78: Full time employees | F78: =J78 -> 102 | I78: 113 | J78: 102 | K78: 136 | L78: 105 | M78: 134
B79: % change | F79: -0.16 | J79: =(J78-I78)/I78 -> -0.097345133 | K79: =(K78-J78)/J78 -> 0.33333333 | L79: =(L78-K78)/K78 -> -0.22794118 | M79: =(M78-L78)/L78 -> 0.27619048
B80: Lives touched | F80: 100576 | I80: =(I78+I74)*$E$94 -> 101203.2 | J80: =(J78+J74)*$E$94 -> 100576 | K80: =(K78+K74)*$E$94 -> 101129.6 | L80: =(L78+L74)*$E$94 -> 100896 | M80: =(M78+M74)*$E$94 -> 107177.6
B81: % change | F81: -0.06 | J81: =(J80-I80)/I80 -> -0.0061974325 | K81: =(K80-J80)/J80 -> 0.0055042953 | L81: =(L80-K80)/K80 -> -0.0023099073 | M81: =(M80-L80)/L80 -> 0.062258167
B82: Underserved Lives Touched | F82: 100250 | I82: =I76*$E$94 -> 100841.6 | J82: =J76*$E$94 -> 100249.6 | K82: =K76*$E$94 -> 100694.4 | L82: =L76*$E$94 -> 100560 | M82: =M76*$E$94 -> 106748.8
B83: % change | F83: -0.06 | J83: =(J82-I82)/I82 -> -0.0058705931 | K83: =(K82-J82)/J82 -> 0.0044369254 | L83: =(L82-K82)/K82 -> -0.0013347316 | M83: =(M82-L82)/L82 -> 0.061543357
B84: Countries in Operation | F84: =J84 -> 2 | I84: 2 | J84: 2 | K84: 4 | L84: 4 | M84: 4
B85: % change | F85: =J85 -> 0 | J85: =(J84-I84)/I84 -> 0 | K85: 0 | L85: =(L84-K84)/K84 -> 0 | M85: =(M84-L84)/L84 -> 0
B88: Female Employees | F88: =J88 -> 75 | J88: 75 | K88: 104 | L88: 80 | M88: 102
B92: Data Assumptions
B94: Household Multiplier | E94: 3.2
B98: Annualized Interest Rate
B99: PAR 90 (Period-End)
B100: Full Time Employees
