Workbook

Sheet KPIs
B2: Quona KPIs - Enza Group | C2: [unit] | E2: 45658 | F2: =EOMONTH(E2,1) -> 45716 | G2: =EOMONTH(F2,1) -> 45747 | H2: =EOMONTH(G2,1) -> 45777 | I2: =EOMONTH(H2,1) -> 45808 | J2: =EOMONTH(I2,1) -> 45838 | K2: =EOMONTH(J2,1) -> 45869 | L2: =EOMONTH(K2,1) -> 45900 | M2: =EOMONTH(L2,1) -> 45930 | ... P2: =EOMONTH(O2,1) -> 46022 | R2: 46023 | S2: =EOMONTH(R2,1) -> 46081 | T2: =EOMONTH(S2,1) -> 46112 | U2: =EOMONTH(T2,1) -> 46142 | V2: =EOMONTH(U2,1) -> 46173 | W2: =EOMONTH(V2,1) -> 46203 | X2: =EOMONTH(W2,1) -> 46234 | Y2: =EOMONTH(X2,1) -> 46265 | Z2: =EOMONTH(Y2,1) -> 46295 | ... AC2: =EOMONTH(AB2,1) -> 46387
B4: Operational Metrics
B5: Total Processed Volumes | C5: USD
B6: Transaction Count | C6: # | E6: =SUM([1]Sheet1!B14:B16,[1]Sheet1!B9) -> 105 | F6: =SUM([1]Sheet1!C14:C16,[1]Sheet1!C9) -> 20 | G6: =SUM([1]Sheet1!D14:D16,[1]Sheet1!D9) -> 8 | H6: =SUM([1]Sheet1!E14:E16,[1]Sheet1!E9) -> 167 | I6: =SUM([1]Sheet1!F14:F16,[1]Sheet1!F9) -> 71 | J6: =SUM([1]Sheet1!G14:G16,[1]Sheet1!G9) -> 80 | K6: =SUM([1]Sheet1!H14:H16,[1]Sheet1!H9) -> 0 | L6: =SUM([1]Sheet1!I14:I16,[1]Sheet1!I9) -> 64 | ... P6: =SUM([1]Sheet1!M14:M16,[1]Sheet1!M9) -> 276 | R6: =SUM([1]Sheet1!O14:O16,[1]Sheet1!O9) -> 530 | S6: =SUM([1]Sheet1!P14:P16,[1]Sheet1!P9) -> 12526 | T6: =SUM([1]Sheet1!Q14:Q16,[1]Sheet1!Q9) -> 6911
B7: Total Revenues | C7: USD | E7: =SUM(E8:E11) -> 15853.23 | F7: =SUM(F8:F11) -> 5050.7412 | G7: =SUM(G8:G11) -> 25050.25 | H7: =SUM(H8:H11) -> 5075.6412 | I7: =SUM(I8:I11) -> 5083.0621 | J7: =SUM(J8:J11) -> 5101.8235 | K7: =SUM(K8:K11) -> 5100 | L7: =SUM(L8:L11) -> 10000.003 | ... P7: =SUM(P8:P11) -> 290500 | R7: =SUM(R8:R11) -> 11600.003 | S7: =SUM(S8:S11) -> 11600.003 | T7: =SUM(T8:T11) -> 397350
B8: Issuer Processing Revenues | C8: USD | E8: ='P&L'!E14 -> 10800 | F8: ='P&L'!F14 -> 0 | G8: ='P&L'!G14 -> 0 | H8: ='P&L'!H14 -> 0 | I8: ='P&L'!I14 -> 0 | J8: ='P&L'!J14 -> 0 | K8: ='P&L'!K14 -> 0 | L8: ='P&L'!L14 -> 0 | ... P8: ='P&L'!P14 -> 300500 | R8: ='P&L'!S14 -> 1600.0027 | S8: ='P&L'!T14 -> 1600.0027 | T8: ='P&L'!U14 -> 387350
B9: Acceptance Revenues | C9: USD | E9: ='P&L'!E24 -> 0 | F9: ='P&L'!F24 -> 0 | G9: ='P&L'!G24 -> 0 | H9: ='P&L'!H24 -> 0 | I9: ='P&L'!I24 -> 0 | J9: ='P&L'!J24 -> 0 | K9: ='P&L'!K24 -> 0 | L9: ='P&L'!L24 -> 0 | ... P9: ='P&L'!P24 -> 0 | R9: ='P&L'!S24 -> 0 | S9: ='P&L'!T24 -> 0 | T9: ='P&L'!U24 -> 0
B10: enza conductor | C10: USD | E10: ='P&L'!E19 -> 5053.2297 | F10: ='P&L'!F19 -> 5050.7412 | G10: ='P&L'!G19 -> 25050.25 | H10: ='P&L'!H19 -> 5075.6412 | I10: ='P&L'!I19 -> 5083.0621 | J10: ='P&L'!J19 -> 5101.8235 | K10: ='P&L'!K19 -> 5100 | L10: ='P&L'!L19 -> 10000.003 | ... P10: ='P&L'!P19 -> -10000.001 | R10: ='P&L'!S19 -> 10000 | S10: ='P&L'!T19 -> 10000 | T10: ='P&L'!U19 -> 9999.9973
B11: Value Add Services Revenues | C11: USD | E11: ='[2]Detailed FS_$ Cons. (formating)'!BR$10 -> 0 | F11: ='[2]Detailed FS_$ Cons. (formating)'!BS$10 -> 0 | G11: ='[2]Detailed FS_$ Cons. (formating)'!BT$10 -> 0 | H11: ='[2]Detailed FS_$ Cons. (formating)'!BU$10 -> 0 | I11: ='[2]Detailed FS_$ Cons. (formating)'!BV$10 -> 0 | J11: ='[2]Detailed FS_$ Cons. (formating)'!BW$10 -> 0 | K11: ='[2]Detailed FS_$ Cons. (formating)'!BX$10 -> 0 | L11: ='[2]Detailed FS_$ Cons. (formating)'!BY$10 -> 0 | ... P11: ='[2]Detailed FS_$ Cons. (formating)'!CC$10 -> 0 | R11: ='[2]Detailed FS_$ Cons. (formating)'!CF$10 -> 0 | S11: ='[2]Detailed FS_$ Cons. (formating)'!CG$10 -> 0 | T11: ='[2]Detailed FS_$ Cons. (formating)'!CH$10 -> 0
B12: COGS | C12: USD | E12: ='P&L'!E51 -> -9999.8639 | F12: ='P&L'!F51 -> -9999.8639 | G12: ='P&L'!G51 -> -10000 | H12: ='P&L'!H51 -> -10000 | I12: ='P&L'!I51 -> 40000 | J12: ='P&L'!J51 -> 0 | K12: ='P&L'!K51 -> 0 | L12: ='P&L'!L51 -> 0 | ... P12: ='P&L'!P51 -> -3580.5118 | R12: ='P&L'!S51 -> -2187.2012 | S12: ='P&L'!T51 -> -2187.2012 | T12: ='P&L'!U51 -> -2187.2012
B13: Contribution Margin | C13: USD | E13: =E7+E12 -> 5853.3658 | F13: =F7+F12 -> -4949.1226 | G13: =G7+G12 -> 15050.25 | H13: =H7+H12 -> -4924.3588 | I13: =I7+I12 -> 45083.062 | J13: =J7+J12 -> 5101.8235 | K13: =K7+K12 -> 5100 | L13: =L7+L12 -> 10000.003 | ... P13: =P7+P12 -> 286919.49 | R13: =R7+R12 -> 9412.8015 | S13: =S7+S12 -> 9412.8015 | T13: =T7+T12 -> 395162.8
B14: Contibution Margin | C14: % | E14: =E13/E7 -> 0.36922229 | F14: =F13/F7 -> -0.97988046 | G14: =G13/G7 -> 0.60080239 | H14: =H13/H7 -> -0.97019444 | I14: =I13/I7 -> 8.8692723 | J14: =J13/J7 -> 1 | K14: =IFERROR(K13/K7,0) -> 1 | L14: =IFERROR(L13/L7,0) -> 1 | M14: =IFERROR(M13/M7,0) -> 1 | N14: =IFERROR(N13/N7,0) -> -15.560166 | O14: =IFERROR(O13/O7,0) -> 0.72417548 | P14: =IFERROR(P13/P7,0) -> 0.98767466 | R14: =IFERROR(R13/R7,0) -> 0.81144822 | S14: =IFERROR(S13/S7,0) -> 0.81144822 | T14: =IFERROR(T13/T7,0) -> 0.99449553
B15: EBITDA | C15: USD | E15: ='P&L'!E120 -> -200195.8 | F15: ='P&L'!F120 -> -254096.13 | G15: ='P&L'!G120 -> -236704.41 | H15: ='P&L'!H120 -> -252988.65 | I15: ='P&L'!I120 -> -292041.93 | J15: ='P&L'!J120 -> -224377.04 | K15: ='P&L'!K120 -> -377020.29 | L15: ='P&L'!L120 -> -248243.75 | ... P15: ='P&L'!P120 -> -32075.749 | R15: ='P&L'!S120 -> -366484.09 | S15: ='P&L'!T120 -> -346373.03 | T15: ='P&L'!U120 -> 64903.82
B17: Employees
B18: Total Employees | C18: # | I18: 54 | J18: 53 | K18: 53 | L18: 54 | M18: 54 | N18: 57 | O18: 60 | P18: 64 | R18: 65 | S18: 63 | T18: 64
B19: Total Female Employees | C19: # | I19: 14 | J19: 14 | K19: 14 | L19: 14 | M19: 19 | N19: 20 | O19: 20 | P19: 20 | R19: =17+1+1 -> 19 | S19: =16+1+1 -> 18 | T19: =15+1+1 -> 17
R20: =32+8+2+4 -> 46 | S20: =31+8+2+4 -> 45 | T20: =32+8+3+4 -> 47
B21: Senior Management
B22: Total Senior Managers | C22: # | I22: 10 | J22: 11 | K22: 11 | L22: 11 | M22: 11 | N22: 11 | O22: 11 | P22: 12 | R22: 12 | S22: 12 | T22: 13
B23: Total Female Senior Managers | C23: # | I23: 2 | J23: 2 | K23: 2 | L23: 2 | M23: 2 | N23: 2 | O23: 2 | P23: 2 | R23: 2 | S23: 2 | T23: 2
B25: Customers
B26: Number of Clients (Banks/Institutions) | C26: # | E26: 2 | F26: 2 | G26: 3 | H26: 3 | I26: 5 | J26: 10 | K26: 10 | L26: 10 | M26: 11 | N26: 11 | O26: 11 | P26: =[1]Sheet1!$O$13+[1]Sheet1!$O$4 -> 11 | R26: =[1]Sheet1!O13+[1]Sheet1!O4 -> 11 | S26: =[1]Sheet1!P13+[1]Sheet1!P4 -> 11 | T26: =[1]Sheet1!Q13+[1]Sheet1!Q4 -> 13
B27: Number of Clients (MFIs and Small FIs) | C27: #
B28: Number of Issuer Credentials
B29: Number of Merchants | C29: # | E29: ='[3]KPIs '!B18 -> 5 | F29: ='[3]KPIs '!C18 -> 5 | G29: ='[3]KPIs '!D18 -> 5 | H29: ='[3]KPIs '!E18 -> 7 | I29: ='[3]KPIs '!F18 -> 8 | J29: ='[3]KPIs '!G18 -> 10 | K29: ='[3]KPIs '!H18 -> 10 | L29: ='[3]KPIs '!I18 -> 11 | ... O29: ='[3]KPIs '!L18 -> 11 | P29: 11 | R29: =[1]Sheet1!O17 -> 12 | S29: =[1]Sheet1!P17 -> 17 | T29: =[1]Sheet1!Q17 -> 18
B31: Cash Reserves
B32: Cash Reserves | C32: USD
B33: Monthly Cash Burn | C33: USD
B34: Runway | C34: USD

Sheet P&L
B1: First Year | C1: 2026
B2: Selected Plan | C2: AV
B3: Last Month | C3: 46053
B5: past months | E5: =IF(AND(E7<=$C$3,YEAR(E7)=YEAR($C$3)),1,0) -> 0 | F5: =IF(AND(F7<=$C$3,YEAR(F7)=YEAR($C$3)),1,0) -> 0 | G5: =IF(AND(G7<=$C$3,YEAR(G7)=YEAR($C$3)),1,0) -> 0 | H5: =IF(AND(H7<=$C$3,YEAR(H7)=YEAR($C$3)),1,0) -> 0 | I5: =IF(AND(I7<=$C$3,YEAR(I7)=YEAR($C$3)),1,0) -> 0 | J5: =IF(AND(J7<=$C$3,YEAR(J7)=YEAR($C$3)),1,0) -> 0 | K5: =IF(AND(K7<=$C$3,YEAR(K7)=YEAR($C$3)),1,0) -> 0 | L5: =IF(AND(L7<=$C$3,YEAR(L7)=YEAR($C$3)),1,0) -> 0 | ... P5: =IF(AND(P7<=$C$3,YEAR(P7)=YEAR($C$3)),1,0) -> 0 | S5: =IF(AND(S7<=$C$3,YEAR(S7)=YEAR($C$3)),1,0) -> 1 | T5: =IF(AND(T7<=$C$3,YEAR(T7)=YEAR($C$3)),1,0) -> 0 | U5: =IF(AND(U7<=$C$3,YEAR(U7)=YEAR($C$3)),1,0) -> 0 | V5: =IF(AND(V7<=$C$3,YEAR(V7)=YEAR($C$3)),1,0) -> 0 | W5: =IF(AND(W7<=$C$3,YEAR(W7)=YEAR($C$3)),1,0) -> 0 | X5: =IF(AND(X7<=$C$3,YEAR(X7)=YEAR($C$3)),1,0) -> 0 | Y5: =IF(AND(Y7<=$C$3,YEAR(Y7)=YEAR($C$3)),1,0) -> 0 | Z5: =IF(AND(Z7<=$C$3,YEAR(Z7)=YEAR($C$3)),1,0) -> 0 | ... AD5: =IF(AND(AD7<=$C$3,YEAR(AD7)=YEAR($C$3)),1,0) -> 0
B6: last month | E6: =IF(E7=$C$3,1,0) -> 0 | F6: =IF(F7=$C$3,1,0) -> 0 | G6: =IF(G7=$C$3,1,0) -> 0 | H6: =IF(H7=$C$3,1,0) -> 0 | I6: =IF(I7=$C$3,1,0) -> 0 | J6: =IF(J7=$C$3,1,0) -> 0 | K6: =IF(K7=$C$3,1,0) -> 0 | L6: =IF(L7=$C$3,1,0) -> 0 | ... P6: =IF(P7=$C$3,1,0) -> 0 | S6: =IF(S7=$C$3,1,0) -> 1 | T6: =IF(T7=$C$3,1,0) -> 0 | U6: =IF(U7=$C$3,1,0) -> 0 | V6: =IF(V7=$C$3,1,0) -> 0 | W6: =IF(W7=$C$3,1,0) -> 0 | X6: =IF(X7=$C$3,1,0) -> 0 | Y6: =IF(Y7=$C$3,1,0) -> 0 | Z6: =IF(Z7=$C$3,1,0) -> 0 | ... AD6: =IF(AD7=$C$3,1,0) -> 0
B7: P&L | C7: USD | E7: 45688 | F7: =EOMONTH(E7,1) -> 45716 | G7: =EOMONTH(F7,1) -> 45747 | H7: =EOMONTH(G7,1) -> 45777 | I7: =EOMONTH(H7,1) -> 45808 | J7: =EOMONTH(I7,1) -> 45838 | K7: =EOMONTH(J7,1) -> 45869 | L7: =EOMONTH(K7,1) -> 45900 | M7: =EOMONTH(L7,1) -> 45930 | ... P7: =EOMONTH(O7,1) -> 46022 | Q7: =YEAR(P7) -> 2025 | S7: =EOMONTH(P7,1) -> 46053 | T7: =EOMONTH(S7,1) -> 46081 | U7: =EOMONTH(T7,1) -> 46112 | V7: =EOMONTH(U7,1) -> 46142 | W7: =EOMONTH(V7,1) -> 46173 | X7: =EOMONTH(W7,1) -> 46203 | Y7: =EOMONTH(X7,1) -> 46234 | Z7: =EOMONTH(Y7,1) -> 46265 | AA7: =EOMONTH(Z7,1) -> 46295 | ... AD7: =EOMONTH(AC7,1) -> 46387 | AE7: =YEAR(AD7) -> 2026 | AH7: =C3 -> 46053 | AI7: YTD
E8: =E9-'[2]Detailed FS_$ Cons. (formating)'!BR13 -> 0 | F8: =F9-'[2]Detailed FS_$ Cons. (formating)'!BS13 -> 0 | G8: =G9-'[2]Detailed FS_$ Cons. (formating)'!BT13 -> 0 | H8: =H9-'[2]Detailed FS_$ Cons. (formating)'!BU13 -> 0 | I8: =I9-'[2]Detailed FS_$ Cons. (formating)'!BV13 -> 0 | J8: =J9-'[2]Detailed FS_$ Cons. (formating)'!BW13 -> 0 | K8: =K9-'[2]Detailed FS_$ Cons. (formating)'!BX13 -> 0 | L8: =L9-'[2]Detailed FS_$ Cons. (formating)'!BY13 -> 0 | ... P8: =P9-'[2]Detailed FS_$ Cons. (formating)'!CC13 -> 0 | Q8: 12 months | S8: =S9-'[2]Detailed FS_$ Cons. (formating)'!CF13 -> 0 | T8: =T9-'[2]Detailed FS_$ Cons. (formating)'!CG13 -> 0 | U8: =U9-'[2]Detailed FS_$ Cons. (formating)'!CH13 -> 0 | AE8: 12 months | AH8: last month | BH8: AV
B9: GMV | C9: Actual | E9: =SUM(E14,E19,E24) -> 15853.23 | F9: =SUM(F14,F19,F24) -> 5050.7412 | G9: =SUM(G14,G19,G24) -> 25050.25 | H9: =SUM(H14,H19,H24) -> 5075.6412 | I9: =SUM(I14,I19,I24) -> 5083.0621 | J9: =SUM(J14,J19,J24) -> 5101.8235 | K9: =SUM(K14,K19,K24) -> 5100 | L9: =SUM(L14,L19,L24) -> 10000.003 | ... P9: =SUM(P14,P19,P24) -> 290500 | Q9: =SUM(E9:P9) -> 416214.75 | S9: =SUM(S14,S19,S24) -> 11600.003 | T9: =SUM(T14,T19,T24) -> 11600.003 | U9: =SUM(U14,U19,U24) -> 397350 | V9: =SUM(V14,V19,V24) -> 0 | W9: =SUM(W14,W19,W24) -> 0 | X9: =SUM(X14,X19,X24) -> 0 | Y9: =SUM(Y14,Y19,Y24) -> 0 | Z9: =SUM(Z14,Z19,Z24) -> 0 | ... AD9: =SUM(AD14,AD19,AD24) -> 0 | AE9: =SUM(S9:AD9) -> 420550 | AH9: =SUMPRODUCT($S$7:$AD$7,S9:AD9) -> 1.9391358e+10 | AI9: =SUMPRODUCT($S$6:$AD$7,S9:AD9) -> #VALUE! | BH9: Mgmt (Adj)
C10: =IF($C$2="AV",C13,IF($C$2="Mgmt",C11,IF($C$2="Mgmt (Adj)",C12))) -> plan (AV) | Q10: =SUM(E10:P10) -> 0 | V10: =IF($C$2="AV",V13,IF($C$2="Mgmt",V11,IF($C$2="Mgmt (Adj)",V12))) -> 0 | W10: =IF($C$2="AV",W13,IF($C$2="Mgmt",W11,IF($C$2="Mgmt (Adj)",W12))) -> 0 | X10: =IF($C$2="AV",X13,IF($C$2="Mgmt",X11,IF($C$2="Mgmt (Adj)",X12))) -> 0 | Y10: =IF($C$2="AV",Y13,IF($C$2="Mgmt",Y11,IF($C$2="Mgmt (Adj)",Y12))) -> 0 | Z10: =IF($C$2="AV",Z13,IF($C$2="Mgmt",Z11,IF($C$2="Mgmt (Adj)",Z12))) -> 0 | AA10: =IF($C$2="AV",AA13,IF($C$2="Mgmt",AA11,IF($C$2="Mgmt (Adj)",AA12))) -> 0 | AB10: =IF($C$2="AV",AB13,IF($C$2="Mgmt",AB11,IF($C$2="Mgmt (Adj)",AB12))) -> 0 | AC10: =IF($C$2="AV",AC13,IF($C$2="Mgmt",AC11,IF($C$2="Mgmt (Adj)",AC12))) -> 0 | AD10: =IF($C$2="AV",AD13,IF($C$2="Mgmt",AD11,IF($C$2="Mgmt (Adj)",AD12))) -> 0 | AE10: =SUM(S10:AD10) -> 0 | AH10: =SUMPRODUCT($E$6:$AD$6,E10:AD10) -> 0 | AI10: =SUMPRODUCT($E$5:$AD$5,E10:AD10) -> 0 | BH10: Mgmt
C11: plan (Mgmt) | E11: =SUM(E16,E21,E26) -> 0 | F11: =SUM(F16,F21,F26) -> 0 | G11: =SUM(G16,G21,G26) -> 0 | H11: =SUM(H16,H21,H26) -> 0 | I11: =SUM(I16,I21,I26) -> 0 | J11: =SUM(J16,J21,J26) -> 0 | K11: =SUM(K16,K21,K26) -> 0 | L11: =SUM(L16,L21,L26) -> 0 | ... P11: =SUM(P16,P21,P26) -> 0 | Q11: =SUM(E11:P11) -> 0 | S11: =SUM(S16,S21,S26) -> 0 | T11: =SUM(T16,T21,T26) -> 0 | U11: =SUM(U16,U21,U26) -> 0 | V11: =SUM(V16,V21,V26) -> 0 | W11: =SUM(W16,W21,W26) -> 0 | X11: =SUM(X16,X21,X26) -> 0 | Y11: =SUM(Y16,Y21,Y26) -> 0 | Z11: =SUM(Z16,Z21,Z26) -> 0 | ... AD11: =SUM(AD16,AD21,AD26) -> 0 | AE11: =SUM(S11:AD11) -> 0 | AH11: =SUMPRODUCT($E$6:$AD$6,E11:AD11) -> 0 | AI11: =SUMPRODUCT($E$5:$AD$5,E11:AD11) -> 0
C12: plan (Mgmt Adj) | E12: =SUM(E17,E22,E27) -> 0 | F12: =SUM(F17,F22,F27) -> 0 | G12: =SUM(G17,G22,G27) -> 0 | H12: =SUM(H17,H22,H27) -> 0 | I12: =SUM(I17,I22,I27) -> 0 | J12: =SUM(J17,J22,J27) -> 0 | K12: =SUM(K17,K22,K27) -> 0 | L12: =SUM(L17,L22,L27) -> 0 | ... P12: =SUM(P17,P22,P27) -> 0 | Q12: =SUM(E12:P12) -> 0 | S12: =SUM(S17,S22,S27) -> 0 | T12: =SUM(T17,T22,T27) -> 0 | U12: =SUM(U17,U22,U27) -> 0 | V12: =SUM(V17,V22,V27) -> 0 | W12: =SUM(W17,W22,W27) -> 0 | X12: =SUM(X17,X22,X27) -> 0 | Y12: =SUM(Y17,Y22,Y27) -> 0 | Z12: =SUM(Z17,Z22,Z27) -> 0 | ... AD12: =SUM(AD17,AD22,AD27) -> 0 | AE12: =SUM(S12:AD12) -> 0 | AH12: =SUMPRODUCT($E$6:$AD$6,E12:AD12) -> 0 | AI12: =SUMPRODUCT($E$5:$AD$5,E12:AD12) -> 0
C13: plan (AV) | E13: =SUM(E18,E23,E28) -> 0 | F13: =SUM(F18,F23,F28) -> 0 | G13: =SUM(G18,G23,G28) -> 0 | H13: =SUM(H18,H23,H28) -> 0 | I13: =SUM(I18,I23,I28) -> 0 | J13: =SUM(J18,J23,J28) -> 0 | K13: =SUM(K18,K23,K28) -> 0 | L13: =SUM(L18,L23,L28) -> 0 | ... P13: =SUM(P18,P23,P28) -> 0 | Q13: =SUM(E13:P13) -> 0 | S13: =SUM(S18,S23,S28) -> 0 | T13: =SUM(T18,T23,T28) -> 0 | U13: =SUM(U18,U23,U28) -> 0 | V13: =SUM(V18,V23,V28) -> 0 | W13: =SUM(W18,W23,W28) -> 0 | X13: =SUM(X18,X23,X28) -> 0 | Y13: =SUM(Y18,Y23,Y28) -> 0 | Z13: =SUM(Z18,Z23,Z28) -> 0 | ... AD13: =SUM(AD18,AD23,AD28) -> 0 | AE13: =SUM(S13:AD13) -> 0 | AH13: =SUMPRODUCT($E$6:$AD$6,E13:AD13) -> 0 | AI13: =SUMPRODUCT($E$5:$AD$5,E13:AD13) -> 0
B14: PaaS | C14: Actual | E14: ='[2]Detailed FS_$ Cons. (formating)'!BR$7 -> 10800 | F14: ='[2]Detailed FS_$ Cons. (formating)'!BS$7 -> 0 | G14: ='[2]Detailed FS_$ Cons. (formating)'!BT$7 -> 0 | H14: ='[2]Detailed FS_$ Cons. (formating)'!BU7 -> 0 | I14: ='[2]Detailed FS_$ Cons. (formating)'!BV7 -> 0 | J14: ='[2]Detailed FS_$ Cons. (formating)'!BW7 -> 0 | K14: ='[2]Detailed FS_$ Cons. (formating)'!BX7 -> 0 | L14: ='[2]Detailed FS_$ Cons. (formating)'!BY7 -> 0 | M14: ='[2]Detailed FS_$ Cons. (formating)'!BZ7 -> 0 | N14: ='[2]Detailed FS_$ Cons. (formating)'!CA7 -> 17800.003 | O14: ='[2]Detailed FS_$ Cons. (formating)'!CB7 -> 1600 | P14: ='[2]Detailed FS_$ Cons. (formating)'!CC7 -> 300500 | Q14: =SUM(E14:P14) -> 330700 | S14: ='[2]Detailed FS_$ Cons. (formating)'!CF7 -> 1600.0027 | T14: ='[2]Detailed FS_$ Cons. (formating)'!CG7 -> 1600.0027 | U14: ='[2]Detailed FS_$ Cons. (formating)'!CH7 -> 387350 | AE14: =SUM(S14:AD14) -> 390550.01 | AH14: =SUMPRODUCT($E$6:$AD$6,E14:AD14) -> 1600.0027 | AI14: =SUMPRODUCT($E$5:$AD$5,E14:AD14) -> 1600.0027
C15: =IF($C$2="AV",C18,IF($C$2="Mgmt",C16,IF($C$2="Mgmt (Adj)",C17))) -> plan (AV) | E15: =IF($C$2="AV",E18,IF($C$2="Mgmt",E16,IF($C$2="Mgmt (Adj)",E17))) -> 0 | F15: =IF($C$2="AV",F18,IF($C$2="Mgmt",F16,IF($C$2="Mgmt (Adj)",F17))) -> 0 | G15: =IF($C$2="AV",G18,IF($C$2="Mgmt",G16,IF($C$2="Mgmt (Adj)",G17))) -> 0 | H15: =IF($C$2="AV",H18,IF($C$2="Mgmt",H16,IF($C$2="Mgmt (Adj)",H17))) -> 0 | I15: =IF($C$2="AV",I18,IF($C$2="Mgmt",I16,IF($C$2="Mgmt (Adj)",I17))) -> 0 | J15: =IF($C$2="AV",J18,IF($C$2="Mgmt",J16,IF($C$2="Mgmt (Adj)",J17))) -> 0 | K15: =IF($C$2="AV",K18,IF($C$2="Mgmt",K16,IF($C$2="Mgmt (Adj)",K17))) -> 0 | L15: =IF($C$2="AV",L18,IF($C$2="Mgmt",L16,IF($C$2="Mgmt (Adj)",L17))) -> 0 | ... P15: =IF($C$2="AV",P18,IF($C$2="Mgmt",P16,IF($C$2="Mgmt (Adj)",P17))) -> 0 | Q15: =SUM(E15:P15) -> 0 | S15: =IF($C$2="AV",S18,IF($C$2="Mgmt",S16,IF($C$2="Mgmt (Adj)",S17))) -> 0 | T15: =IF($C$2="AV",T18,IF($C$2="Mgmt",T16,IF($C$2="Mgmt (Adj)",T17))) -> 0 | U15: =IF($C$2="AV",U18,IF($C$2="Mgmt",U16,IF($C$2="Mgmt (Adj)",U17))) -> 0 | V15: =IF($C$2="AV",V18,IF($C$2="Mgmt",V16,IF($C$2="Mgmt (Adj)",V17))) -> 0 | W15: =IF($C$2="AV",W18,IF($C$2="Mgmt",W16,IF($C$2="Mgmt (Adj)",W17))) -> 0 | X15: =IF($C$2="AV",X18,IF($C$2="Mgmt",X16,IF($C$2="Mgmt (Adj)",X17))) -> 0 | Y15: =IF($C$2="AV",Y18,IF($C$2="Mgmt",Y16,IF($C$2="Mgmt (Adj)",Y17))) -> 0 | Z15: . | AA15: =IF($C$2="AV",AA18,IF($C$2="Mgmt",AA16,IF($C$2="Mgmt (Adj)",AA17))) -> 0 | AB15: =IF($C$2="AV",AB18,IF($C$2="Mgmt",AB16,IF($C$2="Mgmt (Adj)",AB17))) -> 0 | AC15: =IF($C$2="AV",AC18,IF($C$2="Mgmt",AC16,IF($C$2="Mgmt (Adj)",AC17))) -> 0 | AD15: =IF($C$2="AV",AD18,IF($C$2="Mgmt",AD16,IF($C$2="Mgmt (Adj)",AD17))) -> 0 | AE15: =SUM(S15:AD15) -> 0 | AH15: =SUMPRODUCT($E$6:$AD$6,E15:AD15) -> 0 | AI15: =SUMPRODUCT($E$5:$AD$5,E15:AD15) -> 0
C16: plan (Mgmt) | Q16: =SUM(E16:P16) -> 0 | AE16: =SUM(S16:AD16) -> 0 | AH16: =SUMPRODUCT($E$6:$AD$6,E16:AD16) -> 0 | AI16: =SUMPRODUCT($E$5:$AD$5,E16:AD16) -> 0
C17: plan (Mgmt Adj) | Q17: =SUM(E17:P17) -> 0 | AE17: =SUM(S17:AD17) -> 0 | AH17: =SUMPRODUCT($E$6:$AD$6,E17:AD17) -> 0 | AI17: =SUMPRODUCT($E$5:$AD$5,E17:AD17) -> 0
C18: plan (AV) | Q18: =SUM(E18:P18) -> 0 | AE18: =SUM(S18:AD18) -> 0 | AH18: =SUMPRODUCT($E$6:$AD$6,E18:AD18) -> 0 | AI18: =SUMPRODUCT($E$5:$AD$5,E18:AD18) -> 0
B19: enza conductor | C19: Actual | E19: ='[2]Detailed FS_$ Cons. (formating)'!BR$9 -> 5053.2297 | F19: ='[2]Detailed FS_$ Cons. (formating)'!BS$9 -> 5050.7412 | G19: ='[2]Detailed FS_$ Cons. (formating)'!BT$9 -> 25050.25 | H19: ='[2]Detailed FS_$ Cons. (formating)'!BU$9 -> 5075.6412 | I19: ='[2]Detailed FS_$ Cons. (formating)'!BV$9 -> 5083.0621 | J19: ='[2]Detailed FS_$ Cons. (formating)'!BW$9 -> 5101.8235 | K19: ='[2]Detailed FS_$ Cons. (formating)'!BX$9 -> 5100 | L19: ='[2]Detailed FS_$ Cons. (formating)'!BY$9 -> 10000.003 | ... P19: ='[2]Detailed FS_$ Cons. (formating)'!CC$9 -> -10000.001 | Q19: =SUM(E19:P19) -> 85514.75 | S19: ='[2]Detailed FS_$ Cons. (formating)'!CF$9 -> 10000 | T19: ='[2]Detailed FS_$ Cons. (formating)'!CG$9 -> 10000 | U19: ='[2]Detailed FS_$ Cons. (formating)'!CH$9 -> 9999.9973 | AE19: =SUM(S19:AD19) -> 29999.997 | AH19: =SUMPRODUCT($E$6:$AD$6,E19:AD19) -> 10000 | AI19: =SUMPRODUCT($E$5:$AD$5,E19:AD19) -> 10000
C20: =IF($C$2="AV",C23,IF($C$2="Mgmt",C21,IF($C$2="Mgmt (Adj)",C22))) -> plan (AV) | E20: =IF($C$2="AV",E23,IF($C$2="Mgmt",E21,IF($C$2="Mgmt (Adj)",E22))) -> 0 | F20: =IF($C$2="AV",F23,IF($C$2="Mgmt",F21,IF($C$2="Mgmt (Adj)",F22))) -> 0 | G20: =IF($C$2="AV",G23,IF($C$2="Mgmt",G21,IF($C$2="Mgmt (Adj)",G22))) -> 0 | H20: =IF($C$2="AV",H23,IF($C$2="Mgmt",H21,IF($C$2="Mgmt (Adj)",H22))) -> 0 | I20: =IF($C$2="AV",I23,IF($C$2="Mgmt",I21,IF($C$2="Mgmt (Adj)",I22))) -> 0 | J20: =IF($C$2="AV",J23,IF($C$2="Mgmt",J21,IF($C$2="Mgmt (Adj)",J22))) -> 0 | K20: =IF($C$2="AV",K23,IF($C$2="Mgmt",K21,IF($C$2="Mgmt (Adj)",K22))) -> 0 | L20: =IF($C$2="AV",L23,IF($C$2="Mgmt",L21,IF($C$2="Mgmt (Adj)",L22))) -> 0 | ... P20: =IF($C$2="AV",P23,IF($C$2="Mgmt",P21,IF($C$2="Mgmt (Adj)",P22))) -> 0 | Q20: =SUM(E20:P20) -> 0 | S20: =IF($C$2="AV",S23,IF($C$2="Mgmt",S21,IF($C$2="Mgmt (Adj)",S22))) -> 0 | T20: =IF($C$2="AV",T23,IF($C$2="Mgmt",T21,IF($C$2="Mgmt (Adj)",T22))) -> 0 | U20: =IF($C$2="AV",U23,IF($C$2="Mgmt",U21,IF($C$2="Mgmt (Adj)",U22))) -> 0 | V20: =IF($C$2="AV",V23,IF($C$2="Mgmt",V21,IF($C$2="Mgmt (Adj)",V22))) -> 0 | W20: =IF($C$2="AV",W23,IF($C$2="Mgmt",W21,IF($C$2="Mgmt (Adj)",W22))) -> 0 | X20: =IF($C$2="AV",X23,IF($C$2="Mgmt",X21,IF($C$2="Mgmt (Adj)",X22))) -> 0 | Y20: =IF($C$2="AV",Y23,IF($C$2="Mgmt",Y21,IF($C$2="Mgmt (Adj)",Y22))) -> 0 | Z20: =IF($C$2="AV",Z23,IF($C$2="Mgmt",Z21,IF($C$2="Mgmt (Adj)",Z22))) -> 0 | ... AD20: =IF($C$2="AV",AD23,IF($C$2="Mgmt",AD21,IF($C$2="Mgmt (Adj)",AD22))) -> 0 | AE20: =SUM(S20:AD20) -> 0 | AH20: =SUMPRODUCT($E$6:$AD$6,E20:AD20) -> 0 | AI20: =SUMPRODUCT($E$5:$AD$5,E20:AD20) -> 0
C21: plan (Mgmt) | Q21: =SUM(E21:P21) -> 0 | AE21: =SUM(S21:AD21) -> 0 | AH21: =SUMPRODUCT($E$6:$AD$6,E21:AD21) -> 0 | AI21: =SUMPRODUCT($E$5:$AD$5,E21:AD21) -> 0
C22: plan (Mgmt Adj) | Q22: =SUM(E22:P22) -> 0 | AE22: =SUM(S22:AD22) -> 0 | AH22: =SUMPRODUCT($E$6:$AD$6,E22:AD22) -> 0 | AI22: =SUMPRODUCT($E$5:$AD$5,E22:AD22) -> 0
C23: plan (AV) | Q23: =SUM(E23:P23) -> 0 | AE23: =SUM(S23:AD23) -> 0 | AH23: =SUMPRODUCT($E$6:$AD$6,E23:AD23) -> 0 | AI23: =SUMPRODUCT($E$5:$AD$5,E23:AD23) -> 0
B24: Inperson (acceptance) | C24: Actual | Q24: =SUM(E24:P24) -> 0 | X24: 0 | Y24: 0 | Z24: 0 | AA24: 0 | AB24: 0 | AD24: 0 | AE24: =SUM(S24:AD24) -> 0 | AH24: =SUMPRODUCT($E$6:$AD$6,E24:AD24) -> 0 | AI24: =SUMPRODUCT($E$5:$AD$5,E24:AD24) -> 0
C25: =IF($C$2="AV",C28,IF($C$2="Mgmt",C26,IF($C$2="Mgmt (Adj)",C27))) -> plan (AV) | E25: =IF($C$2="AV",E28,IF($C$2="Mgmt",E26,IF($C$2="Mgmt (Adj)",E27))) -> 0 | F25: =IF($C$2="AV",F28,IF($C$2="Mgmt",F26,IF($C$2="Mgmt (Adj)",F27))) -> 0 | G25: =IF($C$2="AV",G28,IF($C$2="Mgmt",G26,IF($C$2="Mgmt (Adj)",G27))) -> 0 | H25: =IF($C$2="AV",H28,IF($C$2="Mgmt",H26,IF($C$2="Mgmt (Adj)",H27))) -> 0 | I25: =IF($C$2="AV",I28,IF($C$2="Mgmt",I26,IF($C$2="Mgmt (Adj)",I27))) -> 0 | J25: =IF($C$2="AV",J28,IF($C$2="Mgmt",J26,IF($C$2="Mgmt (Adj)",J27))) -> 0 | K25: =IF($C$2="AV",K28,IF($C$2="Mgmt",K26,IF($C$2="Mgmt (Adj)",K27))) -> 0 | L25: =IF($C$2="AV",L28,IF($C$2="Mgmt",L26,IF($C$2="Mgmt (Adj)",L27))) -> 0 | ... P25: =IF($C$2="AV",P28,IF($C$2="Mgmt",P26,IF($C$2="Mgmt (Adj)",P27))) -> 0 | Q25: =SUM(E25:P25) -> 0 | S25: =IF($C$2="AV",S28,IF($C$2="Mgmt",S26,IF($C$2="Mgmt (Adj)",S27))) -> 0 | T25: =IF($C$2="AV",T28,IF($C$2="Mgmt",T26,IF($C$2="Mgmt (Adj)",T27))) -> 0 | U25: =IF($C$2="AV",U28,IF($C$2="Mgmt",U26,IF($C$2="Mgmt (Adj)",U27))) -> 0 | V25: =IF($C$2="AV",V28,IF($C$2="Mgmt",V26,IF($C$2="Mgmt (Adj)",V27))) -> 0 | W25: =IF($C$2="AV",W28,IF($C$2="Mgmt",W26,IF($C$2="Mgmt (Adj)",W27))) -> 0 | X25: =IF($C$2="AV",X28,IF($C$2="Mgmt",X26,IF($C$2="Mgmt (Adj)",X27))) -> 0 | Y25: =IF($C$2="AV",Y28,IF($C$2="Mgmt",Y26,IF($C$2="Mgmt (Adj)",Y27))) -> 0 | Z25: =IF($C$2="AV",Z28,IF($C$2="Mgmt",Z26,IF($C$2="Mgmt (Adj)",Z27))) -> 0 | ... AD25: =IF($C$2="AV",AD28,IF($C$2="Mgmt",AD26,IF($C$2="Mgmt (Adj)",AD27))) -> 0 | AE25: =SUM(S25:AD25) -> 0 | AH25: =SUMPRODUCT($E$6:$AD$6,E25:AD25) -> 0 | AI25: =SUMPRODUCT($E$5:$AD$5,E25:AD25) -> 0
C26: plan (Mgmt) | Q26: =SUM(E26:P26) -> 0 | AE26: =SUM(S26:AD26) -> 0 | AH26: =SUMPRODUCT($E$6:$AD$6,E26:AD26) -> 0 | AI26: =SUMPRODUCT($E$5:$AD$5,E26:AD26) -> 0
C27: plan (Mgmt Adj) | Q27: =SUM(E27:P27) -> 0 | AE27: =SUM(S27:AD27) -> 0 | AH27: =SUMPRODUCT($E$6:$AD$6,E27:AD27) -> 0 | AI27: =SUMPRODUCT($E$5:$AD$5,E27:AD27) -> 0
C28: plan (AV) | Q28: =SUM(E28:P28) -> 0 | AE28: =SUM(S28:AD28) -> 0 | AH28: =SUMPRODUCT($E$6:$AD$6,E28:AD28) -> 0 | AI28: =SUMPRODUCT($E$5:$AD$5,E28:AD28) -> 0
AH29: =SUMPRODUCT($E$6:$AD$6,E29:AD29) -> 0 | AI29: =SUMPRODUCT($E$5:$AD$5,E29:AD29) -> 0
B30: Revenue | C30: Actual | E30: =E35+E40+E45 -> 15853.23 | F30: =F35+F40+F45 -> 5050.7412 | G30: =G35+G40+G45 -> 25050.25 | H30: =H35+H40+H45 -> 5075.6412 | I30: =I35+I40+I45 -> 5083.0621 | J30: =J35+J40+J45 -> 5101.8235 | K30: =K35+K40+K45 -> 5100 | L30: =L35+L40+L45 -> 10000.003 | ... P30: =P35+P40+P45 -> 290500 | Q30: =SUM(E30:P30) -> 416214.75 | S30: =S35+S40+S45 -> 11600.003 | T30: =T35+T40+T45 -> 11600.003 | U30: =U35+U40+U45 -> 397350 | V30: =V35+V40+V45 -> 0 | W30: =W35+W40+W45 -> 0 | X30: =X35+X40+X45 -> 0 | Y30: =Y35+Y40+Y45 -> 0 | Z30: =Z35+Z40+Z45 -> 0 | ... AD30: =AD35+AD40+AD45 -> 0 | AE30: =SUM(S30:AD30) -> 420550 | AH30: =SUMPRODUCT($E$6:$AD$6,E30:AD30) -> 11600.003 | AI30: =SUMPRODUCT($E$5:$AD$5,E30:AD30) -> 11600.003
C31: =IF($C$2="AV",C34,IF($C$2="Mgmt",C32,IF($C$2="Mgmt (Adj)",C33))) -> plan (AV) | E31: =IF($C$2="AV",E34,IF($C$2="Mgmt",E32,IF($C$2="Mgmt (Adj)",E33))) -> 0 | F31: =IF($C$2="AV",F34,IF($C$2="Mgmt",F32,IF($C$2="Mgmt (Adj)",F33))) -> 0 | G31: =IF($C$2="AV",G34,IF($C$2="Mgmt",G32,IF($C$2="Mgmt (Adj)",G33))) -> 0 | H31: =IF($C$2="AV",H34,IF($C$2="Mgmt",H32,IF($C$2="Mgmt (Adj)",H33))) -> 0 | I31: =IF($C$2="AV",I34,IF($C$2="Mgmt",I32,IF($C$2="Mgmt (Adj)",I33))) -> 0 | J31: =IF($C$2="AV",J34,IF($C$2="Mgmt",J32,IF($C$2="Mgmt (Adj)",J33))) -> 0 | K31: =IF($C$2="AV",K34,IF($C$2="Mgmt",K32,IF($C$2="Mgmt (Adj)",K33))) -> 0 | L31: =IF($C$2="AV",L34,IF($C$2="Mgmt",L32,IF($C$2="Mgmt (Adj)",L33))) -> 0 | ... P31: =IF($C$2="AV",P34,IF($C$2="Mgmt",P32,IF($C$2="Mgmt (Adj)",P33))) -> 0 | Q31: =SUM(E31:P31) -> 0 | S31: =IF($C$2="AV",S34,IF($C$2="Mgmt",S32,IF($C$2="Mgmt (Adj)",S33))) -> 0 | T31: =IF($C$2="AV",T34,IF($C$2="Mgmt",T32,IF($C$2="Mgmt (Adj)",T33))) -> 0 | U31: =IF($C$2="AV",U34,IF($C$2="Mgmt",U32,IF($C$2="Mgmt (Adj)",U33))) -> 0 | V31: =IF($C$2="AV",V34,IF($C$2="Mgmt",V32,IF($C$2="Mgmt (Adj)",V33))) -> 0 | W31: =IF($C$2="AV",W34,IF($C$2="Mgmt",W32,IF($C$2="Mgmt (Adj)",W33))) -> 0 | X31: =IF($C$2="AV",X34,IF($C$2="Mgmt",X32,IF($C$2="Mgmt (Adj)",X33))) -> 0 | Y31: =IF($C$2="AV",Y34,IF($C$2="Mgmt",Y32,IF($C$2="Mgmt (Adj)",Y33))) -> 0 | Z31: =IF($C$2="AV",Z34,IF($C$2="Mgmt",Z32,IF($C$2="Mgmt (Adj)",Z33))) -> 0 | ... AD31: =IF($C$2="AV",AD34,IF($C$2="Mgmt",AD32,IF($C$2="Mgmt (Adj)",AD33))) -> 0 | AE31: =SUM(S31:AD31) -> 0 | AH31: =SUMPRODUCT($E$6:$AD$6,E31:AD31) -> 0 | AI31: =SUMPRODUCT($E$5:$AD$5,E31:AD31) -> 0
C32: plan (Mgmt) | E32: =E37+E42+E47 -> 0 | F32: =F37+F42+F47 -> 0 | G32: =G37+G42+G47 -> 0 | H32: =H37+H42+H47 -> 0 | I32: =I37+I42+I47 -> 0 | J32: =J37+J42+J47 -> 0 | K32: =K37+K42+K47 -> 0 | L32: =L37+L42+L47 -> 0 | ... P32: =P37+P42+P47 -> 0 | Q32: =SUM(E32:P32) -> 0 | S32: =S37+S42+S47 -> 0 | T32: =T37+T42+T47 -> 0 | U32: =U37+U42+U47 -> 0 | V32: =V37+V42+V47 -> 0 | W32: =W37+W42+W47 -> 0 | X32: =X37+X42+X47 -> 0 | Y32: =Y37+Y42+Y47 -> 0 | Z32: =Z37+Z42+Z47 -> 0 | ... AD32: =AD37+AD42+AD47 -> 0 | AE32: =SUM(S32:AD32) -> 0 | AH32: =SUMPRODUCT($E$6:$AD$6,E32:AD32) -> 0 | AI32: =SUMPRODUCT($E$5:$AD$5,E32:AD32) -> 0
C33: plan (Mgmt Adj) | E33: =E38+E43+E48 -> 0 | F33: =F38+F43+F48 -> 0 | G33: =G38+G43+G48 -> 0 | H33: =H38+H43+H48 -> 0 | I33: =I38+I43+I48 -> 0 | J33: =J38+J43+J48 -> 0 | K33: =K38+K43+K48 -> 0 | L33: =L38+L43+L48 -> 0 | ... P33: =P38+P43+P48 -> 0 | Q33: =SUM(E33:P33) -> 0 | S33: =S38+S43+S48 -> 0 | T33: =T38+T43+T48 -> 0 | U33: =U38+U43+U48 -> 0 | V33: =V38+V43+V48 -> 0 | W33: =W38+W43+W48 -> 0 | X33: =X38+X43+X48 -> 0 | Y33: =Y38+Y43+Y48 -> 0 | Z33: =Z38+Z43+Z48 -> 0 | ... AD33: =AD38+AD43+AD48 -> 0 | AE33: =SUM(S33:AD33) -> 0 | AH33: =SUMPRODUCT($E$6:$AD$6,E33:AD33) -> 0 | AI33: =SUMPRODUCT($E$5:$AD$5,E33:AD33) -> 0
C34: plan (AV) | E34: =E39+E44+E49 -> 0 | F34: =F39+F44+F49 -> 0 | G34: =G39+G44+G49 -> 0 | H34: =H39+H44+H49 -> 0 | I34: =I39+I44+I49 -> 0 | J34: =J39+J44+J49 -> 0 | K34: =K39+K44+K49 -> 0 | L34: =L39+L44+L49 -> 0 | ... P34: =P39+P44+P49 -> 0 | Q34: =SUM(E34:P34) -> 0 | S34: =S39+S44+S49 -> 0 | T34: =T39+T44+T49 -> 0 | U34: =U39+U44+U49 -> 0 | V34: =V39+V44+V49 -> 0 | W34: =W39+W44+W49 -> 0 | X34: =X39+X44+X49 -> 0 | Y34: =Y39+Y44+Y49 -> 0 | Z34: =Z39+Z44+Z49 -> 0 | ... AD34: =AD39+AD44+AD49 -> 0 | AE34: =SUM(S34:AD34) -> 0 | AH34: =SUMPRODUCT($E$6:$AD$6,E34:AD34) -> 0 | AI34: =SUMPRODUCT($E$5:$AD$5,E34:AD34) -> 0
B35: Revenue Stream 1 | C35: Actual | E35: =E14 -> 10800 | F35: =F14 -> 0 | G35: =G14 -> 0 | H35: =H14 -> 0 | I35: =I14 -> 0 | J35: =J14 -> 0 | K35: =K14 -> 0 | L35: =L14 -> 0 | ... P35: =P14 -> 300500 | Q35: =SUM(E35:P35) -> 330700 | S35: =S14 -> 1600.0027 | T35: =T14 -> 1600.0027 | U35: =U14 -> 387350 | AE35: =SUM(S35:AD35) -> 390550.01 | AH35: =SUMPRODUCT($E$6:$AD$6,E35:AD35) -> 1600.0027 | AI35: =SUMPRODUCT($E$5:$AD$5,E35:AD35) -> 1600.0027
C36: =IF($C$2="AV",C39,IF($C$2="Mgmt",C37,IF($C$2="Mgmt (Adj)",C38))) -> plan (AV) | E36: =IF($C$2="AV",E39,IF($C$2="Mgmt",E37,IF($C$2="Mgmt (Adj)",E38))) -> 0 | F36: =IF($C$2="AV",F39,IF($C$2="Mgmt",F37,IF($C$2="Mgmt (Adj)",F38))) -> 0 | G36: =IF($C$2="AV",G39,IF($C$2="Mgmt",G37,IF($C$2="Mgmt (Adj)",G38))) -> 0 | H36: =IF($C$2="AV",H39,IF($C$2="Mgmt",H37,IF($C$2="Mgmt (Adj)",H38))) -> 0 | I36: =IF($C$2="AV",I39,IF($C$2="Mgmt",I37,IF($C$2="Mgmt (Adj)",I38))) -> 0 | J36: =IF($C$2="AV",J39,IF($C$2="Mgmt",J37,IF($C$2="Mgmt (Adj)",J38))) -> 0 | K36: =IF($C$2="AV",K39,IF($C$2="Mgmt",K37,IF($C$2="Mgmt (Adj)",K38))) -> 0 | L36: =IF($C$2="AV",L39,IF($C$2="Mgmt",L37,IF($C$2="Mgmt (Adj)",L38))) -> 0 | ... P36: =IF($C$2="AV",P39,IF($C$2="Mgmt",P37,IF($C$2="Mgmt (Adj)",P38))) -> 0 | Q36: =SUM(E36:P36) -> 0 | S36: =IF($C$2="AV",S39,IF($C$2="Mgmt",S37,IF($C$2="Mgmt (Adj)",S38))) -> 0 | T36: =IF($C$2="AV",T39,IF($C$2="Mgmt",T37,IF($C$2="Mgmt (Adj)",T38))) -> 0 | U36: =IF($C$2="AV",U39,IF($C$2="Mgmt",U37,IF($C$2="Mgmt (Adj)",U38))) -> 0 | V36: =IF($C$2="AV",V39,IF($C$2="Mgmt",V37,IF($C$2="Mgmt (Adj)",V38))) -> 0 | W36: =IF($C$2="AV",W39,IF($C$2="Mgmt",W37,IF($C$2="Mgmt (Adj)",W38))) -> 0 | X36: =IF($C$2="AV",X39,IF($C$2="Mgmt",X37,IF($C$2="Mgmt (Adj)",X38))) -> 0 | Y36: =IF($C$2="AV",Y39,IF($C$2="Mgmt",Y37,IF($C$2="Mgmt (Adj)",Y38))) -> 0 | Z36: . | AA36: =IF($C$2="AV",AA39,IF($C$2="Mgmt",AA37,IF($C$2="Mgmt (Adj)",AA38))) -> 0 | AB36: =IF($C$2="AV",AB39,IF($C$2="Mgmt",AB37,IF($C$2="Mgmt (Adj)",AB38))) -> 0 | AC36: =IF($C$2="AV",AC39,IF($C$2="Mgmt",AC37,IF($C$2="Mgmt (Adj)",AC38))) -> 0 | AD36: =IF($C$2="AV",AD39,IF($C$2="Mgmt",AD37,IF($C$2="Mgmt (Adj)",AD38))) -> 0 | AE36: =SUM(S36:AD36) -> 0 | AH36: =SUMPRODUCT($E$6:$AD$6,E36:AD36) -> 0 | AI36: =SUMPRODUCT($E$5:$AD$5,E36:AD36) -> 0
C37: plan (Mgmt) | Q37: =SUM(E37:P37) -> 0 | AE37: =SUM(S37:AD37) -> 0 | AH37: =SUMPRODUCT($E$6:$AD$6,E37:AD37) -> 0 | AI37: =SUMPRODUCT($E$5:$AD$5,E37:AD37) -> 0
C38: plan (Mgmt Adj) | Q38: =SUM(E38:P38) -> 0 | AE38: =SUM(S38:AD38) -> 0 | AH38: =SUMPRODUCT($E$6:$AD$6,E38:AD38) -> 0 | AI38: =SUMPRODUCT($E$5:$AD$5,E38:AD38) -> 0
C39: plan (AV) | Q39: =SUM(E39:P39) -> 0 | AE39: =SUM(S39:AD39) -> 0 | AH39: =SUMPRODUCT($E$6:$AD$6,E39:AD39) -> 0 | AI39: =SUMPRODUCT($E$5:$AD$5,E39:AD39) -> 0
B40: Revenue Stream 2 | C40: Actual | E40: =E19 -> 5053.2297 | F40: =F19 -> 5050.7412 | G40: =G19 -> 25050.25 | H40: =H19 -> 5075.6412 | I40: =I19 -> 5083.0621 | J40: =J19 -> 5101.8235 | K40: =K19 -> 5100 | L40: =L19 -> 10000.003 | ... P40: =P19 -> -10000.001 | Q40: =SUM(E40:P40) -> 85514.75 | S40: =S19 -> 10000 | T40: =T19 -> 10000 | U40: =U19 -> 9999.9973 | AE40: =SUM(S40:AD40) -> 29999.997 | AH40: =SUMPRODUCT($E$6:$AD$6,E40:AD40) -> 10000 | AI40: =SUMPRODUCT($E$5:$AD$5,E40:AD40) -> 10000
C41: =IF($C$2="AV",C44,IF($C$2="Mgmt",C42,IF($C$2="Mgmt (Adj)",C43))) -> plan (AV) | E41: =IF($C$2="AV",E44,IF($C$2="Mgmt",E42,IF($C$2="Mgmt (Adj)",E43))) -> 0 | F41: =IF($C$2="AV",F44,IF($C$2="Mgmt",F42,IF($C$2="Mgmt (Adj)",F43))) -> 0 | G41: =IF($C$2="AV",G44,IF($C$2="Mgmt",G42,IF($C$2="Mgmt (Adj)",G43))) -> 0 | H41: =IF($C$2="AV",H44,IF($C$2="Mgmt",H42,IF($C$2="Mgmt (Adj)",H43))) -> 0 | I41: =IF($C$2="AV",I44,IF($C$2="Mgmt",I42,IF($C$2="Mgmt (Adj)",I43))) -> 0 | J41: =IF($C$2="AV",J44,IF($C$2="Mgmt",J42,IF($C$2="Mgmt (Adj)",J43))) -> 0 | K41: =IF($C$2="AV",K44,IF($C$2="Mgmt",K42,IF($C$2="Mgmt (Adj)",K43))) -> 0 | L41: =IF($C$2="AV",L44,IF($C$2="Mgmt",L42,IF($C$2="Mgmt (Adj)",L43))) -> 0 | ... P41: =IF($C$2="AV",P44,IF($C$2="Mgmt",P42,IF($C$2="Mgmt (Adj)",P43))) -> 0 | Q41: =SUM(E41:P41) -> 0 | S41: =IF($C$2="AV",S44,IF($C$2="Mgmt",S42,IF($C$2="Mgmt (Adj)",S43))) -> 0 | T41: =IF($C$2="AV",T44,IF($C$2="Mgmt",T42,IF($C$2="Mgmt (Adj)",T43))) -> 0 | U41: =IF($C$2="AV",U44,IF($C$2="Mgmt",U42,IF($C$2="Mgmt (Adj)",U43))) -> 0 | V41: =IF($C$2="AV",V44,IF($C$2="Mgmt",V42,IF($C$2="Mgmt (Adj)",V43))) -> 0 | W41: =IF($C$2="AV",W44,IF($C$2="Mgmt",W42,IF($C$2="Mgmt (Adj)",W43))) -> 0 | X41: =IF($C$2="AV",X44,IF($C$2="Mgmt",X42,IF($C$2="Mgmt (Adj)",X43))) -> 0 | Y41: =IF($C$2="AV",Y44,IF($C$2="Mgmt",Y42,IF($C$2="Mgmt (Adj)",Y43))) -> 0 | Z41: =IF($C$2="AV",Z44,IF($C$2="Mgmt",Z42,IF($C$2="Mgmt (Adj)",Z43))) -> 0 | ... AD41: =IF($C$2="AV",AD44,IF($C$2="Mgmt",AD42,IF($C$2="Mgmt (Adj)",AD43))) -> 0 | AE41: =SUM(S41:AD41) -> 0 | AH41: =SUMPRODUCT($E$6:$AD$6,E41:AD41) -> 0 | AI41: =SUMPRODUCT($E$5:$AD$5,E41:AD41) -> 0
C42: plan (Mgmt) | Q42: =SUM(E42:P42) -> 0 | AE42: =SUM(S42:AD42) -> 0 | AH42: =SUMPRODUCT($E$6:$AD$6,E42:AD42) -> 0 | AI42: =SUMPRODUCT($E$5:$AD$5,E42:AD42) -> 0
C43: plan (Mgmt Adj) | Q43: =SUM(E43:P43) -> 0 | AE43: =SUM(S43:AD43) -> 0 | AH43: =SUMPRODUCT($E$6:$AD$6,E43:AD43) -> 0 | AI43: =SUMPRODUCT($E$5:$AD$5,E43:AD43) -> 0
C44: plan (AV) | Q44: =SUM(E44:P44) -> 0 | AE44: =SUM(S44:AD44) -> 0 | AH44: =SUMPRODUCT($E$6:$AD$6,E44:AD44) -> 0 | AI44: =SUMPRODUCT($E$5:$AD$5,E44:AD44) -> 0
B45: Revenue Stream 3 | C45: Actual | Q45: =SUM(E45:P45) -> 0 | X45: 0 | Y45: 0 | Z45: 0 | AA45: 0 | AB45: 0 | AD45: 0 | AE45: =SUM(S45:AD45) -> 0 | AH45: =SUMPRODUCT($E$6:$AD$6,E45:AD45) -> 0 | AI45: =SUMPRODUCT($E$5:$AD$5,E45:AD45) -> 0
C46: =IF($C$2="AV",C49,IF($C$2="Mgmt",C47,IF($C$2="Mgmt (Adj)",C48))) -> plan (AV) | E46: =IF($C$2="AV",E49,IF($C$2="Mgmt",E47,IF($C$2="Mgmt (Adj)",E48))) -> 0 | F46: =IF($C$2="AV",F49,IF($C$2="Mgmt",F47,IF($C$2="Mgmt (Adj)",F48))) -> 0 | G46: =IF($C$2="AV",G49,IF($C$2="Mgmt",G47,IF($C$2="Mgmt (Adj)",G48))) -> 0 | H46: =IF($C$2="AV",H49,IF($C$2="Mgmt",H47,IF($C$2="Mgmt (Adj)",H48))) -> 0 | I46: =IF($C$2="AV",I49,IF($C$2="Mgmt",I47,IF($C$2="Mgmt (Adj)",I48))) -> 0 | J46: =IF($C$2="AV",J49,IF($C$2="Mgmt",J47,IF($C$2="Mgmt (Adj)",J48))) -> 0 | K46: =IF($C$2="AV",K49,IF($C$2="Mgmt",K47,IF($C$2="Mgmt (Adj)",K48))) -> 0 | L46: =IF($C$2="AV",L49,IF($C$2="Mgmt",L47,IF($C$2="Mgmt (Adj)",L48))) -> 0 | ... P46: =IF($C$2="AV",P49,IF($C$2="Mgmt",P47,IF($C$2="Mgmt (Adj)",P48))) -> 0 | Q46: =SUM(E46:P46) -> 0 | S46: =IF($C$2="AV",S49,IF($C$2="Mgmt",S47,IF($C$2="Mgmt (Adj)",S48))) -> 0 | T46: =IF($C$2="AV",T49,IF($C$2="Mgmt",T47,IF($C$2="Mgmt (Adj)",T48))) -> 0 | U46: =IF($C$2="AV",U49,IF($C$2="Mgmt",U47,IF($C$2="Mgmt (Adj)",U48))) -> 0 | V46: =IF($C$2="AV",V49,IF($C$2="Mgmt",V47,IF($C$2="Mgmt (Adj)",V48))) -> 0 | W46: =IF($C$2="AV",W49,IF($C$2="Mgmt",W47,IF($C$2="Mgmt (Adj)",W48))) -> 0 | X46: =IF($C$2="AV",X49,IF($C$2="Mgmt",X47,IF($C$2="Mgmt (Adj)",X48))) -> 0 | Y46: =IF($C$2="AV",Y49,IF($C$2="Mgmt",Y47,IF($C$2="Mgmt (Adj)",Y48))) -> 0 | Z46: =IF($C$2="AV",Z49,IF($C$2="Mgmt",Z47,IF($C$2="Mgmt (Adj)",Z48))) -> 0 | ... AD46: =IF($C$2="AV",AD49,IF($C$2="Mgmt",AD47,IF($C$2="Mgmt (Adj)",AD48))) -> 0 | AE46: =SUM(S46:AD46) -> 0 | AH46: =SUMPRODUCT($E$6:$AD$6,E46:AD46) -> 0 | AI46: =SUMPRODUCT($E$5:$AD$5,E46:AD46) -> 0
C47: plan (Mgmt) | Q47: =SUM(E47:P47) -> 0 | AE47: =SUM(S47:AD47) -> 0 | AH47: =SUMPRODUCT($E$6:$AD$6,E47:AD47) -> 0 | AI47: =SUMPRODUCT($E$5:$AD$5,E47:AD47) -> 0
C48: plan (Mgmt Adj) | Q48: =SUM(E48:P48) -> 0 | AE48: =SUM(S48:AD48) -> 0 | AH48: =SUMPRODUCT($E$6:$AD$6,E48:AD48) -> 0 | AI48: =SUMPRODUCT($E$5:$AD$5,E48:AD48) -> 0
C49: plan (AV) | Q49: =SUM(E49:P49) -> 0 | AE49: =SUM(S49:AD49) -> 0 | AH49: =SUMPRODUCT($E$6:$AD$6,E49:AD49) -> 0 | AI49: =SUMPRODUCT($E$5:$AD$5,E49:AD49) -> 0
E50: =E51+'[2]Detailed FS_$ Cons. (formating)'!BR21 -> 0 | F50: =F51+'[2]Detailed FS_$ Cons. (formating)'!BS21 -> 0 | G50: =G51+'[2]Detailed FS_$ Cons. (formating)'!BT21 -> 0 | H50: =H51+'[2]Detailed FS_$ Cons. (formating)'!BU21 -> 0 | I50: =I51+'[2]Detailed FS_$ Cons. (formating)'!BV21 -> 0 | J50: =J51+'[2]Detailed FS_$ Cons. (formating)'!BW21 -> 0 | K50: =K51+'[2]Detailed FS_$ Cons. (formating)'!BX21 -> 0 | L50: =L51+'[2]Detailed FS_$ Cons. (formating)'!BY21 -> 0 | ... O50: =O51+'[2]Detailed FS_$ Cons. (formating)'!CB21 -> 0 | AH50: =SUMPRODUCT($E$6:$AD$6,E50:AD50) -> 0 | AI50: =SUMPRODUCT($E$5:$AD$5,E50:AD50) -> 0
B51: Cost of Revenue | C51: Actual | E51: =E56+E61+E66+E76+E71 -> -9999.8639 | F51: =F56+F61+F66+F76+F71 -> -9999.8639 | G51: =G56+G61+G66+G76+G71 -> -10000 | H51: =H56+H61+H66+H76+H71 -> -10000 | I51: =I56+I61+I66+I76+I71 -> 40000 | J51: =J56+J61+J66+J76+J71 -> 0 | K51: =K56+K61+K66+K76+K71 -> 0 | L51: =L56+L61+L66+L76+L71 -> 0 | ... P51: =P56+P61+P66+P76+P71 -> -3580.5118 | Q51: =SUM(E51:P51) -> -16715.949 | S51: =S56+S61+S66+S76+S71 -> -2187.2012 | T51: =T56+T61+T66+T76+T71 -> -2187.2012 | U51: =U56+U61+U66+U76+U71 -> -2187.2012 | V51: =V56+V61+V66+V76+V71 -> 0 | W51: =W56+W61+W66+W76+W71 -> 0 | X51: =X56+X61+X66+X76+X71 -> 0 | Y51: =Y56+Y61+Y66+Y76+Y71 -> 0 | Z51: =Z56+Z61+Z66+Z76+Z71 -> 0 | ... AD51: =AD56+AD61+AD66+AD76+AD71 -> 0 | AE51: =SUM(S51:AD51) -> -6561.6036 | AH51: =SUMPRODUCT($E$6:$AD$6,E51:AD51) -> -2187.2012 | AI51: =SUMPRODUCT($E$5:$AD$5,E51:AD51) -> -2187.2012
C52: =IF($C$2="AV",C55,IF($C$2="Mgmt",C53,IF($C$2="Mgmt (Adj)",C54))) -> plan (AV) | E52: =IF($C$2="AV",E55,IF($C$2="Mgmt",E53,IF($C$2="Mgmt (Adj)",E54))) -> 0 | F52: =IF($C$2="AV",F55,IF($C$2="Mgmt",F53,IF($C$2="Mgmt (Adj)",F54))) -> 0 | G52: =IF($C$2="AV",G55,IF($C$2="Mgmt",G53,IF($C$2="Mgmt (Adj)",G54))) -> 0 | H52: =IF($C$2="AV",H55,IF($C$2="Mgmt",H53,IF($C$2="Mgmt (Adj)",H54))) -> 0 | I52: =IF($C$2="AV",I55,IF($C$2="Mgmt",I53,IF($C$2="Mgmt (Adj)",I54))) -> 0 | J52: =IF($C$2="AV",J55,IF($C$2="Mgmt",J53,IF($C$2="Mgmt (Adj)",J54))) -> 0 | K52: =IF($C$2="AV",K55,IF($C$2="Mgmt",K53,IF($C$2="Mgmt (Adj)",K54))) -> 0 | L52: =IF($C$2="AV",L55,IF($C$2="Mgmt",L53,IF($C$2="Mgmt (Adj)",L54))) -> 0 | ... P52: =IF($C$2="AV",P55,IF($C$2="Mgmt",P53,IF($C$2="Mgmt (Adj)",P54))) -> 0 | Q52: =SUM(E52:P52) -> 0 | S52: =IF($C$2="AV",S55,IF($C$2="Mgmt",S53,IF($C$2="Mgmt (Adj)",S54))) -> 0 | T52: =IF($C$2="AV",T55,IF($C$2="Mgmt",T53,IF($C$2="Mgmt (Adj)",T54))) -> 0 | U52: =IF($C$2="AV",U55,IF($C$2="Mgmt",U53,IF($C$2="Mgmt (Adj)",U54))) -> 0 | V52: =IF($C$2="AV",V55,IF($C$2="Mgmt",V53,IF($C$2="Mgmt (Adj)",V54))) -> 0 | W52: =IF($C$2="AV",W55,IF($C$2="Mgmt",W53,IF($C$2="Mgmt (Adj)",W54))) -> 0 | X52: =IF($C$2="AV",X55,IF($C$2="Mgmt",X53,IF($C$2="Mgmt (Adj)",X54))) -> 0 | Y52: =IF($C$2="AV",Y55,IF($C$2="Mgmt",Y53,IF($C$2="Mgmt (Adj)",Y54))) -> 0 | Z52: =IF($C$2="AV",Z55,IF($C$2="Mgmt",Z53,IF($C$2="Mgmt (Adj)",Z54))) -> 0 | ... AD52: =IF($C$2="AV",AD55,IF($C$2="Mgmt",AD53,IF($C$2="Mgmt (Adj)",AD54))) -> 0 | AE52: =SUM(S52:AD52) -> 0 | AH52: =SUMPRODUCT($E$6:$AD$6,E52:AD52) -> 0 | AI52: =SUMPRODUCT($E$5:$AD$5,E52:AD52) -> 0
C53: plan (Mgmt) | E53: =E58+E63+E68+E78+E73 -> 0 | F53: =F58+F63+F68+F78+F73 -> 0 | G53: =G58+G63+G68+G78+G73 -> 0 | H53: =H58+H63+H68+H78+H73 -> 0 | I53: =I58+I63+I68+I78+I73 -> 0 | J53: =J58+J63+J68+J78+J73 -> 0 | K53: =K58+K63+K68+K78+K73 -> 0 | L53: =L58+L63+L68+L78+L73 -> 0 | ... P53: =P58+P63+P68+P78+P73 -> 0 | Q53: =SUM(E53:P53) -> 0 | S53: =S58+S63+S68+S78+S73 -> 0 | T53: =T58+T63+T68+T78+T73 -> 0 | U53: =U58+U63+U68+U78+U73 -> 0 | V53: =V58+V63+V68+V78+V73 -> 0 | W53: =W58+W63+W68+W78+W73 -> 0 | X53: =X58+X63+X68+X78+X73 -> 0 | Y53: =Y58+Y63+Y68+Y78+Y73 -> 0 | Z53: =Z58+Z63+Z68+Z78+Z73 -> 0 | ... AD53: =AD58+AD63+AD68+AD78+AD73 -> 0 | AE53: =SUM(S53:AD53) -> 0 | AH53: =SUMPRODUCT($E$6:$AD$6,E53:AD53) -> 0 | AI53: =SUMPRODUCT($E$5:$AD$5,E53:AD53) -> 0
C54: plan (Mgmt Adj) | E54: =E59+E64+E69+E79+E74 -> 0 | F54: =F59+F64+F69+F79+F74 -> 0 | G54: =G59+G64+G69+G79+G74 -> 0 | H54: =H59+H64+H69+H79+H74 -> 0 | I54: =I59+I64+I69+I79+I74 -> 0 | J54: =J59+J64+J69+J79+J74 -> 0 | K54: =K59+K64+K69+K79+K74 -> 0 | L54: =L59+L64+L69+L79+L74 -> 0 | ... P54: =P59+P64+P69+P79+P74 -> 0 | Q54: =SUM(E54:P54) -> 0 | S54: =S59+S64+S69+S79+S74 -> 0 | T54: =T59+T64+T69+T79+T74 -> 0 | U54: =U59+U64+U69+U79+U74 -> 0 | V54: =V59+V64+V69+V79+V74 -> 0 | W54: =W59+W64+W69+W79+W74 -> 0 | X54: =X59+X64+X69+X79+X74 -> 0 | Y54: =Y59+Y64+Y69+Y79+Y74 -> 0 | Z54: =Z59+Z64+Z69+Z79+Z74 -> 0 | ... AD54: =AD59+AD64+AD69+AD79+AD74 -> 0 | AE54: =SUM(S54:AD54) -> 0 | AH54: =SUMPRODUCT($E$6:$AD$6,E54:AD54) -> 0 | AI54: =SUMPRODUCT($E$5:$AD$5,E54:AD54) -> 0
C55: plan (AV) | E55: =E60+E65+E70+E80+E75 -> 0 | F55: =F60+F65+F70+F80+F75 -> 0 | G55: =G60+G65+G70+G80+G75 -> 0 | H55: =H60+H65+H70+H80+H75 -> 0 | I55: =I60+I65+I70+I80+I75 -> 0 | J55: =J60+J65+J70+J80+J75 -> 0 | K55: =K60+K65+K70+K80+K75 -> 0 | L55: =L60+L65+L70+L80+L75 -> 0 | ... P55: =P60+P65+P70+P80+P75 -> 0 | Q55: =SUM(E55:P55) -> 0 | S55: =S60+S65+S70+S80+S75 -> 0 | T55: =T60+T65+T70+T80+T75 -> 0 | U55: =U60+U65+U70+U80+U75 -> 0 | V55: =V60+V65+V70+V80+V75 -> 0 | W55: =W60+W65+W70+W80+W75 -> 0 | X55: =X60+X65+X70+X80+X75 -> 0 | Y55: =Y60+Y65+Y70+Y80+Y75 -> 0 | Z55: =Z60+Z65+Z70+Z80+Z75 -> 0 | ... AD55: =AD60+AD65+AD70+AD80+AD75 -> 0 | AE55: =SUM(S55:AD55) -> 0 | AH55: =SUMPRODUCT($E$6:$AD$6,E55:AD55) -> 0 | AI55: =SUMPRODUCT($E$5:$AD$5,E55:AD55) -> 0
B56: Paas | C56: Actual | N56: ='[2]Detailed FS_$ Cons. (formating)'!CA$15*-1 -> -9936.1448 | O56: ='[2]Detailed FS_$ Cons. (formating)'!CB$15*-1 -> -3199.5644 | P56: ='[2]Detailed FS_$ Cons. (formating)'!CC$15*-1 -> -3580.5118 | Q56: =SUM(E56:P56) -> -16716.221 | S56: ='[2]Detailed FS_$ Cons. (formating)'!CF$15*-1 -> -2187.2012 | T56: ='[2]Detailed FS_$ Cons. (formating)'!CG$15*-1 -> -2187.2012 | U56: ='[2]Detailed FS_$ Cons. (formating)'!CH$15*-1 -> -2187.2012 | AE56: =SUM(S56:AD56) -> -6561.6036 | AH56: =SUMPRODUCT($E$6:$AD$6,E56:AD56) -> -2187.2012 | AI56: =SUMPRODUCT($E$5:$AD$5,E56:AD56) -> -2187.2012
C57: =IF($C$2="AV",C60,IF($C$2="Mgmt",C58,IF($C$2="Mgmt (Adj)",C59))) -> plan (AV) | E57: =IF($C$2="AV",E60,IF($C$2="Mgmt",E58,IF($C$2="Mgmt (Adj)",E59))) -> 0 | F57: =IF($C$2="AV",F60,IF($C$2="Mgmt",F58,IF($C$2="Mgmt (Adj)",F59))) -> 0 | G57: =IF($C$2="AV",G60,IF($C$2="Mgmt",G58,IF($C$2="Mgmt (Adj)",G59))) -> 0 | H57: =IF($C$2="AV",H60,IF($C$2="Mgmt",H58,IF($C$2="Mgmt (Adj)",H59))) -> 0 | I57: =IF($C$2="AV",I60,IF($C$2="Mgmt",I58,IF($C$2="Mgmt (Adj)",I59))) -> 0 | J57: =IF($C$2="AV",J60,IF($C$2="Mgmt",J58,IF($C$2="Mgmt (Adj)",J59))) -> 0 | K57: =IF($C$2="AV",K60,IF($C$2="Mgmt",K58,IF($C$2="Mgmt (Adj)",K59))) -> 0 | L57: =IF($C$2="AV",L60,IF($C$2="Mgmt",L58,IF($C$2="Mgmt (Adj)",L59))) -> 0 | ... P57: =IF($C$2="AV",P60,IF($C$2="Mgmt",P58,IF($C$2="Mgmt (Adj)",P59))) -> 0 | Q57: =SUM(E57:P57) -> 0 | S57: =IF($C$2="AV",S60,IF($C$2="Mgmt",S58,IF($C$2="Mgmt (Adj)",S59))) -> 0 | T57: =IF($C$2="AV",T60,IF($C$2="Mgmt",T58,IF($C$2="Mgmt (Adj)",T59))) -> 0 | U57: =IF($C$2="AV",U60,IF($C$2="Mgmt",U58,IF($C$2="Mgmt (Adj)",U59))) -> 0 | V57: =IF($C$2="AV",V60,IF($C$2="Mgmt",V58,IF($C$2="Mgmt (Adj)",V59))) -> 0 | W57: =IF($C$2="AV",W60,IF($C$2="Mgmt",W58,IF($C$2="Mgmt (Adj)",W59))) -> 0 | X57: =IF($C$2="AV",X60,IF($C$2="Mgmt",X58,IF($C$2="Mgmt (Adj)",X59))) -> 0 | Y57: =IF($C$2="AV",Y60,IF($C$2="Mgmt",Y58,IF($C$2="Mgmt (Adj)",Y59))) -> 0 | Z57: =IF($C$2="AV",Z60,IF($C$2="Mgmt",Z58,IF($C$2="Mgmt (Adj)",Z59))) -> 0 | ... AD57: =IF($C$2="AV",AD60,IF($C$2="Mgmt",AD58,IF($C$2="Mgmt (Adj)",AD59))) -> 0 | AE57: =SUM(S57:AD57) -> 0 | AH57: =SUMPRODUCT($E$6:$AD$6,E57:AD57) -> 0 | AI57: =SUMPRODUCT($E$5:$AD$5,E57:AD57) -> 0
C58: plan (Mgmt) | Q58: =SUM(E58:P58) -> 0 | AE58: =SUM(S58:AD58) -> 0 | AH58: =SUMPRODUCT($E$6:$AD$6,E58:AD58) -> 0 | AI58: =SUMPRODUCT($E$5:$AD$5,E58:AD58) -> 0
C59: plan (Mgmt Adj) | Q59: =SUM(E59:P59) -> 0 | AE59: =SUM(S59:AD59) -> 0 | AH59: =SUMPRODUCT($E$6:$AD$6,E59:AD59) -> 0 | AI59: =SUMPRODUCT($E$5:$AD$5,E59:AD59) -> 0
C60: plan (AV) | Q60: =SUM(E60:P60) -> 0 | AE60: =SUM(S60:AD60) -> 0 | AH60: =SUMPRODUCT($E$6:$AD$6,E60:AD60) -> 0 | AI60: =SUMPRODUCT($E$5:$AD$5,E60:AD60) -> 0
B61: Digial Advertising | C61: Actual | Q61: =SUM(E61:P61) -> 0 | AE61: =SUM(S61:AD61) -> 0 | AH61: =SUMPRODUCT($E$6:$AD$6,E61:AD61) -> 0 | AI61: =SUMPRODUCT($E$5:$AD$5,E61:AD61) -> 0
C62: =IF($C$2="AV",C65,IF($C$2="Mgmt",C63,IF($C$2="Mgmt (Adj)",C64))) -> plan (AV) | E62: =IF($C$2="AV",E65,IF($C$2="Mgmt",E63,IF($C$2="Mgmt (Adj)",E64))) -> 0 | F62: =IF($C$2="AV",F65,IF($C$2="Mgmt",F63,IF($C$2="Mgmt (Adj)",F64))) -> 0 | G62: =IF($C$2="AV",G65,IF($C$2="Mgmt",G63,IF($C$2="Mgmt (Adj)",G64))) -> 0 | H62: =IF($C$2="AV",H65,IF($C$2="Mgmt",H63,IF($C$2="Mgmt (Adj)",H64))) -> 0 | I62: =IF($C$2="AV",I65,IF($C$2="Mgmt",I63,IF($C$2="Mgmt (Adj)",I64))) -> 0 | J62: =IF($C$2="AV",J65,IF($C$2="Mgmt",J63,IF($C$2="Mgmt (Adj)",J64))) -> 0 | K62: =IF($C$2="AV",K65,IF($C$2="Mgmt",K63,IF($C$2="Mgmt (Adj)",K64))) -> 0 | L62: =IF($C$2="AV",L65,IF($C$2="Mgmt",L63,IF($C$2="Mgmt (Adj)",L64))) -> 0 | ... P62: =IF($C$2="AV",P65,IF($C$2="Mgmt",P63,IF($C$2="Mgmt (Adj)",P64))) -> 0 | Q62: =SUM(E62:P62) -> 0 | S62: =IF($C$2="AV",S65,IF($C$2="Mgmt",S63,IF($C$2="Mgmt (Adj)",S64))) -> 0 | T62: =IF($C$2="AV",T65,IF($C$2="Mgmt",T63,IF($C$2="Mgmt (Adj)",T64))) -> 0 | U62: =IF($C$2="AV",U65,IF($C$2="Mgmt",U63,IF($C$2="Mgmt (Adj)",U64))) -> 0 | V62: =IF($C$2="AV",V65,IF($C$2="Mgmt",V63,IF($C$2="Mgmt (Adj)",V64))) -> 0 | W62: =IF($C$2="AV",W65,IF($C$2="Mgmt",W63,IF($C$2="Mgmt (Adj)",W64))) -> 0 | X62: =IF($C$2="AV",X65,IF($C$2="Mgmt",X63,IF($C$2="Mgmt (Adj)",X64))) -> 0 | Y62: =IF($C$2="AV",Y65,IF($C$2="Mgmt",Y63,IF($C$2="Mgmt (Adj)",Y64))) -> 0 | Z62: =IF($C$2="AV",Z65,IF($C$2="Mgmt",Z63,IF($C$2="Mgmt (Adj)",Z64))) -> 0 | ... AD62: =IF($C$2="AV",AD65,IF($C$2="Mgmt",AD63,IF($C$2="Mgmt (Adj)",AD64))) -> 0 | AE62: =SUM(S62:AD62) -> 0 | AH62: =SUMPRODUCT($E$6:$AD$6,E62:AD62) -> 0 | AI62: =SUMPRODUCT($E$5:$AD$5,E62:AD62) -> 0
C63: plan (Mgmt) | Q63: =SUM(E63:P63) -> 0 | AE63: =SUM(S63:AD63) -> 0 | AH63: =SUMPRODUCT($E$6:$AD$6,E63:AD63) -> 0 | AI63: =SUMPRODUCT($E$5:$AD$5,E63:AD63) -> 0
C64: plan (Mgmt Adj) | Q64: =SUM(E64:P64) -> 0 | AE64: =SUM(S64:AD64) -> 0 | AH64: =SUMPRODUCT($E$6:$AD$6,E64:AD64) -> 0 | AI64: =SUMPRODUCT($E$5:$AD$5,E64:AD64) -> 0
C65: plan (AV) | Q65: =SUM(E65:P65) -> 0 | AE65: =SUM(S65:AD65) -> 0 | AH65: =SUMPRODUCT($E$6:$AD$6,E65:AD65) -> 0 | AI65: =SUMPRODUCT($E$5:$AD$5,E65:AD65) -> 0 | AM65: -1
B66: Web Hosting | C66: Actual | Q66: =SUM(E66:P66) -> 0 | AE66: =SUM(S66:AD66) -> 0 | AH66: =SUMPRODUCT($E$6:$AD$6,E66:AD66) -> 0 | AI66: =SUMPRODUCT($E$5:$AD$5,E66:AD66) -> 0
C67: =IF($C$2="AV",C70,IF($C$2="Mgmt",C68,IF($C$2="Mgmt (Adj)",C69))) -> plan (AV) | E67: =IF($C$2="AV",E70,IF($C$2="Mgmt",E68,IF($C$2="Mgmt (Adj)",E69))) -> 0 | F67: =IF($C$2="AV",F70,IF($C$2="Mgmt",F68,IF($C$2="Mgmt (Adj)",F69))) -> 0 | G67: =IF($C$2="AV",G70,IF($C$2="Mgmt",G68,IF($C$2="Mgmt (Adj)",G69))) -> 0 | H67: =IF($C$2="AV",H70,IF($C$2="Mgmt",H68,IF($C$2="Mgmt (Adj)",H69))) -> 0 | I67: =IF($C$2="AV",I70,IF($C$2="Mgmt",I68,IF($C$2="Mgmt (Adj)",I69))) -> 0 | J67: =IF($C$2="AV",J70,IF($C$2="Mgmt",J68,IF($C$2="Mgmt (Adj)",J69))) -> 0 | K67: =IF($C$2="AV",K70,IF($C$2="Mgmt",K68,IF($C$2="Mgmt (Adj)",K69))) -> 0 | L67: =IF($C$2="AV",L70,IF($C$2="Mgmt",L68,IF($C$2="Mgmt (Adj)",L69))) -> 0 | ... P67: =IF($C$2="AV",P70,IF($C$2="Mgmt",P68,IF($C$2="Mgmt (Adj)",P69))) -> 0 | Q67: =SUM(E67:P67) -> 0 | S67: =IF($C$2="AV",S70,IF($C$2="Mgmt",S68,IF($C$2="Mgmt (Adj)",S69))) -> 0 | T67: =IF($C$2="AV",T70,IF($C$2="Mgmt",T68,IF($C$2="Mgmt (Adj)",T69))) -> 0 | U67: =IF($C$2="AV",U70,IF($C$2="Mgmt",U68,IF($C$2="Mgmt (Adj)",U69))) -> 0 | V67: =IF($C$2="AV",V70,IF($C$2="Mgmt",V68,IF($C$2="Mgmt (Adj)",V69))) -> 0 | W67: =IF($C$2="AV",W70,IF($C$2="Mgmt",W68,IF($C$2="Mgmt (Adj)",W69))) -> 0 | X67: =IF($C$2="AV",X70,IF($C$2="Mgmt",X68,IF($C$2="Mgmt (Adj)",X69))) -> 0 | Y67: =IF($C$2="AV",Y70,IF($C$2="Mgmt",Y68,IF($C$2="Mgmt (Adj)",Y69))) -> 0 | Z67: =IF($C$2="AV",Z70,IF($C$2="Mgmt",Z68,IF($C$2="Mgmt (Adj)",Z69))) -> 0 | ... AD67: =IF($C$2="AV",AD70,IF($C$2="Mgmt",AD68,IF($C$2="Mgmt (Adj)",AD69))) -> 0 | AE67: =SUM(S67:AD67) -> 0 | AH67: =SUMPRODUCT($E$6:$AD$6,E67:AD67) -> 0 | AI67: =SUMPRODUCT($E$5:$AD$5,E67:AD67) -> 0
C68: plan (Mgmt) | Q68: =SUM(E68:P68) -> 0 | AE68: =SUM(S68:AD68) -> 0 | AH68: =SUMPRODUCT($E$6:$AD$6,E68:AD68) -> 0 | AI68: =SUMPRODUCT($E$5:$AD$5,E68:AD68) -> 0
C69: plan (Mgmt Adj) | Q69: =SUM(E69:P69) -> 0 | AE69: =SUM(S69:AD69) -> 0 | AH69: =SUMPRODUCT($E$6:$AD$6,E69:AD69) -> 0 | AI69: =SUMPRODUCT($E$5:$AD$5,E69:AD69) -> 0
C70: plan (AV) | Q70: =SUM(E70:P70) -> 0 | AE70: =SUM(S70:AD70) -> 0 | AH70: =SUMPRODUCT($E$6:$AD$6,E70:AD70) -> 0 | AI70: =SUMPRODUCT($E$5:$AD$5,E70:AD70) -> 0 | AM70: -1
B71: enza conductor COS | C71: Actual | E71: ='[2]Detailed FS_$ Cons. (formating)'!BR$17*-1 -> -9999.8639 | F71: ='[2]Detailed FS_$ Cons. (formating)'!BS$17*-1 -> -9999.8639 | G71: ='[2]Detailed FS_$ Cons. (formating)'!BT$17*-1 -> -10000 | H71: ='[2]Detailed FS_$ Cons. (formating)'!BU$17*-1 -> -10000 | I71: ='[2]Detailed FS_$ Cons. (formating)'!BV$17*-1 -> 40000 | J71: ='[2]Detailed FS_$ Cons. (formating)'!BW$17*-1 -> 0 | K71: ='[2]Detailed FS_$ Cons. (formating)'!BX$17*-1 -> 0 | L71: ='[2]Detailed FS_$ Cons. (formating)'!BY$17*-1 -> 0 | ... P71: ='[2]Detailed FS_$ Cons. (formating)'!CC$17*-1 -> 0 | Q71: =SUM(E71:P71) -> 0.27225701 | S71: ='[2]Detailed FS_$ Cons. (formating)'!CF$17*-1 -> 0 | T71: ='[2]Detailed FS_$ Cons. (formating)'!CG$17*-1 -> 0 | U71: ='[2]Detailed FS_$ Cons. (formating)'!CH$17*-1 -> 0 | AE71: =SUM(S71:AD71) -> 0 | AH71: =SUMPRODUCT($E$6:$AD$6,E71:AD71) -> 0 | AI71: =SUMPRODUCT($E$5:$AD$5,E71:AD71) -> 0
C72: =IF($C$2="AV",C75,IF($C$2="Mgmt",C73,IF($C$2="Mgmt (Adj)",C74))) -> plan (AV) | E72: =IF($C$2="AV",E75,IF($C$2="Mgmt",E73,IF($C$2="Mgmt (Adj)",E74))) -> 0 | F72: =IF($C$2="AV",F75,IF($C$2="Mgmt",F73,IF($C$2="Mgmt (Adj)",F74))) -> 0 | G72: =IF($C$2="AV",G75,IF($C$2="Mgmt",G73,IF($C$2="Mgmt (Adj)",G74))) -> 0 | H72: =IF($C$2="AV",H75,IF($C$2="Mgmt",H73,IF($C$2="Mgmt (Adj)",H74))) -> 0 | I72: =IF($C$2="AV",I75,IF($C$2="Mgmt",I73,IF($C$2="Mgmt (Adj)",I74))) -> 0 | J72: =IF($C$2="AV",J75,IF($C$2="Mgmt",J73,IF($C$2="Mgmt (Adj)",J74))) -> 0 | K72: =IF($C$2="AV",K75,IF($C$2="Mgmt",K73,IF($C$2="Mgmt (Adj)",K74))) -> 0 | L72: =IF($C$2="AV",L75,IF($C$2="Mgmt",L73,IF($C$2="Mgmt (Adj)",L74))) -> 0 | ... P72: =IF($C$2="AV",P75,IF($C$2="Mgmt",P73,IF($C$2="Mgmt (Adj)",P74))) -> 0 | Q72: =SUM(E72:P72) -> 0 | S72: =IF($C$2="AV",S75,IF($C$2="Mgmt",S73,IF($C$2="Mgmt (Adj)",S74))) -> 0 | T72: =IF($C$2="AV",T75,IF($C$2="Mgmt",T73,IF($C$2="Mgmt (Adj)",T74))) -> 0 | U72: =IF($C$2="AV",U75,IF($C$2="Mgmt",U73,IF($C$2="Mgmt (Adj)",U74))) -> 0 | V72: =IF($C$2="AV",V75,IF($C$2="Mgmt",V73,IF($C$2="Mgmt (Adj)",V74))) -> 0 | W72: =IF($C$2="AV",W75,IF($C$2="Mgmt",W73,IF($C$2="Mgmt (Adj)",W74))) -> 0 | X72: =IF($C$2="AV",X75,IF($C$2="Mgmt",X73,IF($C$2="Mgmt (Adj)",X74))) -> 0 | Y72: =IF($C$2="AV",Y75,IF($C$2="Mgmt",Y73,IF($C$2="Mgmt (Adj)",Y74))) -> 0 | Z72: =IF($C$2="AV",Z75,IF($C$2="Mgmt",Z73,IF($C$2="Mgmt (Adj)",Z74))) -> 0 | ... AD72: =IF($C$2="AV",AD75,IF($C$2="Mgmt",AD73,IF($C$2="Mgmt (Adj)",AD74))) -> 0 | AE72: =SUM(S72:AD72) -> 0 | AH72: =SUMPRODUCT($E$6:$AD$6,E72:AD72) -> 0 | AI72: =SUMPRODUCT($E$5:$AD$5,E72:AD72) -> 0
C73: plan (Mgmt) | Q73: =SUM(E73:P73) -> 0 | AE73: =SUM(S73:AD73) -> 0 | AH73: =SUMPRODUCT($E$6:$AD$6,E73:AD73) -> 0 | AI73: =SUMPRODUCT($E$5:$AD$5,E73:AD73) -> 0
C74: plan (Mgmt Adj) | Q74: =SUM(E74:P74) -> 0 | AE74: =SUM(S74:AD74) -> 0 | AH74: =SUMPRODUCT($E$6:$AD$6,E74:AD74) -> 0 | AI74: =SUMPRODUCT($E$5:$AD$5,E74:AD74) -> 0
C75: plan (AV) | Q75: =SUM(E75:P75) -> 0 | AE75: =SUM(S75:AD75) -> 0 | AH75: =SUMPRODUCT($E$6:$AD$6,E75:AD75) -> 0 | AI75: =SUMPRODUCT($E$5:$AD$5,E75:AD75) -> 0 | AM75: -1
B76: Inperson (acceptance) | C76: Actual | Q76: =SUM(E76:P76) -> 0 | AE76: =SUM(S76:AD76) -> 0 | AH76: =SUMPRODUCT($E$6:$AD$6,E76:AD76) -> 0 | AI76: =SUMPRODUCT($E$5:$AD$5,E76:AD76) -> 0
C77: =IF($C$2="AV",C80,IF($C$2="Mgmt",C78,IF($C$2="Mgmt (Adj)",C79))) -> plan (AV) | E77: =IF($C$2="AV",E80,IF($C$2="Mgmt",E78,IF($C$2="Mgmt (Adj)",E79))) -> 0 | F77: =IF($C$2="AV",F80,IF($C$2="Mgmt",F78,IF($C$2="Mgmt (Adj)",F79))) -> 0 | G77: =IF($C$2="AV",G80,IF($C$2="Mgmt",G78,IF($C$2="Mgmt (Adj)",G79))) -> 0 | H77: =IF($C$2="AV",H80,IF($C$2="Mgmt",H78,IF($C$2="Mgmt (Adj)",H79))) -> 0 | I77: =IF($C$2="AV",I80,IF($C$2="Mgmt",I78,IF($C$2="Mgmt (Adj)",I79))) -> 0 | J77: =IF($C$2="AV",J80,IF($C$2="Mgmt",J78,IF($C$2="Mgmt (Adj)",J79))) -> 0 | K77: =IF($C$2="AV",K80,IF($C$2="Mgmt",K78,IF($C$2="Mgmt (Adj)",K79))) -> 0 | L77: =IF($C$2="AV",L80,IF($C$2="Mgmt",L78,IF($C$2="Mgmt (Adj)",L79))) -> 0 | ... P77: =IF($C$2="AV",P80,IF($C$2="Mgmt",P78,IF($C$2="Mgmt (Adj)",P79))) -> 0 | Q77: =SUM(E77:P77) -> 0 | S77: =IF($C$2="AV",S80,IF($C$2="Mgmt",S78,IF($C$2="Mgmt (Adj)",S79))) -> 0 | T77: =IF($C$2="AV",T80,IF($C$2="Mgmt",T78,IF($C$2="Mgmt (Adj)",T79))) -> 0 | U77: =IF($C$2="AV",U80,IF($C$2="Mgmt",U78,IF($C$2="Mgmt (Adj)",U79))) -> 0 | V77: =IF($C$2="AV",V80,IF($C$2="Mgmt",V78,IF($C$2="Mgmt (Adj)",V79))) -> 0 | W77: =IF($C$2="AV",W80,IF($C$2="Mgmt",W78,IF($C$2="Mgmt (Adj)",W79))) -> 0 | X77: =IF($C$2="AV",X80,IF($C$2="Mgmt",X78,IF($C$2="Mgmt (Adj)",X79))) -> 0 | Y77: =IF($C$2="AV",Y80,IF($C$2="Mgmt",Y78,IF($C$2="Mgmt (Adj)",Y79))) -> 0 | Z77: =IF($C$2="AV",Z80,IF($C$2="Mgmt",Z78,IF($C$2="Mgmt (Adj)",Z79))) -> 0 | ... AD77: =IF($C$2="AV",AD80,IF($C$2="Mgmt",AD78,IF($C$2="Mgmt (Adj)",AD79))) -> 0 | AE77: =SUM(S77:AD77) -> 0 | AH77: =SUMPRODUCT($E$6:$AD$6,E77:AD77) -> 0 | AI77: =SUMPRODUCT($E$5:$AD$5,E77:AD77) -> 0
C78: plan (Mgmt) | Q78: =SUM(E78:P78) -> 0 | AE78: =SUM(S78:AD78) -> 0 | AH78: =SUMPRODUCT($E$6:$AD$6,E78:AD78) -> 0 | AI78: =SUMPRODUCT($E$5:$AD$5,E78:AD78) -> 0
C79: plan (Mgmt Adj) | Q79: =SUM(E79:P79) -> 0 | AE79: =SUM(S79:AD79) -> 0 | AH79: =SUMPRODUCT($E$6:$AD$6,E79:AD79) -> 0 | AI79: =SUMPRODUCT($E$5:$AD$5,E79:AD79) -> 0
C80: plan (AV) | Q80: =SUM(E80:P80) -> 0 | AE80: =SUM(S80:AD80) -> 0 | AH80: =SUMPRODUCT($E$6:$AD$6,E80:AD80) -> 0 | AI80: =SUMPRODUCT($E$5:$AD$5,E80:AD80) -> 0
AH81: =SUMPRODUCT($E$6:$AD$6,E81:AD81) -> 0 | AI81: =SUMPRODUCT($E$5:$AD$5,E81:AD81) -> 0
B82: Gross Profit | C82: Actual | E82: =E30+E51 -> 5853.3658 | F82: =F30+F51 -> -4949.1226 | G82: =G30+G51 -> 15050.25 | H82: =H30+H51 -> -4924.3588 | I82: =I30+I51 -> 45083.062 | J82: =J30+J51 -> 5101.8235 | K82: =K30+K51 -> 5100 | L82: =L30+L51 -> 10000.003 | ... P82: =P30+P51 -> 286919.49 | Q82: =SUM(E82:P82) -> 399498.8 | S82: =S30+S51 -> 9412.8015 | T82: =T30+T51 -> 9412.8015 | U82: =U30+U51 -> 395162.8 | V82: =V30+V51 -> 0 | W82: =W30+W51 -> 0 | X82: =X30+X51 -> 0 | Y82: =Y30+Y51 -> 0 | Z82: =Z30+Z51 -> 0 | ... AD82: =AD30+AD51 -> 0 | AE82: =SUM(S82:AD82) -> 413988.4 | AH82: =SUMPRODUCT($E$6:$AD$6,E82:AD82) -> 9412.8015 | AI82: =SUMPRODUCT($E$5:$AD$5,E82:AD82) -> 9412.8015
C83: =IF($C$2="AV",C86,IF($C$2="Mgmt",C84,IF($C$2="Mgmt (Adj)",C85))) -> plan (AV) | E83: =IF($C$2="AV",E86,IF($C$2="Mgmt",E84,IF($C$2="Mgmt (Adj)",E85))) -> 0 | F83: =IF($C$2="AV",F86,IF($C$2="Mgmt",F84,IF($C$2="Mgmt (Adj)",F85))) -> 0 | G83: =IF($C$2="AV",G86,IF($C$2="Mgmt",G84,IF($C$2="Mgmt (Adj)",G85))) -> 0 | H83: =IF($C$2="AV",H86,IF($C$2="Mgmt",H84,IF($C$2="Mgmt (Adj)",H85))) -> 0 | I83: =IF($C$2="AV",I86,IF($C$2="Mgmt",I84,IF($C$2="Mgmt (Adj)",I85))) -> 0 | J83: =IF($C$2="AV",J86,IF($C$2="Mgmt",J84,IF($C$2="Mgmt (Adj)",J85))) -> 0 | K83: =IF($C$2="AV",K86,IF($C$2="Mgmt",K84,IF($C$2="Mgmt (Adj)",K85))) -> 0 | L83: =IF($C$2="AV",L86,IF($C$2="Mgmt",L84,IF($C$2="Mgmt (Adj)",L85))) -> 0 | ... P83: =IF($C$2="AV",P86,IF($C$2="Mgmt",P84,IF($C$2="Mgmt (Adj)",P85))) -> 0 | Q83: =SUM(E83:P83) -> 0 | S83: =IF($C$2="AV",S86,IF($C$2="Mgmt",S84,IF($C$2="Mgmt (Adj)",S85))) -> 0 | T83: =IF($C$2="AV",T86,IF($C$2="Mgmt",T84,IF($C$2="Mgmt (Adj)",T85))) -> 0 | U83: =IF($C$2="AV",U86,IF($C$2="Mgmt",U84,IF($C$2="Mgmt (Adj)",U85))) -> 0 | V83: =IF($C$2="AV",V86,IF($C$2="Mgmt",V84,IF($C$2="Mgmt (Adj)",V85))) -> 0 | W83: =IF($C$2="AV",W86,IF($C$2="Mgmt",W84,IF($C$2="Mgmt (Adj)",W85))) -> 0 | X83: =IF($C$2="AV",X86,IF($C$2="Mgmt",X84,IF($C$2="Mgmt (Adj)",X85))) -> 0 | Y83: =IF($C$2="AV",Y86,IF($C$2="Mgmt",Y84,IF($C$2="Mgmt (Adj)",Y85))) -> 0 | Z83: =IF($C$2="AV",Z86,IF($C$2="Mgmt",Z84,IF($C$2="Mgmt (Adj)",Z85))) -> 0 | ... AD83: =IF($C$2="AV",AD86,IF($C$2="Mgmt",AD84,IF($C$2="Mgmt (Adj)",AD85))) -> 0 | AE83: =SUM(S83:AD83) -> 0 | AH83: =SUMPRODUCT($E$6:$AD$6,E83:AD83) -> 0 | AI83: =SUMPRODUCT($E$5:$AD$5,E83:AD83) -> 0
C84: plan (Mgmt) | E84: =E32+E53 -> 0 | F84: =F32+F53 -> 0 | G84: =G32+G53 -> 0 | H84: =H32+H53 -> 0 | I84: =I32+I53 -> 0 | J84: =J32+J53 -> 0 | K84: =K32+K53 -> 0 | L84: =L32+L53 -> 0 | ... P84: =P32+P53 -> 0 | Q84: =SUM(E84:P84) -> 0 | S84: =S32+S53 -> 0 | T84: =T32+T53 -> 0 | U84: =U32+U53 -> 0 | V84: =V32+V53 -> 0 | W84: =W32+W53 -> 0 | X84: =X32+X53 -> 0 | Y84: =Y32+Y53 -> 0 | Z84: =Z32+Z53 -> 0 | ... AD84: =AD32+AD53 -> 0 | AE84: =SUM(S84:AD84) -> 0 | AH84: =SUMPRODUCT($S$6:$AD$6,S84:AD84) -> 0 | AI84: =SUMPRODUCT($S$5:$AD$5,S84:AD84) -> 0
C85: plan (Mgmt Adj) | E85: =E33+E54 -> 0 | F85: =F33+F54 -> 0 | G85: =G33+G54 -> 0 | H85: =H33+H54 -> 0 | I85: =I33+I54 -> 0 | J85: =J33+J54 -> 0 | K85: =K33+K54 -> 0 | L85: =L33+L54 -> 0 | ... P85: =P33+P54 -> 0 | Q85: =SUM(E85:P85) -> 0 | S85: =S33+S54 -> 0 | T85: =T33+T54 -> 0 | U85: =U33+U54 -> 0 | V85: =V33+V54 -> 0 | W85: =W33+W54 -> 0 | X85: =X33+X54 -> 0 | Y85: =Y33+Y54 -> 0 | Z85: =Z33+Z54 -> 0 | ... AD85: =AD33+AD54 -> 0 | AE85: =SUM(S85:AD85) -> 0 | AH85: =SUMPRODUCT($S$6:$AD$6,S85:AD85) -> 0 | AI85: =SUMPRODUCT($S$5:$AD$5,S85:AD85) -> 0
C86: plan (AV) | E86: =E34+E55 -> 0 | F86: =F34+F55 -> 0 | G86: =G34+G55 -> 0 | H86: =H34+H55 -> 0 | I86: =I34+I55 -> 0 | J86: =J34+J55 -> 0 | K86: =K34+K55 -> 0 | L86: =L34+L55 -> 0 | ... P86: =P34+P55 -> 0 | Q86: =SUM(E86:P86) -> 0 | S86: =S34+S55 -> 0 | T86: =T34+T55 -> 0 | U86: =U34+U55 -> 0 | V86: =V34+V55 -> 0 | W86: =W34+W55 -> 0 | X86: =X34+X55 -> 0 | Y86: =Y34+Y55 -> 0 | Z86: =Z34+Z55 -> 0 | ... AD86: =AD34+AD55 -> 0 | AE86: =SUM(S86:AD86) -> 0 | AH86: =SUMPRODUCT($S$6:$AD$6,S86:AD86) -> 0 | AI86: =SUMPRODUCT($S$5:$AD$5,S86:AD86) -> 0
B87: Gross Margin % | E87: =E82/E30 -> 0.36922229 | F87: =F82/F30 -> -0.97988046 | G87: =G82/G30 -> 0.60080239 | H87: =H82/H30 -> -0.97019444 | I87: =I82/I30 -> 8.8692723 | J87: =J82/J30 -> 1 | K87: =K82/K30 -> 1 | L87: =L82/L30 -> 1 | ... Q87: =Q82/Q30 -> 0.95983816 | S87: =S82/S30 -> 0.81144822 | T87: =T82/T30 -> 0.81144822 | U87: =U82/U30 -> 0.99449553 | V87: =V82/V30 -> #DIV/0! | W87: =W82/W30 -> #DIV/0! | X87: =X82/X30 -> #DIV/0! | Y87: =Y82/Y30 -> #DIV/0! | Z87: =Z82/Z30 -> #DIV/0! | ... AE87: =AE82/AE30 -> 0.98439757 | AH87: =AH82/AH30 -> 0.81144822 | AI87: =AI82/AI30 -> 0.81144822
E88: =E89-'[2]Detailed FS_$ Cons. (formating)'!BR112 -> 0 | F88: =F89-'[2]Detailed FS_$ Cons. (formating)'!BS112 -> 0 | G88: =G89-'[2]Detailed FS_$ Cons. (formating)'!BT112 -> 0 | H88: =H89-'[2]Detailed FS_$ Cons. (formating)'!BU112 -> 0 | I88: =I89-'[2]Detailed FS_$ Cons. (formating)'!BV112 -> 0 | J88: =J89-'[2]Detailed FS_$ Cons. (formating)'!BW112 -> 0 | K88: =K89-'[2]Detailed FS_$ Cons. (formating)'!BX112 -> 0 | L88: =L89-'[2]Detailed FS_$ Cons. (formating)'!BY112 -> 0 | ... P88: =P89-'[2]Detailed FS_$ Cons. (formating)'!CC112 -> 0 | S88: =S89-'[2]Detailed FS_$ Cons. (formating)'!CF112 -> 0 | T88: =T89-'[2]Detailed FS_$ Cons. (formating)'!CG112 -> 0 | U88: =U89-'[2]Detailed FS_$ Cons. (formating)'!CH112 -> 0 | AI88: =SUMPRODUCT($S$5:$AD$5,S88:AD88) -> 0
B89: Operating Expenses | C89: Actual | E89: =E94+E99+E104+E114+E109 -> 206049.16 | F89: =F94+F99+F104+F114+F109 -> 249147.01 | G89: =G94+G99+G104+G114+G109 -> 251754.66 | H89: =H94+H99+H104+H114+H109 -> 248064.29 | I89: =I94+I99+I104+I114+I109 -> 337124.99 | J89: =J94+J99+J104+J114+J109 -> 229478.86 | K89: =K94+K99+K104+K114+K109 -> 382120.29 | L89: =L94+L99+L104+L114+L109 -> 258243.76 | ... P89: =P94+P99+P104+P114+P109 -> 318995.24 | Q89: =SUM(E89:P89) -> 3266125.8 | S89: =S94+S99+S104+S114+S109 -> 375896.9 | T89: =T94+T99+T104+T114+T109 -> 355785.83 | U89: =U94+U99+U104+U114+U109 -> 330258.98 | V89: =V94+V99+V104+V114+V109 -> 0 | W89: =W94+W99+W104+W114+W109 -> 0 | X89: =X94+X99+X104+X114+X109 -> 0 | Y89: =Y94+Y99+Y104+Y114+Y109 -> 0 | Z89: =Z94+Z99+Z104+Z114+Z109 -> 0 | ... AD89: =AD94+AD99+AD104+AD114+AD109 -> 0 | AE89: =SUM(S89:AD89) -> 1061941.7 | AH89: =SUMPRODUCT($E$6:$AD$6,E89:AD89) -> 375896.9 | AI89: =SUMPRODUCT($E$5:$AD$5,E89:AD89) -> 375896.9
C90: =IF($C$2="AV",C93,IF($C$2="Mgmt",C91,IF($C$2="Mgmt (Adj)",C92))) -> plan (AV) | E90: =IF($C$2="AV",E93,IF($C$2="Mgmt",E91,IF($C$2="Mgmt (Adj)",E92))) -> 0 | F90: =IF($C$2="AV",F93,IF($C$2="Mgmt",F91,IF($C$2="Mgmt (Adj)",F92))) -> 0 | G90: =IF($C$2="AV",G93,IF($C$2="Mgmt",G91,IF($C$2="Mgmt (Adj)",G92))) -> 0 | H90: =IF($C$2="AV",H93,IF($C$2="Mgmt",H91,IF($C$2="Mgmt (Adj)",H92))) -> 0 | I90: =IF($C$2="AV",I93,IF($C$2="Mgmt",I91,IF($C$2="Mgmt (Adj)",I92))) -> 0 | J90: =IF($C$2="AV",J93,IF($C$2="Mgmt",J91,IF($C$2="Mgmt (Adj)",J92))) -> 0 | K90: =IF($C$2="AV",K93,IF($C$2="Mgmt",K91,IF($C$2="Mgmt (Adj)",K92))) -> 0 | L90: =IF($C$2="AV",L93,IF($C$2="Mgmt",L91,IF($C$2="Mgmt (Adj)",L92))) -> 0 | ... P90: =IF($C$2="AV",P93,IF($C$2="Mgmt",P91,IF($C$2="Mgmt (Adj)",P92))) -> 0 | Q90: =SUM(E90:P90) -> 0 | S90: =IF($C$2="AV",S93,IF($C$2="Mgmt",S91,IF($C$2="Mgmt (Adj)",S92))) -> 0 | T90: =IF($C$2="AV",T93,IF($C$2="Mgmt",T91,IF($C$2="Mgmt (Adj)",T92))) -> 0 | U90: =IF($C$2="AV",U93,IF($C$2="Mgmt",U91,IF($C$2="Mgmt (Adj)",U92))) -> 0 | V90: =IF($C$2="AV",V93,IF($C$2="Mgmt",V91,IF($C$2="Mgmt (Adj)",V92))) -> 0 | W90: =IF($C$2="AV",W93,IF($C$2="Mgmt",W91,IF($C$2="Mgmt (Adj)",W92))) -> 0 | X90: =IF($C$2="AV",X93,IF($C$2="Mgmt",X91,IF($C$2="Mgmt (Adj)",X92))) -> 0 | Y90: =IF($C$2="AV",Y93,IF($C$2="Mgmt",Y91,IF($C$2="Mgmt (Adj)",Y92))) -> 0 | Z90: =IF($C$2="AV",Z93,IF($C$2="Mgmt",Z91,IF($C$2="Mgmt (Adj)",Z92))) -> 0 | ... AD90: =IF($C$2="AV",AD93,IF($C$2="Mgmt",AD91,IF($C$2="Mgmt (Adj)",AD92))) -> 0 | AE90: =SUM(S90:AD90) -> 0 | AH90: =SUMPRODUCT($E$6:$AD$6,E90:AD90) -> 0 | AI90: =SUMPRODUCT($E$5:$AD$5,E90:AD90) -> 0
C91: plan (Mgmt) | E91: =E96+E101+E106+E116 -> 0 | F91: =F96+F101+F106+F116 -> 0 | G91: =G96+G101+G106+G116 -> 0 | H91: =H96+H101+H106+H116 -> 0 | I91: =I96+I101+I106+I116 -> 0 | J91: =J96+J101+J106+J116 -> 0 | K91: =K96+K101+K106+K116 -> 0 | L91: =L96+L101+L106+L116 -> 0 | ... P91: =P96+P101+P106+P116 -> 0 | Q91: =SUM(E91:P91) -> 0 | S91: =S96+S101+S106+S116 -> 0 | T91: =T96+T101+T106+T116 -> 0 | U91: =U96+U101+U106+U116 -> 0 | V91: =V96+V101+V106+V116 -> 0 | W91: =W96+W101+W106+W116 -> 0 | X91: =X96+X101+X106+X116 -> 0 | Y91: =Y96+Y101+Y106+Y116 -> 0 | Z91: =Z96+Z101+Z106+Z116 -> 0 | ... AD91: =AD96+AD101+AD106+AD116 -> 0 | AE91: =SUM(S91:AD91) -> 0 | AH91: =SUMPRODUCT($E$6:$AD$6,E91:AD91) -> 0 | AI91: =SUMPRODUCT($E$5:$AD$5,E91:AD91) -> 0
C92: plan (Mgmt Adj) | E92: =E97+E102+E107+E117 -> 0 | F92: =F97+F102+F107+F117 -> 0 | G92: =G97+G102+G107+G117 -> 0 | H92: =H97+H102+H107+H117 -> 0 | I92: =I97+I102+I107+I117 -> 0 | J92: =J97+J102+J107+J117 -> 0 | K92: =K97+K102+K107+K117 -> 0 | L92: =L97+L102+L107+L117 -> 0 | ... P92: =P97+P102+P107+P117 -> 0 | Q92: =SUM(E92:P92) -> 0 | S92: =S97+S102+S107+S117 -> 0 | T92: =T97+T102+T107+T117 -> 0 | U92: =U97+U102+U107+U117 -> 0 | V92: =V97+V102+V107+V117 -> 0 | W92: =W97+W102+W107+W117 -> 0 | X92: =X97+X102+X107+X117 -> 0 | Y92: =Y97+Y102+Y107+Y117 -> 0 | Z92: =Z97+Z102+Z107+Z117 -> 0 | ... AD92: =AD97+AD102+AD107+AD117 -> 0 | AE92: =SUM(S92:AD92) -> 0 | AH92: =SUMPRODUCT($E$6:$AD$6,E92:AD92) -> 0 | AI92: =SUMPRODUCT($E$5:$AD$5,E92:AD92) -> 0
C93: plan (AV) | E93: =E98+E103+E108+E118 -> 0 | F93: =F98+F103+F108+F118 -> 0 | G93: =G98+G103+G108+G118 -> 0 | H93: =H98+H103+H108+H118 -> 0 | I93: =I98+I103+I108+I118 -> 0 | J93: =J98+J103+J108+J118 -> 0 | K93: =K98+K103+K108+K118 -> 0 | L93: =L98+L103+L108+L118 -> 0 | ... P93: =P98+P103+P108+P118 -> 0 | Q93: =SUM(E93:P93) -> 0 | S93: =S98+S103+S108+S118 -> 0 | T93: =T98+T103+T108+T118 -> 0 | U93: =U98+U103+U108+U118 -> 0 | V93: =V98+V103+V108+V118 -> 0 | W93: =W98+W103+W108+W118 -> 0 | X93: =X98+X103+X108+X118 -> 0 | Y93: =Y98+Y103+Y108+Y118 -> 0 | Z93: =Z98+Z103+Z108+Z118 -> 0 | ... AD93: =AD98+AD103+AD108+AD118 -> 0 | AE93: =SUM(S93:AD93) -> 0 | AH93: =SUMPRODUCT($E$6:$AD$6,E93:AD93) -> 0 | AI93: =SUMPRODUCT($E$5:$AD$5,E93:AD93) -> 0
B94: G&A | C94: Actual | E94: ='[3]P&L breakdown'!D10 -> 150024.3 | F94: ='[3]P&L breakdown'!E10 -> 136851.59 | G94: ='[3]P&L breakdown'!F10 -> 157346.78 | H94: ='[3]P&L breakdown'!G10 -> 164871.87 | I94: ='[3]P&L breakdown'!H10 -> 257134.5 | J94: ='[3]P&L breakdown'!I10 -> 184000.87 | K94: ='[3]P&L breakdown'!J10 -> 327097.72 | L94: ='[3]P&L breakdown'!K10 -> 194164.9 | ... P94: ='[3]P&L breakdown'!O10 -> 247847.85 | Q94: =SUM(E94:P94) -> 2438743.8 | S94: ='[3]P&L breakdown'!R10 -> 246017.42 | T94: ='[3]P&L breakdown'!S10 -> 273355.79 | U94: ='[3]P&L breakdown'!T10 -> 233309.12 | AE94: =SUM(S94:AD94) -> 752682.32 | AH94: =SUMPRODUCT($E$6:$AD$6,E94:AD94) -> 246017.42 | AI94: =SUMPRODUCT($E$5:$AD$5,E94:AD94) -> 246017.42
C95: =IF($C$2="AV",C98,IF($C$2="Mgmt",C96,IF($C$2="Mgmt (Adj)",C97))) -> plan (AV) | E95: =IF($C$2="AV",E98,IF($C$2="Mgmt",E96,IF($C$2="Mgmt (Adj)",E97))) -> 0 | F95: =IF($C$2="AV",F98,IF($C$2="Mgmt",F96,IF($C$2="Mgmt (Adj)",F97))) -> 0 | G95: =IF($C$2="AV",G98,IF($C$2="Mgmt",G96,IF($C$2="Mgmt (Adj)",G97))) -> 0 | H95: =IF($C$2="AV",H98,IF($C$2="Mgmt",H96,IF($C$2="Mgmt (Adj)",H97))) -> 0 | I95: =IF($C$2="AV",I98,IF($C$2="Mgmt",I96,IF($C$2="Mgmt (Adj)",I97))) -> 0 | J95: =IF($C$2="AV",J98,IF($C$2="Mgmt",J96,IF($C$2="Mgmt (Adj)",J97))) -> 0 | K95: =IF($C$2="AV",K98,IF($C$2="Mgmt",K96,IF($C$2="Mgmt (Adj)",K97))) -> 0 | L95: =IF($C$2="AV",L98,IF($C$2="Mgmt",L96,IF($C$2="Mgmt (Adj)",L97))) -> 0 | ... P95: =IF($C$2="AV",P98,IF($C$2="Mgmt",P96,IF($C$2="Mgmt (Adj)",P97))) -> 0 | Q95: =SUM(E95:P95) -> 0 | S95: =IF($C$2="AV",S98,IF($C$2="Mgmt",S96,IF($C$2="Mgmt (Adj)",S97))) -> 0 | T95: =IF($C$2="AV",T98,IF($C$2="Mgmt",T96,IF($C$2="Mgmt (Adj)",T97))) -> 0 | U95: =IF($C$2="AV",U98,IF($C$2="Mgmt",U96,IF($C$2="Mgmt (Adj)",U97))) -> 0 | V95: =IF($C$2="AV",V98,IF($C$2="Mgmt",V96,IF($C$2="Mgmt (Adj)",V97))) -> 0 | W95: =IF($C$2="AV",W98,IF($C$2="Mgmt",W96,IF($C$2="Mgmt (Adj)",W97))) -> 0 | X95: =IF($C$2="AV",X98,IF($C$2="Mgmt",X96,IF($C$2="Mgmt (Adj)",X97))) -> 0 | Y95: =IF($C$2="AV",Y98,IF($C$2="Mgmt",Y96,IF($C$2="Mgmt (Adj)",Y97))) -> 0 | Z95: =IF($C$2="AV",Z98,IF($C$2="Mgmt",Z96,IF($C$2="Mgmt (Adj)",Z97))) -> 0 | ... AD95: =IF($C$2="AV",AD98,IF($C$2="Mgmt",AD96,IF($C$2="Mgmt (Adj)",AD97))) -> 0 | AE95: =SUM(S95:AD95) -> 0 | AH95: =SUMPRODUCT($E$6:$AD$6,E95:AD95) -> 0 | AI95: =SUMPRODUCT($E$5:$AD$5,E95:AD95) -> 0
C96: plan (Mgmt) | Q96: =SUM(E96:P96) -> 0 | AE96: =SUM(S96:AD96) -> 0 | AH96: =SUMPRODUCT($E$6:$AD$6,E96:AD96) -> 0 | AI96: =SUMPRODUCT($E$5:$AD$5,E96:AD96) -> 0
C97: plan (Mgmt Adj) | Q97: =SUM(E97:P97) -> 0 | AE97: =SUM(S97:AD97) -> 0 | AH97: =SUMPRODUCT($E$6:$AD$6,E97:AD97) -> 0 | AI97: =SUMPRODUCT($E$5:$AD$5,E97:AD97) -> 0
C98: plan (AV) | Q98: =SUM(E98:P98) -> 0 | AE98: =SUM(S98:AD98) -> 0 | AH98: =SUMPRODUCT($E$6:$AD$6,E98:AD98) -> 0 | AI98: =SUMPRODUCT($E$5:$AD$5,E98:AD98) -> 0
B99: Technology | C99: Actual | E99: ='[3]P&L breakdown'!D18 -> 30366.502 | F99: ='[3]P&L breakdown'!E18 -> 89856.79 | G99: ='[3]P&L breakdown'!F18 -> 36672.77 | H99: ='[3]P&L breakdown'!G18 -> 45575.965 | I99: ='[3]P&L breakdown'!H18 -> 45643.828 | J99: ='[3]P&L breakdown'!I18 -> 32547.694 | K99: ='[3]P&L breakdown'!J18 -> 37718.894 | L99: ='[3]P&L breakdown'!K18 -> 44210.077 | ... P99: ='[3]P&L breakdown'!O18 -> 53328.029 | Q99: =SUM(E99:P99) -> 539277.06 | S99: ='[3]P&L breakdown'!R18 -> 78813.218 | T99: ='[3]P&L breakdown'!S18 -> 58709.223 | U99: ='[3]P&L breakdown'!T18 -> 85306.728 | AE99: =SUM(S99:AD99) -> 222829.17 | AH99: =SUMPRODUCT($E$6:$AD$6,E99:AD99) -> 78813.218 | AI99: =SUMPRODUCT($E$5:$AD$5,E99:AD99) -> 78813.218
C100: =IF($C$2="AV",C103,IF($C$2="Mgmt",C101,IF($C$2="Mgmt (Adj)",C102))) -> plan (AV) | E100: =IF($C$2="AV",E103,IF($C$2="Mgmt",E101,IF($C$2="Mgmt (Adj)",E102))) -> 0 | F100: =IF($C$2="AV",F103,IF($C$2="Mgmt",F101,IF($C$2="Mgmt (Adj)",F102))) -> 0 | G100: =IF($C$2="AV",G103,IF($C$2="Mgmt",G101,IF($C$2="Mgmt (Adj)",G102))) -> 0 | H100: =IF($C$2="AV",H103,IF($C$2="Mgmt",H101,IF($C$2="Mgmt (Adj)",H102))) -> 0 | I100: =IF($C$2="AV",I103,IF($C$2="Mgmt",I101,IF($C$2="Mgmt (Adj)",I102))) -> 0 | J100: =IF($C$2="AV",J103,IF($C$2="Mgmt",J101,IF($C$2="Mgmt (Adj)",J102))) -> 0 | K100: =IF($C$2="AV",K103,IF($C$2="Mgmt",K101,IF($C$2="Mgmt (Adj)",K102))) -> 0 | L100: =IF($C$2="AV",L103,IF($C$2="Mgmt",L101,IF($C$2="Mgmt (Adj)",L102))) -> 0 | ... P100: =IF($C$2="AV",P103,IF($C$2="Mgmt",P101,IF($C$2="Mgmt (Adj)",P102))) -> 0 | Q100: =SUM(E100:P100) -> 0 | S100: =IF($C$2="AV",S103,IF($C$2="Mgmt",S101,IF($C$2="Mgmt (Adj)",S102))) -> 0 | T100: =IF($C$2="AV",T103,IF($C$2="Mgmt",T101,IF($C$2="Mgmt (Adj)",T102))) -> 0 | U100: =IF($C$2="AV",U103,IF($C$2="Mgmt",U101,IF($C$2="Mgmt (Adj)",U102))) -> 0 | V100: =IF($C$2="AV",V103,IF($C$2="Mgmt",V101,IF($C$2="Mgmt (Adj)",V102))) -> 0 | W100: =IF($C$2="AV",W103,IF($C$2="Mgmt",W101,IF($C$2="Mgmt (Adj)",W102))) -> 0 | X100: =IF($C$2="AV",X103,IF($C$2="Mgmt",X101,IF($C$2="Mgmt (Adj)",X102))) -> 0 | Y100: =IF($C$2="AV",Y103,IF($C$2="Mgmt",Y101,IF($C$2="Mgmt (Adj)",Y102))) -> 0 | Z100: =IF($C$2="AV",Z103,IF($C$2="Mgmt",Z101,IF($C$2="Mgmt (Adj)",Z102))) -> 0 | ... AD100: =IF($C$2="AV",AD103,IF($C$2="Mgmt",AD101,IF($C$2="Mgmt (Adj)",AD102))) -> 0 | AE100: =SUM(S100:AD100) -> 0 | AH100: =SUMPRODUCT($E$6:$AD$6,E100:AD100) -> 0 | AI100: =SUMPRODUCT($E$5:$AD$5,E100:AD100) -> 0
C101: plan (Mgmt) | Q101: =SUM(E101:P101) -> 0 | AE101: =SUM(S101:AD101) -> 0 | AH101: =SUMPRODUCT($E$6:$AD$6,E101:AD101) -> 0 | AI101: =SUMPRODUCT($E$5:$AD$5,E101:AD101) -> 0
...

Sheet Balance Sheet
E1: USD
B2: Balance Sheet | C2: USD | E2: 45627 | G2: ='[3]P&L'!E7 -> 45688 | H2: ='[3]P&L'!F7 -> 45716 | I2: ='[3]P&L'!G7 -> 45747 | J2: ='[3]P&L'!H7 -> 45777 | K2: ='[3]P&L'!I7 -> 45808 | L2: ='[3]P&L'!J7 -> 45838 | M2: ='[3]P&L'!K7 -> 45869 | N2: ='[3]P&L'!L7 -> 45900 | ... R2: ='[3]P&L'!P7 -> 46022 | T2: ='[3]P&L'!S7 -> 46053 | U2: ='[3]P&L'!T7 -> 46081 | V2: ='[3]P&L'!U7 -> 46112 | W2: ='[3]P&L'!V7 -> 46142 | X2: ='[3]P&L'!W7 -> 46173 | Y2: ='[3]P&L'!X7 -> 46203 | Z2: ='[3]P&L'!Y7 -> 46234 | AA2: ='[3]P&L'!Z7 -> 46265 | ... AE2: ='[3]P&L'!AD7 -> 46387
A3: Checker | E3: ='[2]Detailed FS_$ Cons. (formating)'!$BP$188-E4 -> 0 | G3: ='[2]Detailed FS_$ Cons. (formating)'!BR$188-G4 -> 0 | H3: ='[2]Detailed FS_$ Cons. (formating)'!BS$188-H4 -> 0 | I3: ='[2]Detailed FS_$ Cons. (formating)'!BT$188-I4 -> 0 | J3: ='[2]Detailed FS_$ Cons. (formating)'!BU$188-J4 -> 0 | K3: ='[2]Detailed FS_$ Cons. (formating)'!BV$188-K4 -> 0 | L3: ='[2]Detailed FS_$ Cons. (formating)'!BW$188-L4 -> 0 | M3: ='[2]Detailed FS_$ Cons. (formating)'!BX$188-M4 -> 0 | N3: ='[2]Detailed FS_$ Cons. (formating)'!BY$188-N4 -> 0 | ... R3: ='[2]Detailed FS_$ Cons. (formating)'!CC$188-R4 -> 0 | T3: ='[2]Detailed FS_$ Cons. (formating)'!CF$188-T4 -> 0 | U3: ='[2]Detailed FS_$ Cons. (formating)'!CG$188-U4 -> 0 | V3: ='[2]Detailed FS_$ Cons. (formating)'!CH$188-V4 -> 0 | AE3: 12 Months
B4: Assets | C4: Actual | E4: =SUM(E5:E13) -> 887568.4 | G4: =SUM(G5:G13) -> 741101.72 | H4: =SUM(H5:H13) -> 4038449.8 | I4: =SUM(I5:I13) -> 6847077 | J4: =SUM(J5:J13) -> 6592995.8 | K4: =SUM(K5:K13) -> 6266914.8 | L4: =SUM(L5:L13) -> 6049231.6 | M4: =SUM(M5:M13) -> 6739571.5 | N4: =SUM(N5:N13) -> 6333649.8 | ... R4: =SUM(R5:R13) -> 5686209.7 | T4: =SUM(T5:T13) -> 5184093.8 | U4: =SUM(U5:U13) -> 4798490.2 | V4: =SUM(V5:V13) -> 4743704.5 | W4: =W6+SUM(W10:W13) -> 0 | X4: =X6+SUM(X10:X13) -> 0 | Y4: =Y6+SUM(Y10:Y13) -> 0 | Z4: =Z6+SUM(Z10:Z13) -> 0 | AA4: =AA6+SUM(AA10:AA13) -> 0 | AB4: =AB6+SUM(AB10:AB13) -> 0 | AC4: =AC6+SUM(AC10:AC13) -> 0 | AD4: =AD6+SUM(AD10:AD13) -> 0 | AE4: =AE6+SUM(AE10:AE13) -> 0
B5: Fixed Assets | C5: Actual | E5: ='[2]Detailed FS_$ Cons. (formating)'!$BP$172 -> 292255.82 | G5: ='[3]BS breakdown'!D14 -> 303526.35 | H5: ='[3]BS breakdown'!E14 -> 380654.78 | I5: ='[3]BS breakdown'!F14 -> 385328.45 | J5: ='[3]BS breakdown'!G14 -> 379589.75 | K5: ='[3]BS breakdown'!H14 -> 499059.9 | L5: ='[3]BS breakdown'!I14 -> 518647.1 | M5: ='[3]BS breakdown'!J14 -> 1783518.3 | N5: ='[3]BS breakdown'!K14 -> 1760098.4 | ... R5: ='[3]BS breakdown'!O14 -> 2070950.3 | T5: ='[3]BS breakdown'!Q14 -> 2099951 | U5: ='[3]BS breakdown'!R14 -> 2058243.3 | V5: ='[3]BS breakdown'!S14 -> 1868794.7
B6: Cash | C6: Actual | E6: ='[2]Detailed FS_$ Cons. (formating)'!$BP$174+'[2]Detailed FS_$ Cons. (formating)'!$BP$177+'[2]Detailed FS_$ Cons. (formating)'!$BP$175 -> 506664.22 | G6: ='[2]Detailed FS_$ Cons. (formating)'!BR$174+'[2]Detailed FS_$ Cons. (formating)'!BR$176+'[2]Detailed FS_$ Cons. (formating)'!BR$177+'[2]Detailed FS_$ Cons. (formating)'!BR$175 -> 297295.28 | H6: ='[2]Detailed FS_$ Cons. (formating)'!BS$174+'[2]Detailed FS_$ Cons. (formating)'!BS$176+'[2]Detailed FS_$ Cons. (formating)'!BS$177+'[2]Detailed FS_$ Cons. (formating)'!BS$175 -> 3496368.1 | I6: ='[2]Detailed FS_$ Cons. (formating)'!BT$174+'[2]Detailed FS_$ Cons. (formating)'!BT$176+'[2]Detailed FS_$ Cons. (formating)'!BT$177+'[2]Detailed FS_$ Cons. (formating)'!BT$175 -> 6273141.9 | J6: ='[2]Detailed FS_$ Cons. (formating)'!BU$174+'[2]Detailed FS_$ Cons. (formating)'!BU$176+'[2]Detailed FS_$ Cons. (formating)'!BU$177+'[2]Detailed FS_$ Cons. (formating)'!BU$175 -> 5795831.3 | K6: ='[2]Detailed FS_$ Cons. (formating)'!BV$174+'[2]Detailed FS_$ Cons. (formating)'!BV$176+'[2]Detailed FS_$ Cons. (formating)'!BV$177+'[2]Detailed FS_$ Cons. (formating)'!BV$175 -> 5294020.1 | L6: ='[2]Detailed FS_$ Cons. (formating)'!BW$174+'[2]Detailed FS_$ Cons. (formating)'!BW$176+'[2]Detailed FS_$ Cons. (formating)'!BW$177+'[2]Detailed FS_$ Cons. (formating)'!BW$175 -> 5033527.6 | M6: ='[2]Detailed FS_$ Cons. (formating)'!BX$174+'[2]Detailed FS_$ Cons. (formating)'!BX$176+'[2]Detailed FS_$ Cons. (formating)'!BX$177+'[2]Detailed FS_$ Cons. (formating)'!BX$175 -> 4447724.2 | N6: ='[2]Detailed FS_$ Cons. (formating)'!BY$174+'[2]Detailed FS_$ Cons. (formating)'!BY$176+'[2]Detailed FS_$ Cons. (formating)'!BY$177+'[2]Detailed FS_$ Cons. (formating)'!BY$175 -> 4147955.3 | ... R6: ='[2]Detailed FS_$ Cons. (formating)'!CC$174+'[2]Detailed FS_$ Cons. (formating)'!CC$176+'[2]Detailed FS_$ Cons. (formating)'!CC$177+'[2]Detailed FS_$ Cons. (formating)'!CC$175 -> 3123512 | T6: ='[2]Detailed FS_$ Cons. (formating)'!CF$174+'[2]Detailed FS_$ Cons. (formating)'!CF$176+'[2]Detailed FS_$ Cons. (formating)'!CF$177+'[2]Detailed FS_$ Cons. (formating)'!CF$175 -> 2596045.7 | U6: ='[2]Detailed FS_$ Cons. (formating)'!CG$174+'[2]Detailed FS_$ Cons. (formating)'!CG$176+'[2]Detailed FS_$ Cons. (formating)'!CG$177+'[2]Detailed FS_$ Cons. (formating)'!CG$175 -> 2210632.7 | V6: ='[2]Detailed FS_$ Cons. (formating)'!CH$174+'[2]Detailed FS_$ Cons. (formating)'!CH$176+'[2]Detailed FS_$ Cons. (formating)'!CH$177+'[2]Detailed FS_$ Cons. (formating)'!CH$175 -> 1929247.4
C7: plan (Mgmt)
C8: plan (Mgmt Adj)
C9: plan (AV)
B10: Receivables | C10: Actual | E10: ='[2]Detailed FS_$ Cons. (formating)'!$BP$178 -> 42763.016 | G10: ='[2]Detailed FS_$ Cons. (formating)'!BR$178 -> 58637.47 | H10: ='[2]Detailed FS_$ Cons. (formating)'!BS$178 -> 91091.643 | I10: ='[2]Detailed FS_$ Cons. (formating)'!BT$178 -> 78002.464 | J10: ='[2]Detailed FS_$ Cons. (formating)'!BU$178 -> 83079.769 | K10: ='[2]Detailed FS_$ Cons. (formating)'!BV$178 -> 88115.821 | L10: ='[2]Detailed FS_$ Cons. (formating)'!BW$178 -> 93226.055 | M10: ='[2]Detailed FS_$ Cons. (formating)'!BX$178 -> 25667.125 | N10: ='[2]Detailed FS_$ Cons. (formating)'!BY$178 -> 35674.716 | ... R10: ='[2]Detailed FS_$ Cons. (formating)'!CC$178 -> 214271.28 | T10: ='[2]Detailed FS_$ Cons. (formating)'!CF$178 -> 152470.53 | U10: ='[2]Detailed FS_$ Cons. (formating)'!CG$178 -> 123308.15 | V10: ='[2]Detailed FS_$ Cons. (formating)'!CH$178 -> 565606.03
B11: Inventory | C11: Actual | E11: ='[2]Detailed FS_$ Cons. (formating)'!$BP$179 -> 0 | G11: ='[2]Detailed FS_$ Cons. (formating)'!BR$179 -> 0 | H11: ='[2]Detailed FS_$ Cons. (formating)'!BS$179 -> 0 | I11: ='[2]Detailed FS_$ Cons. (formating)'!BT$179 -> 0 | J11: ='[2]Detailed FS_$ Cons. (formating)'!BU$179 -> 0 | K11: ='[2]Detailed FS_$ Cons. (formating)'!BV$179 -> 0 | L11: ='[2]Detailed FS_$ Cons. (formating)'!BW$179 -> 0 | M11: ='[2]Detailed FS_$ Cons. (formating)'!BX$179 -> 0 | N11: ='[2]Detailed FS_$ Cons. (formating)'!BY$179 -> 0 | ... R11: ='[2]Detailed FS_$ Cons. (formating)'!CC$179 -> 0 | T11: ='[2]Detailed FS_$ Cons. (formating)'!CF$179 -> 0 | U11: ='[2]Detailed FS_$ Cons. (formating)'!CG$179 -> 0 | V11: ='[2]Detailed FS_$ Cons. (formating)'!CH$179 -> 0
B12: Prepaid Expenses | C12: Actual | E12: ='[2]Detailed FS_$ Cons. (formating)'!$BP$181 -> 27863.813 | G12: ='[3]BS breakdown'!D24 -> 60758.357 | H12: ='[3]BS breakdown'!E24 -> 47826.265 | I12: ='[3]BS breakdown'!F24 -> 33752.716 | J12: ='[3]BS breakdown'!G24 -> 55587.752 | K12: ='[3]BS breakdown'!H24 -> 101282.58 | L12: ='[3]BS breakdown'!I24 -> 116927.06 | M12: ='[3]BS breakdown'!J24 -> 189011.03 | N12: ='[3]BS breakdown'!K24 -> 92484.866 | ... R12: ='[3]BS breakdown'!O24 -> 85929.038 | T12: ='[3]BS breakdown'!Q24 -> 145299.66 | U12: ='[3]BS breakdown'!R24 -> 131963.73 | V12: ='[3]BS breakdown'!S24 -> 144526.8
B13: Other Assets | C13: Actual | E13: ='[2]Detailed FS_$ Cons. (formating)'!$BP$180+'[2]Detailed FS_$ Cons. (formating)'!$BP$182+'[2]Detailed FS_$ Cons. (formating)'!$BP$184+'[2]Detailed FS_$ Cons. (formating)'!$BP$183 -> 18021.527 | G13: ='[3]BS breakdown'!D32 -> 20884.26 | H13: ='[3]BS breakdown'!E32 -> 22509.012 | I13: ='[3]BS breakdown'!F32 -> 76851.518 | J13: ='[3]BS breakdown'!G32 -> 278907.25 | K13: ='[3]BS breakdown'!H32 -> 284436.43 | L13: ='[3]BS breakdown'!I32 -> 286903.83 | M13: ='[3]BS breakdown'!J32 -> 293650.88 | N13: ='[3]BS breakdown'!K32 -> 297436.52 | ... R13: ='[3]BS breakdown'!O32 -> 191547.03 | T13: ='[3]BS breakdown'!Q32 -> 190326.92 | U13: ='[3]BS breakdown'!R32 -> 274342.32 | V13: ='[3]BS breakdown'!S32 -> 235529.63
A14: Checker | E14: ='[2]Detailed FS_$ Cons. (formating)'!$BP$194+'[2]Detailed FS_$ Cons. (formating)'!$BP$201-E15 -> 0 | G14: =('[2]Detailed FS_$ Cons. (formating)'!BR$194+'[2]Detailed FS_$ Cons. (formating)'!BR$201)-G15 -> 0 | H14: =('[2]Detailed FS_$ Cons. (formating)'!BS$194+'[2]Detailed FS_$ Cons. (formating)'!BS$201)-H15 -> 0 | I14: =('[2]Detailed FS_$ Cons. (formating)'!BT$194+'[2]Detailed FS_$ Cons. (formating)'!BT$201)-I15 -> 0 | J14: =('[2]Detailed FS_$ Cons. (formating)'!BU$194+'[2]Detailed FS_$ Cons. (formating)'!BU$201)-J15 -> 0 | K14: =('[2]Detailed FS_$ Cons. (formating)'!BV$194+'[2]Detailed FS_$ Cons. (formating)'!BV$201)-K15 -> 0 | L14: =('[2]Detailed FS_$ Cons. (formating)'!BW$194+'[2]Detailed FS_$ Cons. (formating)'!BW$201)-L15 -> 0 | M14: =('[2]Detailed FS_$ Cons. (formating)'!BX$194+'[2]Detailed FS_$ Cons. (formating)'!BX$201)-M15 -> 0 | N14: =('[2]Detailed FS_$ Cons. (formating)'!BY$194+'[2]Detailed FS_$ Cons. (formating)'!BY$201)-N15 -> 0 | ... R14: =('[2]Detailed FS_$ Cons. (formating)'!CC$194+'[2]Detailed FS_$ Cons. (formating)'!CC$201)-R15 -> 0 | T14: =('[2]Detailed FS_$ Cons. (formating)'!CF$194+'[2]Detailed FS_$ Cons. (formating)'!CF$201)-T15 -> 0 | U14: =('[2]Detailed FS_$ Cons. (formating)'!CG$194+'[2]Detailed FS_$ Cons. (formating)'!CG$201)-U15 -> 0 | V14: =('[2]Detailed FS_$ Cons. (formating)'!CH$194+'[2]Detailed FS_$ Cons. (formating)'!CH$201)-V15 -> 0
B15: Liabilities | C15: Actual | E15: =E16+SUM(E22:E23) -> 227734.05 | G15: =G16+SUM(G22:G23) -> 285834.87 | H15: =H16+SUM(H22:H23) -> 470790.17 | I15: =I16+SUM(I22:I23) -> 147176.02 | J15: =J16+SUM(J22:J23) -> 154781.86 | K15: =K16+SUM(K22:K23) -> 121216.15 | L15: =L16+SUM(L22:L23) -> 133381.11 | M15: =M16+SUM(M22:M23) -> 1216847.2 | N15: =N16+SUM(N22:N23) -> 1092191 | ... R15: =R16+SUM(R22:R23) -> 1247263.5 | T15: =T16+SUM(T22:T23) -> 1149132 | U15: =U16+SUM(U22:U23) -> 1163902.8 | V15: =V16+SUM(V22:V23) -> 1188475.2 | W15: =W16+SUM(W22:W23) -> 0 | X15: =X16+SUM(X22:X23) -> 0 | Y15: =Y16+SUM(Y22:Y23) -> 0 | Z15: =Z16+SUM(Z22:Z23) -> 0 | AA15: =AA16+SUM(AA22:AA23) -> 0 | ... AE15: =AE16+SUM(AE22:AE23) -> 0
B16: Payables & Accruals | C16: Actual | E16: =SUM(E17:E21) -> 179687.05 | G16: =SUM(G17:G21) -> 236758.46 | H16: =SUM(H17:H21) -> 440345.5 | I16: =SUM(I17:I21) -> 122800.42 | J16: =SUM(J17:J21) -> 130117.42 | K16: =SUM(K17:K21) -> 88912.979 | L16: =SUM(L17:L21) -> 100550.81 | M16: =SUM(M17:M21) -> 92500.462 | N16: =SUM(N17:N21) -> 5127.4464 | ... R16: =SUM(R17:R21) -> 209234.47 | T16: =SUM(T17:T21) -> 162239.43 | U16: =SUM(U17:U21) -> 173995.13 | V16: =SUM(V17:V21) -> 303666.7 | W16: =SUM(W17:W21) -> 0 | X16: =SUM(X17:X21) -> 0 | Y16: =SUM(Y17:Y21) -> 0 | Z16: =SUM(Z17:Z21) -> 0 | AA16: =SUM(AA17:AA21) -> 0 | ... AE16: =SUM(AE17:AE21) -> 0
B17: Employees Payable | C17: Actual
B18: Government Payable | C18: Actual | E18: ='[2]Detailed FS_$ Cons. (formating)'!$BO$197 -> 2244.9835 | G18: ='[3]BS breakdown'!D46 -> 519.31848 | H18: ='[3]BS breakdown'!E46 -> 531.98532 | I18: ='[3]BS breakdown'!F46 -> 1146.548 | J18: ='[3]BS breakdown'!G46 -> 637.93315 | K18: ='[3]BS breakdown'!H46 -> 759.25743 | L18: ='[3]BS breakdown'!I46 -> 999.33513 | M18: ='[3]BS breakdown'!J46 -> 153.04997 | N18: ='[3]BS breakdown'!K46 -> 414.21757 | ... R18: ='[3]BS breakdown'!O46 -> 8828.6184 | T18: ='[3]BS breakdown'!Q46 -> 3709.5141 | U18: ='[3]BS breakdown'!R46 -> 3904.6711 | V18: ='[3]BS breakdown'!S46 -> 5799.3091
B19: Suppliers Payable | C19: Actual | E19: ='[2]Detailed FS_$ Cons. (formating)'!$BO$196 -> 177442.07 | G19: ='[2]Detailed FS_$ Cons. (formating)'!BR$196 -> 236239.14 | H19: ='[2]Detailed FS_$ Cons. (formating)'!BS$196 -> 439813.52 | I19: ='[2]Detailed FS_$ Cons. (formating)'!BT$196 -> 121653.87 | J19: ='[2]Detailed FS_$ Cons. (formating)'!BU$196 -> 129479.48 | K19: ='[2]Detailed FS_$ Cons. (formating)'!BV$196 -> 88153.721 | L19: ='[2]Detailed FS_$ Cons. (formating)'!BW$196 -> 99551.477 | M19: ='[2]Detailed FS_$ Cons. (formating)'!BX$196 -> 92347.412 | N19: ='[2]Detailed FS_$ Cons. (formating)'!BY$196 -> 4713.2288 | ... R19: ='[2]Detailed FS_$ Cons. (formating)'!CC$196 -> 200405.85 | T19: ='[2]Detailed FS_$ Cons. (formating)'!CF$196 -> 158529.92 | U19: ='[2]Detailed FS_$ Cons. (formating)'!CG$196 -> 170090.46 | V19: ='[2]Detailed FS_$ Cons. (formating)'!CH$196 -> 243867.39
B20: Customer Payable | C20: Actual
B21: Other Payable | C21: Actual | V21: ='[2]Detailed FS_$ Cons. (formating)'!$CH$200 -> 54000
B22: Lease Liability / Non current lia. | C22: Actual | E22: ='[2]Detailed FS_$ Cons. (formating)'!$BP$191+'[2]Detailed FS_$ Cons. (formating)'!$BO$192 -> 46864.955 | G22: ='[2]Detailed FS_$ Cons. (formating)'!BR$191 -> 41346.414 | H22: ='[2]Detailed FS_$ Cons. (formating)'!BS$191 -> 41566.108 | I22: ='[2]Detailed FS_$ Cons. (formating)'!BT$191 -> 35739.445 | J22: ='[2]Detailed FS_$ Cons. (formating)'!BU$191 -> 36079.359 | K22: ='[2]Detailed FS_$ Cons. (formating)'!BV$191 -> 37359.409 | L22: ='[2]Detailed FS_$ Cons. (formating)'!BW$191 -> 37978.668 | M22: ='[2]Detailed FS_$ Cons. (formating)'!BX$191 -> 1129370.3 | N22: ='[2]Detailed FS_$ Cons. (formating)'!BY$191 -> 1092186.5 | ... R22: ='[2]Detailed FS_$ Cons. (formating)'!CC$191 -> 1020736.2 | T22: ='[2]Detailed FS_$ Cons. (formating)'!CF$191 -> 969956.06 | U22: ='[2]Detailed FS_$ Cons. (formating)'!CG$191 -> 973022.11 | V22: ='[2]Detailed FS_$ Cons. (formating)'!CH$191 -> 869721.86
B23: Other Current Liabilities | C23: Actual | E23: ='[2]Detailed FS_$ Cons. (formating)'!$BP$199+'[2]Detailed FS_$ Cons. (formating)'!$BP$198+'[2]Detailed FS_$ Cons. (formating)'!$BP$193 -> 1182.0435 | G23: ='[3]BS breakdown'!D55 -> 7729.9921 | H23: ='[3]BS breakdown'!E55 -> -11121.437 | I23: ='[3]BS breakdown'!F55 -> -11363.839 | J23: ='[3]BS breakdown'!G55 -> -11414.91 | K23: ='[3]BS breakdown'!H55 -> -5056.2354 | L23: ='[3]BS breakdown'!I55 -> -5148.3701 | M23: ='[3]BS breakdown'!J55 -> -5023.5946 | N23: ='[3]BS breakdown'!K55 -> -5122.9869 | ... R23: ='[3]BS breakdown'!O55 -> 17292.839 | T23: ='[3]BS breakdown'!Q55 -> 16936.519 | U23: ='[3]BS breakdown'!R55 -> 16885.54 | V23: ='[3]BS breakdown'!S55 -> 15086.629
A24: Checker | E24: ='[2]Detailed FS_$ Cons. (formating)'!$BP$210-E25 -> 0 | G24: ='[2]Detailed FS_$ Cons. (formating)'!BR$210-G25 -> 0 | H24: ='[2]Detailed FS_$ Cons. (formating)'!BS$210-H25 -> 0 | I24: ='[2]Detailed FS_$ Cons. (formating)'!BT$210-I25 -> 0 | J24: ='[2]Detailed FS_$ Cons. (formating)'!BU$210-J25 -> 0 | K24: ='[2]Detailed FS_$ Cons. (formating)'!BV$210-K25 -> 0 | L24: ='[2]Detailed FS_$ Cons. (formating)'!BW$210-L25 -> 0 | M24: ='[2]Detailed FS_$ Cons. (formating)'!BX$210-M25 -> 0 | N24: ='[2]Detailed FS_$ Cons. (formating)'!BY$210-N25 -> 0 | ... R24: ='[2]Detailed FS_$ Cons. (formating)'!CC$210-R25 -> 0 | T24: ='[2]Detailed FS_$ Cons. (formating)'!CF$210-T25 -> 0 | U24: ='[2]Detailed FS_$ Cons. (formating)'!CG$210-U25 -> 0 | V24: ='[2]Detailed FS_$ Cons. (formating)'!CH$210-V25 -> 0
B25: Owners Equity | C25: Actual | E25: =E27+E28+E26 -> 659834.34 | G25: =G27+G28+G26 -> 455266.85 | H25: =H27+H28+H26 -> 3567659.6 | I25: =I27+I28+I26 -> 6699901 | J25: =J27+J28+J26 -> 6438213.9 | K25: =K27+K28+K26 -> 6145698.7 | L25: =L27+L28+L26 -> 5915850.5 | M25: =M27+M28+M26 -> 5522724.3 | N25: =N27+N28+N26 -> 5241458.8 | ... R25: =R27+R28+R26 -> 4438946.2 | T25: =T27+T28+T26 -> 4034961.8 | U25: =U27+U28+U26 -> 3634587.4 | V25: =V27+V28+V26 -> 3555229.3
B26: Translation Adj. | E26: ='[2]Detailed FS_$ Cons. (formating)'!$BP$209 -> 68240.513 | G26: ='[2]Detailed FS_$ Cons. (formating)'!BR$209 -> 71595.066 | H26: ='[2]Detailed FS_$ Cons. (formating)'!BS$209 -> 67938.805 | I26: ='[2]Detailed FS_$ Cons. (formating)'!BT$209 -> 68138.573 | J26: ='[2]Detailed FS_$ Cons. (formating)'!BU$209 -> 66639.431 | K26: ='[2]Detailed FS_$ Cons. (formating)'!BV$209 -> 73252.096 | L26: ='[2]Detailed FS_$ Cons. (formating)'!BW$209 -> 75978.478 | M26: ='[2]Detailed FS_$ Cons. (formating)'!BX$209 -> 83149.946 | N26: ='[2]Detailed FS_$ Cons. (formating)'!BY$209 -> 59068.703 | ... R26: ='[2]Detailed FS_$ Cons. (formating)'!CC$209 -> 68098.651 | T26: ='[2]Detailed FS_$ Cons. (formating)'!CF$209 -> 67605.507 | U26: ='[2]Detailed FS_$ Cons. (formating)'!CG$209 -> 54569.865 | V26: ='[2]Detailed FS_$ Cons. (formating)'!CH$209 -> -43305.909
B27: Earnings | C27: Actual | E27: ='[2]Detailed FS_$ Cons. (formating)'!$BP$206 -> -1823199.6 | G27: ='[2]Detailed FS_$ Cons. (formating)'!BR$206 -> -2031121.7 | H27: ='[2]Detailed FS_$ Cons. (formating)'!BS$206 -> -2290072.6 | I27: ='[2]Detailed FS_$ Cons. (formating)'!BT$206 -> -2533031 | J27: ='[2]Detailed FS_$ Cons. (formating)'!BU$206 -> -2793219 | K27: ='[2]Detailed FS_$ Cons. (formating)'!BV$206 -> -3092147.5 | L27: ='[2]Detailed FS_$ Cons. (formating)'!BW$206 -> -3324722.1 | M27: ='[2]Detailed FS_$ Cons. (formating)'!BX$206 -> -3725019.7 | N27: ='[2]Detailed FS_$ Cons. (formating)'!BY$206 -> -3982204 | ... R27: ='[2]Detailed FS_$ Cons. (formating)'!CC$206 -> -4910173.2 | T27: ='[2]Detailed FS_$ Cons. (formating)'!CF$206 -> -5313664.5 | U27: ='[2]Detailed FS_$ Cons. (formating)'!CG$206 -> -5701003.2 | V27: ='[2]Detailed FS_$ Cons. (formating)'!CH$206 -> -5682485.5
B28: Capital | C28: Actual | E28: ='[2]Detailed FS_$ Cons. (formating)'!$BP$203 -> 2414793.5 | G28: ='[2]Detailed FS_$ Cons. (formating)'!BR$203 -> 2414793.5 | H28: ='[2]Detailed FS_$ Cons. (formating)'!BS$203 -> 5789793.5 | I28: ='[2]Detailed FS_$ Cons. (formating)'!BT$203 -> 9164793.5 | J28: ='[2]Detailed FS_$ Cons. (formating)'!BU$203 -> 9164793.5 | K28: ='[2]Detailed FS_$ Cons. (formating)'!BV$203 -> 9164594.1 | L28: ='[2]Detailed FS_$ Cons. (formating)'!BW$203+'[2]Detailed FS_$ Cons. (formating)'!BW$204+'[2]Detailed FS_$ Cons. (formating)'!BW$205 -> 9164594.1 | M28: ='[2]Detailed FS_$ Cons. (formating)'!BX$203+'[2]Detailed FS_$ Cons. (formating)'!BX$204+'[2]Detailed FS_$ Cons. (formating)'!BX$205 -> 9164594.1 | N28: ='[2]Detailed FS_$ Cons. (formating)'!BY$203+'[2]Detailed FS_$ Cons. (formating)'!BY$204+'[2]Detailed FS_$ Cons. (formating)'!BY$205 -> 9164594.1 | O28: ='[2]Detailed FS_$ Cons. (formating)'!BZ$203+'[2]Detailed FS_$ Cons. (formating)'!BZ$204+'[2]Detailed FS_$ Cons. (formating)'!BZ$205 -> 9281020.7 | P28: ='[2]Detailed FS_$ Cons. (formating)'!CA$203+'[2]Detailed FS_$ Cons. (formating)'!CA$204+'[2]Detailed FS_$ Cons. (formating)'!CA$205 -> 9281519.8 | Q28: ='[2]Detailed FS_$ Cons. (formating)'!CB$203+'[2]Detailed FS_$ Cons. (formating)'!CB$204+'[2]Detailed FS_$ Cons. (formating)'!CB$205 -> 9281020.7 | R28: ='[2]Detailed FS_$ Cons. (formating)'!CC$203+'[2]Detailed FS_$ Cons. (formating)'!CC$204+'[2]Detailed FS_$ Cons. (formating)'!CC$205 -> 9281020.7 | T28: ='[2]Detailed FS_$ Cons. (formating)'!CF$203+'[2]Detailed FS_$ Cons. (formating)'!CF$204+'[2]Detailed FS_$ Cons. (formating)'!CF$205 -> 9281020.7 | U28: ='[2]Detailed FS_$ Cons. (formating)'!CG$203+'[2]Detailed FS_$ Cons. (formating)'!CG$204+'[2]Detailed FS_$ Cons. (formating)'!CG$205 -> 9281020.7 | V28: ='[2]Detailed FS_$ Cons. (formating)'!CH$203+'[2]Detailed FS_$ Cons. (formating)'!CH$204+'[2]Detailed FS_$ Cons. (formating)'!CH$205 -> 9281020.7
B30: Reconciliation | E30: =E4-E15-E25 -> 0 | G30: =G4-G15-G25 -> 0 | H30: =H4-H15-H25 -> 0 | I30: =I4-I15-I25 -> 0 | J30: =J4-J15-J25 -> 0 | K30: =K4-K15-K25 -> 0 | L30: =L4-L15-L25 -> 0 | M30: =M4-M15-M25 -> 0 | N30: =N4-N15-N25 -> 0 | ... R30: =R4-R15-R25 -> 0 | T30: =T4-T15-T25 -> 0 | U30: =U4-U15-U25 -> 0 | V30: =V4-V15-V25 -> 0

Sheet CFS
A2: Cash flow | C2: 45688 | D2: 45716 | E2: 45747 | F2: 45777 | G2: 45808 | H2: 45838 | I2: 45869 | J2: 45900 | K2: 45930 | L2: 45961 | M2: 45991 | N2: 46022 | P2: 46053 | Q2: =EOMONTH(P2,1) -> 46081 | R2: =EOMONTH(Q2,1) -> 46112 | S2: =EOMONTH(R2,1) -> 46142 | T2: =EOMONTH(S2,1) -> 46173 | U2: =EOMONTH(T2,1) -> 46203 | V2: =EOMONTH(U2,1) -> 46234 | W2: =EOMONTH(V2,1) -> 46265 | X2: =EOMONTH(W2,1) -> 46295 | ... AA2: =EOMONTH(Z2,1) -> 46387
A3: EBITDA | C3: ='P&L'!E120 -> -200195.8 | D3: ='P&L'!F120 -> -254096.13 | E3: ='P&L'!G120 -> -236704.41 | F3: ='P&L'!H120 -> -252988.65 | G3: ='P&L'!I120 -> -292041.93 | H3: ='P&L'!J120 -> -224377.04 | I3: ='P&L'!K120 -> -377020.29 | J3: ='P&L'!L120 -> -248243.75 | ... N3: ='P&L'!P120 -> -32075.749 | P3: ='P&L'!S120 -> -366484.09 | Q3: ='P&L'!T120 -> -346373.03 | R3: ='P&L'!U120 -> 64903.82
A4: IFRS 16 impact | C4: =-'P&L'!E128 -> -569.27048 | D4: =-'P&L'!F128 -> -564.52276 | E4: =-'P&L'!G128 -> -565.38536 | F4: =-'P&L'!H128 -> -496.84339 | G4: =-'P&L'!I128 -> -507.48231 | H4: =-'P&L'!J128 -> -508.98031 | I4: =-'P&L'!K128 -> -446.77482 | J4: =-'P&L'!L128 -> 9531.1106 | ... N4: =-'P&L'!P128 -> -22389.327 | P4: =-'P&L'!S128 -> -15450.71 | Q4: =-'P&L'!T128 -> -15256.524 | R4: =-'P&L'!U128 -> -19358.999
A5: Tax paid | N5: =-'P&L'!P134 -> -12309.288 | P5: =-'P&L'!S134 -> 0
A6: Non Cash | C6: =-'P&L'!E129 -> -3115.8304 | D6: =-'P&L'!F129 -> 175.41584 | E6: =-'P&L'!G129 -> -75.994986 | F6: =-'P&L'!H129 -> -939.50123 | G6: =-'P&L'!I129 -> -899.89842 | H6: =-'P&L'!J129 -> -1946.4667 | I6: =-'P&L'!K129 -> 1045.9487 | J6: =-'P&L'!L129 -> 33.202888 | ... N6: =-'P&L'!P129 -> -33434.331 | P6: =-'P&L'!S129 -> 2658.0957 | Q6: =-'P&L'!T129 -> 3128.455 | R6: =-'P&L'!U129 -> -5.4962889
A7: Other income & Gain on sale | C7: =-'P&L'!E127 -> 211.75355 | D7: =-'P&L'!F127 -> 64.226178 | E7: =-'P&L'!G127 -> -80.191851 | F7: =-'P&L'!H127 -> -232.86536 | G7: =-'P&L'!I127 -> 152.4943 | H7: =-'P&L'!J127 -> -24.462678 | I7: =-'P&L'!K127 -> 194.27339 | J7: =-'P&L'!L127 -> 20424.817 | ... N7: =-'P&L'!P127 -> 11414.269 | P7: =-'P&L'!S127 -> 4729.0445 | Q7: =-'P&L'!T127 -> 919.77754 | R7: =-'P&L'!U127 -> 653.18417
A8: WC Movements | C8: =-('Balance Sheet'!G10-'Balance Sheet'!E10)-('Balance Sheet'!G11-'Balance Sheet'!E11)-('Balance Sheet'!G12-'Balance Sheet'!E12)-('Balance Sheet'!G13-'Balance Sheet'!E13)+('Balance Sheet'!G16-'Balance Sheet'!E16) -> 5439.6793 | D8: =-('Balance Sheet'!H10-'Balance Sheet'!G10)-('Balance Sheet'!H11-'Balance Sheet'!G11)-('Balance Sheet'!H12-'Balance Sheet'!G12)-('Balance Sheet'!H13-'Balance Sheet'!G13)+('Balance Sheet'!H16-'Balance Sheet'!G16) -> 182440.21 | E8: =-('Balance Sheet'!I10-'Balance Sheet'!H10)-('Balance Sheet'!I11-'Balance Sheet'!H11)-('Balance Sheet'!I12-'Balance Sheet'!H12)-('Balance Sheet'!I13-'Balance Sheet'!H13)+('Balance Sheet'!I16-'Balance Sheet'!H16) -> -344724.86 | F8: =-('Balance Sheet'!J10-'Balance Sheet'!I10)-('Balance Sheet'!J11-'Balance Sheet'!I11)-('Balance Sheet'!J12-'Balance Sheet'!I12)-('Balance Sheet'!J13-'Balance Sheet'!I13)+('Balance Sheet'!J16-'Balance Sheet'!I16) -> -221651.08 | G8: =-('Balance Sheet'!K10-'Balance Sheet'!J10)-('Balance Sheet'!K11-'Balance Sheet'!J11)-('Balance Sheet'!K12-'Balance Sheet'!J12)-('Balance Sheet'!K13-'Balance Sheet'!J13)+('Balance Sheet'!K16-'Balance Sheet'!J16) -> -97464.497 | H8: =-('Balance Sheet'!L10-'Balance Sheet'!K10)-('Balance Sheet'!L11-'Balance Sheet'!K11)-('Balance Sheet'!L12-'Balance Sheet'!K12)-('Balance Sheet'!L13-'Balance Sheet'!K13)+('Balance Sheet'!L16-'Balance Sheet'!K16) -> -11584.268 | I8: =-('Balance Sheet'!M10-'Balance Sheet'!L10)-('Balance Sheet'!M11-'Balance Sheet'!L11)-('Balance Sheet'!M12-'Balance Sheet'!L12)-('Balance Sheet'!M13-'Balance Sheet'!L13)+('Balance Sheet'!M16-'Balance Sheet'!L16) -> -19322.445 | J8: =-('Balance Sheet'!N10-'Balance Sheet'!M10)-('Balance Sheet'!N11-'Balance Sheet'!M11)-('Balance Sheet'!N12-'Balance Sheet'!M12)-('Balance Sheet'!N13-'Balance Sheet'!M13)+('Balance Sheet'!N16-'Balance Sheet'!M16) -> -4640.0833 | K8: =-('Balance Sheet'!O10-'Balance Sheet'!N10)-('Balance Sheet'!O11-'Balance Sheet'!N11)-('Balance Sheet'!O12-'Balance Sheet'!N12)-('Balance Sheet'!O13-'Balance Sheet'!N13)+('Balance Sheet'!O16-'Balance Sheet'!N16) -> 93766.461 | ... N8: =-('Balance Sheet'!R10-'Balance Sheet'!Q10)-('Balance Sheet'!R11-'Balance Sheet'!Q11)-('Balance Sheet'!R12-'Balance Sheet'!Q12)-('Balance Sheet'!R13-'Balance Sheet'!Q13)+('Balance Sheet'!R16-'Balance Sheet'!Q16) -> -68914.207 | P8: =-('Balance Sheet'!T10-'Balance Sheet'!R10)-('Balance Sheet'!T11-'Balance Sheet'!R11)-('Balance Sheet'!T12-'Balance Sheet'!R12)-('Balance Sheet'!T13-'Balance Sheet'!R13)+('Balance Sheet'!T16-'Balance Sheet'!R16) -> -43344.795 | Q8: =-('Balance Sheet'!U10-'Balance Sheet'!T10)-('Balance Sheet'!U11-'Balance Sheet'!T11)-('Balance Sheet'!U12-'Balance Sheet'!T12)-('Balance Sheet'!U13-'Balance Sheet'!T13)+('Balance Sheet'!U16-'Balance Sheet'!T16) -> -29761.4 | R8: =-('Balance Sheet'!V10-'Balance Sheet'!U10)-('Balance Sheet'!V11-'Balance Sheet'!U11)-('Balance Sheet'!V12-'Balance Sheet'!U12)-('Balance Sheet'!V13-'Balance Sheet'!U13)+('Balance Sheet'!V16-'Balance Sheet'!U16) -> -286376.68
A9: Interest paid
A10: Cash Generated from (Used in) Operation Activity | C10: =SUM(C3:C9) -> -198229.46 | D10: =SUM(D3:D9) -> -71980.803 | E10: =SUM(E3:E9) -> -582150.85 | F10: =SUM(F3:F9) -> -476308.94 | G10: =SUM(G3:G9) -> -390761.31 | H10: =SUM(H3:H9) -> -238441.22 | I10: =SUM(I3:I9) -> -395549.29 | J10: =SUM(J3:J9) -> -222894.71 | ... N10: =SUM(N3:N9) -> -157708.63 | P10: =SUM(P3:P9) -> -417892.46 | Q10: =SUM(Q3:Q9) -> -387342.72 | R10: =SUM(R3:R9) -> -240184.17
A12: Capex - Excl. ROU/POS Lease | C12: =-('Balance Sheet'!G5-'Balance Sheet'!E5)-'P&L'!E130 -> -15523.438 | D12: =-('Balance Sheet'!H5-'Balance Sheet'!G5)-'P&L'!F130 -> -81658.377 | E12: =-('Balance Sheet'!I5-'Balance Sheet'!H5)-'P&L'!G130 -> -10206.075 | F12: =-('Balance Sheet'!J5-'Balance Sheet'!I5)-'P&L'!H130 -> 208.62396 | G12: =-('Balance Sheet'!K5-'Balance Sheet'!J5)-'P&L'!I130 -> -125101.84 | H12: =-('Balance Sheet'!L5-'Balance Sheet'!K5)-'P&L'!J130 -> -25304.832 | I12: =-('Balance Sheet'!M5-'Balance Sheet'!L5)-'P&L'!K130 -> -1288942 | J12: =-('Balance Sheet'!N5-'Balance Sheet'!M5)-'P&L'!L130 -> -15509.795 | K12: =-('Balance Sheet'!O5-'Balance Sheet'!N5)-'P&L'!M130 -> -140037.47 | ... N12: =-('Balance Sheet'!R5-'Balance Sheet'!Q5)-'P&L'!P130 -> -129570.88 | P12: =-('Balance Sheet'!T5-'Balance Sheet'!R5)-'P&L'!S130 -> -57944.291 | Q12: =-('Balance Sheet'!U5-'Balance Sheet'!T5)-'P&L'!T130 -> 11950.266 | R12: =-('Balance Sheet'!V5-'Balance Sheet'!U5)-'P&L'!U130 -> 161773.84
A13: CAPEX - ROU
A14: CAPEX - Leased POSs
A15: Cash Generated from (Used in) Investing Activity | C15: =SUM(C12:C14) -> -15523.438 | D15: =SUM(D12:D14) -> -81658.377 | E15: =SUM(E12:E14) -> -10206.075 | F15: =SUM(F12:F14) -> 208.62396 | G15: =SUM(G12:G14) -> -125101.84 | H15: =SUM(H12:H14) -> -25304.832 | I15: =SUM(I12:I14) -> -1288942 | J15: =SUM(J12:J14) -> -15509.795 | ... N15: =SUM(N12:N14) -> -129570.88 | P15: =SUM(P12:P14) -> -57944.291 | Q15: =SUM(Q12:Q14) -> 11950.266 | R15: =SUM(R12:R14) -> 161773.84
A17: Lease Liability | C17: ='Balance Sheet'!G22-'Balance Sheet'!E22 -> -5518.5403 | D17: ='Balance Sheet'!H22-'Balance Sheet'!G22 -> 219.69357 | E17: ='Balance Sheet'!I22-'Balance Sheet'!H22 -> -5826.6623 | F17: ='Balance Sheet'!J22-'Balance Sheet'!I22 -> 339.91336 | G17: ='Balance Sheet'!K22-'Balance Sheet'!J22 -> 1280.0506 | H17: ='Balance Sheet'!L22-'Balance Sheet'!K22 -> 619.25873 | I17: ='Balance Sheet'!M22-'Balance Sheet'!L22 -> 1091391.7 | J17: ='Balance Sheet'!N22-'Balance Sheet'!M22 -> -37183.796 | K17: ='Balance Sheet'!O22-'Balance Sheet'!N22 -> 16238.897 | ... N17: ='Balance Sheet'!R22-'Balance Sheet'!Q22 -> 18018.277 | P17: ='Balance Sheet'!T22-'Balance Sheet'!R22 -> -50780.128 | Q17: ='Balance Sheet'!U22-'Balance Sheet'!T22 -> 3066.0415 | R17: ='Balance Sheet'!V22-'Balance Sheet'!U22 -> -103300.24
A18: Loans
A19: Long-Term Loans
A20: Capital injection | C20: ='Balance Sheet'!G28-'Balance Sheet'!E28 -> 0 | D20: ='Balance Sheet'!H28-'Balance Sheet'!G28 -> 3375000 | E20: ='Balance Sheet'!I28-'Balance Sheet'!H28 -> 3375000 | F20: ='Balance Sheet'!J28-'Balance Sheet'!I28 -> 0 | G20: ='Balance Sheet'!K28-'Balance Sheet'!J28 -> -199.41033 | H20: ='Balance Sheet'!L28-'Balance Sheet'!K28 -> 0 | I20: ='Balance Sheet'!M28-'Balance Sheet'!L28 -> 0 | J20: ='Balance Sheet'!N28-'Balance Sheet'!M28 -> 0 | K20: ='Balance Sheet'!O28-'Balance Sheet'!N28 -> 116426.67 | ... N20: ='Balance Sheet'!R28-'Balance Sheet'!Q28 -> 0 | P20: ='Balance Sheet'!T28-'Balance Sheet'!R28 -> 0 | Q20: ='Balance Sheet'!U28-'Balance Sheet'!T28 -> 0 | R20: ='Balance Sheet'!V28-'Balance Sheet'!U28 -> 0
A21: Others | C21: ='Balance Sheet'!G26-'Balance Sheet'!E26+'Balance Sheet'!G23-'Balance Sheet'!E23 -> 9902.5014 | D21: ='Balance Sheet'!H26-'Balance Sheet'!G26+'Balance Sheet'!H23-'Balance Sheet'!G23 -> -22507.69 | E21: ='Balance Sheet'!I26-'Balance Sheet'!H26+'Balance Sheet'!I23-'Balance Sheet'!H23 -> -42.633343 | F21: ='Balance Sheet'!J26-'Balance Sheet'!I26+'Balance Sheet'!J23-'Balance Sheet'!I23 -> -1550.213 | G21: ='Balance Sheet'!K26-'Balance Sheet'!J26+'Balance Sheet'!K23-'Balance Sheet'!J23 -> 12971.339 | H21: ='Balance Sheet'!L26-'Balance Sheet'!K26+'Balance Sheet'!L23-'Balance Sheet'!K23 -> 2634.2475 | I21: ='Balance Sheet'!M26-'Balance Sheet'!L26+'Balance Sheet'!M23-'Balance Sheet'!L23 -> 7296.2433 | J21: ='Balance Sheet'!N26-'Balance Sheet'!M26+'Balance Sheet'!N23-'Balance Sheet'!M23 -> -24180.635 | K21: ='Balance Sheet'!O26-'Balance Sheet'!N26+'Balance Sheet'!O23-'Balance Sheet'!N23 -> -26234.813 | ... N21: ='Balance Sheet'!R26-'Balance Sheet'!Q26+'Balance Sheet'!R23-'Balance Sheet'!Q23 -> 42051.935 | P21: ='Balance Sheet'!T26-'Balance Sheet'!R26+'Balance Sheet'!T23-'Balance Sheet'!R23 -> -849.46473 | Q21: ='Balance Sheet'!U26-'Balance Sheet'!T26+'Balance Sheet'!U23-'Balance Sheet'!T23 -> -13086.621 | R21: ='Balance Sheet'!V26-'Balance Sheet'!U26+'Balance Sheet'!V23-'Balance Sheet'!U23 -> -99674.684
A22: Cash Generated from (Used in) Financing Activity | C22: =SUM(C17:C21) -> 4383.961 | D22: =SUM(D17:D21) -> 3352712 | E22: =SUM(E17:E21) -> 3369130.7 | F22: =SUM(F17:F21) -> -1210.2997 | G22: =SUM(G17:G21) -> 14051.979 | H22: =SUM(H17:H21) -> 3253.5063 | I22: =SUM(I17:I21) -> 1098687.9 | J22: =SUM(J17:J21) -> -61364.431 | ... N22: =SUM(N17:N21) -> 60070.213 | P22: =SUM(P17:P21) -> -51629.593 | Q22: =SUM(Q17:Q21) -> -10020.58 | R22: =SUM(R17:R21) -> -202974.93
A24: Net change in Cash | C24: =C10+C15+C22 -> -209368.94 | D24: =D10+D15+D22 -> 3199072.8 | E24: =E10+E15+E22 -> 2776773.8 | F24: =F10+F15+F22 -> -477310.62 | G24: =G10+G15+G22 -> -501811.17 | H24: =H10+H15+H22 -> -260492.54 | I24: =I10+I15+I22 -> -585803.34 | J24: =J10+J15+J22 -> -299768.93 | ... N24: =N10+N15+N22 -> -227209.3 | P24: =P10+P15+P22 -> -527466.34 | Q24: =Q10+Q15+Q22 -> -385413.03 | R24: =R10+R15+R22 -> -281385.25
A26: Cash Opening Balance | C26: ='Balance Sheet'!E6 -> 506664.22 | D26: =C27 -> 297295.28 | E26: =D27 -> 3496368.1 | F26: =E27 -> 6273141.9 | G26: =F27 -> 5795831.3 | H26: =G27 -> 5294020.1 | I26: =H27 -> 5033527.6 | J26: =I27 -> 4447724.2 | K26: =J27 -> 4147955.3 | ... N26: =M27 -> 3350721.3 | P26: ='Balance Sheet'!R6 -> 3123512 | Q26: =P27 -> 2596045.7 | R26: =Q27 -> 2210632.7
A27: Cash Ending Balance | C27: =C26+C24 -> 297295.28 | D27: =D26+D24 -> 3496368.1 | E27: =E26+E24 -> 6273141.9 | F27: =F26+F24 -> 5795831.3 | G27: =G26+G24 -> 5294020.1 | H27: =H26+H24 -> 5033527.6 | I27: =I26+I24 -> 4447724.2 | J27: =J26+J24 -> 4147955.3 | ... N27: =N26+N24 -> 3123512 | P27: =P26+P24 -> 2596045.7 | Q27: =Q26+Q24 -> 2210632.7 | R27: =R26+R24 -> 1929247.4
A29: Check | C29: =C27-'Balance Sheet'!G6 -> 0 | D29: =D27-'Balance Sheet'!H6 -> 0 | E29: =E27-'Balance Sheet'!I6 -> 0 | F29: =F27-'Balance Sheet'!J6 -> 0 | G29: =G27-'Balance Sheet'!K6 -> 0 | H29: =H27-'Balance Sheet'!L6 -> 0 | I29: =I27-'Balance Sheet'!M6 -> 0 | J29: =J27-'Balance Sheet'!N6 -> 0 | ... N29: =N27-'Balance Sheet'!R6 -> 0 | P29: =P27-'Balance Sheet'!T6 -> 0 | Q29: =Q27-'Balance Sheet'!U6 -> 0 | R29: =R27-'Balance Sheet'!V6 -> 0
