Workbook
Name __xlnm.Print_Area: 'Aged debtors'!#REF!
Name __xlnm.Print_Area: #REF!
Name __xlnm.Print_Area: 'Customer data'!#REF!
Name __xlnm.Print_Area: #REF!
Name __xlnm.Print_Area: 'Largest debtors'!#REF!
Name __xlnm.Print_Area: #REF!
Name __xlnm.Print_Area: Stock!#REF!
Name __xlnm.Print_Area: #REF!
Name __xlnm.Print_Area_4: 'Aged debtors'!#REF!
Name __xlnm.Print_Area_4: #REF!
Name __xlnm.Print_Area_4: 'Customer data'!#REF!
Name __xlnm.Print_Area_4: 'Largest debtors'!#REF!
Name __xlnm.Print_Area_4: #REF!
Name __xlnm.Print_Area_4: Stock!#REF!
Name __xlnm.Print_Area_4: #REF!
Name a: 'Aged debtors'!#REF!
Name a: 'Customer data'!#REF!
Name a: 'Largest debtors'!#REF!
Name a: #REF!
Name a: Stock!#REF!
Name a: #REF!
Name Acc_Rev_Chart: OFFSET('Aged debtors'!#REF!,0,0,1,COUNTIF('Aged debtors'!#REF!,">0"))
Name Acc_Rev_Chart: OFFSET('Customer data'!#REF!,0,0,1,COUNTIF('Customer data'!#REF!,">0"))
Name Acc_Rev_Chart: OFFSET('Largest debtors'!#REF!,0,0,1,COUNTIF('Largest debtors'!#REF!,">0"))
Name Acc_Rev_Chart: OFFSET(#REF!,0,0,1,COUNTIF(#REF!,">0"))
Name Acc_Rev_Chart: OFFSET(Stock!#REF!,0,0,1,COUNTIF(Stock!#REF!,">0"))
Name Acc_Rev_Chart: OFFSET(#REF!,0,0,1,COUNTIF(#REF!,">0"))
Name Acc_Rev_Plan_Chart: OFFSET('Aged debtors'!#REF!,0,0,1,COUNTIF('Aged debtors'!#REF!,">0"))
Name Acc_Rev_Plan_Chart: OFFSET('Customer data'!#REF!,0,0,1,COUNTIF('Customer data'!#REF!,">0"))
Name Acc_Rev_Plan_Chart: OFFSET('Largest debtors'!#REF!,0,0,1,COUNTIF('Largest debtors'!#REF!,">0"))
Name Acc_Rev_Plan_Chart: OFFSET(#REF!,0,0,1,COUNTIF(#REF!,">0"))
Name Acc_Rev_Plan_Chart: OFFSET(Stock!#REF!,0,0,1,COUNTIF(Stock!#REF!,">0"))
Name Acc_Rev_Plan_Chart: OFFSET(#REF!,0,0,1,COUNTIF(#REF!,">0"))
Name Actual_Staff_YTD: 'Aged debtors'!#REF!
Name Actual_Staff_YTD: 'Customer data'!#REF!
Name Actual_Staff_YTD: 'Largest debtors'!#REF!
Name Actual_Staff_YTD: #REF!
Name Actual_Staff_YTD: Stock!#REF!
Name Actual_Staff_YTD: #REF!
Name Adj_EBITA_P2: 'Aged debtors'!#REF!
Name Adj_EBITA_P2: #REF!
Name Adj_EBITA_P2: 'Customer data'!#REF!
Name Adj_EBITA_P2: 'Largest debtors'!#REF!
Name Adj_EBITA_P2: #REF!
Name Adj_EBITA_P2: Stock!#REF!
Name Adj_EBITA_P2: #REF!
Name annual_mem: 'Aged debtors'!#REF!
Name annual_mem: 'Customer data'!#REF!
Name annual_mem: 'Largest debtors'!#REF!
Name annual_mem: #REF!
Name annual_mem: Stock!#REF!
Name annual_mem: #REF!
Name bob: 'Aged debtors'!#REF!
Name bob: #REF!
Name bob: 'Customer data'!#REF!
Name bob: 'Largest debtors'!#REF!
Name bob: #REF!
Name bob: Stock!#REF!
Name bob: #REF!
Name Bonus_Amount: 'Aged debtors'!#REF!

Sheet Cover
A1: Auto+Hide+Values
B17: Management Accounts
B19: 46054
E21: Company Confidential
AC68: =AC47+AC46-V46-V47 -> 0

Sheet KPIs
A1: Auto+Hide+Values
B2: Key Performance Indicators | C2: 43101 | D2: 43132 | E2: 43160 | F2: 43191 | G2: 43221 | H2: 43252 | I2: 43282 | J2: 43313 | K2: 43344 | L2: 43374 | M2: 43405 | N2: 43435 | O2: 43466 | P2: 43497 | Q2: 43525 | R2: 43556 | S2: 43586 | T2: 43617 | U2: 43647 | V2: 43678 | W2: 43709 | X2: 43739 | Y2: 43770 | Z2: 43800 | AA2: 43831 | AB2: 43862 | AC2: 43891 | AD2: 43922 | AE2: 43952 | AF2: 43983 | AG2: 44013 | AH2: 44044 | AI2: 44075 | AJ2: 44105 | AK2: 44136 | AL2: 44166 | AM2: 44197 | AN2: 44228 | AO2: 44256 | AP2: 44287 | AQ2: 44317 | AR2: 44348 | AS2: 44378 | AT2: 44409 | AU2: 44440 | AV2: 44470 | AW2: 44501 | AX2: 44531 | AY2: 44562 | AZ2: 44593 | BA2: 44621 | BB2: 44652 | BC2: 44682 | BD2: 44713 | BE2: 44743 | BF2: 44774 | BG2: 44805 | BH2: 44835 | BI2: 44866 | BJ2: 44896 | BK2: 44927 | BL2: 44958 | BM2: 44986 | BN2: 45017 | BO2: 45047 | BP2: 45078 | BQ2: 45108 | BR2: 45139 | BS2: 45170 | BT2: 45200 | BU2: 45231 | BV2: 45261 | BW2: 45292 | BX2: 45323 | BY2: 45352 | BZ2: 45383 | CA2: 45413 | CB2: 45444 | CC2: 45474 | CD2: 45505 | CE2: 45536 | CF2: 45566 | CG2: 45597 | CH2: 45627 | CI2: 45658 | CJ2: 45689 | CK2: 45717 | CL2: 45748 | CM2: 45778 | CN2: 45809 | CO2: 45839 | CP2: 45870 | CQ2: 45901 | CR2: 45931 | CS2: 45962 | CT2: 45992 | CU2: 46023 | CV2: 46054 | CX2: 46054 | CY2: 45689 | CZ2: YTD 2026 | DA2: YTD 2026 | DB2: YTD 2025
C3: Actual | D3: Actual | E3: Actual | F3: Actual | G3: Actual | H3: Actual | I3: Actual | J3: Actual | K3: Actual | L3: Actual | M3: Actual | N3: Actual | O3: Actual | P3: Actual | Q3: Actual | R3: Actual | S3: Actual | T3: Actual | U3: Actual | V3: Actual | W3: Actual | X3: Actual | Y3: Actual | Z3: Actual | AA3: Actual | AB3: Actual | AC3: Actual | AD3: Actual | AE3: Actual | AF3: Actual | AG3: Actual | AH3: Actual | AI3: Actual | AJ3: Actual | AK3: Actual | AL3: Actual | AM3: Actual | AN3: Actual | AO3: Actual | AP3: Actual | AQ3: Actual | AR3: Actual | AS3: Actual | AT3: Actual | AU3: Actual | AV3: Actual | AW3: Actual | AX3: Actual | AY3: Actual | AZ3: Actual | BA3: Actual | BB3: Actual | BC3: Actual | BD3: Actual | BE3: Actual | BF3: Actual | BG3: Actual | BH3: Actual | BI3: Actual | BJ3: Actual | BK3: Actual | BL3: Actual | BM3: Actual | BN3: Actual | BO3: Actual | BP3: Actual | BQ3: Actual | BR3: Actual | BS3: Actual | BT3: Actual | BU3: Actual | BV3: Actual | BW3: Actual | BX3: Actual | BY3: Actual | BZ3: Actual | CA3: Actual | CB3: Actual | CC3: Actual | CD3: Actual | CE3: Actual | CF3: Actual | CG3: Actual | CH3: Actual | CI3: Actual | CJ3: Actual | CK3: Actual | CL3: Actual | CM3: Actual | CN3: Actual | CO3: Actual | CP3: Actual | CQ3: Actual | CR3: Actual | CS3: Actual | CT3: Actual | CU3: Actual | CV3: Actual | CX3: Plan | CY3: Actual | CZ3: Actual | DA3: Plan | DB3: Actual
B5: Managed services | C5: ='Financial statements'!BR7 -> 651796 | D5: ='Financial statements'!BS7 -> 641723 | E5: ='Financial statements'!BT7 -> 631570 | F5: ='Financial statements'!BU7 -> 642402 | G5: ='Financial statements'!BV7 -> 652594 | H5: ='Financial statements'!BW7 -> 678176 | I5: ='Financial statements'!BX7 -> 749078 | J5: ='Financial statements'!BY7 -> 761402 | ... CV5: ='Financial statements'!FK7 -> 2031706.2 | CX5: ='Financial plan'!EZ8 -> 2134808.7 | CY5: =CJ5 -> 1913349.3 | CZ5: ='Financial statements'!$P7 -> 4098084.7 | DA5: =SUM('Financial plan'!$EY8:EZ8) -> 4269617.4 | DB5: =SUM($CI5:CJ5) -> 3794897.1
B6: Hardware | C6: ='Financial statements'!BR13 -> 9430 | D6: ='Financial statements'!BS13 -> 48105 | E6: ='Financial statements'!BT13 -> 71213 | F6: ='Financial statements'!BU13 -> 157072 | G6: ='Financial statements'!BV13 -> 48958 | H6: ='Financial statements'!BW13 -> 34054 | I6: ='Financial statements'!BX13 -> 140299 | J6: ='Financial statements'!BY13 -> 20342 | ... CV6: ='Financial statements'!FK13 -> 5967.9228 | CX6: ='Financial plan'!EZ18 -> 94532.828 | CY6: =CJ6 -> 171809.88 | CZ6: ='Financial statements'!$P13 -> 35492.031 | DA6: =SUM('Financial plan'!$EY18:EZ18) -> 189065.66 | DB6: =SUM($CI6:CJ6) -> 177509.73
B7: Consultancy | C7: ='Financial statements'!BR14 -> 17364 | D7: ='Financial statements'!BS14 -> 0 | E7: ='Financial statements'!BT14 -> 8526 | F7: ='Financial statements'!BU14 -> 0 | G7: ='Financial statements'!BV14 -> 3100 | H7: ='Financial statements'!BW14 -> 0 | I7: ='Financial statements'!BX14 -> 43231 | J7: ='Financial statements'!BY14 -> 8500 | ... CV7: ='Financial statements'!FK14 -> 10068.302 | CX7: ='Financial plan'!EZ19 -> 45000 | CY7: =CJ7 -> 92252.94 | CZ7: ='Financial statements'!$P14 -> 17700.495 | DA7: =SUM('Financial plan'!$EY19:EZ19) -> 90000 | DB7: =SUM($CI7:CJ7) -> 157821.08
B8: Total revenue | C8: ='Financial statements'!BR25 -> 678590 | D8: ='Financial statements'!BS25 -> 689828 | E8: ='Financial statements'!BT25 -> 711309 | F8: ='Financial statements'!BU25 -> 799474 | G8: ='Financial statements'!BV25 -> 704652 | H8: ='Financial statements'!BW25 -> 712230 | I8: ='Financial statements'!BX25 -> 932608 | J8: ='Financial statements'!BY25 -> 790244 | ... CV8: ='Financial statements'!FK25 -> 2047742.4 | CX8: =SUM(CX5:CX7) -> 2274341.5 | CY8: =CJ8 -> 2177412.1 | CZ8: =SUM(CZ5:CZ7) -> 4151277.2 | DA8: =SUM('Financial plan'!$EY21:EZ21) -> 4548683.1 | DB8: =SUM($CI8:CJ8) -> 4130228
DB9: =SUM($CI9:CJ9) -> 0
B10: Gross profit | C10: ='Financial statements'!BR44 -> 373435 | D10: ='Financial statements'!BS44 -> 419655 | E10: ='Financial statements'!BT44 -> 398153 | F10: =('Financial statements'!BU44) -> 401277 | G10: =('Financial statements'!BV44) -> 356980 | H10: =('Financial statements'!BW44) -> 381991 | I10: =('Financial statements'!BX44) -> 490834 | J10: =('Financial statements'!BY44) -> 419898 | K10: =('Financial statements'!BZ44) -> 432199 | L10: =('Financial statements'!CA44) -> 473628 | M10: =('Financial statements'!CB44) -> 452372 | ... CV10: =('Financial statements'!FK44) -> 1053666.9 | CX10: ='Financial plan'!EZ39 -> 1102576 | CY10: =CJ10 -> 1023272.3 | CZ10: ='Financial statements'!$P44 -> 1000133.9 | DA10: =SUM('Financial plan'!$EY39:EZ39) -> 2205151.9 | DB10: =SUM($CI10:CJ10) -> 1997789.1
DB12: =SUM($AY12:CG12) -> 0
B13: Overheads | C13: =-'Financial statements'!BR59 -> 435543 | D13: =-'Financial statements'!BS59 -> 437365 | E13: =-'Financial statements'!BT59 -> 469899 | F13: =-'Financial statements'!BU59 -> 480330 | G13: =-'Financial statements'!BV59 -> 469990 | H13: =-'Financial statements'!BW59 -> 482644 | I13: =-'Financial statements'!BX59 -> 522475 | J13: =-'Financial statements'!BY59 -> 501279 | ... CV13: =-'Financial statements'!FK59 -> 880582.43 | CX13: =-'Financial plan'!EZ54 -> 936737.79 | CY13: =CJ13 -> 985290.43 | CZ13: =-'Financial statements'!$P59 -> 1773250.8 | DA13: =-SUM('Financial plan'!$EY54:EZ54) -> 1873475.6 | DB13: =SUM($CI13:CJ13) -> 1953022.7
B14: EBITDA before bonus | C14: =C10-C13 -> -62108 | D14: =D10-D13 -> -17710 | E14: =E10-E13 -> -71746 | F14: =F10-F13 -> -79053 | G14: =G10-G13 -> -113010 | H14: =H10-H13 -> -100653 | I14: =I10-I13 -> -31641 | J14: =J10-J13 -> -81381 | ... CV14: =CV10-CV13 -> 173084.52 | CX14: =CX10-CX13 -> 165838.18 | CY14: =CJ14 -> 37981.869 | CZ14: =CZ10-CZ13 -> -773116.93 | DA14: =SUM('Financial plan'!$EY55:EZ55) -> 331676.36 | DB14: =SUM($CI14:CJ14) -> 44766.431
B15: Bonus | BW15: -54619.972 | BX15: -54212.043 | BY15: -52009.545 | BZ15: -44091.326 | CA15: -52452.662 | CB15: -52654.67 | CC15: -1284.6888 | CD15: 8743.0523 | CE15: 21409.262 | CF15: 28411.953 | CG15: 78473.886 | CH15: 174286.75 | CI15: -61094.728 | CJ15: -60710.738 | CK15: -60921.487 | CL15: -58165.515 | CM15: -25110.533 | CN15: -1288.5775 | CO15: ='Financial statements'!FD61 -> -69.984466 | CP15: ='Financial statements'!FE61 -> -384 | CQ15: ='Financial statements'!FF61 -> -8825.2867 | CR15: ='Financial statements'!FG61 -> 0 | CS15: ='Financial statements'!FH61 -> -52268 | CT15: ='Financial statements'!FI61 -> -85639.578 | CU15: ='Financial statements'!FJ61 -> -57412 | CV15: ='Financial statements'!FK61 -> -57893 | CX15: ='Financial plan'!EZ56 -> -37964.188 | CY15: =CJ15 -> -60710.738 | CZ15: ='Financial statements'!$P61 -> -115305 | DA15: =SUM('Financial plan'!$EY56:EZ56) -> -75928.376 | DB15: =SUM($CI15:CJ15) -> -121805.47
B16: EBITDA after bonus | BW16: =SUM(BW14:BW15) -> -58768.553 | BX16: =SUM(BX14:BX15) -> -66765.881 | BY16: =SUM(BY14:BY15) -> 56193.687 | BZ16: =SUM(BZ14:BZ15) -> -86723.825 | CA16: =SUM(CA14:CA15) -> 6231.966 | CB16: =SUM(CB14:CB15) -> -86099.512 | CC16: =SUM(CC14:CC15) -> -42047.603 | CD16: =SUM(CD14:CD15) -> -26998.69 | ... CV16: =SUM(CV14:CV15) -> 115191.52 | CX16: =SUM(CX14:CX15) -> 127873.99 | CY16: =CJ16 -> -22728.868 | CZ16: =SUM(CZ14:CZ15) -> -888421.93 | DA16: =SUM(DA14:DA15) -> 255747.98 | DB16: =SUM($CI16:CJ16) -> -77039.035
B18: Operating cash inflow/(outflow) | C18: =('Financial statements'!BR101+'Financial statements'!BR103) -> -192575 | D18: =('Financial statements'!BS101+'Financial statements'!BS103) -> -373888 | E18: =('Financial statements'!BT101+'Financial statements'!BT103) -> -219141 | F18: =('Financial statements'!BU101+'Financial statements'!BU103) -> 137024 | G18: =('Financial statements'!BV101+'Financial statements'!BV103) -> -65158 | H18: =('Financial statements'!BW101+'Financial statements'!BW103) -> -275365 | I18: =('Financial statements'!BX101+'Financial statements'!BX103) -> -370534 | J18: =('Financial statements'!BY101+'Financial statements'!BY103) -> 15814 | ... CV18: =('Financial statements'!FK101+'Financial statements'!FK103) -> -234918.61 | CY18: =CJ18 -> 289614.82 | CZ18: =SUM($CU18:CV18) -> -609285.68 | DB18: =SUM($CI18:CJ18) -> -171479.14
B19: Cash | C19: ='Financial statements'!BR115 -> 1163323 | D19: ='Financial statements'!BS115 -> 787372 | E19: ='Financial statements'!BT115 -> 516015 | F19: ='Financial statements'!BU115 -> 609038 | G19: ='Financial statements'!BV115 -> 482329 | H19: ='Financial statements'!BW115 -> 730017 | I19: ='Financial statements'!BX115 -> 274252 | J19: ='Financial statements'!BY115 -> 685169 | ... CV19: ='Financial statements'!FK115 -> 4773852.1 | CY19: =CJ19 -> 3099115.3 | CZ19: =CV19 -> 4773852.1 | DB19: =CJ19 -> 3099115.3
B21: No of customers | C21: ='Customer data'!L268 -> 967 | D21: ='Customer data'!M268 -> 1008 | E21: ='Customer data'!N268 -> 1083 | F21: ='Customer data'!O268 -> 1120 | G21: ='Customer data'!P268 -> 1175 | H21: ='Customer data'!Q268 -> 1221 | I21: ='Customer data'!R268 -> 1216 | J21: ='Customer data'!S268 -> 1252 | ... CV21: ='Customer data'!DE268 -> 1076 | CY21: =CJ21 -> 1033 | CZ21: =SUM($CU21:CV21) -> 2132 | DB21: =CJ21 -> 1033
B22: No of devices | C22: ='Customer data'!L260 -> 1003681 | D22: ='Customer data'!M260 -> 1011809 | E22: ='Customer data'!N260 -> 1054447 | F22: ='Customer data'!O260 -> 946983 | G22: ='Customer data'!P260 -> 968106 | H22: ='Customer data'!Q260 -> 988289 | I22: ='Customer data'!R260 -> 999982 | J22: ='Customer data'!S260 -> 1019404 | ... CV22: ='Customer data'!DE260 -> 5032348 | CY22: =CJ22 -> 2642271 | CZ22: =SUM($CU22:CV22) -> 10035085 | DB22: =CJ22 -> 2642271
B23: % of devices paygo | C23: ='Customer data'!L265 -> 0.44055233 | D23: ='Customer data'!M265 -> 0.43709534 | E23: ='Customer data'!N265 -> 0.43224363 | F23: ='Customer data'!O265 -> 0.36389777 | G23: ='Customer data'!P265 -> 0.35595792 | H23: ='Customer data'!Q265 -> 0.34868849 | I23: ='Customer data'!R265 -> 0.34482721 | J23: ='Customer data'!S265 -> 0.33825745 | ... CV23: ='Customer data'!DE265 -> 0.014371224 | CY23: =CJ23 -> 0.045929051 | CZ23: =SUM($CU23:CV23) -> 0.028915063 | DB23: =CJ23 -> 0.045929051
B24: % of devices emerging markets | C24: ='Customer data'!L266 -> 0 | D24: ='Customer data'!M266 -> 0 | E24: ='Customer data'!N266 -> 0 | F24: ='Customer data'!O266 -> 0.37603949 | G24: ='Customer data'!P266 -> 0.37054207 | H24: ='Customer data'!Q266 -> 0.37522425 | I24: ='Customer data'!R266 -> 0.37162869 | J24: ='Customer data'!S266 -> 0.3764121 | ... CV24: ='Customer data'!DE266 -> 0.10323908 | CY24: =CJ24 -> 0.20056686 | CZ24: =SUM($CU24:CV24) -> 0.20797535 | DB24: =CJ24 -> 0.20056686
B26: Total ARPU (£s) *
B27: Deploying | C27: ='Revenue data'!D67 -> 0 | D27: ='Revenue data'!E67 -> 0 | E27: ='Revenue data'!F67 -> 0 | F27: ='Revenue data'!G67 -> 0.4739376 | G27: ='Revenue data'!H67 -> 0.44698155 | H27: ='Revenue data'!I67 -> 0.4811228 | I27: ='Revenue data'!J67 -> 0.53460122 | J27: ='Revenue data'!K67 -> 0.42195686 | ... CV27: ='Revenue data'!CW67 -> 0.68113994 | CY27: =CJ27 -> 0.62197061
B28: Pre-deployment | C28: ='Revenue data'!D68 -> 0 | D28: ='Revenue data'!E68 -> 0 | E28: ='Revenue data'!F68 -> 0 | F28: ='Revenue data'!G68 -> 1.326 | G28: ='Revenue data'!H68 -> 1.8687671 | H28: ='Revenue data'!I68 -> 2.1264 | I28: ='Revenue data'!J68 -> 3.2501351 | J28: ='Revenue data'!K68 -> 2.6760811 | ... CV28: ='Revenue data'!CW68 -> 0.15024505 | CY28: =CJ28 -> 0.16641292
B29: Other accounts | C29: ='Revenue data'!D69 -> 0 | D29: ='Revenue data'!E69 -> 0 | E29: ='Revenue data'!F69 -> 0 | F29: ='Revenue data'!G69 -> 1.4341518 | G29: ='Revenue data'!H69 -> 1.5458215 | H29: ='Revenue data'!I69 -> 1.3286054 | I29: ='Revenue data'!J69 -> 1.422076 | J29: ='Revenue data'!K69 -> 1.7304567 | ... CV29: ='Revenue data'!CW69 -> 1.2279208 | CY29: =CJ29 -> 1.1809964
B30: Brazil | C30: ='Revenue data'!D70 -> 0 | D30: ='Revenue data'!E70 -> 0 | E30: ='Revenue data'!F70 -> 0 | F30: ='Revenue data'!G70 -> 1.7337056 | G30: ='Revenue data'!H70 -> 1.6915672 | H30: ='Revenue data'!I70 -> 0.98808661 | I30: ='Revenue data'!J70 -> 1.5106707 | J30: ='Revenue data'!K70 -> 1.1871073 | ... CV30: ='Revenue data'!CW70 -> 0.85075652 | CY30: =CJ30 -> 0.86771695
B31: All regions | C31: ='Revenue data'!D73 | D31: ='Revenue data'!E73 | E31: ='Revenue data'!F73 | F31: ='Revenue data'!G73 -> 0.68957537 | G31: ='Revenue data'!H73 -> 0.69043564 | H31: ='Revenue data'!I73 -> 0.6796909 | I31: ='Revenue data'!J73 -> 0.74783621 | J31: ='Revenue data'!K73 -> 0.70462127 | ... CV31: ='Revenue data'!CW73 -> 0.41970865 | CY31: =CJ31 -> 0.72278418
B34: * for consistency, prior period comparatives have been updated for reallocation of Tier 4 accounts and regions in August 2019
B36: Service revenue excl SIM sales | C36: 639147 | D36: 622382 | E36: 605883 | F36: 637640 | G36: 642498 | H36: 669885 | I36: 746354 | J36: 753906 | K36: 735804.27 | L36: 755020 | M36: 786812.81 | N36: 821137 | O36: =('Financial statements'!CD7-'Financial statements'!CD11) -> 802039 | P36: =('Financial statements'!CE7-'Financial statements'!CE11) -> 799566 | Q36: =('Financial statements'!CF7-'Financial statements'!CF11) -> 840978 | R36: =('Financial statements'!CG7-'Financial statements'!CG11) -> 829964.46 | S36: =('Financial statements'!CH7-'Financial statements'!CH11) -> 840841.92 | T36: =('Financial statements'!CI7-'Financial statements'!CI11) -> 854073 | U36: =('Financial statements'!CJ7-'Financial statements'!CJ11) -> 897330.29 | V36: =('Financial statements'!CK7-'Financial statements'!CK11) -> 932348.39 | ... CV36: =('Financial statements'!FK7-'Financial statements'!FK11) -> 1997378.2
B37: Service COS from above excl SIMs | C37: -253784.82 | D37: -223280.03 | E37: -221613.58 | F37: -274831.37 | G37: -275266.41 | H37: -276183.85 | I37: -296698.88 | J37: -334737.68 | K37: -313929.84 | L37: -301441.01 | M37: -336950.49 | N37: -261748.01 | O37: -358318.49 | P37: -374434.91 | Q37: -433952 | R37: -446927.98 | S37: -426542 | T37: -475745.53 | U37: -473212.71 | V37: -489166.48 | W37: -512771.55 | X37: -492932.86 | Y37: -486789.05 | Z37: -520508.88 | AA37: -540281.29 | AB37: -544638.95 | AC37: -521877.28 | AD37: -500224.97 | AE37: -525698.37 | AF37: -490930.38 | AG37: -527790.56 | AH37: -496612.21 | AI37: -478920.58 | AJ37: -487671.28 | AK37: -489808.53 | AL37: -490328.1 | AM37: -476672.98 | AN37: -480585.02 | AO37: -489223.81 | AP37: -492939.29 | AQ37: -502357.39 | AR37: -508518.51 | AS37: -563486.09 | AT37: -610546.9 | AU37: -588358.14 | AV37: -623265.16 | AW37: -638209.67 | AX37: -626478.01 | AY37: -641602.08 | AZ37: -656573.28 | BA37: -687946.19 | BB37: -736431.94 | BC37: -770425.05 | BD37: -781268.71 | BE37: -853578.88 | BF37: -841171 | BG37: -888188.48 | BH37: -844912.75 | BI37: -820049.93 | BJ37: -777082.46 | BK37: -773105.38 | BL37: -769185.26 | BM37: -803811.66 | BN37: -807633.22 | BO37: -818541.91 | BP37: ='Financial statements'!EE28+81815.52 -> -850574.01 | BQ37: ='Financial statements'!EF28-39296.05+155656.07 -> -835206.55 | BR37: -833702.69 | BS37: -834493.98 | BT37: -843928.03 | BU37: -862625.28 | BV37: -839983.69 | BW37: -820294.42 | BX37: -825606.73 | BY37: -875623.64 | BZ37: -886195.76 | CA37: -876476.56 | CB37: -892632.66 | CC37: -890287.7 | CD37: -900034.36 | CE37: -904632.7 | CF37: -901978.8 | CG37: -923068.28 | CH37: -893177.63 | CI37: -905740.26 | CJ37: -911726.59 | CK37: -899445.97 | CL37: -909998.43 | CM37: -902434.5 | CN37: -904871.73 | CO37: -973813.84 | CP37: -989227.46 | CQ37: -1005662.9 | CR37: -985394.19 | CS37: -985185.83 | CT37: -962071.94 | CU37: -966952.22 | CV37: -961251.51
B38: Gross service profit excl SIMS | C38: =SUM(C36:C37) -> 385362.18 | D38: =SUM(D36:D37) -> 399101.97 | E38: =SUM(E36:E37) -> 384269.42 | F38: =SUM(F36:F37) -> 362808.63 | G38: =SUM(G36:G37) -> 367231.59 | H38: =SUM(H36:H37) -> 393701.15 | I38: =SUM(I36:I37) -> 449655.12 | J38: =SUM(J36:J37) -> 419168.32 | ... CV38: =SUM(CV36:CV37) -> 1036126.7
B39: Managed services GM% EXC SIMS | C39: =C38/C36 -> 0.60293201 | D39: =D38/D36 -> 0.64124921 | E39: =E38/E36 -> 0.6342304 | F39: =F38/F36 -> 0.56898662 | G39: =G38/G36 -> 0.57156846 | H39: =H38/H36 -> 0.58771453 | I39: =I38/I36 -> 0.60246896 | J39: =J38/J36 -> 0.55599547 | ... CV39: =CV38/CV36 -> 0.51874337
AX44: 2021 | BJ44: 2022 | BK44: 2023
AL45: =AL22 -> 1431382 | AX45: =AX22 -> 1890458 | BJ45: =BJ22 -> 2311815 | BK45: =BV22 -> 2452291 | BL45: =BK45*1.2 -> 2942749.2
AX46: =AX45-AL45 -> 459076 | BJ46: =BJ45-AX45 -> 421357 | BK46: =BK45-BJ45 -> 140476
AX47: =AX46/AL45 -> 0.32072221 | AY47: =AY46/AM45 -> #DIV/0! | AZ47: =AZ46/AN45 -> #DIV/0! | BA47: =BA46/AO45 -> #DIV/0! | BB47: =BB46/AP45 -> #DIV/0! | BC47: =BC46/AQ45 -> #DIV/0! | BD47: =BD46/AR45 -> #DIV/0! | BE47: =BE46/AS45 -> #DIV/0! | ... BJ47: =BJ46/AX45 -> 0.2228862 | BK47: =BK46/BJ45 -> 0.060764378
BK49: =(BK45/AL45)^(1/3)-1 -> 0.19657195

Sheet Financial statements
A1: Auto+Hide+Values
B2: GBP | F2: FY16 | G2: FY17 | H2: FY18 | I2: FY19 | J2: FY20 | K2: FY21 | L2: FY22 | M2: FY23 | N2: FY24 | O2: FY25 | P2: FY26 | R2: Q1-17 | S2: Q2-17 | T2: Q3-17 | U2: Q4-17 | V2: Q1-18 | W2: Q2-18 | X2: Q3-18 | Y2: Q4-18 | Z2: Q1-19 | AA2: Q2-19 | AB2: Q3-19 | AC2: Q4-19 | AD2: Q1-20 | AE2: Q2-20 | AF2: Q3-20 | AG2: Q4-20 | AH2: Q1-21 | AI2: Q2-21 | AJ2: Q3-21 | AK2: Q4-21 | AL2: Q1-22 | AM2: Q2-22 | AN2: Q3-22 | AO2: Q4-22 | AP2: Q1-23 | AQ2: Q2-23 | AR2: Q3-23 | AS2: Q4-23 | AT2: Q1-24 | AU2: Q2-24 | AV2: Q3-24 | AW2: Q4-24 | AX2: Q1-25 | AY2: Q2-25 | AZ2: Q3-25 | BA2: Q4-25 | BB2: Q1-26 | BC2: Q2-26 | BD2: Q3-26 | BE2: Q4-26 | BF2: 42736 | BG2: 42767 | BH2: 42795 | BI2: 42826 | BJ2: 42856 | BK2: 42887 | BL2: 42917 | BM2: 42948 | BN2: 42979 | BO2: 43009 | BP2: 43040 | BQ2: 43070 | BR2: 43101 | BS2: 43132 | BT2: 43160 | BU2: 43191 | BV2: 43221 | BW2: 43252 | BX2: 43282 | BY2: 43313 | BZ2: 43344 | CA2: 43374 | CB2: 43405 | CC2: 43435 | CD2: 43466 | CE2: 43497 | CF2: 43525 | CG2: 43556 | CH2: 43586 | CI2: 43617 | CJ2: 43647 | CK2: 43678 | CL2: 43709 | CM2: 43739 | CN2: 43770 | CO2: 43800 | CP2: 43831 | CQ2: 43862 | CR2: 43891 | CS2: 43922 | CT2: 43952 | CU2: 43983 | CV2: 44013 | CW2: 44044 | CX2: 44075 | CY2: 44105 | CZ2: 44136 | DA2: 44166 | DB2: 44197 | DC2: 44228 | DD2: 44256 | DE2: 44287 | DF2: 44317 | DG2: 44348 | DH2: 44378 | DI2: 44409 | DJ2: 44440 | DK2: 44470 | DL2: 44501 | DM2: 44531 | DN2: 44562 | DO2: 44593 | DP2: 44621 | DQ2: 44652 | DR2: 44682 | DS2: 44713 | DT2: 44743 | DU2: 44774 | DV2: 44805 | DW2: 44835 | DX2: 44866 | DY2: 44896 | DZ2: 44927 | EA2: 44958 | EB2: 44986 | EC2: 45017 | ED2: 45047 | EE2: 45078 | EF2: 45108 | EG2: 45139 | EH2: 45170 | EI2: 45200 | EJ2: 45231 | EK2: 45261 | EL2: 45292 | EM2: 45323 | EN2: 45352 | EO2: 45383 | EP2: 45413 | EQ2: 45444 | ER2: 45474 | ES2: 45505 | ET2: 45536 | EU2: 45566 | EV2: 45597 | EW2: 45627 | EX2: 45658 | EY2: 45689 | EZ2: 45717 | FA2: 45748 | FB2: 45778 | FC2: 45809 | FD2: 45839 | FE2: 45870 | FF2: 45901 | FG2: 45931 | FH2: 45962 | FI2: 45992 | FJ2: 46023 | FK2: 46054 | FN2: 46054 | FO2: Var to Jan-26 | FP2: Var to Jan-26 budget | FQ2: Var to Jan-26 budget | FR2: Var to Jan-26 budget | FS2: Var to Feb-26 budget | FT2: YTD-26 | FU2: YTD-26 | FV2: Var to YTD-26 budget
F3: actual | G3: plan | H3: actual | I3: actual | J3: actual | K3: actual | L3: actual | M3: actual | N3: actual | O3: actual | P3: actual | R3: actual | S3: actual | T3: actual | U3: actual | V3: actual | W3: actual | X3: actual | Y3: actual | Z3: actual | AA3: actual | AB3: actual | AC3: actual | AD3: actual | AE3: actual | AF3: actual | AG3: actual | AH3: actual | AI3: actual | AJ3: actual | AK3: actual | AL3: actual | AM3: actual | AN3: actual | AO3: actual | AP3: actual | AQ3: actual | AR3: actual | AS3: actual | AT3: actual | AU3: actual | AV3: actual | AW3: actual | AX3: actual | AY3: actual | AZ3: actual | BA3: actual | BB3: actual | BC3: actual | BD3: actual | BE3: actual | BR3: actual | BS3: actual | BT3: actual | BU3: actual | BV3: actual | BW3: actual | BX3: actual | BY3: actual | BZ3: actual | CA3: actual | CB3: actual | CC3: actual | CD3: actual | CE3: actual | CF3: actual | CG3: actual | CH3: actual | CI3: actual | CJ3: actual | CK3: actual | CL3: actual | CM3: actual | CN3: actual | CO3: actual | CP3: actual | CQ3: actual | CR3: actual | CS3: actual | CT3: actual | CU3: actual | CV3: actual | CW3: actual | CX3: actual | CY3: actual | CZ3: actual | DA3: actual | DB3: actual | DC3: actual | DD3: actual | DE3: actual | DF3: actual | DG3: actual | DH3: actual | DI3: actual | DJ3: actual | DK3: actual | DL3: actual | DM3: actual | DN3: actual | DO3: actual | DP3: actual | DQ3: actual | DR3: actual | DS3: actual | DT3: actual | DU3: actual | DV3: actual | DW3: actual | DX3: actual | DY3: actual | DZ3: actual | EA3: actual | EB3: actual | EC3: actual | ED3: actual | EE3: actual | EF3: actual | EG3: actual | EH3: actual | EI3: actual | EJ3: actual | EK3: actual | EL3: actual | EM3: actual | EN3: actual | EO3: actual | EP3: actual | EQ3: actual | ER3: actual | ES3: actual | ET3: actual | EU3: actual | EV3: actual | EW3: actual | EX3: actual | EY3: actual | EZ3: actual | FA3: actual | FB3: actual | FC3: actual | FD3: actual | FE3: actual | FF3: actual | FG3: actual | FH3: actual | FI3: actual | FJ3: actual | FK3: actual | FN3: budget | FT3: actual | FU3: budget
B4: Profit & loss account | AQ4: 3 | AR4: 6 | AS4: 9 | AT4: 2 | AU4: 3 | AV4: 6 | AW4: 9
D6: Revenue
E7: Managed services | F7: 5243000 | G7: =SUM(R7:U7) -> 6817494 | H7: =SUM(V7:Y7) -> 8562442 | I7: =SUM(Z7:AC7) -> 11137767 | J7: =SUM(AD7:AG7) -> 12663055 | K7: =SUM(AH7:AK7) -> 15236724 | L7: =SUM(AL7:AO7) -> 19841951 | M7: =SUM(AP7:AS7) -> 22122280 | N7: =SUM(AT7:AW7) -> 22910027 | O7: =SUM(AX7:BA7) -> 23609043 | P7: =SUM($FJ7:FK7) -> 4098084.7 | R7: =SUM(BF7:BH7) -> 1504042 | S7: =SUM(BI7:BK7) -> 1661076 | T7: =SUM(BL7:BN7) -> 1803269 | U7: =SUM(BO7:BQ7) -> 1849107 | V7: =SUM(BR7:BT7) -> 1925089 | W7: =SUM(BU7:BW7) -> 1973172 | X7: =SUM(BX7:BZ7) -> 2270128 | Y7: =SUM(CA7:CC7) -> 2394053 | Z7: =SUM(CD7:CF7) -> 2503013 | AA7: =SUM(CG7:CI7) -> 2652640 | AB7: =SUM(CJ7:CL7) -> 2862560 | AC7: =SUM(CM7:CO7) -> 3119554 | AD7: =SUM(CP7:CR7) -> 3227336 | AE7: =SUM(CS7:CU7) -> 3126544 | AF7: =SUM(CV7:CX7) -> 3129665 | AG7: =SUM(CY7:DA7) -> 3179509.9 | AH7: =SUM(DB7:DD7) -> 3285464.2 | AI7: =SUM(DE7:DG7) -> 3598475.4 | AJ7: =SUM(DH7:DJ7) -> 4039992.2 | AK7: =SUM(DK7:DM7) -> 4312791.9 | AL7: =SUM(DN7:DP7) -> 4324050 | AM7: =SUM(DQ7:DS7) -> 4836138.7 | AN7: =SUM(DT7:DV7) -> 5140234.2 | AO7: =SUM(DW7:DY7) -> 5541528 | AP7: =SUM(DZ7:EB7) -> 5429734.5 | AQ7: =OFFSET($DZ7,0,AQ$4)+OFFSET($EA7,0,AQ$4)+OFFSET($EB7,0,AQ$4) -> 5446302.2 | AR7: =OFFSET($DZ7,0,AR$4)+OFFSET($EA7,0,AR$4)+OFFSET($EB7,0,AR$4) -> 5584122.4 | AS7: =OFFSET($DZ7,0,AS$4)+OFFSET($EA7,0,AS$4)+OFFSET($EB7,0,AS$4) -> 5662121.2 | AT7: =SUM(EL7:EN7) -> 5807553.7 | AU7: =OFFSET($EL7,0,AU$4)+OFFSET($EM7,0,AU$4)+OFFSET($EN7,0,AU$4) -> 5777611.7 | AV7: =OFFSET($EL7,0,AV$4)+OFFSET($EM7,0,AV$4)+OFFSET($EN7,0,AV$4) -> 5659968.2 | AW7: =OFFSET($EL7,0,AW$4)+OFFSET($EM7,0,AW$4)+OFFSET($EN7,0,AW$4) -> 5664893.9 | AX7: =SUM(EX7:EZ7) -> 5620968.6 | AY7: =SUM(FA7:FC7) -> 5626791 | AZ7: =SUM(FD7:FF7) -> 6040665 | BA7: =SUM(FG7:FI7) -> 6320618.9 | BB7: =SUM(FJ7:FL7) -> 4098084.7 | BF7: 499065 | BG7: 471161 | BH7: 533816 | BI7: 544008 | BJ7: 573225 | BK7: 543843 | BL7: 569705 | BM7: 627045 | BN7: 606519 | BO7: 623258 | BP7: 611216 | BQ7: 614633 | BR7: 651796 | BS7: 641723 | BT7: 631570 | BU7: 642402 | BV7: 652594 | BW7: 678176 | BX7: =839078-90000 -> 749078 | BY7: 761402 | BZ7: 759648 | CA7: 774937 | CB7: =792087+5000 -> 797087 | CC7: 822029 | CD7: =831828-6500 -> 825328 | CE7: 826846 | CF7: 850839 | CG7: =881601-2000 -> 879601 | CH7: 883292 | CI7: 889747 | CJ7: 932124 | CK7: 948245 | CL7: =972191+10000 -> 982191 | CM7: =993575+10000 -> 1003575 | CN7: =1030522+20000 -> 1050522 | CO7: 1065457 | CP7: 1067087 | CQ7: 1078237 | CR7: 1082012 | CS7: 1063341 | CT7: 1032987 | CU7: 1030216 | CV7: 1044271 | CW7: 1034501.2 | CX7: 1050892.7 | CY7: 1055268.6 | CZ7: 1066025.1 | DA7: 1058216.2 | DB7: 1082826.5 | DC7: 1089809.2 | DD7: 1112828.5 | DE7: 1193927.1 | DF7: 1174221.9 | DG7: 1230326.4 | DH7: 1272166.2 | DI7: 1385697.3 | DJ7: 1382128.6 | DK7: 1438639.5 | DL7: 1453159.5 | DM7: 1420993 | DN7: 1430084.2 | DO7: 1435938.1 | DP7: 1458027.7 | DQ7: 1574785.9 | DR7: 1608150.5 | DS7: 1653202.3 | DT7: 1686256.9 | DU7: 1670379.2 | DV7: 1783598.2 | DW7: 1782606.8 | DX7: 1898032.2 | DY7: 1860889 | DZ7: 1779915.2 | EA7: 1806110 | EB7: 1843709.3 | EC7: 1827965.7 | ED7: 1776744.8 | EE7: 1841591.7 | EF7: 1851580.9 | EG7: 1841623.1 | EH7: 1890918.4 | EI7: 1845701.8 | EJ7: 1884822.5 | EK7: 1931596.9 | EL7: 1868668.5 | EM7: 1942526.1 | EN7: 1996359.1 | EO7: 1955878.3 | EP7: 1925178.5 | EQ7: 1896554.9 | ER7: 1892327.6 | ES7: 1897669.7 | ET7: 1869970.9 | EU7: 1903531.7 | EV7: 1909338.7 | EW7: 1852023.5 | EX7: 1881547.8 | EY7: 1913349.3 | EZ7: 1826071.4 | FA7: 1890987.3 | FB7: 1835211.3 | FC7: 1900592.4 | FD7: 1937480 | FE7: 1996687.5 | FF7: 2106497.5 | FG7: 2081008.8 | FH7: 2102511.8 | FI7: 2137098.3 | FJ7: 2066378.5 | FK7: 2031706.2 | FN7: ='Financial plan'!EZ8 -> 2134808.7 | FO7: =FK7-FJ7 -> -34672.39 | FP7: =FK7-FN7 -> -103102.55 | FQ7: =FL7-#REF! -> #REF! | FR7: =FM7-FO7 -> 34672.39 | FS7: =FK7-FN7 -> -103102.55 | FT7: =SUM($FJ7:FK7) -> 4098084.7 | FU7: =SUM('Financial plan'!$EY8:EZ8) -> 4269617.4 | FV7: =FT7-FU7 -> -171532.71
E8: Connectivity | H8: =SUM(V8:Y8) -> 0 | L8: =SUM(AL8:AO8) -> 16191409 | M8: =SUM(AP8:AS8) -> 18545178 | N8: =SUM(AT8:AW8) -> 18942230 | O8: =SUM(AX8:BA8) -> 19381277 | AJ8: =SUM(DH8:DJ8) -> 3145685.8 | AK8: =SUM(DK8:DM8) -> 3429560 | AL8: =SUM(DN8:DP8) -> 3594702.5 | AM8: =SUM(DQ8:DS8) -> 3936053 | AN8: =SUM(DT8:DV8) -> 4180409.2 | AO8: =SUM(DW8:DY8) -> 4480244.2 | AP8: =SUM(DZ8:EB8) -> 4616510.1 | AQ8: =OFFSET($DZ8,0,AQ$4)+OFFSET($EA8,0,AQ$4)+OFFSET($EB8,0,AQ$4) -> 4642098.7 | AR8: =OFFSET($DZ8,0,AR$4)+OFFSET($EA8,0,AR$4)+OFFSET($EB8,0,AR$4) -> 4575717.3 | AS8: =OFFSET($DZ8,0,AS$4)+OFFSET($EA8,0,AS$4)+OFFSET($EB8,0,AS$4) -> 4710851.5 | AT8: =SUM(EL8:EN8) -> 4825956 | AU8: =OFFSET($EL8,0,AU$4)+OFFSET($EM8,0,AU$4)+OFFSET($EN8,0,AU$4) -> 4830694.7 | AV8: =OFFSET($EL8,0,AV$4)+OFFSET($EM8,0,AV$4)+OFFSET($EN8,0,AV$4) -> 4663263.4 | AW8: =OFFSET($EL8,0,AW$4)+OFFSET($EM8,0,AW$4)+OFFSET($EN8,0,AW$4) -> 4622316 | AX8: =SUM(EX8:EZ8) -> 4681426.9 | AY8: =SUM(FA8:FC8) -> 4617999.9 | AZ8: =SUM(FD8:FF8) -> 4968774.3 | BA8: =SUM(FG8:FI8) -> 5113075.9 | BF8: 499065 | CD8: 649914.65 | CE8: 681816.84 | CF8: 686818.05 | CG8: 706085.33 | CH8: 721614.65 | CI8: 745628.79 | CJ8: 784828.18 | CK8: 811360.14 | CL8: 807040.97 | CM8: 819251.52 | CN8: 834555.22 | CO8: 826333.14 | CP8: 852657.06 | CQ8: 871151.98 | CR8: 887552.88 | CS8: 869608.72 | CT8: 858430.71 | CU8: 872676.06 | CV8: 877679.48 | CW8: 877817.22 | CX8: 894364 | CY8: 904984.66 | CZ8: 902572.94 | DA8: 907463.8 | DB8: 914883.48 | DC8: 923861.36 | DD8: 921084.36 | DE8: 921218.86 | DF8: 945230.31 | DG8: 972248.69 | DH8: 1019061.1 | DI8: 1078991.3 | DJ8: 1047633.3 | DK8: 1111496.4 | DL8: 1143557.7 | DM8: 1174505.9 | DN8: 1167208.2 | DO8: 1190776.2 | DP8: 1236718.2 | DQ8: 1274583.4 | DR8: 1313786.4 | DS8: 1347683.2 | DT8: 1367994.9 | DU8: 1364861.3 | DV8: 1447553 | DW8: 1499541.8 | DX8: 1491842.8 | DY8: 1488859.5 | DZ8: 1534812.5 | EA8: 1539169.7 | EB8: 1542527.9 | EC8: 1542706.9 | ED8: =1544033.79561978 -> 1544033.8 | EE8: 1555358 | EF8: 1499181.4 | EG8: 1524805.9 | EH8: 1551730.1 | EI8: 1559962.4 | EJ8: 1579492.6 | EK8: 1571396.4 | EL8: 1598122.5 | EM8: 1615036.4 | EN8: 1612797.1 | EO8: 1606008.7 | EP8: 1613232.2 | EQ8: 1611453.8 | ER8: 1589514.1 | ES8: 1561702.4 | ET8: 1512047 | EU8: 1516975.1 | EV8: 1564706.8 | EW8: 1540634.1 | EX8: 1554387.3 | EY8: 1575260.9 | EZ8: 1551778.6 | FA8: 1533379.3 | FB8: 1537217.6 | FC8: 1547402.9 | FD8: 1628511.8 | FE8: 1649960 | FF8: 1690302.6 | FG8: 1676517 | FH8: 1729604.5 | FI8: 1706954.4 | FJ8: 1689488.1 | FK8: 1672630.6 | FO8: =FK8-FJ8 -> -16857.479 | FS8: =FK8-FN8 -> 1672630.6 | FT8: =SUM($FJ8:FK8) -> 3362118.7
E9: AddOns | H9: =SUM(V9:Y9) -> 0 | L9: =SUM(AL9:AO9) -> 1284247 | M9: =SUM(AP9:AS9) -> 1338044.3 | N9: =SUM(AT9:AW9) -> 1412569.9 | O9: =SUM(AX9:BA9) -> 1568018.7 | AJ9: =SUM(DH9:DJ9) -> 283167.75 | AK9: =SUM(DK9:DM9) -> 289688.79 | AL9: =SUM(DN9:DP9) -> 308558.35 | AM9: =SUM(DQ9:DS9) -> 316546.78 | AN9: =SUM(DT9:DV9) -> 327240 | AO9: =SUM(DW9:DY9) -> 331901.87 | AP9: =SUM(DZ9:EB9) -> 325457.31 | AQ9: =OFFSET($DZ9,0,AQ$4)+OFFSET($EA9,0,AQ$4)+OFFSET($EB9,0,AQ$4) -> 325603.29 | AR9: =OFFSET($DZ9,0,AR$4)+OFFSET($EA9,0,AR$4)+OFFSET($EB9,0,AR$4) -> 339970.17 | AS9: =OFFSET($DZ9,0,AS$4)+OFFSET($EA9,0,AS$4)+OFFSET($EB9,0,AS$4) -> 347013.56 | AT9: =SUM(EL9:EN9) -> 335426.66 | AU9: =OFFSET($EL9,0,AU$4)+OFFSET($EM9,0,AU$4)+OFFSET($EN9,0,AU$4) -> 339342.55 | AV9: =OFFSET($EL9,0,AV$4)+OFFSET($EM9,0,AV$4)+OFFSET($EN9,0,AV$4) -> 368529.73 | AW9: =OFFSET($EL9,0,AW$4)+OFFSET($EM9,0,AW$4)+OFFSET($EN9,0,AW$4) -> 369270.93 | AX9: =SUM(EX9:EZ9) -> 373465.58 | AY9: =SUM(FA9:FC9) -> 376116.08 | AZ9: =SUM(FD9:FF9) -> 393616.64 | BA9: =SUM(FG9:FI9) -> 424820.45 | BF9: 499065 | CD9: 36859.29 | CE9: 44348.864 | CF9: 43639.913 | CG9: 44970.84 | CH9: 45780.697 | CI9: 50743.463 | CJ9: 48705.546 | CK9: 52394.197 | CL9: 57081.888 | CM9: 55048.636 | CN9: 56835.674 | CO9: 54750.02 | CP9: 62069.802 | CQ9: 57378.902 | CR9: 63279.561 | CS9: 62477.314 | CT9: 59353.216 | CU9: 57107.825 | CV9: 60740.504 | CW9: 59045.584 | CX9: 59229.911 | CY9: 55992.25 | CZ9: 63583.127 | DA9: 74498.473 | DB9: 74617.088 | DC9: 74820.536 | DD9: 74115.377 | DE9: 77672.938 | DF9: 78378.376 | DG9: 77683.002 | DH9: 84580.315 | DI9: 113345.31 | DJ9: 85242.12 | DK9: 87640.482 | DL9: 102842.86 | DM9: 99205.452 | DN9: 102385.1 | DO9: 102010.1 | DP9: 104163.14 | DQ9: 105466.17 | DR9: 105518.01 | DS9: 105562.6 | DT9: 106301.98 | DU9: 103742.32 | DV9: 117195.7 | DW9: 113559.1 | DX9: 112845.07 | DY9: 105497.7 | DZ9: 107727.63 | EA9: 108828.44 | EB9: 108901.25 | EC9: 107874.92 | ED9: 107164.95 | EE9: 110563.42 | EF9: 114057.54 | EG9: 112571.73 | EH9: 113340.9 | EI9: 116453.03 | EJ9: 116873.71 | EK9: 113686.82 | EL9: 110115.54 | EM9: 112345.63 | EN9: 112965.49 | EO9: 112636.17 | EP9: 111453.7 | EQ9: 115252.68 | ER9: 117996.57 | ES9: 119977.75 | ET9: 130555.41 | EU9: 121134.64 | EV9: 124189.01 | EW9: 123947.28 | EX9: 127027.11 | EY9: 120080.45 | EZ9: 126358.02 | FA9: 126480.71 | FB9: 124680.07 | FC9: 124955.29 | FD9: 126338.74 | FE9: 133037.76 | FF9: 134240.14 | FG9: 142709.25 | FH9: 145014.65 | FI9: 137096.55 | FJ9: 135720.34 | FK9: 148231.81 | FO9: =FK9-FJ9 -> 12511.47 | FS9: =FK9-FN9 -> 148231.81 | FT9: =SUM($FJ9:FK9) -> 283952.16
E10: Variable | H10: =SUM(V10:Y10) -> 0 | L10: =SUM(AL10:AO10) -> 1428728.8 | M10: =SUM(AP10:AS10) -> 1615107.7 | N10: =SUM(AT10:AW10) -> 1652962.7 | O10: =SUM(AX10:BA10) -> 1855901.6 | AJ10: =SUM(DH10:DJ10) -> 331899.66 | AK10: =SUM(DK10:DM10) -> 377831.98 | AL10: =SUM(DN10:DP10) -> 250233.31 | AM10: =SUM(DQ10:DS10) -> 304123.1 | AN10: =SUM(DT10:DV10) -> 394740.8 | AO10: =SUM(DW10:DY10) -> 479631.63 | AP10: =SUM(DZ10:EB10) -> 372003.41 | AQ10: =OFFSET($DZ10,0,AQ$4)+OFFSET($EA10,0,AQ$4)+OFFSET($EB10,0,AQ$4) -> 353720.92 | AR10: =OFFSET($DZ10,0,AR$4)+OFFSET($EA10,0,AR$4)+OFFSET($EB10,0,AR$4) -> 418521.96 | AS10: =OFFSET($DZ10,0,AS$4)+OFFSET($EA10,0,AS$4)+OFFSET($EB10,0,AS$4) -> 470861.41 | AT10: =SUM(EL10:EN10) -> 412730.42 | AU10: =OFFSET($EL10,0,AU$4)+OFFSET($EM10,0,AU$4)+OFFSET($EN10,0,AU$4) -> 413770.95 | AV10: =OFFSET($EL10,0,AV$4)+OFFSET($EM10,0,AV$4)+OFFSET($EN10,0,AV$4) -> 390449.89 | AW10: =OFFSET($EL10,0,AW$4)+OFFSET($EM10,0,AW$4)+OFFSET($EN10,0,AW$4) -> 436011.47 | AX10: =SUM(EX10:EZ10) -> 399003.81 | AY10: =SUM(FA10:FC10) -> 406872.76 | AZ10: =SUM(FD10:FF10) -> 525545.57 | BA10: =SUM(FG10:FI10) -> 524479.43 | CD10: 115265.06 | CE10: 73400.298 | CF10: 110520.03 | CG10: 78908.288 | CH10: 73446.58 | CI10: 57700.747 | CJ10: 63796.568 | CK10: 68594.054 | CL10: 110272.22 | CM10: 114969.85 | CN10: 109016.1 | CO10: 148342.53 | CP10: 134624.61 | CQ10: 119228.13 | CR10: 116947.82 | CS10: 87540.765 | CT10: 100803.65 | CU10: 85470.339 | CV10: 95643.46 | CW10: 85534.126 | CX10: 54786.481 | CY10: 63422.039 | CZ10: 51677.73 | DA10: 52458.945 | DB10: 59966.895 | DC10: 70716.794 | DD10: 69099.117 | DE10: 89731.045 | DF10: 95975.835 | DG10: 89080.428 | DH10: 93721.34 | DI10: 108308.03 | DJ10: 129870.29 | DK10: 111176.15 | DL10: 119661.18 | DM10: 146994.65 | DN10: 95809.609 | DO10: 100039.77 | DP10: 54383.936 | DQ10: 94127.176 | DR10: 107269.93 | DS10: 102726 | DT10: 119312.79 | DU10: 141159.21 | DV10: 134268.8 | DW10: 125073.6 | DX10: 134559.81 | DY10: 219998.22 | DZ10: 121179.36 | EA10: 135522.96 | EB10: 115301.09 | EC10: 138343.65 | ED10: 104276.51 | EE10: 111100.76 | EF10: 135028.2 | EG10: 124028.09 | EH10: 159465.67 | EI10: 116480.37 | EJ10: 146149.99 | EK10: 208231.04 | EL10: 124658.72 | EM10: 133202.46 | EN10: 154869.24 | EO10: 183304.36 | EP10: 127767.04 | EQ10: 102699.56 | ER10: 112158.63 | ES10: 128419.14 | ET10: 149872.12 | EU10: 132883.23 | EV10: 160801.78 | EW10: 142326.47 | EX10: 150188.56 | EY10: 125467.55 | EZ10: 123347.7 | FA10: 133927.93 | FB10: 129671.2 | FC10: 143273.64 | FD10: 159021.78 | FE10: 172412.62 | FF10: 194111.17 | FG10: 173698.1 | FH10: 177777.09 | FI10: 173004.23 | FJ10: 162529.94 | FK10: 176515.8 | FO10: =FK10-FJ10 -> 13985.861 | FS10: =FK10-FN10 -> 176515.8 | FT10: =SUM($FJ10:FK10) -> 339045.73
E11: SIM Sales | H11: =SUM(V11:Y11) -> 0 | L11: =SUM(AL11:AO11) -> 937577.31 | M11: =SUM(AP11:AS11) -> 581736.07 | N11: =SUM(AT11:AW11) -> 821325.35 | O11: =SUM(AX11:BA11) -> 802927.44 | AJ11: =SUM(DH11:DJ11) -> 279239.17 | AK11: =SUM(DK11:DM11) -> 215711.05 | AL11: =SUM(DN11:DP11) -> 170534.04 | AM11: =SUM(DQ11:DS11) -> 279448.86 | AN11: =SUM(DT11:DV11) -> 237844.28 | AO11: =SUM(DW11:DY11) -> 249750.14 | AP11: =SUM(DZ11:EB11) -> 115763.7 | AQ11: =OFFSET($DZ11,0,AQ$4)+OFFSET($EA11,0,AQ$4)+OFFSET($EB11,0,AQ$4) -> 118022.66 | AR11: =OFFSET($DZ11,0,AR$4)+OFFSET($EA11,0,AR$4)+OFFSET($EB11,0,AR$4) -> 229393.18 | AS11: =OFFSET($DZ11,0,AS$4)+OFFSET($EA11,0,AS$4)+OFFSET($EB11,0,AS$4) -> 118556.53 | AT11: =SUM(EL11:EN11) -> 209862.3 | AU11: =OFFSET($EL11,0,AU$4)+OFFSET($EM11,0,AU$4)+OFFSET($EN11,0,AU$4) -> 171081.41 | AV11: =OFFSET($EL11,0,AV$4)+OFFSET($EM11,0,AV$4)+OFFSET($EN11,0,AV$4) -> 222837.8 | AW11: =OFFSET($EL11,0,AW$4)+OFFSET($EM11,0,AW$4)+OFFSET($EN11,0,AW$4) -> 217543.84 | AX11: =SUM(EX11:EZ11) -> 168953.57 | AY11: =SUM(FA11:FC11) -> 224202.27 | AZ11: =SUM(FD11:FF11) -> 152728.45 | BA11: =SUM(FG11:FI11) -> 257043.14 | CD11: 23289 | CE11: 27280 | CF11: 9861 | CG11: 49636.538 | CH11: 42450.077 | CI11: 35674 | CJ11: 34793.706 | CK11: 15896.612 | CL11: 7795.9174 | CM11: 14305 | CN11: 50115 | CO11: 35602 | CP11: 17402.333 | CQ11: 30416.103 | CR11: 14232 | CS11: 43714.435 | CT11: 14430.765 | CU11: 14993.349 | CV11: 10207.669 | CW11: 12104.249 | CX11: 42512.312 | CY11: 31461.706 | CZ11: 48191.385 | DA11: 23794.565 | DB11: 33359.074 | DC11: 20369.052 | DD11: 48529.665 | DE11: 105305.01 | DF11: 54637.385 | DG11: 91605.607 | DH11: 74803.47 | DI11: 85052.698 | DJ11: 119383 | DK11: 128326.36 | DL11: 87097.78 | DM11: 286.90206 | DN11: 64659.563 | DO11: 43112.054 | DP11: 62762.421 | DQ11: 100642.12 | DR11: 81576.157 | DS11: 97230.584 | DT11: 92647.184 | DU11: 60616.364 | DV11: 84580.73 | DW11: 44432.29 | DX11: 158784.3 | DY11: 46533.546 | DZ11: 16195.721 | EA11: 22588.916 | EB11: 76979.067 | EC11: 39040.245 | ED11: 21269.585 | EE11: 57712.828 | EF11: 96567.482 | EG11: 73396.968 | EH11: 59428.727 | EI11: 47781.628 | EJ11: 37356.638 | EK11: 33418.262 | EL11: 27919.988 | EM11: 74067.919 | EN11: 107874.39 | EO11: 46017.345 | EP11: 64850.202 | EQ11: 60213.863 | ER11: 65770.981 | ES11: 83570.394 | ET11: 73496.426 | EU11: 124709.57 | EV11: 51718.627 | EW11: 41115.648 | EX11: 48944.892 | EY11: 91540.353 | EZ11: 28468.33 | FA11: 95899.364 | FB11: 43342.372 | FC11: 84960.537 | FD11: 23607.711 | FE11: 41277.143 | FF11: 87843.597 | FG11: 86884.464 | FH11: 50115.492 | FI11: 120043.19 | FJ11: 78640.174 | FK11: 34327.932 | FO11: =FK11-FJ11 -> -44312.242 | FS11: =FK11-FN11 -> 34327.932 | FT11: =SUM($FJ11:FK11) -> 112968.11
E12: Launchpad | L12: =SUM(AL12:AO12) -> 0 | M12: =SUM(AP12:AS12) -> 42214.701 | N12: =SUM(AT12:AW12) -> 80939.47 | O12: =SUM(AX12:BA12) -> 5800 | AA12: =SUM(CG12:CI12) -> 0 | AJ12: =SUM(DH12:DJ12) -> 0 | AK12: =SUM(DK12:DM12) -> 0 | AL12: =SUM(DN12:DP12) -> 0 | AM12: =SUM(DQ12:DS12) -> 0 | AN12: =SUM(DT12:DV12) -> 0 | AO12: =SUM(DW12:DY12) -> 0 | AP12: =SUM(DZ12:EB12) -> 0 | AQ12: =OFFSET($DZ12,0,AQ$4)+OFFSET($EA12,0,AQ$4)+OFFSET($EB12,0,AQ$4) -> 6856.6718 | AR12: =OFFSET($DZ12,0,AR$4)+OFFSET($EA12,0,AR$4)+OFFSET($EB12,0,AR$4) -> 20519.793 | AS12: =OFFSET($DZ12,0,AS$4)+OFFSET($EA12,0,AS$4)+OFFSET($EB12,0,AS$4) -> 14838.236 | AT12: =SUM(EL12:EN12) -> 23578.326 | AU12: =OFFSET($EL12,0,AU$4)+OFFSET($EM12,0,AU$4)+OFFSET($EN12,0,AU$4) -> 22722.132 | AV12: =OFFSET($EL12,0,AV$4)+OFFSET($EM12,0,AV$4)+OFFSET($EN12,0,AV$4) -> 14887.358 | AW12: =OFFSET($EL12,0,AW$4)+OFFSET($EM12,0,AW$4)+OFFSET($EN12,0,AW$4) -> 19751.654 | AX12: =SUM(EX12:EZ12) -> 3000 | AY12: =SUM(FA12:FC12) -> 1600 | AZ12: =SUM(FD12:FF12) -> 0 | BA12: =SUM(FG12:FI12) -> 1200 | BR12: =$V12/3 -> 0 | BS12: =$V12/3 -> 0 | BT12: =$V12/3 -> 0 | BU12: =$W12/3 -> 0 | BV12: =$W12/3 -> 0 | BW12: =$W12/3 -> 0 | BX12: =$X12/3 -> 0 | BY12: =$X12/3 -> 0 | BZ12: =$X12/3 -> 0 | CA12: =$Y12/3 -> 0 | CB12: =$Y12/3 -> 0 | CC12: =$Y12/3 -> 0 | CD12: =$Y12/3 -> 0 | EE12: 6856.6718 | EF12: 6746.3506 | EG12: 6820.439 | EH12: 6953.0032 | EI12: 5024.3569 | EJ12: 4949.5379 | EK12: 4864.3413 | EL12: 7851.7911 | EM12: 7873.6906 | EN12: 7852.8444 | EO12: 7911.7828 | EP12: 7875.4042 | EQ12: 6934.9447 | ER12: 6887.3582 | ES12: 4000 | ET12: 4000 | EU12: 7829.1538 | EV12: 7922.5001 | EW12: 4000 | EX12: 1000 | EY12: 1000 | EZ12: 1000 | FA12: 1300 | FB12: 300 | FC12: 0 | FD12: 0 | FE12: 0 | FF12: 0 | FG12: 1200 | FH12: 0 | FI12: 0 | FJ12: 0 | FK12: 0 | FO12: =FK12-FJ12 -> 0 | FS12: =FK12-FN12 -> 0 | FT12: =SUM($FJ12:FK12) -> 0
E13: Hardware | F13: 3463000 | G13: =SUM(R13:U13) -> 2366877 | H13: =SUM(V13:Y13) -> 988091 | I13: =SUM(Z13:AC13) -> 1242439 | J13: =SUM(AD13:AG13) -> 1617692.9 | K13: =SUM(AH13:AK13) -> 1112186.6 | L13: =SUM(AL13:AO13) -> 1417113.5 | M13: =SUM(AP13:AS13) -> 1100085.6 | N13: =SUM(AT13:AW13) -> 762730.39 | O13: =SUM(AX13:BA13) -> 1154651.5 | P13: =FJ13 -> 35492.031 | R13: =SUM(BF13:BH13) -> 743655 | S13: =SUM(BI13:BK13) -> 371572 | T13: =SUM(BL13:BN13) -> 373641 | U13: =SUM(BO13:BQ13) -> 878009 | V13: =SUM(BR13:BT13) -> 128748 | W13: =SUM(BU13:BW13) -> 240084 | X13: =SUM(BX13:BZ13) -> 199978 | Y13: =SUM(CA13:CC13) -> 419281 | Z13: =SUM(CD13:CF13) -> 276645 | AA13: =SUM(CG13:CI13) -> 297568 | AB13: =SUM(CJ13:CL13) -> 366985 | AC13: =SUM(CM13:CO13) -> 301241 | AD13: =SUM(CP13:CR13) -> 457553 | AE13: =SUM(CS13:CU13) -> 690431 | AF13: =SUM(CV13:CX13) -> 259512.28 | AG13: =SUM(CY13:DA13) -> 210196.58 | AH13: =SUM(DB13:DD13) -> 232662.11 | AI13: =SUM(DE13:DG13) -> 309222.63 | AJ13: =SUM(DH13:DJ13) -> 413104.04 | AK13: =SUM(DK13:DM13) -> 157197.77 | AL13: =SUM(DN13:DP13) -> 241145.52 | AM13: =SUM(DQ13:DS13) -> 313656.01 | AN13: =SUM(DT13:DV13) -> 478260.9 | AO13: =SUM(DW13:DY13) -> 384051.08 | AP13: =SUM(DZ13:EB13) -> 208481.71 | AQ13: =OFFSET($DZ13,0,AQ$4)+OFFSET($EA13,0,AQ$4)+OFFSET($EB13,0,AQ$4) -> 285083.34 | AR13: =OFFSET($DZ13,0,AR$4)+OFFSET($EA13,0,AR$4)+OFFSET($EB13,0,AR$4) -> 226270.69 | AS13: =OFFSET($DZ13,0,AS$4)+OFFSET($EA13,0,AS$4)+OFFSET($EB13,0,AS$4) -> 380249.86 | AT13: =SUM(EL13:EN13) -> 241769.57 | AU13: =OFFSET($EL13,0,AU$4)+OFFSET($EM13,0,AU$4)+OFFSET($EN13,0,AU$4) -> 270294.94 | AV13: =OFFSET($EL13,0,AV$4)+OFFSET($EM13,0,AV$4)+OFFSET($EN13,0,AV$4) -> 111667.39 | AW13: =OFFSET($EL13,0,AW$4)+OFFSET($EM13,0,AW$4)+OFFSET($EN13,0,AW$4) -> 138998.49 | AX13: =SUM(EX13:EZ13) -> 185596.49 | AY13: =SUM(FA13:FC13) -> 241618.85 | AZ13: =SUM(FD13:FF13) -> 579986.7 | BA13: =SUM(FG13:FI13) -> 147449.46 | BB13: =SUM(FJ13:FL13) -> 41459.954 | BF13: 654126 | BG13: 11580 | BH13: 77949 | BI13: 57451 | BJ13: 255545 | BK13: 58576 | BL13: 57120 | BM13: 138179 | BN13: 178342 | BO13: 665930 | BP13: 146843 | BQ13: 65236 | BR13: 9430 | BS13: 48105 | BT13: 71213 | BU13: 157072 | BV13: 48958 | BW13: 34054 | BX13: 140299 | BY13: 20342 | BZ13: 39337 | CA13: 128471 | CB13: 16346 | CC13: 274464 | CD13: 129508 | CE13: 13152 | CF13: 133985 | CG13: 264786 | CH13: 18236 | CI13: 14546 | CJ13: 93059 | CK13: 68613 | CL13: 205313 | CM13: 62214 | CN13: 133730 | CO13: 105297 | CP13: 303450 | CQ13: 32485 | CR13: 121618 | CS13: 116168 | CT13: 330962 | CU13: 243301 | CV13: 27193 | CW13: 2790.5 | CX13: 229528.78 | CY13: 150115.17 | CZ13: =30356.92-0.09 -> 30356.83 | DA13: 29724.58 | DB13: 183477.43 | DC13: =35596.47-0.09 -> 35596.38 | DD13: 13588.3 | DE13: 12172.14 | DF13: 27121.33 | DG13: 269929.16 | DH13: 244135.2 | DI13: 128273.85 | DJ13: 40694.99 | DK13: 27195.9 | DL13: 24129.56 | DM13: 105872.31 | DN13: 35574.36 | DO13: 14132.3 | DP13: 191438.86 | DQ13: 138850.63 | DR13: 162944.53 | DS13: 11860.85 | DT13: 25840.52 | DU13: 147417.4 | DV13: 305002.98 | DW13: 14502.12 | DX13: 50499 | DY13: 319049.96 | DZ13: 23688.56 | EA13: 5833.56 | EB13: 178959.59 | EC13: 63193.34 | ED13: 64965.84 | EE13: 156924.16 | EF13: 132446.09 | EG13: 81073.888 | EH13: 12750.715 | EI13: 152529.23 | EJ13: 126874.81 | EK13: 100845.82 | EL13: 18673.033 | EM13: 44687.518 | EN13: 178409.02 | EO13: 16172.264 | EP13: 116334.87 | EQ13: 137787.8 | ER13: 26635.98 | ES13: 66614.784 | ET13: 18416.63 | EU13: 33514.747 | EV13: 98079.36 | EW13: 7404.38 | EX13: 5699.8505 | EY13: 171809.88 | EZ13: 8086.7602 | FA13: 54512.492 | FB13: 176384.02 | FC13: 10722.343 | FD13: 194362.9 | FE13: 140511.83 | FF13: 245111.98 | FG13: 22686.995 | FH13: 5096.3657 | FI13: 119666.1 | FJ13: 35492.031 | FK13: 5967.9228 | FN13: ='Financial plan'!EZ18 -> 94532.828 | FO13: =FK13-FJ13 -> -29524.109 | FP13: =FK13-FN13 -> -88564.905 | FQ13: =FL13-#REF! -> #REF! | FR13: =FM13-FO13 -> 29524.109 | FS13: =FK13-FN13 -> -88564.905 | FT13: =SUM($FJ13:FK13) -> 41459.954 | FU13: =SUM('Financial plan'!$EY18:EZ18) -> 189065.66 | FV13: =FT13-FU13 -> -147605.7
E14: Consultancy | F14: 173000 | G14: =SUM(R14:U14) -> 151312 | H14: =SUM(V14:Y14) -> 166181 | I14: =SUM(Z14:AC14) -> 117066 | J14: =SUM(AD14:AG14) -> 532586.26 | K14: =SUM(AH14:AK14) -> 319517.41 | L14: =SUM(AL14:AO14) -> 537797.18 | M14: =SUM(AP14:AS14) -> 749820.46 | N14: =SUM(AT14:AW14) -> 878350.6 | O14: =SUM(AX14:BA14) -> 852881.87 | P14: =FJ14 -> 17700.495 | R14: =SUM(BF14:BH14) -> 42801 | S14: =SUM(BI14:BK14) -> 52523 | T14: =SUM(BL14:BN14) -> 45989 | U14: =SUM(BO14:BQ14) -> 9999 | V14: =SUM(BR14:BT14) -> 25890 | W14: =SUM(BU14:BW14) -> 3100 | X14: =SUM(BX14:BZ14) -> 68820 | Y14: =SUM(CA14:CC14) -> 68371 | Z14: =SUM(CD14:CF14) -> 17525 | AA14: =SUM(CG14:CI14) -> 8596 | AB14: =SUM(CJ14:CL14) -> 17440 | AC14: =SUM(CM14:CO14) -> 73505 | AD14: =SUM(CP14:CR14) -> 72280 | AE14: =SUM(CS14:CU14) -> 97187 | AF14: =SUM(CV14:CX14) -> 154889.26 | AG14: =SUM(CY14:DA14) -> 208230 | AH14: =SUM(DB14:DD14) -> 101944.35 | AI14: =SUM(DE14:DG14) -> 98946.47 | AJ14: =SUM(DH14:DJ14) -> 46289.61 | AK14: =SUM(DK14:DM14) -> 72336.98 | AL14: =SUM(DN14:DP14) -> 91170.09 | AM14: =SUM(DQ14:DS14) -> 144447.63 | AN14: =SUM(DT14:DV14) -> 166988.99 | AO14: =SUM(DW14:DY14) -> 135190.47 | AP14: =SUM(DZ14:EB14) -> 104909.41 | AQ14: =OFFSET($DZ14,0,AQ$4)+OFFSET($EA14,0,AQ$4)+OFFSET($EB14,0,AQ$4) -> 131801.87 | AR14: =OFFSET($DZ14,0,AR$4)+OFFSET($EA14,0,AR$4)+OFFSET($EB14,0,AR$4) -> 219953.36 | AS14: =OFFSET($DZ14,0,AS$4)+OFFSET($EA14,0,AS$4)+OFFSET($EB14,0,AS$4) -> 293155.82 | AT14: =SUM(EL14:EN14) -> 279442.49 | AU14: =OFFSET($EL14,0,AU$4)+OFFSET($EM14,0,AU$4)+OFFSET($EN14,0,AU$4) -> 287024.3 | AV14: =OFFSET($EL14,0,AV$4)+OFFSET($EM14,0,AV$4)+OFFSET($EN14,0,AV$4) -> 297140.74 | AW14: =OFFSET($EL14,0,AW$4)+OFFSET($EM14,0,AW$4)+OFFSET($EN14,0,AW$4) -> 14743.069 | AX14: =SUM(EX14:EZ14) -> 221862.7 | AY14: =SUM(FA14:FC14) -> 175682.49 | AZ14: =SUM(FD14:FF14) -> 224583.26 | BA14: =SUM(FG14:FI14) -> 230753.41 | BB14: =SUM(FJ14:FL14) -> 27768.797 | BF14: 10000 | BG14: 12937 | BH14: 19864 | BI14: 20159 | BJ14: 9575 | BK14: 22789 | BL14: 10960 | BM14: 15029 | BN14: 20000 | BO14: 8333 | BP14: 833 | BQ14: 833 | BR14: 17364 | BS14: 0 | BT14: 8526 | BU14: 0 | BV14: 3100 | BW14: 0 | BX14: 43231 | BY14: 8500 | BZ14: 17089 | CA14: 27493 | CB14: 37878 | CC14: 3000 | CD14: 1500 | CE14: 16025 | CF14: 0 | CG14: 0 | CH14: 288 | CI14: 8308 | CJ14: 0 | CK14: 10582 | CL14: 6858 | CM14: 30100 | CN14: =1000+10000 -> 11000 | CO14: 32405 | CP14: 7581 | CQ14: 46547 | CR14: 18152 | CS14: 29327 | CT14: 27211 | CU14: 40649 | CV14: 53633 | CW14: 51256.26 | CX14: 50000 | CY14: 75707.83 | CZ14: 67025 | DA14: 65497.17 | DB14: 40000.28 | DC14: 40000 | DD14: 21944.07 | DE14: 30182.6 | DF14: 31415.43 | DG14: 37348.44 | DH14: 12811.89 | DI14: 3986.54 | DJ14: 29491.18 | DK14: 7509.78 | DL14: 14039.72 | DM14: 50787.48 | DN14: 9634.47 | DO14: 10864.91 | DP14: 70670.71 | DQ14: 49612.77 | DR14: 79154.94 | DS14: 15679.92 | DT14: 13657.19 | DU14: 44891.384 | DV14: 108440.42 | DW14: 25877.37 | DX14: 72782.48 | DY14: 36530.62 | DZ14: 27724.44 | EA14: 23263.95 | EB14: 53921.02 | EC14: 23160.78 | ED14: 76654.2 | EE14: 31986.89 | EF14: 28256.076 | EG14: 57130.256 | EH14: 134567.02 | EI14: 80414.973 | EJ14: 75914.929 | EK14: 136825.92 | EL14: 76987.468 | EM14: 90733.98 | EN14: 111721.04 | EO14: 29006.563 | EP14: 148282.31 | EQ14: 109735.43 | ER14: 104906.03 | ES14: 114396.43 | ET14: 77838.281 | EU14: 41890.712 | EV14: 28596.837 | EW14: -55744.48 | EX14: 65568.137 | EY14: 92252.94 | EZ14: 64041.624 | FA14: 51555.678 | FB14: 42881.247 | FC14: 81245.563 | FD14: 79485.141 | FE14: 84359.948 | FF14: 60738.173 | FG14: 65842.484 | FH14: 83846.499 | FI14: 81064.431 | FJ14: 17700.495 | FK14: 10068.302 | FN14: ='Financial plan'!EZ19 -> 45000 | FO14: =FK14-FJ14 -> -7632.1926 | FP14: =FK14-FN14 -> -34931.698 | FQ14: =FL14-#REF! -> #REF! | FR14: =FM14-FO14 -> 7632.1926 | FS14: =FK14-FN14 -> -34931.698 | FT14: =SUM($FJ14:FK14) -> 27768.797 | FU14: =SUM('Financial plan'!$EY19:EZ19) -> 90000 | FV14: =FT14-FU14 -> -62231.203
E15: General Consultancy | CD15: 1500 | CE15: 16025 | CF15: 0 | CG15: 0 | CH15: 288 | CI15: 8308 | CJ15: 0 | CK15: 10582 | CL15: 6858 | CM15: 30100 | CN15: 11000 | CO15: 32405 | CP15: 7581 | CQ15: 46547 | CR15: 18152 | CS15: 29327 | CT15: 27211 | CU15: 40649 | CV15: 53633.572 | CW15: 51256.26 | CX15: 50000 | CY15: 75707.831 | CZ15: 67025 | DA15: 65497.17 | DB15: 40000.28 | DC15: 40000 | DD15: -10469.436 | DE15: 6995.2635 | DF15: 18946.8 | DG15: 37348.444 | DH15: 12811.892 | DI15: 0 | DJ15: 24150 | DK15: 0 | DL15: 7707.51 | DM15: 0 | DN15: 0 | DO15: 0 | DP15: 20.24 | DR15: 15854.5 | DU15: 12406.01 | EC15: 2200 | FA15: 3801.3223 | FO15: =FK15-FJ15 -> 0 | FP15: =FK15-FN15 -> 0 | FQ15: =FL15-#REF! -> #REF! | FR15: =FM15-FO15 -> 0 | FS15: =FK15-FN15 -> 0 | FT15: =SUM($FJ15:FK15) -> 0
E16: Deployment Services | P16: =FJ16 -> 2259.2952 | AZ16: =SUM(FD16:FG16) -> 40576.867 | BB16: =SUM(FJ16:FL16) -> 4053.8648 | CD16: 0 | CE16: 0 | CF16: 0 | CG16: 0 | CH16: 0 | CI16: 0 | CJ16: 0 | CK16: 0 | CL16: 0 | CM16: 0 | CN16: 0 | CO16: 0 | CP16: 0 | CQ16: 0 | CR16: 0 | CS16: 0 | CT16: 0 | CU16: 0 | CV16: 0 | CW16: 0 | CX16: 0 | CY16: 0 | CZ16: 0 | DA16: 0 | DB16: 0 | DC16: 0 | DD16: 32413.092 | DE16: 23187.34 | DF16: 12469.034 | DG16: 0 | DH16: -1.8189894e-12 | DI16: 3986.537 | DJ16: 5341.1812 | DK16: 7509.7799 | DL16: 4132.8898 | DM16: 12069.793 | DN16: 5511.619 | DO16: 10864.909 | DP16: 8264.1201 | DQ16: 1792.28 | DR16: 17334.931 | DS16: 4516.1613 | DT16: 7878.1 | DU16: 13642.28 | DV16: 13924.119 | DW16: 18312.24 | DX16: 9205.8079 | DY16: 16697.674 | DZ16: 19168.4 | EA16: 6512.6125 | EB16: 3730.1279 | EC16: 7363.3933 | ED16: 2275.9012 | EE16: 1908.9262 | EF16: 14439.366 | EG16: 5060.5621 | EH16: 11540.3 | EI16: 11896.457 | EJ16: 2165.9 | EK16: 36612.435 | EL16: 455.3202 | EM16: 14527.95 | EN16: 2809.5048 | EO16: 3733.0272 | EP16: 14615.479 | EQ16: 6177.2445 | ER16: 14530.97 | ES16: 16602.27 | ET16: =6205.802403313 -> 6205.8024 | EU16: 4745.3868 | EV16: 9414.48 | EW16: 4080.87 | EX16: 10280 | EY16: 4907.6078 | EZ16: =7185.22654141451+15000 -> 22185.227 | FA16: 3982.4 | FB16: 1931.3745 | FC16: =2014.12455963009+22500 -> 24514.125 | FD16: =11472.7883077621+2156.85+16302.46 -> 29932.098 | FE16: 2079.7384 | FF16: 924.36051 | FG16: 7640.67 | FH16: 11328.987 | FI16: =2605+1076 -> 3681 | FJ16: 2259.2952 | FK16: 1794.5695 | FO16: =FK16-FJ16 -> -464.72571 | FP16: =FK16-FN16 -> 1794.5695 | FQ16: =FL16-#REF! -> #REF! | FR16: =FM16-FO16 -> 464.72571 | FS16: =FK16-FN16 -> 1794.5695 | FT16: =SUM($FJ16:FK16) -> 4053.8648
E17: Migration Services | P17: =FJ17 -> 0 | AZ17: =SUM(FD17:FG17) -> 0 | BB17: =SUM(FJ17:FL17) -> 0 | ES17: 19320.456 | ET17: 3785.1656 | EU17: 20000 | EV17: 0 | EZ17: 0 | FA17: 9015.73 | FB17: 1500 | FC17: 0 | FE17: 0 | FH17: 10250 | FJ17: 0 | FK17: 0 | FO17: =FK17-FJ17 -> 0 | FP17: =FK17-FN17 -> 0 | FQ17: =FL17-#REF! -> #REF! | FR17: =FM17-FO17 -> 0 | FS17: =FK17-FN17 -> 0 | FT17: =SUM($FJ17:FK17) -> 0
E18: Software Licensing Service | P18: =FJ18 -> 0 | AZ18: =SUM(FD18:FG18) -> 20209.931 | BB18: =SUM(FJ18:FL18) -> 0 | EK18: 11843.044 | EO18: 16779.516 | EP18: 0 | EQ18: 0 | ER18: 0 | ES18: 0 | FD18: 7574.2674 | FE18: 12635.664 | FO18: =FK18-FJ18 -> 0 | FP18: =FK18-FN18 -> 0 | FQ18: =FL18-#REF! -> #REF! | FR18: =FM18-FO18 -> 0 | FS18: =FK18-FN18 -> 0 | FT18: =SUM($FJ18:FK18) -> 0
E19: Device Design | P19: =FJ19 -> 0 | AZ19: =SUM(FD19:FG19) -> 15543.78 | BB19: =SUM(FJ19:FL19) -> 0 | CD19: 0 | CE19: 0 | CF19: 0 | CG19: 0 | CH19: 0 | CI19: 0 | CJ19: 0 | CK19: 0 | CL19: 0 | CM19: 0 | CN19: 0 | CO19: 0 | CP19: 0 | CQ19: 0 | CR19: 0 | CS19: 0 | CT19: 0 | CU19: 0 | CV19: 0 | CW19: 0 | CX19: 0 | CY19: 0 | CZ19: 0 | DA19: 0 | DB19: 0 | DC19: 0 | DD19: 0 | DE19: 0 | DF19: 0 | DG19: 0 | DH19: 0 | DI19: 0 | DJ19: 0 | DK19: 0 | DL19: -7.2759576e-12 | DM19: 38717.69 | DN19: 0 | DO19: 0 | DP19: 60088.42 | DR19: 28466.546 | DS19: 5600 | DU19: 8400 | DV19: 33434.848 | DX19: 54262.96 | DY19: 18756.366 | DZ19: 3364.3183 | EA19: 15841.811 | EB19: 13678.378 | EC19: 9907.56 | ED19: 44009.465 | EE19: 6042.36 | EF19: 4000 | EG19: 6474.26 | EH19: 40745.3 | EI19: 0 | EJ19: 1146.7085 | EK19: 9338.2086 | EL19: 0 | EM19: 0 | EN19: 25000 | EP19: 10468.994 | EQ19: 37116.698 | ER19: =23369.4812214799+6219.77 -> 29589.251 | ES19: 18403 | EU19: 3063.3231 | EW19: 5000 | EY19: 51016.436 | FD19: 15543.78 | FE19: 0 | FO19: =FK19-FJ19 -> 0 | FP19: =FK19-FN19 -> 0 | FQ19: =FL19-#REF! -> #REF! | FR19: =FM19-FO19 -> 0 | FS19: =FK19-FN19 -> 0 | FT19: =SUM($FJ19:FK19) -> 0
E20: IOT Advisory Services | P20: =FJ20 -> 4316.1994 | AZ20: =SUM(FD20:FG20) -> 126971.08 | BB20: =SUM(FJ20:FL20) -> 8589.9319 | CD20: 0 | CE20: 0 | CF20: 0 | CG20: 0 | CH20: 0 | CI20: 0 | CJ20: 0 | CK20: 0 | CL20: 0 | CM20: 0 | CN20: 0 | CO20: 0 | CP20: 0 | CQ20: 0 | CR20: 0 | CS20: 0 | CT20: 0 | CU20: 0 | CV20: 0 | CW20: 0 | CX20: 0 | CY20: 0 | CZ20: 0 | DA20: 0 | DB20: 0 | DC20: 0 | DD20: 0 | DE20: 0 | DF20: 0 | DG20: 0 | DH20: 0 | DI20: 0 | DJ20: 0 | DK20: 0 | DL20: 2199.32 | DM20: 0 | DN20: 4122.85 | DO20: 0 | DP20: 2297.93 | DQ20: 9254.82 | DR20: 7980.92 | DS20: 5563.76 | DT20: 5779.08 | DU20: 5789.47 | DV20: 6035.6 | DW20: 7565.1 | DX20: 9313.71 | DY20: 1000 | DZ20: 5272.38 | EA20: 909.52819 | EB20: 30340.89 | EC20: 3689.8247 | ED20: 30368.83 | EE20: 18142.89 | EF20: 4681.72 | EG20: 35755.803 | EH20: 11544.1 | EI20: 8063.3305 | EJ20: 11629.683 | EK20: 13078.083 | EL20: 16563.25 | EM20: 14376.744 | EN20: 15721.417 | EO20: 1312.0775 | EQ20: 3150 | ER20: 1000 | ET20: 7610.4655 | EU20: 7620.2123 | EV20: 10109.34 | EW20: 7746.8703 | EX20: 22201.701 | EY20: 7814.628 | EZ20: =6205.86619233899+7645.76 -> 13851.626 | FA20: 7603.931 | FB20: 12589.983 | FC20: 29500.406 | FE20: 86043.574 | FF20: 30244.577 | FG20: 10682.929 | FH20: 7783.3664 | FI20: 29383.194 | FJ20: 4316.1994 | FK20: 4273.7325 | FO20: =FK20-FJ20 -> -42.46688 | FP20: =FK20-FN20 -> 4273.7325 | FQ20: =FL20-#REF! -> #REF! | FR20: =FM20-FO20 -> 42.46688 | FS20: =FK20-FN20 -> 4273.7325 | FT20: =SUM($FJ20:FK20) -> 8589.9319
E21: Device Certification Services | P21: =FJ21 -> 0 | AZ21: =SUM(FD21:FG21) -> 0 | BB21: =SUM(FJ21:FL21) -> 0 | DR21: 9518.04 | DU21: 4653.62 | DV21: 11009.17 | EG21: 9839.6 | EH21: 11205.2 | EO21: 0 | FO21: =FK21-FJ21 -> 0 | FP21: =FK21-FN21 -> 0 | FQ21: =FL21-#REF! -> #REF! | FR21: =FM21-FO21 -> 0 | FS21: =FK21-FN21 -> 0 | FT21: =SUM($FJ21:FK21) -> 0
E22: Interconnect | P22: =FJ22 -> 0 | AZ22: =SUM(FD22:FG22) -> 100398.11 | BB22: =SUM(FJ22:FL22) -> 0 | CD22: 0 | CE22: 0 | CF22: 0 | CG22: 0 | CH22: 0 | CI22: 0 | CJ22: 0 | CK22: 0 | CL22: 0 | CM22: 0 | CN22: 0 | CO22: 0 | CP22: 0 | CQ22: 0 | CR22: 0 | CS22: 0 | CT22: 0 | CU22: 0 | CV22: 0 | CW22: 0 | CX22: 0 | CY22: 0 | CZ22: 0 | DA22: 0 | DB22: 0 | DC22: 0 | DD22: 0 | DE22: 0 | DF22: 0 | DG22: 0 | DH22: 0 | DI22: 0 | DJ22: 0 | DK22: 0 | DL22: 0 | DM22: -2.9132252e-13 | DN22: 0 | DO22: 0 | DP22: 0 | DQ22: 38565.67 | DV22: 44036.679 | EB22: 6171.62 | EE22: 5892.71 | EF22: 5134.99 | EH22: 59532.1 | EI22: 60455.186 | EJ22: 60972.67 | EK22: 59497.589 | EL22: 58746.152 | EM22: 58444.205 | EN22: 58502.622 | EP22: 120586.73 | EQ22: 59980.513 | ER22: 59785.807 | ES22: 60070.817 | ET22: 60236.847 | EV22: 9073.02 | EW22: -75072.217 | EX22: 28900.831 | EY22: 28514.268 | EZ22: 27704.755 | FA22: 27152.298 | FB22: 26715.191 | FC22: 26356.032 | FD22: 26434.99 | FF22: 26444.236 | FG22: 47518.886 | FH22: 48394.427 | FI22: 48000.368 | FO22: =FK22-FJ22 -> 0 | FP22: =FK22-FN22 -> 0 | FQ22: =FL22-#REF! -> #REF! | FR22: =FM22-FO22 -> 0 | FS22: =FK22-FN22 -> 0 | FT22: =SUM($FJ22:FK22) -> 0
E23: VPN Set Up Fees | P23: =FJ23 -> 4000 | AZ23: =SUM(FD23:FG23) -> 0 | BB23: =SUM(FJ23:FL23) -> 4000 | EK23: 6456.5588 | EL23: 1222.75 | EM23: 3385.08 | EN23: 9687.5 | EO23: 7181.943 | EP23: 2611.1058 | EQ23: 3310.9724 | EU23: 6461.79 | EW23: 2500 | EX23: 4185.57 | EZ23: 300.02 | FB23: 144.69816 | FC23: 875 | FH23: 2964.7183 | FJ23: 4000 | FO23: =FK23-FJ23 -> -4000 | FP23: =FK23-FN23 -> 0 | FQ23: =FL23-#REF! -> #REF! | FR23: =FM23-FO23 -> 4000 | FS23: =FK23-FN23 -> 0 | FT23: =SUM($FJ23:FK23) -> 4000
E24: Recurring Professional Services | P24: =FJ24 -> 7125 | BB24: =SUM(FJ24:FL24) -> 11125 | FF24: 3125 | FG24: 0 | FH24: 3125 | FJ24: 7125 | FK24: 4000 | FO24: =FK24-FJ24 -> -3125 | FP24: =FK24-FN24 -> 4000 | FQ24: =FL24-#REF! -> #REF! | FR24: =FM24-FO24 -> 3125 | FS24: =FK24-FN24 -> 4000 | FT24: =SUM($FJ24:FK24) -> 11125
C25: Total Revenue | F25: =SUM(F13:F14,F7) -> 8879000 | G25: =SUM(G13:G14,G7) -> 9335683 | H25: =SUM(H13:H14,H7) -> 9716714 | I25: =SUM(I13:I14,I7) -> 12497272 | J25: =SUM(J13:J14,J7) -> 14813334 | K25: =SUM(K13:K14,K7) -> 16668428 | L25: =SUM(L13:L14,L7) -> 21796862 | M25: =SUM(M13:M14,M7) -> 23972186 | N25: =SUM(AT25:AW25) -> 24551108 | O25: =SUM(AX25:BA25) -> 25616577 | P25: =FJ25 -> 2119571.1 | R25: =SUM(R13:R14,R7) -> 2290498 | S25: =SUM(S13:S14,S7) -> 2085171 | T25: =SUM(T13:T14,T7) -> 2222899 | U25: =SUM(U13:U14,U7) -> 2737115 | V25: =SUM(V13:V14,V7) -> 2079727 | W25: =SUM(W13:W14,W7) -> 2216356 | X25: =SUM(X13:X14,X7) -> 2538926 | Y25: =SUM(Y13:Y14,Y7) -> 2881705 | ... AS25: =SUM(AS13:AS14,AS7) -> 6335526.9 | AT25: =SUM(EL25:EN25) -> 6328765.7 | AU25: =OFFSET($EL25,0,AU$4)+OFFSET($EM25,0,AU$4)+OFFSET($EN25,0,AU$4) -> 6334930.9 | AV25: =OFFSET($EL25,0,AV$4)+OFFSET($EM25,0,AV$4)+OFFSET($EN25,0,AV$4) -> 6068776.3 | AW25: =OFFSET($EL25,0,AW$4)+OFFSET($EM25,0,AW$4)+OFFSET($EN25,0,AW$4) -> 5818635.5 | AX25: =SUM(EX25:EZ25) -> 6028427.8 | AY25: =SUM(FA25:FC25) -> 6044092.3 | AZ25: =SUM(FD25:FF25) -> 6845234.9 | BA25: =SUM(FG25:FI25) -> 6698821.8 | BB25: =SUM(FJ25:FL25) -> 4167313.4 | BF25: =SUM(BF13:BF14,BF7) -> 1163191 | BG25: =SUM(BG13:BG14,BG7) -> 495678 | BH25: =SUM(BH13:BH14,BH7) -> 631629 | BI25: =SUM(BI13:BI14,BI7) -> 621618 | BJ25: =SUM(BJ13:BJ14,BJ7) -> 838345 | BK25: =SUM(BK13:BK14,BK7) -> 625208 | BL25: =SUM(BL13:BL14,BL7) -> 637785 | BM25: =SUM(BM13:BM14,BM7) -> 780253 | ... FK25: =SUM(FK13:FK14,FK7) -> 2047742.4 | FN25: ='Financial plan'!EZ21 -> 2274341.5 | FO25: =FK25-FJ25 -> -71828.691 | FP25: =FK25-FN25 -> -226599.15 | FQ25: =FL25-#REF! -> #REF! | FR25: =FM25-FO25 -> 71828.691 | FS25: =FK25-FN25 -> -226599.15 | FT25: =SUM($FJ25:FK25) -> 4167313.4 | FU25: =SUM('Financial plan'!$EY21:EZ21) -> 4548683.1 | FV25: =FT25-FU25 -> -381369.62
P26: =FJ26 -> 0 | AZ26: =SUM(FD26:FG26) -> 0 | BB26: =FJ26 -> 0
D27: Cost of sales | P27: =FJ27 -> 0 | BB27: =FJ27 -> 0
E28: Managed services | F28: =F33-F7 -> -2971000 | G28: =SUM(R28:U28) -> -3832592 | H28: =SUM(V28:Y28) -> -3774353 | I28: =SUM(Z28:AC28) -> -6409124 | J28: =SUM(AD28:AG28) -> -6501073.6 | K28: =SUM(AH28:AK28) -> -7814619.7 | L28: =SUM(AL28:AO28) -> -10526450 | M28: =SUM(AP28:AS28) -> -10765425 | N28: =SUM(AT28:AW28) -> -11705674 | O28: =SUM(AX28:BA28) -> -12397390 | P28: =SUM($FJ28:FK28) -> -2079882.3 | R28: =SUM(BF28:BH28) -> -903401 | S28: =SUM(BI28:BK28) -> -1058983 | T28: =SUM(BL28:BN28) -> -1041368 | U28: =SUM(BO28:BQ28) -> -828840 | V28: =SUM(BR28:BT28) -> -792925 | W28: =SUM(BU28:BW28) -> -928848 | X28: =SUM(BX28:BZ28) -> -1071997 | Y28: =SUM(CA28:CC28) -> -980583 | Z28: =SUM(CD28:CG28) -> -1770106 | AA28: =SUM(CG28:CI28) -> -1466428 | AB28: =SUM(CJ28:CL28) -> -1559480 | AC28: =SUM(CM28:CO28) -> -1613110 | AD28: =SUM(CP28:CR28) -> -1704857 | AE28: =SUM(CS28:CU28) -> -1640594 | AF28: =SUM(CV28:CX28) -> -1567939.5 | AG28: =SUM(CY28:DA28) -> -1587683.1 | AH28: =SUM(DB28:DD28) -> -1601546.6 | AI28: =SUM(DE28:DG28) -> -1835852 | AJ28: =SUM(DH28:DJ28) -> -2135067.5 | AK28: =SUM(DK28:DM28) -> -2242153.6 | AL28: =SUM(DN28:DP28) -> -2234767.7 | AM28: =SUM(DQ28:DS28) -> -2606385.3 | AN28: =SUM(DT28:DV28) -> -2888517.1 | AO28: =SUM(DW28:DY28) -> -2796780.1 | AP28: =SUM(DZ28:EB28) -> -2566593.4 | AQ28: =OFFSET($DZ28,0,AQ$4)+OFFSET($EA28,0,AQ$4)+OFFSET($EB28,0,AQ$4) -> -2670701.7 | AR28: =OFFSET($DZ28,0,AR$4)+OFFSET($EA28,0,AR$4)+OFFSET($EB28,0,AR$4) -> -2797121.8 | AS28: =OFFSET($DZ28,0,AS$4)+OFFSET($EA28,0,AS$4)+OFFSET($EB28,0,AS$4) -> -2731008.1 | AT28: =SUM(EL28:EN28) -> -2779859.6 | AU28: =OFFSET($EL28,0,AU$4)+OFFSET($EM28,0,AU$4)+OFFSET($EN28,0,AU$4) -> -2881176.9 | AV28: =OFFSET($EL28,0,AV$4)+OFFSET($EM28,0,AV$4)+OFFSET($EN28,0,AV$4) -> -2951614.7 | AW28: =OFFSET($EL28,0,AW$4)+OFFSET($EM28,0,AW$4)+OFFSET($EN28,0,AW$4) -> -3093023.1 | AX28: =SUM(EX28:EZ28) -> -2951668 | AY28: =SUM(FA28:FC28) -> -3010342.9 | AZ28: =SUM(FD28:FF28) -> -3153859 | BA28: =SUM(FG28:FI28) -> -3281520.4 | BB28: =SUM(FJ28:FL28) -> -2079882.3 | BF28: -237878 | BG28: -261878 | BH28: -403645 | BI28: -420236 | BJ28: -330134 | BK28: -308613 | BL28: -272961 | BM28: -318902 | BN28: -449505 | BO28: -313061 | BP28: -243781 | BQ28: -271998 | BR28: -286590 | BS28: -253632 | BT28: -252703 | BU28: =-308975 -> -308975 | BV28: -316922 | BW28: -302951 | BX28: =-388761+26000 -> -362761 | BY28: =-296101-70000+4000 -> -362101 | BZ28: =-347135 -> -347135 | CA28: -356582 | CB28: -377316 | CC28: =-246685 -> -246685 | CD28: =-403145+20000-17000-5000 -> -405145 | CE28: =-463242+36000+17000 -> -410242 | CF28: =-455810-11400-10000+15000 -> -462210 | CG28: =-505009+12500 -> -492509 | CH28: =-457032-8024 -> -465056 | CI28: -508863 | CJ28: -513448 | CK28: -524734 | CL28: -521298 | CM28: -516344 | CN28: =-531978 -> -531978 | CO28: -564788 | CP28: =-579994+5000 -> -574994 | CQ28: -580757 | CR28: -549106 | CS28: -570501 | CT28: -554396 | CU28: =-500697-15000 -> -515697 | CV28: -527790 | CW28: -520953.54 | CX28: -519195.96 | CY28: -522900.01 | CZ28: -540422.13 | DA28: -524360.96 | DB28: -524908.45 | DC28: -515620.42 | DD28: -561017.75 | DE28: -620663.93 | DF28: -581832.19 | DG28: -633355.85 | DH28: -664764.5 | DI28: -715779.83 | DJ28: -754523.2 | DK28: -766988.74 | DL28: -762525.06 | DM28: -712639.79 | DN28: -729745.52 | DO28: -733012.16 | DP28: -772010.04 | DQ28: -824616.27 | DR28: -874168.12 | DS28: -907600.91 | DT28: -966925.76 | DU28: -930898.63 | DV28: -990692.69 | DW28: -921226.82 | DX28: -995345.49 | DY28: -880207.8 | DZ28: -835565.95 | EA28: -820490.21 | EB28: -910537.21 | EC28: -866271.65 | ED28: -872040.55 | EE28: -932389.53 | EF28: -951566.57 | EG28: -932515.64 | EH28: -913039.64 | EI28: -917874.17 | EJ28: -925203.67 | EK28: -887930.3 | EL28: -868870.45 | EM28: -933826.77 | EN28: -977162.34 | EO28: -953722.04 | EP28: -955237.38 | EQ28: -972217.53 | ER28: -956293.68 | ES28: -991122.61 | ET28: -1004198.4 | EU28: -1046159.6 | EV28: -996988.26 | EW28: -1049875.2 | EX28: -971585.29 | EY28: -1033717.5 | EZ28: -946365.22 | FA28: -1017629 | FB28: -983473.02 | FC28: -1009240.9 | FD28: -1001479.1 | FE28: -1062049.1 | FF28: -1090330.8 | FG28: -1119669.8 | FH28: -1042051.4 | FI28: -1119799.2 | FJ28: -1089792.3 | FK28: -990090.01 | FN28: ='Financial plan'!EZ24 -> -1103147.6 | FO28: =FK28-FJ28 -> 99702.308 | FP28: =FK28-FN28 -> 113057.62 | FQ28: =FL28-#REF! -> #REF! | FR28: =FM28-FO28 -> -99702.308 | FS28: =FK28-FN28 -> 113057.62 | FT28: =SUM($FJ28:FK28) -> -2079882.3 | FU28: =SUM('Financial plan'!$EY24:EZ24) -> -2206295.3 | FV28: =FT28-FU28 -> 126412.93
E29: Hardware | F29: =F34-F13 -> -2480000 | G29: =SUM(R29:U29) -> -1418225 | H29: =SUM(V29:Y29) -> -603284 | I29: =SUM(Z29:AC29) -> -756405 | J29: =SUM(AD29:AG29) -> -1020744.1 | K29: =SUM(AH29:AK29) -> -737560.97 | L29: =SUM(AL29:AO29) -> -965868.16 | M29: =SUM(AP29:AS29) -> -667421.49 | N29: =SUM(AT29:AW29) -> -460103.7 | O29: =SUM(AX29:BA29) -> -794721.11 | P29: =FJ29 -> -25934.5 | R29: =SUM(BF29:BH29) -> -389782 | S29: =SUM(BI29:BK29) -> -278793 | T29: =SUM(BL29:BN29) -> -231837 | U29: =SUM(BO29:BQ29) -> -517813 | V29: =SUM(BR29:BT29) -> -82614 | W29: =SUM(BU29:BW29) -> -145760 | X29: =SUM(BX29:BZ29) -> -109823 | Y29: =SUM(CA29:CC29) -> -265087 | Z29: =SUM(CD29:CF29) -> -173167 | AA29: =SUM(CG29:CI29) -> -173421 | AB29: =SUM(CJ29:CL29) -> -217472 | AC29: =SUM(CM29:CO29) -> -192345 | AD29: =SUM(CP29:CR29) -> -282374 | AE29: =SUM(CS29:CU29) -> -457874 | AF29: =SUM(CV29:CX29) -> -152675.73 | AG29: =SUM(CY29:DA29) -> -127820.41 | AH29: =SUM(DB29:DD29) -> -139039.73 | AI29: =SUM(DE29:DG29) -> -200771.65 | AJ29: =SUM(DH29:DJ29) -> -293893.88 | AK29: =SUM(DK29:DM29) -> -103855.71 | AL29: =SUM(DN29:DP29) -> -150349.67 | AM29: =SUM(DQ29:DS29) -> -217636.47 | AN29: =SUM(DT29:DV29) -> -344147.34 | AO29: =SUM(DW29:DY29) -> -253734.68 | AP29: =SUM(DZ29:EB29) -> -139205.18 | AQ29: =OFFSET($DZ29,0,AQ$4)+OFFSET($EA29,0,AQ$4)+OFFSET($EB29,0,AQ$4) -> -145169.28 | AR29: =OFFSET($DZ29,0,AR$4)+OFFSET($EA29,0,AR$4)+OFFSET($EB29,0,AR$4) -> -142828.89 | AS29: =OFFSET($DZ29,0,AS$4)+OFFSET($EA29,0,AS$4)+OFFSET($EB29,0,AS$4) -> -240218.13 | AT29: =SUM(EL29:EN29) -> -146527.57 | AU29: =OFFSET($EL29,0,AU$4)+OFFSET($EM29,0,AU$4)+OFFSET($EN29,0,AU$4) -> -157773.47 | AV29: =OFFSET($EL29,0,AV$4)+OFFSET($EM29,0,AV$4)+OFFSET($EN29,0,AV$4) -> -74240.152 | AW29: =OFFSET($EL29,0,AW$4)+OFFSET($EM29,0,AW$4)+OFFSET($EN29,0,AW$4) -> -81562.503 | AX29: =SUM(EX29:EZ29) -> -132996.36 | AY29: =SUM(FA29:FC29) -> -171264.45 | AZ29: =SUM(FD29:FG29) -> -392144.93 | BA29: =SUM(FG29:FI29) -> -98315.361 | BB29: =SUM(FJ29:FL29) -> -29919.921 | BF29: -330514 | BG29: -11238 | BH29: -48030 | BI29: -44272 | BJ29: -196271 | BK29: -38250 | BL29: -40199 | BM29: -86066 | BN29: -105572 | BO29: -380838 | BP29: -100670 | BQ29: -36305 | BR29: -7565 | BS29: -27541 | BT29: -47508 | BU29: -89222 | BV29: -29250 | BW29: -27288 | BX29: =-102231+30903 -> -71328 | BY29: =-5456+711 -> -4745 | BZ29: =-20259-13491 -> -33750 | CA29: =-82222+1531 -> -80691 | CB29: =-3615+1092 -> -2523 | CC29: =-176802-3403-1668 -> -181873 | CD29: =-81796+581 -> -81215 | CE29: =-7678+945 -> -6733 | CF29: =-86154+935 -> -85219 | CG29: =-155426-511 -> -155937 | CH29: -9605 | CI29: =-8121+242 -> -7879 | CJ29: =-43996-1458 -> -45454 | CK29: =-38470-867 -> -39337 | CL29: =-132810+129 -> -132681 | CM29: -42103 | CN29: =-84343+1060 -> -83283 | CO29: =-76229+9270 -> -66959 | CP29: =-187864-901 -> -188765 | CQ29: -17525 | CR29: =-75020-1064 -> -76084 | CS29: =-72819+722 -> -72097 | CT29: =-227835-1219 -> -229054 | CU29: =-156368-355 -> -156723 | CV29: -13499 | CW29: -2929.95 | CX29: -136246.78 | CY29: -89796.91 | CZ29: -17831.82 | DA29: =-20191.34-0.34 -> -20191.68 | DB29: =-115573.88+0.05 -> -115573.83 | DC29: =-16697.83+0.03 -> -16697.8 | DD29: -6768.1 | DE29: -5932.53 | DF29: -18117.31 | DG29: -176721.81 | DH29: -174429.51 | DI29: -97227.84 | DJ29: -22236.53 | DK29: -12199.92 | DL29: -12664.19 | DM29: -78991.6 | DN29: -17397.71 | DO29: -7389.72 | DP29: -125562.24 | DQ29: -112882.03 | DR29: -100742.79 | DS29: -4011.65 | DT29: -10912.92 | DU29: -97178.21 | DV29: -236056.21 | DW29: -4928.4 | DX29: -31618 | DY29: -217188.28 | DZ29: -10979.72 | EA29: -4689.67 | EB29: -123535.79 | EC29: -25065.92 | ED29: -27032.33 | EE29: -93071.03 | EF29: -88477.59 | EG29: -49957.24 | EH29: -4394.0642 | EI29: -91032.638 | EJ29: -85760.567 | EK29: -63424.93 | EL29: -14483.481 | EM29: -24607.354 | EN29: -107436.74 | EO29: -12181.083 | EP29: -69511.799 | EQ29: -76080.591 | ER29: -17161.355 | ES29: -43489.927 | ET29: -13588.87 | EU29: -27665.773 | EV29: -63313.309 | EW29: 9416.58 | EX29: -6713.7269 | EY29: -120422.28 | EZ29: -5860.3553 | FA29: -34259.796 | FB29: -128471.99 | FC29: -8532.6692 | FD29: -121085.39 | FE29: -93148.084 | FF29: -165652.24 | FG29: -12259.226 | FH29: -4538.6401 | FI29: -81517.495 | FJ29: -25934.5 | FK29: -3985.4213 | FN29: ='Financial plan'!EZ25 -> -67751.263 | FO29: =FK29-FJ29 -> 21949.079 | FP29: =FK29-FN29 -> 63765.841 | FQ29: =FL29-#REF! -> #REF! | FR29: =FM29-FO29 -> -21949.079 | FS29: =FK29-FN29 -> 63765.841 | FT29: =SUM($FJ29:FK29) -> -29919.921 | FU29: =SUM('Financial plan'!$EY25:EZ25) -> -135502.53 | FV29: =FT29-FU29 -> 105582.6
E30: Consultancy | F30: =F35-F14 -> -112000 | G30: =SUM(R30:U30) -> -70831 | H30: =SUM(V30:Y30) -> -67720 | I30: =SUM(Z30:AC30) -> -18893 | J30: =SUM(AD30:AG30) -> -21655.22 | K30: =SUM(AH30:AK30) -> -11050.37 | L30: =SUM(AL30:AO30) -> -8244.93 | M30: =SUM(AP30:AS30) -> -58251.021 | N30: =SUM(AT30:AW30) -> -64937.009 | O30: =SUM(AX30:BA30) -> -17798.066 | P30: =FJ30 -> -3710.37 | R30: =SUM(BF30:BH30) -> -21134 | S30: =SUM(BI30:BK30) -> -26097 | T30: =SUM(BL30:BN30) -> -24224 | U30: =SUM(BO30:BQ30) -> 624 | V30: =SUM(BR30:BT30) -> -12945 | W30: =SUM(BU30:BW30) -> -1500 | X30: =SUM(BX30:BZ30) -> -14175 | Y30: =SUM(CA30:CC30) -> -39100 | Z30: =SUM(CD30:CF30) -> -8000 | AA30: =SUM(CG30:CI30) -> -3530 | AB30: =SUM(CJ30:CL30) -> -5563 | AC30: =SUM(CM30:CO30) -> -1800 | AD30: =SUM(CP30:CR30) -> -3850 | AE30: =SUM(CS30:CU30) -> -10189 | AF30: =SUM(CV30:CX30) -> 0 | AG30: =SUM(CY30:DA30) -> -7616.22 | AH30: =SUM(DB30:DD30) -> 0 | AI30: =SUM(DE30:DG30) -> -5225 | AJ30: =SUM(DH30:DJ30) -> 0 | AK30: =SUM(DK30:DM30) -> -5825.37 | AL30: =SUM(DN30:DP30) -> -975.12 | AM30: =SUM(DQ30:DS30) -> -3667.29 | AN30: =SUM(DT30:DV30) -> -2702.52 | AO30: =SUM(DW30:DY30) -> -900 | AP30: =SUM(DZ30:EB30) -> 0 | AQ30: =OFFSET($DZ30,0,AQ$4)+OFFSET($EA30,0,AQ$4)+OFFSET($EB30,0,AQ$4) -> 0 | AR30: =OFFSET($DZ30,0,AR$4)+OFFSET($EA30,0,AR$4)+OFFSET($EB30,0,AR$4) -> -10450 | AS30: =OFFSET($DZ30,0,AS$4)+OFFSET($EA30,0,AS$4)+OFFSET($EB30,0,AS$4) -> -47801.021 | AT30: =SUM(EL30:EN30) -> -39985.454 | AU30: =OFFSET($EL30,0,AU$4)+OFFSET($EM30,0,AU$4)+OFFSET($EN30,0,AU$4) -> -17632.957 | AV30: =OFFSET($EL30,0,AV$4)+OFFSET($EM30,0,AV$4)+OFFSET($EN30,0,AV$4) -> -7325.6443 | AW30: =OFFSET($EL30,0,AW$4)+OFFSET($EM30,0,AW$4)+OFFSET($EN30,0,AW$4) -> 7.046184 | AX30: =SUM(EX30:EZ30) -> 0 | AY30: =SUM(FA30:FC30) -> 0 | AZ30: =SUM(FD30:FG30) -> -17798.066 | BA30: =SUM(FG30:FI30) -> 0 | BB30: =SUM(FJ30:FL30) -> -3710.37 | BF30: -3600 | BG30: -6847 | BH30: -10687 | BI30: -10936 | BJ30: -4930 | BK30: -10231 | BL30: -7128 | BM30: -7676 | BN30: -9420 | BO30: -5000 | BP30: 624 | BQ30: 5000 | BR30: -11000 | BS30: 11000 | BT30: -12945 | BU30: 0 | BV30: -1500 | BW30: 0 | BX30: -7685 | BY30: =-3500 -> -3500 | BZ30: -2990 | CA30: -20000 | CB30: -19100 | CC30: 0 | CD30: 0 | CE30: -8000 | CF30: 0 | CG30: 0 | CH30: 0 | CI30: -3530 | CJ30: 0 | CK30: -2808 | CL30: -2755 | CM30: 0 | CN30: 0 | CO30: -1800 | CP30: -3850 | CQ30: 0 | CR30: 0 | CS30: 0 | CT30: 0 | CU30: -10189 | CV30: 0 | CW30: 0 | CX30: 0 | CY30: -7616.22 | CZ30: 0 | DA30: 0 | DB30: 0 | DC30: 0 | DD30: 0 | DE30: 0 | DF30: 0 | DG30: -5225 | DH30: 0 | DI30: 0 | DJ30: 0 | DK30: -4700.37 | DL30: -1125 | DM30: 0 | DO30: -975.12 | DQ30: -990.84 | DR30: 141.06 | DS30: -2817.51 | DT30: -2642.52 | DU30: -60 | DV30: 0 | DW30: 0 | DX30: -900 | DY30: 0 | DZ30: 0 | EA30: 0 | EB30: 0 | EC30: 0 | ED30: 0 | EE30: 0 | EF30: 0 | EG30: -5500 | EH30: -4950 | EI30: -16386.377 | EJ30: -14538.888 | EK30: -16875.756 | EL30: -11149.828 | EM30: -14500.01 | EN30: -14335.617 | EO30: -12822.041 | EP30: -2411.7148 | EQ30: -2399.2017 | ER30: -2513.3755 | ES30: -2402.8138 | ET30: -2409.455 | EU30: -2446.0039 | EV30: 2453.0501 | EW30: 0 | FF30: -17798.066 | FG30: 0 | FH30: 0 | FI30: 0 | FJ30: -3710.37 | FK30: 0 | FN30: ='[1]Financial plan'!EX26 -> 0 | FO30: =FK30-FJ30 -> 3710.37 | FP30: =FK30-FN30 -> 0 | FQ30: =FL30-#REF! -> #REF! | FR30: =FM30-FO30 -> -3710.37 | FS30: =FK30-FN30 -> 0 | FT30: =SUM($FJ30:FK30) -> -3710.37 | FU30: =SUM('Financial plan'!$EY26:EZ26) -> -1733.3333 | FV30: =FT30-FU30 -> -1977.0367
P31: =FJ31 -> 0
D32: Gross profit | P32: =FJ32 -> 0
E33: Managed services | F33: 2272000 | G33: =G7+G28 -> 2984902 | H33: =H7+H28 -> 4788089 | I33: =SUM(Z33:AC33) -> 5221152 | J33: =SUM(AD33:AG33) -> 6161981.2 | K33: =SUM(AH33:AK33) -> 7422104.1 | L33: =SUM(AL33:AO33) -> 9315500.7 | M33: =SUM(AP33:AS33) -> 11356855 | N33: =SUM(AT33:AW33) -> 11204353 | O33: =SUM(AX33:BA33) -> 11211653 | P33: =SUM($FJ33:FK33) -> 2018202.4 | R33: =R7+R28 -> 600641 | S33: =S7+S28 -> 602093 | T33: =SUM(BL33:BN33) -> 761901 | U33: =U7+U28 -> 1020267 | V33: =V7+V28 -> 1132164 | W33: =W7+W28 -> 1044324 | X33: =X7+X28 -> 1198131 | Y33: =Y7+Y28 -> 1413470 | Z33: =SUM(CD33:CF33) -> 1225416 | AA33: =SUM(CG33:CI33) -> 1186212 | AB33: =SUM(CJ33:CL33) -> 1303080 | AC33: =SUM(CM33:CO33) -> 1506444 | AD33: =SUM(CP33:CR33) -> 1522479 | AE33: =SUM(CS33:CU33) -> 1485950 | AF33: =SUM(CV33:CX33) -> 1561725.5 | AG33: =SUM(CY33:DA33) -> 1591826.8 | AH33: =SUM(DB33:DD33) -> 1683917.6 | AI33: =SUM(DE33:DG33) -> 1762623.4 | AJ33: =SUM(DH33:DJ33) -> 1904924.7 | AK33: =SUM(DK33:DM33) -> 2070638.3 | AL33: =SUM(DN33:DP33) -> 2089282.3 | AM33: =SUM(DQ33:DS33) -> 2229753.4 | AN33: =SUM(DT33:DV33) -> 2251717.2 | AO33: =SUM(DW33:DY33) -> 2744747.9 | AP33: =SUM(DZ33:EB33) -> 2863141.1 | AQ33: =OFFSET($DZ33,0,AQ$4)+OFFSET($EA33,0,AQ$4)+OFFSET($EB33,0,AQ$4) -> 2775600.5 | AR33: =OFFSET($DZ33,0,AR$4)+OFFSET($EA33,0,AR$4)+OFFSET($EB33,0,AR$4) -> 2787000.6 | AS33: =OFFSET($DZ33,0,AS$4)+OFFSET($EA33,0,AS$4)+OFFSET($EB33,0,AS$4) -> 2931113.1 | AT33: =SUM(EL33:EN33) -> 3027694.1 | AU33: =OFFSET($EL33,0,AU$4)+OFFSET($EM33,0,AU$4)+OFFSET($EN33,0,AU$4) -> 2896434.8 | AV33: =OFFSET($EL33,0,AV$4)+OFFSET($EM33,0,AV$4)+OFFSET($EN33,0,AV$4) -> 2708353.5 | AW33: =OFFSET($EL33,0,AW$4)+OFFSET($EM33,0,AW$4)+OFFSET($EN33,0,AW$4) -> 2571870.8 | AX33: =SUM(EX33:EZ33) -> 2669300.6 | AY33: =SUM(FA33:FC33) -> 2616448.1 | AZ33: =SUM(FD33:FF33) -> 2886806 | BA33: =SUM(FG33:FI33) -> 3039098.6 | BB33: =SUM(FJ33:FL33) -> 2018202.4 | BF33: =BF7+BF28 -> 261187 | BG33: =BG7+BG28 -> 209283 | BH33: =BH7+BH28 -> 130171 | BI33: =BI7+BI28 -> 123772 | BJ33: =BJ7+BJ28 -> 243091 | BK33: =BK7+BK28 -> 235230 | BL33: =BL7+BL28 -> 296744 | BM33: =BM7+BM28 -> 308143 | ... FK33: =FK7+FK28 -> 1041616.1 | FN33: ='Financial plan'!EZ29 -> 1031661.1 | FO33: =FK33-FJ33 -> 65029.918 | FP33: =FK33-FN33 -> 9955.0691 | FQ33: =FL33-#REF! -> #REF! | FR33: =FM33-FO33 -> -65029.918 | FS33: =FK33-FN33 -> 9955.0691 | FT33: =SUM($FJ33:FK33) -> 2018202.4 | FU33: =SUM('Financial plan'!$EY29:EZ29) -> 2063322.1 | FV33: =FT33-FU33 -> -45119.78
E34: Hardware | F34: 983000 | G34: =SUM(R34:U34) -> 948652 | H34: =SUM(V34:Y34) -> 384807 | I34: =SUM(Z34:AC34) -> 486034 | J34: =SUM(AD34:AG34) -> 596948.72 | K34: =SUM(AH34:AK34) -> 374625.58 | L34: =SUM(AL34:AO34) -> 451245.35 | M34: =SUM(AP34:AS34) -> 432664.11 | N34: =SUM(AT34:AW34) -> 302626.69 | O34: =SUM(AX34:BA34) -> 372189.62 | P34: =SUM($FJ34:FK34) -> 11540.033 | R34: =R13+R29 -> 353873 | S34: =S13+S29 -> 92779 | T34: =SUM(BL34:BN34) -> 141804 | U34: =U13+U29 -> 360196 | V34: =V13+V29 -> 46134 | W34: =W13+W29 -> 94324 | X34: =X13+X29 -> 90155 | Y34: =Y13+Y29 -> 154194 | Z34: =SUM(CD34:CF34) -> 103478 | AA34: =SUM(CG34:CI34) -> 124147 | AB34: =SUM(CJ34:CL34) -> 149513 | AC34: =SUM(CM34:CO34) -> 108896 | AD34: =SUM(CP34:CR34) -> 175179 | AE34: =SUM(CS34:CU34) -> 232557 | AF34: =SUM(CV34:CX34) -> 106836.55 | AG34: =SUM(CY34:DA34) -> 82376.17 | AH34: =SUM(DB34:DD34) -> 93622.38 | AI34: =SUM(DE34:DG34) -> 108450.98 | AJ34: =SUM(DH34:DJ34) -> 119210.16 | AK34: =SUM(DK34:DM34) -> 53342.06 | AL34: =SUM(DN34:DP34) -> 90795.85 | AM34: =SUM(DQ34:DS34) -> 96019.54 | AN34: =SUM(DT34:DV34) -> 134113.56 | AO34: =SUM(DW34:DY34) -> 130316.4 | AP34: =SUM(DZ34:EB34) -> 69276.53 | AQ34: =OFFSET($DZ34,0,AQ$4)+OFFSET($EA34,0,AQ$4)+OFFSET($EB34,0,AQ$4) -> 139914.06 | AR34: =OFFSET($DZ34,0,AR$4)+OFFSET($EA34,0,AR$4)+OFFSET($EB34,0,AR$4) -> 83441.795 | AS34: =OFFSET($DZ34,0,AS$4)+OFFSET($EA34,0,AS$4)+OFFSET($EB34,0,AS$4) -> 140031.73 | AT34: =SUM(EL34:EN34) -> 95242 | AU34: =OFFSET($EL34,0,AU$4)+OFFSET($EM34,0,AU$4)+OFFSET($EN34,0,AU$4) -> 112521.47 | AV34: =OFFSET($EL34,0,AV$4)+OFFSET($EM34,0,AV$4)+OFFSET($EN34,0,AV$4) -> 37427.242 | AW34: =OFFSET($EL34,0,AW$4)+OFFSET($EM34,0,AW$4)+OFFSET($EN34,0,AW$4) -> 57435.984 | AX34: =SUM(EX34:EZ34) -> 52600.13 | AY34: =SUM(FA34:FC34) -> 70354.399 | AZ34: =SUM(FD34:FF34) -> 200100.99 | BA34: =SUM(FG34:FI34) -> 49134.102 | BB34: =SUM(FJ34:FL34) -> 11540.033 | BF34: =BF13+BF29 -> 323612 | BG34: =BG13+BG29 -> 342 | BH34: =BH13+BH29 -> 29919 | BI34: =BI13+BI29 -> 13179 | BJ34: =BJ13+BJ29 -> 59274 | BK34: =BK13+BK29 -> 20326 | BL34: =BL13+BL29 -> 16921 | BM34: =BM13+BM29 -> 52113 | ... FK34: =FK13+FK29 -> 1982.5015 | FN34: ='Financial plan'!EZ30 -> 26781.566 | FO34: =FK34-FJ34 -> -7575.0299 | FP34: =FK34-FN34 -> -24799.064 | FQ34: =FL34-#REF! -> #REF! | FR34: =FM34-FO34 -> 7575.0299 | FS34: =FK34-FN34 -> -24799.064 | FT34: =SUM($FJ34:FK34) -> 11540.033 | FU34: =SUM('Financial plan'!$EY30:EZ30) -> 53563.131 | FV34: =FT34-FU34 -> -42023.098
E35: Consultancy | F35: 61000 | G35: =SUM(R35:U35) -> 80481 | H35: =SUM(V35:Y35) -> 98461 | I35: =SUM(Z35:AC35) -> 98173 | J35: =SUM(AD35:AG35) -> 510931.04 | K35: =SUM(AH35:AK35) -> 308467.04 | L35: =SUM(AL35:AO35) -> 529552.25 | M35: =SUM(AP35:AS35) -> 691569.44 | N35: =SUM(AT35:AW35) -> 813413.59 | O35: =SUM(AX35:BA35) -> 835083.8 | P35: =SUM($FJ35:FK35) -> 24058.427 | R35: =R14+R30 -> 21667 | S35: =S14+S30 -> 26426 | T35: =SUM(BL35:BN35) -> 21765 | U35: =U14+U30 -> 10623 | V35: =V14+V30 -> 12945 | W35: =W14+W30 -> 1600 | X35: =X14+X30 -> 54645 | Y35: =Y14+Y30 -> 29271 | Z35: =SUM(CD35:CF35) -> 9525 | AA35: =SUM(CG35:CI35) -> 5066 | AB35: =SUM(CJ35:CL35) -> 11877 | AC35: =SUM(CM35:CO35) -> 71705 | AD35: =SUM(CP35:CR35) -> 68430 | AE35: =SUM(CS35:CU35) -> 86998 | AF35: =SUM(CV35:CX35) -> 154889.26 | AG35: =SUM(CY35:DA35) -> 200613.78 | AH35: =SUM(DB35:DD35) -> 101944.35 | AI35: =SUM(DE35:DG35) -> 93721.47 | AJ35: =SUM(DH35:DJ35) -> 46289.61 | AK35: =SUM(DK35:DM35) -> 66511.61 | AL35: =SUM(DN35:DP35) -> 90194.97 | AM35: =SUM(DQ35:DS35) -> 140780.34 | AN35: =SUM(DT35:DV35) -> 164286.47 | AO35: =SUM(DW35:DY35) -> 134290.47 | AP35: =SUM(DZ35:EB35) -> 104909.41 | AQ35: =OFFSET($DZ35,0,AQ$4)+OFFSET($EA35,0,AQ$4)+OFFSET($EB35,0,AQ$4) -> 131801.87 | AR35: =OFFSET($DZ35,0,AR$4)+OFFSET($EA35,0,AR$4)+OFFSET($EB35,0,AR$4) -> 209503.36 | AS35: =OFFSET($DZ35,0,AS$4)+OFFSET($EA35,0,AS$4)+OFFSET($EB35,0,AS$4) -> 245354.8 | AT35: =SUM(EL35:EN35) -> 239457.04 | AU35: =OFFSET($EL35,0,AU$4)+OFFSET($EM35,0,AU$4)+OFFSET($EN35,0,AU$4) -> 269391.34 | AV35: =OFFSET($EL35,0,AV$4)+OFFSET($EM35,0,AV$4)+OFFSET($EN35,0,AV$4) -> 289815.1 | AW35: =OFFSET($EL35,0,AW$4)+OFFSET($EM35,0,AW$4)+OFFSET($EN35,0,AW$4) -> 14750.115 | AX35: =SUM(EX35:EZ35) -> 221862.7 | AY35: =SUM(FA35:FC35) -> 175682.49 | AZ35: =SUM(FD35:FF35) -> 206785.2 | BA35: =SUM(FG35:FI35) -> 230753.41 | BB35: =SUM(FJ35:FL35) -> 24058.427 | BF35: =BF14+BF30 -> 6400 | BG35: =BG14+BG30 -> 6090 | BH35: =BH14+BH30 -> 9177 | BI35: =BI14+BI30 -> 9223 | BJ35: =BJ14+BJ30 -> 4645 | BK35: =BK14+BK30 -> 12558 | BL35: =BL14+BL30 -> 3832 | BM35: =BM14+BM30 -> 7353 | ... FK35: =FK14+FK30 -> 10068.302 | FN35: ='Financial plan'!EZ31 -> 44133.333 | FO35: =FK35-FJ35 -> -3921.8226 | FP35: =FK35-FN35 -> -34065.031 | FQ35: =FL35-#REF! -> #REF! | FR35: =FM35-FO35 -> 3921.8226 | FS35: =FK35-FN35 -> -34065.031 | FT35: =SUM($FJ35:FK35) -> 24058.427 | FU35: =SUM('Financial plan'!$EY31:EZ31) -> 88266.667 | FV35: =FT35-FU35 -> -64208.24
O36: =SUM(AX36:BA36) -> 0 | P36: =SUM($FJ36:FK36) -> 0 | FT36: =SUM($FJ36:FK36) -> 0 | FU36: =SUM('Financial plan'!$EY32:EZ32) -> 0 | FV36: =FT36-FU36 -> 0
D37: Gross margin % | O37: =SUM(AX37:BA37) -> 0
E38: Managed services inc sims | F38: =F33/F7 -> 0.43333969 | G38: =G33/G7 -> 0.43782979 | H38: =H33/H7 -> 0.55919666 | I38: =I33/I7 -> 0.46877906 | J38: =J33/J7 -> 0.48661096 | K38: =K33/K7 -> 0.48711942 | L38: =L33/L7 -> 0.46948512 | M38: =M33/M7 -> 0.5133673 | ... P38: =P33/P7 -> 0.49247454 | R38: =IFERROR(R33/R7,"") -> 0.39935121 | S38: =IFERROR(S33/S7,"") -> 0.36247167 | T38: =IFERROR(T33/T7,"") -> 0.42251101 | U38: =IFERROR(U33/U7,"") -> 0.55176201 | V38: =IFERROR(V33/V7,"") -> 0.58810995 | W38: =IFERROR(W33/W7,"") -> 0.52926151 | X38: =IFERROR(X33/X7,"") -> 0.52778125 | Y38: =IFERROR(Y33/Y7,"") -> 0.59040882 | ... BB38: =IFERROR(BB33/BB7,"") -> 0.49247454 | BF38: =IFERROR(BF33/BF7,"") -> 0.52335267 | BG38: =IFERROR(BG33/BG7,"") -> 0.44418575 | BH38: =IFERROR(BH33/BH7,"") -> 0.24384994 | BI38: =IFERROR(BI33/BI7,"") -> 0.22751871 | BJ38: =IFERROR(BJ33/BJ7,"") -> 0.42407606 | BK38: =IFERROR(BK33/BK7,"") -> 0.43253292 | BL38: =IFERROR(BL33/BL7,"") -> 0.52087308 | BM38: =IFERROR(BM33/BM7,"") -> 0.49142087 | ... FK38: =IFERROR(FK33/FK7,"") -> 0.51268051 | FN38: =IFERROR(FN33/FN7,"") -> 0.48325692 | FO38: =FK38-FJ38 -> 0.040072898 | FP38: =FK38-FN38 -> 0.029423591 | FQ38: =FL38-#REF! -> #REF! | FR38: =FM38-FO38 -> -0.040072898 | FS38: =FK38-FN38 -> 0.029423591 | FT38: =IFERROR(FT33/FT7,"") -> 0.49247454 | FU38: =IFERROR(FU33/FU7,"") -> 0.48325692 | FV38: =FT38-FU38 -> 0.0092176205
E39: Managed services exc sims | H39: =SUM(KPIs!C38:N38)/SUM(KPIs!C36:N36) -> 0.5995392 | I39: =SUM(KPIs!O38:Z38)/SUM(KPIs!O36:Z36) -> 0.49112522 | J39: =SUM(KPIs!AA38:AL38)/SUM(KPIs!AA36:AL36) -> 0.50687842 | K39: =SUM(KPIs!AM38:AX38)/SUM(KPIs!AM36:AX36) -> 0.54123883 | L39: =SUM(KPIs!AY38:BJ38)/SUM(KPIs!AY36:BJ36) -> 0.50809104 | M39: =SUM(KPIs!BK38:BV38)/SUM(KPIs!BK36:BV36) -> 0.54166471 | N39: =SUM(KPIs!BW38:CH38)/SUM(KPIs!BW36:CH36) -> 0.52056897 | O39: =SUM(KPIs!BX38:CI38)/SUM(KPIs!BX36:CI36) -> 0.51652237 | P39: =SUM(KPIs!BY38:CJ38)/SUM(KPIs!BY36:CJ36) -> 0.51159026 | AP39: =SUM(KPIs!BK38:BM38)/SUM(KPIs!BK36:BM36) -> 0.55850297 | AQ39: =SUM(KPIs!BN38:BP38)/SUM(KPIs!BN36:BP36) -> 0.53516907 | AR39: =SUM(KPIs!BQ38:BS38)/SUM(KPIs!BQ36:BS36) -> 0.53248743 | AS39: =SUM(KPIs!BR38:BT38)/SUM(KPIs!BR36:BT36) -> 0.53458797 | AT39: =SUM(KPIs!BW38:BY38)/SUM(KPIs!BW36:BY36) -> 0.54954201 | AU39: =SUM(KPIs!BZ38:CB38)/SUM(KPIs!BZ36:CB36) -> 0.52639068 | AV39: =SUM(KPIs!CC38:CE38)/SUM(KPIs!CC36:CE36) -> 0.50434244 | AW39: =SUM(KPIs!CF38:CH38)/SUM(KPIs!CF36:CH36) -> 0.50100054 | AX39: =SUM(KPIs!CG38:CI38)/SUM(KPIs!CG36:CI36) -> 0.50519516 | AY39: =SUM(KPIs!CH38:CJ38)/SUM(KPIs!CH36:CJ36) -> 0.5040282 | AZ39: =SUM(KPIs!CI38:CK38)/SUM(KPIs!CI36:CK36) -> 0.50166813 | BA39: =SUM(KPIs!CJ38:CL38)/SUM(KPIs!CJ36:CL36) -> 0.49742895 | BB39: =SUM(KPIs!CK38:CM38)/SUM(KPIs!CK36:CM36) -> 0.49636017 | BR39: =KPIs!C39 -> 0.60293201 | BS39: =KPIs!D39 -> 0.64124921 | BT39: =KPIs!E39 -> 0.6342304 | BU39: =KPIs!F39 -> 0.56898662 | BV39: =KPIs!G39 -> 0.57156846 | BW39: =KPIs!H39 -> 0.58771453 | BX39: =KPIs!I39 -> 0.60246896 | BY39: =KPIs!J39 -> 0.55599547 | ... FK39: =KPIs!CV39 -> 0.51874337 | FN39: =KPIs!#REF! -> #REF! | FO39: =FK39-FJ39 -> 0.0052018652 | FS39: =FK39-FN39 -> #REF! | FT39: =KPIs!DD39 -> 0 | FU39: =KPIs!DE39 -> 0 | FV39: =FT39-FU39 -> 0
E40: Hardware | F40: =F34/F13 -> 0.28385793 | G40: =G34/G13 -> 0.40080325 | H40: =H34/H13 -> 0.3894449 | I40: =I34/I13 -> 0.39119345 | J40: =J34/J13 -> 0.3690124 | K40: =K34/K13 -> 0.336837 | L40: =L34/L13 -> 0.31842569 | M40: =M34/M13 -> 0.3933004 | ... P40: =P34/P13 -> 0.32514433 | R40: =IFERROR(R34/R13,"") -> 0.47585641 | S40: =IFERROR(S34/S13,"") -> 0.2496932 | T40: =IFERROR(T34/T13,"") -> 0.37951938 | U40: =IFERROR(U34/U13,"") -> 0.41024181 | V40: =IFERROR(V34/V13,"") -> 0.3583279 | W40: =IFERROR(W34/W13,"") -> 0.39287916 | X40: =IFERROR(X34/X13,"") -> 0.45082459 | Y40: =IFERROR(Y34/Y13,"") -> 0.36775814 | ... BB40: =IFERROR(BB34/BB13,"") -> 0.27834167 | BF40: =IFERROR(BF34/BF13,"") -> 0.49472426 | BG40: =IFERROR(BG34/BG13,"") -> 0.029533679 | BH40: =IFERROR(BH34/BH13,"") -> 0.38382789 | BI40: =IFERROR(BI34/BI13,"") -> 0.22939548 | BJ40: =IFERROR(BJ34/BJ13,"") -> 0.23195132 | BK40: =IFERROR(BK34/BK13,"") -> 0.34700219 | BL40: =IFERROR(BL34/BL13,"") -> 0.29623599 | BM40: =IFERROR(BM34/BM13,"") -> 0.37714124 | ... FK40: =IFERROR(FK34/FK13,"") -> 0.33219289 | FN40: =IFERROR(FN34/FN13,"") -> 0.28330439 | FO40: =FK40-FJ40 -> 0.062906203 | FP40: =FK40-FN40 -> 0.048888493 | FQ40: =FL40-#REF! -> #REF! | FR40: =FM40-FO40 -> -0.062906203 | FS40: =FK40-FN40 -> 0.048888493 | FT40: =IFERROR(FT34/FT13,"") -> 0.27834167 | FU40: =IFERROR(FU34/FU13,"") -> 0.28330439 | FV40: =FT40-FU40 -> -0.0049627234
E41: Consultancy | F41: =F35/F14 -> 0.35260116 | G41: =G35/G14 -> 0.53188776 | H41: =H35/H14 -> 0.59249252 | I41: =I35/I14 -> 0.83861241 | J41: =J35/J14 -> 0.95933951 | K41: =K35/K14 -> 0.96541544 | L41: =L35/L14 -> 0.98466907 | M41: =M35/M14 -> 0.92231337 | ... P41: =P35/P14 -> 1.3591952 | R41: =IFERROR(R35/R14,"") -> 0.50622649 | S41: =IFERROR(S35/S14,"") -> 0.50313196 | T41: =IFERROR(T35/T14,"") -> 0.47326535 | U41: =IFERROR(U35/U14,"") -> 1.0624062 | V41: =IFERROR(V35/V14,"") -> 0.5 | W41: =IFERROR(W35/W14,"") -> 0.51612903 | X41: =IFERROR(X35/X14,"") -> 0.7940279 | Y41: =IFERROR(Y35/Y14,"") -> 0.42812011 | ... BB41: =IFERROR(BB35/BB14,"") -> 0.86638348 | BF41: =IFERROR(BF35/BF14,"") -> 0.64 | BG41: =IFERROR(BG35/BG14,"") -> 0.47074283 | BH41: =IFERROR(BH35/BH14,"") -> 0.46199154 | BI41: =IFERROR(BI35/BI14,"") -> 0.45751277 | BJ41: =IFERROR(BJ35/BJ14,"") -> 0.48511749 | BK41: =IFERROR(BK35/BK14,"") -> 0.55105533 | BL41: =IFERROR(BL35/BL14,"") -> 0.34963504 | BM41: =IFERROR(BM35/BM14,"") -> 0.48925411 | ... FK41: =IFERROR(FK35/FK14,"") -> 1 | FN41: =IFERROR(FN35/FN14,"") -> 0.98074074 | FO41: =FK41-FJ41 -> 0.20961957 | FP41: =FK41-FN41 -> 0.019259259 | FQ41: =FL41-#REF! -> #REF! | FR41: =FM41-FO41 -> -0.20961957 | FS41: =FK41-FN41 -> 0.019259259 | FT41: =IFERROR(FT35/FT14,"") -> 0.86638348 | FU41: =IFERROR(FU35/FU14,"") -> 0.98074074 | FV41: =FT41-FU41 -> -0.11435726
E42: Overall | F42: =IFERROR((F33+F34+F35)/F25,"") -> 0.37346548 | G42: =IFERROR((G33+G34+G35)/G25,"") -> 0.42996693 | H42: =IFERROR((H33+H34+H35)/H25,"") -> 0.54250408 | I42: =IFERROR((I33+I34+I35)/I25,"") -> 0.4645301 | J42: =IFERROR((J33+J34+J35)/J25,"") -> 0.49076467 | K42: =IFERROR((K33+K34+K35)/K25,"") -> 0.48626042 | L42: =IFERROR((L33+L34+L35)/L25,"") -> 0.47237527 | M42: =IFERROR((M33+M34+M35)/M25,"") -> 0.52064875 | ... P42: =IFERROR((P33+P34+P35)/P25,"") -> 0.96897002 | V42: =IFERROR((V33+V34+V35)/V25,"") -> 0.57278816 | W42: =IFERROR((W33+W34+W35)/W25,"") -> 0.5144697 | X42: =IFERROR((X33+X34+X35)/X25,"") -> 0.52893664 | Y42: =IFERROR((Y33+Y34+Y35)/Y25,"") -> 0.55416325 | Z42: =IFERROR((Z33+Z34+Z35)/Z25,"") -> 0.47848818 | AA42: =IFERROR((AA33+AA34+AA35)/AA25,"") -> 0.44457997 | AB42: =IFERROR((AB33+AB34+AB35)/AB25,"") -> 0.45102457 | AC42: =IFERROR((AC33+AC34+AC35)/AC25,"") -> 0.48279913 | ... BA42: =IFERROR((BA33+BA34+BA35)/BA25,"") -> 0.49545818 | BB42: =FJ42 -> 0.47185673 | BR42: =IFERROR((BR33+BR34+BR35)/BR25,"") -> 0.5503102 | BS42: =IFERROR((BS33+BS34+BS35)/BS25,"") -> 0.6083473 | BT42: =IFERROR((BT33+BT34+BT35)/BT25,"") -> 0.55974689 | BU42: =IFERROR((BU33+BU34+BU35)/BU25,"") -> 0.50192627 | BV42: =IFERROR((BV33+BV34+BV35)/BV25,"") -> 0.50660468 | BW42: =IFERROR((BW33+BW34+BW35)/BW25,"") -> 0.53633096 | BX42: =IFERROR((BX33+BX34+BX35)/BX25,"") -> 0.52630258 | BY42: =IFERROR((BY33+BY34+BY35)/BY25,"") -> 0.53135234 | ... FK42: =IFERROR((FK33+FK34+FK35)/FK25,"") -> 0.51455054 | FN42: =IFERROR((FN33+FN34+FN35)/FN25,"") -> 0.48478909 | FO42: =FK42-FJ42 -> 0.042693807 | FP42: =FK42-FN42 -> 0.029761445 | FQ42: =FL42-#REF! -> #REF! | FR42: =FM42-FO42 -> -0.042693807 | FS42: =FK42-FN42 -> 0.029761445 | FT42: =IFERROR((FT33+FT34+FT35)/FT25,"") -> 0.4928357 | FU42: =IFERROR((FU33+FU34+FU35)/FU25,"") -> 0.48478909 | FV42: =FT42-FU42 -> 0.0080466021
N43: =SUM(AT43:BA43) -> 0 | AT43: =SUM(EL43:EN43) -> 0 | AU43: =OFFSET($EL43,0,AU$4)+OFFSET($EM43,0,AU$4)+OFFSET($EN43,0,AU$4) -> 0 | AV43: =OFFSET($EL43,0,AV$4)+OFFSET($EM43,0,AV$4)+OFFSET($EN43,0,AV$4) -> 0 | AW43: =OFFSET($EL43,0,AW$4)+OFFSET($EM43,0,AW$4)+OFFSET($EN43,0,AW$4) -> 0 | AZ43: =FD43 -> 0 | BB43: =FJ43 -> 0 | FS43: =FK43-FN43 -> 0 | FT43: =SUM($FJ43:FK43) -> 0
C44: Total Gross Profit | F44: =SUM(F33:F36) -> 3316000 | G44: =SUM(G33:G36) -> 4014035 | H44: =SUM(H33:H36) -> 5271357 | I44: =SUM(I33:I36) -> 5805359 | J44: =SUM(J33:J36) -> 7269861 | K44: =SUM(K33:K36) -> 8105196.7 | L44: =SUM(L33:L36) -> 10296298 | M44: =SUM(M33:M36) -> 12481089 | N44: =SUM(AT44:AW44) -> 12320393 | O44: =SUM(AX44:BA44) -> 12418927 | P44: =FJ44 -> 1000133.9 | R44: =SUM(R33:R36) -> 976181 | S44: =SUM(S33:S36) -> 721298 | T44: =SUM(T33:T36) -> 925470 | U44: =SUM(U33:U36) -> 1391086 | V44: =SUM(V33:V36) -> 1191243 | W44: =SUM(W33:W36) -> 1140248 | X44: =SUM(X33:X36) -> 1342931 | Y44: =SUM(Y33:Y36) -> 1596935 | ... AS44: =SUM(AS33:AS36) -> 3316499.6 | AT44: =SUM(EL44:EN44) -> 3362393.1 | AU44: =OFFSET($EL44,0,AU$4)+OFFSET($EM44,0,AU$4)+OFFSET($EN44,0,AU$4) -> 3278347.6 | AV44: =OFFSET($EL44,0,AV$4)+OFFSET($EM44,0,AV$4)+OFFSET($EN44,0,AV$4) -> 3035595.8 | AW44: =OFFSET($EL44,0,AW$4)+OFFSET($EM44,0,AW$4)+OFFSET($EN44,0,AW$4) -> 2644056.9 | AX44: =SUM(EX44:EZ44) -> 2943763.4 | AY44: =SUM(FA44:FC44) -> 2862485 | AZ44: =SUM(FD44:FF44) -> 3293692.2 | BA44: =SUM(FG44:FI44) -> 3318986.1 | BB44: =SUM(FJ44:FL44) -> 2053800.8 | BF44: =SUM(BF33:BF36) -> 591199 | BG44: =SUM(BG33:BG36) -> 215715 | BH44: =SUM(BH33:BH36) -> 169267 | BI44: =SUM(BI33:BI36) -> 146174 | BJ44: =SUM(BJ33:BJ36) -> 307010 | BK44: =SUM(BK33:BK36) -> 268114 | BL44: =SUM(BL33:BL36) -> 317497 | BM44: =SUM(BM33:BM36) -> 367609 | ... FK44: =SUM(FK33:FK36) -> 1053666.9 | FN44: =SUM(FN33:FN36) -> 1102576 | FO44: =FK44-FJ44 -> 53533.066 | FP44: =FK44-FN44 -> -48909.026 | FQ44: =FL44-#REF! -> #REF! | FR44: =FM44-FO44 -> -53533.066 | FS44: =FK44-FN44 -> -48909.026 | FT44: =SUM($FJ44:FK44) -> 2053800.8 | FU44: =SUM('Financial plan'!$EY39:EZ39) -> 2205151.9 | FV44: =FT44-FU44 -> -151351.12
D45: Overheads | AZ45: =FD45 -> 0 | BB45: =FJ45 -> 0 | FT45: =SUM($FJ45:FK45) -> 0
E46: Staff Costs before bonus | F46: =SUM(F47:F51) -> -3791000 | G46: =SUM(R46:U46) -> -4037339 | H46: =SUM(V46:Y46) -> -4229555 | I46: =SUM(Z46:AC46) -> -5391425 | J46: =SUM(AD46:AG46) -> -5518861.6 | K46: =SUM(AH46:AK46) -> -8214488.3 | L46: =SUM(AL46:AO46) -> -9822865.4 | M46: =SUM(AP46:AS46) -> -9000305.6 | N46: =SUM(AT46:AW46) -> -8639670.5 | O46: =SUM(AX46:BA46) -> -7142699.6 | P46: =SUM($FJ46:FK46) -> -1139603.9 | R46: =SUM(BF46:BH46) -> -1068554 | S46: =SUM(BI46:BK46) -> -1009108 | T46: =SUM(BL46:BN46) -> -969751 | U46: =SUM(BO46:BQ46) -> -989926 | V46: =SUM(BR46:BT46) -> -990788 | W46: =SUM(BU46:BW46) -> -1088158 | X46: =SUM(BX46:BZ46) -> -1112226 | Y46: =SUM(CA46:CC46) -> -1038383 | Z46: =SUM(CD46:CF46) -> -1180444 | AA46: =SUM(CG46:CI46) -> -1325407 | AB46: =SUM(CJ46:CL46) -> -1410042 | AC46: =SUM(CM46:CO46) -> -1475532 | AD46: =SUM(CP46:CR46) -> -1490263 | AE46: =SUM(CS46:CU46) -> -1248141 | AF46: =SUM(CV46:CX46) -> -1255160.7 | AG46: =SUM(CY46:DA46) -> -1525296.9 | AH46: =SUM(DB46:DD46) -> -1819180.5 | AI46: =SUM(DE46:DG46) -> -1974437.1 | AJ46: =SUM(DH46:DJ46) -> -2140752.2 | AK46: =SUM(DK46:DM46) -> -2280118.6 | AL46: =SUM(DN46:DP46) -> -2485099.2 | AM46: =SUM(DQ46:DS46) -> -2570037.1 | AN46: =SUM(DT46:DV46) -> -2420398.9 | AO46: =SUM(DW46:DY46) -> -2347330.2 | AP46: =SUM(DZ46:EB46) -> -2278483 | AQ46: =OFFSET($DZ46,0,AQ$4)+OFFSET($EA46,0,AQ$4)+OFFSET($EB46,0,AQ$4) -> -2235904.6 | AR46: =OFFSET($DZ46,0,AR$4)+OFFSET($EA46,0,AR$4)+OFFSET($EB46,0,AR$4) -> -2261961.8 | AS46: =OFFSET($DZ46,0,AS$4)+OFFSET($EA46,0,AS$4)+OFFSET($EB46,0,AS$4) -> -2223956.1 | AT46: =SUM(EL46:EN46) -> -2228341.5 | AU46: =OFFSET($EL46,0,AU$4)+OFFSET($EM46,0,AU$4)+OFFSET($EN46,0,AU$4) -> -2168519 | AV46: =OFFSET($EL46,0,AV$4)+OFFSET($EM46,0,AV$4)+OFFSET($EN46,0,AV$4) -> -2196954.3 | AW46: =OFFSET($EL46,0,AW$4)+OFFSET($EM46,0,AW$4)+OFFSET($EN46,0,AW$4) -> -2045855.8 | AX46: =SUM(EX46:EZ46) -> -1863497.9 | AY46: =SUM(FA46:FC46) -> -1826491.2 | AZ46: =SUM(FD46:FF46) -> -1846611.9 | BA46: =SUM(FG46:FI46) -> -1606098.6 | BB46: =SUM(FJ46:FL46) -> -1139603.9 | BF46: -380676 | BG46: -348519 | BH46: -339359 | BI46: -352216 | BJ46: -339486 | BK46: -317406 | BL46: -331155 | BM46: -316603 | BN46: -321993 | BO46: -315049 | BP46: -336989 | BQ46: -337888 | BR46: =-315594+1873 -> -313721 | BS46: =-320231+1929 -> -318302 | BT46: =-365243+30000-(15000*0.758)-12152 -> -358765 | BU46: -354502 | BV46: -350092 | BW46: -383564 | BX46: -373728 | BY46: -369381 | BZ46: -369117 | CA46: -350661 | CB46: -378163 | CC46: -309559 | CD46: =-362919-9000 -> -371919 | CE46: -388029 | CF46: -420496 | CG46: =-527562+41000+32500 -> -454062 | CH46: -452228 | CI46: -419117 | CJ46: =-529247+15000 -> -514247 | CK46: =-488943+40000 -> -448943 | CL46: =-475852+17000+12000 -> -446852 | CM46: -474875 | CN46: -530495 | CO46: =-553162+83000 -> -470162 | CP46: -496546 | CQ46: -509283 | CR46: -484434 | CS46: -431544 | CT46: -408463 | CU46: -408134 | CV46: =-426924+13000 -> -413924 | CW46: -415308.43 | CX46: -425928.31 | CY46: -508756.25 | CZ46: -498380.55 | DA46: -518160.08 | DB46: -602704.73 | DC46: -624710.52 | DD46: -591765.22 | DE46: -598310.46 | DF46: -663932.32 | DG46: -712194.31 | DH46: -691829.63 | DI46: -723990.91 | DJ46: -724931.62 | DK46: -761328.93 | DL46: -766775.66 | DM46: -752014 | DN46: -821819.66 | DO46: -859035.74 | DP46: -804243.8 | DQ46: -888975.64 | DR46: -870782.07 | DS46: -810279.39 | DT46: -805402.25 | DU46: -792365.09 | DV46: -822631.59 | DW46: -767826.02 | DX46: -766623.99 | DY46: -812880.18 | DZ46: -799644.89 | EA46: -751062.5 | EB46: -727775.57 | EC46: -750417.22 | ED46: -726261.97 | EE46: -759225.44 | EF46: -764461.4 | EG46: -750540.46 | EH46: -746959.96 | EI46: -753544.65 | EJ46: -774611.75 | EK46: -695799.75 | EL46: -740090.76 | EM46: -738522.21 | EN46: -749728.49 | EO46: -727697.62 | EP46: -712734.19 | EQ46: -728087.18 | ER46: -739815.69 | ES46: -745189.49 | ET46: -711949.09 | EU46: -744854.83 | EV46: -693079.93 | EW46: -607921.02 | EX46: =SUM(EX47:EX49) -> -621235.74 | EY46: =-689802.971350273-EY61 -> -629092.23 | EZ46: =-674091.435311964-EZ61 -> -613169.95 | FA46: =-665278.23794974-FA61 -> -607112.72 | FB46: =-669815.761926187+30192-FB61 -> -614513.23 | FC46: =-606153.839223977-FC61 -> -604865.26 | FD46: =-616660.727199158-FD61 -> -616590.74 | FE46: =-617980.241435366+384 -> -617596.24 | FF46: =-621250.171716019-FF61 -> -612424.89 | FG46: -564632.65 | FH46: =-591688.155446946-FH61 -> -539420.16 | FI46: =-587685.342120415-FI61 -> -502045.76 | FJ46: =-626657.781435291-FJ61 -> -569245.78 | FK46: =-628251.140092751-FK61 -> -570358.14 | FN46: ='Financial plan'!EZ41 -> -573474.34 | FO46: =FK46-FJ46 -> -1112.3587 | FP46: =FK46-FN46 -> 3116.2019 | FQ46: =FL46-#REF! -> #REF! | FR46: =FM46-FO46 -> 1112.3587 | FS46: =FK46-FN46 -> 3116.2019 | FT46: =SUM($FJ46:FK46) -> -1139603.9 | FU46: =SUM('Financial plan'!$EY41:EZ41) -> -1146948.7 | FV46: =FT46-FU46 -> 7344.7625
E47: Gross pay/bonus/pension etc | F47: -3791000 | G47: =SUM(R47:U47) -> -4008000 | H47: =SUM(V47:Y47) -> 0 | K47: =SUM(AH47:AK47) -> -7897373.2 | L47: =SUM(AL47:AO47) -> -9447679.5 | M47: =SUM(AP47:AS47) -> -8773379.1 | N47: =SUM(AT47:AW47) -> -8282140.7 | O47: =SUM(AX47:BA47) -> -4926265.7 | P47: =SUM($FJ47:FK47) -> -1110650.6 | R47: -1062000 | S47: -1002000 | T47: -969000 | U47: -975000 | AH47: =SUM(DB47:DD47) -> -1727722.9 | AI47: =SUM(DE47:DG47) -> -1889024.1 | AJ47: =SUM(DH47:DJ47) -> -2109192.4 | AK47: =SUM(DK47:DM47) -> -2171433.8 | AL47: =SUM(DN47:DP47) -> -2428490.4 | AM47: =SUM(DQ47:DS47) -> -2496986 | AN47: =SUM(DT47:DV47) -> -2330180.4 | AO47: =SUM(DW47:DY47) -> -2192022.7 | AP47: =SUM(DZ47:EB47) -> -2217680.1 | AQ47: =OFFSET($DZ47,0,AQ$4)+OFFSET($EA47,0,AQ$4)+OFFSET($EB47,0,AQ$4) -> -2180446.8 | AR47: =OFFSET($DZ47,0,AR$4)+OFFSET($EA47,0,AR$4)+OFFSET($EB47,0,AR$4) -> -2203733.2 | AS47: =OFFSET($DZ47,0,AS$4)+OFFSET($EA47,0,AS$4)+OFFSET($EB47,0,AS$4) -> -2171519 | AT47: =SUM(EL47:EN47) -> -2177881.8 | AU47: =OFFSET($EL47,0,AU$4)+OFFSET($EM47,0,AU$4)+OFFSET($EN47,0,AU$4) -> -2230371.2 | AV47: =OFFSET($EL47,0,AV$4)+OFFSET($EM47,0,AV$4)+OFFSET($EN47,0,AV$4) -> -2165808.5 | AW47: =OFFSET($EL47,0,AW$4)+OFFSET($EM47,0,AW$4)+OFFSET($EN47,0,AW$4) -> -1708079.1 | AX47: =SUM(EX47:EZ47) -> -1836942.3 | AY47: =SUM(FA47:FC47) -> -1935104.6 | AZ47: =FD47 -> -606197.97 | BA47: =FG47 -> -548020.78 | BB47: =SUM(FJ47:FL47) -> -1110650.6 | BF47: 380676 | CT47: =CS47-CR47 -> 0 | DB47: -561651.76 | DC47: -583824.11 | DD47: -582247.03 | DE47: =DE46-DE48-DE49 -> -570788.47 | DF47: =DF46-DF48-DF49 -> -643163.51 | DG47: =DG46-DG48-DG49 -> -675072.07 | DH47: =DH46-DH48-DH49 -> -679410.43 | DI47: =DI46-DI48-DI49 -> -713271.09 | DJ47: =DJ46-DJ48-DJ49 -> -716510.93 | DK47: =DK46-DK48-DK49 -> -729235.66 | DL47: =DL46-DL48-DL49 -> -747863.44 | ... ED47: =ED46-ED48-ED49 -> -705736.9 | EE47: -744817.74 | EF47: -738412.18 | EG47: -733804.02 | EH47: -731516.99 | EI47: -741805.33 | EJ47: -748716.61 | EK47: -680997.08 | EL47: =EL46-EL48-EL49 -> -725284.23 | EM47: =EM46-EM48-EM49 -> -723696.96 | EN47: =EN46-EN48-EN49 -> -728900.65 | EO47: =EO46-EO48-EO49 -> -710146.28 | EP47: -752407.26 | EQ47: -767817.68 | ER47: -767278.67 | ES47: -718278.57 | ET47: -680251.27 | EU47: -702180.77 | EV47: -602204.67 | EW47: -403693.66 | EX47: =-673223.086246999-EX61 -> -612128.36 | EY47: =-673223.086246999-EY61 -> -612512.35 | EZ47: =-673223.086246999-EZ61 -> -612301.6 | FA47: =-673223.086246999-FA61 -> -615057.57 | FB47: =-673223.086246999-FB61 -> -648112.55 | FC47: =-673223.086246999-FC61 -> -671934.51 | FD47: =-606267.958073686-FD61 -> -606197.97 | FE47: -606210.21 | FF47: =-608026.653100257-FF61 -> -599201.37 | FG47: -548020.78 | FH47: =-579696.033020572-FH61 -> -527428.03 | FI47: =-574809.41297516-FI61 -> -489169.84 | FJ47: =-617602.556969026-FJ61 -> -560190.56 | FK47: =-608353.066390732-FK61 -> -550460.07 | FN47: ='[1]Financial plan'!EW42 -> 0 | FO47: =FK47-FJ47 -> 9730.4906 | FP47: =FK47-FN47 -> -550460.07 | FQ47: =FL47-#REF! -> #REF! | FR47: =FM47-FO47 -> -9730.4906 | FS47: =FK47-FN47 -> -550460.07 | FT47: =SUM($FJ47:FK47) -> -1110650.6 | FV47: =FT47-FU47 -> -1110650.6
E48: Recruitment costs | F48: 0 | G48: =SUM(R48:U48) -> 0 | H48: =SUM(V48:Y48) -> 0 | K48: =SUM(AH48:AK48) -> -184126.84 | L48: =SUM(AL48:AO48) -> -53708.65 | M48: =SUM(AP48:AS48) -> -22995.171 | N48: =SUM(AT48:AW48) -> -31651.133 | O48: =SUM(AX48:BA48) -> -13095.913 | P48: =SUM($FJ48:FK48) -> -12713.02 | R48: 0 | S48: 0 | T48: 0 | U48: 0 | AH48: =SUM(DB48:DD48) -> -74915.978 | AI48: =SUM(DE48:DG48) -> -64864.438 | AJ48: =SUM(DH48:DJ48) -> -13043.26 | AK48: =SUM(DK48:DM48) -> -31303.165 | AL48: =SUM(DN48:DP48) -> -18668.25 | AM48: =SUM(DQ48:DS48) -> -18039.71 | AN48: =SUM(DT48:DV48) -> -8525.15 | AO48: =SUM(DW48:DY48) -> -8475.54 | AP48: =SUM(DZ48:EB48) -> -5607.53 | AQ48: =OFFSET($DZ48,0,AQ$4)+OFFSET($EA48,0,AQ$4)+OFFSET($EB48,0,AQ$4) -> -6506.86 | AR48: =OFFSET($DZ48,0,AR$4)+OFFSET($EA48,0,AR$4)+OFFSET($EB48,0,AR$4) -> -7250.26 | AS48: =OFFSET($DZ48,0,AS$4)+OFFSET($EA48,0,AS$4)+OFFSET($EB48,0,AS$4) -> -3630.5215 | AT48: =SUM(EL48:EN48) -> -7395.0042 | AU48: =OFFSET($EL48,0,AU$4)+OFFSET($EM48,0,AU$4)+OFFSET($EN48,0,AU$4) -> -11847.455 | AV48: =OFFSET($EL48,0,AV$4)+OFFSET($EM48,0,AV$4)+OFFSET($EN48,0,AV$4) -> -8652.0546 | AW48: =OFFSET($EL48,0,AW$4)+OFFSET($EM48,0,AW$4)+OFFSET($EN48,0,AW$4) -> -3756.62 | AX48: =SUM(EX48:EZ48) -> -2964.14 | AY48: =SUM(FA48:FC48) -> -4160.6133 | AZ48: =FD48 -> -942.42 | BA48: =FG48 -> -5028.74 | BB48: =SUM(FJ48:FL48) -> -12713.02 | BF48: 380676 | CT48: =CS48-CR48 -> 0 | DB48: -32407.05 | DC48: -37793.548 | DD48: -4715.38 | DE48: -22393.328 | DF48: -14010.53 | DG48: -28460.58 | DH48: -6854.63 | DI48: -3754.39 | DJ48: -2434.24 | DK48: -17571.72 | DL48: -1875.42 | DM48: -11856.025 | DN48: -8671.97 | DO48: -6647 | DP48: -3349.28 | DQ48: -13045.5 | DR48: -3249.83 | DS48: -1744.38 | DT48: -2374.76 | DU48: -2767.79 | DV48: -3382.6 | DW48: -3260.28 | DX48: -2933.08 | DY48: -2282.18 | DZ48: -1624.75 | EA48: -1353.53 | EB48: -2629.25 | EC48: -2629.25 | ED48: -2629.25 | EE48: -1248.36 | EF48: -2550.86 | EG48: -2397.16 | EH48: -2302.24 | EI48: -1327.1 | EJ48: -1400.49 | EK48: -902.93149 | EL48: -1407.43 | EM48: -1205.91 | EN48: -4781.6642 | EO48: -7263.4745 | EP48: -3703.09 | EQ48: -880.89 | ER48: -5301.5846 | ES48: -3651.75 | ET48: 301.28 | EU48: -1560.88 | EV48: -1199.81 | EW48: -995.93 | EX48: -979.75 | EY48: -735.41 | EZ48: -1248.98 | FA48: -1344.036 | FB48: -1241.6173 | FC48: -1574.96 | FD48: -942.42 | FE48: -883.19 | FF48: -979.91 | FG48: -5028.74 | FH48: -1297.46 | FI48: -1290.52 | FJ48: -1176.11 | FK48: -11536.91 | FN48: ='[1]Financial plan'!EW43 -> 0 | FO48: =FK48-FJ48 -> -10360.8 | FP48: =FK48-FN48 -> -11536.91 | FQ48: =FL48-#REF! -> #REF! | FR48: =FM48-FO48 -> 10360.8 | FS48: =FK48-FN48 -> -11536.91 | FT48: =SUM($FJ48:FK48) -> -12713.02 | FV48: =FT48-FU48 -> -12713.02
E49: Other staff costs (training etc) | F49: 0 | G49: =SUM(R49:U49) -> 0 | H49: =SUM(V49:Y49) -> 0 | K49: =SUM(AH49:AK49) -> -132988.27 | L49: =SUM(AL49:AO49) -> -321477.22 | M49: =SUM(AP49:AS49) -> -203931.29 | N49: =SUM(AT49:AW49) -> -163945.8 | O49: =SUM(AX49:BA49) -> -81593.006 | P49: =SUM($FJ49:FK49) -> -16240.278 | S49: 0 | T49: 0 | U49: 0 | AH49: =SUM(DB49:DD49) -> -16541.603 | AI49: =SUM(DE49:DG49) -> -20548.6 | AJ49: =SUM(DH49:DJ49) -> -18516.459 | AK49: =SUM(DK49:DM49) -> -77381.605 | AL49: =SUM(DN49:DP49) -> -37940.52 | AM49: =SUM(DQ49:DS49) -> -55011.382 | AN49: =SUM(DT49:DV49) -> -81693.357 | AO49: =SUM(DW49:DY49) -> -146831.96 | AP49: =SUM(DZ49:EB49) -> -55195.347 | AQ49: =OFFSET($DZ49,0,AQ$4)+OFFSET($EA49,0,AQ$4)+OFFSET($EB49,0,AQ$4) -> -48950.986 | AR49: =OFFSET($DZ49,0,AR$4)+OFFSET($EA49,0,AR$4)+OFFSET($EB49,0,AR$4) -> -50978.362 | AS49: =OFFSET($DZ49,0,AS$4)+OFFSET($EA49,0,AS$4)+OFFSET($EB49,0,AS$4) -> -48806.597 | AT49: =SUM(EL49:EN49) -> -43064.624 | AU49: =OFFSET($EL49,0,AU$4)+OFFSET($EM49,0,AU$4)+OFFSET($EN49,0,AU$4) -> -31407.651 | AV49: =OFFSET($EL49,0,AV$4)+OFFSET($EM49,0,AV$4)+OFFSET($EN49,0,AV$4) -> -36626.069 | AW49: =OFFSET($EL49,0,AW$4)+OFFSET($EM49,0,AW$4)+OFFSET($EN49,0,AW$4) -> -52847.455 | AX49: =SUM(EX49:EZ49) -> -33395.302 | AY49: =SUM(FA49:FC49) -> -27164.218 | AZ49: =FD49 -> -9450.3491 | BA49: =FG49 -> -11583.136 | BB49: =SUM(FJ49:FL49) -> -16240.278 | BF49: 380676 | CT49: =CS49-CR49 -> 0 | DB49: -8645.9264 | DC49: -3092.8677 | DD49: -4802.8085 | DE49: -5128.6621 | DF49: -6758.2807 | DG49: -8661.6574 | DH49: -5564.5734 | DI49: -6965.431 | DJ49: -5986.4543 | DK49: -14521.548 | DL49: -17036.797 | DM49: -45823.26 | DN49: -9800.75 | DO49: -8925 | DP49: =5785.23-25000 -> -19214.77 | DQ49: -11638.515 | DR49: -23728.981 | DS49: -19643.885 | DT49: -21906.274 | DU49: -8291.8173 | DV49: -51495.265 | DW49: -27074.442 | DX49: -29676.583 | DY49: -90080.939 | DZ49: -24965.008 | EA49: -12334.518 | EB49: -17895.821 | EC49: -17895.821 | ED49: -17895.821 | EE49: =EE46-EE47-EE48 -> -13159.343 | EF49: -23498.356 | EG49: -14339.279 | EH49: -13140.727 | EI49: -10412.22 | EJ49: -24494.645 | EK49: -13899.732 | EL49: -13399.099 | EM49: -13619.342 | EN49: -16046.182 | EO49: -10287.87 | EP49: -9076.5042 | EQ49: -12043.278 | ER49: -11520.119 | ES49: -14516.118 | ET49: -10589.832 | EU49: -12701.22 | EV49: -11201.566 | EW49: -28944.669 | EX49: -8127.6274 | EY49: -15352.548 | EZ49: -9915.1264 | FA49: -7558.8518 | FB49: -9714.268 | FC49: -9891.0988 | FD49: -9450.3491 | FE49: -10886.841 | FF49: -12243.609 | FG49: -11583.136 | FH49: -10694.662 | FI49: -11585.409 | FJ49: -7879.1145 | FK49: -8361.1637 | FN49: ='[1]Financial plan'!EW44 -> 0 | FO49: =FK49-FJ49 -> -482.04924 | FP49: =FK49-FN49 -> -8361.1637 | FQ49: =FL49-#REF! -> #REF! | FR49: =FM49-FO49 -> 482.04924 | FS49: =FK49-FN49 -> -8361.1637 | FT49: =SUM($FJ49:FK49) -> -16240.278 | FV49: =FT49-FU49 -> -16240.278
F50: 0 | G50: =SUM(R50:U50) -> 0 | H50: =SUM(V50:Y50) -> 0 | L50: =SUM(AL50:AO50) -> 0 | M50: =SUM(AP50:AS50) -> 0 | N50: =SUM(AT50:BA50) -> 0 | P50: =SUM($FJ50:FK50) -> 0 | R50: 0 | S50: 0 | T50: 0 | U50: 0 | AJ50: =SUM(DH50:DJ50) -> 0 | AK50: =SUM(DK50:DM50) -> 0 | AL50: =SUM(DN50:DP50) -> 0 | AM50: =SUM(DQ50:DS50) -> 0 | AN50: =SUM(DT50:DV50) -> 0 | AO50: =SUM(DW50:DY50) -> 0 | AP50: =SUM(DZ50:EB50) -> 0 | AQ50: =OFFSET($DZ50,0,AQ$4)+OFFSET($EA50,0,AQ$4)+OFFSET($EB50,0,AQ$4) -> 0 | AR50: =OFFSET($DZ50,0,AR$4)+OFFSET($EA50,0,AR$4)+OFFSET($EB50,0,AR$4) -> 0 | AS50: =OFFSET($DZ50,0,AS$4)+OFFSET($EA50,0,AS$4)+OFFSET($EB50,0,AS$4) -> 0 | AT50: =SUM(EL50:EN50) -> 0 | AU50: =OFFSET($EL50,0,AU$4)+OFFSET($EM50,0,AU$4)+OFFSET($EN50,0,AU$4) -> 0 | AV50: =OFFSET($EL50,0,AV$4)+OFFSET($EM50,0,AV$4)+OFFSET($EN50,0,AV$4) -> 0 | AW50: =OFFSET($EL50,0,AW$4)+OFFSET($EM50,0,AW$4)+OFFSET($EN50,0,AW$4) -> 0 | AX50: =SUM(EX50:EZ50) -> 0 | AY50: =SUM(FA50:FC50) -> 0 | AZ50: =FD50 -> 0 | BA50: =FG50 -> 0 | BB50: =SUM(FJ50:FL50) -> 0 | BF50: 380676 | CT50: =CS50-CR50 -> 0
H51: =SUM(V51:Y51) -> 0 | L51: =SUM(AL51:AO51) -> 0 | M51: =SUM(AP51:AS51) -> 0 | N51: =SUM(AT51:BA51) -> 0 | P51: =SUM($FJ51:FK51) -> 0 | R51: 0 | S51: 0 | T51: 0 | U51: 0 | AJ51: =SUM(DH51:DJ51) -> 0 | AK51: =SUM(DK51:DM51) -> 0 | AL51: =SUM(DN51:DP51) -> 0 | AM51: =SUM(DQ51:DS51) -> 0 | AN51: =SUM(DT51:DV51) -> 0 | AO51: =SUM(DW51:DY51) -> 0 | AP51: =SUM(DZ51:EB51) -> 0 | AQ51: =OFFSET($DZ51,0,AQ$4)+OFFSET($EA51,0,AQ$4)+OFFSET($EB51,0,AQ$4) -> 0 | AR51: =OFFSET($DZ51,0,AR$4)+OFFSET($EA51,0,AR$4)+OFFSET($EB51,0,AR$4) -> 0 | AS51: =OFFSET($DZ51,0,AS$4)+OFFSET($EA51,0,AS$4)+OFFSET($EB51,0,AS$4) -> 0 | AT51: =SUM(EL51:EN51) -> 0 | AU51: =OFFSET($EL51,0,AU$4)+OFFSET($EM51,0,AU$4)+OFFSET($EN51,0,AU$4) -> 0 | AV51: =OFFSET($EL51,0,AV$4)+OFFSET($EM51,0,AV$4)+OFFSET($EN51,0,AV$4) -> 0 | AW51: =OFFSET($EL51,0,AW$4)+OFFSET($EM51,0,AW$4)+OFFSET($EN51,0,AW$4) -> 0 | AX51: =SUM(EX51:EZ51) -> 0 | AY51: =SUM(FA51:FC51) -> 0 | AZ51: =FD51 -> 0 | BA51: =FG51 -> 0 | BB51: =SUM(FJ51:FL51) -> 0 | BF51: 380676 | CT51: =CS51-CR51 -> 0
L52: =SUM(AL52:AO52) -> 0 | M52: =SUM(AP52:AS52) -> 0 | N52: =SUM(AT52:BA52) -> 0 | O52: =SUM(AX52:BA52) -> 0 | P52: =SUM($FJ52:FK52) -> 0 | AJ52: =SUM(DH52:DJ52) -> 0 | AK52: =SUM(DK52:DM52) -> 0 | AL52: =SUM(DN52:DP52) -> 0 | AM52: =SUM(DQ52:DS52) -> 0 | AN52: =SUM(DT52:DV52) -> 0 | AO52: =SUM(DW52:DY52) -> 0 | AP52: =SUM(DZ52:EB52) -> 0 | AQ52: =OFFSET($DZ52,0,AQ$4)+OFFSET($EA52,0,AQ$4)+OFFSET($EB52,0,AQ$4) -> 0 | AR52: =OFFSET($DZ52,0,AR$4)+OFFSET($EA52,0,AR$4)+OFFSET($EB52,0,AR$4) -> 0 | AS52: =OFFSET($DZ52,0,AS$4)+OFFSET($EA52,0,AS$4)+OFFSET($EB52,0,AS$4) -> 0 | AT52: =SUM(EL52:EN52) -> 0 | AU52: =OFFSET($EL52,0,AU$4)+OFFSET($EM52,0,AU$4)+OFFSET($EN52,0,AU$4) -> 0 | AV52: =OFFSET($EL52,0,AV$4)+OFFSET($EM52,0,AV$4)+OFFSET($EN52,0,AV$4) -> 0 | AW52: =OFFSET($EL52,0,AW$4)+OFFSET($EM52,0,AW$4)+OFFSET($EN52,0,AW$4) -> 0 | AX52: =SUM(EX52:EZ52) -> 0 | AY52: =SUM(FA52:FC52) -> 0 | AZ52: =FD52 -> 0 | BA52: =FG52 -> 0 | BB52: =SUM(FJ52:FL52) -> 0 | BF52: 380676 | BI52: =$W52/3 -> 0 | BJ52: =$W52/3 -> 0 | BK52: =$W52/3 -> 0 | BL52: =$X52/3 -> 0 | BM52: =$X52/3 -> 0 | BN52: =$X52/3 -> 0 | BO52: =$Y52/3 -> 0 | BP52: =$Y52/3 -> 0 | BQ52: =$Y52/3 -> 0 | BR52: =$V52/3 -> 0 | BS52: =$V52/3 -> 0 | BT52: =$V52/3 -> 0 | BU52: =$W52/3 -> 0 | BV52: =$W52/3 -> 0 | BW52: =$W52/3 -> 0 | BX52: =$X52/3 -> 0 | BY52: =$X52/3 -> 0 | BZ52: =$X52/3 -> 0 | CA52: =$Y52/3 -> 0 | CB52: =$Y52/3 -> 0 | CC52: =$Y52/3 -> 0 | CD52: =$Y52/3 -> 0 | CT52: =CS52-CR52 -> 0
E53: Technical | F53: -171000 | G53: =SUM(R53:U53) -> -257104 | H53: =SUM(V53:Y53) -> -385909 | I53: =SUM(Z53:AC53) -> -534421 | J53: =SUM(AD53:AG53) -> -872341.57 | K53: =SUM(AH53:AK53) -> -1146244.9 | L53: =SUM(AL53:AO53) -> -1642108.8 | M53: =SUM(AP53:AS53) -> -1764564 | N53: =SUM(AT53:AW53) -> -1905862 | O53: =SUM(AX53:BA53) -> -2393615.6 | P53: =SUM($FJ53:FK53) -> -387501.02 | R53: =SUM(BF53:BH53) -> -56182 | S53: =SUM(BI53:BK53) -> -58549 | T53: =SUM(BL53:BN53) -> -68850 | U53: =SUM(BO53:BQ53) -> -73523 | V53: =SUM(BR53:BT53) -> -93756 | W53: =SUM(BU53:BW53) -> -73436 | X53: =SUM(BX53:BZ53) -> -93891 | Y53: =SUM(CA53:CC53) -> -124826 | Z53: =SUM(CD53:CF53) -> -145309 | AA53: =SUM(CG53:CI53) -> -134503 | AB53: =SUM(CJ53:CL53) -> -119646 | AC53: =SUM(CM53:CO53) -> -134963 | AD53: =SUM(CP53:CR53) -> -151827 | AE53: =SUM(CS53:CU53) -> -229115 | AF53: =SUM(CV53:CX53) -> -264283.91 | AG53: =SUM(CY53:DA53) -> -227115.66 | AH53: =SUM(DB53:DD53) -> -253185.52 | AI53: =SUM(DE53:DG53) -> -259953.32 | AJ53: =SUM(DH53:DJ53) -> -282228.56 | AK53: =SUM(DK53:DM53) -> -350877.47 | AL53: =SUM(DN53:DP53) -> -406322.64 | AM53: =SUM(DQ53:DS53) -> -391701.45 | AN53: =SUM(DT53:DV53) -> -444530.28 | AO53: =SUM(DW53:DY53) -> -399554.47 | AP53: =SUM(DZ53:EB53) -> -414863.42 | AQ53: =OFFSET($DZ53,0,AQ$4)+OFFSET($EA53,0,AQ$4)+OFFSET($EB53,0,AQ$4) -> -454507.34 | AR53: =OFFSET($DZ53,0,AR$4)+OFFSET($EA53,0,AR$4)+OFFSET($EB53,0,AR$4) -> -437878.8 | AS53: =OFFSET($DZ53,0,AS$4)+OFFSET($EA53,0,AS$4)+OFFSET($EB53,0,AS$4) -> -457314.41 | AT53: =SUM(EL53:EN53) -> -452128.78 | AU53: =OFFSET($EL53,0,AU$4)+OFFSET($EM53,0,AU$4)+OFFSET($EN53,0,AU$4) -> -505643.58 | AV53: =OFFSET($EL53,0,AV$4)+OFFSET($EM53,0,AV$4)+OFFSET($EN53,0,AV$4) -> -449819.46 | AW53: =OFFSET($EL53,0,AW$4)+OFFSET($EM53,0,AW$4)+OFFSET($EN53,0,AW$4) -> -498270.18 | AX53: =SUM(EX53:EZ53) -> -583252.24 | AY53: =SUM(FA53:FC53) -> -599042.53 | AZ53: =SUM(FD53:FF53) -> -601348.39 | BA53: =SUM(FG53:FI53) -> -609972.39 | BB53: =SUM(FJ53:FL53) -> -387501.02 | BF53: -18802 | BG53: -15974 | BH53: -21406 | BI53: -19152 | BJ53: -18258 | BK53: -21139 | BL53: -29724 | BM53: -11816 | BN53: -27310 | BO53: -23078 | BP53: -27287 | BQ53: -23158 | BR53: =-20961-35 -> -20996 | BS53: =-28878-681 -> -29559 | BT53: =-27077-30000+12152+1724 -> -43201 | BU53: -30228 | BV53: -26338 | BW53: -16870 | BX53: -31472 | BY53: -30962 | BZ53: -31457 | CA53: -37465 | CB53: -37098 | CC53: -50263 | CD53: -37301 | CE53: =-41757-11000 -> -52757 | CF53: -55251 | CG53: -41277 | CH53: -30359 | CI53: -62867 | CJ53: -42239 | CK53: -34332 | CL53: -43075 | CM53: -43334 | CN53: -37498 | CO53: -54131 | CP53: -42541 | CQ53: -45703 | CR53: -63583 | CS53: -66175 | CT53: -80722 | CU53: -82218 | CV53: =-81944-4000 -> -85944 | CW53: -84070.71 | CX53: -94269.2 | CY53: -84768.9 | CZ53: -63708.13 | DA53: -78638.63 | DB53: -87083.88 | DC53: -81735.09 | DD53: -84366.55 | DE53: -83905 | DF53: -85429.81 | DG53: -90618.51 | DH53: -86197.4 | DI53: -92249.88 | DJ53: -103781.28 | DK53: -106851.23 | DL53: -115429.48 | DM53: =37969.24-166566 -> -128596.76 | DN53: -119369.52 | DO53: -133357.01 | DP53: -153596.11 | DQ53: -125015.97 | DR53: -133588.51 | DS53: -133096.97 | DT53: -145816.88 | DU53: -151701.39 | DV53: -147012.01 | DW53: -131660.84 | DX53: -134633.89 | DY53: -133259.74 | DZ53: -136913.74 | EA53: -138827.84 | EB53: -139121.83 | EC53: -149490.3 | ED53: -153749.01 | EE53: -151268.04 | EF53: -141645.71 | EG53: -144999.54 | EH53: -151233.55 | EI53: -158256.45 | EJ53: -144979.13 | EK53: -154078.83 | EL53: -143962.61 | EM53: -154605.1 | EN53: -153561.07 | EO53: -165466.1 | EP53: -168924.46 | EQ53: -171253.02 | ER53: -172135.77 | ES53: -170529.95 | ET53: -107153.74 | EU53: -165893.78 | EV53: -166502.49 | EW53: -165873.91 | EX53: -198486.88 | EY53: -195717.92 | EZ53: -189047.43 | FA53: -193519.85 | FB53: -200110.97 | FC53: -205411.71 | FD53: -203222.71 | FE53: -199215.63 | FF53: -198910.06 | FG53: -206843.86 | FH53: -199749.42 | FI53: -203379.11 | FJ53: -194013.99 | FK53: -193487.03 | FN53: ='Financial plan'!EZ48 -> -209590.33 | FO53: =FK53-FJ53 -> 526.95747 | FP53: =FK53-FN53 -> 16103.301 | FQ53: =FL53-#REF! -> #REF! | FR53: =FM53-FO53 -> -526.95747 | FS53: =FK53-FN53 -> 16103.301 | FT53: =SUM($FJ53:FK53) -> -387501.02 | FU53: =SUM('Financial plan'!$EY48:EZ48) -> -419180.67 | FV53: =FT53-FU53 -> 31679.644
E54: Office | F54: -222000 | G54: =SUM(R54:U54) -> -311697 | H54: =SUM(V54:Y54) -> -474212 | I54: =SUM(Z54:AC54) -> -509991 | J54: =SUM(AD54:AG54) -> -505231.03 | K54: =SUM(AH54:AK54) -> -472606.64 | L54: =SUM(AL54:AO54) -> -478766.52 | M54: =SUM(AP54:AS54) -> -605595.18 | N54: =SUM(AT54:AW54) -> -631653.5 | O54: =SUM(AX54:BA54) -> -636961.01 | P54: =SUM($FJ54:FK54) -> -79138.736 | R54: =SUM(BF54:BH54) -> -68832 | S54: =SUM(BI54:BK54) -> -69024 | T54: =SUM(BL54:BN54) -> -83732 | U54: =SUM(BO54:BQ54) -> -90109 | V54: =SUM(BR54:BT54) -> -98436 | W54: =SUM(BU54:BW54) -> -92223 | X54: =SUM(BX54:BZ54) -> -110013 | Y54: =SUM(CA54:CC54) -> -173540 | Z54: =SUM(CD54:CF54) -> -138902 | AA54: =SUM(CG54:CI54) -> -116654 | AB54: =SUM(CJ54:CL54) -> -144689 | AC54: =SUM(CM54:CO54) -> -109746 | AD54: =SUM(CP54:CR54) -> -134024 | AE54: =SUM(CS54:CU54) -> -137757 | AF54: =SUM(CV54:CX54) -> -112461.36 | AG54: =SUM(CY54:DA54) -> -120988.67 | AH54: =SUM(DB54:DD54) -> -116735.15 | AI54: =SUM(DE54:DG54) -> -110137.55 | AJ54: =SUM(DH54:DJ54) -> -128387.67 | AK54: =SUM(DK54:DM54) -> -117346.27 | AL54: =SUM(DN54:DP54) -> -110646.12 | AM54: =SUM(DQ54:DS54) -> -120079.58 | AN54: =SUM(DT54:DV54) -> -110476.57 | AO54: =SUM(DW54:DY54) -> -137564.25 | AP54: =SUM(DZ54:EB54) -> -124010.88 | AQ54: =OFFSET($DZ54,0,AQ$4)+OFFSET($EA54,0,AQ$4)+OFFSET($EB54,0,AQ$4) -> -146763.18 | AR54: =OFFSET($DZ54,0,AR$4)+OFFSET($EA54,0,AR$4)+OFFSET($EB54,0,AR$4) -> -163414.96 | AS54: =OFFSET($DZ54,0,AS$4)+OFFSET($EA54,0,AS$4)+OFFSET($EB54,0,AS$4) -> -171406.15 | AT54: =SUM(EL54:EN54) -> -158224.4 | AU54: =OFFSET($EL54,0,AU$4)+OFFSET($EM54,0,AU$4)+OFFSET($EN54,0,AU$4) -> -126750.48 | AV54: =OFFSET($EL54,0,AV$4)+OFFSET($EM54,0,AV$4)+OFFSET($EN54,0,AV$4) -> -152028.24 | AW54: =OFFSET($EL54,0,AW$4)+OFFSET($EM54,0,AW$4)+OFFSET($EN54,0,AW$4) -> -194650.38 | AX54: =SUM(EX54:EZ54) -> -140550.58 | AY54: =SUM(FA54:FC54) -> -159301.68 | AZ54: =SUM(FD54:FF54) -> -171039.33 | BA54: =SUM(FG54:FI54) -> -166069.42 | BB54: =SUM(FJ54:FL54) -> -79138.736 | BF54: -23237 | BG54: -17214 | BH54: -28381 | BI54: -16497 | BJ54: -27748 | BK54: -24779 | BL54: -29500 | BM54: -27438 | BN54: -26794 | BO54: -33345 | BP54: -22056 | BQ54: -34708 | BR54: =-37387-1873+35 -> -39225 | BS54: =-29409-1929+681 -> -30657 | BT54: =-26830-1724 -> -28554 | BU54: -30764 | BV54: -32015 | BW54: -29444 | BX54: -37706 | BY54: -36937 | BZ54: -35370 | CA54: -42969 | CB54: -35858 | CC54: -94713 | CD54: -47790 | CE54: -45466 | CF54: -45646 | CG54: -37559 | CH54: -34560 | CI54: -44535 | CJ54: -43657 | CK54: -49483 | CL54: -51549 | CM54: -51640 | CN54: =-50726+5000 -> -45726 | CO54: -12380 | CP54: =-58736+5000 -> -53736 | CQ54: -38231 | CR54: =-49057+7000 -> -42057 | CS54: -46071 | CT54: -45246 | CU54: =-38440-8000 -> -46440 | CV54: -38902 | CW54: -34238.33 | CX54: -39321.03 | CY54: -41118.56 | CZ54: -40758.87 | DA54: -39111.24 | DB54: -40303.81 | DC54: -38808.87 | DD54: -37622.47 | DE54: -35045.36 | DF54: -36997.33 | DG54: -38094.86 | DH54: =-48708.81+3378 -> -45330.81 | DI54: -38449.25 | DJ54: -44607.61 | DK54: -36368.43 | DL54: -41885.12 | DM54: -39092.72 | DN54: -38539.95 | DO54: -35243.01 | DP54: -36863.16 | DQ54: -39738.75 | DR54: -41766.68 | DS54: -38574.15 | DT54: -38320.44 | DU54: -30317.37 | DV54: -41838.76 | DW54: -38779.08 | DX54: -40593.39 | DY54: -58191.78 | DZ54: -36855.612 | EA54: -47233.303 | EB54: -39921.97 | EC54: -45583.44 | ED54: -47250.191 | EE54: -53929.552 | EF54: -54034.779 | EG54: -51833.283 | EH54: -57546.897 | EI54: -46701.917 | EJ54: -54096.737 | EK54: -70607.498 | EL54: -61044.452 | EM54: -55056.153 | EN54: -42123.794 | EO54: -39609.781 | EP54: -56271.911 | EQ54: -30868.791 | ER54: -58938.54 | ES54: -42811.639 | ET54: -50278.057 | EU54: -80319.095 | EV54: -56173.993 | EW54: -58157.29 | EX54: -43886.042 | EY54: -55450.819 | EZ54: -41213.723 | FA54: -52553.787 | FB54: -52245.288 | FC54: -54502.605 | FD54: -50716.75 | FE54: -53708.582 | FF54: -66613.995 | FG54: -58622.522 | FH54: -63665.971 | FI54: -43780.925 | FJ54: =-61208.1719057155+16168 -> -45040.172 | FK54: -34098.564 | FN54: ='Financial plan'!EZ49 -> -54281 | FO54: =FK54-FJ54 -> 10941.608 | FP54: =FK54-FN54 -> 20182.436 | FQ54: =FL54-#REF! -> #REF! | FR54: =FM54-FO54 -> -10941.608 | FS54: =FK54-FN54 -> 20182.436 | FT54: =SUM($FJ54:FK54) -> -79138.736 | FU54: =SUM('Financial plan'!$EY49:EZ49) -> -108562 | FV54: =FT54-FU54 -> 29423.264
E55: Travel & Entertainment | F55: -292000 | G55: =SUM(R55:U55) -> -288564 | H55: =SUM(V55:Y55) -> -260407 | I55: =SUM(Z55:AC55) -> -296323 | J55: =SUM(AD55:AG55) -> -85664.93 | K55: =SUM(AH55:AK55) -> -77496.52 | L55: =SUM(AL55:AO55) -> -211597.69 | M55: =SUM(AP55:AS55) -> -193224.45 | N55: =SUM(AT55:AW55) -> -193981.91 | O55: =SUM(AX55:BA55) -> -142503.27 | P55: =SUM($FJ55:FK55) -> -20996.628 | R55: =SUM(BF55:BH55) -> -68344 | S55: =SUM(BI55:BK55) -> -53104 | T55: =SUM(BL55:BN55) -> -83928 | U55: =SUM(BO55:BQ55) -> -83188 | V55: =SUM(BR55:BT55) -> -45830 | W55: =SUM(BU55:BW55) -> -65553 | X55: =SUM(BX55:BZ55) -> -81379 | Y55: =SUM(CA55:CC55) -> -67645 | Z55: =SUM(CD55:CF55) -> -53110 | AA55: =SUM(CG55:CI55) -> -73217 | AB55: =SUM(CJ55:CL55) -> -73924 | AC55: =SUM(CM55:CO55) -> -96072 | AD55: =SUM(CP55:CR55) -> -72823 | AE55: =SUM(CS55:CU55) -> -5615 | AF55: =SUM(CV55:CX55) -> -4235.57 | AG55: =SUM(CY55:DA55) -> -2991.36 | AH55: =SUM(DB55:DD55) -> -6319.49 | AI55: =SUM(DE55:DG55) -> -5229.28 | AJ55: =SUM(DH55:DJ55) -> -26452.8 | AK55: =SUM(DK55:DM55) -> -39494.95 | AL55: =SUM(DN55:DP55) -> -35687.31 | AM55: =SUM(DQ55:DS55) -> -39359.63 | AN55: =SUM(DT55:DV55) -> -86166.63 | AO55: =SUM(DW55:DY55) -> -50384.12 | AP55: =SUM(DZ55:EB55) -> -62644.926 | AQ55: =OFFSET($DZ55,0,AQ$4)+OFFSET($EA55,0,AQ$4)+OFFSET($EB55,0,AQ$4) -> -27005.702 | AR55: =OFFSET($DZ55,0,AR$4)+OFFSET($EA55,0,AR$4)+OFFSET($EB55,0,AR$4) -> -49236.065 | AS55: =OFFSET($DZ55,0,AS$4)+OFFSET($EA55,0,AS$4)+OFFSET($EB55,0,AS$4) -> -54337.756 | AT55: =SUM(EL55:EN55) -> -37336.295 | AU55: =OFFSET($EL55,0,AU$4)+OFFSET($EM55,0,AU$4)+OFFSET($EN55,0,AU$4) -> -65496.498 | AV55: =OFFSET($EL55,0,AV$4)+OFFSET($EM55,0,AV$4)+OFFSET($EN55,0,AV$4) -> -45847.814 | AW55: =OFFSET($EL55,0,AW$4)+OFFSET($EM55,0,AW$4)+OFFSET($EN55,0,AW$4) -> -45301.305 | AX55: =SUM(EX55:EZ55) -> -42846.397 | AY55: =SUM(FA55:FC55) -> -24994.698 | AZ55: =SUM(FD55:FF55) -> -31565.897 | BA55: =SUM(FG55:FI55) -> -43096.282 | BB55: =SUM(FJ55:FL55) -> -20996.628 | BF55: -29372 | BG55: -15499 | BH55: -23473 | BI55: -14341 | BJ55: -15423 | BK55: -23340 | BL55: -28170 | BM55: -28023 | BN55: -27735 | BO55: -27401 | BP55: -34105 | BQ55: -21682 | BR55: -22588 | BS55: -8566 | BT55: -14676 | BU55: -21130 | BV55: -28027 | BW55: -16396 | BX55: -25878 | BY55: -21719 | BZ55: -33782 | CA55: -19523 | CB55: -14635 | CC55: -33487 | CD55: -21879 | CE55: -16404 | CF55: -14827 | CG55: -22730 | CH55: -23056 | CI55: -27431 | CJ55: -14671 | CK55: -33512 | CL55: -25741 | CM55: -34985 | CN55: -33429 | CO55: -27658 | CP55: -33262 | CQ55: -23588 | CR55: -15973 | CS55: -2034 | CT55: -1024 | CU55: -2557 | CV55: -1121 | CW55: -1005.97 | CX55: -2108.6 | CY55: -1458.89 | CZ55: -3901.47 | DA55: 2369 | DB55: -1459.38 | DC55: -1623.78 | DD55: -3236.33 | DE55: -39.99 | DF55: -1463.38 | DG55: -3725.91 | DH55: -15786.18 | DI55: -6158.29 | DJ55: -4508.33 | DK55: -10649.98 | DL55: -17539.48 | DM55: -11305.49 | DN55: -15810.36 | DO55: -12566.97 | DP55: -7309.98 | DQ55: -10670.43 | DR55: -15133.9 | DS55: -13555.3 | DT55: -45820.72 | DU55: -23120.34 | DV55: -17225.57 | DW55: -25611.1 | DX55: -14843.94 | DY55: -9929.08 | DZ55: -13506.797 | EA55: -25274.806 | EB55: -23863.323 | EC55: -5951.3515 | ED55: -10687.714 | EE55: -10366.636 | EF55: -4658.5902 | EG55: -20961.566 | EH55: -23615.909 | EI55: -19785.629 | EJ55: -17341.969 | EK55: -17210.158 | EL55: -15209.384 | EM55: -14162.65 | EN55: -7964.2603 | EO55: -12422.008 | EP55: -26602.867 | EQ55: -26471.623 | ER55: -9418.8239 | ES55: -4221.4329 | ET55: -32207.557 | EU55: -7937.7308 | EV55: -7901.2338 | EW55: -29462.34 | EX55: -18913.03 | EY55: -15657.887 | EZ55: -8275.4803 | FA55: -5819.3741 | FB55: -8572.2171 | FC55: -10603.107 | FD55: -6351.3025 | FE55: -6805.3024 | FF55: -18409.292 | FG55: -15343.836 | FH55: -14667.774 | FI55: -13084.672 | FJ55: -8666.9383 | FK55: -12329.689 | FN55: ='Financial plan'!EZ50 -> -13517.845 | FO55: =FK55-FJ55 -> -3662.7509 | FP55: =FK55-FN55 -> 1188.1562 | FQ55: =FL55-#REF! -> #REF! | FR55: =FM55-FO55 -> 3662.7509 | FS55: =FK55-FN55 -> 1188.1562 | FT55: =SUM($FJ55:FK55) -> -20996.628 | FU55: =SUM('Financial plan'!$EY50:EZ50) -> -27035.691 | FV55: =FT55-FU55 -> 6039.0633
E56: Legal Patents & audit | F56: -244000 | G56: =SUM(R56:U56) -> -302506 | H56: =SUM(V56:Y56) -> -251333 | I56: =SUM(Z56:AC56) -> -440372 | J56: =SUM(AD56:AG56) -> -257464.16 | K56: =SUM(AH56:AK56) -> -336745.73 | L56: =SUM(AL56:AO56) -> -498744.12 | M56: =SUM(AP56:AS56) -> -538745.73 | N56: =SUM(AT56:AW56) -> -694313.39 | O56: =SUM(AX56:BA56) -> -615342.67 | P56: =SUM($FJ56:FK56) -> -92569.279 | R56: =SUM(BF56:BH56) -> -51453 | S56: =SUM(BI56:BK56) -> -87275 | T56: =SUM(BL56:BN56) -> -81934 | U56: =SUM(BO56:BQ56) -> -81844 | V56: =SUM(BR56:BT56) -> -50638 | W56: =SUM(BU56:BW56) -> -57247 | X56: =SUM(BX56:BZ56) -> -49884 | Y56: =SUM(CA56:CC56) -> -93564 | Z56: =SUM(CD56:CF56) -> -92598 | AA56: =SUM(CG56:CI56) -> -137178 | AB56: =SUM(CJ56:CL56) -> -102397 | AC56: =SUM(CM56:CO56) -> -108199 | AD56: =SUM(CP56:CR56) -> -67328 | AE56: =SUM(CS56:CU56) -> -59623 | AF56: =SUM(CV56:CX56) -> -56929.41 | AG56: =SUM(CY56:DA56) -> -73583.75 | AH56: =SUM(DB56:DD56) -> -65309.04 | AI56: =SUM(DE56:DG56) -> -65790.27 | AJ56: =SUM(DH56:DJ56) -> -90176.53 | AK56: =SUM(DK56:DM56) -> -115469.89 | AL56: =SUM(DN56:DP56) -> -95678.96 | AM56: =SUM(DQ56:DS56) -> -100174.66 | AN56: =SUM(DT56:DV56) -> -146152.65 | AO56: =SUM(DW56:DY56) -> -156737.85 | AP56: =SUM(DZ56:EB56) -> -117829.97 | AQ56: =OFFSET($DZ56,0,AQ$4)+OFFSET($EA56,0,AQ$4)+OFFSET($EB56,0,AQ$4) -> -131220.01 | AR56: =OFFSET($DZ56,0,AR$4)+OFFSET($EA56,0,AR$4)+OFFSET($EB56,0,AR$4) -> -144500.73 | AS56: =OFFSET($DZ56,0,AS$4)+OFFSET($EA56,0,AS$4)+OFFSET($EB56,0,AS$4) -> -145195.03 | AT56: =SUM(EL56:EN56) -> -157187.79 | AU56: =OFFSET($EL56,0,AU$4)+OFFSET($EM56,0,AU$4)+OFFSET($EN56,0,AU$4) -> -155325.03 | AV56: =OFFSET($EL56,0,AV$4)+OFFSET($EM56,0,AV$4)+OFFSET($EN56,0,AV$4) -> -200491.34 | AW56: =OFFSET($EL56,0,AW$4)+OFFSET($EM56,0,AW$4)+OFFSET($EN56,0,AW$4) -> -181309.22 | AX56: =SUM(EX56:EZ56) -> -134375.61 | AY56: =SUM(FA56:FC56) -> -144087.85 | AZ56: =SUM(FD56:FF56) -> -165863.98 | BA56: =SUM(FG56:FI56) -> -171015.23 | BB56: =SUM(FJ56:FL56) -> -92569.279 | BF56: -12006 | BG56: -26281 | BH56: -13166 | BI56: -20156 | BJ56: -50294 | BK56: -16825 | BL56: -37606 | BM56: -25741 | BN56: -18587 | BO56: -39137 | BP56: -19399 | BQ56: -23308 | BR56: -11106 | BS56: -28602 | BT56: =-33930+23000 -> -10930 | BU56: -17886 | BV56: -19257 | BW56: -20104 | BX56: -19374 | BY56: =-7864-10000 -> -17864 | BZ56: -12646 | CA56: -21854 | CB56: -23296 | CC56: -48414 | CD56: =-23345-15000 -> -38345 | CE56: =-39980+15000 -> -24980 | CF56: -29273 | CG56: -66282 | CH56: -31149 | CI56: -39747 | CJ56: -21013 | CK56: -48710 | CL56: -32674 | CM56: -32552 | CN56: =-44944+6000 -> -38944 | CO56: -36703 | CP56: -25303 | CQ56: -15019 | CR56: -27006 | CS56: -17238 | CT56: -21432 | CU56: -20953 | CV56: -15572 | CW56: -19863.41 | CX56: -21494 | CY56: -24679.72 | CZ56: -20168.2 | DA56: -28735.83 | DB56: -22759.81 | DC56: -19893.34 | DD56: -22655.89 | DE56: -22051.1 | DF56: -20695.67 | DG56: -23043.5 | DH56: -28497.48 | DI56: -30451.08 | DJ56: -31227.97 | DK56: -35994.2 | DL56: -39741.36 | DM56: -39734.33 | DN56: -27361.8 | DO56: -38407.15 | DP56: -29910.01 | DQ56: -25427.01 | DR56: -37923.35 | DS56: -36824.3 | DT56: -50217.54 | DU56: -39761.58 | DV56: -56173.53 | DW56: -55827.3 | DX56: -50714.99 | DY56: -50195.56 | DZ56: -42015.84 | EA56: -39011.196 | EB56: -36802.933 | EC56: -40512.725 | ED56: -47218.031 | EE56: -43489.252 | EF56: -53937.172 | EG56: -36902.288 | EH56: -53661.268 | EI56: -54776.299 | EJ56: -46442.294 | EK56: -43976.436 | EL56: -50589.876 | EM56: -59144.66 | EN56: -47453.256 | EO56: -52540.06 | EP56: -47353.199 | EQ56: -55431.769 | ER56: -60363.279 | ES56: -68175.723 | ET56: -71952.339 | EU56: -69353.149 | EV56: -55680.106 | EW56: -56275.97 | EX56: -47456.762 | EY56: -43683.88 | EZ56: -43234.973 | FA56: -49651.128 | FB56: -49969.181 | FC56: -44467.538 | FD56: -54730.192 | FE56: -53284.157 | FF56: -57849.629 | FG56: -55426.936 | FH56: -55048.484 | FI56: -60539.812 | FJ56: -48634.389 | FK56: -43934.89 | FN56: ='Financial plan'!EZ51 -> -50000 | FO56: =FK56-FJ56 -> 4699.4991 | FP56: =FK56-FN56 -> 6065.1101 | FQ56: =FL56-#REF! -> #REF! | FR56: =FM56-FO56 -> -4699.4991 | FS56: =FK56-FN56 -> 6065.1101 | FT56: =SUM($FJ56:FK56) -> -92569.279 | FU56: =SUM('Financial plan'!$EY51:EZ51) -> -100000 | FV56: =FT56-FU56 -> 7430.721
E57: Marketing | F57: -152000 | G57: -152000 | H57: =SUM(V57:Y57) -> -330374 | I57: =SUM(Z57:AC57) -> -497381 | J57: =SUM(AD57:AG57) -> -323004.12 | K57: =SUM(AH57:AK57) -> -814155.23 | L57: =SUM(AL57:AO57) -> -781863.61 | M57: =SUM(AP57:AS57) -> -649091.91 | N57: =SUM(AT57:AW57) -> -640096.34 | O57: =SUM(AX57:BA57) -> -367686.99 | P57: =SUM($FJ57:FK57) -> -29753.759 | R57: =SUM(BF57:BH57) -> -64304 | S57: =SUM(BI57:BK57) -> -34569 | T57: =SUM(BL57:BN57) -> -66056 | U57: =SUM(BO57:BQ57) -> -48996 | V57: =SUM(BR57:BT57) -> -60954 | W57: =SUM(BU57:BW57) -> -47178 | X57: =SUM(BX57:BZ57) -> -69714 | Y57: =SUM(CA57:CC57) -> -152528 | Z57: =SUM(CD57:CF57) -> -151645 | AA57: =SUM(CG57:CI57) -> -138715 | AB57: =SUM(CJ57:CL57) -> -101392 | AC57: =SUM(CM57:CO57) -> -105629 | AD57: =SUM(CP57:CR57) -> -112657 | AE57: =SUM(CS57:CU57) -> -54184 | AF57: =SUM(CV57:CX57) -> -91038.67 | AG57: =SUM(CY57:DA57) -> -65124.45 | AH57: =SUM(DB57:DD57) -> -153995.56 | AI57: =SUM(DE57:DG57) -> -203521.33 | AJ57: =SUM(DH57:DJ57) -> -236564.96 | AK57: =SUM(DK57:DM57) -> -220073.38 | AL57: =SUM(DN57:DP57) -> -223108.08 | AM57: =SUM(DQ57:DS57) -> -235329.09 | AN57: =SUM(DT57:DV57) -> -153007.06 | AO57: =SUM(DW57:DY57) -> -170419.38 | AP57: =SUM(DZ57:EB57) -> -169576.63 | AQ57: =OFFSET($DZ57,0,AQ$4)+OFFSET($EA57,0,AQ$4)+OFFSET($EB57,0,AQ$4) -> -173098 | AR57: =OFFSET($DZ57,0,AR$4)+OFFSET($EA57,0,AR$4)+OFFSET($EB57,0,AR$4) -> -170010.67 | AS57: =OFFSET($DZ57,0,AS$4)+OFFSET($EA57,0,AS$4)+OFFSET($EB57,0,AS$4) -> -136406.61 | AT57: =SUM(EL57:EN57) -> -192424.73 | AU57: =OFFSET($EL57,0,AU$4)+OFFSET($EM57,0,AU$4)+OFFSET($EN57,0,AU$4) -> -230775.75 | AV57: =OFFSET($EL57,0,AV$4)+OFFSET($EM57,0,AV$4)+OFFSET($EN57,0,AV$4) -> -100562.65 | AW57: =OFFSET($EL57,0,AW$4)+OFFSET($EM57,0,AW$4)+OFFSET($EN57,0,AW$4) -> -116333.21 | AX57: =SUM(EX57:EZ57) -> -130804.52 | AY57: =SUM(FA57:FC57) -> -109750.88 | AZ57: =SUM(FD57:FF57) -> -72723.716 | BA57: =SUM(FG57:FI57) -> -54407.876 | BB57: =SUM(FJ57:FL57) -> -29753.759 | BF57: -29806 | BG57: -24660 | BH57: -9838 | BI57: -7201 | BJ57: -18421 | BK57: -8947 | BL57: -35035 | BM57: -18302 | BN57: -12719 | BO57: -11210 | BP57: -26158 | BQ57: -11628 | BR57: -28778 | BS57: -17877 | BT57: =-14299 -> -14299 | BU57: -17932 | BV57: -13886 | BW57: -15360 | BX57: -24063 | BY57: -21100 | BZ57: -24551 | CA57: -33273 | CB57: -86164 | CC57: -33091 | CD57: =-23798-45000 -> -68798 | CE57: =-103613+45000 -> -58613 | CF57: -24234 | CG57: -37302 | CH57: -38583 | CI57: -62830 | CJ57: -31934 | CK57: -29570 | CL57: -39888 | CM57: -24175 | CN57: =-39339+10000 -> -29339 | CO57: =-52115 -> -52115 | CP57: -22716 | CQ57: -53084 | CR57: -36857 | CS57: -18172 | CT57: -14921 | CU57: -21091 | CV57: -27176 | CW57: -29454.8 | CX57: -34407.87 | CY57: -23002.33 | CZ57: -17090.28 | DA57: -25031.84 | DB57: -31772.04 | DC57: -58775.31 | DD57: -63448.21 | DE57: -96271.95 | DF57: -49804.32 | DG57: -57445.06 | DH57: -58834.33 | DI57: -81366.22 | DJ57: -96364.41 | DK57: -78396.94 | DL57: -76115.14 | DM57: -65561.3 | DN57: -58483.8 | DO57: -78634.62 | DP57: -85989.66 | DQ57: -99593.49 | DR57: -70020.88 | DS57: -65714.72 | DT57: -47736.99 | DU57: -46646 | DV57: -58624.07 | DW57: -71929.62 | DX57: -49097.33 | DY57: -49392.43 | DZ57: -53821.98 | EA57: -60334.84 | EB57: -55419.81 | EC57: -57935.15 | ED57: -68074.92 | EE57: -47087.93 | EF57: -66343.467 | EG57: -31343.314 | EH57: -72323.886 | EI57: -65638.248 | EJ57: -36484.963 | EK57: -34283.401 | EL57: -44775.231 | EM57: -81217.229 | EN57: -66432.274 | EO57: -49246.305 | EP57: -78792.352 | EQ57: -102737.1 | ER57: -33577.62 | ES57: -34283.979 | ET57: -32701.048 | EU57: -39519.414 | EV57: -41446.721 | EW57: -35367.07 | EX57: -29180.123 | EY57: -35274.161 | EZ57: -66350.231 | FA57: -36688.241 | FB57: -31240.127 | FC57: -41822.509 | FD57: -24630.596 | FE57: -19712.225 | FF57: -28380.895 | FG57: -16134.908 | FH57: -28088.661 | FI57: -10184.307 | FJ57: -14547.376 | FK57: -15206.383 | FN57: ='Financial plan'!EZ52 -> -23333.333 | FO57: =FK57-FJ57 -> -659.00655 | FP57: =FK57-FN57 -> 8126.9507 | FQ57: =FL57-#REF! -> #REF! | FR57: =FM57-FO57 -> 659.00655 | FS57: =FK57-FN57 -> 8126.9507 | FT57: =SUM($FJ57:FK57) -> -29753.759 | FU57: =SUM('Financial plan'!$EY52:EZ52) -> -46666.667 | FV57: =FT57-FU57 -> 16912.908
E58: Finance & bad debt | F58: -21000 | G58: =SUM(R58:U58) -> -12976 | H58: =SUM(V58:Y58) -> -160164 | I58: =SUM(Z58:AC58) -> -111239 | J58: =SUM(AD58:AG58) -> -163742 | K58: =SUM(AH58:AK58) -> -32407.86 | L58: =SUM(AL58:AO58) -> -100115.91 | M58: =SUM(AP58:AS58) -> -97969.462 | N58: =SUM(AT58:AW58) -> -117170.2 | O58: =SUM(AX58:BA58) -> -162604.59 | P58: =SUM($FJ58:FK58) -> -23687.47 | R58: =SUM(BF58:BH58) -> -14095 | S58: =SUM(BI58:BK58) -> 2198 | T58: =SUM(BL58:BN58) -> -11164 | U58: =SUM(BO58:BQ58) -> 10085 | V58: =SUM(BR58:BT58) -> -2405 | W58: =SUM(BU58:BW58) -> -9169 | X58: =SUM(BX58:BZ58) -> -16075 | Y58: =SUM(CA58:CC58) -> -132515 | Z58: =SUM(CD58:CF58) -> -22257 | AA58: =SUM(CG58:CI58) -> -21959 | AB58: =SUM(CJ58:CL58) -> -10922 | AC58: =SUM(CM58:CO58) -> -56101 | AD58: =SUM(CP58:CR58) -> -23422 | AE58: =SUM(CS58:CU58) -> -56704 | AF58: =SUM(CV58:CX58) -> -57236.7 | AG58: =SUM(CY58:DA58) -> -26379.3 | AH58: =SUM(DB58:DD58) -> -33787.85 | AI58: =SUM(DE58:DG58) -> -25026.61 | AJ58: =SUM(DH58:DJ58) -> -1074.09 | AK58: =SUM(DK58:DM58) -> 27480.69 | AL58: =SUM(DN58:DP58) -> -26516.36 | AM58: =SUM(DQ58:DS58) -> -29403.48 | AN58: =SUM(DT58:DV58) -> -29855.85 | AO58: =SUM(DW58:DY58) -> -14340.22 | AP58: =SUM(DZ58:EB58) -> -40617.407 | AQ58: =OFFSET($DZ58,0,AQ$4)+OFFSET($EA58,0,AQ$4)+OFFSET($EB58,0,AQ$4) -> -37912.471 | AR58: =OFFSET($DZ58,0,AR$4)+OFFSET($EA58,0,AR$4)+OFFSET($EB58,0,AR$4) -> -12728.559 | AS58: =OFFSET($DZ58,0,AS$4)+OFFSET($EA58,0,AS$4)+OFFSET($EB58,0,AS$4) -> -6711.0234 | AT58: =SUM(EL58:EN58) -> -45248.876 | AU58: =OFFSET($EL58,0,AU$4)+OFFSET($EM58,0,AU$4)+OFFSET($EN58,0,AU$4) -> -43229.943 | AV58: =OFFSET($EL58,0,AV$4)+OFFSET($EM58,0,AV$4)+OFFSET($EN58,0,AV$4) -> -39957.32 | AW58: =OFFSET($EL58,0,AW$4)+OFFSET($EM58,0,AW$4)+OFFSET($EN58,0,AW$4) -> 11265.941 | AX58: =SUM(EX58:EZ58) -> -28053.351 | AY58: =SUM(FA58:FC58) -> -32800.568 | AZ58: =SUM(FD58:FF58) -> -42804.823 | BA58: =SUM(FG58:FI58) -> -58945.849 | BB58: =SUM(FJ58:FL58) -> -23687.47 | BF58: -11558 | BG58: 795 | BH58: -3332 | BI58: 4083 | BJ58: 255 | BK58: -2140 | BL58: -2755 | BM58: -2496 | BN58: -5913 | BO58: 8772 | BP58: -712 | BQ58: 2025 | BR58: =-651+1522 -> 871 | BS58: =-4497+695 -> -3802 | BT58: =-1362+1888 -> 526 | BU58: =-9253+1365 -> -7888 | BV58: =-1559+1184 -> -375 | BW58: =-1643+737 -> -906 | BX58: =-2863-7391 -> -10254 | BY58: =-3316 -> -3316 | BZ58: -2505 | CA58: -10608 | CB58: -4033 | CC58: -117874 | CD58: -2929 | CE58: -15673 | CF58: -3655 | CG58: -5823 | CH58: =-60244+56900 -> -3344 | CI58: -12792 | CJ58: -5960 | CK58: =-13191+10845 -> -2346 | CL58: =-10478+7862 -> -2616 | CM58: =-9979-1020+7862 -> -3137 | CN58: =-32860+7862+21000 -> -3998 | CO58: =-57726+8760 -> -48966 | CP58: =-1976-5000 -> -6976 | CQ58: -2010 | CR58: =-17769+3333 -> -14436 | CS58: =-22013+2051 -> -19962 | CT58: =-26060+7634 -> -18426 | CU58: =-51483+33167 -> -18316 | CV58: -19048 | CW58: -19464.57 | CX58: -18724.13 | CY58: -21052.58 | CZ58: -20407.04 | DA58: 15080.32 | DB58: -14513.14 | DC58: =-4677.62-10000 -> -14677.62 | DD58: -4597.09 | DE58: =-2519.99-5000 -> -7519.99 | DF58: -8418.21 | DG58: -9088.41 | DH58: -2779.75 | DI58: -3040.85 | DJ58: 4746.51 | DK58: 7006.75 | DL58: 15823.64 | DM58: 4650.3 | DN58: -8755.2 | DO58: -9740.83 | DP58: -8020.33 | DQ58: -9316.74 | DR58: -8478.32 | DS58: -11608.42 | DT58: -8413.35 | DU58: -11022.21 | DV58: -10420.29 | DW58: -10097.59 | DX58: -10899.17 | DY58: 6656.54 | DZ58: -12426.663 | EA58: -15175.937 | EB58: -13014.808 | EC58: -12942.953 | ED58: -13738.476 | EE58: -11231.043 | EF58: -12522.708 | EG58: -12460.2 | EH58: 12254.348 | EI58: 3207.0212 | EJ58: 1953.0653 | EK58: -11871.11 | EL58: -18301.545 | EM58: -14859.279 | EN58: -12088.052 | EO58: -17982.597 | EP58: -13271.207 | EQ58: -11976.139 | ER58: -14414.392 | ES58: -12195.053 | ET58: -13347.875 | EU58: -13455.279 | EV58: 19823.08 | EW58: 4898.14 | EX58: -8573.6845 | EY58: -10413.529 | EZ58: -9066.1376 | FA58: -9278.7583 | FB58: -14714.345 | FC58: -8807.4653 | FD58: -13772.121 | FE58: -13805.475 | FF58: -15227.227 | FG58: -14671.2 | FH58: -11585 | FI58: -32689.65 | FJ58: -12519.743 | FK58: -11167.727 | FN58: ='Financial plan'!EZ53 -> -12540.938 | FO58: =FK58-FJ58 -> 1352.016 | FP58: =FK58-FN58 -> 1373.2107 | FQ58: =FL58-#REF! -> #REF! | FR58: =FM58-FO58 -> -1352.016 | FS58: =FK58-FN58 -> 1373.2107 | FT58: =SUM($FJ58:FK58) -> -23687.47 | FU58: =SUM('Financial plan'!$EY53:EZ53) -> -25081.875 | FV58: =FT58-FU58 -> 1394.4054
C59: Total Overheads | F59: =SUM(F46,F53,F54,F55,F56,F57,F58) -> -4893000 | G59: =SUM(G46,G53,G54,G55,G56,G57,G58) -> -5362186 | H59: =SUM(H46,H53,H54,H55,H56,H57,H58) -> -6091954 | I59: =SUM(I46,I53,I54,I55,I56,I57,I58) -> -7781152 | J59: =SUM(J46,J53,J54,J55,J56,J57,J58) -> -7726309.4 | K59: =SUM(K46,K53,K54,K55,K56,K57,K58) -> -11094145 | L59: =SUM(L46,L53,L54,L55,L56,L57,L58) -> -13536062 | M59: =SUM(M46,M53,M54,M55,M56,M57,M58) -> -12849496 | N59: =SUM(AT59:AW59) -> -12822748 | O59: =SUM(AX59:BA59) -> -11461414 | P59: =SUM($FJ59:FK59) -> -1773250.8 | R59: =SUM(R46,R53,R54,R55,R56,R57,R58) -> -1391764 | S59: =SUM(S46,S53,S54,S55,S56,S57,S58) -> -1309431 | T59: =SUM(T46,T53,T54,T55,T56,T57,T58) -> -1365415 | U59: =SUM(U46,U53,U54,U55,U56,U57,U58) -> -1357501 | V59: =SUM(V46,V53,V54,V55,V56,V57,V58) -> -1342807 | W59: =SUM(W46,W53,W54,W55,W56,W57,W58) -> -1432964 | X59: =SUM(X46,X53,X54,X55,X56,X57,X58) -> -1533182 | Y59: =SUM(Y46,Y53,Y54,Y55,Y56,Y57,Y58) -> -1783001 | ... AS59: =SUM(AS46,AS53,AS54,AS55,AS56,AS57,AS58) -> -3195327.1 | AT59: =SUM(EL59:EN59) -> -3270892.3 | AU59: =OFFSET($EL59,0,AU$4)+OFFSET($EM59,0,AU$4)+OFFSET($EN59,0,AU$4) -> -3295740.3 | AV59: =OFFSET($EL59,0,AV$4)+OFFSET($EM59,0,AV$4)+OFFSET($EN59,0,AV$4) -> -3185661.1 | AW59: =OFFSET($EL59,0,AW$4)+OFFSET($EM59,0,AW$4)+OFFSET($EN59,0,AW$4) -> -3070454.1 | AX59: =SUM(EX59:EZ59) -> -2923380.6 | AY59: =SUM(FA59:FC59) -> -2896469.4 | AZ59: =SUM(FD59:FF59) -> -2931958 | BA59: =SUM(FG59:FI59) -> -2709605.6 | BB59: =SUM(FJ59:FL59) -> -1773250.8 | BF59: =SUM(BF46,BF53,BF54,BF55,BF56,BF57,BF58) -> -505457 | BG59: =SUM(BG46,BG53,BG54,BG55,BG56,BG57,BG58) -> -447352 | BH59: =SUM(BH46,BH53,BH54,BH55,BH56,BH57,BH58) -> -438955 | BI59: =SUM(BI46,BI53,BI54,BI55,BI56,BI57,BI58) -> -425480 | BJ59: =SUM(BJ46,BJ53,BJ54,BJ55,BJ56,BJ57,BJ58) -> -469375 | BK59: =SUM(BK46,BK53,BK54,BK55,BK56,BK57,BK58) -> -414576 | BL59: =SUM(BL46,BL53,BL54,BL55,BL56,BL57,BL58) -> -493945 | BM59: =SUM(BM46,BM53,BM54,BM55,BM56,BM57,BM58) -> -430419 | ... FH59: =SUM(FH46,FH53,FH54,FH55,FH56,FH57,FH58) -> -912225.47 | FI59: =FI46+SUM(FI53:FI58) -> -865704.24 | FJ59: =FJ46+SUM(FJ53:FJ58) -> -892668.39 | FK59: =FK46+SUM(FK53:FK58) -> -880582.43 | FN59: =SUM(FN46,FN53,FN54,FN55,FN56,FN57,FN58) -> -936737.79 | FO59: =FK59-FJ59 -> 12085.964 | FP59: =FK59-FN59 -> 56155.366 | FQ59: =FL59-#REF! -> #REF! | FR59: =FM59-FO59 -> -12085.964 | FS59: =FK59-FN59 -> 56155.366 | FT59: =SUM($FJ59:FK59) -> -1773250.8 | FU59: =SUM('Financial plan'!$EY54:EZ54) -> -1873475.6 | FV59: =FT59-FU59 -> 100224.77
C60: EBITDA before bonus | N60: =SUM(AT60:AW60) -> -502354.34 | O60: =SUM(AX60:BA60) -> 957512.94 | P60: =SUM($FJ60:FK60) -> 280550.01 | AT60: =SUM(EL60:EN60) -> 91500.813 | AU60: =OFFSET($EL60,0,AU$4)+OFFSET($EM60,0,AU$4)+OFFSET($EN60,0,AU$4) -> -17392.713 | AV60: =OFFSET($EL60,0,AV$4)+OFFSET($EM60,0,AV$4)+OFFSET($EN60,0,AV$4) -> -150065.25 | AW60: =OFFSET($EL60,0,AW$4)+OFFSET($EM60,0,AW$4)+OFFSET($EN60,0,AW$4) -> -426397.19 | AX60: =SUM(EX60:EZ60) -> 20382.763 | AY60: =SUM(FA60:FC60) -> -33984.443 | AZ60: =SUM(FD60:FF60) -> 361734.17 | BA60: =SUM(FG60:FI60) -> 609380.45 | BB60: =SUM(FJ60:FL60) -> 280550.01 | EL60: =EL59+EL44 -> -4148.5816 | EM60: =EM59+EM44 -> -12553.838 | EN60: =EN59+EN44 -> 108203.23 | EO60: =EO59+EO44 -> -42632.498 | EP60: =EP59+EP44 -> 58684.628 | EQ60: =EQ59+EQ44 -> -33444.842 | ER60: =ER59+ER44 -> -40762.915 | ES60: =ES59+ES44 -> -35741.743 | ... FK60: =FK59+FK44 -> 173084.52 | FN60: ='Financial plan'!EZ55 -> 165838.18 | FO60: =FK60-FJ60 -> 65619.03 | FP60: =FK60-FN60 -> 7246.3399 | FQ60: =FL60-#REF! -> #REF! | FR60: =FM60-FO60 -> -65619.03 | FS60: =FK60-FN60 -> 7246.3399 | FT60: =SUM($FJ60:FK60) -> 280550.01 | FU60: =SUM('Financial plan'!$EY55:EZ55) -> 331676.36 | FV60: =FT60-FU60 -> -51126.35
E61: Bonus expense | N61: =SUM(AT61:AW61) -> 4.6566129e-10 | O61: =SUM(AX61:BA61) -> -414478.43 | P61: =SUM($FJ61:FK61) -> -115305 | AT61: =SUM(EL61:EN61) -> -160841.56 | AU61: =OFFSET($EL61,0,AU$4)+OFFSET($EM61,0,AU$4)+OFFSET($EN61,0,AU$4) -> -149198.66 | AV61: =OFFSET($EL61,0,AV$4)+OFFSET($EM61,0,AV$4)+OFFSET($EN61,0,AV$4) -> 28867.626 | AW61: =OFFSET($EL61,0,AW$4)+OFFSET($EM61,0,AW$4)+OFFSET($EN61,0,AW$4) -> 281172.59 | AX61: =SUM(EX61:EZ61) -> -182726.95 | AY61: =SUM(FA61:FC61) -> -84564.626 | AZ61: =SUM(FD61:FF61) -> -9279.2711 | BA61: =SUM(FG61:FI61) -> -137907.58 | BB61: =SUM(FJ61:FL61) -> -115305 | EL61: -54619.972 | EM61: -54212.043 | EN61: -52009.545 | EO61: -44091.326 | EP61: -52452.662 | EQ61: -52654.67 | ER61: -1284.6888 | ES61: 8743.0523 | ET61: 21409.262 | EU61: 28411.953 | EV61: 78473.886 | EW61: 174286.75 | EX61: -61094.728 | EY61: -60710.738 | EZ61: -60921.487 | FA61: -58165.515 | FB61: -25110.533 | FC61: -1288.5775 | FD61: -69.984466 | FE61: -384 | FF61: -8825.2867 | FG61: 0 | FH61: -52268 | FI61: -85639.578 | FJ61: -57412 | FK61: -57893 | FN61: ='Financial plan'!EZ56 -> -37964.188 | FO61: =FK61-FJ61 -> -481 | FP61: =FK61-FN61 -> -19928.812 | FQ61: =FL61-#REF! -> #REF! | FR61: =FM61-FO61 -> 481 | FS61: =FK61-FN61 -> -19928.812 | FT61: =SUM($FJ61:FK61) -> -115305 | FU61: =SUM('Financial plan'!$EY56:EZ56) -> -75928.376 | FV61: =FT61-FU61 -> -39376.624
C62: EBITDA | F62: =F44+F59 -> -1577000 | G62: =G44+G59 -> -1348151 | H62: =H44+H59 -> -820597 | I62: =I44+I59 -> -1975793 | J62: =J44+J59 -> -456448.44 | K62: =K44+K59 -> -2988948.5 | L62: =L44+L59 -> -3239763.8 | M62: =M44+M59 -> -368407.48 | N62: =SUM(AT62:AW62) -> -502354.34 | O62: =SUM(AX62:BA62) -> 543034.51 | P62: =SUM($FJ62:FK62) -> 165245.01 | R62: =R44+R59 -> -415583 | S62: =S44+S59 -> -588133 | T62: =T44+T59 -> -439945 | U62: =U44+U59 -> 33585 | V62: =V44+V59 -> -151564 | W62: =W44+W59 -> -292716 | X62: =X44+X59 -> -190251 | Y62: =Y44+Y59 -> -186066 | ... AS62: =AS44+AS59 -> 121172.46 | AT62: =SUM(EL62:EN62) -> -69340.747 | AU62: =OFFSET($EL62,0,AU$4)+OFFSET($EM62,0,AU$4)+OFFSET($EN62,0,AU$4) -> -166591.37 | AV62: =OFFSET($EL62,0,AV$4)+OFFSET($EM62,0,AV$4)+OFFSET($EN62,0,AV$4) -> -121197.62 | AW62: =OFFSET($EL62,0,AW$4)+OFFSET($EM62,0,AW$4)+OFFSET($EN62,0,AW$4) -> -145224.6 | AX62: =SUM(EX62:EZ62) -> -162344.19 | AY62: =SUM(FA62:FC62) -> -118549.07 | AZ62: =SUM(FD62:FF62) -> 352454.9 | BA62: =SUM(FG62:FI62) -> 471472.87 | BB62: =SUM(FJ62:FL62) -> 165245.01 | BF62: =BF44+BF59 -> 85742 | BG62: =BG44+BG59 -> -231637 | BH62: =BH44+BH59 -> -269688 | BI62: =BI44+BI59 -> -279306 | BJ62: =BJ44+BJ59 -> -162365 | BK62: =BK44+BK59 -> -146462 | BL62: =BL44+BL59 -> -176448 | BM62: =BM44+BM59 -> -62810 | ... EK62: =EK44+EK59 -> 173210.43 | EL62: =EL61+EL60 -> -58768.553 | EM62: =EM61+EM60 -> -66765.881 | EN62: =EN61+EN60 -> 56193.687 | EO62: =EO61+EO60 -> -86723.825 | EP62: =EP61+EP60 -> 6231.966 | EQ62: =EQ61+EQ60 -> -86099.512 | ER62: =ER61+ER60 -> -42047.603 | ES62: =ES61+ES60 -> -26998.69 | ... FK62: =FK61+FK60 -> 115191.52 | FN62: =FN61+FN60 -> 127873.99 | FO62: =FK62-FJ62 -> 65138.03 | FP62: =FK62-FN62 -> -12682.472 | FQ62: =FL62-#REF! -> #REF! | FR62: =FM62-FO62 -> -65138.03 | FS62: =FK62-FN62 -> -12682.472 | FT62: =SUM($FJ62:FK62) -> 165245.01 | FU62: =SUM('Financial plan'!$EY57:EZ57) -> 255747.98 | FV62: =FT62-FU62 -> -90502.974
D63: Forex (loss) / gain | F63: 0 | G63: =SUM(R63:U63) -> -35686 | H63: =SUM(V63:Y63) -> -31469 | I63: =SUM(Z63:AC63) -> -24710 | J63: =SUM(AD63:AG63) -> -32645.17 | K63: =SUM(AH63:AK63) -> -37944.49 | L63: =SUM(AL63:AO63) -> 54357.005 | M63: =SUM(AP63:AS63) -> -120350.12 | N63: =SUM(AT63:AW63) -> 76558.971 | O63: =SUM(AX63:BA63) -> -80955.684 | P63: =SUM($FJ63:FK63) -> -7927.6836 | R63: =SUM(BF63:BH63) -> -10259 | S63: =SUM(BI63:BK63) -> -13106 | T63: =SUM(BL63:BN63) -> 14826 | U63: =SUM(BO63:BQ63) -> -27147 | V63: =SUM(BR63:BT63) -> -51807 | W63: =SUM(BU63:BW63) -> 18287 | X63: =SUM(BX63:BZ63) -> 4277 | Y63: =SUM(CA63:CC63) -> -2226 | Z63: =SUM(CD63:CF63) -> -13454 | AA63: =SUM(CG63:CI63) -> 13203 | AB63: =SUM(CJ63:CL63) -> 6481 | AC63: =SUM(CM63:CO63) -> -30940 | AD63: =SUM(CP63:CR63) -> 7745 | AE63: =SUM(CS63:CU63) -> -23914 | AF63: =SUM(CV63:CX63) -> -3880.84 | AG63: =SUM(CY63:DA63) -> -12595.33 | AH63: =SUM(DB63:DD63) -> -30306.13 | AI63: =SUM(DE63:DG63) -> -21284.56 | AJ63: =SUM(DH63:DJ63) -> 9352.48 | AK63: =SUM(DK63:DM63) -> 4293.72 | AL63: =SUM(DN63:DP63) -> -487.12 | AM63: =SUM(DQ63:DS63) -> 16698.06 | AN63: =SUM(DT63:DV63) -> 88952.02 | AO63: =SUM(DW63:DY63) -> -50805.955 | AP63: =SUM(DZ63:EB63) -> -48779.997 | AQ63: =OFFSET($DZ63,0,AQ$4)+OFFSET($EA63,0,AQ$4)+OFFSET($EB63,0,AQ$4) -> -66611.95 | AR63: =OFFSET($DZ63,0,AR$4)+OFFSET($EA63,0,AR$4)+OFFSET($EB63,0,AR$4) -> 7131.5145 | AS63: =OFFSET($DZ63,0,AS$4)+OFFSET($EA63,0,AS$4)+OFFSET($EB63,0,AS$4) -> -12089.683 | AT63: =SUM(EL63:EN63) -> 7216.1587 | AU63: =OFFSET($EL63,0,AU$4)+OFFSET($EM63,0,AU$4)+OFFSET($EN63,0,AU$4) -> 843.01153 | AV63: =OFFSET($EL63,0,AV$4)+OFFSET($EM63,0,AV$4)+OFFSET($EN63,0,AV$4) -> -6560.1757 | AW63: =OFFSET($EL63,0,AW$4)+OFFSET($EM63,0,AW$4)+OFFSET($EN63,0,AW$4) -> 75059.977 | AX63: =SUM(EX63:EZ63) -> -18831.361 | AY63: =SUM(FA63:FC63) -> -52007.464 | AZ63: =SUM(FD63:FF63) -> 9700.4362 | BA63: =SUM(FG63:FI63) -> -19817.296 | BB63: =SUM(FJ63:FL63) -> -7927.6836 | BF63: -9551 | BG63: 376 | BH63: -1084 | BI63: -9566 | BJ63: 8408 | BK63: -11948 | BL63: 1018 | BM63: 17407 | BN63: -3599 | BO63: 8600 | BP63: -26093 | BQ63: -9654 | BR63: -59760 | BS63: 15476 | BT63: =-7523 -> -7523 | BU63: -3066 | BV63: 15720 | BW63: 5633 | BX63: 2378 | BY63: 5072 | BZ63: -3173 | CA63: 6682 | CB63: -5911 | CC63: -2997 | CD63: -18595 | CE63: -2092 | CF63: 7233 | CG63: -3423 | CH63: -15967 | CI63: 32593 | CJ63: 8341 | CK63: 3646 | CL63: -5506 | CM63: -9974 | CN63: -5658 | CO63: -15308 | CP63: -5447 | CQ63: 1829 | CR63: 11363 | CS63: -7889 | CT63: -4447 | CU63: -11578 | CV63: 2619 | CW63: -33272.56 | CX63: 26772.72 | CY63: -15327.65 | CZ63: -23604.42 | DA63: 26336.74 | DB63: -8965.43 | DC63: -18593.64 | DD63: -2747.06 | DE63: 4765.95 | DF63: -15798.45 | DG63: -10252.06 | DH63: -7852.88 | DI63: 7760.75 | DJ63: 9444.61 | DK63: -9299.12 | DL63: 29793.03 | DM63: -16200.19 | DN63: -4631.15 | DO63: 3143.66 | DP63: 1000.37 | DQ63: -6333.95 | DR63: 839.8 | DS63: 22192.21 | DT63: -6587.11 | DU63: 23164.1 | DV63: 72375.03 | DW63: -40261.89 | DX63: -47764.36 | DY63: 37220.295 | DZ63: -48444.337 | EA63: 35949.633 | EB63: -36285.292 | EC63: -14274.151 | ED63: -5198.7798 | EE63: -47139.02 | EF63: -17518.631 | EG63: 18986.702 | EH63: 5663.4435 | EI63: 23503.735 | EJ63: -17911.878 | EK63: =-16710.419377752-971.12 -> -17681.539 | EL63: -1499.8562 | EM63: 8154.5284 | EN63: 561.4865 | EO63: 8200.376 | EP63: -6769.9378 | EQ63: -587.42675 | ER63: 5747.5528 | ES63: -14244.81 | ET63: 1937.0813 | EU63: 9792.0153 | EV63: -29909.379 | EW63: 95177.34 | EX63: 7978.5587 | EY63: -15360.503 | EZ63: -11449.416 | FA63: -30555.528 | FB63: -6035.0713 | FC63: -15416.865 | FD63: 13059.366 | FE63: -7937.8412 | FF63: 4578.9117 | FG63: -6422.4536 | FH63: 24816.44 | FI63: -38211.282 | FJ63: -29962.835 | FK63: 22035.152
D64: Exceptionals | F64: 0 | G64: 0 | H64: =SUM(V64:Y64) -> -56011 | I64: =SUM(Z64:AC64) -> -139900 | J64: =SUM(AD64:AG64) -> -857549 | K64: =SUM(AH64:AK64) -> -601790.76 | L64: =SUM(AL64:AO64) -> -367128 | M64: =SUM(AP64:AS64) -> -1099735 | N64: =SUM(AT64:AW64) -> -699346.62 | O64: =SUM(AX64:BA64) -> -198204.21 | P64: =SUM($FJ64:FK64) -> 0 | V64: =SUM(BR64:BT64) -> -23000 | W64: =SUM(BU64:BW64) -> 0 | X64: =SUM(BX64:BZ64) -> -20000 | Y64: =SUM(CA64:CC64) -> -13011 | Z64: =SUM(CD64:CF64) -> 0 | AA64: =SUM(CG64:CI64) -> -56900 | AB64: =SUM(CJ64:CL64) -> 0 | AC64: =SUM(CM64:CO64) -> -83000 | AD64: =SUM(CP64:CR64) -> 0 | AE64: =SUM(CS64:CU64) -> 0 | AF64: =SUM(CV64:CX64) -> -532549 | AG64: =SUM(CY64:DA64) -> -325000 | AH64: =SUM(DB64:DD64) -> 0 | AI64: =SUM(DE64:DG64) -> 0 | AJ64: =SUM(DH64:DJ64) -> 0 | AK64: =SUM(DK64:DM64) -> -601790.76 | AL64: =SUM(DN64:DP64) -> 0 | AM64: =SUM(DQ64:DS64) -> 0 | AN64: =SUM(DT64:DV64) -> 0 | AO64: =SUM(DW64:DY64) -> -367128 | AP64: =SUM(DZ64:EB64) -> -192044.56 | AQ64: =OFFSET($DZ64,0,AQ$4)+OFFSET($EA64,0,AQ$4)+OFFSET($EB64,0,AQ$4) -> -132335.33 | AR64: =OFFSET($DZ64,0,AR$4)+OFFSET($EA64,0,AR$4)+OFFSET($EB64,0,AR$4) -> -36272 | AS64: =OFFSET($DZ64,0,AS$4)+OFFSET($EA64,0,AS$4)+OFFSET($EB64,0,AS$4) -> -739083.07 | AT64: =SUM(EL64:EN64) -> -196090.13 | AU64: =OFFSET($EL64,0,AU$4)+OFFSET($EM64,0,AU$4)+OFFSET($EN64,0,AU$4) -> -31400.01 | AV64: =OFFSET($EL64,0,AV$4)+OFFSET($EM64,0,AV$4)+OFFSET($EN64,0,AV$4) -> -466.65 | AW64: =OFFSET($EL64,0,AW$4)+OFFSET($EM64,0,AW$4)+OFFSET($EN64,0,AW$4) -> -471389.83 | AX64: =SUM(EX64:EZ64) -> -36002.673 | AY64: =SUM(FA64:FC64) -> -15313.84 | AZ64: =SUM(FD64:FF64) -> -33334 | BA64: =SUM(FG64:FI64) -> -113553.7 | BB64: =SUM(FJ64:FL64) -> 0 | BR64: 0 | BS64: 0 | BT64: -23000 | BU64: 0 | BV64: 0 | BW64: 0 | BX64: 0 | BY64: -20000 | BZ64: 0 | CA64: 0 | CC64: -13011 | CD64: =-255863+234415+21448 -> 0 | CE64: 0 | CF64: 0 | CG64: 0 | CH64: -56900 | CI64: 0 | CJ64: 0 | CK64: 0 | CL64: 0 | CM64: 0 | CN64: 0 | CO64: =-83000 -> -83000 | CP64: 0 | CQ64: 0 | CR64: 0 | CS64: 0 | CT64: 0 | CU64: 0 | CV64: 0 | CW64: 0 | CX64: -532549 | CY64: -30000 | CZ64: 0 | DA64: -295000 | DB64: 0 | DC64: 0 | DD64: 0 | DE64: 0 | DF64: 0 | DG64: 0 | DH64: 0 | DI64: 0 | DJ64: 0 | DK64: 0 | DM64: =-495294-273062-0.76+166566 -> -601790.76 | DN64: 0 | DO64: 0 | DP64: 0 | DQ64: 0 | DR64: 0 | DS64: 0 | DT64: 0 | DU64: 0 | DV64: 0 | DW64: 0 | DX64: 0 | DY64: -367128 | DZ64: 0 | EA64: -50000 | EB64: -142044.56 | EC64: 0 | ED64: -6002 | EE64: -126333.33 | EF64: -25000 | EG64: 0 | EH64: -11272 | EI64: -30519.5 | EJ64: -26284.458 | EK64: =2585.88870584354-684865 -> -682279.11 | EL64: 0 | EM64: -16000 | EN64: -180090.13 | EO64: -30466.67 | EP64: -466.67 | EQ64: -466.67 | ER64: -466.65 | ES64: 0 | ET64: 0 | EU64: -75000 | EV64: -161332.58 | EW64: -235057.25 | EX64: 0 | EY64: -25918.14 | EZ64: -10084.533 | FA64: -15313.84 | FB64: 0 | FC64: 0 | FD64: 0 | FE64: -33334 | FF64: 0 | FG64: -17750 | FH64: -62470.696 | FI64: -33333 | FJ64: 0 | FK64: 0
D65: Recoverable taxes | F65: 0 | G65: 0 | H65: 0 | I65: 0 | J65: 0 | K65: 0 | L65: =SUM(AL65:AO65) -> 0.12788801 | M65: =SUM(AP65:AS65) -> 0 | N65: =SUM(AT65:AW65) -> 0 | O65: =SUM(AX65:BA65) -> 0 | P65: =SUM($FJ65:FK65) -> 0 | AL65: =SUM(DN65:DP65) -> 0 | AM65: =SUM(DQ65:DS65) -> 0 | AN65: =SUM(DT65:DV65) -> 0 | AO65: =SUM(DW65:DY65) -> 0.12788801 | AP65: =SUM(DZ65:EB65) -> 0 | AQ65: =OFFSET($DZ65,0,AQ$4)+OFFSET($EA65,0,AQ$4)+OFFSET($EB65,0,AQ$4) -> 0 | AR65: =OFFSET($DZ65,0,AR$4)+OFFSET($EA65,0,AR$4)+OFFSET($EB65,0,AR$4) -> 0 | AS65: =OFFSET($DZ65,0,AS$4)+OFFSET($EA65,0,AS$4)+OFFSET($EB65,0,AS$4) -> 0 | AT65: =SUM(EL65:EN65) -> 0 | AU65: =OFFSET($EL65,0,AU$4)+OFFSET($EM65,0,AU$4)+OFFSET($EN65,0,AU$4) -> 0 | AV65: =OFFSET($EL65,0,AV$4)+OFFSET($EM65,0,AV$4)+OFFSET($EN65,0,AV$4) -> 0 | AW65: =OFFSET($EL65,0,AW$4)+OFFSET($EM65,0,AW$4)+OFFSET($EN65,0,AW$4) -> 0 | AX65: =SUM(EX65:EZ65) -> 0 | AY65: =SUM(FA65:FC65) -> 0 | AZ65: =SUM(FD65:FF65) -> 0 | BA65: =SUM(FG65:FI65) -> 0 | BB65: =SUM(FJ65:FL65) -> 0 | DM65: 0 | DN65: 0 | DO65: 0 | DP65: 0 | DQ65: 0 | DR65: 0 | DS65: 0 | DT65: 0 | DU65: 0 | DV65: 0 | DW65: 0 | DX65: -50711.68 | DY65: 50711.808 | DZ65: 0 | EA65: 0 | EB65: 0 | EC65: 0 | ED65: 0 | EE65: 0 | EF65: 0 | EG65: 0 | EH65: 0 | EI65: 0 | EJ65: 0 | EL65: 0 | EM65: 0 | EN65: 0 | EO65: 0 | EP65: 0 | EQ65: 0 | ER65: 0 | ES65: 0 | ET65: 0
D66: Depreciation & amortization | F66: -646000 | G66: =SUM(R66:U66) -> -515595 | H66: =SUM(V66:Y66) -> -623719 | I66: =SUM(Z66:AC66) -> -828764 | J66: =SUM(AD66:AG66) -> -1071616.9 | K66: =SUM(AH66:AK66) -> -1450296.6 | L66: =SUM(AL66:AO66) -> -2054155.7 | M66: =SUM(AP66:AS66) -> -2573506.1 | N66: =SUM(AT66:AW66) -> -3279886.6 | O66: =SUM(AX66:BA66) -> -3662847 | P66: =SUM($FJ66:FK66) -> -632338.97 | R66: =SUM(BF66:BH66) -> -97219 | S66: =SUM(BI66:BK66) -> -140807 | T66: =SUM(BL66:BN66) -> -138968 | U66: =SUM(BO66:BQ66) -> -138601 | V66: =SUM(BR66:BT66) -> -126709 | W66: =SUM(BU66:BW66) -> -151723 | X66: =SUM(BX66:BZ66) -> -145057 | Y66: =SUM(CA66:CC66) -> -200230 | Z66: =SUM(CD66:CF66) -> -182492 | AA66: =SUM(CG66:CI66) -> -193473 | AB66: =SUM(CJ66:CL66) -> -213652 | AC66: =SUM(CM66:CO66) -> -239147 | AD66: =SUM(CP66:CR66) -> -252359 | AE66: =SUM(CS66:CU66) -> -275343 | AF66: =SUM(CV66:CX66) -> -252558.5 | AG66: =SUM(CY66:DA66) -> -291356.42 | AH66: =SUM(DB66:DD66) -> -325752.96 | AI66: =SUM(DE66:DG66) -> -343184.2 | AJ66: =SUM(DH66:DJ66) -> -369221.14 | AK66: =SUM(DK66:DM66) -> -412138.28 | AL66: =SUM(DN66:DP66) -> -441673.97 | AM66: =SUM(DQ66:DS66) -> -479490.86 | AN66: =SUM(DT66:DV66) -> -550514.9 | AO66: =SUM(DW66:DY66) -> -582475.98 | AP66: =SUM(DZ66:EB66) -> -590394.8 | AQ66: =OFFSET($DZ66,0,AQ$4)+OFFSET($EA66,0,AQ$4)+OFFSET($EB66,0,AQ$4) -> -631153.57 | AR66: =OFFSET($DZ66,0,AR$4)+OFFSET($EA66,0,AR$4)+OFFSET($EB66,0,AR$4) -> -654278.53 | AS66: =OFFSET($DZ66,0,AS$4)+OFFSET($EA66,0,AS$4)+OFFSET($EB66,0,AS$4) -> -697679.22 | AT66: =SUM(EL66:EN66) -> -729418.08 | AU66: =OFFSET($EL66,0,AU$4)+OFFSET($EM66,0,AU$4)+OFFSET($EN66,0,AU$4) -> -763474.5 | AV66: =OFFSET($EL66,0,AV$4)+OFFSET($EM66,0,AV$4)+OFFSET($EN66,0,AV$4) -> -863981.41 | AW66: =OFFSET($EL66,0,AW$4)+OFFSET($EM66,0,AW$4)+OFFSET($EN66,0,AW$4) -> -923012.6 | AX66: =SUM(EX66:EZ66) -> -914229.83 | AY66: =SUM(FA66:FC66) -> -916705.98 | AZ66: =SUM(FD66:FF66) -> -903836.23 | BA66: =SUM(FG66:FI66) -> -928074.92 | BB66: =SUM(FJ66:FL66) -> -632338.97 | BF66: -27725 | BG66: -35466 | BH66: -34028 | BI66: -38469 | BJ66: -61040 | BK66: -41298 | BL66: -40907 | BM66: -50544 | BN66: -47517 | BO66: -42737 | BP66: -51476 | BQ66: -44388 | BR66: -38604 | BS66: -42760 | BT66: -45345 | BU66: -59497 | BV66: -46402 | BW66: -45824 | BX66: -54608 | BY66: -44179 | BZ66: -46270 | CA66: -60629 | CB66: -47529 | CC66: -92072 | CD66: =-14996-37000 -> -51996 | CE66: -62412 | CF66: -68084 | CG66: -77544 | CH66: -55406 | CI66: -60523 | CJ66: -68722 | CK66: -65298 | CL66: -79632 | CM66: -67828 | CN66: -75431 | CO66: -95888 | CP66: =-32959-50000 -> -82959 | CQ66: =-7941-75000 -> -82941 | CR66: =-16459-70000 -> -86459 | CS66: =-272733+195000 -> -77733 | CT66: -102593 | CU66: -95017 | CV66: -77598 | CW66: -75800.33 | CX66: -99160.17 | CY66: -99268.19 | CZ66: -93609.36 | DA66: -98478.87 | DB66: -114870.52 | DC66: -102081.57 | DD66: -108800.87 | DE66: -106479.68 | DF66: -110580.23 | DG66: -126124.29 | DH66: -126828.09 | DI66: -123800.89 | DJ66: -118592.16 | DK66: -129145.8 | DL66: -127123.76 | DM66: -155868.72 | DN66: -141089.89 | DO66: -143302.88 | DP66: -157281.2 | DQ66: -179765.24 | DR66: -171720.19 | DS66: -128005.43 | DT66: -174088.15 | DU66: -182972.95 | DV66: -193453.8 | DW66: -185347.71 | DX66: -191985.72 | DY66: -205142.55 | DZ66: -192349.01 | EA66: -198190.69 | EB66: -199855.1 | EC66: -202972.52 | ED66: -212823.55 | EE66: -215357.51 | EF66: -214424.98 | EG66: -221220.22 | EH66: -218633.33 | EI66: -223571.39 | EJ66: -224469.21 | EK66: -249638.61 | EL66: -240383.15 | EM66: -245052.97 | EN66: -243981.95 | EO66: -250904.33 | EP66: -253890.83 | EQ66: -258679.34 | ER66: -265045.89 | ES66: -264074.91 | ET66: -334860.61 | EU66: -281085.31 | EV66: -316436.73 | EW66: -325490.56 | EX66: -303191.99 | EY66: -304469.69 | EZ66: -306568.15 | FA66: -300742.97 | FB66: -315057.8 | FC66: -300905.21 | FD66: -298099.03 | FE66: -301095.96 | FF66: -304641.24 | FG66: -305261.95 | FH66: -310756.54 | FI66: -312056.43 | FJ66: -315263.59 | FK66: -317075.39
D67: Interest | F67: -161000 | G67: =SUM(R67:U67) -> -277945 | H67: =SUM(V67:Y67) -> -579208 | I67: =SUM(Z67:AC67) -> -658767 | J67: =SUM(AD67:AG67) -> -868636.41 | K67: =SUM(AH67:AK67) -> -370416.06 | L67: =SUM(AL67:AO67) -> -240892.98 | M67: =SUM(AP67:AS67) -> -699035.14 | N67: =SUM(AT67:AW67) -> -625155.54 | O67: =SUM(AX67:BA67) -> -1310305.7 | P67: =SUM($FJ67:FK67) -> -165112.13 | R67: =SUM(BF67:BH67) -> -58716 | S67: =SUM(BI67:BK67) -> -61528 | T67: =SUM(BL67:BN67) -> -76260 | U67: =SUM(BO67:BQ67) -> -81441 | V67: =SUM(BR67:BT67) -> -102178 | W67: =SUM(BU67:BW67) -> -106408 | X67: =SUM(BX67:BZ67) -> -135464 | Y67: =SUM(CA67:CC67) -> -235158 | Z67: =SUM(CD67:CF67) -> -168423 | AA67: =SUM(CG67:CI67) -> -108476 | AB67: =SUM(CJ67:CL67) -> -205272 | AC67: =SUM(CM67:CO67) -> -176596 | AD67: =SUM(CP67:CR67) -> -172999 | AE67: =SUM(CS67:CU67) -> -213404 | AF67: =SUM(CV67:CX67) -> -202480.55 | AG67: =SUM(CY67:DA67) -> -279752.86 | AH67: =SUM(DB67:DD67) -> -102986 | AI67: =SUM(DE67:DG67) -> -99051.12 | AJ67: =SUM(DH67:DJ67) -> -92662.675 | AK67: =SUM(DK67:DM67) -> -75716.26 | AL67: =SUM(DN67:DP67) -> -65751.84 | AM67: =SUM(DQ67:DS67) -> -101619.24 | AN67: =SUM(DT67:DV67) -> -101032.48 | AO67: =SUM(DW67:DY67) -> 27510.581 | AP67: =SUM(DZ67:EB67) -> -121194.02 | AQ67: =OFFSET($DZ67,0,AQ$4)+OFFSET($EA67,0,AQ$4)+OFFSET($EB67,0,AQ$4) -> -122456.99 | AR67: =OFFSET($DZ67,0,AR$4)+OFFSET($EA67,0,AR$4)+OFFSET($EB67,0,AR$4) -> -112361.6 | AS67: =OFFSET($DZ67,0,AS$4)+OFFSET($EA67,0,AS$4)+OFFSET($EB67,0,AS$4) -> -343022.54 | AT67: =SUM(EL67:EN67) -> -124756.31 | AU67: =OFFSET($EL67,0,AU$4)+OFFSET($EM67,0,AU$4)+OFFSET($EN67,0,AU$4) -> -151604.05 | AV67: =OFFSET($EL67,0,AV$4)+OFFSET($EM67,0,AV$4)+OFFSET($EN67,0,AV$4) -> -206649.76 | AW67: =OFFSET($EL67,0,AW$4)+OFFSET($EM67,0,AW$4)+OFFSET($EN67,0,AW$4) -> -142145.42 | AX67: =SUM(EX67:EZ67) -> -296053.71 | AY67: =SUM(FA67:FC67) -> -296200.32 | AZ67: =SUM(FD67:FF67) -> -344035.65 | BA67: =SUM(FG67:FI67) -> -374015.99 | BB67: =SUM(FJ67:FL67) -> -165112.13 | BF67: -20283 | BG67: -18267 | BH67: -20166 | BI67: -20091 | BJ67: -19412 | BK67: -22025 | BL67: -25614 | BM67: -25851 | BN67: -24795 | BO67: -25615 | BP67: -26131 | BQ67: -29695 | BR67: -33262 | BS67: -33331 | BT67: -35585 | BU67: -34200 | BV67: -35468 | BW67: -36740 | BX67: -43669 | BY67: -45558 | BZ67: -46237 | CA67: -37735 | CB67: -42197 | CC67: -155226 | CD67: =97-49000 -> -48903 | CE67: -61721 | CF67: -57799 | CG67: -55817 | CH67: -18410 | CI67: -34249 | CJ67: -84808 | CK67: =-51677-10845 -> -62522 | CL67: =-50080-7862 -> -57942 | CM67: =-51818-7862 -> -59680 | CN67: =-49511-7862 -> -57373 | CO67: =-737742+686959-8760 -> -59543 | CP67: -52168 | CQ67: =-48577-17023 -> -65600 | CR67: =-51898-3333 -> -55231 | CS67: =-54797-2051 -> -56848 | CT67: =-58817-7634 -> -66451 | CU67: =-56938-33167 -> -90105 | CV67: -63831 | CW67: -73810.4 | CX67: -64839.15 | CY67: -55416.78 | CZ67: -68197.25 | DA67: -156138.83 | DB67: -65187.06 | DC67: -3027.68 | DD67: -34771.26 | DE67: -33844.8 | DF67: -33048.23 | DG67: -32158.09 | DH67: -32371.64 | DI67: -24183.89 | DJ67: -36107.145 | DK67: -27453.14 | DL67: -24662.94 | DM67: -23600.18 | DN67: -24940.93 | DO67: -20978.04 | DP67: -19832.87 | DQ67: -17184.94 | DR67: -13186.2 | DS67: -71248.1 | DT67: -12826.91 | DU67: -12661.76 | DV67: -75543.81 | DW67: -45461.87 | DX67: -46869 | DY67: 119841.45 | DZ67: -42405.349 | EA67: -37295.45 | EB67: -41493.217 | EC67: -40066.531 | ED67: -43678.452 | EE67: -38712.002 | EF67: -41282.102 | EG67: -37187.547 | EH67: -33891.946 | EI67: -31818.436 | EJ67: -51998.222 | EK67: -259205.89 | EL67: -36285.625 | EM67: -41645.079 | EN67: -46825.605 | EO67: -45991.592 | EP67: -55228.674 | EQ67: -50383.781 | ER67: -56606.467 | ES67: -62250.155 | ET67: -87793.14 | EU67: -76849.242 | EV67: -83599.067 | EW67: 18302.89 | EX67: -102373.49 | EY67: -98227.282 | EZ67: -95452.935 | FA67: -100790.74 | FB67: -105364.83 | FC67: -90044.747 | FD67: -102751.76 | FE67: -135658.08 | FF67: -105625.81 | FG67: -129790.3 | FH67: -117575.5 | FI67: -126650.2 | FJ67: -119271.02 | FK67: -45841.107
C68: PBT | F68: =SUM(F62:F67) -> -2384000 | G68: =SUM(R68:U68) -> -2239302 | H68: =SUM(V68:Y68) -> -2111004 | I68: =SUM(Z68:AC68) -> -3627934 | J68: =SUM(AD68:AG68) -> -3286895.9 | K68: =SUM(AH68:AK68) -> -5449396.4 | L68: =SUM(AL68:AO68) -> -5847583.4 | M68: =SUM(AP68:AS68) -> -4861033.8 | N68: =SUM(AT68:AW68) -> -5030184.1 | O68: =SUM(AX68:BA68) -> -4709278 | P68: =SUM($FJ68:FK68) -> -640133.78 | R68: =SUM(R62:R67) -> -581777 | S68: =SUM(S62:S67) -> -803574 | T68: =SUM(T62:T67) -> -640347 | U68: =SUM(U62:U67) -> -213604 | V68: =SUM(V62:V67) -> -455258 | W68: =SUM(W62:W67) -> -532560 | X68: =SUM(X62:X67) -> -486495 | Y68: =SUM(Y62:Y67) -> -636691 | ... AS68: =SUM(AS62:AS67) -> -1670702.1 | AT68: =SUM(EL68:EN68) -> -1112389.1 | AU68: =OFFSET($EL68,0,AU$4)+OFFSET($EM68,0,AU$4)+OFFSET($EN68,0,AU$4) -> -1112226.9 | AV68: =OFFSET($EL68,0,AV$4)+OFFSET($EM68,0,AV$4)+OFFSET($EN68,0,AV$4) -> -1198855.6 | AW68: =OFFSET($EL68,0,AW$4)+OFFSET($EM68,0,AW$4)+OFFSET($EN68,0,AW$4) -> -1606712.5 | AX68: =SUM(EX68:EZ68) -> -1427461.8 | AY68: =SUM(FA68:FC68) -> -1398776.7 | AZ68: =SUM(FD68:FF68) -> -919050.54 | BA68: =SUM(FG68:FI68) -> -963989.03 | BB68: =SUM(FJ68:FL68) -> -640133.78 | BF68: =SUM(BF62:BF67) -> 28183 | BG68: =SUM(BG62:BG67) -> -284994 | BH68: =SUM(BH62:BH67) -> -324966 | BI68: =SUM(BI62:BI67) -> -347432 | BJ68: =SUM(BJ62:BJ67) -> -234409 | BK68: =SUM(BK62:BK67) -> -221733 | BL68: =SUM(BL62:BL67) -> -241951 | BM68: =SUM(BM62:BM67) -> -121798 | ... FK68: =SUM(FK62:FK67) -> -225689.82
D69: Tax (charge)/credit | H69: =SUM(V69:Y69) -> 289829 | I69: =SUM(Z69:AC69) -> 475120 | J69: =SUM(AD69:AG69) -> 368610.3 | L69: =SUM(DN69:DY69) -> 312501.15 | M69: =SUM(AP69:AS69) -> 176829.87 | N69: =SUM(AT69:AW69) -> 384054.73 | O69: =SUM(AX69:BA69) -> -465675.74 | P69: =SUM($FJ69:FK69) -> -49646.318 | V69: =SUM(BR69:BT69) -> 0 | W69: =SUM(BU69:BW69) -> 0 | X69: =SUM(BX69:BZ69) -> 0 | Y69: =SUM(CA69:CC69) -> 289829 | Z69: =SUM(CD69:CF69) -> 0 | AA69: =SUM(CG69:CI69) -> 0 | AB69: =SUM(CJ69:CL69) -> 0 | AC69: =SUM(CM69:CO69) -> 475120 | AD69: =SUM(CP69:CR69) -> 0 | AE69: =SUM(CS69:CU69) -> 0 | AF69: =SUM(CV69:CX69) -> 0 | AG69: =SUM(CY69:DA69) -> 368610.3 | AH69: =SUM(DB69:DD69) -> 0 | AI69: =SUM(DE69:DG69) -> 0 | AJ69: =SUM(DH69:DJ69) -> -3378.3981 | AK69: =SUM(DK69:DM69) -> 253029.45 | AL69: =SUM(DN69:DP69) -> 0 | AM69: =SUM(DQ69:DS69) -> 0 | AN69: =SUM(DT69:DV69) -> 0 | AO69: =SUM(DW69:DY69) -> 312501.15 | AP69: =SUM(DZ69:EB69) -> -37321.807 | AQ69: =OFFSET($DZ69,0,AQ$4)+OFFSET($EA69,0,AQ$4)+OFFSET($EB69,0,AQ$4) -> -107527.7 | AR69: =OFFSET($DZ69,0,AR$4)+OFFSET($EA69,0,AR$4)+OFFSET($EB69,0,AR$4) -> -92328.323 | AS69: =OFFSET($DZ69,0,AS$4)+OFFSET($EA69,0,AS$4)+OFFSET($EB69,0,AS$4) -> 414007.7 | AT69: =SUM(EL69:EN69) -> -92030.751 | AU69: =OFFSET($EL69,0,AU$4)+OFFSET($EM69,0,AU$4)+OFFSET($EN69,0,AU$4) -> -59634.596 | AV69: =OFFSET($EL69,0,AV$4)+OFFSET($EM69,0,AV$4)+OFFSET($EN69,0,AV$4) -> -164434.08 | AW69: =OFFSET($EL69,0,AW$4)+OFFSET($EM69,0,AW$4)+OFFSET($EN69,0,AW$4) -> 700154.16 | AX69: =SUM(EX69:EZ69) -> -107878.97 | AY69: =SUM(FA69:FC69) -> -174961.41 | AZ69: =SUM(FD69:FF69) -> -83271.896 | BA69: =SUM(FG69:FI69) -> -99563.467 | BB69: =SUM(FJ69:FL69) -> -49646.318 | BR69: 0 | BS69: 0 | BT69: 0 | BU69: 0 | BV69: 0 | BW69: 0 | BX69: 0 | BY69: 0 | CA69: 0 | CB69: 0 | CC69: 289829 | CO69: 475120 | DA69: 368610.3 | DH69: -3378.3981 | DM69: 253029.45 | DN69: 0 | DO69: 0 | DP69: 0 | DQ69: 0 | DR69: 0 | DS69: 0 | DT69: 0 | DU69: 0 | DV69: 0 | DW69: -213141.76 | DX69: -50697.3 | DY69: 576340.21 | DZ69: 0 | EA69: -37321.807 | EB69: 0 | EC69: -37175.523 | ED69: -35179.558 | EE69: -35172.623 | EF69: -46440.556 | EG69: -45887.767 | EH69: 0 | EI69: 0 | EJ69: 0 | EK69: 414007.7 | EL69: -46247.775 | EM69: -45782.976 | EN69: =-249374.370418552+249374.370418552 -> 0 | EO69: 0 | EP69: -59634.596 | ER69: -55592.851 | ES69: -29320.239 | ET69: -79520.993 | EU69: -69098.753 | EV69: -32150.464 | EW69: 801403.38 | EY69: -81875.468 | EZ69: -26003.502 | FA69: -75516.469 | FB69: -75515.469 | FC69: -23929.468 | FD69: -26459.478 | FE69: -26756.179 | FF69: -30056.24 | FG69: -26733.757 | FH69: -37959.958 | FI69: -34869.752 | FJ69: -34868.752 | FK69: -14777.566
C70: PAT | F70: =SUM(F68:F69) -> -2384000 | G70: =SUM(G68:G69) -> -2239302 | H70: =SUM(H68:H69) -> -1821175 | I70: =SUM(I68:I69) -> -3152814 | J70: =SUM(AD70:AG70) -> -2918285.6 | K70: =SUM(AH70:AK70) -> -5199745.3 | L70: =SUM(L68:L69) -> -5535082.2 | M70: =SUM(M68:M69) -> -4684204 | N70: =SUM(AT70:AW70) -> -4646129.4 | O70: =SUM(AX70:BA70) -> -5174953.7 | P70: =SUM($FJ70:FK70) -> -689780.09 | Q70: =SUM(Q68:Q69) -> 0 | R70: =SUM(R68:R69) -> -581777 | S70: =SUM(S68:S69) -> -803574 | T70: =SUM(T68:T69) -> -640347 | U70: =SUM(U68:U69) -> -213604 | V70: =SUM(V68:V69) -> -455258 | W70: =SUM(W68:W69) -> -532560 | X70: =SUM(X68:X69) -> -486495 | ... AS70: =SUM(AS68:AS69) -> -1256694.4 | AT70: =SUM(EL70:EN70) -> -1204419.9 | AU70: =OFFSET($EL70,0,AU$4)+OFFSET($EM70,0,AU$4)+OFFSET($EN70,0,AU$4) -> -1171861.5 | AV70: =OFFSET($EL70,0,AV$4)+OFFSET($EM70,0,AV$4)+OFFSET($EN70,0,AV$4) -> -1363289.7 | AW70: =OFFSET($EL70,0,AW$4)+OFFSET($EM70,0,AW$4)+OFFSET($EN70,0,AW$4) -> -906558.31 | AX70: =SUM(EX70:EZ70) -> -1535340.7 | AY70: =SUM(FA70:FC70) -> -1573738.1 | AZ70: =SUM(FD70:FF70) -> -1002322.4 | BA70: =SUM(FG70:FI70) -> -1063552.5 | BB70: =SUM(FJ70:FL70) -> -689780.09 | BF70: =SUM(BF68:BF69) -> 28183 | BG70: =SUM(BG68:BG69) -> -284994 | BH70: =SUM(BH68:BH69) -> -324966 | BI70: =SUM(BI68:BI69) -> -347432 | BJ70: =SUM(BJ68:BJ69) -> -234409 | BK70: =SUM(BK68:BK69) -> -221733 | BL70: =SUM(BL68:BL69) -> -241951 | BM70: =SUM(BM68:BM69) -> -121798 | ... FK70: =SUM(FK68:FK69) -> -240467.39
BB71: =FJ71 -> 0
B72: Balance Sheet | BB72: =FJ72 -> 0
C73: Fixed Assets | G73: =U73 -> 1427037 | H73: =Y73 -> 1488326 | I73: =AC73 -> 2103439 | J73: =AE73 -> 2198377 | K73: =DM73 -> 3798669.9 | L73: =DY73 -> 4399256.6 | M73: =AS73 -> 5113923.8 | N73: =AW73 -> 6230621.8 | O73: =FG73 -> 6172805.2 | P73: =FK73 -> 6276671.4 | R73: 1409000 | S73: 1449000 | T73: 1448000 | U73: 1427037 | V73: =BT73 -> 1398930 | W73: =BW73 -> 1379715 | X73: =BZ73 -> 1456688 | Y73: =CC73 -> 1488326 | Z73: =CF73 -> 1527684 | AA73: =CI73 -> 1568741 | AB73: =CL73 -> 1567452 | AC73: =CO73 -> 2103439 | AD73: =CR73 -> 2175439 | AE73: =CU73 -> 2198377 | AF73: =CX73 -> 2217046.2 | AG73: =DA73 -> 2584233.3 | AH73: =DD73 -> 2735279.6 | AI73: =DG73 -> 2932247.1 | AJ73: =DJ73 -> 3105711.6 | AK73: =DM73 -> 3798669.9 | AL73: =DP73 -> 4080644.5 | AM73: =DS73 -> 4234559.7 | AN73: =DV73 -> 4310063 | AO73: =DY73 -> 4399256.6 | AP73: =EB73 -> 4562408.4 | AQ73: =EE73 -> 4624711.3 | AR73: =EH73 -> 4783744.5 | AS73: =EK73 -> 5113923.8 | AT73: =EN73 -> 5468417.3 | AU73: =EQ73 -> 5754651.7 | AV73: =ET73 -> 5982956.4 | AW73: =EW73 -> 6230621.8 | AX73: =EZ73 -> 6179959.3 | AY73: =FC73 -> 6051180.6 | AZ73: =FF73 -> 6120529.5 | BA73: =FI73 -> 6223838.5 | BB73: =FK73 -> 6276671.4 | BR73: =U73-BR105+BR66 -> 1434311 | BS73: =BR73-BS105+BS66 -> 1392251 | BT73: =BS73-BT105+BT66 -> 1398930 | BU73: =BT73-BU105+BU66 -> 1383486 | BV73: =BU73-BV105+BV66 -> 1398560 | BW73: =BV73-BW105+BW66 -> 1379715 | BX73: =BW73-BX105+BX66 -> 1410344 | BY73: =BX73-BY105+BY66 -> 1431097 | BZ73: =BY73-BZ105+BZ66 -> 1456688 | ... CC73: =CB73-CC105+CC66 -> 1488326 | CD73: =CC73-CD105+CD66-13000 -> 1480551 | CE73: =CD73-CE105+CE66+40000-3000 -> 1520707 | CF73: =CE73-CF105+CF66-9000 -> 1527684 | CG73: =CF73-CG105+CG66-12000 -> 1513132 | CH73: =CG73-CH105+CH66-12000 -> 1508928 | CI73: =CH73-CI105+CI66+3000 -> 1568741 | CJ73: =CI73-CJ105+CJ66 -> 1572181 | CK73: =CJ73-CK105+CK66-6000 -> 1559807 | CL73: =CK73-CL105+CL66 -> 1567452 | CM73: =CL73-CM105+CM66+80000-21000 -> 1618898 | CN73: =CM73-CN105+CN66+200000-54000 -> 1792655 | CO73: =CN73-CO105+CO66+212000 -> 2103439 | CP73: =CO73-CP105+CP66 -> 2085710 | CQ73: =CP73-CQ105+CQ66 -> 2127779 | CR73: =CQ73-CR105+CR66 -> 2175439 | CS73: =CR73-CS105+CS66 -> 2230529 | CT73: =CS73-CT105+CT66 -> 2199830 | CU73: =CT73-CU105+CU66 -> 2198377 | CV73: =CU73-CV105+CV66 -> 2199312 | CW73: =CV73-CW105+CW66 -> 2225353.3 | ... CY73: =CX73-CY105+CY66 -> 2281503.1 | CZ73: =CY73-CZ105+CZ66-CZ137+CY137 -> 2454970.7 | DA73: =CZ73-DA105+DA66-DA137+CZ137 -> 2584233.3 | DB73: =DA73-DB105+DB66-DB137+DA137 -> 2508133.5 | DC73: =DB73-DC105+DC66-DC137+DB137 -> 2630409.2 | DD73: =DC73-DD105+DD66-DD137+DC137 -> 2735279.6 | DE73: =DD73-DE105+DE66-DE137+DD137 -> 2802741.7 | DF73: =DE73-DF105+DF66-DF137+DE137 -> 2838869.9 | DG73: =DF73-DG105+DG66-DG137+DF137 -> 2932247.1 | ... EG73: =EF73-EG105+EG66-EG137+EF137 -> 4764776.8 | EH73: 4783744.5 | EI73: 4841236.4 | EJ73: 5069791.8 | EK73: 5113923.8 | EL73: 5186782.3 | EM73: 5343438.1 | EN73: 5468417.3 | EO73: 5549316.6 | EP73: 5654636.1 | EQ73: 5754651.7 | ER73: 5840604.2 | ES73: 5892947.2 | ET73: 5982956.4 | EU73: 6069094.4 | EV73: 6162865.4 | EW73: 6230621.8 | EX73: 6257537.4 | EY73: 6223337.5 | EZ73: 6179959.3 | FA73: 6130224.6 | FB73: 6087501.6 | FC73: 6051180.6 | FD73: 6033448.4 | FE73: 6052626 | FF73: 6120529.5 | FG73: 6172805.2 | FH73: 6205535 | FI73: 6223838.5 | FJ73: 6232709.6 | FK73: 6276671.4
G74: =U74 -> 0 | H74: =Y74 -> 0 | I74: =Z74 -> 0 | P74: =FJ74 -> 0 | BB74: =FJ74 -> 0
D75: Stock | G75: =U75 -> 272439 | H75: =Y75 -> 370046 | I75: =AC75 -> 374696 | J75: =AE75 -> 346220 | K75: =DM75 -> 1197538.2 | L75: =DY75 -> 1145752.7 | M75: =AS75 -> 1252883.2 | N75: =AW75 -> 972274.85 | O75: =FG75 -> 782857.29 | P75: =FK75 -> 912917.56 | R75: 418000 | S75: 277000 | T75: 276000 | U75: 272439 | V75: =BT75 -> 370038 | W75: =BW75 -> 495792 | X75: =BZ75 -> 515569 | Y75: =CC75 -> 370046 | Z75: =CF75 -> 525715 | AA75: =CI75 -> 378442 | AB75: =CL75 -> 414224 | AC75: =CO75 -> 374696 | AD75: =CR75 -> 352268 | AE75: =CU75 -> 346220 | AF75: =CX75 -> 320801.47 | AG75: =DA75 -> 550531.74 | AH75: =DD75 -> 784117.87 | AI75: =DG75 -> 1001159.8 | AJ75: =DJ75 -> 1023564 | AK75: =DM75 -> 1197538.2 | AL75: =DP75 -> 1326672.4 | AM75: =DS75 -> 1331262.6 | AN75: =DV75 -> 1370081.9 | AO75: =DY75 -> 1145752.7 | AP75: =EB75 -> 1197520.3 | AQ75: =EE75 -> 1144708.9 | AR75: =EH75 -> 1255789.8 | AS75: =EK75 -> 1252883.2 | AT75: =EN75 -> 1090621.3 | AU75: =EQ75 -> 1033955.5 | AV75: =ET75 -> 904191.29 | AW75: =EW75 -> 972274.85 | AX75: =EZ75 -> 1201714.1 | AY75: =FC75 -> 959881.83 | AZ75: =FF75 -> 953451.39 | BA75: =FI75 -> 792988.9 | BB75: =FK75 -> 912917.56 | BR75: 407022 | BS75: 363134 | BT75: =370038 -> 370038 | BU75: 301673 | BV75: 418926 | BW75: 495792 | BX75: 468436 | BY75: 490403 | BZ75: 515569 | CA75: 465886 | CB75: 454847 | CC75: 370046 | CD75: 306887 | CE75: 429043 | CF75: 525715 | CG75: =471292-99500 -> 371792 | CH75: 359452 | CI75: 378442 | CJ75: 348362 | CK75: 301421 | CL75: 414224 | CM75: 449680 | CN75: 481827 | CO75: 374696 | CP75: 278631 | CQ75: 281865 | CR75: 352268 | CS75: 486643 | CT75: 412589 | CU75: 346220 | CV75: 304855 | CW75: 286853.71 | CX75: 320801.47 | CY75: 263021.81 | CZ75: 488666.33 | DA75: 550531.74 | DB75: 514332.8 | DC75: 567018.8 | DD75: 784117.87 | DE75: 794424.73 | DF75: 899700.88 | DG75: 1001159.8 | DH75: 908138.42 | DI75: 987696.67 | DJ75: 1023564 | DK75: 1218735.6 | DL75: 1160916.2 | DM75: 1197538.2 | DN75: 1218478.3 | DO75: 1439477.4 | DP75: 1326672.4 | DQ75: 1460583.8 | DR75: 1451019.1 | DS75: 1331262.6 | DT75: 1251103.2 | DU75: 1195506.8 | DV75: 1370081.9 | DW75: 1300213 | DX75: 1199848 | DY75: 1145752.7 | DZ75: 1255073.1 | EA75: 1303300.3 | EB75: 1197520.3 | EC75: 1182413.4 | ED75: 1199195.8 | EE75: 1144708.9 | EF75: 1076630.6 | EG75: 1328785.2 | EH75: 1255789.8 | EI75: 1258201.8 | EJ75: 1179286.5 | EK75: 1252883.2 | EL75: 1212632.5 | EM75: 1266062.2 | EN75: 1090621.3 | EO75: 1164734.2 | EP75: 1033344.4 | EQ75: 1033955.5 | ER75: 951385.38 | ES75: 999992.52 | ET75: 904191.29 | EU75: 1075173.2 | EV75: 1014689.2 | EW75: 972274.85 | EX75: 1091329.5 | EY75: 1059240.4 | EZ75: 1201714.1 | FA75: 1090316.6 | FB75: 935216.17 | FC75: 959881.83 | FD75: 938429.29 | FE75: 842963.53 | FF75: 953451.39 | FG75: 782857.29 | FH75: 835809.17 | FI75: 792988.9 | FJ75: 938223.27 | FK75: 912917.56
D76: Trade & other debtors | G76: =U76 -> 1526048 | H76: =Y76 -> 2408867 | I76: =AC76 -> 2430609 | J76: =AE76 -> 1998945 | K76: =DM76 -> 2893161.3 | L76: =DY76 -> 3722297 | M76: =AS76 -> 3774890.2 | N76: =AW76 -> 4546706.4 | O76: =FG76 -> 4273907.8 | P76: =FK76 -> 4231642.1 | R76: 1225000 | S76: 1536000 | T76: 1450000 | U76: 1526048 | V76: =BT76 -> 1824907 | W76: =BW76 -> 1678996 | X76: =BZ76 -> 2104092 | Y76: =CC76 -> 2408867 | Z76: =CF76 -> 2007743 | AA76: =CI76 -> 1993903 | AB76: =CL76 -> 2312943 | AC76: =CO76 -> 2430609 | AD76: =CR76 -> 2211054 | AE76: =CU76 -> 1998945 | AF76: =CX76 -> 2043836 | AG76: =DA76 -> 1708661.2 | AH76: =DD76 -> 1712261.1 | AI76: =DG76 -> 2349779.2 | AJ76: =DJ76 -> 2507631 | AK76: =DM76 -> 2893161.3 | AL76: =DP76 -> 2677300.7 | AM76: =DS76 -> 3212031 | AN76: =DV76 -> 3510765.2 | AO76: =DY76 -> 3722297 | AP76: =EB76 -> 3463065.1 | AQ76: =EE76 -> 3620038 | AR76: =EH76 -> 4045800.7 | AS76: =EK76 -> 3774890.2 | AT76: =EN76 -> 3704064.4 | AU76: =EQ76 -> 3900367.6 | AV76: =ET76 -> 3611889.8 | AW76: =EW76 -> 4546706.4 | AX76: =EZ76 -> 4079335.1 | AY76: =FC76 -> 4241733.8 | AZ76: =FF76 -> 4311141.6 | BA76: =FI76 -> 4814493.2 | BB76: =FK76 -> 4231642.1 | BR76: =1339434+141544-20000 -> 1460978 | BS76: =1440838+133730-21257 -> 1553311 | BT76: =1739877+129524-13237-21257-10000 -> 1824907 | BU76: =1636028+127495-21257-10000-10000 -> 1722266 | BV76: =1630680+146383-21257 -> 1755806 | BW76: =1543282+156971-21257 -> 1678996 | BX76: =1956809-21257+172478+6181-13 -> 2114198 | BY76: =1884281+183073+11214-21257-21 -> 2057290 | BZ76: =1925430+188436+11488-21257-5 -> 2104092 | CA76: =1899600+25779+197082-21257+2 -> 2101206 | CB76: =1968796+204311-21257-23+5000 -> 2156827 | CC76: =2220150+150841+51980-21257-28+7181 -> 2408867 | CD76: =2034354+126245+68849-21257-3+1 -> 2208189 | CE76: =2133641-21257+122982+69188+1-5 -> 2304550 | CF76: =1934796-21257+119442+69765+1-4-95000 -> 2007743 | CG76: =2017447-21257+77147+119790+9 -> 2193136 | CH76: =1690461-21257+56874+121845-7 -> 1847916 | CI76: =1810898-21257+79003+125261-2+359606-359606 -> 1993903 | CJ76: =1933105+133021+84616-21257-9 -> 2129476 | CK76: =1923103+121903+67230-21257+2 -> 2090981 | CL76: =2152190+99004+83010-21257-4 -> 2312943 | CM76: =1880898+99066+75329-21257+4 -> 2034040 | CN76: =2190980+30114+80426-2-21257 -> 2280261 | CO76: =2126572+217270+86768-1 -> 2430609 | CP76: =2543699+183416+77636-21257-4001-7 -> 2779486 | CQ76: =1908789+57390+83900-27941+3 -> 2022141 | CR76: =2072636+51213+87204+1 -> 2211054 | CS76: =2237005+52729+82593-6 -> 2372321 | CT76: =2463611+79337+49908+3 -> 2592859 | CU76: =1863620+49444+85917-36 -> 1998945 | CV76: 1881847 | CW76: 1918045.8 | CX76: 2043836 | CY76: 1679568.7 | CZ76: 1764280.3 | DA76: 1708661.2 | DB76: 2152892 | DC76: 2183204 | DD76: 1712261.1 | DE76: 1820129.3 | DF76: 2017438.3 | DG76: 2349779.2 | DH76: 2422334.6 | DI76: 2625521.1 | DJ76: 2507631 | DK76: 2808618.1 | DL76: 2524727.5 | DM76: 2893161.3 | DN76: 2801695.9 | DO76: 2767696 | DP76: 2677300.7 | DQ76: 3113961.5 | DR76: 3001640.8 | DS76: 3212031 | DT76: 3278947.1 | DU76: 2871589.6 | DV76: 3510765.2 | DW76: 3390886.5 | DX76: 3354952.4 | DY76: 3722297 | DZ76: =3202132.33+123974 -> 3326106.3 | EA76: =3425417.36+123974 -> 3549391.4 | EB76: =3339091.14+123974 -> 3463065.1 | EC76: =3546605.53+123974 -> 3670579.5 | ED76: =3292465.6+123974 -> 3416439.6 | EE76: 3620038 | EF76: 3538474.5 | EG76: 3603519.8 | EH76: 4045800.7 | EI76: 3975709.7 | EJ76: 3847572.2 | EK76: 3774890.2 | EL76: 3189931.4 | EM76: 3418674 | EN76: 3704064.4 | EO76: 3604713 | EP76: 3368564.3 | EQ76: 3900367.6 | ER76: 3561048.7 | ES76: 3630703.6 | ET76: 3611889.8 | EU76: 3546239 | EV76: 4233470.2 | EW76: 4546706.4 | EX76: 4684579.5 | EY76: 4770415.7 | EZ76: 4079335.1 | FA76: 4078485.5 | FB76: 4244326.9 | FC76: 4241733.8 | FD76: 4487337.5 | FE76: 3861467.3 | FF76: 4311141.6 | FG76: 4273907.8 | FH76: 5284125.3 | FI76: 4814493.2 | FJ76: 4296170.3 | FK76: 4231642.1
D77: Prepayments & accrued Income | G77: =U77 -> 292653 | H77: =Y77 -> 285730 | I77: =AC77 -> 655728 | J77: =AE77 -> 952447 | K77: =DM77 -> 1712448.2 | L77: =DY77 -> 1841259.2 | M77: =AS77 -> 2267599.4 | N77: =AW77 -> 2055378.1 | O77: =FG77 -> 2323243.7 | P77: =FK77 -> 2584988.9 | R77: 332000 | S77: 387000 | T77: 389000 | U77: 292653 | V77: =BT77 -> 322768 | W77: =BW77 -> 294648 | X77: =BZ77 -> 343700 | Y77: =CC77 -> 285730 | Z77: =CF77 -> 433102 | AA77: =CI77 -> 782559 | AB77: =CL77 -> 710222 | AC77: =CO77 -> 655728 | AD77: =CR77 -> 926341 | AE77: =CU77 -> 952447 | AF77: =CX77 -> 1388310.8 | AG77: =DA77 -> 1308793.2 | AH77: =DD77 -> 1188487.3 | AI77: =DG77 -> 1258101.3 | AJ77: =DJ77 -> 1494271.9 | AK77: =DM77 -> 1712448.2 | AL77: =DP77 -> 1928542.2 | AM77: =DS77 -> 1751761.6 | AN77: =DV77 -> 1967503.8 | AO77: =DY77 -> 1841259.2 | AP77: =EB77 -> 2256503 | AQ77: =EE77 -> 2086849 | AR77: =EH77 -> 1680347.7 | AS77: =EK77 -> 2267599.4 | AT77: =EN77 -> 2536239.2 | AU77: =EQ77 -> 2651549.9 | AV77: =ET77 -> 2547345.4 | AW77: =EW77 -> 2055378.1 | AX77: =EZ77 -> 2160372.5 | AY77: =FC77 -> 2055205.3 | AZ77: =FF77 -> 2335284.8 | BA77: =FI77 -> 2033204.6 | BB77: =FK77 -> 2584988.9 | BR77: =412170-150570 -> 261600 | BS77: =450471-150570 -> 299901 | BT77: =473338-150570 -> 322768 | BU77: =461455-150570 -> 310885 | BV77: =459134-150570 -> 308564 | BW77: =445218-150570 -> 294648 | BX77: =454147-150570 -> 303577 | BY77: =418094-150570 -> 267524 | BZ77: =494270-150570 -> 343700 | CA77: =491876-150570 -> 341306 | CB77: 285750 | CC77: 285730 | CD77: 329217 | CE77: 342210 | CF77: 433102 | CG77: 618800 | CH77: 635080 | CI77: 782559 | CJ77: 575478 | CK77: 699173 | CL77: 710222 | CM77: 759364 | CN77: 824679 | CO77: 655728 | CP77: 693257 | CQ77: 705423 | CR77: 926341 | CS77: 797545 | CT77: 855395 | CU77: 952447 | CV77: 1259561 | CW77: 1303987.9 | CX77: 1388310.8 | CY77: 1310766.2 | CZ77: 1218713.6 | DA77: 1308793.2 | DB77: 1154714.6 | DC77: 1136941.1 | DD77: 1188487.3 | DE77: 1135137.3 | DF77: 1318833.6 | DG77: 1258101.3 | DH77: 1518752.4 | DI77: 1552270.6 | DJ77: 1494271.9 | DK77: 1421689 | DL77: 1706551.4 | DM77: 1712448.2 | DN77: 1712206.1 | DO77: 1742432 | DP77: 1928542.2 | DQ77: 1903812.1 | DR77: 1868617.7 | DS77: 1751761.6 | DT77: 1594999.9 | DU77: 1599879.3 | DV77: 1967503.8 | DW77: 1836086.1 | DX77: 1799077 | DY77: 1841259.2 | DZ77: 1752974.5 | EA77: 1736218.4 | EB77: 2256503 | EC77: 2180131 | ED77: 2075128.4 | EE77: 2086849 | EF77: 1814215.8 | EG77: 1722721.7 | EH77: 1680347.7 | EI77: 2179287 | EJ77: 2130428.9 | EK77: 2267599.4 | EL77: 2168972.3 | EM77: 2530528.8 | EN77: 2536239.2 | EO77: 2785739.3 | EP77: 2841634.3 | EQ77: 2651549.9 | ER77: 2503013.7 | ES77: 2448693.4 | ET77: 2547345.4 | EU77: 2494730.7 | EV77: 2197160.5 | EW77: 2055378.1 | EX77: 1940998.1 | EY77: 1942674.5 | EZ77: 2160372.5 | FA77: 2104338.3 | FB77: 2023055.8 | FC77: 2055205.3 | FD77: 2231913.1 | FE77: 2435789.8 | FF77: 2335284.8 | FG77: 2323243.7 | FH77: 2085968.6 | FI77: 2033204.6 | FJ77: 1975568.2 | FK77: 2584988.9
D78: R&D tax credit | G78: =U78 -> 363620 | H78: =Y78 -> 317100 | I78: =AC78 -> 545200 | J78: =AE78 -> 448784 | K78: =DM78 -> 525747.17 | L78: =DY78 -> 1319079.6 | M78: =AS78 -> 777530.52 | N78: =AW78 -> 879798.01 | O78: =FG78 -> 1003675.6 | P78: =FK78 -> 270760.93 | R78: 324000 | S78: 324000 | T78: 324000 | U78: 363620 | V78: =BT78 -> 363620 | W78: =BW78 -> 363620 | X78: =BZ78 -> 0 | Y78: =CC78 -> 317100 | Z78: =CD78 -> 317100 | AA78: =CI78 -> 317100 | AB78: =CL78 -> 317100 | AC78: =CO78 -> 545200 | AD78: =CR78 -> 448784 | AE78: =CU78 -> 448784 | AF78: =CX78 -> 1.58 | AG78: =DA78 -> 427376.58 | AH78: =DD78 -> 427376.58 | AI78: =DG78 -> 427376.58 | AJ78: =DJ78 -> 1.58 | AK78: =DM78 -> 525747.17 | AL78: =DP78 -> 525747.17 | AM78: =DS78 -> 525747.17 | AN78: =DV78 -> 525747.17 | AO78: =DY78 -> 1319079.6 | AP78: =EB78 -> 826174 | AQ78: =EE78 -> 826174 | AR78: =EH78 -> -0.48 | AS78: =EK78 -> 777530.52 | AT78: =EN78 -> 777530.52 | AU78: =EQ78 -> 777530.52 | AV78: =ET78 -> 777530.52 | AW78: =EW78 -> 879798.01 | AX78: =EZ78 -> 879798.01 | AY78: =FC78 -> 871773.21 | AZ78: =FF78 -> 1000480.6 | BA78: =FI78 -> 992947.22 | BB78: =FK78 -> 270760.93 | BR78: 363620 | BS78: 363620 | BT78: 363620 | BU78: 363620 | BV78: 363620 | BW78: 363620 | BX78: 363620 | BY78: 363620 | BZ78: 0 | CA78: 0 | CB78: 0 | CC78: 317100 | CD78: 317100 | CE78: 317100 | CF78: 317100 | CG78: 317100 | CH78: 317100 | CI78: 317100 | CJ78: 317100 | CK78: 317100 | CL78: 317100 | CM78: 317100 | CN78: 317100 | CO78: 545200 | CP78: =1043+447741 -> 448784 | CQ78: =1043+447741 -> 448784 | CR78: =1043+447741 -> 448784 | CS78: =1043+447741 -> 448784 | CT78: =1043+447741 -> 448784 | CU78: 448784 | CV78: 448784 | CW78: 448783.58 | CX78: 1.58 | CY78: 1.58 | CZ78: 1.58 | DA78: 427376.58 | DB78: 427376.58 | DC78: 427376.58 | DD78: 427376.58 | DE78: 427376.58 | DF78: 427376.58 | DG78: 427376.58 | DH78: 427376.58 | DI78: 427376.58 | DJ78: 1.58 | DK78: 1.58 | DL78: 1.58 | DM78: 525747.17 | DN78: 525747.17 | DO78: 525747.17 | DP78: 525747.17 | DQ78: 525747.17 | DR78: 525747.17 | DS78: 525747.17 | DT78: 525747.17 | DU78: 525747.17 | DV78: 525747.17 | DW78: 525747.17 | DX78: 525747 | DY78: 1319079.6 | DZ78: 826174 | EA78: 826174 | EB78: 826174 | EC78: 826174 | ED78: 826174 | EE78: 826174 | EF78: 826174 | EG78: -0.48 | EH78: -0.48 | EI78: -0.48 | EJ78: -0.48 | EK78: 777530.52 | EL78: =549999.52+227531 -> 777530.52 | EM78: 777530.52 | EN78: 777530.52 | EO78: 777530.52 | EP78: =549999.52+227531 -> 777530.52 | EQ78: 777530.52 | ER78: 777530.52 | ES78: 777530.52 | ET78: 777530.52 | EU78: 777530.52 | EV78: 777530.52 | EW78: 879798.01 | EX78: 879798.01 | EY78: 879798.01 | EZ78: 879798.01 | FA78: 879798.01 | FB78: 868551.92 | FC78: 871773.21 | FD78: 869853.23 | FE78: 994506.87 | FF78: 1000480.6 | FG78: 1003675.6 | FH78: 1003990.5 | FI78: 992947.22 | FJ78: 261569.5 | FK78: 270760.93
C79: Current Assets | G79: =U79 -> 2454760 | H79: =Y79 -> 3381743 | I79: =AC79 -> 4006233 | J79: =AE79 -> 3746396 | K79: =DM79 -> 6328894.9 | L79: =DY79 -> 8028388.6 | M79: =AS79 -> 8072903.2 | N79: =AW79 -> 8454157.3 | O79: =FG79 -> 8383684.3 | P79: =FK79 -> 8000309.5 | R79: =SUM(R75:R78) -> 2299000 | S79: =SUM(S75:S78) -> 2524000 | T79: =SUM(T75:T78) -> 2439000 | U79: =SUM(U75:U78) -> 2454760 | V79: =SUM(V75:V78) -> 2881333 | W79: =SUM(W75:W78) -> 2833056 | X79: =SUM(X75:X78) -> 2963361 | Y79: =SUM(Y75:Y78) -> 3381743 | ... AG79: =SUM(AG75:AG78) -> 3995362.7 | AH79: =DD79 -> 4112242.9 | AI79: =DG79 -> 5036416.8 | AJ79: =DJ79 -> 5025468.5 | AK79: =DM79 -> 6328894.9 | AL79: =DP79 -> 6458262.5 | AM79: =DS79 -> 6820802.3 | AN79: =DV79 -> 7374098.1 | AO79: =DY79 -> 8028388.6 | AP79: =EB79 -> 7743262.5 | AQ79: =EE79 -> 7677769.9 | AR79: =EH79 -> 6981937.8 | AS79: =EK79 -> 8072903.2 | AT79: =EN79 -> 8108455.5 | AU79: =EQ79 -> 8363403.5 | AV79: =ET79 -> 7840957 | AW79: =EW79 -> 8454157.3 | AX79: =EZ79 -> 8321219.8 | AY79: =FC79 -> 8128594.2 | AZ79: =FF79 -> 8600358.5 | BA79: =FI79 -> 8633634 | BB79: =FK79 -> 8000309.5 | BR79: =SUM(BR75:BR78) -> 2493220 | BS79: =SUM(BS75:BS78) -> 2579966 | BT79: =SUM(BT75:BT78) -> 2881333 | BU79: =SUM(BU75:BU78) -> 2698444 | BV79: =SUM(BV75:BV78) -> 2846916 | BW79: =SUM(BW75:BW78) -> 2833056 | BX79: =SUM(BX75:BX78) -> 3249831 | BY79: =SUM(BY75:BY78) -> 3178837 | ... FK79: =SUM(FK75:FK78) -> 8000309.5
N80: =AW80 -> 0 | O80: =FG80 -> 0 | P80: =FK80 -> 0 | AX80: =EZ80 -> 0 | AY80: =FC80 -> 0 | AZ80: =FF80 -> 0 | BA80: =FI80 -> 0 | BB80: =FK80 -> 0
C81: Bank | G81: =U81 -> 1150398 | H81: =Y81 -> 903850 | I81: =AC81 -> 1049830 | J81: =AE81 -> 3104267 | K81: =DM81 -> 12171162 | L81: =DY81 -> 8442637 | M81: =AS81 -> 4143324.4 | N81: =AW81 -> 4672940.1 | O81: =FG81 -> 2430217.7 | P81: =FK81 -> 4773852.1 | R81: 841800 | S81: 666800 | T81: 556800 | U81: 1150398 | V81: =BT81 -> 516015 | W81: =BW81 -> 730017 | X81: =BZ81 -> 680510 | Y81: =CC81 -> 903850 | Z81: =CF81 -> 1198409 | AA81: =CI81 -> 2518462 | AB81: =CL81 -> 1814205 | AC81: =CO81 -> 1049830 | AD81: =CR81 -> 2326307 | AE81: =CU81 -> 3104267 | AF81: =CX81 -> 1862349.9 | AG81: =DA81 -> 16244488 | AH81: =DD81 -> 13513987 | AI81: =DG81 -> 11668910 | AJ81: =DJ81 -> 14657635 | AK81: =DM81 -> 12171162 | AL81: =DP81 -> 9613613.4 | AM81: =DS81 -> 8765841.2 | AN81: =DV81 -> 10392751 | AO81: =DY81 -> 8442637 | AP81: =EB81 -> 7017717.7 | AQ81: =EE81 -> 5559138.8 | AR81: =EH81 -> 5295596.6 | AS81: =EK81 -> 4143324.4 | AT81: =EN81 -> 2605792.5 | AU81: =EQ81 -> 2353140.3 | AV81: =ET81 -> 3428321.7 | AW81: =EW81 -> 4672940.1 | AX81: =EZ81 -> 2834130.6 | AY81: =FC81 -> 2537064.2 | AZ81: =FF81 -> 2603949.9 | BA81: =FI81 -> 3096169.7 | BB81: =FK81 -> 4773852.1 | BR81: =BR117 -> 1163323 | BS81: =BS117 -> 787372 | BT81: =BT117 -> 516015 | BU81: =BU117 -> 609038 | BV81: =BV117 -> 482329 | BW81: =BW117 -> 730017 | BX81: =BX117 -> 274252 | BY81: =BY117 -> 685169 | ... EM81: =EM117 -> 3197701.6 | EN81: =2632362.18754199-26569.7029448939 -> 2605792.5 | EO81: =2778751.83676858-19576.14832496 -> 2759175.7 | EP81: =2468183.92044976+580.129159906559 -> 2468764 | EQ81: =2388036.28720759-34895.9921824599 -> 2353140.3 | ER81: =3155573.23121543-25262.6779948433 -> 3130310.6 | ES81: =4269667.93261626-14555.9015540332 -> 4255112 | ET81: =3406425.12143667+21896.6145897333 -> 3428321.7 | EU81: =3016552.97697381+29189.2927231315 -> 3045742.3 | EV81: =2356157.46871165-4974.52859474681 -> 2351182.9 | EW81: =4672940.1 -> 4672940.1 | EX81: =3851685.54+54346.2234248561 -> 3906031.8 | EY81: =3015164.28335278+83951.0033543529 -> 3099115.3 | EZ81: =2774034.22490301+60096.3754730415 -> 2834130.6 | FA81: =2344040.07819684+123058.413756386 -> 2467098.5 | FB81: =2301913.54+125718.321697984 -> 2427631.9 | FC81: =2408045.9174616+129018.307740026 -> 2537064.2 | FD81: =3335424.00407999-33799.0584686127 -> 3301624.9 | FE81: =3312472.15583401-27259.2285961048 -> 3285212.9 | FF81: =2633537.84306776-29587.979256918 -> 2603949.9 | FG81: =2453004.44205656-22786.7587239975 -> 2430217.7 | FH81: =1799802.9878651-24301.1411787807 -> 1775501.8 | FI81: =3117120.11618585-20950.3673085214 -> 3096169.7 | FJ81: =3157101.03614932-10745.72 -> 3146355.3 | FK81: =4792915.84-19063.7742633564 -> 4773852.1
N82: =AW82 -> 0 | O82: =FG82 -> 0 | P82: =FK82 -> 0 | AX82: =EZ82 -> 0 | AY82: =FC82 -> 0 | AZ82: =FF82 -> 0 | BA82: =FI82 -> 0 | BB82: =FK82 -> 0
D83: Creditors | G83: =U83 -> -1836074 | H83: =Y83 -> -1545040 | I83: =AC83 -> -1965591 | J83: =AE83 -> -2110595 | K83: =DM83 -> -2866024.4 | L83: =DY83 -> -2651977.9 | M83: =AS83 -> -2889805.6 | N83: =AW83 -> -4381818.3 | O83: =FG83 -> -4120073.5 | P83: =FK83 -> -4228544.7 | R83: -1658000 | S83: -1944000 | T83: -2336000 | U83: -1836074 | V83: =BT83 -> -1778117 | W83: =BW83 -> -1699743 | X83: =BZ83 -> -1579639 | Y83: =CC83 -> -1545040 | Z83: =CF83 -> -1734340 | AA83: =CI83 -> -1635868 | AB83: =CL83 -> -2018267 | AC83: =CO83 -> -1965591 | AD83: =CR83 -> -2510655 | AE83: =CU83 -> -2110595 | AF83: =CX83 -> -1860863 | AG83: =DA83 -> -2522470.5 | AH83: =DD83 -> -2121007.8 | AI83: =DG83 -> -2593488 | AJ83: =DJ83 -> -2792404.3 | AK83: =DM83 -> -2866024.4 | AL83: =DP83 -> -2593796.7 | AM83: =DS83 -> -2771222.1 | AN83: =DV83 -> -2618390.5 | AO83: =DY83 -> -2651977.9 | AP83: =EB83 -> -2726074.4 | AQ83: =EE83 -> -2784174.1 | AR83: =EH83 -> -2980622.5 | AS83: =EK83 -> -2889805.6 | AT83: =EN83 -> -3519581.1 | AU83: =EQ83 -> -3969283.5 | AV83: =ET83 -> -4058918.9 | AW83: =EW83 -> -4381818.3 | AX83: =EZ83 -> -4220495.5 | AY83: =FC83 -> -4754249.2 | AZ83: =FF83 -> -4097355.8 | BA83: =FI83 -> -4185025.2 | BB83: =FK83 -> -4228544.7 | BR83: -1872326 | BS83: -1720789 | BT83: -1778117 | BU83: -1804013 | BV83: -2005719 | BW83: =-1699738-5 -> -1699743 | BX83: -1890282 | BY83: -1794131 | BZ83: -1579639 | CA83: -1375446 | CB83: -1372689 | CC83: -1545040 | CD83: =-1447284 -> -1447284 | CE83: -1544781 | CF83: =-1734340 -> -1734340 | CG83: =-2139209+99500 -> -2039709 | CH83: =-1845498-29648-81179 -> -1956325 | CI83: =-1588440-75811+28383 -> -1635868 | CJ83: =-1904575+29505 -> -1875070 | CK83: =-1628199+25967-65406 -> -1667638 | CL83: =-2048855+30588 -> -2018267 | CM83: =-2053904-103854+25914 -> -2131844 | CN83: =-1873228-162956+25270 -> -2010914 | CO83: -1965591 | CP83: =-2315978-75996+30458 -> -2361516 | CQ83: =-2295922+6356+58895+22888 -> -2207783 | CR83: =-2535713+6356+18702 -> -2510655 | CS83: =-2685804+6356+11637 -> -2667811 | CT83: =-2537140+6977 -> -2530163 | CU83: =-2109886-709 -> -2110595 | CV83: -1991205 | CW83: =-2028619.62 -> -2028619.6 | CX83: =-1886424+25561 -> -1860863 | CY83: =-2290830.01+4008 -> -2286822 | CZ83: =-2122474.44+1035 -> -2121439.4 | DA83: -2522470.5 | DB83: =-2512434.9+11764 -> -2500670.9 | DC83: =-1928700.37-15355 -> -1944055.4 | DD83: =-2089375.83-31632 -> -2121007.8 | DE83: =-2212515.85+20709 -> -2191806.9 | DF83: =-2376378.93+29675 -> -2346703.9 | DG83: =-2612576.01+19088 -> -2593488 | DH83: =-2619510.76+12025 -> -2607485.8 | DI83: =-2442077.49+39316.5022032448 -> -2402761 | DJ83: =-2825176.26+32772 -> -2792404.3 | DK83: =-2594090.7+33673 -> -2560417.7 | DL83: =-2812599.67+34000 -> -2778599.7 | DM83: -2866024.4 | DN83: =-2942224.63+44899.09 -> -2897325.5 | DO83: =-2627735.09+26274.18 -> -2601460.9 | DP83: =-2586504.36-7292.35 -> -2593796.7 | DQ83: =-2682401.01+23325.95 -> -2659075.1 | DR83: =-2665804.01+41204 -> -2624600 | DS83: =-2800572.91+29350.8 -> -2771222.1 | DT83: =-2245986.74+2415 -> -2243571.7 | DU83: =-2686991.88+77678 -> -2609313.9 | DV83: =-2668994.5+27728+22876 -> -2618390.5 | DW83: =-2745236.06+22766 -> -2722470.1 | DX83: =-2169239.7+18284 -> -2150955.7 | DY83: -2651977.9 | DZ83: =-2917159.93+40539+149083.01176331 -> -2727537.9 | EA83: =-2618966.5+26728+149083.01176331 -> -2443155.5 | EB83: =-2907693.45+32536+149083.01176331 -> -2726074.4 | EC83: =-2355818.51+9196+149083.01176331 -> -2197539.5 | ED83: =-2695849.51+2313+149083.01176331 -> -2544453.5 | EE83: =-2780285.07-3889 -> -2784174.1 | EF83: =-3506847.99265804-2263 -> -3509111 | EG83: -2811890.9 | EH83: =-2949109.84270885-31512.6758849399 -> -2980622.5 | EI83: =-3102420.94851458-51710.9 -> -3154131.8 | EJ83: =-2591746.60757249-26506.1820300563 -> -2618252.8 | EK83: =-2884082.37336596-5723.24662998971 -> -2889805.6 | EL83: =-3179852.04843719+35539.2091236794 -> -3144312.8 | EM83: =-3694303.00818554+56531.7489671917 -> -3637771.3 | EN83: =-3546150.81824185+26569.7029448939 -> -3519581.1 | EO83: =-4406715.14319828+19576.14832496 -> -4387139 | EP83: =-3835648.11621522-580.129159906559 -> -3836228.2 | EQ83: =-4004179.52869261+34895.9921824599 -> -3969283.5 | ER83: =-4697830.0499271+25262.6779948433 -> -4672567.4 | ES83: =-3937363.82787576+14555.9015540332 -> -3922807.9 | ET83: =-4037022.33523317-21896.6145897333 -> -4058918.9 | EU83: =-4404652.36693368-29189.2927231315 -> -4433841.7 | EV83: =-4723355.92946604+4974.52859474681 -> -4718381.4 | EW83: -4381818.3 | EX83: =-3946586.84781045-54346.2234248561 -> -4000933.1 | EY83: =-4341106.46916961-83951.0033543529 -> -4425057.5 | EZ83: =-4168389.14625327-60096.3754730415+7990.00000000373 -> -4220495.5 | FA83: -4197500 | FB83: -4424737.6 | FC83: -4754249.2 | FD83: -4238577.9 | FE83: -4191248.2 | FF83: -4097355.8 | FG83: -4120073.5 | FH83: -4112169.3 | FI83: =-4205975.56224875+20950.3673085214 -> -4185025.2 | FJ83: =-3739365.02889979+10745.72 -> -3728619.3 | FK83: =-4247608.49661802+19063.7742633564 -> -4228544.7
D84: Accruals & deferred Income | G84: =U84 -> -769627 | H84: =Y84 -> -585512 | I84: =AC84 -> -1111666 | J84: =AE84 -> -1141158 | K84: =DM84 -> -2275087.5 | L84: =DY84 -> -1898219 | M84: =AS84 -> -2168705 | N84: =AW84 -> -2541112.5 | O84: =FG84 -> -2617657 | P84: =FK84 -> -2392084.2 | R84: -944000 | S84: -883000 | T84: -1017000 | U84: -769627 | V84: =BT84 -> -809726 | W84: =BW84 -> -917857 | X84: =BZ84 -> -1017121 | Y84: =CC84 -> -585512 | Z84: =CF84 -> -814312 | AA84: =CI84 -> -702166 | AB84: =CL84 -> -682772 | AC84: =CO84 -> -1111666 | AD84: =CR84 -> -881062 | AE84: =CU84 -> -1141158 | AF84: =CX84 -> -1192896.5 | AG84: =DA84 -> -1656484.6 | AH84: =DD84 -> -1066222.1 | AI84: =DG84 -> -1264429.6 | AJ84: =DJ84 -> -1462148.1 | AK84: =DM84 -> -2275087.5 | AL84: =DP84 -> -2036467.9 | AM84: =DS84 -> -1683081.3 | AN84: =DV84 -> -2190455.5 | AO84: =DY84 -> -1898219 | AP84: =EB84 -> -1854967.4 | AQ84: =EE84 -> -1908393.3 | AR84: =EH84 -> -2079841.5 | AS84: =EK84 -> -2168705 | AT84: =EN84 -> -1715996.1 | AU84: =EQ84 -> -1864052.3 | AV84: =ET84 -> -1992129.8 | AW84: =EW84 -> -2541112.5 | AX84: =EZ84 -> -2522815.2 | AY84: =FC84 -> -2832174 | AZ84: =FF84 -> -2793983.8 | BA84: =FI84 -> -3139344.6 | BB84: =FK84 -> -2392084.2 | BR84: =-762611-83630 -> -846241 | BS84: -690167 | BT84: -809726 | BU84: -821634 | BV84: -797566 | BW84: -917857 | BX84: -788685 | BY84: =-954248-20000 -> -974248 | BZ84: =-1017121 -> -1017121 | CA84: -908004 | CB84: =-841846-52742+130000 -> -764588 | CC84: -585512 | CD84: =-780420-67922-22000-45000-15000 -> -930342 | CE84: =-698045-67922-22000-45000-15000+36000+17000-11000+60000 -> -745967 | CF84: =-746390-67922 -> -814312 | CG84: =-727956-67922 -> -795878 | CH84: =-800265-67922+120000 -> -748187 | CI84: =-822166+120000 -> -702166 | CJ84: =-705807+120000 -> -585807 | CK84: =-776251+120000+40000 -> -616251 | CL84: =-802772+120000 -> -682772 | CM84: =-808277+120000 -> -688277 | CN84: -863166 | CO84: -1111666 | CP84: =-732290-174225 -> -906515 | CQ84: -819467 | CR84: -881062 | CS84: -851357 | CT84: =-728374-189836 -> -918210 | CU84: -1141158 | CV84: -905747 | CW84: -864823.48 | CX84: -1192896.5 | CY84: -1135956.1 | CZ84: =-1287200.17 -> -1287200.2 | DA84: -1656484.6 | DB84: -876016.06 | DC84: -953656.31 | DD84: -1066222.1 | DE84: -946426.32 | DF84: -1070399 | DG84: -1264429.6 | DH84: -1214406.7 | DI84: -1342257.8 | DJ84: -1462148.1 | DK84: -1806014.1 | DL84: -1777603.5 | DM84: -2275087.5 | DN84: -1502652.8 | DO84: -2093116 | DP84: -2036467.9 | DQ84: -2092550.8 | DR84: -1771451.7 | DS84: -1683081.3 | DT84: -2179425.1 | DU84: -1826386.4 | DV84: -2190455.5 | DW84: -2037631.1 | DX84: -2073144.4 | DY84: -1898219 | DZ84: -2039574.7 | EA84: -1702997.5 | EB84: -1854967.4 | EC84: -1905517.8 | ED84: -1860313.8 | EE84: -1908393.3 | EF84: -1834514.3 | EG84: -1895805.3 | EH84: -2079841.5 | EI84: -1957916.6 | EJ84: -2145598 | EK84: -2168705 | EL84: -1899068.2 | EM84: -1544740.8 | EN84: -1715996.1 | EO84: -1621898.5 | EP84: -1734618.8 | EQ84: -1864052.3 | ER84: =-1886673.51121764+43000 -> -1843673.5 | ES84: -1901546.4 | ET84: -1992129.8 | EU84: -1999845.6 | EV84: -2080150.6 | EW84: -2541112.5 | EX84: -2502493.6 | EY84: -2452114 | EZ84: -2522815.2 | FA84: -2535198.7 | FB84: =-2757318.79959342+30192 -> -2727126.8 | FC84: -2832174 | FD84: -2771481.1 | FE84: -2716800.5 | FF84: -2793983.8 | FG84: -2617657 | FH84: -2720362.5 | FI84: -3139344.6 | FJ84: -2718812.8 | FK84: -2392084.2
D85: Loans | G85: =U85 -> -2529327 | H85: =Y85 -> -3708790 | I85: =AC85 -> -1227010 | J85: =AE85 -> -1422227 | K85: =DM85 -> -235136.94 | L85: =DY85 -> -173280.85 | M85: =AS85 -> -264960.88 | N85: =AW85 -> -901124.75 | O85: =FG85 -> -1014436.8 | P85: =FK85 -> -1810104 | R85: -714000 | S85: -1391000 | T85: -1467000 | U85: -2529327 | V85: =BT85 -> -2716328 | W85: =BW85 -> -3372745 | X85: =BZ85 -> -3508262 | Y85: =CC85 -> -3708790 | Z85: =CF85 -> -3852250 | AA85: =CI85 -> -1008841 | AB85: =CL85 -> -1154683 | AC85: =CO85 -> -1227010 | AD85: =CR85 -> -1350629 | AE85: =CU85 -> -1422227 | AF85: =CX85 -> -1509615.3 | AG85: =DA85 -> -455623.72 | AH85: =DD85 -> -457240.98 | AI85: =DG85 -> -458363.96 | AJ85: =DJ85 -> -272675 | AK85: =DM85 -> -235136.94 | AL85: =DP85 -> -234758.68 | AM85: =DS85 -> -156247.14 | AN85: =DV85 -> -160398.26 | AO85: =DY85 -> -173280.85 | AP85: =EB85 -> -178991.39 | AQ85: =EE85 -> -186667.86 | AR85: =EH85 -> -194391.26 | AS85: =EK85 -> -264960.88 | AT85: =EN85 -> -267173.83 | AU85: =EQ85 -> -1284802.1 | AV85: =ET85 -> -803971.06 | AW85: =EW85 -> -901124.75 | AX85: =EZ85 -> -536725.5 | AY85: =FC85 -> -686711.92 | AZ85: =FF85 -> -886045.75 | BA85: =FI85 -> -2226037.2 | BB85: =FK85 -> -1810104 | BR85: =U85-BR134-BR110 -> -2813967 | BS85: =BR85-BS134-BS110 -> -2845935 | BT85: =BS85-BT134-BT110+165000 -> -2716328 | BU85: =BT85-BU134-BU110 -> -2750580 | BV85: =BU85-BV134-BV110 -> -2785973 | BW85: =BV85-BW134-BW110 -> -3372745 | BX85: =BW85-BX134-BX110 -> -3416420 | BY85: =BX85-BY134-BY110 -> -3462013 | BZ85: =BY85-BZ134-BZ110 -> -3508262 | CA85: =BZ85-CA134-CA110 -> -3546033 | CB85: =-3783475+165000 -> -3618475 | CC85: =-3607199-101591 -> -3708790 | CD85: =-3550704-101591 -> -3652295 | CE85: =-3705441-101591 -> -3807032 | CF85: =-3750659-101591 -> -3852250 | CG85: =-3789230-101591 -> -3890821 | CH85: =-6307750-101591+2500000+2935000 -> -974341 | CI85: =-6342250-101591+2500000+2935000 -> -1008841 | CJ85: =-6385931-101591+2500000+2935000 -> -1052522 | CK85: =-6437833-101591+2500000+2935000 -> -1104424 | CL85: =-6488092-101591+2500000+2935000 -> -1154683 | CM85: =-6484752-101591+2500000+2935000 -> -1151343 | CN85: =-3600335-101591+2500000 -> -1201926 | CO85: =-3625419-101591+2500000 -> -1227010 | CP85: =-3648933-101591+2500000 -> -1250524 | CQ85: =-3697114-101591+2500000 -> -1298705 | CR85: =-5519038-101591+2500000+270000+1500000 -> -1350629 | CS85: =-5204381-101591+4000000 -> -1305972 | CT85: =-5263461-101591+4000000 -> -1365052 | CU85: =-5320636-101591+4000000 -> -1422227 | CV85: =-5227211+3733333+100000 -> -1393878 | CW85: =-5186028.4+3733333 -> -1452695.4 | CX85: =-5242948.26+3733333 -> -1509615.3 | CY85: =-4948449.56+3466666 -> -1481783.6 | CZ85: =-5000149.29+3466666 -> -1533483.3 | DA85: =-3922289.72+3466666 -> -455623.72 | DB85: =-4771098.47+3199999+1225396 -> -345703.47 | DC85: =-3633847.81+3199999 -> -433848.81 | DD85: =-3657239.98+3199999 -> -457240.98 | DE85: =-3349058.29+2933332 -> -415726.29 | DF85: =-3370726.61+2933332 -> -437394.61 | DG85: =-3391695.96+2933332 -> -458363.96 | DH85: =-3086928.28+2666665 -> -420263.28 | DI85: =-3107356.33+2666665 -> -440691.33 | DJ85: =-2939340+2666665 -> -272675 | DK85: =-2637140.36+0.97+2399998 -> -237141.39 | DL85: =-2654183.63+0.97+2399998 -> -254184.66 | DM85: =-2635134.94+2399998 -> -235136.94 | DN85: =-2336174.66+2133331 -> -202843.66 | DO85: =-2351290.03+2133331 -> -217959.03 | DP85: =-2368089.68+2133331 -> -234758.68 | DQ85: =-2073523.36+1866664 -> -206859.36 | DR85: =-2089190.58+1866664 -> -222526.58 | DS85: =-3656247.14+3500000 -> -156247.14 | DT85: =-3670487.53+3500000 -> -170487.53 | DU85: =-7194053.27+7000000 -> -194053.27 | DV85: =-6787065.26+6626667 -> -160398.26 | DW85: =-6847953.32+6626667 -> -221286.32 | DX85: =-6906877+6626667 -> -280210 | DY85: =-6426614.85+6253334 -> -173280.85 | DZ85: =-6485234.65+6253334 -> -231900.65 | EA85: =-6538389.1+6253334 -> -285055.1 | EB85: =-6058992.39+5880001 -> -178991.39 | EC85: =-6112619.09+5880001 -> -232618.09 | ED85: =-6167995.49+5880001 -> -287994.49 | EE85: =-5693335.86+5506668 -> -186667.86 | EF85: -242044.27 | EG85: -290717.66 | EH85: -194391.26 | EI85: -243064.65 | EJ85: -182481.94 | EK85: -264960.88 | EL85: =-277763.88-32927.08 -> -310690.96 | EM85: -219167.94 | EN85: -267173.83 | EO85: -313659.68 | EP85: =-232562.83-500000 -> -732562.83 | EQ85: =-284802.1-1000000 -> -1284802.1 | ER85: =-340841.01-1000000 -> -1340841 | ES85: =-2749212.14+2500000-1000000 -> -1249212.1 | ET85: =-2803971.06+2500000-500000 -> -803971.06 | EU85: =-2882054.65+2500000-500000 -> -882054.65 | EV85: =-2813869.56+2500000-500000 -> -813869.56 | EW85: =-11451124.75+6000000+4550000 -> -901124.75 | EX85: =-11579986.73+6000000+4580000 -> -999986.73 | EY85: =-11023195.72+6000000+4580000 -> -443195.72 | EZ85: =-11116725.5+6000000+4580000 -> -536725.5 | FA85: =-11214816.87+6000000+4580000 -> -634816.87 | FB85: =-11180094.58+6000000+4580000 -> -600094.58 | FC85: =-11266711.92+6000000+4580000 -> -686711.92 | FD85: =-13056582.8+6000000+6270000 -> -786582.8 | FE85: =-13052065.34+6000000+6270000 -> -782065.34 | FF85: =-13156045.75+6000000+6270000 -> -886045.75 | FG85: =-13284436.8+6000000+6270000 -> -1014436.8 | FH85: =-13758701.75+6000000+6270000 -> -1488701.8 | FI85: =-14496037.2+6000000+6270000 -> -2226037.2 | FJ85: =-14613219.75+6000000+6270000 -> -2343219.8 | FK85: =-16780104+6000000+6270000+2700000 -> -1810104
C86: Current Liabilities | G86: =U86 -> -5135028 | H86: =Y86 -> -5839342 | I86: =AC86 -> -4304267 | J86: =AE86 -> -4673980 | K86: =DM86 -> -5376248.9 | L86: =DY86 -> -4723477.7 | M86: =AS86 -> -5323471.5 | N86: =AW86 -> -7824055.5 | O86: =FG86 -> -7752167.3 | P86: =FK86 -> -8430732.9 | R86: =SUM(R83:R85) -> -3316000 | S86: =SUM(S83:S85) -> -4218000 | T86: =SUM(T83:T85) -> -4820000 | U86: =SUM(U83:U85) -> -5135028 | V86: =SUM(V83:V85) -> -5304171 | W86: =SUM(W83:W85) -> -5990345 | X86: =SUM(X83:X85) -> -6105022 | Y86: =SUM(Y83:Y85) -> -5839342 | ... AF86: =SUM(AF83:AF85) -> -4563374.7 | AG86: =DA86 -> -4634578.9 | AH86: =DD86 -> -3644471 | AI86: =DG86 -> -4316281.6 | AJ86: =DJ86 -> -4527227.4 | AK86: =DM86 -> -5376248.9 | AL86: =DP86 -> -4865023.3 | AM86: =DS86 -> -4610550.6 | AN86: =DV86 -> -4969244.3 | AO86: =DY86 -> -4723477.7 | AP86: =EB86 -> -4760033.2 | AQ86: =EE86 -> -4879235.3 | AR86: =EH86 -> -5254855.3 | AS86: =EK86 -> -5323471.5 | AT86: =EN86 -> -5502751 | AU86: =EQ86 -> -7118137.9 | AV86: =ET86 -> -6855019.8 | AW86: =EW86 -> -7824055.5 | AX86: =EZ86 -> -7280036.2 | AY86: =FC86 -> -8273135.1 | AZ86: =FF86 -> -7777385.3 | BA86: =FI86 -> -9550407 | BB86: =FK86 -> -8430732.9 | BR86: =SUM(BR83:BR85) -> -5532534 | BS86: =SUM(BS83:BS85) -> -5256891 | BT86: =SUM(BT83:BT85) -> -5304171 | BU86: =SUM(BU83:BU85) -> -5376227 | BV86: =SUM(BV83:BV85) -> -5589258 | BW86: =SUM(BW83:BW85) -> -5990345 | BX86: =SUM(BX83:BX85) -> -6095387 | BY86: =SUM(BY83:BY85) -> -6230392 | ... FK86: =SUM(FK83:FK85) -> -8430732.9
