Workbook
Name _1_0REPLA: [2]PXMODEL!#REF!
Name _1_0REPLA: #REF!
Name _2_0pric: [3]Sheet1!#REF!
Name _2_0pric: #REF!
Name _3_0TAB: [2]PXMODEL!#REF!
Name _3_0TAB: #REF!
Name _4_0TAB: [2]PXMODEL!#REF!
Name _4_0TAB: #REF!
Name _5_0TAB: [2]PXMODEL!#REF!
Name _5_0TAB: #REF!
Name _Table1_In1: #REF!
Name _Table1_Out: #REF!
Name AllData: [5]Data!$F$5:$BS$240
Name AllData: #REF!
Name asda: #REF!
Name Asia_Pipeline_Biolight: '[7]GP - Pipeline'!$J$8:$J$127
Name Asia_Pipeline_Biolight: #REF!
Name Asia_Pipeline_Eco: '[7]GP - Pipeline'!$E$8:$E$127
Name Asia_Pipeline_Eco: #REF!
Name Asia_Pipeline_Eco_mini: '[7]GP - Pipeline'!$M$135:$M$254
Name Asia_Pipeline_Eco_mini: #REF!
Name Asia_Pipeline_Est_Ship_Quarter: '[7]GP - Pipeline'!$O$8:$O$127
Name Asia_Pipeline_Est_Ship_Quarter: #REF!
Name Asia_Pipeline_Home_System_10W: '[7]GP - Pipeline'!$L$8:$L$127
Name Asia_Pipeline_Home_System_10W: #REF!
Name Asia_Pipeline_Home_System_5w: '[7]GP - Pipeline'!$K$8:$K$127
Name Asia_Pipeline_Home_System_5w: #REF!
Name Asia_Pipeline_Mobile: '[7]GP - Pipeline'!$I$8:$I$127
Name Asia_Pipeline_Mobile: #REF!
Name Asia_Pipeline_Pro: '[7]GP - Pipeline'!$G$8:$G$127
Name Asia_Pipeline_Pro: #REF!
Name Asia_Pipeline_Pro2: '[7]GP - Pipeline'!$H$8:$H$127
Name Asia_Pipeline_Pro2: #REF!
Name Asia_Pipeline_Solo: '[7]GP - Pipeline'!$F$8:$F$127
Name Asia_Pipeline_Solo: #REF!
Name astq: #REF!
Name astq: #REF!
Name bal: #REF!
Name bal: #REF!
Name balstr: #REF!
Name balstr: #REF!
Name BLPH1: #REF!
Name BLPH2: #REF!
Name BLPH3: #REF!
Name brneng: #REF!
Name brneng: #REF!
Name brneng2: #REF!
Name brneng2: #REF!
Name brneng3: #REF!
Name brneng3: #REF!
Name brnfrn: #REF!
Name brnfrn: #REF!
Name brnspn: #REF!
Name brnspn: #REF!
Name dat: #REF!
Name dat: #REF!
Name dateng: [5]Data!#REF!
Name dateng: #REF!
Name dateng1: [5]Data!#REF!
Name dateng1: #REF!

Sheet KPI's
B2: Key Performance Indicators
D4: Q4 | E4: Q3 | F4: Q2 | G4: Q1 | H4: Q4 | I4: Q3 | J4: Q2 | K4: Q1 | L4: Q4 | M4: Q3 | N4: Q2 | O4: Q1 | P4: Q4
D5: December 2025 | E5: September 2025 | F5: June 2025 | G5: March 2025 | H5: December 2024 | I5: September 2024 | J5: June 2024 | K5: March 2024 | L5: December 2023 | M5: September 2023 | N5: June 2023 | O5: March 2023 | P5: December 2022
B6: 1. | C6: Financial Metrics
B7: 1.1 | C7: Credit Revenue | D7: =SUM('P&L -Dec25'!DP10:DR12) -> 1.8414588e+08 | E7: 1.8062808e+08 | F7: 188579765 | G7: 1.9233536e+08 | H7: 2.0778243e+08 | I7: 2.039527e+08 | J7: 1.8187705e+08 | K7: 1.6141535e+08 | L7: 1.3756157e+08 | M7: 1.1350807e+08 | N7: 95112059 | O7: 81434822 | P7: 72661909
B8: 1.2 | C8: EBITDA | D8: =SUM('P&L -Dec25'!DP193:DR193) -> 1875504.4 | E8: 667728.6 | F8: 1607086.7 | G8: -6027694.8 | H8: -2239794.4 | I8: 7230381.3 | J8: 3398808.1 | K8: 15765215 | L8: 11078509 | M8: 4787161 | N8: 7546615.8 | O8: 2877871.6 | P8: 670856.47
B9: 2. | C9: Operational Metrics
B10: 2.1 | C10: Loans Disbursed (number) | D10: =SUM('Advance Analysis - Dec25'!H129:H131) -> 4732 | E10: 4634 | F10: 4637 | G10: 4960 | H10: 6041 | I10: 5967 | J10: 5847 | K10: 5806 | L10: 4903 | M10: 4079 | N10: 3319 | O10: 2831 | P10: 2451
B11: 2.2 | C11: Loans Financed (value) | D11: =SUM('Advance Analysis - Dec25'!C129:C131) -> 7.7965187e+08 | E11: 7.1808045e+08 | F11: 682236875 | G11: 694787927 | H11: 877464420 | I11: 9.0962379e+08 | J11: 891190309 | K11: 965864749 | L11: 874151968 | M11: 7.1614809e+08 | N11: 565912078 | O11: 5.2008684e+08 | P11: 408919831
B12: 2.3 | C12: Average Loan Size Disbursed | D12: =D11/D10 -> 164761.6 | E12: 154959.1 | F12: 147128.94 | G12: 140078.21 | H12: 145251.52 | I12: 152442.4 | J12: 152418.39 | K12: 166356.31 | L12: 178289.2 | M12: 175569.52 | N12: 170506.8 | O12: 183711.35 | P12: 166837.96
B13: 2.4 | C13: Net Loan Portfolio | D13: ='Notes - Dec25'!C8 -> 1.5068569e+09 | E13: 1.5291501e+09 | F13: 1.6068918e+09 | G13: 1.6977565e+09 | H13: 1806577762 | I13: 1825326392 | J13: 1.7082092e+09 | K13: 1.588821e+09 | L13: 1.3099124e+09 | M13: 1.0865726e+09 | N13: 9.0562427e+08 | O13: 7.6787109e+08 | P13: 6.4040303e+08
B14: 2.5 | C14: Charge offs:
B15: 2.5.1 | C15: -Per Quarter | D15: ='Notes - Dec25'!C5-'Notes - Dec25'!I5 -> -80270700 | E15: -48307722 | F15: -1.1465888e+08 | G15: -24489772 | H15: -19085600 | I15: -27153340 | J15: -23730180 | K15: -26910923 | L15: -16763889 | M15: -14493891 | N15: -9124086 | O15: -12700787 | P15: -6666991
B16: 2.5.2 | C16: -YTD (December 2025) | D16: -251569961 | E16: -171299261 | F16: -120682891 | G16: -6024016 | H16: -77417697 | I16: -58332097 | J16: -31178757 | K16: -7448576.7 | L16: -42875697 | M16: -26111808 | N16: -11617917 | O16: -2493831 | P16: -19102882
B17: 2.5.3 | C17: -Since inception | D17: -4.7614752e+08 | E17: -3.9587682e+08 | F17: -3.4526045e+08 | G17: -2.3060158e+08 | H17: -206111803 | I17: -1.870262e+08 | J17: -1.5987286e+08 | K17: -1.3614268e+08 | L17: -1.0923176e+08 | M17: -92467871 | N17: -77973980 | O17: -68849894 | P17: -56149107
B18: 2.6 | C18: Average Annualized Interest Rate | D18: =AVERAGE('Advance Analysis - Dec25'!G129:G131) -> 0.40932423 | E18: 0.39655377 | F18: 0.41968004 | G18: 0.39253481 | H18: 0.4120476 | I18: 0.4253749 | J18: 0.41325824 | K18: 0.42848331 | L18: 0.44249042 | M18: 0.44428702 | N18: 0.44507762 | O18: 0.45498687 | P18: 0.46200035
B19: 2.7 | C19: Par 30 + Restructured loans | D19: ='Balance Sheet - Dec25'!C53 -> 0.078022146 | E19: 0.080367317 | F19: 0.086420848 | G19: 0.11733451 | H19: 0.09013019 | I19: 0.069128131 | J19: 0.056762139 | K19: 0.044721985 | L19: 0.042817934 | M19: 0.040916738 | N19: 0.042591592 | O19: 0.044835966 | P19: 0.050030707
B20: 2.8 | C20: Par 90 | D20: ='Covenants - Dec25'!G47/'Covenants - Dec25'!G54 -> 0.053955519 | E20: 0.053493269 | F20: 0.051156311 | G20: 0.085042421 | H20: 0.06119064 | I20: 0.038681647 | J20: 0.027314633 | K20: 0.021083442 | L20: 0.021114483 | M20: 0.022365324 | N20: 0.026563286 | O20: 0.020694972 | P20: 0.025214518
B21: 3. | C21: Impact Metrics
B22: 3.1 | C22: Total businesses funded - Unique Q3 - '25 | D22: =SUM('Advance Analysis - Dec25'!I129:I131) -> 1200 | E22: 1050 | F22: 984 | G22: 1087 | H22: 1598 | I22: 1688 | J22: 1624 | K22: 1699 | L22: 1699 | M22: 1685 | N22: 1289 | O22: 1039 | P22: 1052
B23: 3.1.1 | C23: -Total active clients | D23: ='Advance Analysis - Dec25'!K131 -> 9920 | E23: 10294 | F23: 10597 | G23: 12288 | H23: 11182 | I23: 10455 | J23: 9558 | K23: 9415 | L23: 7737 | M23: 7075 | N23: 5934 | O23: 5356 | P23: 4730
B24: 3.2 | C24: Number of SMEs - Unique to date | D24: ='Advance Analysis - Dec25'!I132 -> 24921 | E24: 23721 | F24: 22671 | G24: 21687 | H24: 20600 | I24: 19002 | J24: 17314 | K24: 15690 | L24: 13991 | M24: 12292 | N24: 10607 | O24: 9318 | P24: 8279
B25: 3.3 | C25: Fulltime employees (in Lulalend) | D25: 242 | E25: 244 | F25: 241 | G25: 236 | H25: 235 | I25: 224 | J25: 202 | K25: 177 | L25: 168 | M25: 151 | N25: 129 | O25: 119 | P25: 118
B26: 3.4 | C26: of which # of female employees | D26: 116 | E26: 118 | F26: 110 | G26: 112 | H26: 111 | I26: 107 | J26: 102 | K26: 88 | L26: 80 | M26: 75 | N26: 63 | O26: 58 | P26: 59
B27: 3.5 | C27: Countries in operation | D27: 1 | E27: 1 | F27: 1 | G27: 1 | H27: 1 | I27: 1 | J27: 1 | K27: 1 | L27: 1 | M27: 1 | N27: 1 | O27: 1 | P27: 1

Sheet P&L -Dec25
A1: Profit & Loss | T1: Profit & Loss
A2: Lula Lend (Pty) Ltd | T2: Lula Lend (Pty) Ltd
A3: For the month ended 31 December 2025 | T3: For the month ended 28 February 2019
B5: YTD - Feb 16 | C5: Dec-16 | D5: Jan-17 | E5: Feb-17 | F5: YTD - Feb 17 | G5: Mar-17 | H5: Apr-17 | I5: May-17 | J5: June-17 | K5: July-17 | L5: Aug-17 | M5: Sept-17 | N5: Oct-17 | O5: Nov-17 | P5: Dec-17 | Q5: Jan-18 | R5: Feb-18 | S5: YTD - Feb 18 | T5: Mar-18 | U5: Apr-18 | V5: May-18 | W5: Jun-18 | X5: Jul-18 | Y5: Aug-18 | Z5: Sep-18 | AA5: Oct-18 | AB5: Nov-18 | AC5: Dec-18 | AD5: Jan-19 | AE5: Feb-19 | AF5: YTD - Feb 19 | AG5: Mar-19 | AH5: Apr-19 | AI5: May-19 | AJ5: Jun-19 | AK5: Jul-19 | AL5: Aug-19 | AM5: Sep-19 | AN5: Oct-19 | AO5: Nov-19 | AP5: Dec-19 | AQ5: Jan-20 | AR5: Feb-20 | AS5: YTD - Feb 20 | AT5: YE Journals | AU5: YTD - Feb 20 | AV5: Mar-20 | AW5: Apr-20 | AX5: May-20 | AY5: Jun-20 | AZ5: Jul-20 | BA5: Aug-20 | BB5: Sep-20 | BC5: Oct-20 | BD5: Nov-20 | BE5: Dec-20 | BF5: Jan-21 | BG5: Feb-21 | BH5: YTD - Feb 21 | BI5: Mar-21 | BJ5: Apr-21 | BK5: May-21 | BL5: Jun-21 | BM5: Jul-21 | BN5: Aug-21 | BO5: Sep-21 | BP5: Oct-21 | BQ5: Nov-21 | BR5: Dec-21 | BS5: Jan-22 | BT5: Feb-22 | BU5: YTD - Feb 22 | BV5: Mar-22 | BW5: Apr-22 | BX5: May-22 | BY5: Jun-22 | BZ5: Jul-22 | CA5: Aug-22 | CB5: Sep-22 | CC5: Oct-22 | CD5: Nov-22 | CE5: Dec-22 | CF5: Jan-23 | CG5: Feb-23 | CH5: YTD - Feb 23 | CI5: Mar-23 | CJ5: Apr-23 | CK5: May-23 | CL5: Jun-23 | CM5: Jul-23 | CN5: Aug-23 | CO5: Sep-23 | CP5: Oct-23 | CQ5: Nov-23 | CR5: Dec-23 | CS5: Jan-24 | CT5: Feb-24 | CU5: YTD - Feb 24 | CV5: Mar-24 | CW5: Apr-24 | CX5: May-24 | CY5: Jun-24 | CZ5: Jul-24 | DA5: Aug-24 | DB5: Sep-24 | DC5: Oct-24 | DD5: Nov-24 | DE5: Dec-24 | DF5: Jan-25 | DG5: Feb-25 | DH5: YTD - Feb 25 | DI5: Mar-25 | DJ5: Apr-25 | DK5: May-25 | DL5: Jun-25 | DM5: Jul-25 | DN5: Aug-25 | DO5: Sep-25 | DP5: Oct-25 | DQ5: Nov-25 | DR5: Dec-25 | DS5: Jan-26 | DT5: Feb-26 | DU5: YTD - Feb 26
A7: Income
A9: Total credit revenue
A10: Fee Income | B10: 1612107.5 | C10: 376479.18 | D10: 380118.85 | E10: 366150.87 | F10: 3994702 | G10: 503039 | H10: 497939.76 | I10: 518376.5 | J10: 616800.86 | K10: 683198.24 | L10: 818281.91 | M10: 845743.59 | N10: 802652.41 | O10: 857386.41 | P10: 1024526.4 | Q10: 1009094.9 | R10: 1035779.8 | S10: 9212819.9 | T10: 1309133.1 | U10: 1150151 | V10: 1253953.7 | W10: 1420249.1 | X10: 1475498.8 | Y10: 1777647.5 | Z10: 1743165.8 | AA10: 2056626.7 | AB10: 2327350.5 | AC10: 2617279 | AD10: 2646158 | AE10: 2949013.9 | AF10: 22726227 | AG10: 3421586.8 | AH10: 3454018.5 | AI10: 3472579 | AJ10: 3574012.1 | AK10: 4132800.6 | AL10: 4371043.4 | AM10: 4309601.7 | AN10: 4926256.8 | AO10: 5542864.8 | AP10: 6758421.6 | AQ10: 6942007.6 | AR10: 6729387.7 | AS10: 57634581 | AU10: 57634581 | AV10: 7590219.6 | AW10: 6319900.3 | AX10: 5290066.5 | AY10: 5848754.2 | AZ10: 6420536.7 | BA10: 6300848.2 | BB10: 6382928.9 | BC10: 7051063.7 | BD10: 7017252.1 | BE10: 7834691.7 | BF10: 7647493.5 | BG10: 7958422.9 | BH10: 81662178 | BI10: 9539930.6 | BJ10: 10195342 | BK10: 10553393 | BL10: 9931901 | BM10: 11752286 | BN10: =12143711.46+100000 -> 12243711 | BO10: 13476587 | BP10: 14804007 | BQ10: 14687672 | BR10: 15634881 | BS10: 17092559 | BT10: 16070903 | BU10: =SUM(BI10:BT10) -> 1.5598317e+08 | BV10: 19214302 | BW10: 17427762 | BX10: 18349718 | BY10: 19078922 | BZ10: 20717685 | CA10: 20747708 | CB10: 20074617 | CC10: 23489683 | CD10: 23054635 | CE10: 26117592 | CF10: 26162566 | CG10: 26314765 | CH10: =SUM(BV10:CG10) -> 2.6074995e+08 | CI10: 28957491 | CJ10: 28813278 | CK10: 32665912 | CL10: 33632869 | CM10: 36817300 | CN10: 37636512 | CO10: 39054254 | CP10: 43228923 | CQ10: 45193130 | CR10: 49139513 | CS10: 51746873 | CT10: 73149316 | CU10: =SUM(CI10:CT10) -> 5.0003537e+08 | CV10: 56078872 | CW10: 60749393 | CX10: 60040503 | CY10: 61087157 | CZ10: 67698354 | DA10: 68072377 | DB10: 68181972 | DC10: 66088564 | DD10: 70263806 | DE10: 71430062 | DF10: 64703646 | DG10: 28937022 | DH10: =SUM(CV10:DG10) -> 7.4333173e+08 | DI10: 67585759 | DJ10: 64064942 | DK10: 64447739 | DL10: 60067084 | DM10: 60007608 | DN10: 60524917 | DO10: 60098551 | DP10: 61925143 | DQ10: 56622421 | DR10: 65156273 | DU10: =SUM(DI10:DT10) -> 6.2050044e+08
A12: Total non-credit revenue | BZ12: =SUM(BZ13:BZ16) -> 69.56 | CA12: =SUM(CA13:CA16) -> 536.52 | CB12: =SUM(CB13:CB16) -> 906.97 | CC12: =SUM(CC13:CC16) -> 434.03 | CD12: =SUM(CD13:CD16) -> 1119 | CE12: =SUM(CE13:CE16) -> 1493.15 | CF12: =SUM(CF13:CF16) -> 1885.9 | CG12: =SUM(CG13:CG16) -> 5584.8 | ... CT12: =SUM(CT13:CT16) -> 63539.56 | CU12: =SUM(CI12:CT12) -> 616118.32 | CV12: =SUM(CV13:CV16) -> 105369.42 | CW12: =SUM(CW13:CW16) -> 74645.51 | CX12: =SUM(CX13:CX16) -> 91409.26 | CY12: =SUM(CY13:CY16) -> 89509.09 | CZ12: =SUM(CZ13:CZ16) -> 94073.53 | DA12: =SUM(DA13:DA16) -> 103920.73 | DB12: =SUM(DB13:DB16) -> 105585.35 | DC12: =SUM(DC13:DC16) -> 115719.57 | ... DG12: =SUM(DG13:DG16) -> 134436.15 | DH12: =SUM(CV12:DG12) -> 1285525.5 | DI12: =SUM(DI13:DI16) -> 198582.65 | DJ12: =SUM(DJ13:DJ16) -> 172253.48 | DK12: =SUM(DK13:DK16) -> 203976.26 | DL12: =SUM(DL13:DL16) -> 213038.06 | DM12: =SUM(DM13:DM16) -> 258775.85 | DN12: =SUM(DN13:DN16) -> 255560.01 | DO12: =SUM(DO13:DO16) -> 258897.04 | DP12: =SUM(DP13:DP16) -> 292689.97 | ... DT12: =SUM(DT13:DT16) -> 0 | DU12: =SUM(DI12:DT12) -> 2003126.7
A13: Subscription Revenue | CI13: 870 | CJ13: 1739 | CK13: 869.57 | CL13: 0.01 | CM13: 1739.13 | CN13: 1304.35 | CO13: 1304.35 | CP13: 1304.35 | CQ13: 2173.91 | CR13: 3043.48 | CS13: 3913.04 | CT13: 0 | CU13: =SUM(CI13:CT13) -> 18261.19 | CV13: 3478.26 | CW13: 4347.83 | CX13: 2608.7 | CY13: 6521.74 | CZ13: 5217.39 | DA13: 5652.17 | DB13: 5652.17 | DC13: 6086.96 | DD13: 7826.09 | DE13: 6521.74 | DF13: 7826.09 | DG13: 12608.7 | DH13: =SUM(CV13:DG13) -> 74347.84 | DI13: 17826.09 | DJ13: 20869.57 | DK13: 25652.17 | DL13: 37826.09 | DM13: 40869.57 | DN13: 42608.7 | DO13: 36521.74 | DP13: 40434.78 | DQ13: 55652.17 | DR13: 0 | DU13: =SUM(DI13:DT13) -> 318260.88
A14: Transaction Revenue | BZ14: 69.56 | CA14: 536.52 | CB14: 906.97 | CC14: 434.03 | CD14: 976.52 | CE14: 1326.98 | CF14: 1641.75 | CG14: 1578.61 | CH14: =SUM(BV14:CG14) -> 7470.94 | CI14: 898.69 | CJ14: 635.96 | CK14: 4435.32 | CL14: 6836.98 | CM14: 8926.09 | CN14: 9564.27 | CO14: 8440.11 | CP14: 8305.77 | CQ14: 11852.44 | CR14: 13236.59 | CS14: 13837.77 | CT14: 15874.22 | CU14: =SUM(CI14:CT14) -> 102844.21 | CV14: 10415.3 | CW14: 8378.28 | CX14: 25040.25 | CY14: 20814.29 | CZ14: 29856 | DA14: 28522.36 | DB14: 35713.75 | DC14: 33811.72 | DD14: 35012.36 | DE14: 39839.5 | DF14: 36024.12 | DG14: 41791.63 | DH14: =SUM(CV14:DG14) -> 345219.56 | DI14: 45332.57 | DJ14: 38881.38 | DK14: 56283.99 | DL14: 52846.44 | DM14: 51880.19 | DN14: 52795.31 | DO14: 59198.46 | DP14: 71298.91 | DQ14: 40487.15 | DR14: 0 | DU14: =SUM(DI14:DT14) -> 469004.4
A15: Interchange Revenue | CV15: 9827.49 | CW15: 14353.43 | CX15: 21706.18 | CY15: 19723.26 | CZ15: 19642.17 | DA15: 22854.31 | DB15: 25922.92 | DC15: 29936.25 | DD15: 31825.98 | DE15: 27573.78 | DF15: 22524.37 | DG15: 22248.08 | DH15: =SUM(CV15:DG15) -> 268138.22 | DI15: 33126.09 | DJ15: 24511.73 | DK15: 28501.73 | DL15: 28289.25 | DM15: 40168.1 | DN15: 36418.6 | DO15: 37338.99 | DP15: 65118.13 | DQ15: 32687.22 | DR15: 0 | DU15: =SUM(DI15:DT15) -> 326159.84
A16: Earned interest | BV16: 0 | BW16: 0 | BX16: 0 | BY16: 0 | BZ16: 0 | CA16: 0 | CB16: 0 | CC16: 0 | CD16: 142.48 | CE16: 166.17 | CF16: 244.15 | CG16: 4006.19 | CH16: =SUM(BV16:CG16) -> 4558.99 | CI16: 6600.42 | CJ16: 8953.13 | CK16: 6729.73 | CL16: 36721.44 | CM16: 49757.5 | CN16: 69495.45 | CO16: 59589.89 | CP16: 60807.24 | CQ16: 53460.95 | CR16: 51489.63 | CS16: 43742.2 | CT16: 47665.34 | CU16: =SUM(CI16:CT16) -> 495012.92 | CV16: 81648.37 | CW16: 47565.97 | CX16: 42054.13 | CY16: 42449.8 | CZ16: 39357.97 | DA16: 46891.89 | DB16: 38296.51 | DC16: 45884.64 | DD16: 36635.99 | DE16: 63304.89 | DF16: 55942 | DG16: 57787.74 | DH16: =SUM(CV16:DG16) -> 597819.9 | DI16: 102297.9 | DJ16: 87990.8 | DK16: 93538.37 | DL16: 94076.28 | DM16: 125857.99 | DN16: 123737.4 | DO16: 125837.85 | DP16: 115838.15 | DQ16: 20526.79 | DR16: 0 | DU16: =SUM(DI16:DT16) -> 889701.53
A18: Total Revenue | B18: =SUM(B10) -> 1612107.5 | C18: =SUM(C10) -> 376479.18 | D18: =SUM(D10) -> 380118.85 | E18: =SUM(E10) -> 366150.87 | F18: =SUM(F10) -> 3994702 | G18: =SUM(G10) -> 503039 | H18: =SUM(H10) -> 497939.76 | I18: =SUM(I10) -> 518376.5 | ... S18: =SUM(S10) -> 9212819.9 | T18: =T10 -> 1309133.1 | U18: 1150151 | V18: =+V10 -> 1253953.7 | W18: =+W10 -> 1420249.1 | X18: =+X10 -> 1475498.8 | Y18: =SUM(Y10) -> 1777647.5 | Z18: =SUM(Z10) -> 1743165.8 | AA18: =SUM(AA10) -> 2056626.7 | AB18: =SUM(AB10) -> 2327350.5 | AC18: =SUM(AC10) -> 2617279 | AD18: =SUM(AD10) -> 2646158 | AE18: =+AE10 -> 2949013.9 | AF18: 22726227 | AG18: 3421586.8 | AH18: 3454018.5 | AI18: 3472579 | AJ18: 3574012.1 | AK18: 4132800.6 | AL18: 4371043.4 | AM18: 4309601.7 | AN18: 4926256.8 | AO18: 5542864.8 | AP18: 6758421.6 | AQ18: 6942007.6 | AR18: 6729387.7 | AS18: 57634581 | AT18: 0 | AU18: 57634581 | AV18: 7590219.6 | AW18: 6319900.3 | AX18: 5290066.5 | AY18: 5848754.2 | AZ18: 6420536.7 | BA18: 6300848.2 | BB18: 6382928.9 | BC18: 7051063.7 | BD18: 7017252.1 | BE18: 7834691.7 | BF18: 7647493.5 | BG18: 7958422.9 | BH18: 81662178 | BI18: =+BI10 -> 9539930.6 | BJ18: =+BJ10 -> 10195342 | BK18: =+BK10 -> 10553393 | BL18: =+BL10 -> 9931901 | BM18: =+BM10 -> 11752286 | BN18: =+BN10 -> 12243711 | BO18: =+BO10 -> 13476587 | BP18: =+BP10 -> 14804007 | ... BT18: =+BT10 -> 16070903 | BU18: =BU10 -> 1.5598317e+08 | BV18: =+BV10+BV14 -> 19214302 | BW18: =+BW10+BW14 -> 17427762 | BX18: =+BX10+BX14 -> 18349718 | BY18: =+BY10+BY14 -> 19078922 | BZ18: =+BZ10+BZ14 -> 20717754 | CA18: =+CA10+CA14 -> 20748245 | CB18: =+CB10+CB14 -> 20075524 | CC18: =+CC10+CC14 -> 23490117 | CD18: =+CD10+CD14+CD16 -> 23055754 | CE18: =+CE10+CE14+CE16 -> 26119085 | CF18: =+CF10+CF14+CF16 -> 26164452 | CG18: =+CG10+CG14+CG16 -> 26320350 | CH18: =+CH10+CH14+CH16 -> 2.6076198e+08 | CI18: =CI10+CI12 -> 28965860 | CJ18: =CJ10+CJ12 -> 28824606 | CK18: =CK10+CK12 -> 32677947 | CL18: =CL10+CL12 -> 33676427 | CM18: =CM10+CM12 -> 36877722 | CN18: =CN10+CN12 -> 37716876 | CO18: =CO10+CO12 -> 39123589 | CP18: =CP10+CP12 -> 43299341 | ... CT18: =CT10+CT12 -> 73212856 | CU18: =SUM(CI18:CT18) -> 5.0065149e+08 | CV18: =CV10+CV12 -> 56184241 | CW18: =CW10+CW12 -> 60824039 | CX18: =CX10+CX12 -> 60131912 | CY18: =CY10+CY12 -> 61176666 | CZ18: =CZ10+CZ12 -> 67792428 | DA18: =DA10+DA12 -> 68176297 | DB18: =DB10+DB12 -> 68287557 | DC18: =DC10+DC12 -> 66204284 | ... DG18: =DG10+DG12 -> 29071458 | DH18: =SUM(CV18:DG18) -> 7.4461725e+08 | DI18: =DI10+DI12 -> 67784341 | DJ18: =DJ10+DJ12 -> 64237195 | DK18: =DK10+DK12 -> 64651716 | DL18: =DL10+DL12 -> 60280122 | DM18: =DM10+DM12 -> 60266384 | DN18: =DN10+DN12 -> 60780477 | DO18: =DO10+DO12 -> 60357448 | DP18: =DP10+DP12 -> 62217833 | ... DT18: =DT10+DT12 -> 0 | DU18: =SUM(DI18:DT18) -> 6.2250356e+08
A20: Lula Credit - cost of service
CR21: =(CR27-CQ27)/CQ27 -> 0.20414687
A23: Net Impairment and Provision on Advances | AF23: 0 | AS23: 0 | AU23: 0 | BH23: 0 | BU23: =AX23+AY23 -> 0 | CH23: =BK23+BL23 -> 0 | CU23: =AX23+AY23 -> 0 | DH23: =AZ23+BA23 -> 0
A24: Bad Debts Recovered | M24: -13283.32 | S24: -13283.32 | X24: -2000 | AF24: -2000 | AS24: 0 | AU24: 0 | BH24: 0 | BU24: =AX24+AY24 -> 0 | CH24: =BK24+BL24 -> 0 | CU24: =AX24+AY24 -> 0 | DH24: =AZ24+BA24 -> 0
A25: Default Advance Provision | B25: =155258.33+292400 -> 447658.33 | C25: 153445.65 | D25: 109675.82 | E25: =-678893.96+805220.97 -> 126327.01 | F25: =802881.94+805219.97 -> 1608101.9 | G25: 144889.46 | H25: 148380.47 | I25: 152114.61 | J25: 170205.57 | K25: =K27 -> 164711.88 | L25: 149999.75 | M25: 133307.94 | N25: 118941.39 | O25: 157201.49 | S25: 1339752.6 | X25: 63852.33 | AF25: 63852.33 | AS25: 0 | AU25: 0 | BH25: 0 | BU25: =AX25+AY25 -> 0 | CH25: =BK25+BL25 -> 0 | CU25: =AX25+AY25 -> 0 | DH25: =AZ25+BA25 -> 0
A26: Default Advances Written Off | C26: 0 | D26: 0 | G26: 0 | H26: 0 | I26: 0 | M26: 0 | N26: 13893.08 | S26: 13893.08 | X26: 0 | AF26: 0 | AS26: 0 | AU26: 0 | BH26: 0 | BU26: =AX26+AY26 -> 0 | CH26: =BK26+BL26 -> 0 | CU26: =AX26+AY26 -> 0 | DH26: =AZ26+BA26 -> 0
A27: Total debtors cost net recoveries (write-offs & provision movement) | B27: =SUM(B25:B26) -> 447658.33 | C27: =SUM(C25:C26) -> 153445.65 | D27: =SUM(D25:D26) -> 109675.82 | E27: =SUM(E25:E26) -> 126327.01 | F27: =SUM(F25:F26) -> 1608101.9 | G27: 144889.46 | H27: 148380.47 | I27: =SUM(I25) -> 152114.61 | J27: =SUM(J25) -> 170205.57 | K27: 164711.88 | L27: =SUM(L24:L26) -> 149999.75 | M27: =SUM(M24:M26) -> 120024.62 | N27: =SUM(N24:N26) -> 132834.47 | O27: =SUM(O24:O26) -> 157201.49 | P27: 219400.02 | Q27: 183902.08 | R27: 40602.42 | S27: 1784267 | T27: 56589.38 | U27: 69493 | V27: 122213.81 | W27: 47577.37 | X27: =SUM(X24:X26) -> 61852.33 | Y27: 184180.48 | Z27: 148020.35 | AA27: 149280.6 | AB27: 340215.34 | AC27: 302147.57 | AD27: 138348.65 | AE27: 361059.64 | AF27: 1980978.5 | AG27: 179876.68 | AH27: 106580.96 | AI27: 299597.62 | AJ27: 271085.5 | AK27: 308139.93 | AL27: 358637.46 | AM27: 491334.5 | AN27: 576970.53 | AO27: 615552.06 | AP27: 778503.51 | AQ27: 640191.21 | AR27: 676046.12 | AS27: 5302516.1 | AU27: 5302516.1 | AV27: 3551871.3 | AW27: 4240585.1 | AX27: 3335482.6 | AY27: 2195810 | AZ27: 1844635.4 | BA27: 391389.83 | BB27: 558275.99 | BC27: 400813.53 | BD27: 339820.6 | BE27: 932271.93 | BF27: 1013947.4 | BG27: 1025001.2 | BH27: 19829905 | BI27: 970793.34 | BJ27: 1046312.3 | BK27: 1219502.8 | BL27: 771882.63 | BM27: 1186052.8 | BN27: 2003127.2 | BO27: 1855119.1 | BP27: 2823572.9 | BQ27: 2766723 | BR27: 2617642.3 | BS27: 3839489.1 | BT27: 4885294.1 | BU27: =SUM(BI27:BT27) -> 25985512 | BV27: 3939284 | BW27: 2858473.5 | BX27: =2231829-183003 -> 2048826 | BY27: 1913351.3 | BZ27: 3548713 | CA27: 3019990 | CB27: 2210237 | CC27: 2517442 | CD27: 2030772 | CE27: 2972999 | CF27: 5090145 | CG27: 5203966 | CH27: =SUM(BV27:CG27) -> 37354199 | CI27: 6002804 | CJ27: 5697624.1 | CK27: 5804345 | CL27: 6442861 | CM27: 7110137.7 | CN27: 8114529.9 | CO27: 7083430.4 | CP27: 6787205.2 | CQ27: 7918572.2 | CR27: 9535124 | CS27: 12233977 | CT27: 51227944 | CU27: =SUM(CI27:CT27) -> 1.3395856e+08 | CV27: =CV28-CV29 -> 20189758 | CW27: =CW28-CW29 -> 13569169 | CX27: =CX28-CX29 -> 19610517 | CY27: =CY28-CY29 -> 19232876 | CZ27: =CZ28-CZ29 -> 17071962 | DA27: =DA28-DA29 -> 17643675 | DB27: =DB28-DB29 -> 18499466 | DC27: =DC28-DC29 -> 20772870 | ... DR27: =DR28-DR29 -> 9788800.6 | DU27: =SUM(DI27:DT27) -> 1.5212118e+08
A28: Debtors Cost | CV28: 20459176 | CW28: 13838730 | CX28: 19818534 | CY28: 19729726 | CZ28: 17477902 | DA28: 18024607 | DB28: 18816372 | DC28: 21072307 | DD28: 20315855 | DE28: 24754076 | DF28: 25697777 | DG28: -11788479 | DH28: 2.3970545e+08 | DI28: 19254241 | DJ28: 20551603 | DK28: 17787253 | DL28: 17601693 | DM28: 11549100 | DN28: 17966573 | DO28: 13616641 | DP28: 13712365 | DQ28: 20330617 | DR28: 10279097 | DU28: =SUM(DI28:DT28) -> 1.6264918e+08
A29: Bad debts recovered | CV29: 269418 | CW29: 269561.19 | CX29: 208017.2 | CY29: 496849.67 | CZ29: 405939.5 | DA29: 380932.25 | DB29: 316906.18 | DC29: 299437.39 | DD29: 228692.53 | DE29: 522373.28 | DF29: 354718.38 | DG29: 241450.34 | DH29: =SUM(CV29:DG29) -> 3994295.9 | DI29: 416655.6 | DJ29: 368893.54 | DK29: 2945608.4 | DL29: 833477.86 | DM29: 1195265 | DN29: 676323.5 | DO29: 1223568.3 | DP29: 1420530.5 | DQ29: 957383.22 | DR29: 490296.77 | DU29: =SUM(DI29:DQ29) -> 10037706
A32: Net Interest Expense
A33: Interest Expense: Commission | B33: 2801.79 | C33: 487.62 | D33: 451.1 | E33: 188.64 | F33: 5862.02 | G33: 813 | H33: 548.14 | I33: 563 | J33: 536.99 | K33: 549.2 | L33: 558.86 | M33: 531.05 | N33: 572.32 | O33: 591.8 | P33: 578.68 | Q33: 522.85 | R33: 443.2 | S33: 6809.03 | T33: 503.44 | U33: 496 | V33: 531.14 | W33: 540.93 | X33: 564.16 | Y33: 613.72 | Z33: 612.71 | AA33: 308.41 | AB33: 293.82 | AC33: 304.09 | AD33: 291.87 | AE33: 271.34 | AF33: 5331.63 | AG33: 306.4 | AH33: 287.01 | AI33: 302.77 | AJ33: 304.97 | AK33: 294.35 | AL33: 0 | AM33: 0 | AN33: 0 | AO33: 0 | AP33: 0 | AQ33: 0 | AR33: 0 | AS33: 1495.5 | AU33: 1495.5 | AV33: 0 | AW33: 0 | AX33: 0 | AY33: 0 | AZ33: 0 | BA33: 0 | BB33: 0 | BC33: 0 | BD33: 0 | BE33: 0 | BF33: 0 | BG33: 0 | BH33: 0 | BI33: 0 | BJ33: 0 | BU33: =SUM(BI33:BJ33) -> 0 | CH33: =SUM(BV33:BW33) -> 0 | CU33: =SUM(BI33:BJ33) -> 0 | DH33: =SUM(BK33:BL33) -> 0
A34: Interest Expense: Local | B34: 33261.5 | C34: 16237.47 | D34: 24866.29 | E34: 22719.67 | F34: 207865.5 | G34: 10354.8 | H34: 17258.97 | I34: 17834.26 | J34: 39253.11 | K34: 45863.02 | L34: 51267.15 | M34: 44383.56 | N34: 45863.02 | O34: 45647.26 | P34: 33357.88 | Q34: 31743.15 | R34: 13320.2 | S34: 396146.38 | T34: 8917.81 | U34: 8630 | V34: 9760.28 | W34: 17054.8 | X34: 17410.96 | Y34: 21000.01 | Z34: 52191.79 | AA34: 123575.34 | AB34: 159315.07 | AC34: 144808.22 | AD34: 144808.22 | AE34: 130794.52 | AF34: 838267.02 | AG34: 144808.22 | AH34: 140136.99 | AI34: 144808.22 | AJ34: 140136.99 | AK34: 144808.22 | AL34: 144808.22 | AM34: 140136.99 | AN34: 163169.1 | AO34: 131369.86 | AP34: 484754.7 | AQ34: 464623.28 | AR34: 461049.12 | AS34: 2704609.9 | AU34: 2704609.9 | AV34: 473867.86 | AW34: 337500 | AX34: 337500 | AY34: 110000 | AZ34: 255434.76 | BA34: 262554.73 | BB34: 254966.5 | BC34: 261953.31 | BD34: 252679.38 | BE34: 237827.84 | BF34: 175286.73 | BG34: 219020.59 | BH34: 3178591.7 | BI34: 451666.67 | BJ34: 437500 | BK34: 451666.67 | BL34: 436997.73 | BM34: 408560.39 | BN34: 120178.88 | BO34: 93752.7 | BP34: 96459.77 | BQ34: 93750 | BR34: 62291.67 | BS34: 0 | BT34: 0 | BU34: =SUM(BI34:BT34) -> 2652824.5 | BV34: 0 | BW34: 0 | BX34: 0 | BY34: 0 | BZ34: 0 | CA34: 0 | CB34: 0 | CC34: 0 | CD34: 0 | CE34: 0 | CF34: 0 | CG34: 0 | CH34: =SUM(BV34:CG34) -> 0 | CU34: =SUM(BV34:CJ34) -> 0 | CV34: 0 | CW34: 0 | CX34: 0 | CY34: 0 | CZ34: 0 | DA34: 0 | DB34: 0 | DC34: 0 | DD34: 0 | DE34: 0 | DF34: 0 | DG34: 0 | DH34: =SUM(CV34:DG34) -> 0
A35: Interest Expense: Long-term Liabilities | B35: 69234.04 | C35: 14556.77 | D35: 16492.17 | E35: 9899.67 | F35: 140613.66 | G35: 24192.36 | H35: 18163.23 | I35: 20992 | J35: 19077.4 | K35: 20790 | L35: 21333.86 | M35: 20457.48 | N35: 25498.94 | O35: 38555.17 | P35: 37700.78 | Q35: 34328.25 | R35: 41187.84 | S35: 322277.62 | T35: 109513.14 | U35: 110499.62 | V35: 115143.06 | W35: 117579.94 | X35: 132329.33 | Y35: 155776.13 | Z35: 186411.91 | AA35: 210261.12 | AB35: 334550.26 | AC35: 382446.21 | AD35: 442224.42 | AE35: 417350.19 | AF35: 2714085.3 | AG35: 469330.51 | AH35: 480051.21 | AI35: 502185.19 | AJ35: 535833.42 | AK35: 491701.03 | AL35: 515974.13 | AM35: 508859.66 | AN35: 556465.99 | AO35: 1048109.1 | AP35: 1190869.6 | AQ35: 1122329.9 | AR35: 1129177.7 | AS35: 8550887.4 | AU35: 8550887.4 | AV35: 1174731 | AW35: 1379466.1 | AX35: 1401092.9 | AY35: 1300734.3 | AZ35: 1308071 | BA35: 1339362.2 | BB35: 1408960.1 | BC35: 1774910.9 | BD35: 1639704.8 | BE35: 1497413.8 | BF35: 1437461.4 | BG35: 1315215.7 | BH35: 16977124 | BI35: 1444578.9 | BJ35: 1380716.7 | BK35: 1626891.6 | BL35: 1555560.3 | BM35: 1911126.5 | BN35: 2425047.4 | BO35: 3314643.2 | BP35: 3543492.5 | BQ35: 3906075 | BR35: 3877122.2 | BS35: 4105584.6 | BT35: 4018423.1 | BU35: =SUM(BI35:BT35) -> 33109262 | BV35: 4407573.1 | BW35: 4754546.7 | BX35: 4912001.7 | BY35: 4777058.5 | BZ35: 5637130.6 | CA35: 6078993 | CB35: 5984592.7 | CC35: 5998297.2 | CD35: 6537273.5 | CE35: 6648599.7 | CF35: 6101160 | CG35: 5105732.8 | CH35: =SUM(BV35:CG35) -> 66942960 | CI35: 5437328.9 | CJ35: 5969296.3 | CK35: 6550431.8 | CL35: 5941327 | CM35: 6434798 | CN35: 6222944.8 | CO35: 7628802.6 | CP35: 8747549.9 | CQ35: 9468807.4 | CR35: 10858966 | CS35: 11738763 | CT35: 10862088 | CU35: =SUM(CI35:CT35) -> 95861104 | CV35: 11804940 | CW35: 13279291 | CX35: 14683697 | CY35: 16017514 | CZ35: 16558260 | DA35: 15942279 | DB35: 16812205 | DC35: 17315169 | DD35: 17435284 | DE35: 17893639 | DF35: 17353034 | DG35: 15969163 | DH35: =SUM(CV35:DG35) -> 1.9106448e+08 | DI35: 16392934 | DJ35: 15284635 | DK35: 15733045 | DL35: 14927615 | DM35: 15224722 | DN35: 14630437 | DO35: 13509793 | DP35: 12886454 | DQ35: 12851992 | DR35: 14193631
A36: Interest Income: Bank | B36: -0.21 | C36: -66734.66 | D36: -67807.07 | E36: -67629.78 | F36: -206566.13 | G36: -57868.88 | H36: -59862.75 | I36: -52549.35 | J36: -54359.94 | K36: -50876.73 | L36: -46900.01 | M36: -37923.45 | N36: -35071 | O36: -42528.28 | P36: -31978.41 | Q36: -24472.72 | R36: -18334.26 | S36: -512725.78 | T36: -14356.93 | U36: -18902 | V36: -16629.43 | W36: -9589.28 | X36: -11967.2 | Y36: -4584.06 | Z36: -3552.72 | AA36: -9020.22 | AB36: -8221.88 | AC36: -38725.63 | AD36: -73438.58 | AE36: -62692.65 | AF36: -271680.58 | AG36: -25670.72 | AH36: -37622.92 | AI36: -60127.97 | AJ36: -14729.5 | AK36: -66292.97 | AL36: 0 | AM36: 0 | AN36: 0 | AO36: 0 | AP36: 0 | AQ36: 0 | AR36: 0 | AS36: -204444.08 | AU36: -204444.08 | AV36: 0 | AW36: 0 | AX36: 0 | AY36: 0 | AZ36: 0 | BA36: 0 | BB36: 0 | BC36: 0 | BD36: 0 | BH36: 0 | BI36: 0 | BJ36: 0 | BU36: =SUM(BI36:BJ36) -> 0 | CH36: =SUM(BV36:BW36) -> 0 | CU36: =SUM(BI36:BJ36) -> 0 | DH36: =SUM(BK36:BL36) -> 0 | DU36: =SUM(BX36:BY36) -> 0
A37: Total Net Interest Expense | B37: =SUM(B33:B36) -> 105297.12 | C37: =SUM(C33:C36) -> -35452.8 | D37: =SUM(D33:D36) -> -25997.51 | E37: =SUM(E33:E36) -> -34821.8 | F37: =SUM(F33:F36) -> 147775.05 | G37: =SUM(G33:G36) -> -22508.72 | H37: =SUM(H33:H36) -> -23892.41 | I37: =SUM(I33:I36) -> -13160.09 | ... AE37: =SUM(AE33:AE36) -> 485723.4 | AF37: 3286003.4 | AG37: 588774.41 | AH37: 582852.29 | AI37: 587168.21 | AJ37: 661545.88 | AK37: 570510.63 | AL37: 660782.35 | AM37: 648996.65 | AN37: 719635.09 | AO37: 1179479 | AP37: 1675624.3 | AQ37: 1586953.2 | AR37: 1590226.8 | AS37: 11052549 | AT37: 0 | AU37: 11052549 | AV37: 1648598.9 | AW37: 1716966.1 | AX37: 1738592.9 | AY37: 1410734.3 | AZ37: 1563505.7 | BA37: 1601916.9 | BB37: 1663926.6 | BC37: 2036864.2 | BD37: 1892384.2 | BE37: 1735241.6 | BF37: 1612748.1 | BG37: 1534236.3 | BH37: 20155716 | BI37: =SUM(BI33:BI36) -> 1896245.5 | BJ37: =SUM(BJ33:BJ36) -> 1818216.7 | BK37: =SUM(BK33:BK36) -> 2078558.2 | BL37: =SUM(BL33:BL36) -> 1992558.1 | BM37: =SUM(BM33:BM36) -> 2319686.9 | BN37: =SUM(BN33:BN36) -> 2545226.3 | BO37: =SUM(BO33:BO36) -> 3408395.9 | BP37: =SUM(BP33:BP36) -> 3639952.3 | ... BR37: =SUM(BR33:BR36) -> 3939413.9 | BS37: =SUM(BS34:BS35) -> 4105584.6 | BT37: =SUM(BT34:BT35) -> 4018423.1 | BU37: =SUM(BI37:BT37) -> 35762086 | BV37: =SUM(BV34:BV35) -> 4407573.1 | BW37: =SUM(BW33:BW36) -> 4754546.7 | BX37: =SUM(BX33:BX36) -> 4912001.7 | BY37: =SUM(BY33:BY36) -> 4777058.5 | BZ37: =SUM(BZ33:BZ36) -> 5637130.6 | CA37: =SUM(CA33:CA36) -> 6078993 | CB37: =SUM(CB33:CB36) -> 5984592.7 | CC37: =SUM(CC33:CC36) -> 5998297.2 | CD37: =SUM(CD33:CD36) -> 6537273.5 | ... CG37: =SUM(CG33:CG36) -> 5105732.8 | CH37: =SUM(BV37:CG37) -> 66942960 | CI37: =SUM(CI33:CI36) -> 5437328.9 | CJ37: =SUM(CJ33:CJ36) -> 5969296.3 | CK37: =SUM(CK33:CK36) -> 6550431.8 | CL37: =SUM(CL33:CL36) -> 5941327 | CM37: =SUM(CM33:CM36) -> 6434798 | CN37: =SUM(CN33:CN36) -> 6222944.8 | CO37: =SUM(CO33:CO36) -> 7628802.6 | CP37: =SUM(CP33:CP36) -> 8747549.9 | ... CT37: =SUM(CT33:CT36) -> 10862088 | CU37: =SUM(CI37:CT37) -> 95861104 | CV37: =SUM(CV33:CV36) -> 11804940 | CW37: =SUM(CW33:CW36) -> 13279291 | CX37: =SUM(CX33:CX36) -> 14683697 | CY37: =SUM(CY33:CY36) -> 16017514 | CZ37: =SUM(CZ33:CZ36) -> 16558260 | DA37: =SUM(DA33:DA36) -> 15942279 | DB37: =SUM(DB33:DB36) -> 16812205 | DC37: =SUM(DC33:DC36) -> 17315169 | ... DG37: =SUM(DG33:DG36) -> 15969163 | DH37: =SUM(CV37:DG37) -> 1.9106448e+08 | DI37: =SUM(DI33:DI36) -> 16392934 | DJ37: =SUM(DJ33:DJ36) -> 15284635 | DK37: =SUM(DK33:DK36) -> 15733045 | DL37: =SUM(DL33:DL36) -> 14927615 | DM37: =SUM(DM33:DM36) -> 15224722 | DN37: =SUM(DN33:DN36) -> 14630437 | DO37: =SUM(DO33:DO36) -> 13509793 | DP37: =SUM(DP33:DP36) -> 12886454 | ... DT37: =SUM(DT33:DT36) -> 0 | DU37: =SUM(DI37:DT37) -> 1.4563526e+08
A39: Total Default and Interest Charges | B39: =(0+(0)+(B27)+(B37))-(0) -> 552955.45 | C39: =(0+(0)+(C27)+(C37))-(0) -> 117992.85 | D39: =(0+(0)+(D27)+(D37))-(0) -> 83678.31 | E39: =(0+(0)+(E27)+(E37))-(0) -> 91505.21 | F39: =(0+(0)+(F27)+(F37))-(0) -> 1755877 | G39: =G27+G37 -> 122380.74 | H39: =H27+H37 -> 124488.06 | I39: =I27+I37 -> 138954.52 | J39: =J27+J37 -> 174713.13 | K39: =K27+K37 -> 181037.37 | L39: =L27+L37 -> 176259.61 | M39: =M27+M37 -> 147473.26 | N39: =N27+N37 -> 169697.75 | ... S39: =S27+S37 -> 1996774.3 | T39: =+T27+T37 -> 161166.84 | U39: =+U37+U27 -> 170216.62 | V39: =+V37+V27 -> 231018.86 | W39: =+W37+W27 -> 173163.76 | X39: =+X37+X27 -> 200189.58 | Y39: =+Y37+Y27 -> 356986.28 | Z39: =+Z37+Z27 -> 383684.04 | AA39: =+AA37+AA27 -> 474405.25 | AB39: =+AB37+AB27 -> 826152.61 | ... AE39: =+AE37+AE27 -> 846783.04 | AF39: 5266981.9 | AG39: 768651.09 | AH39: 689433.25 | AI39: 886765.83 | AJ39: 932472.65 | AK39: 879159.51 | AL39: 1019419.8 | AM39: 1140247.3 | AN39: 1296605.6 | AO39: 1795031 | AP39: 2454127.8 | AQ39: 2227144.4 | AR39: 2266272.9 | AS39: 16355331 | AT39: 0 | AU39: 16355331 | AV39: 5200470.2 | AW39: 5957551.1 | AX39: 5074075.5 | AY39: 3606544.3 | AZ39: 3408141.1 | BA39: 1993306.8 | BB39: 2222202.6 | BC39: 2437677.7 | BD39: 2232204.8 | BE39: 2667513.6 | BF39: 2626695.5 | BG39: 2559237.5 | BH39: 39985621 | BI39: =(0+(0)+('P&L -Dec25'!BI27)+('P&L -Dec25'!BI37))-(0) -> 2867038.9 | BJ39: =(0+(0)+('P&L -Dec25'!BJ27)+('P&L -Dec25'!BJ37))-(0) -> 2864528.9 | BK39: =(0+(0)+('P&L -Dec25'!BK27)+('P&L -Dec25'!BK37))-(0) -> 3298061 | BL39: =(0+(0)+('P&L -Dec25'!BL27)+('P&L -Dec25'!BL37))-(0) -> 2764440.7 | BM39: =(0+(0)+('P&L -Dec25'!BM27)+('P&L -Dec25'!BM37))-(0) -> 3505739.7 | BN39: =(0+(0)+('P&L -Dec25'!BN27)+('P&L -Dec25'!BN37))-(0) -> 4548353.5 | BO39: =(0+(0)+('P&L -Dec25'!BO27)+('P&L -Dec25'!BO37))-(0) -> 5263515.1 | BP39: =(0+(0)+('P&L -Dec25'!BP27)+('P&L -Dec25'!BP37))-(0) -> 6463525.2 | ... BT39: =(0+(0)+('P&L -Dec25'!BT27)+('P&L -Dec25'!BT37))-(0) -> 8903717.2 | BU39: =SUM(BI39:BT39) -> 61747598 | BV39: =(0+(0)+('P&L -Dec25'!BV27)+('P&L -Dec25'!BV37))-(0) -> 8346857.1 | BW39: =(0+(0)+('P&L -Dec25'!BW27)+('P&L -Dec25'!BW37))-(0) -> 7613020.2 | BX39: =(0+(0)+('P&L -Dec25'!BX27)+('P&L -Dec25'!BX37))-(0) -> 6960827.7 | BY39: =(0+(0)+('P&L -Dec25'!BY27)+('P&L -Dec25'!BY37))-(0) -> 6690409.8 | BZ39: =(0+(0)+('P&L -Dec25'!BZ27)+('P&L -Dec25'!BZ37))-(0) -> 9185843.6 | CA39: =(0+(0)+('P&L -Dec25'!CA27)+('P&L -Dec25'!CA37))-(0) -> 9098983 | CB39: =(0+(0)+('P&L -Dec25'!CB27)+('P&L -Dec25'!CB37))-(0) -> 8194829.7 | CC39: =(0+(0)+('P&L -Dec25'!CC27)+('P&L -Dec25'!CC37))-(0) -> 8515739.2 | ... CG39: =(0+(0)+('P&L -Dec25'!CG27)+('P&L -Dec25'!CG37))-(0) -> 10309699 | CH39: =SUM(BV39:CG39) -> 1.0429716e+08 | CI39: =(0+(0)+('P&L -Dec25'!CI27)+('P&L -Dec25'!CI37))-(0) -> 11440133 | CJ39: =(0+(0)+('P&L -Dec25'!CJ27)+('P&L -Dec25'!CJ37))-(0) -> 11666920 | CK39: =(0+(0)+('P&L -Dec25'!CK27)+('P&L -Dec25'!CK37))-(0) -> 12354777 | CL39: =(0+(0)+('P&L -Dec25'!CL27)+('P&L -Dec25'!CL37))-(0) -> 12384188 | CM39: =(0+(0)+('P&L -Dec25'!CM27)+('P&L -Dec25'!CM37))-(0) -> 13544936 | CN39: =(0+(0)+('P&L -Dec25'!CN27)+('P&L -Dec25'!CN37))-(0) -> 14337475 | CO39: =(0+(0)+('P&L -Dec25'!CO27)+('P&L -Dec25'!CO37))-(0) -> 14712233 | CP39: =(0+(0)+('P&L -Dec25'!CP27)+('P&L -Dec25'!CP37))-(0) -> 15534755 | ... CT39: =(0+(0)+('P&L -Dec25'!CT27)+('P&L -Dec25'!CT37))-(0) -> 62090032 | CU39: =SUM(CI39:CT39) -> 2.2981966e+08 | CV39: =(0+(0)+('P&L -Dec25'!CV27)+('P&L -Dec25'!CV37))-(0) -> 31994698 | CW39: =(0+(0)+('P&L -Dec25'!CW27)+('P&L -Dec25'!CW37))-(0) -> 26848460 | CX39: =(0+(0)+('P&L -Dec25'!CX27)+('P&L -Dec25'!CX37))-(0) -> 34294214 | CY39: =(0+(0)+('P&L -Dec25'!CY27)+('P&L -Dec25'!CY37))-(0) -> 35250390 | CZ39: =(0+(0)+('P&L -Dec25'!CZ27)+('P&L -Dec25'!CZ37))-(0) -> 33630223 | DA39: =(0+(0)+('P&L -Dec25'!DA27)+('P&L -Dec25'!DA37))-(0) -> 33585954 | DB39: =(0+(0)+('P&L -Dec25'!DB27)+('P&L -Dec25'!DB37))-(0) -> 35311671 | DC39: =(0+(0)+('P&L -Dec25'!DC27)+('P&L -Dec25'!DC37))-(0) -> 38088039 | ... DG39: =(0+(0)+('P&L -Dec25'!DG27)+('P&L -Dec25'!DG37))-(0) -> 3939233.2 | DH39: =SUM(CV39:DG39) -> 3.9528676e+08 | DI39: =(0+(0)+('P&L -Dec25'!DI27)+('P&L -Dec25'!DI37))-(0) -> 35230520 | DJ39: =(0+(0)+('P&L -Dec25'!DJ27)+('P&L -Dec25'!DJ37))-(0) -> 35467345 | DK39: =(0+(0)+('P&L -Dec25'!DK27)+('P&L -Dec25'!DK37))-(0) -> 30574690 | DL39: =(0+(0)+('P&L -Dec25'!DL27)+('P&L -Dec25'!DL37))-(0) -> 31695830 | DM39: =(0+(0)+('P&L -Dec25'!DM27)+('P&L -Dec25'!DM37))-(0) -> 25578557 | DN39: =(0+(0)+('P&L -Dec25'!DN27)+('P&L -Dec25'!DN37))-(0) -> 31920686 | DO39: =(0+(0)+('P&L -Dec25'!DO27)+('P&L -Dec25'!DO37))-(0) -> 25902866 | DP39: =(0+(0)+('P&L -Dec25'!DP27)+('P&L -Dec25'!DP37))-(0) -> 25178288 | ... DT39: =(0+(0)+('P&L -Dec25'!DT27)+('P&L -Dec25'!DT37))-(0) -> 0 | DU39: =SUM(DI39:DT39) -> 2.9775644e+08
A41: Other Charges
A42: Fixed Charges
A43: Funding Expense (Guarantees and Upfront fees) | R43: 10636.53 | S43: 10636.53 | T43: 10636.53 | U43: 10637 | V43: 11061.66 | W43: 11061.66 | X43: 25511.43 | Y43: 26208.44 | Z43: 30041.44 | AA43: 26899.68 | AB43: 53351.59 | AC43: 71339.79 | AD43: 56890.02 | AE43: 56217.75 | AF43: 389856.99 | AG43: 51592.29 | AH43: 88968.39 | AI43: 75955.68 | AJ43: 75955.68 | AK43: 75955.68 | AL43: 75700.02 | AM43: 65682.42 | AN43: 65682.42 | AO43: 47220.26 | AP43: 29232.06 | AQ43: 29232.06 | AR43: 28158.35 | AS43: 709335.31 | AU43: 709335.31 | AV43: 14773.93 | AW43: 4166.67 | AX43: 0 | AY43: 0 | AZ43: 0 | BA43: 0 | BB43: 0 | BC43: 0 | BD43: 0 | BE43: 0 | BF43: 0 | BG43: 0 | BH43: 18940.6 | BI43: 0 | BJ43: 0 | BK43: 0 | BL43: 0 | BM43: 0 | BN43: 0 | BO43: 0 | BP43: 0 | BQ43: 0 | BR43: 0 | BS43: 0 | BT43: 0 | BU43: =SUM(BI43:BT43) -> 0 | BV43: 0 | BW43: 0 | BX43: 0 | BY43: 0 | BZ43: 0 | CA43: 0 | CB43: 0 | CC43: 0 | CD43: 0 | CE43: 0 | CF43: 0 | CG43: 0 | CH43: =SUM(BV43:CG43) -> 0 | CI43: 0 | CJ43: 0 | CK43: 0 | CL43: 0 | CM43: 0 | CU43: =SUM(CI43:CM43) -> 0 | CV43: 0 | CW43: 0 | CX43: 0 | CY43: 0 | CZ43: 0 | DA43: 0 | DH43: =SUM(CV43:DG43) -> 0 | DU43: =SUM(DI43:DT43) -> 0
A45: Variable Charges
A46: Banking Fees - Intecon | B46: 14521.93 | C46: 3349.32 | D46: 3914.58 | E46: 3738.59 | F46: 39667.44 | G46: 4559.4 | H46: 4167.48 | I46: 4300.51 | J46: 4525.51 | K46: 4572.84 | L46: 5476.67 | M46: 5403.02 | N46: 4938.56 | O46: 5313.34 | P46: 5708.39 | Q46: 6019.64 | R46: 5623.65 | S46: 60609.01 | T46: 6995.65 | U46: 6002 | V46: 6555.64 | W46: 7451.39 | X46: 8194.87 | Y46: 9416.96 | Z46: 8881.13 | AA46: 10499.42 | AB46: 11606.13 | AC46: 11391.57 | AD46: 12302.65 | AE46: 11325.33 | AF46: 110622.74 | AG46: 12790.64 | AH46: 12772.94 | AI46: 13358.09 | AJ46: 12924.15 | AK46: 14452.43 | AL46: 15127.82 | AM46: 14895.92 | AN46: 16872.31 | AO46: 19320.98 | AP46: 20954.47 | AQ46: 26370.13 | AR46: 26337.35 | AS46: 206177.23 | AU46: 206177.23 | AV46: 28539.97 | AW46: 28636.98 | AX46: 23416.82 | AY46: 22282.83 | AZ46: 24792.59 | BA46: 22289.57 | BB46: 23963.42 | BC46: 23779.28 | BD46: 23255.88 | BE46: 25201.55 | BF46: 25097.3 | BG46: 25954.68 | BH46: 297210.87 | BI46: 29863.6 | BJ46: 30384.88 | BK46: 29154.07 | BL46: 27181.59 | BM46: 28045.25 | BN46: 26100.11 | BO46: 24973.74 | BP46: 25153.79 | BQ46: 25490 | BR46: 24145.75 | BS46: 27287.95 | BT46: 25303.18 | BU46: =SUM(BI46:BT46) -> 323083.91 | BV46: 31942.99 | BW46: 30280.97 | BX46: 34147.74 | BY46: 30460.64 | BZ46: 31859.34 | CA46: 32657.71 | CB46: 31933.28 | CC46: 35526.96 | CD46: 34553.33 | CE46: 36690.24 | CF46: 38769.96 | CG46: 38284.36 | CH46: =SUM(BV46:CG46) -> 407107.52 | CI46: 45197.4 | CJ46: 37845.61 | CK46: 47393.24 | CL46: 46114.98 | CM46: 50670.63 | CN46: 52107.47 | CO46: 53700.78 | CP46: 57486.13 | CQ46: 60998.35 | CR46: 63746.13 | CS46: 69859.86 | CT46: 67696.03 | CU46: =SUM(CI46:CT46) -> 652816.61 | CV46: 72244.44 | CW46: 78358.16 | CX46: 79411.37 | CY46: 76097.08 | CZ46: 90119.35 | DA46: 85777.32 | DB46: 80718.43 | DC46: 84468.39 | DD46: 81543.44 | DE46: 82691.7 | DF46: 63218.13 | DG46: 72100.73 | DH46: =SUM(CV46:DG46) -> 946748.54 | DI46: 84496.12 | DJ46: 72179.04 | DK46: 76323.94 | DL46: 72952.62 | DM46: 72008.11 | DN46: 68996.94 | DO46: 71683.15 | DP46: 73518.15 | DQ46: 66822.99 | DR46: 71410.7 | DU46: =SUM(DI46:DT46) -> 730391.76
A47: Credit Assessments | B47: 33247.76 | C47: 8858.85 | D47: 8797.97 | E47: 11336.77 | F47: 88834.65 | G47: 13652.37 | H47: 14198.74 | I47: 14191.95 | J47: 13049.43 | K47: 16822.13 | L47: 15774.48 | M47: 15920.96 | N47: 15562.09 | O47: 11293.78 | P47: 17805.76 | Q47: 9253.02 | R47: 17607.92 | S47: 175132.63 | T47: 16420.39 | U47: 16034 | V47: 15379.57 | W47: 21118.58 | X47: 17409.52 | Y47: 17335.86 | Z47: 23479.45 | AA47: 28814.51 | AB47: 25646.65 | AC47: 28054.09 | AD47: 24224.83 | AE47: 33968.18 | AF47: 267885.63 | AG47: 36535.12 | AH47: 40625.14 | AI47: 33401.3 | AJ47: 49482.39 | AK47: 54962.47 | AL47: 58084.68 | AM47: 70186.26 | AN47: 67884.04 | AO47: 88337.76 | AP47: 95085.19 | AQ47: 57712.94 | AR47: 127575.35 | AS47: 779872.64 | AU47: 779872.64 | AV47: 82296.79 | AW47: 59486.39 | AX47: 78059.78 | AY47: 59638.99 | AZ47: 49160.37 | BA47: 72481.12 | BB47: 77029.13 | BC47: 74453.13 | BD47: 83643.98 | BE47: 66900.33 | BF47: 60243.65 | BG47: 105679.47 | BH47: 869073.13 | BI47: 104315.96 | BJ47: 91766.69 | BK47: 89473.75 | BL47: 91898.13 | BM47: 77716.64 | BN47: 79325 | BO47: 80477.07 | BP47: 103477.97 | BQ47: 108437 | BR47: 133209.6 | BS47: 78955.53 | BT47: 105952.34 | BU47: =SUM(BI47:BT47) -> 1145005.7 | BV47: 102472.6 | BW47: 86095.31 | BX47: 105390.54 | BY47: 123689.7 | BZ47: 127955.3 | CA47: 119073.68 | CB47: 113575.9 | CC47: 105106.25 | CD47: 130476.58 | CE47: 121391.75 | CF47: 93672.61 | CG47: 105454.78 | CH47: =SUM(BV47:CG47) -> 1334355 | CI47: 110987.76 | CJ47: 105671.88 | CK47: 124632.75 | CL47: 143502.27 | CM47: 149627.66 | CN47: 170372.67 | CO47: 160822.05 | CP47: 168322.17 | CQ47: 166620.82 | CR47: 175877.51 | CS47: 140780.49 | CT47: 188378.22 | CU47: =SUM(CI47:CT47) -> 1805596.2 | CV47: 191028.52 | CW47: 164721.23 | CX47: 161033.93 | CY47: 196534.11 | CZ47: 215087.78 | DA47: 190730.21 | DB47: 214247.43 | DC47: 256941.01 | DD47: 241643.68 | DE47: 186666.51 | DF47: 255147.99 | DG47: 227639.59 | DH47: =SUM(CV47:DG47) -> 2501422 | DI47: 171754.87 | DJ47: 189388.8 | DK47: 154980.47 | DL47: 216849.44 | DM47: 178478.72 | DN47: 178012.24 | DO47: 177831.27 | DP47: 175679.69 | DQ47: 230587.81 | DR47: 183259.17 | DU47: =SUM(DI47:DT47) -> 1856822.5
A48: Total Other Charges | B48: =SUM(B46:B47) -> 47769.69 | C48: =SUM(C46:C47) -> 12208.17 | D48: =SUM(D46:D47) -> 12712.55 | E48: =SUM(E46:E47) -> 15075.36 | F48: =SUM(F46:F47) -> 128502.09 | G48: =SUM(G41:G47) -> 18211.77 | H48: =SUM(H41:H47) -> 18366.22 | I48: =SUM(I41:I47) -> 18492.46 | J48: =SUM(J41:J47) -> 17574.94 | K48: =SUM(K41:K47) -> 21394.97 | L48: =SUM(L41:L47) -> 21251.15 | M48: =SUM(M41:M47) -> 21323.98 | N48: =SUM(N41:N47) -> 20500.65 | ... R48: =SUM(R41:R47) -> 33868.1 | S48: =SUM(S43:S47) -> 246378.17 | T48: =SUM(T46:T47) -> 23416.04 | U48: 22035 | V48: =SUM(V46:V47) -> 21935.21 | W48: =SUM(W46:W47) -> 28569.97 | X48: =SUM(X46:X47) -> 25604.39 | Y48: =SUM(Y46:Y47) -> 26752.82 | Z48: =SUM(Z46:Z47) -> 32360.58 | AA48: =SUM(AA46:AA47) -> 39313.93 | AB48: =SUM(AB46:AB47) -> 37252.78 | AC48: =SUM(AC46:AC47) -> 39445.66 | ... AE48: =SUM(AE46:AE47) -> 45293.51 | AF48: 378507.37 | AG48: 49325.76 | AH48: 53398.08 | AI48: 46759.39 | AJ48: 62406.54 | AK48: 69414.9 | AL48: 73212.5 | AM48: 85082.18 | AN48: 84756.35 | AO48: 107658.74 | AP48: 116039.66 | AQ48: 84083.07 | AR48: 153912.7 | AS48: 986049.87 | AT48: 0 | AU48: 986049.87 | AV48: 110836.76 | AW48: 88123.37 | AX48: 101476.6 | AY48: 81921.82 | AZ48: 73952.96 | BA48: 94770.69 | BB48: 100992.55 | BC48: 98232.41 | BD48: 106899.86 | BE48: 92101.88 | BF48: 85340.95 | BG48: 131634.15 | BH48: 1166284 | BI48: =SUM('P&L -Dec25'!BI46:BI47) -> 134179.56 | BJ48: =SUM('P&L -Dec25'!BJ46:BJ47) -> 122151.57 | BK48: =SUM('P&L -Dec25'!BK46:BK47) -> 118627.82 | BL48: =SUM('P&L -Dec25'!BL46:BL47) -> 119079.72 | BM48: =SUM('P&L -Dec25'!BM46:BM47) -> 105761.89 | BN48: =SUM('P&L -Dec25'!BN46:BN47) -> 105425.11 | BO48: =SUM('P&L -Dec25'!BO46:BO47) -> 105450.81 | BP48: =SUM('P&L -Dec25'!BP46:BP47) -> 128631.76 | ... BR48: =SUM('P&L -Dec25'!BR46:BR47) -> 157355.35 | BS48: =SUM(BS46:BS47) -> 106243.48 | BT48: =SUM(BT46:BT47) -> 131255.52 | BU48: =SUM(BI48:BT48) -> 1468089.6 | BV48: =SUM(BV46:BV47) -> 134415.59 | BW48: =SUM('P&L -Dec25'!BW46:BW47) -> 116376.28 | BX48: =SUM('P&L -Dec25'!BX46:BX47) -> 139538.28 | BY48: =SUM('P&L -Dec25'!BY46:BY47) -> 154150.34 | BZ48: =SUM('P&L -Dec25'!BZ46:BZ47) -> 159814.64 | CA48: =SUM('P&L -Dec25'!CA46:CA47) -> 151731.39 | CB48: =SUM('P&L -Dec25'!CB46:CB47) -> 145509.18 | CC48: =SUM('P&L -Dec25'!CC46:CC47) -> 140633.21 | CD48: =SUM('P&L -Dec25'!CD46:CD47) -> 165029.91 | ... CG48: =SUM('P&L -Dec25'!CG46:CG47) -> 143739.14 | CH48: =SUM(BV48:CG48) -> 1741462.5 | CI48: =SUM('P&L -Dec25'!CI46:CI47) -> 156185.16 | CJ48: =SUM('P&L -Dec25'!CJ46:CJ47) -> 143517.49 | CK48: =SUM('P&L -Dec25'!CK46:CK47) -> 172025.99 | CL48: =SUM('P&L -Dec25'!CL46:CL47) -> 189617.25 | CM48: =SUM('P&L -Dec25'!CM46:CM47) -> 200298.29 | CN48: =SUM('P&L -Dec25'!CN46:CN47) -> 222480.14 | CO48: =SUM('P&L -Dec25'!CO46:CO47) -> 214522.83 | CP48: =SUM('P&L -Dec25'!CP46:CP47) -> 225808.3 | ... CT48: =SUM('P&L -Dec25'!CT46:CT47) -> 256074.25 | CU48: =SUM(CI48:CT48) -> 2458412.9 | CV48: =SUM('P&L -Dec25'!CV46:CV47) -> 263272.96 | CW48: =SUM('P&L -Dec25'!CW46:CW47) -> 243079.39 | CX48: =SUM('P&L -Dec25'!CX46:CX47) -> 240445.3 | CY48: =SUM('P&L -Dec25'!CY46:CY47) -> 272631.19 | CZ48: =SUM('P&L -Dec25'!CZ46:CZ47) -> 305207.13 | DA48: =SUM('P&L -Dec25'!DA46:DA47) -> 276507.53 | DB48: =SUM('P&L -Dec25'!DB46:DB47) -> 294965.86 | DC48: =SUM('P&L -Dec25'!DC46:DC47) -> 341409.4 | ... DG48: =SUM('P&L -Dec25'!DG46:DG47) -> 299740.32 | DH48: =SUM(CV48:DG48) -> 3448170.5 | DI48: =SUM('P&L -Dec25'!DI46:DI47) -> 256250.99 | DJ48: =SUM('P&L -Dec25'!DJ46:DJ47) -> 261567.84 | DK48: =SUM('P&L -Dec25'!DK46:DK47) -> 231304.41 | DL48: =SUM('P&L -Dec25'!DL46:DL47) -> 289802.06 | DM48: =SUM('P&L -Dec25'!DM46:DM47) -> 250486.83 | DN48: =SUM('P&L -Dec25'!DN46:DN47) -> 247009.18 | DO48: =SUM('P&L -Dec25'!DO46:DO47) -> 249514.42 | DP48: =SUM('P&L -Dec25'!DP46:DP47) -> 249197.84 | ... DT48: =SUM('P&L -Dec25'!DT46:DT47) -> 0 | DU48: =SUM(DI48:DT48) -> 2587214.2
A50: Lula Banking - cost of service
A52: Banking (Connect)
A53: Courier and fees | CA53: 5000 | CB53: 1071.21 | CC53: 243.6 | CD53: 243.6 | CE53: 243.6 | CF53: 243.6 | CG53: 487.21 | CH53: =SUM(BV53:CG53) -> 7532.82 | CI53: 81.2 | CJ53: 243.6 | CK53: 1218.02 | CL53: 3106.84 | CM53: 20395.01 | CN53: 9112.57 | CO53: 6471.35 | CP53: 10569.32 | CQ53: 23300.05 | CR53: 15475.36 | CS53: 9053.75 | CT53: 23889.54 | CU53: =SUM(CI53:CT53) -> 122916.61 | CV53: 30024.92 | CW53: 24645.33 | CX53: 47188.52 | CY53: 42244.81 | CZ53: 38000.19 | DA53: 32611.73 | DB53: 37657.77 | DC53: 44648.62 | DD53: 43415.74 | DE53: 13292.97 | DF53: 29549.32 | DG53: 28116.21 | DH53: =SUM(CV53:DG53) -> 411396.13 | DI53: 22775.18 | DJ53: 76723.57 | DK53: 25762.51 | DL53: 23449.2 | DM53: 24724.32 | DN53: 22529.89 | DO53: 8284.14 | DP53: 53923.21 | DQ53: 13563.22 | DR53: 0 | DU53: =SUM(DI53:DT53) -> 271735.24
A54: Interest expense (Connect) | CV54: 9886.31 | CW54: 10415.43 | CX54: 6299.47 | CY54: 9168.64 | CZ54: 9168.64 | DA54: 8434.48 | DB54: 7170.78 | DC54: 9581.11 | DD54: 8381.53 | DE54: 12070.17 | DF54: 11820.44 | DG54: 12114.15 | DH54: =SUM(CV54:DG54) -> 114511.15 | DI54: 21296.19 | DJ54: 17437.4 | DK54: 19517.32 | DL54: 21567.18 | DM54: 26096.79 | DN54: 25776.57 | DO54: 25484.47 | DP54: 27472.27 | DQ54: 0 | DR54: 0 | DU54: =SUM(DI54:DT54) -> 184648.19
A55: Transaction costs (Connect) | BV55: 0 | BW55: 0 | BX55: 0 | BY55: 0 | BZ55: 0 | CA55: 179.21 | CB55: 132.1 | CC55: 361.05 | CD55: 236.13 | CE55: 260.3 | CF55: 785.47 | CG55: 807.77 | CH55: =SUM(BV55:CG55) -> 2762.03 | CI55: 776.38 | CJ55: 841.33 | CK55: 2845.54 | CL55: 4908.35 | CM55: 6022.33 | CN55: 6913.94 | CO55: 7102.94 | CP55: 5824.24 | CQ55: 8761.73 | CR55: 11327.86 | CS55: 12126.89 | CT55: 12801.3 | CU55: =SUM(CI55:CT55) -> 80252.83 | CV55: 16028.44 | CW55: 16496.26 | CX55: 25749.29 | CY55: 26132.89 | CZ55: 30455.85 | DA55: 35006.84 | DB55: 34878.9 | DC55: 39204.74 | DD55: 42244.78 | DE55: 45681 | DF55: 25058.7 | DG55: 50004.89 | DH55: =SUM(CV55:DG55) -> 386942.58 | DI55: 55887.84 | DJ55: 53990.17 | DK55: 53962.8 | DL55: 61529.07 | DM55: 71508.09 | DN55: 142926.92 | DO55: 34264.86 | DP55: 78307.64 | DQ55: 11837.47 | DR55: 0 | DU55: =SUM(DI55:DT55) -> 564214.86
A56: Total - Banking (Connect) | T56: =SUM(T53:T55) -> 0 | U56: =SUM(U53:U55) -> 0 | V56: =SUM(V53:V55) -> 0 | W56: =SUM(W53:W55) -> 0 | X56: =SUM(X53:X55) -> 0 | Y56: =SUM(Y53:Y55) -> 0 | Z56: =SUM(Z53:Z55) -> 0 | AA56: =SUM(AA53:AA55) -> 0 | ... DG56: =SUM(DG53:DG55) -> 90235.25 | DH56: =SUM(DH51:DH55) -> 912849.86 | DI56: =SUM(DI53:DI55) -> 99959.21 | DJ56: =SUM(DJ53:DJ55) -> 148151.14 | DK56: =SUM(DK53:DK55) -> 99242.63 | DL56: =SUM(DL53:DL55) -> 106545.45 | DM56: =SUM(DM53:DM55) -> 122329.2 | DN56: =SUM(DN53:DN55) -> 191233.38 | DO56: =SUM(DO53:DO55) -> 68033.47 | DP56: =SUM(DP53:DP55) -> 159703.12 | ... DT56: =SUM(DT53:DT55) -> 0 | DU56: =SUM(DU51:DU55) -> 1020598.3
A58: Total Cost of Sales | B58: =(0+(0)+(B48)+(B39))-(0) -> 600725.14 | C58: =(0+(0)+(C48)+(C39))-(0) -> 130201.02 | D58: =(0+(0)+(D48)+(D39))-(0) -> 96390.86 | E58: =(0+(0)+(E48)+(E39))-(0) -> 106580.57 | F58: =(0+(0)+(F48)+(F39))-(0) -> 1884379.1 | G58: =(0+(0)+(G48)+(G39))-(0) -> 140592.51 | H58: =(0+(0)+(H48)+(H39))-(0) -> 142854.28 | I58: =(0+(0)+(I48)+(I39))-(0) -> 157446.98 | ... S58: =(0+(0)+(S48)+(S39))-(0) -> 2243152.4 | T58: =+T39+T43+T48+T56 -> 195219.41 | U58: =+U39+U43+U48+U56 -> 202888.62 | V58: =+V39+V43+V48+V56 -> 264015.73 | W58: =+W39+W43+W48+W56 -> 212795.39 | X58: =+X39+X43+X48+X56 -> 251305.4 | Y58: =+Y39+Y43+Y48+Y56 -> 409947.54 | Z58: =+Z39+Z43+Z48+Z56 -> 446086.06 | AA58: =+AA39+AA43+AA48+AA56 -> 540618.86 | ... DG58: =+DG39+DG43+DG48+DG56 -> 4329208.8 | DH58: =SUM(CV58:DG58) -> 3.9964778e+08 | DI58: =+DI39+DI43+DI48+DI56 -> 35586730 | DJ58: =+DJ39+DJ43+DJ48+DJ56 -> 35877064 | DK58: =+DK39+DK43+DK48+DK56 -> 30905237 | DL58: =+DL39+DL43+DL48+DL56 -> 32092178 | DM58: =+DM39+DM43+DM48+DM56 -> 25951373 | DN58: =+DN39+DN43+DN48+DN56 -> 32358929 | DO58: =+DO39+DO43+DO48+DO56 -> 26220414 | DP58: =+DP39+DP43+DP48+DP56 -> 25587189 | ... DT58: =+DT39+DT43+DT48+DT56 -> 0 | DU58: =SUM(DI58:DT58) -> 3.0136425e+08
A60: Gross Profit | B60: =(B18)-(B58) -> 1011382.4 | C60: =(C18)-(C58) -> 246278.16 | D60: =(D18)-(D58) -> 283727.99 | E60: =(E18)-(E58) -> 259570.3 | F60: =(F18)-(F58) -> 2110323 | G60: =(G10)-(G58) -> 362446.49 | H60: =(H10)-(H58) -> 355085.48 | I60: =(I10)-(I58) -> 360929.52 | J60: =(J10)-(J58) -> 424512.79 | K60: =(K10)-(K58) -> 480765.9 | L60: =(L10)-(L58) -> 620771.15 | M60: =(M10)-(M58) -> 676946.35 | N60: =(N10)-(N58) -> 612454.01 | ... T60: =(T10)-(T58) -> 1113913.7 | U60: =+U18-U58 -> 947262.38 | V60: =+V18-V58 -> 989937.98 | W60: =+W18-W58 -> 1207453.7 | X60: =+X18-X58 -> 1224193.4 | Y60: =+Y18-Y58 -> 1367699.9 | Z60: =+Z18-Z58 -> 1297079.8 | AA60: =+AA18-AA58 -> 1516007.8 | AB60: =+AB18-AB58 -> 1410593.5 | ... AE60: =+AE18-AE58 -> 2000719.6 | AF60: 16690881 | AG60: 2552017.7 | AH60: 2622218.8 | AI60: 2463098.1 | AJ60: 2503177.2 | AK60: 3108270.5 | AL60: 3202711 | AM60: 3018589.8 | AN60: 3479212.4 | AO60: 3592954.7 | AP60: 4159022 | AQ60: 4601548.1 | AR60: 4281043.7 | AS60: 39583864 | AT60: 0 | AU60: 39583864 | AV60: 2264138.7 | AW60: 270059.15 | AX60: 114514.44 | AY60: 2160288.1 | AZ60: 2938442.7 | BA60: 4212770.7 | BB60: 4059733.8 | BC60: 4515153.6 | BD60: 4678147.5 | BE60: 5075076.2 | BF60: 4935457 | BG60: 5267551.2 | BH60: 40491333 | BI60: =+BI18-BI58 -> 6538712.2 | BJ60: =+BJ18-BJ58 -> 7208661.4 | BK60: =+BK18-BK58 -> 7136704 | BL60: =+BL18-BL58 -> 7048380.6 | BM60: =+BM18-BM58 -> 8140784.1 | BN60: =+BN18-BN58 -> 7589932.9 | BO60: =+BO18-BO58 -> 8107621.5 | BP60: =+BP18-BP58 -> 8211850 | ... BT60: =+BT18-BT58 -> 7035930.2 | BU60: =SUM(BI60:BT60) -> 92767485 | BV60: =+BV18-BV58 -> 10733029 | BW60: =+BW18-BW58 -> 9698365.2 | BX60: =+BX18-BX58 -> 11249353 | BY60: =+BY18-BY58 -> 12234362 | BZ60: =+BZ18-BZ58 -> 11372096 | CA60: =+CA18-CA58 -> 11492351 | CB60: =+CB18-CB58 -> 11733982 | CC60: =+CC18-CC58 -> 14833140 | ... CG60: =+CG18-CG58 -> 15865617 | CH60: =SUM(BV60:CG60) -> 1.5471307e+08 | CI60: =+CI18-CI58 -> 17368685 | CJ60: =+CJ18-CJ58 -> 17013083 | CK60: =+CK18-CK58 -> 20147080 | CL60: =+CL18-CL58 -> 21094607 | CM60: =+CM18-CM58 -> 23106071 | CN60: =+CN18-CN58 -> 23140895 | CO60: =+CO18-CO58 -> 24183258 | CP60: =+CP18-CP58 -> 27522384 | ... CT60: =+CT18-CT58 -> 10830058 | CU60: =SUM(CI60:CT60) -> 2.6817025e+08 | CV60: =+CV18-CV58 -> 23870331 | CW60: =+CW18-CW58 -> 33680943 | CX60: =+CX18-CX58 -> 25518016 | CY60: =+CY18-CY58 -> 25576098 | CZ60: =+CZ18-CZ58 -> 33779373 | DA60: =+DA18-DA58 -> 34237783 | DB60: =+DB18-DB58 -> 32601212 | DC60: =+DC18-DC58 -> 27681401 | ... DG60: =+DG18-DG58 -> 24742249 | DH60: =SUM(CV60:DG60) -> 3.4496947e+08 | DI60: =+DI18-DI58 -> 32197611 | DJ60: =+DJ18-DJ58 -> 28360131 | DK60: =+DK18-DK58 -> 33746479 | DL60: =+DL18-DL58 -> 28187945 | DM60: =+DM18-DM58 -> 34315011 | DN60: =+DN18-DN58 -> 28421548 | DO60: =+DO18-DO58 -> 34137034 | DP60: =+DP18-DP58 -> 36630643 | ... DT60: =+DT18-DT58 -> 0 | DU60: =SUM(DI60:DT60) -> 3.2113931e+08
A62: Plus Other Income
A63: Insurance Income | BB63: 3092.59 | BH63: 3092.59 | BI63: 0 | BJ63: 0 | BK63: 0 | BL63: 0 | BM63: 0 | BN63: 0 | BO63: 0 | BP63: 0 | BQ63: 0 | BR63: 0 | BS63: 0 | BT63: 0 | BU63: =SUM(BI63:BT63) -> 0 | BV63: 0 | BW63: 0 | BX63: 0 | BY63: 0 | BZ63: 0 | CA63: 0 | CB63: 0 | CC63: 0 | CD63: 0 | CE63: 0 | CF63: 0 | CG63: 0 | CH63: =SUM(BV63:CG63) -> 0 | CI63: 0 | CJ63: 0 | CU63: =SUM(CI63:CM63) -> 0
A64: Share in JV Profits | BG64: 220421.47 | BH64: 220421.47 | BI64: 0 | BJ64: 0 | BK64: 0 | BL64: 0 | BM64: 0 | BN64: 0 | BO64: 0 | BP64: 0 | BQ64: 0 | BR64: 0 | BS64: 0 | BT64: 0 | BU64: =SUM(BI64:BT64) -> 0 | BV64: 0 | BW64: 0 | BX64: 0 | BY64: 0 | BZ64: 0 | CA64: 0 | CB64: 0 | CC64: 0 | CD64: 0 | CE64: 0 | CF64: 0 | CG64: 0 | CH64: =SUM(BV64:CG64) -> 0 | CI64: 0 | CJ64: 0 | CU64: =SUM(CI64:CM64) -> 0
A65: Interest Income: JV Loan | BG65: 27192.5 | BH65: 27192.5 | BI65: 0 | BJ65: 0 | BK65: 0 | BL65: 0 | BM65: 0 | BN65: 0 | BO65: 0 | BP65: 0 | BQ65: 0 | BR65: 0 | BS65: 0 | BT65: 0 | BU65: =SUM(BI65:BT65) -> 0 | BV65: 0 | BW65: 0 | BX65: 0 | BY65: 0 | BZ65: 0 | CA65: 0 | CB65: 0 | CC65: 0 | CD65: 0 | CE65: 0 | CF65: 0 | CG65: 0 | CH65: =SUM(BV65:CG65) -> 0 | CI65: 0 | CJ65: 0 | CU65: =SUM(CI65:CM65) -> 0
A66: Interest Income: Investment Account | AG66: 0 | AH66: 0 | AI66: 0 | AJ66: 0 | AK66: 0 | AL66: 366054.34 | AM66: 349664.73 | AN66: 335807.95 | AO66: 503350.94 | AP66: 522627.23 | AQ66: 646512.57 | AR66: 525437.39 | AS66: 3249455.1 | AU66: 3249455.1 | AV66: 428140.5 | AW66: 346943.12 | AX66: 337169.84 | AY66: 304353.52 | AZ66: 295907.39 | BA66: 301273.04 | BB66: 325995.24 | BC66: 400806.23 | BD66: 324242.12 | BE66: 211414.44 | BF66: 193349.54 | BG66: 162611.59 | BH66: 3632206.6 | BI66: 197723.95 | BJ66: 122606.01 | BK66: 151281.61 | BL66: 59702.31 | BM66: 141189.82 | BN66: 262460.59 | BO66: 203035.57 | BP66: 190880.78 | BQ66: 274579 | BR66: 203952.8 | BS66: 300711.73 | BT66: 340304.45 | BU66: =SUM(BI66:BT66) -> 2448428.6 | BV66: 358208.74 | BW66: 453012.33 | BX66: 426403.56 | BY66: 311535.52 | BZ66: 482017.18 | CA66: 643767.99 | CB66: 493358.04 | CC66: 295501.93 | CD66: 555352.16 | CE66: 306816.15 | CF66: 881938.33 | CG66: 1744622.6 | CH66: =SUM(BV66:CG66) -> 6952534.5 | CI66: 1919606.5 | CJ66: 1803996.6 | CK66: 1612086.9 | CL66: 1388331.1 | CM66: 1147802.3 | CN66: 672737.47 | CO66: 957340.61 | CP66: 857246.35 | CQ66: 1030392.3 | CR66: 787960.52 | CS66: 1293692.7 | CT66: 383084.42 | CU66: =SUM(CI66:CT66) -> 13854278 | CV66: 417405.25 | CW66: 469177.75 | CX66: 863944.56 | CY66: 1181731.3 | CZ66: 733164.02 | DA66: 421927.2 | DB66: 925734.21 | DC66: 633895.42 | DD66: 883480.7 | DE66: 714055.11 | DF66: 1065794.3 | DG66: 857879.43 | DH66: =SUM(CV66:DG66) -> 9168189.3 | DI66: 309278.45 | DJ66: 880186.89 | DK66: 1567763.3 | DL66: 1459184.4 | DM66: 1340163.2 | DN66: 1197835.4 | DO66: 676064.03 | DP66: 534191.2 | DQ66: 676901.15 | DR66: 777831.26 | DU66: =SUM(DI66:DT66) -> 9419399.2
A67: Total Other Income | AG67: 0 | AH67: 0 | AI67: 0 | AJ67: 0 | AK67: 0 | AL67: 366054.34 | AM67: 349664.73 | AN67: 335807.95 | AO67: 503350.94 | AP67: 522627.23 | AQ67: 646512.57 | AR67: 525437.39 | AS67: 3249455.1 | AT67: 0 | AU67: 3249455.1 | AV67: 428140.5 | AW67: 346943.12 | AX67: 337169.84 | AY67: 304353.52 | AZ67: 295907.39 | BA67: 301273.04 | BB67: 329087.83 | BC67: 400806.23 | BD67: 324242.12 | BE67: 211414.44 | BF67: 193349.54 | BG67: 410225.56 | BH67: 3882913.1 | BI67: =SUM(BI63:BI66) -> 197723.95 | BJ67: =SUM(BJ63:BJ66) -> 122606.01 | BK67: =SUM(BK63:BK66) -> 151281.61 | BL67: =SUM(BL63:BL66) -> 59702.31 | BM67: =SUM(BM63:BM66) -> 141189.82 | BN67: =SUM(BN63:BN66) -> 262460.59 | BO67: =SUM(BO63:BO66) -> 203035.57 | BP67: =SUM(BP63:BP66) -> 190880.78 | ... BT67: =SUM(BT63:BT66) -> 340304.45 | BU67: =SUM(BI67:BT67) -> 2448428.6 | BV67: =SUM(BV63:BV66) -> 358208.74 | BW67: =SUM(BW63:BW66) -> 453012.33 | BX67: =SUM(BX63:BX66) -> 426403.56 | BY67: =SUM(BY63:BY66) -> 311535.52 | BZ67: =SUM(BZ63:BZ66) -> 482017.18 | CA67: =SUM(CA63:CA66) -> 643767.99 | CB67: =SUM(CB63:CB66) -> 493358.04 | CC67: =SUM(CC63:CC66) -> 295501.93 | ... CG67: =SUM(CG63:CG66) -> 1744622.6 | CH67: =SUM(BV67:CG67) -> 6952534.5 | CI67: =SUM(CI63:CI66) -> 1919606.5 | CJ67: =SUM(CJ63:CJ66) -> 1803996.6 | CK67: =SUM(CK63:CK66) -> 1612086.9 | CL67: =SUM(CL63:CL66) -> 1388331.1 | CM67: =SUM(CM63:CM66) -> 1147802.3 | CN67: =SUM(CN63:CN66) -> 672737.47 | CO67: =SUM(CO63:CO66) -> 957340.61 | CP67: =SUM(CP63:CP66) -> 857246.35 | ... CT67: =SUM(CT63:CT66) -> 383084.42 | CU67: =SUM(CI67:CT67) -> 13854278 | CV67: =SUM(CV63:CV66) -> 417405.25 | CW67: =SUM(CW63:CW66) -> 469177.75 | CX67: =SUM(CX63:CX66) -> 863944.56 | CY67: =SUM(CY63:CY66) -> 1181731.3 | CZ67: =SUM(CZ63:CZ66) -> 733164.02 | DA67: =SUM(DA63:DA66) -> 421927.2 | DB67: =SUM(DB63:DB66) -> 925734.21 | DC67: =SUM(DC63:DC66) -> 633895.42 | ... DU67: =SUM(DU63:DU66) -> 9419399.2
A69: Less Operating Expenses
A71: Credit Operating Expenses
A73: General Admin
A74: Bank Fees | B74: 3824.29 | C74: 839.75 | D74: 816.08 | E74: 938.24 | F74: 7861.97 | G74: 1499.66 | H74: 933.45 | I74: 1415.04 | J74: 1296.88 | K74: 1146.6 | L74: 1244.28 | M74: 894.15 | N74: 1066.82 | O74: 1067.54 | P74: 1270.62 | Q74: 1284.31 | R74: 1120.26 | S74: 14239.61 | T74: 1580.53 | U74: 857 | V74: 1313.09 | W74: 1333.36 | X74: 1580.35 | Y74: 1735.01 | Z74: 2531.39 | AA74: 2592.92 | AB74: 2531.69 | AC74: 2739.26 | AD74: 2533.75 | AE74: 2354.5 | AF74: 23682.85 | AG74: 2853.85 | AH74: 2972.33 | AI74: 4524.14 | AJ74: 3549.37 | AK74: 2974.4 | AL74: 3713.74 | AM74: 4365.81 | AN74: 3879.04 | AO74: 3756.9 | AP74: 5921.62 | AQ74: 6710.86 | AR74: 4896.65 | AS74: 50118.71 | AU74: 50118.71 | AV74: 7280.23 | AW74: 11009.87 | AX74: 8796.15 | AY74: 6065.44 | AZ74: 4509.48 | BA74: 2714.03 | BB74: 3180.56 | BC74: 3270.64 | BD74: 6449.36 | BE74: 4463.23 | BF74: 6057.22 | BG74: 4159.97 | BH74: 67956.18 | BI74: 3963.49 | BJ74: 4449.42 | BK74: 5309.85 | BL74: 6738.75 | BM74: 5971.2 | BN74: 8985.25 | BO74: 5458.46 | BP74: 9409.29 | BQ74: 6715 | BR74: 7995.68 | BS74: 10443.09 | BT74: 10549.88 | BU74: =SUM(BI74:BT74) -> 85989.36 | BV74: 9265.85 | BW74: 5636.67 | BX74: 7117.47 | BY74: 6328.96 | BZ74: 6417.95 | CA74: 8251.14 | CB74: 7340.58 | CC74: 10152.4 | CD74: 8350.28 | CE74: 10141.34 | CF74: 11159.82 | CG74: 9718.41 | CH74: =SUM(BV74:CG74) -> 99880.87 | CI74: 9289.23 | CJ74: 10021.41 | CK74: 8848.43 | CL74: 13741.23 | CM74: =14196.16-2 -> 14194.16 | CN74: 12806.18 | CO74: 13205.07 | CP74: 10359.53 | CQ74: 13318.69 | CR74: 16106.9 | CS74: 13399.99 | CT74: 18396.93 | CU74: =SUM(CI74:CT74) -> 153687.75 | CV74: 13480.98 | CW74: 14223.72 | CX74: 15053.24 | CY74: 17705.8 | CZ74: 12615.86 | DA74: 12735.46 | DB74: 15160.96 | DC74: 16796.89 | DD74: 15562.01 | DE74: 17040.45 | DF74: 15058.85 | DG74: 13901.31 | DH74: =SUM(CV74:DG74) -> 179335.53 | DI74: 14012.38 | DJ74: 12151.83 | DK74: 13311.51 | DL74: 14966.69 | DM74: 12020.86 | DN74: 15049.28 | DO74: 14312.35 | DP74: 20831.58 | DQ74: 19912.4 | DR74: 31761.59 | DU74: =SUM(DI74:DT74) -> 168330.47
A75: Forex Charges | B75: 4394.07 | C75: 550 | D75: 6382.81 | E75: 1510 | F75: 18131.65 | G75: 1510 | H75: 810 | I75: 6896.54 | J75: 1333.78 | K75: 535 | L75: 580.1 | M75: 2767.28 | N75: 8179.49 | O75: 2170.33 | P75: 3072.92 | Q75: 592 | R75: 4967.43 | S75: 33414.87 | T75: 8515.74 | U75: 2207 | V75: 3738.47 | W75: 3049.48 | X75: 10483.99 | Y75: 4654.26 | Z75: 12091.51 | AA75: 10334.66 | AB75: 20991.03 | AC75: 38541.06 | AD75: 5135.9 | AE75: 2856.16 | AF75: 122599.26 | AG75: 6265.99 | AH75: 20281.71 | AI75: 3679.37 | AJ75: 26355.49 | AK75: 107205.99 | AL75: 11588.13 | AM75: 12765.86 | AN75: 13483.93 | AO75: 65976.95 | AP75: 39991.66 | AQ75: 3974.3 | AR75: 7279.12 | AS75: 318848.5 | AU75: 318848.5 | AV75: 18369.39 | AW75: 1511.9 | AX75: 3220.09 | AY75: 9350.6 | AZ75: 13120.48 | BA75: 3552.23 | BB75: 7010.54 | BC75: 8257.91 | BD75: 9147.94 | BE75: 5144.9 | BF75: 7192.14 | BG75: 1573.98 | BH75: 87452.1 | BI75: 5334.12 | BJ75: 10695.31 | BK75: 6121.47 | BL75: 6352.89 | BM75: 19077.87 | BN75: 3797.87 | BO75: 8138.71 | BP75: 16443.99 | BQ75: 5041 | BR75: 12917.33 | BS75: 14099.98 | BT75: 13748.74 | BU75: =SUM(BI75:BT75) -> 121769.28 | BV75: 27035.69 | BW75: 36920.95 | BX75: 22294.02 | BY75: 27242.83 | BZ75: 38032.31 | CA75: 29205.46 | CB75: 22962.07 | CC75: 7124.8 | CD75: 13234.48 | CE75: 17860.43 | CF75: 29512.98 | CG75: 54318.95 | CH75: =SUM(BV75:CG75) -> 325744.97 | CI75: 19684.29 | CJ75: 9673.08 | CK75: 10092.86 | CL75: 9516.75 | CM75: 14957.42 | CN75: 23401.08 | CO75: 22882.77 | CP75: 22355.82 | CQ75: 19736.66 | CR75: 19566.5 | CS75: 17976.65 | CT75: 4792.02 | CU75: =SUM(CI75:CT75) -> 194635.9 | CV75: 20585.61 | CW75: 24654.37 | CX75: 18165.41 | CY75: 10462.5 | CZ75: 22118.87 | DA75: 13209.05 | DB75: 19219.54 | DC75: 20213.47 | DD75: 16566.26 | DE75: 18956.84 | DF75: 23336.37 | DG75: 18592.88 | DH75: =SUM(CV75:DG75) -> 226081.17 | DI75: 39750.45 | DJ75: 16513.38 | DK75: 26804.16 | DL75: 100220.85 | DM75: 42008.44 | DN75: 37212.96 | DO75: 38759.08 | DP75: 28033.32 | DQ75: 29218.9 | DR75: 35070.42 | DU75: =SUM(DI75:DT75) -> 393591.96
A76: Insurance | B76: 0 | C76: 1611.2 | D76: 2104.57 | E76: 3078 | F76: 6793.77 | G76: 3720.2 | H76: 3446.6 | I76: 2457.02 | J76: 2870.9 | K76: 3138.12 | L76: 3451.54 | M76: 4404.93 | N76: 4251.01 | O76: 4199.11 | P76: 4515.02 | Q76: 3949.8 | R76: 446.87 | S76: 40851.12 | T76: 2436.97 | U76: 2348 | V76: 2404.81 | W76: 4062.04 | X76: 1075.73 | Y76: 1075.73 | Z76: 1111.01 | AA76: 1111.01 | AB76: 1111.01 | AC76: 1111.01 | AD76: 1110.98 | AE76: 1110.98 | AF76: 20069.28 | AG76: 1110.98 | AH76: 1110.98 | AI76: 1110.98 | AJ76: 2152.65 | AK76: 2152.65 | AL76: 3162.79 | AM76: 3027.26 | AN76: 3027.26 | AO76: 3027.26 | AP76: 3027.26 | AQ76: 15084.91 | AR76: 15084.81 | AS76: 53079.79 | AU76: 53079.79 | AV76: 15084.81 | AW76: 15356.45 | AX76: 15429.19 | AY76: 13762.52 | AZ76: 13762.52 | BA76: 13762.52 | BB76: 13816.55 | BC76: 13816.55 | BD76: 25670.19 | BE76: 19743.37 | BF76: 7685.82 | BG76: 40528.35 | BH76: 208418.84 | BI76: 26713.18 | BJ76: 26713.18 | BK76: 26713.18 | BL76: 26713.18 | BM76: 26713.18 | BN76: 26713.18 | BO76: 26864.2 | BP76: 28692.25 | BQ76: 31223 | BR76: 30036.97 | BS76: 39505.71 | BT76: 39505.71 | BU76: =SUM(BI76:BT76) -> 356106.92 | BV76: 39505.71 | BW76: 39505.71 | BX76: 39505.71 | BY76: 39505.71 | BZ76: 39505.71 | CA76: 39505.71 | CB76: 33328.38 | CC76: 39871.19 | CD76: 41293.69 | CE76: 40582.44 | CF76: 40582.44 | CG76: 40582.44 | CH76: =SUM(BV76:CG76) -> 473274.84 | CI76: 41193.62 | CJ76: 41193.62 | CK76: 41193.62 | CL76: 41193.62 | CM76: 41193.62 | CN76: 45057.59 | CO76: 41122.59 | CP76: 45554.65 | CQ76: 46807.81 | CR76: 46181.23 | CS76: 46181.25 | CT76: 46181.23 | CU76: =SUM(CI76:CT76) -> 523054.45 | CV76: 51780.15 | CW76: 45570.78 | CX76: 45570.77 | CY76: 45570.77 | CZ76: 45570.77 | DA76: 45570.77 | DB76: 37566.59 | DC76: 46220.72 | DD76: 47188.98 | DE76: 46704.79 | DF76: 46705.05 | DG76: 46705.05 | DH76: =SUM(CV76:DG76) -> 550725.19 | DI76: 54064.8 | DJ76: 54064.8 | DK76: 54098.03 | DL76: 54031.58 | DM76: 54064.8 | DN76: 54064.8 | DO76: 44244.13 | DP76: 54589.65 | DQ76: 54589.65 | DR76: 54589.65 | DU76: =SUM(DI76:DT76) -> 532401.89
A77: Legal & Accounting | B77: 65029.89 | C77: 192992.18 | D77: 17053.35 | E77: 13742.37 | F77: 857567.7 | G77: 28226.35 | H77: 3050 | I77: 15759.32 | J77: 15213.81 | K77: 137711.01 | L77: 16094.36 | M77: 14169.11 | N77: 5741.18 | O77: 10174.81 | P77: 19995.83 | Q77: 17095.5 | R77: 29991.47 | S77: 313222.75 | T77: 11423.69 | U77: 9563 | V77: 22856.51 | W77: 11186.22 | X77: 21199.29 | Y77: 16865 | Z77: 48909.58 | AA77: 37661.5 | AB77: 44830.44 | AC77: 33894.81 | AD77: 46014.09 | AE77: 22644.79 | AF77: 327048.92 | AG77: 4973.55 | AH77: 36110.14 | AI77: 58790.13 | AJ77: 75259.09 | AK77: 939287.86 | AL77: 243446.98 | AM77: 36505.97 | AN77: 27785.68 | AO77: 51364 | AP77: 32576.23 | AQ77: 33110.51 | AR77: 21046.13 | AS77: 1560256.3 | AT77: -1211435.4 | AU77: 348820.89 | AV77: 34808.99 | AW77: 11020.7 | AX77: 26950.95 | AY77: 45782.81 | AZ77: 35444.94 | BA77: 57921.72 | BB77: 31596.75 | BC77: 81249.22 | BD77: 33157.89 | BE77: 50543.3 | BF77: 17390.09 | BG77: 31527.84 | BH77: 457395.2 | BI77: 65055.25 | BJ77: 125811.28 | BK77: 79425.43 | BL77: 98729.63 | BM77: 177263.02 | BN77: 76930.16 | BO77: 137898.6 | BP77: 72892.42 | BQ77: 167778 | BR77: 184198.79 | BS77: 204424.17 | BT77: 118604.02 | BU77: =SUM(BI77:BT77) -> 1509010.8 | BV77: 104430.51 | BW77: 67836.32 | BX77: 127209.75 | BY77: 203321.64 | BZ77: 66174.65 | CA77: 31038.3 | CB77: 217062.98 | CC77: 127874.24 | CD77: 159203 | CE77: 102200.3 | CF77: 89759.18 | CG77: 107573.45 | CH77: =SUM(BV77:CG77) -> 1403684.3 | CI77: 144451.46 | CJ77: 125088.4 | CK77: 186116.85 | CL77: 121992.43 | CM77: 144372.92 | CN77: 158136.02 | CO77: 119059.72 | CP77: 181472.39 | CQ77: 129751.33 | CR77: 105489.77 | CS77: 104479.63 | CT77: -2634.49 | CU77: =SUM(CI77:CT77) -> 1517776.4 | CV77: 175549.56 | CW77: 182444.06 | CX77: 182716.5 | CY77: 209265.84 | CZ77: 210971.68 | DA77: 326625.98 | DB77: 365106.42 | DC77: 393874.05 | DD77: 438226.71 | DE77: 881317.26 | DF77: 445669.15 | DG77: 373153.76 | DH77: =SUM(CV77:DG77) -> 4184921 | DI77: 458256.76 | DJ77: 347217.46 | DK77: 437437.65 | DL77: 507523.64 | DM77: 525037.65 | DN77: 739792.48 | DO77: 1541086.5 | DP77: 369770.83 | DQ77: 1235547.6 | DR77: 472267.91 | DU77: =SUM(DI77:DT77) -> 6633938.4
A78: Other Expenses - General | B78: 3344.08 | C78: 1616.19 | D78: 1027.85 | E78: 1153.29 | F78: 20985.28 | G78: 1800.05 | H78: 985.54 | I78: 1367.86 | J78: 1873.5 | K78: 1151.53 | L78: 2003.81 | M78: 2066.13 | N78: 2198.45 | O78: 4869.94 | P78: 3863 | Q78: 3737.17 | R78: 2933.46 | S78: 28850.44 | T78: 4041.63 | U78: 4116 | V78: 4331.9 | W78: 3068.29 | X78: 5006.39 | Y78: 5848.28 | Z78: 4786.26 | AA78: 8737.18 | AB78: 7738.37 | AC78: 14684.94 | AD78: 3624.05 | AE78: 3769.81 | AF78: 69753.1 | AG78: 5146.79 | AH78: 4851.45 | AI78: 9778.55 | AJ78: 8097.34 | AK78: 12690.86 | AL78: 25054.45 | AM78: 10206.66 | AN78: 27231.36 | AO78: 22394.21 | AP78: 34440.94 | AQ78: 23363.71 | AR78: 33034.69 | AS78: 216291.01 | AU78: 216291.01 | AV78: 16120.7 | AW78: 11706.51 | AX78: 10839.15 | AY78: 7947.11 | AZ78: 9426.79 | BA78: 7935.47 | BB78: 8547.58 | BC78: 11001.66 | BD78: 15462.62 | BE78: 46834.45 | BF78: 11795.5 | BG78: 9365.27 | BH78: 166982.81 | BI78: 13970.99 | BJ78: 13928.37 | BK78: 20243.08 | BL78: 42221.78 | BM78: 22756.4 | BN78: 29410.16 | BO78: 26831.59 | BP78: 18157.46 | BQ78: 40772 | BR78: 79461.3 | BS78: 32228.43 | BT78: 27520.21 | BU78: =SUM(BI78:BT78) -> 367501.77 | BV78: 15371.07 | BW78: 11506.03 | BX78: 12169.51 | BY78: 9775.41 | BZ78: 9518.26 | CA78: 10213.75 | CB78: 11720.82 | CC78: 9779.25 | CD78: 8855.25 | CE78: 14006.91 | CF78: 9079.25 | CG78: 9941.25 | CH78: =SUM(BV78:CG78) -> 131936.76 | CI78: 4823.29 | CJ78: 4447.68 | CK78: 5446 | CL78: 6097.47 | CM78: 4376.4 | CN78: 16000.32 | CO78: 5040.24 | CP78: 4563.37 | CQ78: 4376.4 | CR78: 10053.04 | CS78: 4376.32 | CT78: 4868.94 | CU78: =SUM(CI78:CT78) -> 74469.47 | CV78: =3582.66+35424.63 -> 39007.29 | CW78: 101490.96 | CX78: 25665.02 | CY78: 58906.38 | CZ78: 7444.33 | DA78: 54486.63 | DB78: 50372.82 | DC78: 188413 | DD78: 100104.37 | DE78: 7585 | DF78: 6315 | DG78: 61554.5 | DH78: =SUM(CV78:DG78) -> 701345.3 | DI78: =2088.33+25265.96 -> 27354.29 | DJ78: 63711.86 | DK78: 33143.3 | DL78: 54151.24 | DM78: 107034.96 | DN78: 97394.93 | DO78: 68233.19 | DP78: 133156.79 | DQ78: 165910.87 | DR78: 11375.25 | DU78: =SUM(DI78:DT78) -> 761466.68
A79: Statutory and Regulatory Expenses | B79: 2400 | C79: 0 | D79: 729.17 | E79: 0 | F79: 879.17 | CU79: =BV79 -> 0 | DH79: =SUM(CV79:DG79) -> 0 | DI79: 0 | DJ79: 0 | DK79: 0 | DL79: 0 | DM79: 0 | DU79: =SUM(DI79:DT79) -> 0
A80: Total General Admin | B80: =SUM(B74:B79) -> 78992.33 | C80: =SUM(C74:C79) -> 197609.32 | D80: =SUM(D74:D79) -> 28113.83 | E80: =SUM(E74:E79) -> 20421.9 | F80: =SUM(F74:F79) -> 912219.54 | G80: =SUM(G74:G79) -> 36756.26 | H80: =SUM(H74:H79) -> 9225.59 | I80: =SUM(I74:I79) -> 27895.78 | ... R80: =SUM(R74:R79) -> 39459.49 | S80: =SUM(S74:S78) -> 430578.79 | T80: =SUM(T74:T78) -> 27998.56 | U80: 19092 | V80: =SUM(V74:V78) -> 34644.78 | W80: =SUM(W74:W78) -> 22699.39 | X80: =SUM(X74:X78) -> 39345.75 | Y80: =SUM(Y74:Y78) -> 30178.28 | Z80: =SUM(Z74:Z78) -> 69429.75 | AA80: =SUM(AA74:AA78) -> 60437.27 | AB80: =SUM(AB74:AB78) -> 77202.54 | AC80: =SUM(AC74:AC78) -> 90971.08 | ... AE80: =SUM(AE74:AE78) -> 32736.24 | AF80: 563154.41 | AG80: 20351.16 | AH80: 65326.61 | AI80: 77883.17 | AJ80: 115413.94 | AK80: 1064311.8 | AL80: 286966.09 | AM80: 66871.56 | AN80: 75407.27 | AO80: 146519.32 | AP80: 115957.71 | AQ80: 82244.29 | AR80: 81341.4 | AS80: 2198594.3 | AT80: -1211435.4 | AU80: 987158.9 | AV80: 91664.12 | AW80: 50605.43 | AX80: 65235.53 | AY80: 82908.48 | AZ80: 76264.21 | BA80: 85885.97 | BB80: 64151.98 | BC80: 117595.98 | BD80: 89888 | BE80: 126729.25 | BF80: 50120.77 | BG80: 87155.41 | BH80: 988205.13 | BI80: =SUM(BI74:BI78) -> 115037.03 | BJ80: =SUM(BJ74:BJ78) -> 181597.56 | BK80: =SUM(BK74:BK78) -> 137813.01 | BL80: =SUM(BL74:BL78) -> 180756.23 | BM80: =SUM(BM74:BM78) -> 251781.67 | BN80: =SUM(BN74:BN78) -> 145836.62 | BO80: =SUM(BO74:BO78) -> 205191.56 | BP80: =SUM(BP74:BP78) -> 145595.41 | ... BT80: =SUM(BT74:BT78) -> 209928.56 | BU80: =SUM(BI80:BT80) -> 2440378.1 | BV80: =SUM(BV74:BV78) -> 195608.83 | BW80: =SUM(BW74:BW78) -> 161405.68 | BX80: =SUM(BX74:BX78) -> 208296.46 | BY80: =SUM(BY74:BY78) -> 286174.55 | BZ80: =SUM(BZ74:BZ78) -> 159648.88 | CA80: =SUM(CA74:CA78) -> 118214.36 | CB80: =SUM(CB74:CB78) -> 292414.83 | CC80: =SUM(CC74:CC78) -> 194801.88 | ... CG80: =SUM(CG74:CG78) -> 222134.5 | CH80: =SUM(BV80:CG80) -> 2434521.8 | CI80: =SUM(CI74:CI78) -> 219441.89 | CJ80: =SUM(CJ74:CJ78) -> 190424.19 | CK80: =SUM(CK74:CK78) -> 251697.76 | CL80: =SUM(CL74:CL78) -> 192541.5 | CM80: =SUM(CM74:CM78) -> 219094.52 | CN80: =SUM(CN74:CN78) -> 255401.19 | CO80: =SUM(CO74:CO78) -> 201310.39 | CP80: =SUM(CP74:CP78) -> 264305.76 | ... CT80: =SUM(CT74:CT78) -> 71604.63 | CU80: =SUM(CI80:CT80) -> 2463624 | CV80: =SUM(CV74:CV78) -> 300403.59 | CW80: =SUM(CW74:CW78) -> 368383.89 | CX80: =SUM(CX74:CX78) -> 287170.94 | CY80: =SUM(CY74:CY78) -> 341911.29 | CZ80: =SUM(CZ74:CZ78) -> 298721.51 | DA80: =SUM(DA74:DA78) -> 452627.89 | DB80: =SUM(DB74:DB78) -> 487426.33 | DC80: =SUM(DC74:DC78) -> 665518.13 | ... DG80: =SUM(DG74:DG78) -> 513907.5 | DH80: =SUM(CV80:DG80) -> 5842408.2 | DI80: =SUM(DI74:DI79) -> 593438.68 | DJ80: =SUM(DJ74:DJ79) -> 493659.33 | DK80: =SUM(DK74:DK79) -> 564794.65 | DL80: =SUM(DL74:DL79) -> 730894 | DM80: =SUM(DM74:DM79) -> 740166.71 | DN80: =SUM(DN74:DN78) -> 943514.45 | DO80: =SUM(DO74:DO78) -> 1706635.2 | DP80: =SUM(DP74:DP78) -> 606382.17 | DQ80: =SUM(DQ74:DQ78) -> 1505179.4 | DR80: =SUM(DR74:DR78) -> 605064.82 | DS80: =SUM(DS74:DS78) -> 0 | DT80: =SUM(DT74:DT78) -> 0 | DU80: =SUM(DI80:DT80) -> 8489729.4
A82: Branding | CI82: 500000 | CJ82: 491129 | CK82: 400000 | CL82: 0 | CM82: 0 | CN82: 0 | CO82: 0 | CP82: 0 | CQ82: 0 | CR82: 0 | CS82: 0 | CT82: 0 | CU82: =SUM(CI82:CT82) -> 1391129 | CV82: 63494.01 | CW82: 79844.87 | CX82: 62319.09 | CY82: 141044.33 | CZ82: 265598.57 | DA82: 384218.25 | DB82: 314266.53 | DC82: 224537.1 | DD82: 217176.92 | DE82: 165373.72 | DF82: 165373.72 | DG82: 157548.12 | DH82: =SUM(CV82:DG82) -> 2240795.2 | DI82: 58837.94 | DJ82: 288837.94 | DK82: 77023 | DL82: 279859.54 | DM82: 121353.13 | DN82: 177607.14 | DO82: 324616.9 | DP82: 267479.46 | DQ82: 387151.16 | DR82: 210417.68 | DU82: =SUM(DI82:DT82) -> 2193183.9
A84: Marketing - direct
A85: Other Marketing | B85: 0 | C85: 0 | D85: 9289.01 | E85: 3250 | F85: 14762.01 | G85: 14820 | H85: 6840 | I85: 0 | J85: 5174.65 | K85: 24508.65 | L85: 29643.08 | M85: 11708.65 | N85: 29330.49 | O85: 46218.32 | P85: 29590.01 | Q85: 28008.65 | R85: 50136.22 | S85: 275978.72 | T85: 47211.05 | U85: 43596 | V85: 37995.9 | W85: 10115.14 | X85: 87334.41 | Y85: 76656.89 | Z85: 209945.48 | AA85: 305844.44 | AB85: 371394.53 | AC85: 232350.56 | AD85: 206838.8 | AE85: 393128.78 | AF85: 2022412 | AG85: 201364.33 | AH85: 301684.84 | AI85: 167659.3 | AJ85: 49380 | AK85: 106500.06 | AL85: 277966.75 | AM85: 137225.63 | AN85: 515519.68 | AO85: 699800.3 | AP85: 1440309.2 | AQ85: 674122.18 | AR85: 1209877.8 | AS85: 5781410 | AU85: 5781410 | AV85: 834545.48 | AW85: 248231.3 | AX85: 220347.85 | AY85: 285877.52 | AZ85: 259058.68 | BA85: 257146.31 | BB85: 218346.61 | BC85: 221739 | BD85: 773968.6 | BE85: 284813.09 | BF85: 229656.02 | BG85: 592008.26 | BH85: 4425738.7 | BI85: 519456.7 | BJ85: 590990.86 | BK85: 521891.06 | BL85: 641144.82 | BM85: 792977.47 | BN85: 638978.59 | BO85: 987653.35 | BP85: 866261 | BQ85: 948714 | BR85: 574013.39 | BS85: 227878.67 | BT85: 990875.22 | BU85: =SUM(BI85:BT85) -> 8300835.1 | BV85: 821741.28 | BW85: 901077.04 | BX85: 1527646.7 | BY85: 1526314 | BZ85: 1167153 | CA85: 1016056.6 | CB85: 1825906.8 | CC85: 2483989.6 | CD85: 1887428 | CE85: 1931051.6 | CF85: 2085744.6 | CG85: 1977358.9 | CH85: =SUM(BV85:CG85) -> 19151468 | CI85: 1710231.5 | CJ85: 1488649.8 | CK85: 1777439 | CL85: 2028763.1 | CM85: 2056371.1 | CN85: 2655832.5 | CO85: 2703875.3 | CP85: 2526114.5 | CQ85: 1613464.1 | CR85: 544910.9 | CS85: 91457.82 | CT85: 559727.08 | CU85: =SUM(CI85:CT85) -> 19756837 | CV85: 413767.09 | CW85: 507807.79 | CX85: 477745.65 | CY85: 476903.67 | CZ85: 481221.72 | DA85: 484054.66 | DB85: 863057.61 | DC85: 197764.85 | DD85: 564402.06 | DE85: 562167.38 | DF85: 334736.16 | DG85: 732542.91 | DH85: =SUM(CV85:DG85) -> 6096171.5 | DI85: 487028.03 | DJ85: 506107.59 | DK85: 596051.07 | DL85: 765736.72 | DM85: 627330.91 | DN85: 477196.63 | DO85: 339421.63 | DP85: 554219.07 | DQ85: 328240.73 | DR85: 792485.43 | DU85: =SUM(DI85:DT85) -> 5473817.8
A86: PPC Marketing | B86: 100529.35 | C86: 24766.68 | D86: 25700 | E86: 40299 | F86: 282065.68 | G86: 41400.77 | H86: 35000 | I86: 39352.65 | J86: 34793.88 | K86: 36601.01 | L86: 37787.86 | M86: 34126.67 | N86: 34268.24 | O86: 39363.92 | P86: 34109.43 | Q86: 33868.88 | R86: 33621.32 | S86: 434294.69 | T86: 33708.3 | U86: 23645 | V86: =95165.73-37806.4 -> 57359.33 | W86: 108669.19 | X86: 55000 | Y86: 94558.76 | Z86: 90000 | AA86: 110000 | AB86: 100000 | AC86: 65000 | AD86: 155000 | AE86: 135000 | AF86: =SUM(T86:AE86) -> 1027940.6 | AG86: 240000 | AH86: 265750.47 | AI86: 325000 | AJ86: 270000 | AK86: 543586.03 | AL86: 479417.56 | AM86: 395943.91 | AN86: 503988.49 | AO86: 958005.32 | AP86: 296367.17 | AQ86: 686639.96 | AR86: 1002550.6 | AS86: 5967249.5 | AU86: 5967249.5 | AV86: 513097.49 | AW86: 48801.1 | AX86: 242227.38 | AY86: 69353.03 | AZ86: 224771.84 | BA86: 210470.52 | BB86: 439343.7 | BC86: 354920.58 | BD86: 275825.28 | BE86: 176702.68 | BF86: 408166.86 | BG86: 555049.08 | BH86: 3518729.5 | BI86: 846107.81 | BJ86: 711445.74 | BK86: 907071.82 | BL86: 923006.85 | BM86: 1134172.2 | BN86: 1566551.8 | BO86: 1616105.4 | BP86: 1658245.9 | BQ86: 1947156 | BR86: 1701759.9 | BS86: 1229078.4 | BT86: 1900274 | BU86: =SUM(BI86:BT86) -> 16140976 | BV86: 2233186 | BW86: 1775788.2 | BX86: 2787302.3 | BY86: 2620231.6 | BZ86: 2455258.2 | CA86: 2132792.6 | CB86: 1788522.7 | CC86: 2679025.3 | CD86: 3048218.2 | CE86: 925374.71 | CF86: 1973220.8 | CG86: 1911305.9 | CH86: =SUM(BV86:CG86) -> 26330226 | CI86: 1765427.2 | CJ86: 1560540.1 | CK86: 2150737.6 | CL86: 2766300.3 | CM86: 2502762.6 | CN86: 2940579.3 | CO86: 1700234.2 | CP86: 1751008.4 | CQ86: 3031751.1 | CR86: 1948361.3 | CS86: 2817454.6 | CT86: 3141204 | CU86: =SUM(CI86:CT86) -> 28076361 | CV86: 2386793.5 | CW86: 3343845.5 | CX86: 3203530.8 | CY86: 1271440.6 | CZ86: 2323810.9 | DA86: 2483751.4 | DB86: 3706857.9 | DC86: 4487886.6 | DD86: 3129166.5 | DE86: 3919710.8 | DF86: 3306299.4 | DG86: 2963591.8 | DH86: =SUM(CV86:DG86) -> 36526686 | DI86: 3993757.4 | DJ86: 2533641.2 | DK86: 2763206.8 | DL86: 2786945.3 | DM86: 4632902.3 | DN86: 2893781.1 | DO86: 3355447.2 | DP86: 3531863.7 | DQ86: 3531864 | DR86: 3108499.3 | DU86: =SUM(DI86:DT86) -> 33131908
A87: Social Marketing | B87: 0 | C87: 0 | D87: 5399.39 | E87: 9746.7 | F87: 15146.09 | G87: 13952.84 | H87: 7624.12 | I87: 1851.34 | J87: 24810.55 | K87: 22438.05 | L87: 17067.9 | M87: 6216.25 | N87: 10930.94 | O87: 0 | P87: 0 | R87: 0 | S87: 104891.99 | T87: 51.54 | U87: 6653 | V87: 11617.44 | W87: 13551.63 | X87: 4436.52 | Y87: 6518.62 | Z87: 6208.52 | AA87: 5315.76 | AB87: 5076.05 | AC87: 1035.8 | AD87: 698.64 | AE87: 301.36 | AF87: 61464.88 | AG87: 1000 | AH87: 1637.62 | AI87: 41252.77 | AJ87: 109264.09 | AK87: 170533.34 | AL87: 128332.29 | AM87: 285243.95 | AN87: 372624.12 | AO87: 314013.43 | AP87: 150111.27 | AQ87: 344487.25 | AR87: 274412.07 | AS87: 2192912.2 | AU87: 2192912.2 | AV87: 212355.45 | AW87: 0 | AX87: -908.05 | AY87: 0 | AZ87: 36837.5 | BA87: 82623.77 | BB87: 171514.86 | BC87: 318641.23 | BD87: 157745.34 | BE87: 137943.66 | BF87: 330625 | BG87: 235095.32 | BH87: 1682474.1 | BI87: 411216.82 | BJ87: 408353.64 | BK87: 484698.04 | BL87: 458563.86 | BM87: 306706.49 | BN87: 391251.67 | BO87: 388858.63 | BP87: 402435.15 | BQ87: 504375 | BR87: 477074.27 | BS87: 389686.09 | BT87: 955927.5 | BU87: =SUM(BI87:BT87) -> 5579147.2 | BV87: 964116.31 | BW87: 587908.36 | BX87: 996990.96 | BY87: 1112625.8 | BZ87: 913276.49 | CA87: 859236.88 | CB87: 1322500 | CC87: 1236240.8 | CD87: 1480728.1 | CE87: 251002.07 | CF87: 380222.7 | CG87: 422148.6 | CH87: =SUM(BV87:CG87) -> 10526997 | CI87: 507884.49 | CJ87: 403049.2 | CK87: 294035.86 | CL87: 620696.78 | CM87: 637168.5 | CN87: 310654.92 | CO87: 211230.04 | CP87: 518662.66 | CQ87: 699107 | CR87: 314376.9 | CS87: 256815 | CT87: 374184 | CU87: =SUM(CI87:CT87) -> 5147865.4 | CV87: 423074.68 | CW87: 374975.35 | CX87: 539244.45 | CY87: 522064.36 | CZ87: 1013557.3 | DA87: 1213158.6 | DB87: 945543.82 | DC87: 1474193.1 | DD87: 1464878.9 | DE87: 3574.8 | DF87: 0 | DG87: 338168.27 | DH87: =SUM(CV87:DG87) -> 8312433.7 | DI87: 11061.99 | DJ87: 1150 | DK87: 63964.58 | DL87: 364535.97 | DM87: 468290.3 | DN87: 512282.13 | DO87: 560848.32 | DP87: 671257.63 | DQ87: 64057.94 | DR87: 354.95 | DS87: 0 | DT87: 0 | DU87: =SUM(DI87:DT87) -> 2717803.8
A88: Total Marketing - direct | T88: =SUM(T85:T87) -> 80970.89 | U88: =SUM(U85:U87) -> 73894 | V88: =SUM(V85:V87) -> 106972.67 | W88: =SUM(W85:W87) -> 132335.96 | X88: =SUM(X85:X87) -> 146770.93 | Y88: =SUM(Y85:Y87) -> 177734.27 | Z88: =SUM(Z85:Z87) -> 306154 | AA88: =SUM(AA85:AA87) -> 421160.2 | ... DU88: =SUM(DU85:DU87) -> 41323530
A90: Partner / Affiliate Commission | B90: 46379 | C90: 3635.5 | D90: 9855.75 | E90: 5349.75 | F90: 63494.5 | G90: 9959.25 | H90: 5977.5 | I90: 14943.5 | J90: 13478.5 | K90: 21506.25 | L90: 21193.25 | M90: 10112.75 | N90: 22143.5 | O90: 23446 | P90: 12220 | Q90: 32688 | R90: 40119.5 | S90: 227788 | T90: 59012.5 | U90: 11942 | V90: 11718.96 | W90: 74031.13 | X90: 55021.01 | Y90: 58594.33 | Z90: 42214.33 | AA90: 52332.41 | AB90: 37273.38 | AC90: 104984.84 | AD90: 61967.17 | AE90: 99984.45 | AF90: 669076.51 | AG90: 147117.17 | AH90: 46167.08 | AI90: 66806.43 | AJ90: 88811.04 | AK90: 102299.1 | AL90: 125930.35 | AM90: 126696.27 | AN90: 144490.85 | AO90: 298975.9 | AP90: 143258.48 | AQ90: 240052.69 | AR90: 180272.78 | AS90: 1710878.1 | AU90: 1710878.1 | AV90: 423275.2 | AW90: 196274.92 | AX90: 96984.83 | AY90: 104600.47 | AZ90: 282687.7 | BA90: 467368.02 | BB90: 492865.35 | BC90: 550693.58 | BD90: 610623.02 | BE90: 672843.6 | BF90: 586927.9 | BG90: 907695.88 | BH90: 5392840.5 | BI90: 1547013.1 | BJ90: 915719.98 | BK90: 1382203.3 | BL90: 904168.59 | BM90: 1250726.8 | BN90: 1302070.9 | BO90: 1418350.2 | BP90: 1860872.2 | BQ90: 1967357 | BR90: 1272666 | BS90: 2002263 | BT90: 1731163.2 | BU90: =SUM(BI90:BT90) -> 17554574 | BV90: 1332610.6 | BW90: 1680494.4 | BX90: 1761788.9 | BY90: 1945691.7 | BZ90: 1793003.5 | CA90: 2608325.7 | CB90: 2384917.4 | CC90: 3056739.2 | CD90: 2775920.8 | CE90: 3951339.3 | CF90: 3596242.6 | CG90: 2480514.7 | CH90: =SUM(BV90:CG90) -> 29367589 | CI90: 4487844.5 | CJ90: 3519595.4 | CK90: 2936928.7 | CL90: 3885031 | CM90: 5472351.9 | CN90: 4462748 | CO90: 5486594.8 | CP90: 6693743.6 | CQ90: 6938457.3 | CR90: 6891498.7 | CS90: 6821311.7 | CT90: 8749768.3 | CU90: =SUM(CI90:CT90) -> 66345874 | CV90: 6762336.9 | CW90: 7670864.6 | CX90: 6993374.2 | CY90: 7353911.2 | CZ90: 6821834.1 | DA90: 6890244.6 | DB90: 6270796.8 | DC90: 8512203.9 | DD90: 9578811.7 | DE90: 6269175.4 | DF90: 4614032 | DG90: 6976224.3 | DH90: =SUM(CV90:DG90) -> 84713810 | DI90: 4987575.3 | DJ90: 5624259.4 | DK90: 7201288.3 | DL90: 5807827.6 | DM90: 5722604.2 | DN90: 8069093 | DO90: 4810982.3 | DP90: 6089002.4 | DQ90: 6958869.3 | DR90: 10274787 | DU90: =SUM(DI90:DT90) -> 65546289
A92: Total Marketing | B92: =SUM(B85:B91) -> 146908.35 | C92: =SUM(C85:C91) -> 28402.18 | D92: =SUM(D85:D91) -> 50244.15 | E92: =SUM(E85:E91) -> 58645.45 | F92: =SUM(F85:F91) -> 375468.28 | G92: =SUM(G85:G91) -> 80132.86 | H92: =SUM(H85:H91) -> 55441.62 | I92: =SUM(I85:I91) -> 56147.49 | ... S92: =SUM(S85:S91) -> 1042953.4 | T92: =T82+T88+T90 -> 139983.39 | U92: =U82+U88+U90 -> 85836 | V92: =V82+V88+V90 -> 118691.63 | W92: =W82+W88+W90 -> 206367.09 | X92: =X82+X88+X90 -> 201791.94 | Y92: =Y82+Y88+Y90 -> 236328.6 | Z92: =Z82+Z88+Z90 -> 348368.33 | AA92: =AA82+AA88+AA90 -> 473492.61 | ... DG92: =DG82+DG88+DG90 -> 11168075 | DH92: =SUM(CV92:DG92) -> 1.378899e+08 | DI92: =DI82+DI88+DI90 -> 9538260.7 | DJ92: =DJ82+DJ88+DJ90 -> 8953996.2 | DK92: =DK82+DK88+DK90 -> 10701534 | DL92: =DL82+DL88+DL90 -> 10004905 | DM92: =DM82+DM88+DM90 -> 11572481 | DN92: =DN82+DN88+DN90 -> 12129960 | DO92: =DO82+DO88+DO90 -> 9391316.4 | DP92: =DP82+DP88+DP90 -> 11113822 | ... DT92: =DT82+DT88+DT90 -> 0 | DU92: =SUM(DI92:DT92) -> 1.09063e+08
A94: Payroll
A95: Design Fees | B95: 0 | G95: 9731 | H95: 7332.58 | I95: 1507.52 | J95: 7045.07 | K95: 6620.74 | L95: 8712.5 | M95: 6232.89 | N95: 7184.04 | O95: 12753.79 | P95: 1471.41 | Q95: 7385.62 | R95: 7769.5 | S95: 83746.66 | T95: 7358.96 | U95: 8243 | V95: 7421.86 | W95: 7598.58 | X95: 7501.51 | Y95: 12346.12 | Z95: 22610.03 | AA95: 22662.03 | AB95: 8064.41 | AC95: 8567.55 | AD95: 8149.82 | AE95: 8174.99 | AF95: 128698.86 | AG95: 8241.33 | AH95: 8244.04 | AI95: 8242.58 | AJ95: 13720.61 | AK95: 8227.19 | AL95: 1740.47 | AM95: 15463.11 | AN95: 1665.23 | AO95: 1680.96 | AP95: 1609.58 | AQ95: 1663.67 | AR95: 1746.3 | AS95: 72245.07 | AU95: 72245.07 | AV95: 1972.34 | AW95: 2165.89 | AX95: 2008.65 | AY95: 1950.74 | AZ95: 1896.96 | BA95: 1918.16 | BB95: 1949.98 | BC95: 1843.26 | BD95: 1728.25 | BE95: 1662.02 | BF95: 1736.25 | BG95: 1712.05 | BH95: 22544.55 | BI95: 1709.11 | BJ95: 1624.65 | BK95: 1585.07 | BL95: 1617.87 | BM95: 1690.98 | BN95: 1707.39 | BO95: 1702.49 | BP95: 1686.58 | BQ95: 1809 | BR95: 2561.17 | BS95: 1737.4 | BT95: 1747.31 | BU95: =SUM(BI95:BT95) -> 21179.02 | BV95: 1653.2 | BW95: 1776.22 | BX95: 1783.14 | BY95: -1783.14 | BZ95: 0 | CA95: 2500 | CB95: 0 | CC95: 0 | CD95: 1419.9 | CE95: 0 | CF95: 0 | CG95: 0 | CH95: =SUM(BV95:CG95) -> 7349.32 | CI95: 0 | CJ95: 0 | CK95: 0 | CL95: 0 | CM95: 0 | CN95: 339.01 | CO95: 0 | CP95: 0 | CQ95: 0 | CR95: 1107.83 | CS95: 1107.83 | CT95: 2337.5 | CU95: =SUM(CI95:CT95) -> 4892.17 | CV95: 1327.83 | CW95: 1327.83 | CX95: 3052.43 | CY95: 1645.17 | CZ95: 3454.64 | DA95: 4075.81 | DB95: 1645.17 | DC95: 1645.17 | DD95: 2323.91 | DE95: 1808.88 | DF95: 1491.54 | DG95: 1491.54 | DH95: =SUM(CV95:DG95) -> 25289.92 | DI95: 1491.54 | DJ95: 1491.54 | DK95: 1491.54 | DL95: 1491.54 | DM95: 1491.54 | DN95: 1491.54 | DO95: 1491.54 | DP95: 1491.54 | DQ95: 1491.54 | DR95: 1549.58 | DU95: =SUM(DI95:DT95) -> 14973.44
A96: Other Payroll Costs (Consulting, recruitment) | B96: 11235.94 | C96: 3918.9 | D96: 131.99 | E96: 4005.54 | F96: 14924.23 | G96: 153.99 | H96: 74598 | I96: 6175.99 | J96: 6942.48 | K96: 6242 | L96: 7137 | M96: 14342.5 | N96: 14342.5 | O96: 14510.79 | P96: 18325.29 | Q96: 25914.17 | R96: 68525.11 | S96: 257209.82 | T96: 62413.73 | U96: 63484 | V96: 42574.54 | W96: 8698.84 | X96: 18528.86 | Y96: 16385.74 | Z96: 4621.74 | AA96: 2606.1 | AB96: 2459.74 | AC96: 102160.74 | AD96: 81289.55 | AE96: 86934.27 | AF96: 492157.85 | AG96: 74124.07 | AH96: 93012.7 | AI96: 111787.97 | AJ96: 148716.1 | AK96: 156525.88 | AL96: 134634.1 | AM96: 79298.6 | AN96: 80729.77 | AO96: 79699.77 | AP96: 123583.93 | AQ96: 158492.97 | AR96: 197210.75 | AS96: 1437816.6 | AU96: 1437816.6 | AV96: 115199.65 | AW96: 90928.45 | AX96: 41035.5 | AY96: 41485.84 | AZ96: 69622.34 | BA96: 84952.73 | BB96: 41817.78 | BC96: 43177.71 | BD96: 72566.27 | BE96: 57641.06 | BF96: 59748.14 | BG96: 13178.51 | BH96: 731353.98 | BI96: 32896.6 | BJ96: 59280.77 | BK96: 37101.45 | BL96: 190877.7 | BM96: 613540.28 | BN96: 501010.02 | BO96: 460333.12 | BP96: 584116.01 | BQ96: 331669 | BR96: 450059.93 | BS96: 284150.54 | BT96: 559090.22 | BU96: =SUM(BI96:BT96) -> 4104125.6 | BV96: 450662.96 | BW96: 435166.35 | BX96: 498870.68 | BY96: 566103.52 | BZ96: 623942.06 | CA96: =334915.33+290779.63 -> 625694.96 | CB96: 788770.01 | CC96: 861041.61 | CD96: 904470.69 | CE96: 777237.8 | CF96: 966539.71 | CG96: 1158666.7 | CH96: =SUM(BV96:CG96) -> 8657167 | CI96: 815703 | CJ96: 866751 | CK96: 841056.57 | CL96: 839656.23 | CM96: 877374.37 | CN96: 848552.73 | CO96: 1050709.6 | CP96: =324128.69+796811.17 -> 1120939.9 | CQ96: 1022363.8 | CR96: 972713.57 | CS96: 1143526 | CT96: 985587.8 | CU96: =SUM(CI96:CT96) -> 11384935 | CV96: 541783.12 | CW96: 773381.39 | CX96: =1716395.36-207000 -> 1509395.4 | CY96: 1532055.8 | CZ96: 1866139.3 | DA96: 1853026.8 | DB96: 2028837 | DC96: -553280.42 | DD96: -12671.93 | DE96: 383565 | DF96: 2260275.9 | DG96: 2366030.2 | DH96: =SUM(CV96:DG96) -> 14548538 | DI96: 2363103.8 | DJ96: 2388505.4 | DK96: 1787312.4 | DL96: 1294230.2 | DM96: 1483539.3 | DN96: 1379277.4 | DO96: 1186775.3 | DP96: 1447470.6 | DQ96: 1600064.5 | DR96: 1488183.3 | DU96: =SUM(DI96:DT96) -> 16418462
A97: PAYE/UIF/SDL company contribution | B97: 185278.83 | C97: 56784.06 | D97: 39321.37 | E97: 59614.07 | F97: 362312.59 | G97: 114500.13 | H97: 112823.79 | I97: 6144.46 | J97: 6192.03 | K97: 6012.38 | L97: 6018.68 | M97: 6341.01 | N97: 6374.64 | O97: 6343.2 | P97: 6429 | Q97: 6460.2 | R97: 6698.24 | S97: 290337.76 | T97: 7380.94 | U97: 8240 | V97: 8809.33 | W97: 8889.63 | X97: 8809.93 | Y97: 9457.29 | Z97: 8479.54 | AA97: 9478.59 | AB97: 10156.58 | AC97: 8952.25 | AD97: 8887.59 | AE97: 9203.38 | AF97: 106745.05 | AG97: 10549.61 | AH97: 11722.05 | AI97: 12234.41 | AJ97: 13350.51 | AK97: 16606 | AL97: 18188.26 | AM97: 20041.69 | AN97: 21682.79 | AO97: 21818.06 | AP97: 23023.83 | AQ97: 24643.32 | AR97: 26690.7 | AS97: 220551.23 | AU97: 220551.23 | AV97: 29240.3 | AW97: 28977.78 | AX97: 7539.24 | AY97: 7508.77 | AZ97: 7235.58 | BA97: 7690.46 | BB97: 31625.39 | BC97: 30403.93 | BD97: 32727.91 | BE97: 34141.02 | BF97: 33073.21 | BG97: 33509.23 | BH97: 283672.82 | BI97: 35973.14 | BJ97: 37044.34 | BK97: 33970.25 | BL97: 36322.16 | BM97: 38119.78 | BN97: 41382.22 | BO97: 43678.77 | BP97: 45065.53 | BQ97: 47064 | BR97: 46371.84 | BS97: 49647.28 | BT97: 51566.03 | BU97: =SUM(BI97:BT97) -> 506205.34 | BV97: 74936.46 | BW97: 54582.97 | BX97: 55907.79 | BY97: 54251.75 | BZ97: 55979.96 | CA97: 59294.36 | CB97: 61985 | CC97: 68649.7 | CD97: 71703 | CE97: 74782.98 | CF97: 112992.92 | CG97: 76526.26 | CH97: =SUM(BV97:CG97) -> 821593.15 | CI97: 100466.57 | CJ97: 66604.43 | CK97: 67115.84 | CL97: 68054.51 | CM97: 69818.45 | CN97: 71984.6 | CO97: 82011.59 | CP97: 87148.42 | CQ97: 90469.17 | CR97: 91249 | CS97: 95110.86 | CT97: 92927.73 | CU97: =SUM(CI97:CT97) -> 982961.17 | CV97: 85522.03 | CW97: 91297.27 | CX97: 98229.86 | CY97: 100646.63 | CZ97: 106068.67 | DA97: 162054.45 | DB97: 106367.3 | DC97: 109997.37 | DD97: 112666.94 | DE97: 114160.9 | DF97: 119821.24 | DG97: 122050.33 | DH97: =SUM(CV97:DG97) -> 1328883 | DI97: 140785.56 | DJ97: 139139.1 | DK97: 141496.94 | DL97: 138946.12 | DM97: 139397.24 | DN97: 140156.57 | DO97: 139311.98 | DP97: 145381.44 | DQ97: 152799.89 | DR97: 145528.5 | DU97: =SUM(DI97:DT97) -> 1422943.3
A98: Salaries | B98: 222135.57 | C98: 174238.11 | D98: 159686.85 | E98: 177227.7 | F98: 1290798.7 | G98: 168700.24 | H98: 302558.21 | I98: 355783.01 | J98: 327573.92 | K98: 339631.94 | L98: 320859.48 | M98: 291830.77 | N98: 307349.23 | O98: 305990.38 | P98: 289430 | Q98: 286850 | R98: 325455 | S98: 3622012.2 | T98: 375509.69 | U98: 444537 | V98: 443795.16 | W98: 430353.5 | X98: 422702.51 | Y98: 468465.37 | Z98: 420264.42 | AA98: 436801.38 | AB98: 537819.05 | AC98: 398936.01 | AD98: 466324.1 | AE98: 496985.95 | AF98: 5342494.1 | AG98: 568050.14 | AH98: 681687.74 | AI98: 715485.63 | AJ98: 745782.9 | AK98: 895416.51 | AL98: 1017760.1 | AM98: 1171966.4 | AN98: 1249601.9 | AO98: 1280255.4 | AP98: 1318830.5 | AQ98: 1403430.3 | AR98: 1553596.7 | AS98: 12601864 | AU98: 12601864 | AV98: 1637369.1 | AW98: 1615338.6 | AX98: 1553821.3 | AY98: 1469262.8 | AZ98: 1550633.9 | BA98: 1584907.8 | BB98: 1618914.3 | BC98: 1610224.2 | BD98: 1655501 | BE98: 1763775.9 | BF98: 1574897.3 | BG98: 1650029 | BH98: 19284675 | BI98: =1912599.63+55581.39 -> 1968181 | BJ98: =2004152.19+75127.9 -> 2079280.1 | BK98: =1864957.67+33627.84 -> 1898585.5 | BL98: =1873732.98+75997.01 -> 1949730 | BM98: =1878894.32+49098.93 -> 1927993.2 | BN98: =2048408.09+54116.55 -> 2102524.6 | BO98: =2070420.67+108022.34 -> 2178443 | BP98: =2083655.9+37385.59 -> 2121041.5 | BQ98: 1961532 | BR98: 1994584.4 | BS98: 2664522.6 | BT98: =2440357.75+120743.27 -> 2561101 | BU98: =SUM(BI98:BT98) -> 25407519 | BV98: =2711200.91+120849.21 -> 2832050.1 | BW98: =2452254.2+115661.53 -> 2567915.7 | BX98: 2658623.8 | BY98: 2623420.6 | BZ98: 2807792 | CA98: 2898398.5 | CB98: 3094575.9 | CC98: 3425299.3 | CD98: 3654623.9 | CE98: 4244519.4 | CF98: 3934277.2 | CG98: 3925060.4 | CH98: =SUM(BV98:CG98) -> 38666557 | CI98: 3178941 | CJ98: 3454257 | CK98: 3318541.9 | CL98: 3606993.2 | CM98: 3850806.1 | CN98: 3830581 | CO98: 4861159.9 | CP98: 4772689.1 | CQ98: 5004181.9 | CR98: 5155552.1 | CS98: 5560733 | CT98: 5145129 | CU98: =SUM(CI98:CT98) -> 51739565 | CV98: 5369017.4 | CW98: 5386190.7 | CX98: =5903467.69+207000 -> 6110467.7 | CY98: 5806135.2 | CZ98: 6293925.6 | DA98: 6348823 | DB98: 6526687 | DC98: 6437062.3 | DD98: 5917920.5 | DE98: 7283459 | DF98: 7023306.7 | DG98: 6841596 | DH98: =SUM(CV98:DG98) -> 75344591 | DI98: 7000130.5 | DJ98: 7120795.6 | DK98: 7273710.7 | DL98: 7607931.7 | DM98: 7535924.2 | DN98: 7596285.6 | DO98: 7499217.6 | DP98: 7871213.5 | DQ98: 8698688.6 | DR98: 7938456.6 | DU98: =SUM(DI98:DT98) -> 76142354
A99: Total Payroll | B99: =SUM(B95:B98) -> 418650.34 | C99: =SUM(C96:C98) -> 234941.07 | D99: =SUM(D96:D98) -> 199140.21 | E99: =SUM(E96:E98) -> 240847.31 | F99: =SUM(F96:F98) -> 1668035.5 | G99: =SUM(G95:G98) -> 293085.36 | H99: =SUM(H95:H98) -> 497312.58 | I99: =SUM(I95:I98) -> 369610.98 | J99: =SUM(J95:J98) -> 347753.5 | K99: =SUM(K95:K98) -> 358507.06 | L99: =SUM(L95:L98) -> 342727.66 | M99: =SUM(M95:M98) -> 318747.17 | N99: =SUM(N95:N98) -> 335250.41 | ... T99: =SUM(T95:T98) -> 452663.32 | U99: 524504 | V99: =SUM(V95:V98) -> 502600.89 | W99: =SUM(W95:W98) -> 455540.55 | X99: =SUM(X95:X98) -> 457542.81 | Y99: =SUM(Y95:Y98) -> 506654.52 | Z99: =SUM(Z95:Z98) -> 455975.73 | AA99: =SUM(AA95:AA98) -> 471548.1 | AB99: =SUM(AB95:AB98) -> 558499.78 | AC99: =SUM(AC95:AC98) -> 518616.55 | ... AE99: =SUM(AE95:AE98) -> 601298.59 | AF99: 6070095.9 | AG99: 660965.15 | AH99: 794666.53 | AI99: 847750.59 | AJ99: 921570.12 | AK99: 1076775.6 | AL99: 1172323 | AM99: 1286769.8 | AN99: 1353679.7 | AO99: 1383454.2 | AP99: 1467047.8 | AQ99: 1588230.2 | AR99: 1779244.4 | AS99: 14332477 | AT99: 0 | AU99: 14332477 | AV99: 1783781.3 | AW99: 1737410.7 | AX99: 1604404.7 | AY99: 1520208.1 | AZ99: 1629388.8 | BA99: 1679469.2 | BB99: 1694307.5 | BC99: 1685649.1 | BD99: 1762523.4 | BE99: 1857220 | BF99: 1669454.9 | BG99: 1698428.8 | BH99: 20322246 | BI99: =SUM(BI95:BI98) -> 2038759.9 | BJ99: =SUM(BJ95:BJ98) -> 2177229.8 | BK99: =SUM(BK95:BK98) -> 1971242.3 | BL99: =SUM(BL95:BL98) -> 2178547.7 | BM99: =SUM(BM95:BM98) -> 2581344.3 | BN99: =SUM(BN95:BN98) -> 2646624.3 | BO99: =SUM(BO95:BO98) -> 2684157.4 | BP99: =SUM(BP95:BP98) -> 2751909.6 | ... BT99: =SUM(BT95:BT98) -> 3173504.6 | BU99: =SUM(BI99:BT99) -> 30039029 | BV99: =SUM(BV95:BV98) -> 3359302.7 | BW99: =SUM(BW95:BW98) -> 3059441.3 | BX99: =SUM(BX95:BX98) -> 3215185.4 | BY99: =SUM(BY95:BY98) -> 3241992.7 | BZ99: =SUM(BZ95:BZ98) -> 3487714 | CA99: =SUM(CA95:CA98) -> 3585887.8 | CB99: =SUM(CB95:CB98) -> 3945330.9 | CC99: =SUM(CC95:CC98) -> 4354990.6 | ... CG99: =SUM(CG95:CG98) -> 5160253.3 | CH99: =SUM(BV99:CG99) -> 48152666 | CI99: =SUM(CI95:CI98) -> 4095110.6 | CJ99: =SUM(CJ95:CJ98) -> 4387612.4 | CK99: =SUM(CK95:CK98) -> 4226714.3 | CL99: =SUM(CL95:CL98) -> 4514704 | CM99: =SUM(CM95:CM98) -> 4797998.9 | CN99: =SUM(CN95:CN98) -> 4751457.3 | CO99: =SUM(CO95:CO98) -> 5993881.1 | CP99: =SUM(CP95:CP98) -> 5980777.4 | ... CT99: =SUM(CT95:CT98) -> 6225982 | CU99: =SUM(CI99:CT99) -> 64112353 | CV99: =SUM(CV95:CV98) -> 5997650.4 | CW99: =SUM(CW95:CW98) -> 6252197.2 | CX99: =SUM(CX95:CX98) -> 7721145.3 | CY99: =SUM(CY95:CY98) -> 7440482.8 | CZ99: =SUM(CZ95:CZ98) -> 8269588.2 | DA99: =SUM(DA95:DA98) -> 8367980.1 | DB99: =SUM(DB95:DB98) -> 8663536.5 | DC99: =SUM(DC95:DC98) -> 5995424.4 | ... DG99: =SUM(DG95:DG98) -> 9331168.1 | DH99: =SUM(CV99:DG99) -> 91247302 | DI99: =SUM(DI95:DI98) -> 9505511.4 | DJ99: =SUM(DJ95:DJ98) -> 9649931.6 | DK99: =SUM(DK95:DK98) -> 9204011.5 | DL99: =SUM(DL95:DL98) -> 9042599.6 | DM99: =SUM(DM95:DM98) -> 9160352.3 | DN99: =SUM(DN95:DN98) -> 9117211.1 | DO99: =SUM(DO95:DO98) -> 8826796.4 | DP99: =SUM(DP95:DP98) -> 9465557 | ... DT99: =SUM(DT95:DT98) -> 0 | DU99: =SUM(DI99:DT99) -> 93998733
A101: Rental & Communication
A102: Building & Bandwidth | B102: 114626 | C102: 24359.49 | D102: 23452.8 | E102: 27331.8 | F102: 193678.51 | G102: 28151.82 | H102: 28343.82 | I102: 30748.4 | J102: 32125.98 | K102: 31982.34 | L102: 32054.16 | M102: 32047.8 | N102: 35701.55 | O102: 34374.48 | P102: 34270.67 | Q102: 11969.98 | R102: 35574.37 | S102: 367345.37 | T102: 34551.35 | U102: 40531 | V102: 40626.05 | W102: 41238.71 | X102: 41167.51 | Y102: 42227.27 | Z102: 42577.66 | AA102: 41376.47 | AB102: 42390.29 | AC102: 41607.22 | AD102: 43026.68 | AE102: 47157.43 | AF102: 498477.64 | AG102: 41888.18 | AH102: 45940.07 | AI102: 44804.03 | AJ102: 45200.5 | AK102: 15153.71 | AL102: 22644.9 | AM102: 25599.12 | AN102: 22188.45 | AO102: 25739.11 | AP102: 36110.75 | AQ102: 29935.4 | AR102: 34469.02 | AS102: 389673.24 | AU102: 389673.24 | AV102: 35596.59 | AW102: 30570.44 | AX102: 30458.95 | AY102: 24341.08 | AZ102: 25159.1 | BA102: 21972.84 | BB102: 26792.36 | BC102: 40882.8 | BD102: 40751.78 | BE102: 42565.23 | BF102: 42535.13 | BG102: 37545.12 | BH102: 399171.42 | BI102: 27406.85 | BJ102: 25454.03 | BK102: 49550.42 | BL102: 32643.5 | BM102: 28702.48 | BN102: 32448.52 | BO102: 25638.22 | BP102: 37651.53 | BQ102: 11507 | BR102: 36493.96 | BS102: 34366.01 | BT102: 68224.49 | BU102: =SUM(BI102:BT102) -> 410087.01 | BV102: 51314.04 | BW102: 72783.74 | BX102: 67027.82 | BY102: 62525.92 | BZ102: 64045.61 | CA102: 84919.31 | CB102: 86684.47 | CC102: 82521.31 | CD102: 76109.71 | CE102: 76823.53 | CF102: 102350.1 | CG102: 80301.13 | CH102: =SUM(BV102:CG102) -> 907406.69 | CI102: 69891.88 | CJ102: 81813.68 | CK102: 55654.67 | CL102: 60117.06 | CM102: 224742.23 | CN102: 262302.17 | CO102: 262146.89 | CP102: 97682.31 | CQ102: 63180.06 | CR102: 76505.7 | CS102: 78496.76 | CT102: 85888.43 | CU102: =SUM(CI102:CT102) -> 1418421.8 | CV102: 96895.32 | CW102: 89441.78 | CX102: 76053.54 | CY102: 84821.01 | CZ102: 77097.02 | DA102: 94621 | DB102: 97163.24 | DC102: 99351.11 | DD102: 101615.61 | DE102: 86408.93 | DF102: 93011.27 | DG102: 88265.77 | DH102: =SUM(CV102:DG102) -> 1084745.6 | DI102: 123448.79 | DJ102: 154259.59 | DK102: 169500.43 | DL102: 148203.41 | DM102: 137452.43 | DN102: 137844.69 | DO102: 161571.46 | DP102: 166037.98 | DQ102: 52826.68 | DR102: 188294.88 | DU102: =SUM(DI102:DT102) -> 1439440.3
A103: Depreciation - Right Of Use Asset | AG103: 0 | AH103: 0 | AI103: 0 | AJ103: 0 | AK103: 0 | AL103: 97151.73 | AM103: 97151.73 | AN103: 97151.73 | AO103: 97151.73 | AP103: 97151.73 | AQ103: 97151.73 | AR103: 97151.73 | AS103: 680062.11 | AU103: 680062.11 | AV103: 97151.73 | AW103: 97151.73 | AX103: 97151.73 | AY103: 97151.73 | AZ103: 97151.73 | BA103: 97151.73 | BB103: 97151.73 | BC103: 97151.74 | BD103: 97151.73 | BE103: 97151.73 | BF103: 97151.73 | BG103: 97151.73 | BH103: 1165820.8 | BI103: 97151.73 | BJ103: 97151.73 | BK103: 97151.73 | BL103: 97151.73 | BM103: 97151.73 | BN103: 97151.73 | BO103: 97151.73 | BP103: 97151.73 | BQ103: 89869 | BR103: 89868.51 | BS103: 92737.47 | BT103: 148100.26 | BU103: =SUM(BI103:BT103) -> 1197789.1 | BV103: 148100.26 | BW103: 148100.26 | BX103: 148100.26 | BY103: 148100.26 | BZ103: 148100.26 | CA103: 148100.26 | CB103: 148100.26 | CC103: 148100.26 | CD103: 148100.25 | CE103: 148100.26 | CF103: 148100.26 | CG103: 148100.26 | CH103: =SUM(BV103:CG103) -> 1777203.1 | CI103: 118608.47 | CJ103: 148100.26 | CK103: 121115.28 | CL103: 121115.3 | CM103: 121115.29 | CN103: 121115.31 | CO103: 121115.29 | CP103: 121115.31 | CQ103: 280744.66 | CR103: 254954.01 | CS103: 254953.99 | CT103: 254953.98 | CU103: =SUM(CI103:CT103) -> 2039007.1 | CV103: 240673.61 | CW103: 233144.79 | CX103: 233144.77 | CY103: 233144.8 | CZ103: 233144.77 | DA103: 233144.79 | DB103: 233144.77 | DC103: 269608.74 | DD103: 260492.66 | DE103: 260492.69 | DF103: 260492.69 | DG103: 260492.67 | DH103: =SUM(CV103:DG103) -> 2951121.8 | DI103: 285847.69 | DJ103: 285847.66 | DK103: 285847.69 | DL103: 285847.69 | DM103: 285847.67 | DN103: 285847.68 | DO103: 285847.67 | DP103: 285847.69 | DQ103: 285847.68 | DR103: 285847.67 | DU103: =SUM(DI103:DT103) -> 2858476.8
A104: Land Line & Installation Fees | B104: 10481.48 | C104: 1759.09 | D104: 927.6 | E104: 1576.96 | F104: 12723.29 | G104: 1245.14 | H104: 3690.65 | I104: 1558.81 | J104: 2317.43 | K104: 2234.47 | L104: 2539.69 | M104: 2254.32 | N104: 1950.29 | O104: 2086.95 | P104: 2039.47 | Q104: 1444.13 | R104: 3081.8 | S104: 26443.15 | T104: 3242.62 | U104: 3335 | V104: 3599.7 | W104: 4057.56 | X104: 6368.34 | Y104: 4327.53 | Z104: 8479.34 | AA104: 7950.87 | AB104: 6777.76 | AC104: 5333.17 | AD104: 3308.34 | AE104: 5439.03 | AF104: 62219.26 | AG104: 5089.93 | AH104: 4990.53 | AI104: 5570.48 | AJ104: 16251.18 | AK104: 9498.97 | AL104: 14879.57 | AM104: 17040.1 | AN104: 15280.24 | AO104: 20932.83 | AP104: 14921.8 | AQ104: 9096.67 | AR104: 17380.59 | AS104: 150932.89 | AU104: 150932.89 | AV104: 14060.5 | AW104: 9659.33 | AX104: 7906.66 | AY104: 9331.71 | AZ104: 10611.82 | BA104: 10539.27 | BB104: 10303.64 | BC104: 10076.75 | BD104: 11748.4 | BE104: 11208.47 | BF104: 9724.13 | BG104: 14402.9 | BH104: 129573.58 | BI104: 17413.01 | BJ104: 16356.66 | BK104: 18038.27 | BL104: 22979.35 | BM104: 21989.12 | BN104: 19147.56 | BO104: 20847.9 | BP104: 23565.09 | BQ104: 30879 | BR104: 25191.99 | BS104: 19555.08 | BT104: 23027.52 | BU104: =SUM(BI104:BT104) -> 258990.55 | BV104: 23476.87 | BW104: 25253.74 | BX104: 22898.71 | BY104: 31962.48 | BZ104: 54529.1 | CA104: 71413.8 | CB104: 83600.06 | CC104: 57931.75 | CD104: 129505.66 | CE104: 42884.42 | CF104: 119371.41 | CG104: 157985.44 | CH104: =SUM(BV104:CG104) -> 820813.44 | CI104: 110655.81 | CJ104: 76473.39 | CK104: 70269.03 | CL104: 73442.84 | CM104: 71394.72 | CN104: 90789.28 | CO104: 74323.1 | CP104: 119978.71 | CQ104: 174973.95 | CR104: 70521.46 | CS104: 87721.02 | CT104: 177186.16 | CU104: =SUM(CI104:CT104) -> 1197729.5 | CV104: 83029.78 | CW104: 99079.36 | CX104: 137294.68 | CY104: 152916.04 | CZ104: 185614.45 | DA104: 214951.93 | DB104: 205618.85 | DC104: 336129.16 | DD104: 295966.88 | DE104: 194807.96 | DF104: 241648.71 | DG104: 233714.08 | DH104: =SUM(CV104:DG104) -> 2380771.9 | DI104: 153316.27 | DJ104: 102904.07 | DK104: 117604.08 | DL104: 99798.9 | DM104: 115896.66 | DN104: 98276.3 | DO104: 103641.29 | DP104: 92427.92 | DQ104: 150828.25 | DR104: 46029.23 | DU104: 883865.49
A105: License Fees: Yodlee, SME finance association | B105: 61722.81 | C105: 14127.13 | D105: 13399.5 | E105: 13353.6 | F105: 148963.61 | G105: 13801.22 | H105: 13842.33 | I105: 12908.2 | J105: 12265.13 | K105: 7677.21 | L105: 14241.94 | M105: 14100.11 | N105: 13908.36 | O105: 14348.48 | P105: 14199.87 | Q105: 11592.86 | R105: 12281 | S105: 155166.71 | T105: 13126.24 | U105: 13344 | V105: 13622.68 | W105: 15074.72 | X105: 17454.99 | Y105: 15383.57 | Z105: 17845.73 | AA105: 17751.81 | AB105: 21529.55 | AC105: 21392.53 | AD105: 21279.47 | AE105: 25200.63 | AF105: 213005.92 | AG105: 26984.69 | AH105: 26453.27 | AI105: 25197.72 | AJ105: 25248.1 | AK105: 27545.99 | AL105: 23202.66 | AM105: 27208.3 | AN105: 30083.4 | AO105: 30229.72 | AP105: 33354.89 | AQ105: 34055.82 | AR105: 39345.65 | AS105: 348910.21 | AU105: 348910.21 | AV105: 44075.56 | AW105: 47789.64 | AX105: 47969.97 | AY105: 44622.87 | AZ105: 42584.49 | BA105: 44341.98 | BB105: 44346.04 | BC105: 46325.58 | BD105: 45153.38 | BE105: 48164.75 | BF105: 48369.21 | BG105: 50881.58 | BH105: 554625.05 | BI105: 51455.93 | BJ105: 49707.36 | BK105: 47993.31 | BL105: 47086.92 | BM105: 46323.91 | BN105: 45043.11 | BO105: 43923.18 | BP105: 50000.01 | BQ105: 54165 | BR105: 50497.92 | BS105: 52398.43 | BT105: 93857.67 | BU105: =SUM(BI105:BT105) -> 632452.75 | BV105: 50080.08 | BW105: 52045.9 | BX105: 7744.89 | BY105: 59177.64 | BZ105: 72613.82 | CA105: 62205.27 | CB105: 62737.45 | CC105: 65325 | CD105: 62291.96 | CE105: 57656.73 | CF105: 57484.74 | CG105: 63784.09 | CH105: =SUM(BV105:CG105) -> 673147.57 | CI105: 47380.11 | CJ105: 50148.94 | CK105: 52331.37 | CL105: 57695.2 | CM105: 57810.21 | CN105: 53223.03 | CO105: 59266.17 | CP105: 48616.33 | CQ105: 37891.42 | CR105: 56008.26 | CS105: 28897.47 | CT105: 39263.4 | CU105: =SUM(CI105:CT105) -> 588531.91 | CV105: 32127.34 | CW105: 36965.64 | CX105: 38122.7 | CY105: 6683.67 | CZ105: 34590.92 | DA105: 33525.75 | DB105: 32946.73 | DC105: 37206.64 | DD105: 27605.23 | DE105: 32212.78 | DF105: 31956.86 | DG105: 31240.01 | DH105: =SUM(CV105:DG105) -> 375184.27 | DI105: 31563.59 | DJ105: 32597.86 | DK105: 31245.79 | DL105: 29255 | DM105: 34969.21 | DN105: 34969.21 | DO105: 31769.47 | DP105: 28385.21 | DQ105: 37698.19 | DR105: 36615.21 | DU105: =SUM(DI105:DT105) -> 329068.74
A106: Webservice costs: Site Hosting, Security, Leads | B106: 55354.77 | C106: 9108.61 | D106: 15493.13 | E106: 12375.11 | F106: 107788.73 | G106: 11294.56 | H106: 16939.9 | I106: 11829.22 | J106: 10468.74 | K106: 8932.67 | L106: 10381.45 | M106: 10217.66 | N106: 10644.57 | O106: 11318.34 | P106: 11049.7 | Q106: 10431.76 | R106: 12382.38 | S106: 135890.95 | T106: 12260.41 | U106: 13001 | V106: 12864.98 | W106: 13322.36 | X106: 13837.86 | Y106: 13583.67 | Z106: 14019.32 | AA106: 13892.79 | AB106: 14483.64 | AC106: 14906.9 | AD106: 22453.9 | AE106: 16256.29 | AF106: 174883.12 | AG106: 17625.87 | AH106: 18377.21 | AI106: 37582.12 | AJ106: 61412.92 | AK106: 66643.04 | AL106: 72387.36 | AM106: 73866.36 | AN106: 107379.56 | AO106: 91494.83 | AP106: 91647.03 | AQ106: 90108.45 | AR106: 99404.86 | AS106: 827929.61 | AU106: 827929.61 | AV106: 125245.05 | AW106: 130402.08 | AX106: 131933.61 | AY106: 138083.66 | AZ106: 136577.85 | BA106: 134772.21 | BB106: 136968.84 | BC106: 136404.19 | BD106: 136683.72 | BE106: 143309.67 | BF106: 149350.57 | BG106: 125482.63 | BH106: 1625214.1 | BI106: 119267.15 | BJ106: 127518.73 | BK106: 117365.76 | BL106: 128114.83 | BM106: 145601 | BN106: 166617.42 | BO106: 248596.27 | BP106: 280117 | BQ106: 324658 | BR106: 349673.04 | BS106: 297886.53 | BT106: 424740.98 | BU106: =SUM(BI106:BT106) -> 2730156.7 | BV106: 397586.76 | BW106: 397638.77 | BX106: 472290.99 | BY106: 454225.95 | BZ106: 485782.73 | CA106: 495841.04 | CB106: 673493.56 | CC106: 656453.23 | CD106: 790430.45 | CE106: 804370.99 | CF106: 742637.8 | CG106: 1005014.1 | CH106: =SUM(BV106:CG106) -> 7375766.4 | CI106: 676633.05 | CJ106: 776346.52 | CK106: 907240.24 | CL106: 988747.35 | CM106: 957457.88 | CN106: 1056999.7 | CO106: 1117279.8 | CP106: 1190960.4 | CQ106: 1217062.6 | CR106: 1280034.7 | CS106: 1573320.8 | CT106: 1535430.4 | CU106: =SUM(CI106:CT106) -> 13277513 | CV106: 1732946.1 | CW106: 1730852.6 | CX106: 1887838.3 | CY106: 1704536.4 | CZ106: 1983716.3 | DA106: 2363950.3 | DB106: 1981834.5 | DC106: 2365324.4 | DD106: 2361901.8 | DE106: 2452103.1 | DF106: 1706672.8 | DG106: 2559558.7 | DH106: =SUM(CV106:DG106) -> 24831235 | DI106: 2691809.4 | DJ106: 2578977.2 | DK106: 2608617 | DL106: 2697808.5 | DM106: 2879216.5 | DN106: 2938656.6 | DO106: 2626563.4 | DP106: 2862442.5 | DQ106: 3059984.9 | DR106: 3121912.6 | DU106: =SUM(DI106:DT106) -> 28065989
A107: Total Rental & Communication | B107: =SUM(B102:B106) -> 242185.06 | C107: =SUM(C102:C106) -> 49354.32 | D107: =SUM(D102:D106) -> 53273.03 | E107: =SUM(E102:E106) -> 54637.47 | F107: =SUM(F102:F106) -> 463154.14 | G107: =SUM(G102:G106) -> 54492.74 | H107: =SUM(H102:H106) -> 62816.7 | I107: =SUM(I102:I106) -> 57044.63 | ... T107: =SUM(T102:T106) -> 63180.62 | U107: 70211 | V107: =SUM(V102:V106) -> 70713.41 | W107: =SUM(W102:W106) -> 73693.35 | X107: =SUM(X102:X106) -> 78828.7 | Y107: =SUM(Y102:Y106) -> 75522.04 | Z107: =SUM(Z102:Z106) -> 82922.05 | AA107: =SUM(AA102:AA106) -> 80971.94 | AB107: =SUM(AB102:AB106) -> 85181.24 | AC107: =SUM(AC102:AC106) -> 83239.82 | ... AE107: =SUM(AE102:AE106) -> 94053.38 | AF107: 948585.94 | AG107: 91588.67 | AH107: 95761.08 | AI107: 113154.35 | AJ107: 148112.7 | AK107: 118841.71 | AL107: 230266.22 | AM107: 240865.61 | AN107: 272083.38 | AO107: 265548.22 | AP107: 273186.2 | AQ107: 260348.07 | AR107: 287751.85 | AS107: 2397508.1 | AT107: 0 | AU107: 2397508.1 | AV107: 316129.43 | AW107: 315573.22 | AX107: 315420.92 | AY107: 313531.05 | AZ107: 312084.99 | BA107: 308778.03 | BB107: 315562.61 | BC107: 330841.06 | BD107: 331489.01 | BE107: 342399.85 | BF107: 347130.77 | BG107: 325463.96 | BH107: 3874404.9 | BI107: =SUM(BI102:BI106) -> 312694.67 | BJ107: =SUM(BJ102:BJ106) -> 316188.51 | BK107: =SUM(BK102:BK106) -> 330099.49 | BL107: =SUM(BL102:BL106) -> 327976.33 | BM107: =SUM(BM102:BM106) -> 339768.24 | BN107: =SUM(BN102:BN106) -> 360408.34 | BO107: =SUM(BO102:BO106) -> 436157.3 | BP107: =SUM(BP102:BP106) -> 488485.36 | ... BT107: =SUM(BT102:BT106) -> 757950.92 | BU107: =SUM(BI107:BT107) -> 5229476.1 | BV107: =SUM(BV102:BV106) -> 670558.01 | BW107: =SUM(BW102:BW106) -> 695822.41 | BX107: =SUM(BX102:BX106) -> 718062.67 | BY107: =SUM(BY102:BY106) -> 755992.25 | BZ107: =SUM(BZ102:BZ106) -> 825071.52 | CA107: =SUM(CA102:CA106) -> 862479.68 | CB107: =SUM(CB102:CB106) -> 1054615.8 | CC107: =SUM(CC102:CC106) -> 1010331.6 | ... CG107: =SUM(CG102:CG106) -> 1455185 | CH107: =SUM(BV107:CG107) -> 11554337 | CI107: =SUM(CI102:CI106) -> 1023169.3 | CJ107: =SUM(CJ102:CJ106) -> 1132882.8 | CK107: =SUM(CK102:CK106) -> 1206610.6 | CL107: =SUM(CL102:CL106) -> 1301117.8 | CM107: =SUM(CM102:CM106) -> 1432520.3 | CN107: =SUM(CN102:CN106) -> 1584429.5 | CO107: =SUM(CO102:CO106) -> 1634131.2 | CP107: =SUM(CP102:CP106) -> 1578353 | ... CT107: =SUM(CT102:CT106) -> 2092722.4 | CU107: =SUM(CI107:CT107) -> 18521204 | CV107: =SUM(CV102:CV106) -> 2185672.1 | CW107: =SUM(CW102:CW106) -> 2189484.2 | CX107: =SUM(CX102:CX106) -> 2372454 | CY107: =SUM(CY102:CY106) -> 2182101.9 | CZ107: =SUM(CZ102:CZ106) -> 2514163.5 | DA107: =SUM(DA102:DA106) -> 2940193.8 | DB107: =SUM(DB102:DB106) -> 2550708.1 | DC107: =SUM(DC102:DC106) -> 3107620 | ... DG107: =SUM(DG102:DG106) -> 3173271.3 | DH107: =SUM(CV107:DG107) -> 31623059 | DI107: =SUM(DI102:DI106) -> 3285985.7 | DJ107: =SUM(DJ102:DJ106) -> 3154586.4 | DK107: =SUM(DK102:DK106) -> 3212815 | DL107: =SUM(DL102:DL106) -> 3260913.5 | DM107: =SUM(DM102:DM106) -> 3453382.5 | DN107: =SUM(DN102:DN106) -> 3495594.5 | DO107: =SUM(DO102:DO106) -> 3209393.3 | DP107: =SUM(DP102:DP106) -> 3435141.3 | ... DT107: =SUM(DT102:DT106) -> 0 | DU107: =SUM(DI107:DT107) -> 33773698
A109: Travel
A110: Travel - Sales Team & Execs | B110: 8584.08 | C110: 0 | D110: 7641.96 | E110: 1733.03 | F110: 36961.04 | G110: 12457.71 | H110: 0 | I110: 210 | J110: =672+653.78 -> 1325.78 | K110: 0 | L110: 3180.18 | M110: 2995 | N110: 17689.69 | O110: 20555.64 | P110: 0 | Q110: 20649.42 | R110: 0 | S110: 79063.42 | T110: 0 | U110: 0 | V110: 0 | W110: 814 | X110: 690.7 | Y110: 0 | Z110: 2520.08 | AA110: 0 | AB110: 262 | AC110: 26383.77 | AD110: 30785.87 | AE110: 14013.82 | AF110: 75470.24 | AG110: 0 | AH110: 0 | AI110: 7010.72 | AJ110: 2323 | AK110: 12701.54 | AL110: 3734.08 | AM110: 0 | AN110: 36055.35 | AO110: 25270.3 | AP110: 0 | AQ110: 0 | AR110: 9068.94 | AS110: 96163.93 | AU110: 96163.93 | AV110: 0 | AW110: 0 | AX110: 23831.85 | AY110: 0 | AZ110: 0 | BA110: 0 | BB110: 3977.91 | BC110: 0 | BD110: 0 | BE110: 0 | BF110: 0 | BG110: 0 | BH110: 27809.76 | BI110: 0 | BJ110: 0 | BK110: 0 | BL110: 0 | BM110: 0 | BN110: 0 | BO110: 0 | BP110: 0 | BQ110: 18304 | BR110: 0 | BS110: 0 | BT110: 44758.42 | BU110: =SUM(BI110:BT110) -> 63062.42 | BV110: 0 | BW110: 10281.981 | BX110: 14912.79 | BY110: 13850 | BZ110: 10347.07 | CA110: 59106.97 | CB110: 59106.98 | CC110: 5456 | CD110: 17650.6 | CE110: 6724 | CF110: 0 | CG110: 158328.93 | CH110: =SUM(BV110:CG110) -> 355765.32 | CI110: 4903.56 | CJ110: 0 | CK110: 0 | CL110: 0 | CM110: 0 | CN110: 52298.36 | CO110: 13269 | CP110: 19692.98 | CQ110: 119156.2 | CR110: 226670.65 | CS110: 67845.2 | CT110: 26054.66 | CU110: =SUM(CI110:CT110) -> 529890.61 | DH110: =SUM(CV110:DG110) -> 0 | DI110: 0 | DJ110: 0 | DK110: 0 | DU110: =SUM(DI110:DT110) -> 0
A111: Total Travel | B111: =SUM(B110) -> 8584.08 | C111: =SUM(C110) -> 0 | D111: =SUM(D110) -> 7641.96 | E111: =SUM(E110) -> 1733.03 | F111: =SUM(F110) -> 36961.04 | G111: =SUM(G110) -> 12457.71 | H111: =SUM(H110) -> 0 | I111: =SUM(I110) -> 210 | ... S111: =SUM(S110) -> 79063.42 | T111: 0 | U111: 0 | V111: 0 | W111: =+W110 -> 814 | X111: =SUM(X110) -> 690.7 | Y111: 0 | Z111: =SUM(Z110) -> 2520.08 | AA111: =SUM(AA110) -> 0 | AB111: =SUM(AB110) -> 262 | AC111: =SUM(AC110) -> 26383.77 | AD111: =SUM(AD110) -> 30785.87 | AE111: =SUM(AE110) -> 14013.82 | AF111: 75470.24 | AG111: 0 | AH111: 0 | AI111: 7010.72 | AJ111: 2323 | AK111: 12701.54 | AL111: 3734.08 | AM111: 0 | AN111: 36055.35 | AO111: 25270.3 | AP111: 0 | AQ111: 0 | AR111: 9068.94 | AS111: 96163.93 | AT111: 0 | AU111: 96163.93 | AV111: 0 | AW111: 0 | AX111: 23831.85 | AY111: 0 | AZ111: 0 | BA111: 0 | BB111: 3977.91 | BC111: 0 | BD111: 0 | BE111: 0 | BF111: 0 | BG111: 0 | BH111: 27809.76 | BI111: =BI110 -> 0 | BJ111: =BJ110 -> 0 | BK111: =BK110 -> 0 | BL111: =BL110 -> 0 | BM111: =BM110 -> 0 | BN111: =BN110 -> 0 | BO111: =BO110 -> 0 | BP111: =BP110 -> 0 | ... BT111: =BT110 -> 44758.42 | BU111: =SUM(BI111:BT111) -> 63062.42 | BV111: =BV110 -> 0 | BW111: =BW110 -> 10281.981 | BX111: =BX110 -> 14912.79 | BY111: =BY110 -> 13850 | BZ111: =BZ110 -> 10347.07 | CA111: =CA110 -> 59106.97 | CB111: =CB110 -> 59106.98 | CC111: =CC110 -> 5456 | ... CG111: =CG110 -> 158328.93 | CH111: =SUM(BV111:CG111) -> 355765.32 | CI111: =CI110 -> 4903.56 | CJ111: =CJ110 -> 0 | CK111: =CK110 -> 0 | CL111: =CL110 -> 0 | CM111: =CM110 -> 0 | CN111: =CN110 -> 52298.36 | CO111: =CO110 -> 13269 | CP111: =CP110 -> 19692.98 | ... CT111: =CT110 -> 26054.66 | CU111: =SUM(CI111:CT111) -> 529890.61 | CV111: =CV110 -> 0 | DH111: =SUM(CV111:DG111) -> 0 | DI111: =SUM(CW111:DH111) -> 0 | DJ111: =SUM(CX111:DI111) -> 0 | DK111: =SUM(CY111:DJ111) -> 0 | DL111: 0 | DM111: 0 | DN111: 0 | DU111: =SUM(DI111:DT111) -> 0
A113: Total Credit Operating Expenses | B113: =(0+(0)+(B80)+(B92)+(B99)+(B107)+(B111))-(0) -> 895320.16 | C113: =(0+(0)+(C80)+(C92)+(C99)+(C107)+(C111))-(0) -> 510306.89 | D113: =(0+(0)+(D80)+(D92)+(D99)+(D107)+(D111))-(0) -> 338413.18 | E113: =(0+(0)+(E80)+(E92)+(E99)+(E107)+(E111))-(0) -> 376285.16 | F113: =(0+(0)+(F80)+(F92)+(F99)+(F107)+(F111))-(0) -> 3455838.5 | G113: =(0+(0)+(G80)+(G92)+(G99)+(G107)+(G111))-(0) -> 476924.93 | H113: =(0+(0)+(H80)+(H92)+(H99)+(H107)+(H111))-(0) -> 624796.49 | I113: =(0+(0)+(I80)+(I92)+(I99)+(I107)+(I111))-(0) -> 510908.88 | ... T113: =(0+(0)+(T80)+(T92)+(T99)+(T107)+(T111))-(0) -> 683825.89 | U113: 699642 | V113: =+V107+V99+V92+V80 -> 726650.71 | W113: =+W111+W107+W99+W92+W80 -> 759114.38 | X113: =+X111+X107+X99+X92+X80 -> 778199.9 | Y113: =+Y111+Y107+Y99+Y92+Y80 -> 848683.44 | Z113: =+Z111+Z107+Z99+Z92+Z80 -> 959215.94 | AA113: =+AA111+AA107+AA99+AA92+AA80 -> 1086449.9 | AB113: =+AB111+AB107+AB99+AB92+AB80 -> 1234889.5 | AC113: =+AC111+AC107+AC99+AC92+AC80 -> 1122582.4 | AD113: =+AD111+AD107+AD99+AD92+AD80 -> 1168428.7 | ... AF113: =+AF111+AF107+AF99+AF92+AF80 -> 11438200 | AG113: 1362386.5 | AH113: 1570994.2 | AI113: 1646517.3 | AJ113: 1704874.9 | AK113: 3195549.1 | AL113: 2704936.3 | AM113: 2539616.8 | AN113: 3273848.8 | AO113: 4091586.9 | AP113: 3886237.8 | AQ113: 3876124.7 | AR113: 4824519.8 | AS113: 34677193 | AT113: -1211435.4 | AU113: 33465758 | AV113: 4174848.5 | AW113: 2596896.6 | AX113: 2567545 | AY113: 2376478.7 | AZ113: 2821093.7 | BA113: 3091741.8 | BB113: 3400070.5 | BC113: 3580080.5 | BD113: 4002062.7 | BE113: 3598652.1 | BF113: 3622082.2 | BG113: 4400896.7 | BH113: 40232449 | BI113: =(0+(0)+('P&L -Dec25'!BI80)+('P&L -Dec25'!BI92)+('P&L -Dec25'!BI99)+('P&L -Dec25'!BI107))-(0)+BI111 -> 5790286 | BJ113: =(0+(0)+('P&L -Dec25'!BJ80)+('P&L -Dec25'!BJ92)+('P&L -Dec25'!BJ99)+('P&L -Dec25'!BJ107))-(0)+BJ111 -> 5301526.1 | BK113: =(0+(0)+('P&L -Dec25'!BK80)+('P&L -Dec25'!BK92)+('P&L -Dec25'!BK99)+('P&L -Dec25'!BK107))-(0)+BK111 -> 5735019 | BL113: =(0+(0)+('P&L -Dec25'!BL80)+('P&L -Dec25'!BL92)+('P&L -Dec25'!BL99)+('P&L -Dec25'!BL107))-(0)+BL111 -> 5614164.4 | BM113: =(0+(0)+('P&L -Dec25'!BM80)+('P&L -Dec25'!BM92)+('P&L -Dec25'!BM99)+('P&L -Dec25'!BM107))-(0)+BM111 -> 6657477.2 | BN113: =(0+(0)+('P&L -Dec25'!BN80)+('P&L -Dec25'!BN92)+('P&L -Dec25'!BN99)+('P&L -Dec25'!BN107))-(0)+BN111 -> 7051722.1 | BO113: =(0+(0)+('P&L -Dec25'!BO80)+('P&L -Dec25'!BO92)+('P&L -Dec25'!BO99)+('P&L -Dec25'!BO107))-(0)+BO111 -> 7736473.8 | BP113: =(0+(0)+('P&L -Dec25'!BP80)+('P&L -Dec25'!BP92)+('P&L -Dec25'!BP99)+('P&L -Dec25'!BP107))-(0)+BP111 -> 8173804.6 | ... BT113: =(0+(0)+('P&L -Dec25'!BT80)+('P&L -Dec25'!BT92)+('P&L -Dec25'!BT99)+('P&L -Dec25'!BT107))-(0)+BT111 -> 9764382.4 | BU113: =SUM(BI113:BT113) -> 85347478 | BV113: =(0+(0)+('P&L -Dec25'!BV80)+('P&L -Dec25'!BV92)+('P&L -Dec25'!BV99)+('P&L -Dec25'!BV107))-(0)+BV111 -> 9577123.9 | BW113: =(0+(0)+('P&L -Dec25'!BW80)+('P&L -Dec25'!BW92)+('P&L -Dec25'!BW99)+('P&L -Dec25'!BW107))-(0)+BW111 -> 8872219.4 | BX113: =(0+(0)+('P&L -Dec25'!BX80)+('P&L -Dec25'!BX92)+('P&L -Dec25'!BX99)+('P&L -Dec25'!BX107))-(0)+BX111 -> 11230186 | BY113: =(0+(0)+('P&L -Dec25'!BY80)+('P&L -Dec25'!BY92)+('P&L -Dec25'!BY99)+('P&L -Dec25'!BY107))-(0)+BY111 -> 11502873 | BZ113: =(0+(0)+('P&L -Dec25'!BZ80)+('P&L -Dec25'!BZ92)+('P&L -Dec25'!BZ99)+('P&L -Dec25'!BZ107))-(0)+BZ111 -> 10811473 | CA113: =(0+(0)+('P&L -Dec25'!CA80)+('P&L -Dec25'!CA92)+('P&L -Dec25'!CA99)+('P&L -Dec25'!CA107))-(0)+CA111 -> 11242101 | CB113: =(0+(0)+('P&L -Dec25'!CB80)+('P&L -Dec25'!CB92)+('P&L -Dec25'!CB99)+('P&L -Dec25'!CB107))-(0)+CB111 -> 12673315 | CC113: =(0+(0)+('P&L -Dec25'!CC80)+('P&L -Dec25'!CC92)+('P&L -Dec25'!CC99)+('P&L -Dec25'!CC107))-(0)+CC111 -> 15021575 | ... CG113: =(0+(0)+('P&L -Dec25'!CG80)+('P&L -Dec25'!CG92)+('P&L -Dec25'!CG99)+('P&L -Dec25'!CG107))-(0)+CG111 -> 13787230 | CH113: =SUM(BV113:CG113) -> 1.4787357e+08 | CI113: =(0+(0)+('P&L -Dec25'!CI80)+('P&L -Dec25'!CI92)+('P&L -Dec25'!CI99)+('P&L -Dec25'!CI107))-(0)+CI111 -> 14314013 | CJ113: =(0+(0)+('P&L -Dec25'!CJ80)+('P&L -Dec25'!CJ92)+('P&L -Dec25'!CJ99)+('P&L -Dec25'!CJ107))-(0)+CJ111 -> 13173883 | CK113: =(0+(0)+('P&L -Dec25'!CK80)+('P&L -Dec25'!CK92)+('P&L -Dec25'!CK99)+('P&L -Dec25'!CK107))-(0)+CK111 -> 13244164 | CL113: =(0+(0)+('P&L -Dec25'!CL80)+('P&L -Dec25'!CL92)+('P&L -Dec25'!CL99)+('P&L -Dec25'!CL107))-(0)+CL111 -> 15309154 | CM113: =(0+(0)+('P&L -Dec25'!CM80)+('P&L -Dec25'!CM92)+('P&L -Dec25'!CM99)+('P&L -Dec25'!CM107))-(0)+CM111 -> 17118268 | CN113: =(0+(0)+('P&L -Dec25'!CN80)+('P&L -Dec25'!CN92)+('P&L -Dec25'!CN99)+('P&L -Dec25'!CN107))-(0)+CN111 -> 17013401 | CO113: =(0+(0)+('P&L -Dec25'!CO80)+('P&L -Dec25'!CO92)+('P&L -Dec25'!CO99)+('P&L -Dec25'!CO107))-(0)+CO111 -> 17944526 | CP113: =(0+(0)+('P&L -Dec25'!CP80)+('P&L -Dec25'!CP92)+('P&L -Dec25'!CP99)+('P&L -Dec25'!CP107))-(0)+CP111 -> 19332658 | ... CT113: =(0+(0)+('P&L -Dec25'!CT80)+('P&L -Dec25'!CT92)+('P&L -Dec25'!CT99)+('P&L -Dec25'!CT107))-(0)+CT111 -> 21241247 | CU113: =SUM(CI113:CT113) -> 2.0634514e+08 | CV113: =(0+(0)+('P&L -Dec25'!CV80)+('P&L -Dec25'!CV92)+('P&L -Dec25'!CV99)+('P&L -Dec25'!CV107))-(0)+CV111 -> 18533192 | CW113: =(0+(0)+('P&L -Dec25'!CW80)+('P&L -Dec25'!CW92)+('P&L -Dec25'!CW99)+('P&L -Dec25'!CW107))-(0)+CW111 -> 20787403 | CX113: =(0+(0)+('P&L -Dec25'!CX80)+('P&L -Dec25'!CX92)+('P&L -Dec25'!CX99)+('P&L -Dec25'!CX107))-(0)+CX111 -> 21656984 | CY113: =(0+(0)+('P&L -Dec25'!CY80)+('P&L -Dec25'!CY92)+('P&L -Dec25'!CY99)+('P&L -Dec25'!CY107))-(0)+CY111 -> 19729860 | CZ113: =(0+(0)+('P&L -Dec25'!CZ80)+('P&L -Dec25'!CZ92)+('P&L -Dec25'!CZ99)+('P&L -Dec25'!CZ107))-(0)+CZ111 -> 21988496 | DA113: =(0+(0)+('P&L -Dec25'!DA80)+('P&L -Dec25'!DA92)+('P&L -Dec25'!DA99)+('P&L -Dec25'!DA107))-(0)+DA111 -> 23216229 | DB113: =(0+(0)+('P&L -Dec25'!DB80)+('P&L -Dec25'!DB92)+('P&L -Dec25'!DB99)+('P&L -Dec25'!DB107))-(0)+DB111 -> 23802193 | DC113: =(0+(0)+('P&L -Dec25'!DC80)+('P&L -Dec25'!DC92)+('P&L -Dec25'!DC99)+('P&L -Dec25'!DC107))-(0)+DC110 -> 24665148 | DD113: =(0+(0)+('P&L -Dec25'!DD80)+('P&L -Dec25'!DD92)+('P&L -Dec25'!DD99)+('P&L -Dec25'!DD107))-(0)+DD111 -> 24639906 | DE113: =(0+(0)+('P&L -Dec25'!DE80)+('P&L -Dec25'!DE92)+('P&L -Dec25'!DE99)+('P&L -Dec25'!DE107))-(0)+DE111 -> 22700626 | DF113: =(0+(0)+('P&L -Dec25'!DF80)+('P&L -Dec25'!DF92)+('P&L -Dec25'!DF99)+('P&L -Dec25'!DF107))-(0)+DF111 -> 20696203 | DG113: =(0+(0)+('P&L -Dec25'!DG80)+('P&L -Dec25'!DG92)+('P&L -Dec25'!DG99)+('P&L -Dec25'!DG107))-(0)+DG111 -> 24186422 | DH113: =SUM(CV113:DG113) -> 2.6660266e+08 | DI113: =(0+(0)+('P&L -Dec25'!DI80)+('P&L -Dec25'!DI92)+('P&L -Dec25'!DI99)+('P&L -Dec25'!DI107))-(0)+DI111 -> 22923196 | DJ113: =(0+(0)+('P&L -Dec25'!DJ80)+('P&L -Dec25'!DJ92)+('P&L -Dec25'!DJ99)+('P&L -Dec25'!DJ107))-(0)+DJ111 -> 22252173 | DK113: =(0+(0)+('P&L -Dec25'!DK80)+('P&L -Dec25'!DK92)+('P&L -Dec25'!DK99)+('P&L -Dec25'!DK107))-(0)+DK111 -> 23683155 | DL113: =(0+(0)+('P&L -Dec25'!DL80)+('P&L -Dec25'!DL92)+('P&L -Dec25'!DL99)+('P&L -Dec25'!DL107))-(0)+DL111 -> 23039312 | DM113: =(0+(0)+('P&L -Dec25'!DM80)+('P&L -Dec25'!DM92)+('P&L -Dec25'!DM99)+('P&L -Dec25'!DM107))-(0)+DM111 -> 24926382 | DN113: =(0+(0)+('P&L -Dec25'!DN80)+('P&L -Dec25'!DN92)+('P&L -Dec25'!DN99)+('P&L -Dec25'!DN107))-(0)+DN111 -> 25686280 | DO113: =(0+(0)+('P&L -Dec25'!DO80)+('P&L -Dec25'!DO92)+('P&L -Dec25'!DO99)+('P&L -Dec25'!DO107))-(0)+DO111 -> 23134141 | DP113: =(0+(0)+('P&L -Dec25'!DP80)+('P&L -Dec25'!DP92)+('P&L -Dec25'!DP99)+('P&L -Dec25'!DP107))-(0)+DP111 -> 24620903 | ... DT113: =(0+(0)+('P&L -Dec25'!DT80)+('P&L -Dec25'!DT92)+('P&L -Dec25'!DT99)+('P&L -Dec25'!DT107))-(0)+DT111 -> 0 | DU113: =SUM(DI113:DT113) -> 2.4532516e+08
A115: Non-Credit Operating Expenses
A119: Branding | CB119: 0 | CC119: 0 | CD119: 0 | CE119: 0 | CF119: 0 | CG119: 0 | CH119: =SUM(BV119:CG119) -> 0 | CI119: 500000 | CJ119: 491129.39 | CK119: 590000 | CL119: 129900 | CM119: 181148.69 | CN119: 1976303.7 | CO119: 1715799.9 | CP119: 2347843.4 | CQ119: 1079959.5 | CR119: 1266888.2 | CS119: 200000 | CT119: 341468.25 | CU119: =SUM(CI119:CT119) -> 10820441 | CV119: 1124181.5 | CW119: 766052.53 | CX119: 201020 | CY119: 3689366.6 | CZ119: 2927448.8 | DA119: 3418508.7 | DB119: 3614065.1 | DC119: 1882176.7 | DD119: 1897536.9 | DE119: 1901800.1 | DF119: 1901800.1 | DG119: 1811805.7 | DH119: =SUM(CV119:DG119) -> 25135763 | DI119: 1295027.6 | DJ119: 1003250 | DK119: 885761.28 | DL119: 1583660.6 | DM119: 1474659.4 | DN119: 2042482.3 | DO119: 2733094.6 | DP119: 3076014.7 | DQ119: 2505374.2 | DR119: 2419803.4 | DU119: =SUM(DI119:DT119) -> 19019128
A123: General admin
A124: General admin | CB124: 0 | CC124: 0 | CD124: 0 | CE124: 0 | CF124: 0 | CG124: 0 | CH124: =SUM(BV124:CG124) -> 0 | CI124: 18646.24 | CJ124: 16245.63 | CK124: 16306.47 | CL124: =17541.9+0.75 -> 17542.65 | CM124: =18579.89+0.75 -> 18580.64 | CN124: 24184.81 | CO124: 21796.57 | CP124: 20596.37 | CQ124: 20946.02 | CR124: 22852.78 | CS124: 20262.28 | CT124: 18459.43 | CU124: =SUM(CI124:CT124) -> 236419.89 | CV124: 21064.09 | CW124: 28795.5 | CX124: 27659.31 | CY124: 25226.52 | CZ124: 27601.3 | DA124: 24479.53 | DB124: 24599.61 | DC124: 28402.08 | DD124: 27136 | DE124: 29290.55 | DF124: 25421 | DG124: 28727 | DH124: =SUM(CV124:DG124) -> 318402.49 | DI124: 108119 | DJ124: 95326 | DK124: 116100 | DL124: 148154 | DM124: 231280 | DN124: 182163 | DO124: 225223 | DP124: 103134 | DQ124: 288643 | DR124: 128297 | DU124: =SUM(DI124:DT124) -> 1626439
A125: Initial setup costs | BY125: 48397.79 | BZ125: 10393.18 | CA125: 68841.53 | CB125: 0 | CC125: 801 | CD125: 1739 | CE125: 0 | CF125: 0 | CG125: 0 | CH125: =SUM(BV125:CG125) -> 130172.5 | CI125: 145 | CJ125: 50 | CK125: 700 | CL125: 13000 | CM125: -10000 | CN125: 1000 | CO125: 918.65 | CP125: 3410 | CQ125: 0 | CR125: 0 | CS125: 0 | CT125: 2269 | CU125: =SUM(CI125:CT125) -> 11492.65 | CV125: 1000 | CW125: 0 | CX125: 0 | CY125: 0 | CZ125: 0 | DA125: 0 | DB125: 0 | DC125: 0 | DD125: 0 | DE125: 0 | DF125: 0 | DG125: 0 | DH125: =SUM(CV125:DG125) -> 1000 | DI125: 0 | DJ125: 0 | DK125: 0 | DL125: 0 | DM125: 0 | DN125: 0 | DO125: 0 | DP125: 0 | DQ125: 0 | DR125: 0 | DS125: 0 | DT125: 0 | DU125: =SUM(DI125:DT125) -> 0
A126: Total -General Admin | T126: =SUM(T124:T125) -> 0 | U126: =SUM(U124:U125) -> 0 | V126: =SUM(V124:V125) -> 0 | W126: =SUM(W124:W125) -> 0 | X126: =SUM(X124:X125) -> 0 | Y126: =SUM(Y124:Y125) -> 0 | Z126: =SUM(Z124:Z125) -> 0 | AA126: =SUM(AA124:AA125) -> 0 | ... DU126: =SUM(DU124:DU125) -> 1626439
A129: Marketing | BQ129: 5000 | BR129: 11009.17 | BS129: 14105.13 | BT129: 31022.72 | BU129: =SUM(BI129:BT129) -> 61137.02 | BV129: 60773.12 | BW129: 49252.16 | BX129: 136654.71 | BY129: 250470.55 | BZ129: 484799.51 | CA129: 0 | CB129: 42839.06 | CC129: 7907.29 | CD129: 7911.04 | CE129: 4901.87 | CF129: 4901.87 | CG129: 4901.87 | CH129: =SUM(BV129:CG129) -> 1055313.1 | CI129: 126822.71 | CJ129: 179897.69 | CK129: 177525.82 | CL129: =407425.82-129900 -> 277525.82 | CM129: 973067.32 | CN129: 338789.82 | CO129: 193782.88 | CP129: 300506.16 | CQ129: 238123.41 | CR129: 190077.2 | CS129: 188813.34 | CT129: 263125.48 | CU129: =SUM(CI129:CT129) -> 3448057.7 | CV129: 151127.56 | CW129: 99995.27 | CX129: 87140.76 | CY129: 244609.3 | CZ129: 346661.82 | DA129: 254622.65 | DB129: 287812.98 | DC129: 163841.65 | DD129: 491203.98 | DE129: 318585.79 | DF129: 337723.8 | DG129: 242655.54 | DH129: =SUM(CV129:DG129) -> 3025981.1 | DI129: 170351.35 | DJ129: 114926.28 | DK129: 120826.5 | DL129: 372807.43 | DM129: 83200.71 | DN129: 270207.5 | DO129: 152473.16 | DP129: 116731.67 | DQ129: -7146.5 | DR129: 115570.84 | DU129: =SUM(DI129:DT129) -> 1509948.9
DH130: =SUM(CV130:DG130) -> 0 | DO130: 695877.74 | DU130: =SUM(DI130:DT130) -> 695877.74
A131: Monthly fees | BQ131: 1906 | BR131: 4516.51 | BS131: 6548.82 | BT131: 6433.42 | BU131: =SUM(BI131:BT131) -> 19404.75 | BV131: 6461.3 | BW131: 46565.78 | BX131: -34047.3 | BY131: 7138.07 | BZ131: 7302.31 | CA131: 7467.08 | CB131: 7577.86 | CC131: 10017.33 | CD131: 6669 | CE131: 5272.57 | CF131: 5191.97 | CG131: 5297.3 | CH131: =SUM(BV131:CG131) -> 80913.27 | CI131: 628621.26 | CJ131: 672338 | CK131: 686820 | CL131: 682323.32 | CM131: 677183.83 | CN131: 682085.7 | CO131: 698138.54 | CP131: 737117.08 | CQ131: 738905.76 | CR131: 735366.59 | CS131: 741727.37 | CT131: 765140.06 | CU131: =SUM(CI131:CT131) -> 8445767.5 | CV131: 702591.07 | CW131: 722199.25 | CX131: 722556.6 | CY131: 715413.45 | CZ131: 495590.77 | DA131: 631130.92 | DB131: 544813.86 | DC131: 93157.3 | DD131: 634228.89 | DE131: 587278.81 | DF131: 844388.81 | DG131: 968082.74 | DH131: =SUM(CV131:DG131) -> 7661432.5 | DI131: 1111337.8 | DJ131: 849165.29 | DK131: 1122352.3 | DL131: 1285172.8 | DM131: 1182810.2 | DN131: 1529310.9 | DO131: 741377.74 | DP131: 906062.7 | DQ131: 807483.91 | DR131: 794618.86 | DU131: =SUM(DI131:DT131) -> 10329692
DH132: =SUM(CV132:DG132) -> 0 | DO132: 125347 | DU132: =SUM(DI132:DT132) -> 125347
A133: Payroll | BW133: 147900 | BX133: 79365 | BY133: 77601 | BZ133: 85290 | CA133: 123118 | CB133: 106400 | CC133: 41764.24 | CD133: 64250 | CE133: 64250 | CF133: 64250 | CG133: 64250 | CH133: =SUM(BV133:CG133) -> 918438.24 | CI133: 1429612.6 | CJ133: 1331494.3 | CK133: 1399146.5 | CL133: 1401318.6 | CM133: 1449250.6 | CN133: 1464477.7 | CO133: 1347672.1 | CP133: 1773802.5 | CQ133: 1806996.2 | CR133: 1843678.2 | CS133: 1844707.2 | CT133: 1853515.1 | CU133: =SUM(CI133:CT133) -> 18945672 | CV133: 2021862.1 | CW133: 1954668.8 | CX133: 2345365.8 | CY133: 2301923.1 | CZ133: 2396364.1 | DA133: 2500244.6 | DB133: 2537190.1 | DC133: 2552743.8 | DD133: 2177312.8 | DE133: 2600229.3 | DF133: 2412770 | DG133: 2903937 | DH133: =SUM(CV133:DG133) -> 28704611 | DI133: 1881460 | DJ133: 1931788 | DK133: 1942512 | DL133: 1538404 | DM133: 1817056 | DN133: 1761344 | DO133: 1763672 | DP133: 1861773 | DQ133: 2056817 | DR133: 1836901 | DU133: =SUM(DI133:DT133) -> 18391727
DH134: =SUM(CV134:DG134) -> 0 | DO134: 467116.93 | DU134: =SUM(DI134:DT134) -> 467116.93
A135: Rental & communication | CB135: 0 | CC135: 0 | CD135: 0 | CE135: 0 | CF135: 0 | CG135: 0 | CH135: =SUM(BV135:CG135) -> 0 | CI135: 91676.19 | CJ135: 51827.24 | CK135: 74437.92 | CL135: 77670.35 | CM135: 118123.45 | CN135: 131144.49 | CO135: 128514.16 | CP135: 99390.04 | CQ135: 106563.54 | CR135: 106390.2 | CS135: 111162.08 | CT135: 131081.61 | CU135: =SUM(CI135:CT135) -> 1227981.3 | CV135: 140870.32 | CW135: 152877.25 | CX135: 161538.5 | CY135: 197207.32 | CZ135: 178587.37 | DA135: 193308.19 | DB135: 189624.61 | DC135: 235277.26 | DD135: 228560.25 | DE135: 191307.56 | DF135: 209037 | DG135: 204571 | DH135: =SUM(CV135:DG135) -> 2282766.6 | DI135: 127788 | DJ135: 123795 | DK135: 129943 | DL135: 121105 | DM135: 123484 | DN135: 119779 | DO135: 125347 | DP135: 123168 | DQ135: 113383 | DR135: 119746 | DU135: =SUM(DI135:DT135) -> 1227538
DD136: 0 | DE136: 0 | DH136: =SUM(CV136:DG136) -> 0 | DU136: =SUM(DI136:DT136) -> 0
A137: Transactional write offs | CV137: 0 | CW137: 0 | CX137: 0 | CY137: 0 | CZ137: 50056.98 | DA137: 14087.94 | DB137: 1727.22 | DC137: 0 | DD137: 0 | DE137: 17301.5 | DF137: 68654.64 | DG137: 7335.69 | DH137: =SUM(CV137:DG137) -> 159163.97 | DI137: 88694.54 | DJ137: 35 | DK137: 3256.1 | DL137: 0 | DM137: -677.48 | DN137: -0.44 | DO137: -2551.19 | DP137: 0 | DQ137: -6.89 | DR137: 0 | DU137: =SUM(DI137:DT137) -> 88749.64
...

Sheet Balance Sheet - Dec25
A1: Balance Sheet
A2: Lula Lend (Pty) Ltd
A3: As at 31 December 2025
B5: Note | C5: 46022 | E5: 45991 | G5: 45961 | I5: 45930 | K5: 45900 | M5: 45869 | O5: 45838 | Q5: 45808 | S5: 45777 | U5: 45747 | W5: 45716 | Y5: 45688 | AA5: 45657 | AC5: 45626 | AE5: 45596 | AG5: 45565 | AI5: 45535 | AK5: 45504 | AM5: 45473 | AO5: 45443 | AQ5: 45412 | AS5: 45382 | AU5: 45351 | AW5: 45322 | AY5: 45291 | BA5: 45260 | BC5: 45230 | BE5: 45199 | BG5: 45169 | BI5: 45138 | BK5: 45107 | BM5: 45077 | BO5: 45046 | BQ5: 45016 | BS5: 44985 | BU5: 44957 | BW5: 44926 | BY5: 44895 | CA5: 44865 | CC5: 44834 | CE5: 44804 | CG5: 44773 | CI5: 44742 | CK5: 44712 | CM5: 44681 | CO5: 44651 | CQ5: 44620 | CS5: 31 Jan 2022 | CU5: 31 Dec 2021 | CW5: 30 Nov 2021 | CY5: 31 Oct 2021 | DA5: 30 Sep 2021 | DC5: 31 Aug 2021 | DE5: 31 Jul 2021 | DG5: 30 Jun 2021 | DI5: 31 May 2021 | DK5: 30 April 2021 | DM5: 31 March 2021 | DO5: 28 February 2021 | DQ5: 31 January 2021 | DS5: 31 December 2020 | DU5: 30 November 2020 | DW5: 31 October 2020 | DY5: 30 September 2020 | EA5: 31 August 2020 | EC5: 31 July 2020 | EE5: 30 June 2020 | EG5: 31 May 2020 | EI5: 30 April 2020 | EK5: 31 March 2020 | EM5: 29 February 2020 | EO5: 31 January 2020 | EQ5: 31 December 2019 | ES5: 30 November 2019 | EU5: 31 October 2019 | EW5: 30 September 2019 | EY5: 31 August 2019 | FA5: 31 July 2019 | FC5: 30 June 2019 | FE5: 31 May 2019 | FG5: 30 April 2019 | FI5: 31 March 2019 | FK5: 28 February 2019 | FM5: 31 January 2019 | FO5: 31 December 2018 | FQ5: 30 November 2018 | FS5: 31 October 2018 | FU5: 30 September 2018 | FW5: 31 August 2018 | FY5: 31 July 2018 | GA5: 30 June 2018 | GC5: 31 May 2018 | GE5: 30 April 2018 | GG5: 31 March 2018 | GI5: 28 February 2018 | GK5: 31 January 2018 | GM5: 31 December 2017 | GO5: 30 November 2017 | GQ5: 31 October 2017 | GS5: 30 September 2017 | GU5: 31 August 2017 | GW5: 31 July 2017 | GY5: 30 June 2017 | HA5: 31 May 2017 | HC5: 30 Apr 2017 | HE5: 31 Mar 2017 | HG5: 28 Feb 2017
A7: Assets | C7: =SUM(C8:C17) -> 2.0721263e+09 | E7: =SUM(E8:E17) -> 1.9914537e+09 | G7: =SUM(G8:G17) -> 1.9477409e+09 | I7: 1.9813908e+09 | K7: 2.1090189e+09 | M7: =SUM(M8:M17) -> 2.1518578e+09 | O7: =SUM(O8:O17) -> 2.192448e+09 | Q7: =SUM(Q8:Q17) -> 2.2005295e+09 | S7: =SUM(S8:S17) -> 2.2375257e+09 | U7: =SUM(U8:U17) -> 2.0526214e+09 | W7: =SUM(W8:W17) -> 2.1675086e+09 | Y7: 2.2231317e+09 | AA7: 2.25e+09 | AC7: 2.306836e+09 | AE7: 2.32028e+09 | AG7: 2.2023167e+09 | AI7: 2.2505996e+09 | AK7: 2.0962932e+09 | AM7: 2.100169e+09 | AO7: 2.0503994e+09 | AQ7: 1.9190766e+09 | AS7: 1.8444264e+09 | AU7: =SUM(AU8:AU17) -> 1.6895661e+09 | AW7: 1.7178849e+09 | AY7: 1.7339179e+09 | BA7: 1.5616749e+09 | BC7: 1.5358321e+09 | BE7: 1.429968e+09 | BG7: 1.2772405e+09 | BI7: 1.2549291e+09 | BK7: 1.2300931e+09 | BM7: 1.2357726e+09 | BO7: 1.2053235e+09 | BQ7: =SUM(BQ8:BQ17) -> 5.5468793e+08 | BS7: =SUM(BS8:BS17) -> 1.0772012e+09 | BU7: 1.1831534e+09 | BW7: 8.2663888e+08 | BY7: 8.2024724e+08 | CA7: 7.3039614e+08 | CC7: 7.2894163e+08 | CE7: 7.4957229e+08 | CG7: 7.5474413e+08 | CI7: 6.5282699e+08 | CK7: 6.4966137e+08 | CM7: 6.4393881e+08 | CO7: =SUM(CO8:CO17) -> 6.4783466e+08 | CQ7: =SUM(CQ8:CQ17) -> 6.0766085e+08 | CS7: =SUM(CS8:CS17) -> 5.7276029e+08 | CU7: =SUM(CU8:CU17) -> 4.9987402e+08 | CW7: =SUM(CW8:CW17) -> 5.1305868e+08 | CY7: =SUM(CY8:CY17) -> 5.0840609e+08 | DA7: =SUM(DA8:DA17) -> 4.2506581e+08 | DC7: =SUM(DC8:DC17) -> 4.2511854e+08 | DE7: =SUM(DE8:DE17) -> 3.9147582e+08 | DG7: =SUM(DG8:DG17) -> 3.5750725e+08 | DI7: =SUM(DI8:DI17) -> 3.1940397e+08 | DK7: =SUM(DK8:DK17) -> 3.2303099e+08 | DM7: =SUM(DM8:DM17) -> 3.0301033e+08 | DO7: 3.0165104e+08 | DQ7: 2.7014793e+08 | DS7: 2.6908846e+08 | DU7: 2.8471434e+08 | DW7: 3.0747512e+08 | DY7: 3.1955354e+08 | EA7: 2.703074e+08 | EC7: 2.6770201e+08 | EE7: 2.692046e+08 | EG7: 2.6856269e+08 | EI7: 2.674109e+08 | EK7: 2.7211391e+08 | EM7: 2.7739587e+08 | EO7: 2.7980385e+08 | EQ7: 2.7763278e+08 | ES7: 2.4412734e+08 | EU7: 1.996623e+08 | EW7: 1.7702124e+08 | EY7: 1.7434507e+08 | FA7: 1.7638416e+08 | FC7: 1.7994533e+08 | FE7: 90524983 | FG7: 89224776 | FI7: 87836057 | FK7: 76859702 | FM7: 76851290 | FO7: 80968553 | FQ7: 65961033 | FS7: 67506267 | FU7: 46447928 | FW7: 41982557 | FY7: 38595572 | GA7: 33396339 | GC7: 33009429 | GE7: 31529369 | GG7: 31428514 | GI7: 31020182 | GK7: 27087750 | GM7: 27071748 | GO7: 28067168 | GQ7: 27425147 | GS7: 24771482 | GU7: 25119066 | GW7: 24440237 | GY7: 24597276 | HA7: 22438710 | HC7: 22129893 | HE7: 22332816 | HG7: 22737686
A8: Bank | C8: 46703517 | E8: 38038011 | G8: 38057566 | I8: 40296682 | K8: 41380623 | M8: 43032626 | O8: 66618857 | Q8: 49675407 | S8: 26615001 | U8: 56762148 | W8: 41210243 | Y8: 32658375 | AA8: 32579934 | AC8: 41195859 | AE8: 63666235 | AG8: 34322888 | AI8: 38074906 | AK8: 23161933 | AM8: 72008771 | AO8: 43705687 | AQ8: 27058869 | AS8: 38076302 | AU8: 8466107 | AW8: 19892582 | AY8: 26206943 | BA8: 22515441 | BC8: 1.6100768e+08 | BE8: 59079175 | BG8: 22780795 | BI8: 42452571 | BK8: 25095351 | BM8: 23997635 | BO8: 22517338 | BQ8: 11510023 | BS8: 3.1149569e+08 | BU8: 4.1630095e+08 | BW8: 91652756 | BY8: 70735831 | CA8: 47435565 | CC8: 62296602 | CE8: 122025858 | CG8: 150142123 | CI8: 12395298 | CK8: 11578254 | CM8: 14314168 | CO8: 46108806 | CQ8: 19282406 | CS8: 16343471 | CU8: 13283191 | CW8: 4109352 | CY8: 11430255 | DA8: 6354640.8 | DC8: 6912516.5 | DE8: 6908378.6 | DG8: 24967153 | DI8: 6726657.9 | DK8: 5702844.1 | DM8: 4764699.1 | DO8: 5925577.5 | DQ8: 6977360.1 | DS8: 8175547.1 | DU8: 6134514.7 | DW8: 5407838.8 | DY8: 3296504.7 | EA8: 23306833 | EC8: 24640200 | EE8: 28070477 | EG8: 24530681 | EI8: 22040176 | EK8: 27937729 | EM8: 35049425 | EO8: 50771438 | EQ8: 51911162 | ES8: 21227343 | EU8: 5484862.9 | EW8: 6552421.6 | EY8: 7425167.5 | FA8: 47740848 | FC8: 21050056 | FE8: 8496771.5 | FG8: 7801128.6 | FI8: 18355518 | FK8: 4232869.6 | FM8: 5660186.8 | FO8: 13730334 | FQ8: 7236672.8 | FS8: 19226142 | FU8: 4978040.5 | FW8: 3321017.8 | FY8: 4084405.6 | GA8: 3118219.2 | GC8: 1498945.3 | GE8: 2908466 | GG8: 3644314.4 | GI8: 3766000.9 | GK8: 1372328 | GM8: 2441615.5 | GO8: 3155860.5 | GQ8: 2037962.8 | GS8: 1847396.5 | GU8: 1715156.2 | GW8: 1006738.1 | GY8: 1605637.7 | HA8: 493989.11 | HC8: 1067168.5 | HE8: 831169.98 | HG8: 1817724
A9: Investment Accounts | B9: 5. | C9: ='Notes - Dec25'!C42 -> 1.7070692e+08 | E9: ='Notes - Dec25'!E42 -> 50807984 | G9: ='Notes - Dec25'!G42 -> 81780346 | I9: 74237361 | K9: 1.935832e+08 | M9: 2.0957524e+08 | O9: 2.3852626e+08 | Q9: 2.3021314e+08 | S9: 2.8414521e+08 | U9: 43436803 | W9: 1.0372029e+08 | Y9: 1.2971521e+08 | AA9: 1.384414e+08 | AC9: 1.0728823e+08 | AE9: 1.2740355e+08 | AG9: 97741476 | AI9: ='Notes - Dec25'!AE42 -> 1.2740355e+08 | AK9: 67042340 | AM9: 85725012 | AO9: 1.1974487e+08 | AQ9: 52837446 | AS9: 11875443 | AU9: 1063217.3 | AW9: 1.0979233e+08 | AY9: 2.1667587e+08 | BA9: 88815846 | BC9: 60153463 | BE9: 1.2689133e+08 | BG9: 70416172 | BI9: 1.1620261e+08 | BK9: 1.565131e+08 | BM9: 221534203 | BO9: 2.5022921e+08 | BQ9: 334580676 | BS9: 248861.47 | BU9: 247470.72 | BW9: 246129.7 | BY9: 396673.75 | CA9: 5775722.5 | CC9: 5741456 | CE9: 5710596 | CG9: 5680126 | CI9: 64402412 | CK9: 100160401 | CM9: 1.2366704e+08 | CO9: ='Notes - Dec25'!CO42 -> 1.1014141e+08 | CQ9: ='Notes - Dec25'!CQ42 -> 1.1579483e+08 | CS9: ='Notes - Dec25'!CS42 -> 1.2406481e+08 | CU9: ='Notes - Dec25'!CU42 -> 61352517 | CW9: =+'Notes - Dec25'!CW42 -> 79548039 | CY9: =+'Notes - Dec25'!CY42 -> 1.0847554e+08 | DA9: =+'Notes - Dec25'!DA42 -> 57354789 | DC9: =+'Notes - Dec25'!DC42 -> 87143010 | DE9: =+'Notes - Dec25'!DE42 -> 83247084 | DG9: =+'Notes - Dec25'!DG42 -> 40462362 | DI9: =+'Notes - Dec25'!DI42 -> 32669443 | DK9: =+'Notes - Dec25'!DK42 -> 62893341 | DM9: =+'Notes - Dec25'!DM42 -> 50747876 | DO9: 71550519 | DQ9: 59723956 | DS9: 66038456 | DU9: 81659201 | DW9: 1.2675395e+08 | DY9: 1.5331764e+08 | EA9: 88453000 | EC9: 88715908 | EE9: 79984237 | EG9: 82254324 | EI9: 79996764 | EK9: 62736057 | EM9: 52465200 | EO9: 61664511 | EQ9: 65290791 | ES9: 69919871 | EU9: 64962950 | EW9: 52971149 | EY9: 60987411 | FA9: 41021161 | FC9: 73311111 | FE9: 211641.39 | FG9: 8665305.4 | FI9: 141016.13 | FK9: 3129983.4 | FM9: 9082520.2 | FO9: 11025359 | FQ9: 4009292.9 | FS9: 9285.65 | FU9: 9278.66 | FW9: 9271.45 | FY9: 9264.25 | GA9: 9257.31 | GC9: 1895866.1 | GE9: 2382465 | GG9: 2866713.9 | GI9: 2855804.2 | GK9: 3838203.9 | GM9: 3816668.5 | GO9: 4866941.2 | GQ9: 7125990.2 | GS9: 6191176 | GU9: 6768252.6 | GW9: 8221553 | GY9: 8670910.8 | HA9: 8916823.5 | HC9: 9224313.9 | HE9: 10664451 | HG9: 11006670
A10: Advances (Net) | B10: 1.3 | C10: =+'Notes - Dec25'!C15 -> 1.5068569e+09 | E10: =+'Notes - Dec25'!E15 -> 1.5543096e+09 | G10: =+'Notes - Dec25'!G15 -> 1.487163e+09 | I10: 1.5291501e+09 | K10: 1.540093e+09 | M10: ='Notes - Dec25'!M15 -> 1.5698073e+09 | O10: ='Notes - Dec25'!O15 -> 1.5624488e+09 | Q10: ='Notes - Dec25'!Q15 -> 1.6009868e+09 | S10: ='Notes - Dec25'!S15 -> 1.6171536e+09 | U10: ='Notes - Dec25'!U15 -> 1.6533135e+09 | W10: ='Notes - Dec25'!W15 -> 1.728136e+09 | Y10: 1.7914689e+09 | AA10: 1.8106753e+09 | AC10: 1.889595e+09 | AE10: 1.8758871e+09 | AG10: 1.8294239e+09 | AI10: 1.7953648e+09 | AK10: 1.7692985e+09 | AM10: 1.7123067e+09 | AO10: 1.6679456e+09 | AQ10: 1.6315326e+09 | AS10: 1.5929185e+09 | AU10: ='Notes - Dec25'!AU15 -> 1.4805857e+09 | AW10: 1.4077248e+09 | AY10: 1.3139125e+09 | BA10: 1.273905e+09 | BC10: 1.1569814e+09 | BE10: 1.0908727e+09 | BG10: 1.0369445e+09 | BI10: 9.5321446e+08 | BK10: 9.0806196e+08 | BM10: 8.5524237e+08 | BO10: 8.0665928e+08 | BQ10: =+'Notes - Dec25'!DQ15 -> 1.7844209e+08 | BS10: ='Notes - Dec25'!BS15 -> 669631787 | BU10: 6.7079383e+08 | BW10: 6.4173882e+08 | BY10: 6.5876549e+08 | CA10: 5.9377353e+08 | CC10: 5.8357025e+08 | CE10: 5.4940578e+08 | CG10: 5.2804942e+08 | CI10: 5.0826785e+08 | CK10: 4.7572364e+08 | CM10: 4.4880497e+08 | CO10: =+'Notes - Dec25'!CO15 -> 4.3629512e+08 | CQ10: =+'Notes - Dec25'!CQ15 -> 4.2198443e+08 | CS10: =+'Notes - Dec25'!CS15 -> 3.883681e+08 | CU10: =+'Notes - Dec25'!CU15 -> 3.8057297e+08 | CW10: =+'Notes - Dec25'!CW15 -> 3.8686791e+08 | CY10: =+'Notes - Dec25'!CY15 -> 3.5194409e+08 | DA10: =+'Notes - Dec25'!DA15 -> 3.2717067e+08 | DC10: =+'Notes - Dec25'!DC15 -> 3.009107e+08 | DE10: =+'Notes - Dec25'!DE15 -> 2.7069217e+08 | DG10: =+'Notes - Dec25'!DG15 -> 2.6154039e+08 | DI10: =+'Notes - Dec25'!DI15 -> 2.5086966e+08 | DK10: =+'Notes - Dec25'!DK15 -> 2.2606548e+08 | DM10: =+'Notes - Dec25'!DM15 -> 2.2039062e+08 | DO10: 1.9601839e+08 | DQ10: 1.7844209e+08 | DS10: 1.7208553e+08 | DU10: 1.7399482e+08 | DW10: 1.525848e+08 | DY10: 1.4128786e+08 | EA10: 1.3653779e+08 | EC10: 1.3286184e+08 | EE10: 1.3995046e+08 | EG10: 1.4218065e+08 | EI10: 1.4655205e+08 | EK10: 1.6397432e+08 | EM10: 1.7398916e+08 | EO10: 1.5297567e+08 | EQ10: 1.4624843e+08 | ES10: 1.3950736e+08 | EU10: 1.1560401e+08 | EW10: 1.0408517e+08 | EY10: 92566613 | FA10: 84484576 | FC10: 76456674 | FE10: 72994655 | FG10: 64845496 | FI10: 61979794 | FK10: 62186784 | FM10: 54897873 | FO10: 49311217 | FQ10: 48128211 | FS10: 42010777 | FU10: 35445285 | FW10: 32752530 | FY10: 28775974 | GA10: 24876301 | GC10: 24377633 | GE10: 21238134 | GG10: 20040814 | GI10: 19661322 | GK10: 17226776 | GM10: 16327150 | GO10: 15793239 | GQ10: 14130790 | GS10: 12811910 | GU10: 12944904 | GW10: 11676471 | GY10: 10930713 | HA10: 10069932 | HC10: 8972739.5 | HE10: 8151563.8 | HG10: 7589157.4
A11: Gross loan book (after WO) | GI11: 21438647 | GK11: 18963498 | GM11: 17879970 | GO11: 17218993 | GQ11: 15531633 | GS11: 14093812 | GU11: 14093498 | GW11: 12675065 | HA11: 11473457 | HC11: 10224150 | HE11: 9254593.6
A12: Provision for default | GI12: -1777324.5 | GK12: -1736722.1 | GM12: -1552820 | GO12: -1425753.1 | GQ12: -1400843.3 | GS12: -1281901.9 | GU12: -1148593.9 | GW12: -998594.18 | HA12: -1403524.8 | HC12: -1251410.2 | HE12: -1103029.7
A13: Other Receivables | B13: 2. | C13: =+'Notes - Dec25'!C29 -> 25462543 | E13: =+'Notes - Dec25'!E29 -> 28713521 | G13: =+'Notes - Dec25'!G29 -> 23887603 | I13: 24404813 | K13: 23857912 | M13: ='Notes - Dec25'!M29 -> 23020292 | O13: ='Notes - Dec25'!O29 -> 22610598 | Q13: ='Notes - Dec25'!Q29 -> 21287269 | S13: ='Notes - Dec25'!S29 -> 15342362 | U13: ='Notes - Dec25'!U29 -> 13021611 | W13: ='Notes - Dec25'!W29 -> 18605004 | Y13: 36451408 | AA13: 39686130 | AC13: 43965363 | AE13: 33650504 | AG13: 31832843 | AI13: 32364273 | AK13: 36742135 | AM13: 35197778 | AO13: 30247988 | AQ13: 26079774 | AS13: 25871898 | AU13: ='Notes - Dec25'!AU29 -> 13374102 | AW13: 22503751 | AY13: 23670621 | BA13: 26580915 | BC13: 18939077 | BE13: 19505958 | BG13: 18322892 | BI13: 18250412 | BK13: 19260836 | BM13: 17667400 | BO13: 16195677 | BQ13: =+'Notes - Dec25'!DQ29 -> 747577.42 | BS13: ='Notes - Dec25'!BS29 -> -6157806.8 | BU13: 510050.71 | BW13: 1586292.7 | BY13: 2081594.7 | CA13: -727498.63 | CC13: -2281882.1 | CE13: -2786210.2 | CG13: -430289.48 | CI13: 159660.91 | CK13: -2375186.6 | CM13: 29220.49 | CO13: =+'Notes - Dec25'!CO29 -> 684055.82 | CQ13: =+'Notes - Dec25'!CQ29 -> -1906555.6 | CS13: =+'Notes - Dec25'!CS29 -> -3719477 | CU13: =+'Notes - Dec25'!CU29 -> -1879008.7 | CW13: =+'Notes - Dec25'!CW29 -> -1071105.7 | CY13: =+'Notes - Dec25'!CY29 -> -1104117.1 | DA13: =+'Notes - Dec25'!DA29 -> -1046676.8 | DC13: =+'Notes - Dec25'!DC29 -> -2207639.6 | DE13: =+'Notes - Dec25'!DE29 -> 100689.92 | DG13: =+'Notes - Dec25'!DG29 -> 1546484.9 | DI13: =+'Notes - Dec25'!DI29 -> 1107245.1 | DK13: =+'Notes - Dec25'!DK29 -> 1456716.7 | DM13: =+'Notes - Dec25'!DM29 -> 1203969.3 | DO13: 3110138.7 | DQ13: 747577.42 | DS13: 705056.89 | DU13: 985570.18 | DW13: 1497176.6 | DY13: 69405.14 | EA13: 1067934.1 | EC13: 860081.53 | EE13: 1220789.2 | EG13: 872041.32 | EI13: 979783.08 | EK13: 1278648.1 | EM13: 1269476.4 | EO13: 481510.06 | EQ13: 588272.93 | ES13: 81664.97 | EU13: 545248.18 | EW13: 626549.05 | EY13: 809453.55 | FA13: -5494359.4 | FC13: 1066389.5 | FE13: 1020280.1 | FG13: 960486.14 | FI13: 581294.94 | FK13: 695662.37 | FM13: 823008.82 | FO13: 622750.05 | FQ13: 492937.6 | FS13: 311669.69 | FU13: 280486.45 | FW13: 300766.39 | FY13: 316811.67 | GA13: 198066.28 | GC13: 235600.27 | GE13: 242557 | GG13: 272732.68 | GI13: 304400.55 | GK13: 168833.78 | GM13: 181637.41 | GO13: 172359.74 | GQ13: 220877.93 | GS13: 222962.83 | GU13: 201137.73 | GW13: 200471.38 | GY13: 204271.28 | HA13: 125800.74 | HC13: 148344.8 | HE13: 85635.66 | HG13: 78325.76
A14: Fixed Assets | B14: 3. | C14: =+'Notes - Dec25'!C35 -> 9895009.2 | E14: =+'Notes - Dec25'!E35 -> 10206451 | G14: =+'Notes - Dec25'!G35 -> 10499873 | I14: 10333461 | K14: 10440414 | M14: 10381033 | O14: 10559864 | Q14: 10632744 | S14: 10726675 | U14: 7244930.7 | W14: 7318091.2 | Y14: 7363013.5 | AA14: 7368809 | AC14: 6962804.4 | AE14: 6850809 | AG14: 6682036.6 | AI14: 6479275.4 | AK14: 6590013.9 | AM14: 6398227.1 | AO14: 5980582.1 | AQ14: 5779801.1 | AS14: 5648013.1 | AU14: 5555820.6 | AW14: 5477557.5 | AY14: 5589869.2 | BA14: 5718749 | BC14: 5648672.1 | BE14: 5639584.2 | BG14: 5302695.2 | BI14: 5056850.2 | BK14: 4222596.6 | BM14: 3685970.5 | BO14: 3649510.6 | BQ14: =+'Notes - Dec25'!DQ35 -> 1392999.8 | BS14: 3430239.2 | BU14: 3440307.8 | BW14: 3439080 | BY14: 3446917.5 | CA14: 3382161 | CC14: 3087965.6 | CE14: 2960078.3 | CG14: 3061628.2 | CI14: 3084282.2 | CK14: 3079340.1 | CM14: 3141288.4 | CO14: =+'Notes - Dec25'!CO35 -> 3150491.9 | CQ14: =+'Notes - Dec25'!CQ35 -> 3153400.9 | CS14: =+'Notes - Dec25'!CS35 -> 3278678.8 | CU14: =+'Notes - Dec25'!CU35 -> 2909553 | CW14: =+'Notes - Dec25'!CW35 -> 2566953 | CY14: =+'Notes - Dec25'!CY35 -> 1897690.8 | DA14: =+'Notes - Dec25'!DA35 -> 1915509.7 | DC14: =+'Notes - Dec25'!DC35 -> 1787298.5 | DE14: =+'Notes - Dec25'!DE35 -> 1704291.7 | DG14: =+'Notes - Dec25'!DG35 -> 1573893.4 | DI14: =+'Notes - Dec25'!DI35 -> 1494846.7 | DK14: =+'Notes - Dec25'!DK35 -> 1349096.5 | DM14: =+'Notes - Dec25'!DM35 -> 1392720.8 | DO14: 1368123.1 | DQ14: 1392999.8 | DS14: 1412493.7 | DU14: 1454903.8 | DW14: 1497334.2 | DY14: 1506934.2 | EA14: 1549086.4 | EC14: 1583675.4 | EE14: 1623983.5 | EG14: 1666464.2 | EI14: 1708945.5 | EK14: 1743627.2 | EM14: 1785946.1 | EO14: 1758054.7 | EQ14: 1676962.3 | ES14: 1715533.2 | EU14: 1596171.4 | EW14: 1519362 | EY14: 1486671 | FA14: 1304457.3 | FC14: 1036892.4 | FE14: 964220.93 | FG14: 257715.78 | FI14: 230614.01 | FK14: 218496.12 | FM14: 225522.38 | FO14: 232548.56 | FQ14: 243255.69 | FS14: 252302.75 | FU14: 238689.88 | FW14: 249143.53 | FY14: 250879.43 | GA14: 257719.41 | GC14: 268217.21 | GE14: 271016 | GG14: 258915.01 | GI14: 238897.87 | GK14: 223731.56 | GM14: 242826.23 | GO14: 207820.57 | GQ14: 214084.54 | GS14: 219424.94 | GU14: 193291.66 | GW14: 198690.15 | GY14: 204088.61 | HA14: 209487.02 | HC14: 204391.51 | HE14: 209571.36 | HG14: 189754.21
A15: Intangibles | B15: 4. | C15: ='Notes - Dec25'!C38 -> 2.4371989e+08 | E15: ='Notes - Dec25'!E38 -> 2.4024934e+08 | G15: ='Notes - Dec25'!G38 -> 2.3687644e+08 | I15: 2.3314495e+08 | K15: 2.2949296e+08 | M15: 2.2552317e+08 | O15: 2.2081828e+08 | Q15: 2.1652145e+08 | S15: 2.1198288e+08 | U15: 2.0693501e+08 | W15: 2.0166642e+08 | Y15: 1.9799334e+08 | AA15: 193419717 | AC15: 1.8965275e+08 | AE15: 1.8429843e+08 | AG15: 1.7992552e+08 | AI15: 1.7537199e+08 | AK15: 1.7044859e+08 | AM15: 1.6521189e+08 | AO15: 1.5914318e+08 | AQ15: 1.5184588e+08 | AS15: 145783116 | AU15: 1.4071103e+08 | AW15: 1.3581647e+08 | AY15: 1.308739e+08 | BA15: 1.2683984e+08 | BC15: 1.2123852e+08 | BE15: 1.1596482e+08 | BG15: 1.1130771e+08 | BI15: 1.0743522e+08 | BK15: 1.0447108e+08 | BM15: 1.0102554e+08 | BO15: 96543519 | BQ15: ='Notes - Dec25'!DQ38 -> 18337475 | BS15: 88727261 | BU15: 83685634 | BW15: 78915819 | BY15: 75612645 | CA15: 71400475 | CC15: 67022955 | CE15: 62603791 | CG15: 58440631 | CI15: 54568891 | CK15: 51398241 | CM15: 43737340 | CO15: ='Notes - Dec25'!CO38 -> 41061884 | CQ15: ='Notes - Dec25'!CQ38 -> 38811349 | CS15: ='Notes - Dec25'!CS38 -> 36084237 | CU15: ='Notes - Dec25'!CU38 -> 35307631 | CW15: ='Notes - Dec25'!CW38 -> 32620504 | CY15: ='Notes - Dec25'!CY38 -> 30209807 | DA15: ='Notes - Dec25'!DA38 -> 28381129 | DC15: ='Notes - Dec25'!DC38 -> 25870094 | DE15: ='Notes - Dec25'!DE38 -> 24719197 | DG15: ='Notes - Dec25'!DG38 -> 23260616 | DI15: ='Notes - Dec25'!DI38 -> 22376596 | DK15: ='Notes - Dec25'!DK38 -> 21474044 | DM15: ='Notes - Dec25'!DM38 -> 20450142 | DO15: 19550370 | DQ15: 18337475 | DS15: 15307606 | DU15: 14658096 | DW15: 14042894 | DY15: 13551776 | EA15: 12949933 | EC15: 12323481 | EE15: 11821448 | EG15: 11113706 | EI15: 10446802 | EK15: 9818326.7 | EM15: 9169258.3 | EO15: 8818624.1 | EQ15: 8485966.8 | ES15: 8147211.3 | EU15: 7843565.5 | EW15: 7543940.3 | EY15: 7249951.4 | FA15: 6907979.3 | FC15: 6604711.8 | FE15: 6417919.2 | FG15: 6275150.3 | FI15: 6128325.5 | FK15: 5976412 | FM15: 5864773.6 | FO15: 5748939.4 | FQ15: 5553258 | FS15: 5398684.8 | FU15: 5198742.5 | FW15: 5052423.1 | FY15: 4860832.1 | GA15: 4639370.4 | GC15: 4435762.7 | GE15: 4189326 | GG15: 4047619 | GI15: 3896351.2 | GK15: 3726322.3 | GM15: 3530295.2 | GO15: 3339391.4 | GQ15: 3163886.9 | GS15: 2947057 | GU15: 2764768.7 | GW15: 2621146.3 | GY15: 2516136.1 | HA15: 2386488.5 | HC15: 2276745 | HE15: 2154234.4 | HG15: 2056055.3
A16: Right of Use Asset - lease | C16: 14446522 | E16: 14793846 | G16: 15141170 | I16: 15488494 | K16: 15835818 | M16: 16183141 | O16: 16530465 | Q16: 16877789 | S16: 17225112 | U16: 17572436 | W16: 12517545 | Y16: 12864869 | AA16: 13212193 | AC16: 13559516 | AE16: 13906840 | AG16: 7771494.5 | AI16: 8082354 | AK16: 8393214.1 | AM16: 8704073.9 | AO16: 9014933.7 | AQ16: 9325793.4 | AS16: 9636653.2 | AU16: 9947513 | AW16: 10258373 | AY16: 10569233 | BA16: 10880092 | BC16: 5444294.3 | BE16: 5595524.7 | BG16: 5746755.1 | BI16: 5897985.5 | BK16: 6049215.9 | BM16: 6200446.3 | BO16: 3109990.7 | BQ16: 3258091 | BS16: 3406191.2 | BU16: 3554291.5 | BW16: 3702391.7 | BY16: 3850492 | CA16: 3998592.2 | CC16: 4146692.5 | CE16: 4294792.8 | CG16: 4442893 | CI16: 4590993.3 | CK16: 4739093.5 | CM16: 4887193.8 | CO16: 5035294 | CQ16: 5183394.3 | CS16: 3338434.1 | CU16: 3325134.8 | CW16: 3415003 | CY16: 874365.58 | DA16: 971517.31 | DC16: 1068669 | DE16: 1165820.8 | DG16: 1262972.5 | DI16: 1360124.2 | DK16: 1457276 | DM16: 1554427.7 | DO16: 1651579.4 | DQ16: 1748731.1 | DS16: 1845882.9 | DU16: 1943034.6 | DW16: 2040186.3 | DY16: 2137338.1 | EA16: 2234489.8 | EC16: 2331641.5 | EE16: 2428793.3 | EG16: 2525945 | EI16: 2623096.7 | EK16: 2720248.5 | EM16: 2817400.2 | EO16: 2914551.9 | EQ16: 3011703.6 | ES16: 3108855.4 | EU16: 3206007.1 | EW16: 3303158.8 | EY16: 3400310.6
A17: Deferred Tax Asset | C17: 54334944 | E17: 54334944 | G17: 54334944 | I17: 54334944 | K17: 54334944 | M17: 54334944 | O17: 54334944 | Q17: 54334944 | S17: 54334944 | U17: 54334944 | W17: 54334944 | Y17: 14616528 | AA17: 14616528 | AC17: 14616528 | AE17: 14616528 | AG17: 14616528 | AI17: 14616528 | AK17: 14616528 | AM17: 14616528 | AO17: 14616528 | AQ17: 14616528 | AS17: 14616528 | AU17: 29862619 | AW17: 6418989.3 | AY17: 6418989.3 | BA17: 6418989.3 | BC17: 6418989.3 | BE17: 6418989.3 | BG17: 6418989.3 | BI17: 6418989.3 | BK17: 6418989.3 | BM17: 6418989.3 | BO17: 6418989.3 | BQ17: 6418989.3 | BS17: 6418989.3 | BU17: 4620848.8 | BW17: 5357594.9 | BY17: 5357594.9 | CA17: 5357594.9 | CC17: 5357594.9 | CE17: 5357594.9 | CG17: 5357594.9 | CI17: 5357594.9 | CK17: 5357594.9 | CM17: 5357594.9 | CO17: =5357594.92 -> 5357594.9 | CQ17: 5357595 | CS17: 5002031.1 | CU17: 5002031.1 | CW17: 5002031 | CY17: 4678446 | DA17: 3964226.2 | DC17: 3633894.9 | DE17: 2938186.5 | DG17: 2893377.8 | DI17: 2799403 | DK17: 2632188.1 | DM17: 2505878.5 | DO17: 2476336 | DQ17: 2777741.4 | DS17: 3517886.1 | DU17: 3884206.4 | DW17: 3650942.8 | DY17: 4386085.3 | EA17: 4208326.6 | EC17: 4385180.2 | EE17: 4104410.9 | EG17: 3418880 | EI17: 3063285.9 | EK17: 1904954.1 | EM17: 850003.18 | EO17: 419494.04 | EQ17: 419494.04 | ES17: 419494.04 | EU17: 419494.04 | EW17: 419494.04 | EY17: 419494.04 | FA17: 419494.04 | FC17: 419494.04 | FE17: 419494.04 | FG17: 419494.04 | FI17: 419494.04 | FK17: 419494.04 | FM17: 297405 | FO17: 297405 | FQ17: 297405 | FS17: 297405 | FU17: 297405 | FW17: 297405 | FY17: 297405 | GA17: 297405 | GC17: 297405 | GE17: 297405 | GG17: 297405 | GI17: 297405 | GK17: 531555.06 | GM17: 531555.06 | GO17: 531555.06 | GQ17: 531555.06 | GS17: 531555.06 | GU17: 531555.06 | GW17: 515167.68 | GY17: 465517.68 | HA17: 236189.68 | HC17: 236189.68 | HE17: 236189.68
A19: Liabilities | C19: =SUM(C20:C23) -> 1.5248072e+09 | E19: =SUM(E20:E23) -> 1.4496317e+09 | G19: =SUM(G20:G23) -> 1.397455e+09 | I19: 1.4329935e+09 | K19: 1.5627358e+09 | M19: =SUM(M20:M23) -> 1.6013788e+09 | O19: =SUM(O20:O23) -> 1.6434519e+09 | Q19: =SUM(Q20:Q23) -> 1.6506109e+09 | S19: =SUM(S20:S23) -> 1.690635e+09 | U19: =SUM(U20:U23) -> 1.4985445e+09 | W19: =SUM(W20:W23) -> 1.60699e+09 | Y19: 1.5895809e+09 | AA19: 1.6122707e+09 | AC19: 1.6684955e+09 | AE19: 1.6813434e+09 | AG19: 1.5604341e+09 | AI19: 1.6083227e+09 | AK19: 1.4548569e+09 | AM19: 1.4605851e+09 | AO19: 1.4089313e+09 | AQ19: 1.276569e+09 | AS19: 1.2074164e+09 | AU19: =SUM(AU20:AU23) -> 1.1157798e+09 | AW19: 1.0813949e+09 | AY19: 1.1004699e+09 | BA19: 9.3227176e+08 | BC19: 9.0749302e+08 | BE19: 8.0262376e+08 | BG19: 6.505162e+08 | BI19: 6.2813035e+08 | BK19: 6.0494035e+08 | BM19: 6.1286508e+08 | BO19: 5.8529373e+08 | BQ19: =SUM(BQ20:BQ23) -> 1.6803483e+08 | BS19: =SUM(BS20:BS23) -> 5.09603e+08 | BU19: 5.5494124e+08 | BW19: 6.2796055e+08 | BY19: 6.2143343e+08 | CA19: 5.2440424e+08 | CC19: 5.2359162e+08 | CE19: 5.4720692e+08 | CG19: 5.5555468e+08 | CI19: 4.5501279e+08 | CK19: 4.5498753e+08 | CM19: 4.4829305e+08 | CO19: =SUM(CO20:CO23) -> 4.5940926e+08 | CQ19: =SUM(CQ20:CQ23) -> 5.0472642e+08 | CS19: =SUM(CS20:CS23) -> 4.2004438e+08 | CU19: =SUM(CU20:CU23) -> 3.9227132e+08 | CW19: =SUM(CW20:CW23) -> 4.0650482e+08 | CY19: =SUM(CY20:CY23) -> 4.0084906e+08 | DA19: =SUM(DA20:DA23) -> 3.1691123e+08 | DC19: =SUM(DC20:DC23) -> 3.1719403e+08 | DE19: =SUM(DE20:DE23) -> 283678864 | DG19: =SUM(DG20:DG23) -> 2.5082642e+08 | DI19: =SUM(DI20:DI23) -> 2.132014e+08 | DK19: =SUM(DK20:DK23) -> 2.1766936e+08 | DM19: =SUM(DM20:DM23) -> 1.9890289e+08 | DO19: 1.9795663e+08 | DQ19: 1.6631143e+08 | DS19: 1.6616083e+08 | DU19: 1.8252128e+08 | DW19: 2.0591119e+08 | DY19: 2.1887873e+08 | EA19: 1.7018504e+08 | EC19: 1.6851607e+08 | EE19: 1.698397e+08 | EG19: 1.6783311e+08 | EI19: 1.6486441e+08 | EK19: 1.6774675e+08 | EM19: 1.7091932e+08 | EO19: 1.7134688e+08 | EQ19: 1.6980194e+08 | ES19: 1.3594844e+08 | EU19: 90882705 | EW19: 68753566 | EY19: 66177709 | FA19: 69019819 | FC19: 72353339 | FE19: 68829039 | FG19: 68141454 | FI19: 67352958 | FK19: 57137046 | FM19: 56752313 | FO19: 61946008 | FQ19: 46597952 | FS19: 48160350 | FU19: 27163674 | FW19: 22776147 | FY19: 19680034 | GA19: 15033519 | GC19: 14653918 | GE19: 13263949 | GG19: 13074513 | GI19: 12947422 | GK19: 8857458.3 | GM19: 9206385.3 | GO19: 11045329 | GQ19: 10613453 | GS19: 7786097 | GU19: 8173921.2 | GW19: 7593114.4 | GY19: 7521559.7 | HA19: 5449413.4 | HC19: 4987734 | HE19: 4884636.7 | HG19: 5308458.9
A20: Lease Liabilities | C20: 14372854 | E20: 14799234 | G20: 14732574 | I20: 15644559 | K20: 16063836 | M20: 16474672 | O20: 16881217 | Q20: 17288779 | S20: 17687637 | U20: 18088247 | W20: 13078783 | Y20: 13329868 | AA20: 13566381 | AC20: 13800659 | AE20: 14037002 | AG20: 8602937.8 | AI20: 8894529.2 | AK20: 9182015.6 | AM20: 9467466 | AO20: 9753130.8 | AQ20: 10034537 | AS20: 10316314 | AU20: 10593732 | AW20: 10874169 | AY20: 11134973 | BA20: 11393924 | BC20: 5906797.5 | BE20: 6036588.3 | BG20: 6166836.4 | BI20: 6294907.9 | BK20: 6422132.6 | BM20: 6549913.2 | BO20: 3433765.9 | BQ20: 3577980.7 | BS20: 3720280.1 | BU20: 3863831.6 | BW20: 3992253.1 | BY20: 4119728.5 | CA20: 4247276 | CC20: 4372872.6 | CE20: 4498615.2 | CG20: 4622360.8 | CI20: 4745195.2 | CK20: 4868284 | CM20: =4989307.87 -> 4989307.9 | CO20: 5110657.2 | CQ20: 5229931.6 | CS20: 3358531.9 | CU20: 3443025.7 | CW20: 3526835 | CY20: 980402.33 | DA20: 973109.58 | DC20: 1190363.7 | DE20: 1294294.9 | DG20: 1389245.8 | DI20: 1483563.2 | DK20: 1577251.4 | DM20: 1670314.4 | DO20: 1762756.6 | DQ20: 1854582 | DS20: 1945794.7 | DU20: 2036398.9 | DW20: 2126398.6 | DY20: 2200989.8 | EA20: 2275083.4 | EC20: 2348682.6 | EE20: 2414117.7 | EG20: 2479116.2 | EI20: 2840978.9 | EK20: 2918572.6 | EM20: 2996166.3 | EO20: 3067780 | EQ20: 3139393.8 | ES20: 3211007.5 | EU20: 3282621.2 | EW20: 3364062.3 | EY20: 3430762.3
A21: Other payables | B21: 6. | C21: =+'Notes - Dec25'!C68 -> 56917885 | E21: =+'Notes - Dec25'!E68 -> 48856905 | G21: =+'Notes - Dec25'!G68 -> 70464384 | I21: 1.0179295e+08 | K21: 95634007 | M21: ='Notes - Dec25'!M68 -> 96113838 | O21: ='Notes - Dec25'!O68 -> 1.0112522e+08 | Q21: ='Notes - Dec25'!Q68 -> 1.0607899e+08 | S21: ='Notes - Dec25'!S68-1 -> 84062316 | U21: ='Notes - Dec25'!U68-1 -> 79705449 | W21: ='Notes - Dec25'!W68 -> 73153885 | Y21: 46292580 | AA21: 57676191 | AC21: 68058091 | AE21: 61513709 | AG21: 59664890 | AI21: 58427121 | AK21: 66119932 | AM21: 63145282 | AO21: 66412375 | AQ21: 58859748 | AS21: 69045079 | AU21: ='Notes - Dec25'!AU68 -> 84620867 | AW21: 55846025 | AY21: 54766118 | BA21: 57252208 | BC21: 47474946 | BE21: 40408678 | BG21: 39233177 | BI21: 39406013 | BK21: 37682455 | BM21: 35515183 | BO21: 31397066 | BQ21: =+'Notes - Dec25'!DQ68 -> 2889748.1 | BS21: 18085132 | BU21: 15147152 | BW21: 16580464 | BY21: 12304796 | CA21: 5167190 | CC21: 923254.59 | CE21: -763362.2 | CG21: 3136152 | CI21: 5188609.9 | CK21: 8944969.3 | CM21: 6970371.5 | CO21: =+'Notes - Dec25'!CO68 -> 17254038 | CQ21: =+'Notes - Dec25'!CQ68 -> 11543877 | CS21: =+'Notes - Dec25'!CS68 -> 9276003.4 | CU21: =+'Notes - Dec25'!CU68 -> 5943331.7 | CW21: =+'Notes - Dec25'!CW68 -> 10357142 | CY21: =+'Notes - Dec25'!CY68 -> 8774948.9 | DA21: =+'Notes - Dec25'!DA68 -> 8716059.7 | DC21: =+'Notes - Dec25'!DC68 -> 8028682.1 | DE21: =+'Notes - Dec25'!DE68 -> 10028322 | DG21: =+'Notes - Dec25'!DG68 -> 12970284 | DI21: =+'Notes - Dec25'!DI68 -> 9992336.7 | DK21: =+'Notes - Dec25'!DK68 -> 7359064.3 | DM21: =+'Notes - Dec25'!DM68 -> 6410327.3 | DO21: 3786626.8 | DQ21: 2889748.1 | DS21: 4376458.8 | DU21: 7402248.3 | DW21: 8659608.6 | DY21: 6621626.9 | EA21: 6170585.3 | EC21: 4224449.1 | EE21: 8793020.3 | EG21: -4348680.6 | EI21: -10107344 | EK21: -7551822.2 | EM21: -215808.79 | EO21: 3501535.2 | EQ21: 4724630.5 | ES21: 2352513.2 | EU21: 623716.18 | EW21: 1879523.3 | EY21: 1919971.1 | FA21: 3887097.4 | FC21: 1759172.7 | FE21: 1066617.2 | FG21: 1168889.4 | FI21: 1077597.9 | FK21: 1205336.8 | FM21: 768601.39 | FO21: 775038.76 | FQ21: 1057596.6 | FS21: 424618.05 | FU21: 175149.64 | FW21: -71103.5 | FY21: 630883.42 | GA21: 629747.63 | GC21: 805272.14 | GE21: 622559.5 | GG21: 744652.29 | GI21: 719443.4 | GK21: 367365.93 | GM21: 299414.55 | GO21: 253415.33 | GQ21: 241124.36 | GS21: 330502.97 | GU21: 381313.55 | GW21: 301329.86 | GY21: 313289 | HA21: 197748.61 | HC21: 178343.37 | HE21: 50705.66 | HG21: 41053.3
A22: Shareholders/Directors Loan | B22: 7. | C22: 0 | E22: 0 | G22: 0 | I22: 0 | K22: 0 | M22: 0 | O22: 0 | Q22: 0 | S22: 0 | U22: 0 | W22: 0 | Y22: 0 | AA22: 0 | AC22: 0 | AE22: 0 | AG22: 0 | AI22: 0 | AK22: 0 | AM22: 0 | AO22: 0 | AQ22: 0 | AS22: 0 | AU22: 0 | AW22: 0 | AY22: 0 | BA22: 0 | BC22: 0 | BE22: 0 | BG22: 0 | BI22: 0 | BK22: 0 | BM22: 0 | BO22: 0 | BQ22: 0 | BS22: 0 | BU22: 0 | BW22: 0 | BY22: 0 | CA22: 0 | CC22: 0 | CE22: 0 | CG22: 0 | CI22: 0 | CK22: 0 | CM22: 0 | CO22: 0 | CQ22: 0 | CS22: 0 | CU22: =+'Notes - Dec25'!CU73 -> 0 | CW22: =+'Notes - Dec25'!CW73 -> 0 | CY22: =+'Notes - Dec25'!CY73 -> 0 | DA22: =+'Notes - Dec25'!DA73 -> 0 | DC22: =+'Notes - Dec25'!DC73 -> 0 | DE22: =+'Notes - Dec25'!DE73 -> 0 | DG22: =+'Notes - Dec25'!DG73 -> 0 | DI22: =+'Notes - Dec25'!DI73 -> 0 | DK22: =+'Notes - Dec25'!DK73 -> 0 | DM22: =+'Notes - Dec25'!DM73 -> 0 | DO22: 0 | DQ22: 0 | DS22: 0 | DU22: 0 | DW22: 0 | DY22: 0 | EA22: 0 | EC22: 0 | EE22: 0 | EG22: 0 | EI22: 0 | EK22: 0 | EM22: 0 | EO22: 4132.21 | EQ22: 4547 | ES22: 4547 | EU22: 4547 | EW22: 4547 | EY22: 4547 | FA22: 4547 | FC22: 4547 | FE22: 4547 | FG22: 4547 | FI22: 4547 | FK22: 4547 | FM22: 4547 | FO22: 4547 | FQ22: 4547 | FS22: 4547 | FU22: 4547 | FW22: 4547 | FY22: 4547 | GA22: 4547 | GC22: 4547 | GE22: 4547 | GG22: 4547 | GI22: 4547.212 | GK22: 4547.212 | GM22: 4547.212 | GO22: 4547.212 | GQ22: 4547.212 | GS22: 4547.212 | GU22: 4547.212 | GW22: 4547.21 | GY22: 4547 | HA22: 4547.21 | HC22: 4547.21 | HE22: 4547.21 | HG22: 4547.21
A23: Loans | B23: 8. | C23: =+'Notes - Dec25'!C127 -> 1.4535165e+09 | E23: =+'Notes - Dec25'!E127 -> 1.3859756e+09 | G23: =+'Notes - Dec25'!G127 -> 1.312258e+09 | I23: 1.315556e+09 | K23: 1.451038e+09 | M23: 1.4887903e+09 | O23: 1.5254455e+09 | Q23: 1.5272432e+09 | S23: 1.588885e+09 | U23: 1.4007508e+09 | W23: 1.5207573e+09 | Y23: 1.5299584e+09 | AA23: 1.5410281e+09 | AC23: 1.5866368e+09 | AE23: 1.6057927e+09 | AG23: 1.4921663e+09 | AI23: 1.5410011e+09 | AK23: 1.379555e+09 | AM23: 1.3879723e+09 | AO23: 1.3327658e+09 | AQ23: 1.2076747e+09 | AS23: 1.128055e+09 | AU23: 1.0205652e+09 | AW23: 1.0146747e+09 | AY23: 1.0345688e+09 | BA23: 8.6362563e+08 | BC23: 8.5411128e+08 | BE23: 7.5617849e+08 | BG23: 6.0511619e+08 | BI23: 5.8242943e+08 | BK23: 5.6083576e+08 | BM23: 5.7079999e+08 | BO23: 5.504629e+08 | BQ23: =+'Notes - Dec25'!DQ127 -> 1.615671e+08 | BS23: 4.8779759e+08 | BU23: 5.3593026e+08 | BW23: 6.0738784e+08 | BY23: 6.0500891e+08 | CA23: 5.1498978e+08 | CC23: 5.182955e+08 | CE23: 5.4347166e+08 | CG23: 5.4779617e+08 | CI23: 4.4507899e+08 | CK23: 4.4117427e+08 | CM23: 4.3633337e+08 | CO23: =+'Notes - Dec25'!CO127 -> 4.3704456e+08 | CQ23: =+'Notes - Dec25'!CQ127 -> 4.8795261e+08 | CS23: =+'Notes - Dec25'!CS127 -> 4.0740985e+08 | CU23: =+'Notes - Dec25'!CU127 -> 3.8288496e+08 | CW23: =+'Notes - Dec25'!CW127 -> 3.9262085e+08 | CY23: =+'Notes - Dec25'!CY127 -> 3.9109371e+08 | DA23: =+'Notes - Dec25'!DA127 -> 3.0722206e+08 | DC23: =+'Notes - Dec25'!DC127 -> 3.0797499e+08 | DE23: =+'Notes - Dec25'!DE127 -> 2.7235625e+08 | DG23: =+'Notes - Dec25'!DG127 -> 2.3646689e+08 | DI23: =+'Notes - Dec25'!DI127 -> 2.017255e+08 | DK23: =+'Notes - Dec25'!DK127 -> 2.0873304e+08 | DM23: =+'Notes - Dec25'!DM127 -> 1.9082225e+08 | DO23: 1.9240724e+08 | DQ23: 1.615671e+08 | DS23: 1.5983858e+08 | DU23: 1.7308263e+08 | DW23: 1.9512518e+08 | DY23: 2.1005611e+08 | EA23: 1.6173937e+08 | EC23: 1.6194294e+08 | EE23: 1.5863256e+08 | EG23: 1.6970268e+08 | EI23: 1.7213077e+08 | EK23: 1.7238e+08 | EM23: 1.6813896e+08 | EO23: 1.6477343e+08 | EQ23: 1.6193336e+08 | ES23: 1.3038038e+08 | EU23: 86971820 | EW23: 63505434 | EY23: 60822429 | FA23: 65128175 | FC23: 70589619 | FE23: 67757874 | FG23: 66968018 | FI23: 66270813 | FK23: 55927162 | FM23: 55979164 | FO23: 61166422 | FQ23: 45535809 | FS23: 47731185 | FU23: 26983978 | FW23: 22842703 | FY23: 19044604 | GA23: 14399224 | GC23: 13844099 | GE23: 12636842 | GG23: 12325314 | GI23: 12223432 | GK23: 8485545.2 | GM23: 8902423.5 | GO23: 10787366 | GQ23: 10367781 | GS23: 7451046.8 | GU23: 7788060.5 | GW23: 7287237.3 | GY23: 7203723.7 | HA23: 5247117.6 | HC23: 4804843.4 | HE23: 4829383.8 | HG23: 5262858.4
A25: Equity | C25: =SUM(C26:C30) -> 5.4731902e+08 | E25: =SUM(E26:E30) -> 5.4182198e+08 | G25: =SUM(G26:G30) -> 5.5028592e+08 | I25: 5.4839727e+08 | K25: 5.4628305e+08 | M25: =SUM(M26:M30) -> 5.50479e+08 | O25: =SUM(O26:O30) -> 5.4899612e+08 | Q25: =SUM(Q26:Q30) -> 5.499186e+08 | S25: =SUM(S26:S30) -> 5.4689078e+08 | U25: =SUM(U26:U30) -> 5.5407688e+08 | W25: =SUM(W26:W30) -> 5.6051858e+08 | Y25: 6.3355083e+08 | AA25: 6.3772931e+08 | AC25: 6.3834052e+08 | AE25: 6.3893664e+08 | AG25: 6.4188257e+08 | AI25: 6.4227693e+08 | AK25: 641436337 | AM25: 6.3958392e+08 | AO25: 6.4146807e+08 | AQ25: 6.4250769e+08 | AS25: 6.3701007e+08 | AU25: =SUM(AU26:AU30) -> 5.7378633e+08 | AW25: 6.3649003e+08 | AY25: 6.3344802e+08 | BA25: 6.2940313e+08 | BC25: 6.283391e+08 | BE25: 6.2734429e+08 | BG25: 6.267243e+08 | BI25: 6.2679874e+08 | BK25: 6.2515277e+08 | BM25: 6.2290747e+08 | BO25: 6.2002978e+08 | BQ25: =SUM(BQ26:BQ30) -> 6.189497e+08 | BS25: =SUM(BS26:BS30) -> 5.6759821e+08 | BU25: 6.2821213e+08 | BW25: 1.9867833e+08 | BY25: 1.988138e+08 | CA25: 2.059919e+08 | CC25: 2.0535001e+08 | CE25: 2.0236537e+08 | CG25: 1.9918945e+08 | CI25: 1.978142e+08 | CK25: 1.9467385e+08 | CM25: 1.9564576e+08 | CO25: =SUM(CO26:CO30) -> 1.884254e+08 | CQ25: =SUM(CQ26:CQ30) -> 1.0293443e+08 | CS25: =SUM(CS26:CS30) -> 1.5271591e+08 | CU25: =SUM(CU26:CU30) -> 1.076027e+08 | CW25: =SUM(CW26:CW30) -> 1.0655386e+08 | CY25: =SUM(CY26:CY30) -> 1.0755703e+08 | DA25: =SUM(DA26:DA30) -> 1.0815458e+08 | DC25: =SUM(DC26:DC30) -> 1.0792451e+08 | DE25: =SUM(DE26:DE30) -> 1.0779695e+08 | DG25: =SUM(DG26:DG30) -> 1.0668083e+08 | DI25: =SUM(DI26:DI30) -> 1.0620257e+08 | DK25: =SUM(DK26:DK30) -> 1.0536163e+08 | DM25: =SUM(DM26:DM30) -> 1.0410745e+08 | DO25: 1.0369441e+08 | DQ25: 1.038365e+08 | DS25: 1.0292762e+08 | DU25: 1.0219307e+08 | DW25: 1.0156393e+08 | DY25: 1.0067481e+08 | EA25: 1.0012236e+08 | EC25: 99185937 | EE25: 99364898 | EG25: 1.0072958e+08 | EI25: 1.0254649e+08 | EK25: 1.0436716e+08 | EM25: 1.0647654e+08 | EO25: 1.0845697e+08 | EQ25: 1.0783084e+08 | ES25: 1.0817889e+08 | EU25: 1.087796e+08 | EW25: 1.0826768e+08 | EY25: 1.0816736e+08 | FA25: 1.0736434e+08 | FC25: 1.0759199e+08 | FE25: 21695944 | FG25: 21083322 | FI25: 20483099 | FK25: 19722656 | FM25: 20098977 | FO25: 19022546 | FQ25: 19363081 | FS25: 19345918 | FU25: 19284253 | FW25: 19206410 | FY25: 18915538 | GA25: 18362820 | GC25: 18355511 | GE25: 18265421 | GG25: 18354001 | GI25: 18072759 | GK25: 18230292 | GM25: 17865363 | GO25: 17021839 | GQ25: 16811694 | GS25: 16985385 | GU25: 16945144 | GW25: 16847123 | GY25: 17075716 | HA25: 16989297 | HC25: 17142159 | HE25: 17448179 | HG25: 17429228
A26: Current Year Earnings | C26: ='P&L -Dec25'!DU186 -> -10725910 | E26: -15074573 | G26: -5464539.7 | I26: -6037342.8 | K26: -6832028.5 | M26: -1316551.5 | O26: -1333596.8 | Q26: 1054728.1 | S26: -507249.1 | U26: 278439.81 | W26: -24062778 | Y26: -13675064 | AA26: -8546293.8 | AC26: -6984798.4 | AE26: -5438400.3 | AG26: -1542185.1 | AI26: -197535.79 | AK26: -330711.1 | AM26: -1515358.3 | AO26: 1177025 | AQ26: 3186611.7 | AS26: -1341042.7 | AU26: 6153739.1 | AW26: 18065970 | AY26: 15044468 | BA26: 11020082 | BC26: 9977821.1 | BE26: 9004790.9 | BG26: 8428364 | BI26: 8546371.4 | BK26: 6943965.2 | BM26: 4742231.1 | BO26: 1908104.9 | BQ26: ='P&L -Dec25'!CI186 -> 743233.32 | BS26: -4795572.3 | BU26: -4355076.7 | BW26: -5452749.5 | BY26: -7148508.1 | CA26: -5976729.7 | CC26: -4915058.9 | CE26: -3324099.2 | CG26: -2617182.4 | CI26: -1791106.4 | CK26: -797966.78 | CM26: -280848.91 | CO26: ='P&L -Dec25'!BV186 -> 143106.34 | CQ26: =SUM('P&L -Dec25'!BI186:BT186) -> 295731.26 | CS26: 4047697 | CU26: 3583223 | CW26: 2440120 | CY26: 3538330.1 | DA26: 4184385 | DC26: =3957000.83+100000 -> 4057000.8 | DE26: 4000284.9 | DG26: 2847596.9 | DI26: 1943769.3 | DK26: 1291193.4 | DM26: 232564.46 | DO26: -3021817 | DQ26: -2722395.6 | DS26: -3866825.3 | DU26: -4930527.3 | DW26: -5347158.5 | DY26: -5905764.3 | EA26: -6302205 | EC26: -6831054.4 | EE26: -6389273.6 | EG26: -5955869.3 | EI26: -3992952 | EK26: -1778455.2 | EM26: 2174626.8 | EO26: 4337056.2 | EQ26: 4042172 | ES26: 3594426.5 | EU26: 3936555.5 | EW26: 3556154 | EY26: 3225431.1 | FA26: 2569778.8 | FC26: 2944852.7 | FE26: 2265117.2 | FG26: 1747141.9 | FI26: 856746.02 | FK26: 1439264.7 | FM26: 2190799.1 | FO26: 1350619 | FQ26: 1290321.7 | FS26: 1273158.1 | FU26: 1211493.7 | FW26: 1133651 | FY26: 842779 | GA26: 290061 | GC26: 282751.84 | GE26: 192661 | GG26: 281241.43 | GI26: 257394.26 | GK26: 564874.61 | GM26: 199945.61 | GO26: -643577.87 | GQ26: -853723.12 | GS26: -680031.75 | GU26: -720272.87 | GW26: -818294.41 | GY26: -589701.2 | HA26: -676120.44 | HC26: -523258.41 | HE26: -217237.79 | HG26: -1221755
A27: Retained Earnings | C27: -79860420 | E27: -79860420 | G27: -79860420 | I27: -79856738 | K27: -79856738 | M27: -79856738 | O27: -79856738 | Q27: -79856738 | S27: -79856738 | U27: -79856738 | W27: -55793960 | Y27: 7800854.4 | AA27: 7800854.4 | AC27: 7800854.4 | AE27: 7800854.4 | AG27: 7800854.4 | AI27: 7800854.4 | AK27: 7800854.4 | AM27: 7800854.4 | AO27: 7800854.4 | AQ27: 7800854.4 | AS27: 7800854.4 | AU27: -61947700 | AW27: -11235022 | AY27: -11235022 | BA27: -11235022 | BC27: -11235022 | BE27: -11235022 | BG27: -11235022 | BI27: -11235022 | BK27: -11235022 | BM27: -11235022 | BO27: -11235022 | BQ27: -11235022 | BS27: -57152127 | BU27: -6439449.6 | BW27: -6439449.6 | BY27: -6439449.6 | CA27: -6439449.6 | CC27: -6439449.6 | CE27: -6439449.6 | CG27: -6439449.6 | CI27: -6439450 | CK27: -6439449.6 | CM27: -6439449.6 | CO27: =SUM(CQ26:CQ27) -> -6439450.4 | CQ27: -6735181.7 | CS27: -6735181.7 | CU27: -6735181.7 | CW27: -6735182 | CY27: -6735181.7 | DA27: -6735181.7 | DC27: -6735181.7 | DE27: -6735181.7 | DG27: -6735181.7 | DI27: -6735181.7 | DK27: -6735181.7 | DM27: -6735181.7 | DO27: -3713364.7 | DQ27: -3713364.7 | DS27: -3713364.7 | DU27: -3713364.7 | DW27: -3713364.7 | DY27: -3713364.7 | EA27: -3713364.7 | EC27: -3713364.7 | EE27: -3713364.7 | EG27: -3713364.7 | EI27: -3713364.7 | EK27: -3713364.7 | EM27: -5887991.5 | EO27: 472809.56 | EQ27: 472809.56 | ES27: 509879.55 | EU27: 509879.55 | EW27: 509879.55 | EY27: 509879.55 | FA27: 509879.55 | FC27: 509879.55 | FE27: 509879.55 | FG27: 509879.55 | FI27: 509879.55 | FK27: -929385.17 | FM27: -929385.17 | FO27: -929385.17 | FQ27: -929385.17 | FS27: -929385.17 | FU27: -929385.17 | FW27: -929385.17 | FY27: -929385.17 | GA27: -929385.17 | GC27: -929385.17 | GE27: -929385 | GG27: -929385 | GI27: -1186779.4 | GK27: -1186779.4 | GM27: -1186779.4 | GO27: -1186779.4 | GQ27: -1186779.4 | GS27: -1186779.4 | GU27: -1186779.4 | GW27: -1186779.4 | GY27: -1186779.4 | HA27: -1186779.4 | HC27: -1186779.4 | HE27: -1186779.4 | HG27: -201214.11
A28: Other Comprehensive Reserve | C28: -6359333.1 | E28: -7328623.2 | G28: -8297913.4 | I28: -9267203.6 | K28: -10236494 | M28: -11205784 | O28: -12175074 | Q28: -13144364 | S28: -14113654 | U28: -7216694.5 | W28: 0 | Y28: 0 | AA28: 0 | AC28: 0 | AE28: 0 | AG28: 0 | AI28: 0 | AK28: 0 | AM28: 0 | AO28: 0 | AQ28: 0 | AS28: 0 | AU28: 0 | AW28: 0 | AY28: 0 | BA28: 0 | BC28: 0 | BE28: 0 | BG28: 0 | BI28: 0 | BK28: 0 | BM28: 0 | BO28: 0 | BQ28: 0 | BS28: 0 | BU28: 0 | BW28: 492112.55 | BY28: 721696.42 | CA28: 341280.29 | CC28: -39135.84 | CE28: 690448.03 | CG28: 166710.9 | CI28: -357026.23 | CK28: -820491.61 | CM28: -1346453.8 | CO28: -1872415.9 | CQ28: -2398378.1 | CS28: -67836.33 | CU28: -19246.88 | CW28: -52443 | CY28: -147486.37 | DA28: -195988.58 | DC28: -298671.89 | DE28: -369515.35 | DG28: -332948.62 | DI28: 92622.42 | DK28: -95743.07 | DM28: -329000.42 | DO28: -509472.82 | DQ28: -714095.89 | DS28: -410634.4 | DU28: -103893.01 | DW28: -119891.65 | DY28: -450402.01 | EA28: -606418.78 | EC28: -1013989.2 | EE28: -1276809.7 | EG28: -345532.37 | EI28: -491534.1 | EK28: -885364.61 | EM28: -554435.88 | EO28: -1058786.4 | EQ28: -1390028.9 | ES28: -594235.29 | EU28: -335657.89 | EW28: -467178.82 | EY28: -236769.96 | FA28: -384143.87 | FC28: -351967.78 | FE28: -370529.16 | FG28: -465175.15 | FI28: -175002.66 | FK28: -78699.96 | FM28: -164581.75 | FO28: -400833.33 | FQ28: 0 | FS28: 0 | FU28: 0 | FW28: 0 | FY28: 0 | GA28: 0 | GC28: 0 | GE28: 0 | GG28: 0 | GI28: 0 | GK28: 0 | GM28: 0 | GO28: 0 | GQ28: 0 | GS28: 0 | GU28: 0 | GW28: 0 | GY28: 0 | HA28: 0 | HC28: 0 | HE28: 0
A29: Share in joint operation | C29: 0 | E29: 0 | G29: 0 | I29: 0 | K29: 0 | M29: 0 | O29: 0 | Q29: 0 | S29: 0 | U29: 0 | W29: 0 | Y29: 0 | AA29: 0 | AC29: 0 | AE29: 0 | AG29: 0 | AI29: 0 | AK29: 0 | AM29: 0 | AO29: 0 | AQ29: 0 | AS29: 0 | AU29: 0 | AW29: 0 | AY29: 0 | BA29: 0 | BC29: 0 | BE29: 0 | BG29: 0 | BI29: 0 | BK29: 0 | BM29: 0 | BO29: 0 | BQ29: 0 | BS29: 0 | BU29: 0 | BW29: 0 | BY29: 0 | CA29: 0 | CC29: 0 | CE29: 0 | CG29: 0 | CI29: 0 | CK29: 0 | CM29: 0 | CO29: 0 | CQ29: 0 | CS29: 0 | CU29: 0 | CW29: 0 | CY29: 0 | DA29: 0 | DC29: 0 | DE29: 0 | DG29: 0 | DI29: 0 | DK29: 0 | DM29: 0 | DO29: 0 | DQ29: 242013.52 | DS29: 174103.17 | DU29: 196506.64 | DW29: 0 | DY29: 0 | EA29: 0 | EC29: 0 | EE29: 0 | EG29: 0 | EI29: 0 | EK29: 0 | EM29: 0 | EO29: 0 | EQ29: 0 | ES29: 0 | EU29: 0 | EW29: 0 | EY29: 0 | FA29: 0 | FC29: 0 | FE29: 0 | FG29: 0 | FI29: 0 | FK29: 0 | FM29: 0 | FO29: 0 | FQ29: 0 | FS29: 0 | FU29: 0 | FW29: 0 | FY29: 0 | GA29: 0 | GC29: 0 | GE29: 0 | GG29: 0 | GI29: 0 | GK29: 0 | GM29: 0 | GO29: 0 | GQ29: 0 | GS29: 0 | GU29: 0 | GW29: 0 | GY29: 0 | HA29: 0 | HC29: 0 | HE29: 0
A30: Share Acquisition | C30: 6.4426469e+08 | E30: 6.440856e+08 | G30: 6.4390879e+08 | I30: 6.4355855e+08 | K30: 6.4320831e+08 | M30: 6.4285808e+08 | O30: 6.4236153e+08 | Q30: 6.4186498e+08 | S30: 6.4136842e+08 | U30: 6.4087187e+08 | W30: 6.4037532e+08 | Y30: 6.3942504e+08 | AA30: 6.3847475e+08 | AC30: 6.3752447e+08 | AE30: 6.3657418e+08 | AG30: 6.356239e+08 | AI30: 6.3467361e+08 | AK30: 6.3396619e+08 | AM30: 6.3329842e+08 | AO30: 6.3249019e+08 | AQ30: 6.3152022e+08 | AS30: 6.3055026e+08 | AU30: 6.2958029e+08 | AW30: 6.2965908e+08 | AY30: 6.2963858e+08 | BA30: 6.2961807e+08 | BC30: 6.295963e+08 | BE30: 6.2957452e+08 | BG30: 6.2953096e+08 | BI30: 6.2948739e+08 | BK30: 6.2944383e+08 | BM30: 629400265 | BO30: 629356701 | BQ30: 629441491 | BS30: 6.2954591e+08 | BU30: 6.3900666e+08 | BW30: 2.1007842e+08 | BY30: 2.1168006e+08 | CA30: 2.180668e+08 | CC30: 2.1674365e+08 | CE30: 2.1143847e+08 | CG30: 2.0807937e+08 | CI30: 2.0640178e+08 | CK30: 2.0273175e+08 | CM30: 2.0371252e+08 | CO30: =194166653.91+2427510 -> 1.9659416e+08 | CQ30: =109344748+2427509.81 -> 1.1177226e+08 | CS30: =153914612.72+1556615.94 -> 1.5547123e+08 | CU30: 1.107739e+08 | CW30: =109344748+1556615.94 -> 1.1090136e+08 | CY30: =109344748+1556615.94 -> 1.1090136e+08 | DA30: =109344748+1556615.94 -> 1.1090136e+08 | DC30: =109344748+1556615.94 -> 1.1090136e+08 | DE30: =109344748+1556615.94 -> 1.1090136e+08 | DG30: =109344748+1556615.94 -> 1.1090136e+08 | DI30: =109344748+1556615.94 -> 1.1090136e+08 | DK30: =109344748+1556615.94 -> 1.1090136e+08 | DM30: =109382448+1556615.94 -> 1.1093906e+08 | DO30: 1.1093906e+08 | DQ30: 1.1074435e+08 | DS30: 1.1074435e+08 | DU30: 1.1074435e+08 | DW30: 1.1074435e+08 | DY30: 1.1074435e+08 | EA30: 1.1074435e+08 | EC30: 1.1074435e+08 | EE30: 1.1074435e+08 | EG30: 1.1074435e+08 | EI30: 1.1074435e+08 | EK30: 1.1074435e+08 | EM30: 1.1074435e+08 | EO30: 1.0470589e+08 | EQ30: 1.0470589e+08 | ES30: 1.0466882e+08 | EU30: 1.0466882e+08 | EW30: 1.0466882e+08 | EY30: 1.0466882e+08 | FA30: 1.0466882e+08 | FC30: 1.0448923e+08 | FE30: 19291476 | FG30: 19291476 | FI30: 19291476 | FK30: 19291476 | FM30: 19002145 | FO30: 19002145 | FQ30: 19002145 | FS30: 19002145 | FU30: 19002145 | FW30: 19002145 | FY30: 19002145 | GA30: 19002145 | GC30: 19002145 | GE30: 19002145 | GG30: 19002145 | GI30: 19002145 | GK30: 18852197 | GM30: 18852197 | GO30: 18852197 | GQ30: 18852197 | GS30: 18852197 | GU30: 18852197 | GW30: 18852197 | GY30: 18852197 | HA30: 18852197 | HC30: 18852197 | HE30: 18852197 | HG30: 18852197
A32: Control Checks: | C32: =ROUND(C25+C19-C7,0) -> 0 | E32: =ROUND(E25+E19-E7,0) -> 0 | G32: =ROUND(G25+G19-G7,0) -> 0 | I32: 0 | K32: 0 | M32: =ROUND(M25+M19-M7,0) -> 0 | O32: =ROUND(O25+O19-O7,0) -> 0 | Q32: =ROUND(Q25+Q19-Q7,0) -> 0 | S32: =ROUND(S25+S19-S7,0) -> 0 | U32: =ROUND(U25+U19-U7,0) -> 0 | W32: 0 | Y32: 0 | AA32: 0 | AC32: 0
A33: Check 1: | C33: =C7-C19-C25 -> -0.090000033 | E33: =E7-E19-E25 -> -0.010000348 | G33: =G7-G19-G25 -> 0.38000023 | I33: -0.20000005 | K33: 0.16000009 | M33: 0.15999961 | O33: 0.38999951 | Q33: -0.07000041 | S33: 0.23000026 | U33: 0.37999964 | W33: -0.089999557 | Y33: -0.17999935 | AA33: -0.36000037 | AC33: -0.1000005 | AE33: =AE7-AE19-AE25 -> 0 | AG33: =AG7-AG19-AG25 -> 0 | AI33: 0 | AK33: 0 | AM33: 0 | AO33: 0 | AQ33: 0 | AS33: 0 | AU33: 0 | AW33: 0 | AY33: 0 | BA33: 0 | BC33: 0.41999972 | BE33: 0.22999966 | BG33: 0 | BI33: 0.050000072 | BK33: 0.84999979 | BM33: 0.13 | BO33: -0.090000033 | BQ33: =+BQ7-BQ19-BQ25 -> -2.3229661e+08 | BS33: -0.23899996 | BU33: -0.40900004 | BW33: -0.22899985 | BY33: -0.39899999 | CA33: -0.41900006 | CC33: -0.23899996 | CE33: -0.36900011 | CG33: -0.089000165 | CI33: 0.17099985 | CK33: -0.0090002716 | CM33: 0.08100009 | CO33: =+CO7-CO19-CO25 -> 0.41 | CQ33: =+CQ7-CQ19-CQ25 -> 0.4100001 | CS33: =+CS7-CS19-CS25 -> 0.27000001 | CU33: =+CU7-CU19-CU25 -> 0.49000001 | CW33: =+CW7-CW19-CW25 -> -0.22000003 | CY33: =+CY7-CY19-CY25 -> 0 | DA33: =+DA7-DA19-DA25 -> 0 | DC33: =+DC7-DC19-DC25 -> -0.19999999 | DE33: =+DE7-DE19-DE25 -> -0.19000003 | DG33: =+DG7-DG19-DG25 -> 0.010000065 | DI33: =+DI7-DI19-DI25 -> 0 | DK33: =+DK7-DK19-DK25 -> 0 | DM33: =+DM7-DM19-DM25 -> -0.019999951 | DO33: 0 | DQ33: 0 | DS33: -9.4264746e-05 | DU33: 0.020000041 | DW33: -0.0088889152 | DY33: 0.0099999309 | EA33: 0.0059756637 | EC33: 0.25 | EE33: 0.16000006 | EG33: -0.28000002 | EI33: 0 | EK33: 0.0099999905 | EM33: -0.0099999905 | EO33: 0.01000005 | EQ33: -0.44700004 | ES33: 0.10999997 | EU33: 0.39 | EW33: -0.24000001 | EY33: 0.49000001 | FA33: 0.37 | FC33: -0.27 | FE33: 0.45 | FG33: -0.38999999 | FI33: -0.049999993 | FK33: 0.20000004 | FM33: 0.4 | FO33: -0.13999999 | FQ33: 0.040000003 | FS33: -0.37 | FU33: 0.20000001 | FW33: -0.16999999 | FY33: -0.15 | GA33: -0.10999999 | GC33: -0.36 | GE33: 0.060000002 | GG33: -0.059999991 | GI33: 0.057999991 | GK33: -0.021999996 | GM33: -0.0020000152 | GO33: 0.018000014 | GQ33: -0.021999996 | GS33: -0.011999998 | GU33: -0.012000009 | GW33: 0.15 | GY33: 0.09 | HA33: 0.099999998 | HC33: 0 | HE33: 0 | HG33: 0
A35: Current Assets | CY35: =SUM(CY36:CY38) -> #REF! | DA35: =SUM(DA36:DA38) -> #REF! | DC35: =SUM(DC36:DC38) -> #REF! | DE35: =SUM(DE36:DE38) -> #REF! | DG35: =SUM(DG36:DG38) -> #REF! | DI35: =SUM(DI36:DI38) -> #REF! | DK35: =SUM(DK36:DK38) -> #REF! | DM35: =SUM(DM36:DM38) -> #REF! | DO35: 1.5752867e+08 | DQ35: 1.4130131e+08 | DS35: 1.4557526e+08 | DU35: 1.6170891e+08 | DW35: 1.9688356e+08 | DY35: 2.1629044e+08 | EA35: 1.6999387e+08 | EC35: 1.7047565e+08 | EE35: 1.6804728e+08 | EG35: 1.6642523e+08 | EI35: 1.6245621e+08 | EK35: 1.5683482e+08 | EM35: 1.5666112e+08 | EO35: 1.733818e+08 | EQ35: 1.7526417e+08 | ES35: 1.467023e+08 | EU35: 1.1637489e+08 | EW35: 1.0131784e+08 | EY35: 1.0535083e+08 | FA35: 1.2331092e+08 | FC35: 1.2555087e+08 | FE35: 38595486 | FG35: 43772418 | FI35: 45242487 | FK35: 34644813 | FM35: 39020005 | FO35: 46756948 | FQ35: 32418955 | FS35: 38294175 | FU35: 21835454 | FW35: 19169091 | FY35: 17963851 | GA35: 15137988 | GC35: 15141803 | GE35: 15530547 | GG35: 16434634 | GI35: 16372587 | GK35: 13812858 | GM35: 14358474 | GO35: 15861704 | GQ35: 16341113
A36: GLP maturing within 3 months | CY36: ='Exposure Analysis - Dec25'!BV61 -> #REF! | DA36: ='Exposure Analysis - Dec25'!BX61 -> #REF! | DC36: ='Exposure Analysis - Dec25'!BZ61 -> #REF! | DE36: ='Exposure Analysis - Dec25'!CB61 -> #REF! | DG36: ='Exposure Analysis - Dec25'!BZ61 -> #REF! | DI36: ='Exposure Analysis - Dec25'!BX61 -> #REF! | DK36: ='Exposure Analysis - Dec25'!BV61 -> #REF! | DM36: ='Exposure Analysis - Dec25'!BT61 -> #REF! | DO36: 80052575 | DQ36: 74599997 | DS36: 71361253 | DU36: 73915193 | DW36: 64721769 | DY36: 59676294 | EA36: 58234032 | EC36: 57119545 | EE36: 59992564 | EG36: 59640224 | EI36: 60419267 | EK36: 66161031 | EM36: 69146494 | EO36: 60945847 | EQ36: 58062214 | ES36: 55555082 | EU36: 45927077 | EW36: 41794266 | EY36: 36938249 | FA36: 34548911 | FC36: 31189703 | FE36: 29887073 | FG36: 27305984 | FI36: 26745953 | FK36: 27281960 | FM36: 24277298 | FO36: 22001256 | FQ36: 21172989 | FS36: 19058748 | FU36: 16848135 | FW36: 15838802 | FY36: 13870181 | GA36: 12010512 | GC36: 11746992 | GE36: 10239616 | GG36: 9923605.9 | GI36: 9750782 | GK36: 8602326.2 | GM36: 8100189.8 | GO36: 7838902.5 | GQ36: 7177160.1
A37: Bank | CY37: =CY8 -> 11430255 | DA37: =DA8 -> 6354640.8 | DC37: =DC8 -> 6912516.5 | DE37: =DE8 -> 6908378.6 | DG37: =DG8 -> 24967153 | DI37: =DI8 -> 6726657.9 | DK37: =DK8 -> 5702844.1 | DM37: =DM8 -> 4764699.1 | DO37: 5925577.5 | DQ37: 6977360.1 | DS37: 8175547.1 | DU37: 6134514.7 | DW37: 5407838.8 | DY37: 3296504.7 | EA37: 23306833 | EC37: 24640200 | EE37: 28070477 | EG37: 24530681 | EI37: 22040176 | EK37: 27937729 | EM37: 35049425 | EO37: 50771438 | EQ37: 51911162 | ES37: 21227343 | EU37: 5484862.9 | EW37: 6552421.6 | EY37: 7425167.5 | FA37: 47740848 | FC37: 21050056 | FE37: 8496771.5 | FG37: 7801128.6 | FI37: 18355518 | FK37: 4232869.6 | FM37: 5660186.8 | FO37: 13730334 | FQ37: 7236672.8 | FS37: 19226142 | FU37: 4978040.5 | FW37: 3321017.8 | FY37: 4084405.6 | GA37: 3118219.2 | GC37: 1498945.3 | GE37: 2908466 | GG37: 3644314.4 | GI37: 3766000.9 | GK37: 1372328 | GM37: 2441615.5 | GO37: 3155860.5 | GQ37: 2037962.8
A38: Investment Accounts | CY38: =CY9 -> 1.0847554e+08 | DA38: =DA9 -> 57354789 | DC38: =DC9 -> 87143010 | DE38: =DE9 -> 83247084 | DG38: =DG9 -> 40462362 | DI38: =DI9 -> 32669443 | DK38: =DK9 -> 62893341 | DM38: =DM9 -> 50747876 | DO38: 71550519 | DQ38: 59723956 | DS38: 66038456 | DU38: 81659201 | DW38: 1.2675395e+08 | DY38: 1.5331764e+08 | EA38: 88453000 | EC38: 88715908 | EE38: 79984237 | EG38: 82254324 | EI38: 79996764 | EK38: 62736057 | EM38: 52465200 | EO38: 61664511 | EQ38: 65290791 | ES38: 69919871 | EU38: 64962950 | EW38: 52971149 | EY38: 60987411 | FA38: 41021161 | FC38: 73311111 | FE38: 211641.39 | FG38: 8665305.4 | FI38: 141016.13 | FK38: 3129983.4 | FM38: 9082520.2 | FO38: 11025359 | FQ38: 4009292.9 | FS38: 9285.65 | FU38: 9278.66 | FW38: 9271.45 | FY38: 9264.25 | GA38: 9257.31 | GC38: 1895866.1 | GE38: 2382465 | GG38: 2866713.9 | GI38: 2855804.2 | GK38: 3838203.9 | GM38: 3816668.5 | GO38: 4866941.2 | GQ38: 7125990.2
A40: Current Liabilities | CY40: =SUM(CY41:CY42) -> 7.027693e+08 | DA40: =SUM(DA41:DA42) -> 1.2843421e+08 | DC40: =SUM(DC41:DC42) -> 1.0405061e+08 | DE40: =SUM(DE41:DE42) -> 85817017 | DG40: =SUM(DG41:DG42) -> 84857530 | DI40: =SUM(DI41:DI42) -> 87899539 | DK40: =SUM(DK41:DK42) -> 84023910 | DM40: =SUM(DM41:DM42) -> 97256167 | DO40: 62323263 | DQ40: 52574154 | DS40: 53265302 | DU40: 53298274 | DW40: 69795376 | DY40: 69472306 | EA40: 70074983 | EC40: 54485016 | EE40: 58657565 | EG40: 38909533 | EI40: 31960048 | EK40: 55220667 | EM40: 57252509 | EO40: 58263769 | EQ40: 57884104 | ES40: 10223734 | EU40: 17047351 | EW40: 5800381.7 | EY40: 4074561.5 | FA40: 6088815.7 | FC40: 10113034 | FE40: 9286822.1 | FG40: 9156024.7 | FI40: 8810320 | FK40: 9656349.5 | FM40: 9446793.2 | FO40: 9435661.6 | FQ40: 7614654.7 | FS40: 7245093.1 | FU40: 15516724 | FW40: 11198699 | FY40: 5294482 | GA40: 3615100.1 | GC40: 3200009.1 | GE40: 1896219.4 | GG40: 1901204.8 | GI40: 2545255.1 | GK40: 4220411.4 | GM40: 4467433.5 | GO40: 5859199.2 | GQ40: 5378298.7
A41: Trade payables | CY41: =CY21 -> 8774948.9 | DA41: =DA21 -> 8716059.7 | DC41: =DC21 -> 8028682.1 | DE41: =DE21 -> 10028322 | DG41: =DG21 -> 12970284 | DI41: =DI21 -> 9992336.7 | DK41: =DK21 -> 7359064.3 | DM41: =DM21 -> 6410327.3 | DO41: 3786626.8 | DQ41: 2889748.1 | DS41: 4376458.8 | DU41: 7402248.3 | DW41: 8659608.6 | DY41: 6621626.9 | EA41: 6170585.3 | EC41: 4224449.1 | EE41: 8793020.3 | EG41: -4348680.6 | EI41: -10107344 | EK41: -7551822.2 | EM41: -215808.79 | EO41: 3501535.2 | EQ41: 4724630.5 | ES41: 2352513.2 | EU41: 623716.18 | EW41: 1879523.3 | EY41: 1919971.1 | FA41: 3887097.4 | FC41: 1759172.7 | FE41: 1066617.2 | FG41: 1168889.4 | FI41: 1077597.9 | FK41: 1205336.8 | FM41: 768601.39 | FO41: 775038.76 | FQ41: 1057596.6 | FS41: 424618.05 | FU41: 175149.64 | FW41: -71103.5 | FY41: 630883.42 | GA41: 629747.63 | GC41: 805272.14 | GE41: 622559.5 | GG41: 744652.29 | GI41: 719443.4 | GK41: 367365.93 | GM41: 299414.55 | GO41: 253415.33 | GQ41: 241124.36
A42: Loans | CY42: ='Notes - Dec25'!AC129 -> 6.9399435e+08 | DA42: ='Notes - Dec25'!DA129 -> 1.1971815e+08 | DC42: ='Notes - Dec25'!DC129 -> 96021925 | DE42: ='Notes - Dec25'!DE129 -> 75788695 | DG42: ='Notes - Dec25'!DG129 -> 71887247 | DI42: ='Notes - Dec25'!DI129 -> 77907203 | DK42: ='Notes - Dec25'!DK129 -> 76664845 | DM42: ='Notes - Dec25'!DM129 -> 90845840 | DO42: 58536636 | DQ42: 49684406 | DS42: 48888844 | DU42: 45896025 | DW42: 61135767 | DY42: 62850680 | EA42: 63904398 | EC42: 50260567 | EE42: 49864545 | EG42: 43258214 | EI42: 42067392 | EK42: 62772489 | EM42: 57468317 | EO42: 54762234 | EQ42: 53159473 | ES42: 7871220.3 | EU42: 16423635 | EW42: 3920858.4 | EY42: 2154590.4 | FA42: 2201718.3 | FC42: 8353861.2 | FE42: 8220204.9 | FG42: 7987135.4 | FI42: 7732722.1 | FK42: 8451012.7 | FM42: 8678191.8 | FO42: 8660622.8 | FQ42: 6557058.2 | FS42: 6820475.1 | FU42: 15341575 | FW42: 11269802 | FY42: 4663598.6 | GA42: 2985352.5 | GC42: 2394736.9 | GE42: 1273659.9 | GG42: 1156552.5 | GI42: 1825811.7 | GK42: 3853045.5 | GM42: 4168018.9 | GO42: 5605783.9 | GQ42: 5137174.3
A45: Monitors
A46: CAPEX:
A47: Fixed assets | C47: =C14-E14+'P&L -Dec25'!DC158+'P&L -Dec25'!DC103 -> 151829.29 | E47: =E14-G14+'P&L -Dec25'!DE158+'P&L -Dec25'!DE103 -> 166777.79 | G47: =G14-I14+'P&L -Dec25'!DG158+'P&L -Dec25'!DG103 -> 639024.88 | I47: 386005.59 | K47: 690245.69 | M47: 459615.74 | O47: 560831.12 | Q47: 536935.17 | S47: 4114930.3 | U47: 419797.35 | W47: 427691.07 | Y47: 463719.09 | AA47: 866203.88 | AC47: 530050.41 | AE47: 834805.16 | AG47: 507818.64 | AI47: 307316.63 | AK47: 604837.11 | AM47: 825696.28 | AO47: 601635.28 | AQ47: 526675.98 | AS47: 502173.92 | AU47: 487795.95 | AW47: 297246.53 | AY47: 281101.76 | BA47: 502328.18 | BC47: 278426.76 | BE47: 597562.72 | BG47: 500013.45 | BI47: 1081289.5 | BK47: 643164.06 | BM47: 168808.76 | BO47: 220639.68 | BQ47: =(BQ14-BS14)+'P&L -Dec25'!CE158+'P&L -Dec25'!CE165 -> -1942891.1 | BS47: 87941.64 | BU47: 103104.21 | BW47: 45674.14 | BY47: 164072.08 | CA47: 380051.49 | CC47: 181398.92 | CE47: 30799 | CG47: 79222.42 | CI47: 104171.28 | CK47: 36948.9 | CM47: 88287.89 | CO47: =(CO14-CQ14)+'P&L -Dec25'!BV158 -> 94255.97 | CQ47: =(CQ14-CS14)+'P&L -Dec25'!BT158 -> -41985.48 | CS47: =+CS14-CU14+'P&L -Dec25'!BS159 -> 782083.95 | CU47: =+CU14-CW14+'P&L -Dec25'!BR158 -> 413945 | CW47: =+CW14-CY14+'P&L -Dec25'!BQ158 -> 736546.23 | CY47: =+CY14-DA14+'P&L -Dec25'!BP158 -> 48651.75 | DA47: =+DA14-DC14+'P&L -Dec25'!BO158 -> 192908.58 | DC47: =+DC14-DE14+'P&L -Dec25'!BN158 -> 143817.67 | DE47: =+DE14-DG14+'P&L -Dec25'!BM158 -> 185620.13 | DG47: =+DG14-DI14+'P&L -Dec25'!BL158 -> 125353.6 | DI47: =+DI14-DK14+'P&L -Dec25'!BK158 -> 191538.15 | DK47: =+DK14-DM14+'P&L -Dec25'!BJ158 -> 195.01 | DM47: =+DM14-DO14+'P&L -Dec25'!BI158 -> 66995 | DO47: 17918 | DQ47: 22942 | DS47: -1.0186341e-10 | DU47: -20 | DW47: 32140.95 | DY47: -206.22 | EA47: 7054.4 | EC47: 1844.99 | EE47: 0 | EG47: 0 | EI47: 7800 | EK47: 3.5652192e-10 | EM47: 68506 | EO47: 122141.27 | EQ47: 0 | ES47: 156998.76 | EU47: 113225.18 | EW47: 67552.84 | EY47: 269681.68 | FA47: 265621.28 | FC47: 82057 | FE47: 714777.17 | FG47: 26477 | FI47: 19243.05 | FK47: 0 | FM47: 0 | FO47: 0 | FQ47: 0 | FS47: 24409.91 | FU47: 0 | FW47: 8999 | FY47: 3676 | GA47: 0 | GC47: 7699 | GE47: 16397 | GG47: 26986 | GI47: 0 | GK47: 2900 | GM47: 41269.62 | GS47: 31620 | HA47: 10494 | HE47: 24997
A48: Intangibles | C48: =C15-E15+'P&L -Dec25'!DR159+'P&L -Dec25'!DR169 -> 6028436.2 | E48: 5911806.3 | G48: 6258035.3 | I48: 6364158.2 | K48: 6592567.4 | M48: 7311767.9 | O48: 6910199.6 | Q48: 7161343.2 | S48: 7695207.8 | U48: 7980766.5 | W48: 6444859.9 | Y48: 7326142.2 | AA48: 6457976.9 | AC48: 7780352.1 | AE48: 11397349 | AG48: 11907063 | AI48: 7349432.2 | AK48: 7634613.8 | AM48: 8013013.7 | AO48: 9140181.5 | AQ48: 7595657.6 | AS48: 6490228.4 | AU48: 6361570.2 | AW48: 6376558.8 | AY48: 5452212.4 | BA48: 7006380.9 | BC48: 6616844.6 | BE48: 5996013.3 | BG48: 5202458.2 | BI48: 4290197.1 | BK48: 4768960.2 | BM48: 5048035.6 | BO48: 4475564.6 | BQ48: =BQ15-BS15+'P&L -Dec25'!CE159 -> -69747695 | BS48: 5683581.8 | BU48: 5327976.5 | BW48: 3878751.2 | BY48: 4857700.7 | CA48: 4973455.6 | CC48: 4994741.4 | CE48: 4729171.5 | CG48: 4429901.8 | CI48: 3703153 | CK48: 8213190.5 | CM48: 3178077.3 | CO48: =CO15-CQ15++'P&L -Dec25'!BV159 -> 2690448.4 | CQ48: =CQ15-CS15++'P&L -Dec25'!BT159 -> 3129579 | CS48: =CS15-CU15+'P&L -Dec25'!BS159 -> 1189564.3 | CU48: =+CU15-CW15+'P&L -Dec25'!BR159 -> 3099884.7 | CW48: =+CW15-CY15+'P&L -Dec25'!BQ159 -> 2777561.1 | CY48: =+CY15-DA15+'P&L -Dec25'!BP159 -> 2193239.2 | DA48: =+DA15-DC15+'P&L -Dec25'!BO159 -> 2884131.3 | DC48: =+DC15-DE15+'P&L -Dec25'!BN159 -> 1538418.1 | DE48: =+DE15-DG15+'P&L -Dec25'!BM159 -> 1806297.9 | DG48: =+DG15-DI15+'P&L -Dec25'!BL159 -> 1232933.3 | DI48: =+DI15-DK15+'P&L -Dec25'!BK159 -> 1252923.3 | DK48: =+DK15-DM15+'P&L -Dec25'!BJ159 -> 1362964.5 | DM48: =+DM15-DO15+'P&L -Dec25'!BI159 -> 1230766.8 | DO48: 1543019.3 | DQ48: 3341627.8 | DS48: 958599.77 | DU48: 912674.97 | DW48: 787017.43 | DY48: 869995.23 | EA48: 880346.65 | EC48: 742220.87 | EE48: 937081.1 | EG48: 823969.69 | EI48: 778250 | EK48: 794734.07 | EM48: 496657.63 | EO48: 474971.81 | EQ48: 467075.46 | ES48: 422681.34 | EU48: 415325.01 | EW48: 403699.32 | EY48: 447382 | FA48: 408065.8 | FC48: 288321.56 | FE48: 241451.32 | FG48: 239886.46 | FI48: 245120.86 | FK48: 202393.98 | FM48: 199824.97 | FO48: 274102.61 | FQ48: 229069.96 | FS48: 274602.45 | FU48: 217123.58 | FW48: 256328.25 | FY48: 278361.49 | GA48: 252744 | GC48: 295971.84 | GE48: 185043 | GG48: 192558 | GI48: 181495 | GK48: 223236 | GM48: 217742.6 | GO48: 201521.62 | GQ48: 242775.75 | GS48: 206829.95 | GU48: 166551.17 | GW48: 127476.66 | GY48: 149189.58 | HA48: 129285.36 | HC48: 141771.95 | HE48: 117208.91
A49: Total | C49: =SUM(C47:C48) -> 6180265.5 | E49: =SUM(E47:E48) -> 6078584.1 | G49: =SUM(G47:G48) -> 6897060.1 | I49: 6750163.8 | K49: 7282813.1 | M49: 7771383.6 | O49: 7471030.8 | Q49: 6611860.5 | S49: 10723720 | U49: 7314145.5 | W49: 6872551 | Y49: 7789861.3 | AA49: 7324180.8 | AC49: 8310402.5 | AE49: 12232154 | AG49: 12414882 | AI49: 7656748.8 | AK49: 8239450.9 | AM49: 8838709.9 | AO49: 9741816.8 | AQ49: 8122333.6 | AS49: 6992402.3 | AU49: 6849366.1 | AW49: 6673805.3 | AY49: 5733314.2 | BA49: 7508709.1 | BC49: 6895271.4 | BE49: 6593576.1 | BG49: 5702471.7 | BI49: 5371486.6 | BK49: 5412124.3 | BM49: 5216844.4 | BO49: 4696204.3 | BQ49: =SUM(BQ47:BQ48) -> -71690586 | BS49: 5771523.4 | BU49: 5431080.7 | BW49: 3924425.4 | BY49: 5021772.8 | CA49: 5353507.1 | CC49: 5176140.3 | CE49: 4759970.5 | CG49: 4509124.2 | CI49: 3807324.3 | CK49: 8250139.4 | CM49: 3266365.2 | CO49: =SUM(CO47:CO48) -> 2784704.3 | CQ49: =SUM(CQ47:CQ48) -> 3087593.6 | CS49: =SUM(CS47:CS48) -> 1971648.3 | CU49: =SUM(CU47:CU48) -> 3513829.7 | CW49: =SUM(CW47:CW48) -> 3514107.4 | CY49: =SUM(CY47:CY48) -> 2241891 | DA49: =SUM(DA47:DA48) -> 3077039.9 | DC49: =SUM(DC47:DC48) -> 1682235.8 | DE49: =SUM(DE47:DE48) -> 1991918 | DG49: =SUM(DG47:DG48) -> 1358286.9 | DI49: =SUM(DI47:DI48) -> 1444461.5 | DK49: =SUM(DK47:DK48) -> 1363159.5 | DM49: =SUM(DM47:DM48) -> 1297761.8 | DO49: 1560937.3 | DQ49: 3364569.8 | DS49: 958599.77 | DU49: 912654.97 | DW49: 819158.38 | DY49: 869789.01 | EA49: 887401.05 | EC49: 744065.86 | EE49: 937081.1 | EG49: 823969.69 | EI49: 786050 | EK49: 794734.07 | EM49: 565163.63 | EO49: 597113.08 | EQ49: 467075.46 | ES49: 579680.1 | EU49: 528550.19 | EW49: 471252.16 | EY49: 717063.68 | FA49: 673687.08 | FC49: 370378.56 | FE49: 956228.49 | FG49: 266363.46 | FI49: 264363.91 | FK49: 202393.98 | FM49: 199824.97 | FO49: 274102.61 | FQ49: 229069.96 | FS49: 299012.36 | FU49: 217123.58 | FW49: 265327.25 | FY49: 282037.49 | GA49: 252744 | GC49: 303670.84 | GE49: 201440 | GG49: 219544 | GI49: 181495 | GK49: 226136 | GM49: 259012.22 | GO49: 201521.62 | GQ49: 242775.75 | GS49: 238449.95 | GU49: 166551.17 | GW49: 127476.66 | GY49: 149189.58 | HA49: 139779.36 | HC49: 141771.95 | HE49: 142205.91
A51: Ratios and percentages:
A52: Debt/equity ratio | C52: =C19/C25 -> 2.785957 | E52: =E19/E25 -> 2.675476 | G52: =G19/G25 -> 2.5395071 | I52: 2.6130574 | K52: 2.8606705 | M52: 2.5565969 | O52: 2.6345025 | Q52: 2.6563316 | S52: 2.7306381 | U52: 1.9441228 | W52: 2.5273944 | Y52: 2.5090029 | AA52: 2.5281426 | AC52: 2.6138017 | AE52: 2.6314713 | AG52: 2.4310274 | AI52: 2.5040954 | AK52: 2.2681236 | AM52: 2.2836488 | AO52: 2.1964169 | AQ52: 1.986854 | AS52: 1.8954432 | AU52: 1.7341123 | AW52: 1.6989973 | AY52: 1.7372694 | BA52: 1.4811997 | BC52: 1.4442727 | BE52: 1.2793992 | BG52: 1.0379623 | BI52: 1.0021245 | BK52: 0.96766802 | BM52: 0.9838782 | BO52: 0.9439768 | BQ52: =+BQ19/BQ25 -> 0.27148382 | BS52: 0.82418572 | BU52: 0.88336601 | BW52: 3.1606897 | BY52: 3.1257057 | CA52: 2.5457518 | CC52: 2.5497521 | CE52: 2.7040541 | CG52: 2.7890769 | CI52: 2.3002029 | CK52: 2.3371785 | CM52: 2.2913506 | CO52: =+CO19/CO25 -> 2.4381492 | CQ52: =+CQ19/CQ25 -> 4.903378 | CS52: =+CS19/CS25 -> 2.7504953 | CU52: =+CU19/CU25 -> 3.6455529 | CW52: =+CW19/CW25 -> 3.8150174 | CY52: =+CY19/CY25 -> 3.7268515 | DA52: =+DA19/DA25 -> 2.9301693 | DC52: =+DC19/DC25 -> 2.9390361 | DE52: =+DE19/DE25 -> 2.6316038 | DG52: =+DG19/DG25 -> 2.3511855 | DI52: =+DI19/DI25 -> 2.0074975 | DK52: =+DK19/DK25 -> 2.0659262 | DM52: =+DM19/DM25 -> 1.9105539 | DO52: 1.9090386 | DQ52: 1.6016663 | DS52: 1.6143567 | DU52: 1.7860436 | DW52: 2.0274046 | DY52: 2.174116 | EA52: 1.6997706 | EC52: 1.6989915 | EE52: 1.7092525 | EG52: 1.6661751 | EI52: 1.6093553 | EK52: 1.6072752 | EM52: 1.6052298 | EO52: 1.5798605 | EQ52: 1.5747065 | ES52: 1.2567003 | EU52: 0.83547564 | EW52: 0.63503317 | EY52: 0.61180848 | FA52: 0.64285611 | FC52: 0.67247886 | FE52: 3.1724381 | FG52: 3.2320074 | FI52: 3.2882211 | FK52: 2.897026 | FM52: 2.8236419 | FO52: 3.2564521 | FQ52: 2.406536 | FS52: 2.4894322 | FU52: 1.4085935 | FW52: 1.1858617 | FY52: 1.0404163 | GA52: 0.81869333 | GC52: 0.79833888 | GE52: 0.7261781 | GG52: 0.7123522 | GI52: 0.7164054 | GK52: 0.48586487 | GM52: 0.51532036 | GO52: 0.6488916 | GQ52: 0.63131371 | GS52: 0.45839978 | GU52: 0.48237543 | GW52: 0.45070689 | GY52: 0.44048282 | HA52: 0.32075568 | HC52: 0.290963 | HE52: 0.27995108
A53: PAR>30 days + restructured loans/gross advances | C53: ='Covenants - Dec25'!G37 -> 0.078022146 | E53: ='Covenants - Dec25'!I37 -> 0.078549029 | G53: ='Covenants - Dec25'!K37 -> 0.081525058 | I53: ='Covenants - Dec25'!M37 -> 0.080367317 | K53: 0.081399503 | M53: 0.087621166 | O53: 0.086420848 | Q53: 0.08674479 | S53: 0.083458711 | U53: 0.11733451 | W53: 0.099638024 | Y53: 0.099532571 | AA53: 0.09013019 | AC53: 0.079981745 | AE53: 0.069510591 | AG53: 0.069128131 | AI53: 0.061912426 | AK53: 0.06205228 | AM53: 0.056762139 | AO53: 0.049948065 | AQ53: 0.044984031 | AS53: 0.0447 | AU53: 0.039468074 | AW53: 0.0431 | AY53: 0.042817934 | BA53: 0.04067319 | BC53: 0.041760987 | BE53: 0.040916738 | BG53: 0.045922195 | BI53: 0.042586859 | BK53: 0.042591592 | BM53: 0.043884235 | BO53: 0.044043654 | BQ53: ='Covenants - Dec25'!DU37 -> 0.064430639 | BS53: 0.042731749 | BU53: 0.048691469 | BW53: 0.050030707 | BY53: 0.050300102 | CA53: 0.05138579 | CC53: 0.053700973 | CE53: 0.055211194 | CG53: 0.056308591 | CI53: 0.054408356 | CK53: 0.057833173 | CM53: 0.057349047 | CO53: 0.055457232 | CQ53: 0.05298851 | CS53: 0.042175162 | CU53: 0.047732602 | CW53: 0.040234048 | CY53: 0.042517368 | DA53: 0.042420348 | DC53: 0.04213862 | DE53: 0.041880562 | DG53: 0.041192592 | DI53: 0.043445333 | DK53: 0.044302809 | DM53: 0.042759141 | DO53: 0.04308006 | DQ53: 0.064430639 | DS53: 0.076464833 | DU53: 0.079176222 | DW53: 0.094763182 | DY53: 0.11881345 | EA53: 0.12785606 | EC53: 0.12315854 | EE53: 0.11697257 | EG53: 0.12117045 | EI53: 0.088028568 | EK53: 0.041128685 | EM53: 0.0236 | EO53: 0.0307 | EQ53: 0.0304 | ES53: 0.0287 | EU53: 0.032 | EW53: 0.0281 | EY53: 0.03 | FA53: 0.0346 | FC53: 0.036002716 | FE53: 0.027171955 | FG53: 0.033418553 | FI53: 0.038743958 | FK53: 0.036699012 | FM53: 0.0459 | FO53: 0.0484 | FQ53: 0.0528 | FS53: 0.049 | FU53: 0.0531 | FW53: 0.0583 | FY53: 0.0634 | GA53: 0.0618 | GC53: 0.0687 | GE53: 0.0611 | GG53: 0.0787 | GI53: 0.078056114 | GK53: 0.078 | GM53: 0.0794 | GO53: 0.078553495 | GQ53: 0.072505686 | GS53: 0.072441202 | GU53: 0.07770388 | GW53: 0.0834 | GY53: 0.079194302 | HA53: 0.1155161 | HC53: 0.13546606 | HE53: 0.11506687
A54: Provision for default / GLP | C54: =-'Notes - Dec25'!C7/'Notes - Dec25'!C6 -> 0.15688074 | E54: =-'Notes - Dec25'!E7/'Notes - Dec25'!E6 -> 0.15409715 | G54: =-('Notes - Dec25'!G7+'Notes - Dec25'!G12)/SUM('Notes - Dec25'!G6,'Notes - Dec25'!G11) -> 0.15803955 | I54: 0.15173732 | K54: 0.15206817 | M54: 0.09263191 | O54: 0.094652753 | Q54: 0.093190666 | S54: 0.08874374 | U54: 0.11775275 | W54: 0.1074629 | Y54: 0.10382339 | AA54: 0.09360078 | AC54: 0.081248932 | AE54: 0.075603377 | AG54: 0.071051717 | AI54: 0.06769832 | AK54: 0.064265209 | AM54: 0.061784108 | AO54: 0.057391571 | AQ54: 0.051954451 | AS54: 0.049583673 | AU54: 0.043616257 | AW54: 0.046847152 | AY54: 0.04553002 | BA54: 0.044037148 | BC54: 0.046171004 | BE54: 0.04778976 | BG54: 0.048259066 | BI54: 0.050085365 | BK54: 0.048821589 | BM54: 0.048650156 | BO54: 0.048584364 | BQ54: =-SUM('Notes - Dec25'!DQ7+'Notes - Dec25'!DQ12)/SUM('Notes - Dec25'!DQ6,'Notes - Dec25'!DQ11) -> 0.066024239 | BS54: 0.045085043 | BU54: 0.042470324 | BW54: 0.045742533 | BY54: 0.043875347 | CA54: 0.04830504 | CC54: 0.048102682 | CE54: 0.050270759 | CG54: 0.049913467 | CI54: 0.04913694 | CK54: 0.051477413 | CM54: 0.053976158 | CO54: =-'Notes - Dec25'!CO7/'Notes - Dec25'!CO6 -> 0.05232999 | CQ54: =-'Notes - Dec25'!CQ7/'Notes - Dec25'!CQ6 -> 0.04814631 | CS54: =-'Notes - Dec25'!CS7/'Notes - Dec25'!CS6 -> 0.042897581 | CU54: =-'Notes - Dec25'!CU7/'Notes - Dec25'!CU6 -> 0.045084124 | CW54: =-'Notes - Dec25'!CW7/'Notes - Dec25'!CW6 -> 0.041415602 | CY54: =-'Notes - Dec25'!CY7/'Notes - Dec25'!CY6 -> 0.04025289 | DA54: =-'Notes - Dec25'!DA7/'Notes - Dec25'!DA6 -> 0.038331779 | DC54: =-'Notes - Dec25'!DC7/'Notes - Dec25'!DC6 -> 0.038904547 | DE54: =-'Notes - Dec25'!DE7/'Notes - Dec25'!DE6 -> 0.038568527 | DG54: =-'Notes - Dec25'!DG7/'Notes - Dec25'!DG6 -> 0.039385785 | DI54: =-'Notes - Dec25'!DI7/'Notes - Dec25'!DI6 -> 0.040453158 | DK54: =-'Notes - Dec25'!DK7/'Notes - Dec25'!DK6 -> 0.042853778 | DM54: =-'Notes - Dec25'!DM7/'Notes - Dec25'!DM6 -> 0.042106299 | DO54: 0.042559287 | DQ54: 0.061131569 | DS54: 0.070353179 | DU54: 0.072135122 | DW54: 0.079968934 | DY54: 0.094126018 | EA54: 0.099854502 | EC54: 0.10243639 | EE54: 0.094533558 | EG54: 0.084277108 | EI54: 0.067695934 | EK54: 0.04006388 | EM54: 0.020050953 | EO54: 0.025384559 | EQ54: 0.023574462 | ES54: 0.021314092 | EU54: 0.0209 | EW54: 0.022846845 | EY54: 0.02413893 | FA54: 0.024542279 | FC54: 0.024999118 | FE54: 0.023752473 | FG54: 0.025781234 | FI54: 0.028634404 | FK54: 0.028303782 | FM54: 0.030578061 | FO54: 0.03533704 | FQ54: 0.032646452 | FS54: 0.034651783 | FU54: 0.042183808 | FW54: 0.04301028 | FY54: 0.048811474 | GA54: 0.05374177 | GC54: 0.060201523 | GE54: 0.063471118 | GG54: 0.083837107
A55: Monthly APR - gross GLP | C55: ='Advance Analysis - Dec25'!G131 -> 0.43747624 | E55: ='Advance Analysis - Dec25'!G130 -> 0.36978786 | G55: 0.42 | I55: 0.39987977 | K55: 0.39987977 | M55: 0.40643181 | O55: 0.40778908 | Q55: 0.42793458 | S55: 0.42331647 | U55: 0.42303324 | W55: 0.36414146 | Y55: 0.39042973 | AA55: 0.43131178 | AC55: 0.41202862 | AE55: 0.39280239 | AG55: 0.4176481 | AI55: 0.43200485 | AK55: 0.43200485 | AM55: 0.40393907 | AO55: 0.40967864 | AQ55: 0.42615701 | AS55: 0.404 | AU55: 0.4027505 | AW55: 0.42326477 | AY55: 0.43144176 | BA55: 0.41030191 | BC55: 0.43115735 | BE55: 0.41273179 | BG55: 0.41814942 | BI55: 0.44391976 | BK55: 0.42643483 | BM55: 0.4400704 | BO55: 0.41180464 | BQ55: ='Advance Analysis - Dec25'!G98 -> 0.43466175 | BS55: 0.42671754 | BU55: 0.44904562 | BW55: 0.46701041 | BY55: 0.40235064 | CA55: 0.4528157 | CC55: 0.3938586 | CE55: 0.43144595 | CG55: 0.44844845 | CI55: 0.42851316 | CK55: 0.43925964 | CM55: 0.44106037 | CO55: ='Advance Analysis - Dec25'!G86 -> 0.50109493 | CQ55: ='Advance Analysis - Dec25'!G85 -> 0.43525195 | CS55: ='Advance Analysis - Dec25'!G84 -> 0.50577974 | CU55: ='Advance Analysis - Dec25'!G83 -> 0.47104948 | CW55: ='Advance Analysis - Dec25'!G82 -> 0.43697954 | CY55: =#REF! -> #REF! | DA55: =#REF! -> #REF! | DC55: =#REF! -> #REF! | DE55: =#REF! -> #REF! | DG55: =#REF! -> #REF! | DI55: =+#REF! -> #REF! | DK55: =+#REF! -> #REF! | DM55: =+#REF! -> #REF! | DO55: 0.46682005 | DQ55: 0.48297929 | DS55: 0.50804694 | DU55: 0.44954031 | DW55: 0.5103937 | DY55: 0.49128672 | EA55: 0.49871688 | EC55: 0.5201138 | EE55: 0.45429704 | EG55: 0.40894574 | EI55: 0.51748716 | EK55: 0.53360167 | EM55: 0.45499175 | EO55: 0.55 | EQ55: 0.54160064 | ES55: 0.46671946 | EU55: 0.51 | EW55: 0.48557708 | EY55: 0.55306568 | FA55: 0.57273249 | FC55: 0.54705225 | FE55: 0.55749406 | FG55: 0.62386256 | FI55: 0.6440171 | FK55: 0.55317 | FM55: 0.56073071 | FO55: 0.61441406 | FQ55: 0.5613433 | FS55: 0.58745688 | FU55: 0.59014874 | FW55: 0.65130145 | FY55: 0.61530448 | GA55: 0.68510945 | GC55: 0.61726439 | GE55: 0.64985991 | GG55: 0.78388018 | GI55: 0.63217306 | GK55: 0.70292547 | GM55: 0.75299833 | GO55: 0.6514583 | GQ55: 0.68162001 | GS55: 0.79214754 | GU55: 0.75855203 | GW55: 0.70212816 | GY55: 0.67713884 | HA55: 0.6177319 | HC55: 0.66593677 | HE55: 0.74052882

Sheet Notes - Dec25
A1: NOTES
C2: 46022 | E2: 45991 | G2: 45961 | I2: 45930 | K2: 45900 | M2: 45869 | O2: 45838 | Q2: 45808 | S2: 45777 | U2: 45747 | W2: 45716 | Y2: 45688 | AA2: 45657 | AC2: 45626 | AE2: 45596 | AG2: 45565 | AI2: 45535 | AK2: 45504 | AM2: 45473 | AO2: 45443 | AQ2: 45412 | AS2: 45382 | AU2: 45351 | AW2: 45322 | AY2: 45291 | BA2: 45260 | BC2: 45230 | BE2: 45199 | BG2: 45169 | BI2: 45138 | BK2: 45107 | BM2: 45077 | BO2: 45046 | BQ2: 45016 | BS2: 44985 | BU2: 44957 | BW2: 44926 | BY2: 44895 | CA2: 44865 | CC2: 44834 | CE2: 44804 | CG2: 44773 | CI2: 44742 | CK2: 44712 | CM2: 44681 | CO2: 44651 | CQ2: 44620 | CS2: 31-Jan-22 | CU2: 31-Dec-21 | CW2: 30-Nov-21 | CY2: 31-Oct-21 | DA2: 30-Sep-21 | DC2: 31-Aug-21 | DE2: 31-Jul-21 | DG2: 30-Jun-21 | DI2: 31-May-21 | DK2: 30-Apr-21 | DM2: 31-Mar-21 | DO2: 28-Feb-21 | DQ2: 31-Jan-21 | DS2: 31-Dec-20 | DU2: 30-Nov-20 | DW2: 31-Oct-20 | DY2: 30-Sep-20 | EA2: 31-Aug-20 | EC2: 31-July-20 | EE2: 30-June-20 | EG2: 31-May-20 | EI2: 30-Apr-20 | EK2: 31-Mar-20 | EM2: 29-Feb-20 | EO2: 31-Jan-20 | EQ2: 31-Dec-19 | ES2: 30-Nov-19 | EU2: 31-Oct-19 | EW2: 30-Sep-19 | EY2: 31-Aug-19 | FA2: 31-Jul-19 | FC2: 30-Jun-19 | FE2: 31-May-19 | FG2: 30-Apr-19 | FI2: 31-Mar-19 | FK2: 28-Feb-19 | FM2: 31-Jan-19 | FO2: 31-Dec-18 | FQ2: 30-Nov-18 | FS2: 31-Oct-18 | FU2: 30-Sep-18 | FW2: 31-Aug-18 | FY2: 43312 | GA2: 30-Jun-18 | GC2: 31-May-18 | GE2: 43220 | GG2: 43190 | GI2: 43159 | GK2: 43131 | GM2: 43100 | GO2: 43069 | GQ2: 43039
