Workbook
Name TB_PFW_2023: '[1]MasterTB(US)'!$A$4:$AA$416

Sheet TableofContent
A1: POWER FINANCIAL WELLNESS INC | F1: USD
A2: CONSOLIDATED MANAGEMENT ACCOUNTS
A3: TABLE OF CONTENT
A4: FOR PERIOD ENDED JULY 31, 2025
A5: PREPARED BY: MOSES KIGO
A6: MONTH | C6: JUL
F7: Tab
L8: JAN
L9: FEB
B10: Balance Sheet - Quarterly | L10: MAR
L11: APR
B12: Balance Sheet - Monthly | L12: MAY
L13: JUN
B14: Balance Sheet - By entity MOM | L14: JUL
L15: AUG
B16: Income Statement - Quartely | L16: SEP
L17: OCT
B18: Income Statement - Monthly | L18: NOV
L19: DEC
B20: Income Statement - For the month by entity
B22: Income Statement - By Business Unit for the month
B24: 12 Month - Cashflow Statement

Sheet BS_Qrtly
A1: =TableofContent!A1 -> POWER FINANCIAL WELLNESS INC | F1: =TableofContent!F1 -> USD
A2: =TableofContent!A2 -> CONSOLIDATED MANAGEMENT ACCOUNTS
A3: QUARTERLY BALANCE SHEET
A4: =TableofContent!A4 -> FOR PERIOD ENDED JULY 31, 2025
A5: =TableofContent!A5 -> PREPARED BY: MOSES KIGO
B7: ASSETS | C7: Q1 | D7: Q2 | E7: Q3 | F7: Q4
A8: 010 | B8: Current Assets
A9: 020 | B9: Cash & Cash Equivalents | C9: ='BS(Qrtly('!T4 -> 689896 | D9: ='BS(Qrtly('!U4 -> 653836 | E9: ='BS(Qrtly('!V4 -> 537995.66 | F9: ='BS(Qrtly('!W4 -> 0
A10: 030 | B10: Net Loan Receivable | C10: ='BS(Qrtly('!T5 -> 1172340 | D10: ='BS(Qrtly('!U5 -> 1368363 | E10: ='BS(Qrtly('!V5 -> 1645999.1 | F10: ='BS(Qrtly('!W5 -> 0
A11: 040 | B11: Interco-Receivable | C11: ='BS(Qrtly('!T6 -> 1146509 | D11: ='BS(Qrtly('!U6 -> 1324774 | E11: ='BS(Qrtly('!V6 -> 1623863.2 | F11: ='BS(Qrtly('!W6 -> 0
A12: 050 | B12: Other Current Assets | C12: ='BS(Qrtly('!T7 -> 218927 | D12: ='BS(Qrtly('!U7 -> 176172 | E12: ='BS(Qrtly('!V7 -> 181855.23 | F12: ='BS(Qrtly('!W7 -> 0
A13: 099 | B13: Total Current Assets | C13: =SUM(C9:C12) -> 3227672 | D13: =SUM(D9:D12) -> 3523145 | E13: =SUM(E9:E12) -> 3989713.2 | F13: =SUM(F9:F12) -> 0
A15: 100 | B15: Non-Current Assets
A16: 110 | B16: Gross Fixed Assets | C16: ='BS(Qrtly('!T11 -> 45208 | D16: ='BS(Qrtly('!U11 -> 46249 | E16: ='BS(Qrtly('!V11 -> 50070.5 | F16: ='BS(Qrtly('!W11 -> 0
B17: Accumilated Depreciation | C17: ='BS(Qrtly('!T12 -> -22835 | D17: ='BS(Qrtly('!U12 -> -26189 | E17: ='BS(Qrtly('!V12 -> -29699.01 | F17: ='BS(Qrtly('!W12 -> 0
A18: 120 | B18: Gross Intangible Assets | C18: ='BS(Qrtly('!T13 -> 740386 | D18: ='BS(Qrtly('!U13 -> 740386 | E18: ='BS(Qrtly('!V13 -> 740386.28 | F18: ='BS(Qrtly('!W13 -> 0
B19: Accumilated Ammortizaion | C19: ='BS(Qrtly('!T14 -> -646808 | D19: ='BS(Qrtly('!U14 -> -707313 | E19: ='BS(Qrtly('!V14 -> -735507.41 | F19: ='BS(Qrtly('!W14 -> 0
A20: 130 | B20: Interco-Receivable Long Term | C20: ='BS(Qrtly('!T15 -> 2127703 | D20: ='BS(Qrtly('!U15 -> 2127703 | E20: ='BS(Qrtly('!V15 -> 2127702.6 | F20: ='BS(Qrtly('!W15 -> 0
A21: 140 | B21: Other Long Term Assets | C21: ='BS(Qrtly('!T16 -> 19380 | D21: ='BS(Qrtly('!U16 -> 19380 | E21: ='BS(Qrtly('!V16 -> 19380.33 | F21: ='BS(Qrtly('!W16 -> 0
A22: 199 | B22: Total Non-Current Assets | C22: =SUM(C16:C21) -> 2263034 | D22: =SUM(D16:D21) -> 2200216 | E22: =SUM(E16:E21) -> 2172333.3 | F22: =SUM(F16:F21) -> 0
A24: F1 | B24: TOTAL ASSETS | C24: =C13+C22 -> 5490706 | D24: =D13+D22 -> 5723361 | E24: =E13+E22 -> 6162046.5 | F24: =F13+F22 -> 0
B26: LIABILITIES
A27: 200 | B27: Current Liabilities
A28: 210 | B28: Accounts Payable | C28: ='BS(Qrtly('!T23 -> 225656 | D28: ='BS(Qrtly('!U23 -> 227115 | E28: ='BS(Qrtly('!V23 -> 263042.26 | F28: ='BS(Qrtly('!W23 -> 0
A29: 220 | B29: Intercompany Payable | C29: ='BS(Qrtly('!T24 -> 888576 | D29: ='BS(Qrtly('!U24 -> 1046101 | E29: ='BS(Qrtly('!V24 -> 1275262.4 | F29: ='BS(Qrtly('!W24 -> 0
A30: 230 | B30: Overdraft / Revolver | C30: ='BS(Qrtly('!T25 -> 39566 | D30: ='BS(Qrtly('!U25 -> 53316 | E30: ='BS(Qrtly('!V25 -> 41005.26 | F30: ='BS(Qrtly('!W25 -> 0
A31: 240 | B31: Customer Deposits | C31: ='BS(Qrtly('!T26 -> 41667 | D31: ='BS(Qrtly('!U26 -> 28365 | E31: ='BS(Qrtly('!V26 -> 24579.65 | F31: ='BS(Qrtly('!W26 -> 0
A32: 250 | B32: Accrued Expenses | C32: ='BS(Qrtly('!T27 -> 163075 | D32: ='BS(Qrtly('!U27 -> 116305 | E32: ='BS(Qrtly('!V27 -> 119738.96 | F32: ='BS(Qrtly('!W27 -> 0
A33: 290 | B33: Total Current Liabilities | C33: =+SUM(C28:C32) -> 1358540 | D33: =+SUM(D28:D32) -> 1471202 | E33: =+SUM(E28:E32) -> 1723628.5 | F33: =+SUM(F28:F32) -> 0
A35: 300 | B35: Non-Current Liabilities
A36: 310 | B36: LT Intercompany Loan | C36: ='BS(Qrtly('!T31 -> 2362682 | D36: ='BS(Qrtly('!U31 -> 2362681 | E36: ='BS(Qrtly('!V31 -> 2475151.4 | F36: ='BS(Qrtly('!W31 -> 0
A37: 320 | B37: LT Debt | C37: ='BS(Qrtly('!T32 -> 1901589 | D37: ='BS(Qrtly('!U32 -> 2151589 | E37: ='BS(Qrtly('!V32 -> 2652200.4 | F37: ='BS(Qrtly('!W32 -> 0
A38: 390 | B38: Total Non-Current Liabilities | C38: =SUM(C36:C37) -> 4264271 | D38: =SUM(D36:D37) -> 4514270 | E38: =SUM(E36:E37) -> 5127351.8 | F38: =SUM(F36:F37) -> 0
A40: 400 | B40: EQUITY
A41: 410 | B41: Share Capital | C41: ='BS(Qrtly('!T36 -> 3984300 | D41: ='BS(Qrtly('!U36 -> 3984335 | E41: ='BS(Qrtly('!V36 -> 3984334.9 | F41: ='BS(Qrtly('!W36 -> 0
A42: 420 | B42: Parent Company Investment in Subsidiary | C42: ='BS(Qrtly('!T37 -> -8519 | D42: ='BS(Qrtly('!U37 -> -8519 | E42: ='BS(Qrtly('!V37 -> -8519.07 | F42: ='BS(Qrtly('!W37 -> 0
A43: 430 | B43: PY Retained Earnings | C43: ='BS(Qrtly('!T38 -> -3740271.1 | D43: ='BS(Qrtly('!U38 -> -3576720.9 | E43: ='BS(Qrtly('!V38 -> -891053.5 | F43: ='BS(Qrtly('!W38 -> 0
A44: 440 | B44: CY Retained Earnings | C44: ='BS(Qrtly('!T39 -> -265161.94 | D44: ='BS(Qrtly('!U39 -> -558683.07 | E44: ='BS(Qrtly('!V39 -> -3671175.6 | F44: ='BS(Qrtly('!W39 -> 0
A45: 450 | B45: CY Foreign Currency Transalation | C45: ='BS(Qrtly('!T40 -> -102453 | D45: ='BS(Qrtly('!U40 -> -102523 | E45: ='BS(Qrtly('!V40 -> -102520.58 | F45: ='BS(Qrtly('!W40 -> 0
A46: 499 | B46: Total Equity | C46: =SUM(C40:C45) -> -132105 | D46: =SUM(D40:D45) -> -262111 | E46: =SUM(E40:E45) -> -688933.85 | F46: =SUM(F40:F45) -> 0
A48: F2 | B48: TOTAL LIABILITY & SHAREHOLDER EQUITY | C48: =C33+C38+C46 -> 5490706 | D48: =D33+D38+D46 -> 5723361 | E48: =E33+E38+E46 -> 6162046.5 | F48: =F33+F38+F46 -> 0
A50: 999 | B50: Check | C50: =C24-C48 -> 0 | D50: =D24-D48 -> 0 | E50: =E24-E48 -> 0 | F50: =F24-F48 -> 0
B53: OD

Sheet BS_12MoM
A1: =TableofContent!A1 -> POWER FINANCIAL WELLNESS INC | C1: USD | O1: =TableofContent!F1 -> USD
A2: =TableofContent!A2 -> CONSOLIDATED MANAGEMENT ACCOUNTS
A3: =TableofContent!A3 -> TABLE OF CONTENT
A4: =TableofContent!A4 -> FOR PERIOD ENDED JULY 31, 2025
A5: =TableofContent!A5 -> PREPARED BY: MOSES KIGO
C8: 45657 | D8: 45658 | E8: =EOMONTH(D8,1) -> 45716 | F8: =EOMONTH(E8,1) -> 45747 | G8: =EOMONTH(F8,1) -> 45777 | H8: =EOMONTH(G8,1) -> 45808 | I8: =EOMONTH(H8,1) -> 45838 | J8: =EOMONTH(I8,1) -> 45869 | K8: =EOMONTH(J8,1) -> 45900 | L8: =EOMONTH(K8,1) -> 45930 | ... O8: =EOMONTH(N8,1) -> 46022
B9: ASSETS
A10: 010 | B10: Current Assets
A11: 020 | B11: Cash & Cash Equivalents | C11: 627920 | D11: ='BS (MoM)'!T4 -> 794294.22 | E11: ='BS (MoM)'!U4 -> 760065.78 | F11: ='BS (MoM)'!V4 -> 689215.17 | G11: ='BS (MoM)'!W4 -> 828564.78 | H11: ='BS (MoM)'!X4 -> 888683.76 | I11: ='BS (MoM)'!Y4 -> 653154.78 | J11: ='BS (MoM)'!Z4 -> 511499.83 | K11: ='BS (MoM)'!AA4 -> 445399.48 | ... O11: ='BS (MoM)'!AE4 -> 0
A12: 030 | B12: Net Loan Receivable | C12: 805429 | D12: ='BS (MoM)'!T5 -> 1012498.9 | E12: ='BS (MoM)'!U5 -> 1178406.4 | F12: ='BS (MoM)'!V5 -> 1172488.3 | G12: ='BS (MoM)'!W5 -> 1229612.8 | H12: ='BS (MoM)'!X5 -> 1285940.7 | I12: ='BS (MoM)'!Y5 -> 1368511.6 | J12: ='BS (MoM)'!Z5 -> 1435517.8 | K12: ='BS (MoM)'!AA5 -> 1548630.6 | ... O12: ='BS (MoM)'!AE5 -> 0
A13: 040 | B13: Interco-Receivable | C13: 885375 | D13: ='BS (MoM)'!T6 -> 982416.07 | E13: ='BS (MoM)'!U6 -> 1106888 | F13: ='BS (MoM)'!V6 -> 1146508.9 | G13: ='BS (MoM)'!W6 -> 1222569.7 | H13: ='BS (MoM)'!X6 -> 1301171.1 | I13: ='BS (MoM)'!Y6 -> 1324774.1 | J13: ='BS (MoM)'!Z6 -> 1515179.9 | K13: ='BS (MoM)'!AA6 -> 1566113 | ... O13: ='BS (MoM)'!AE6 -> 0
A14: 050 | B14: Other Current Assets | C14: 245167 | D14: ='BS (MoM)'!T7 -> 250633.59 | E14: ='BS (MoM)'!U7 -> 241222.22 | F14: ='BS (MoM)'!V7 -> 226124.11 | G14: ='BS (MoM)'!W7 -> 222716.97 | H14: ='BS (MoM)'!X7 -> 200695.6 | I14: ='BS (MoM)'!Y7 -> 179384.61 | J14: ='BS (MoM)'!Z7 -> 176608.82 | K14: ='BS (MoM)'!AA7 -> 175775.56 | ... O14: ='BS (MoM)'!AE7 -> 0
A15: 099 | B15: Total Current Assets | C15: 2563891 | D15: =SUM(D11:D14) -> 3039842.8 | E15: =SUM(E11:E14) -> 3286582.3 | F15: =SUM(F11:F14) -> 3234336.5 | G15: =SUM(G11:G14) -> 3503464.3 | H15: =SUM(H11:H14) -> 3676491.2 | I15: =SUM(I11:I14) -> 3525825 | J15: =SUM(J11:J14) -> 3638806.3 | K15: =SUM(K11:K14) -> 3735918.7 | ... O15: =SUM(O11:O14) -> 0
D16: =D15-'BS (MoM)'!T8 -> 0 | E16: =E15-'BS (MoM)'!U8 -> 0 | F16: =F15-'BS (MoM)'!V8 -> 0 | G16: =G15-'BS (MoM)'!W8 -> 0 | H16: =H15-'BS (MoM)'!X8 -> 0 | I16: =I15-'BS (MoM)'!Y8 -> 0 | J16: =J15-'BS (MoM)'!Z8 -> 0
A17: 100 | B17: Non-Current Assets
A18: 110 | B18: Gross Fixed Assets | C18: 34348 | D18: ='BS (MoM)'!T11 -> 36694.76 | E18: ='BS (MoM)'!U11 -> 41233.54 | F18: ='BS (MoM)'!V11 -> 45208.34 | G18: ='BS (MoM)'!W11 -> 45728.89 | H18: ='BS (MoM)'!X11 -> 45728.89 | I18: ='BS (MoM)'!Y11 -> 46249.44 | J18: ='BS (MoM)'!Z11 -> 48005.79 | K18: ='BS (MoM)'!AA11 -> 48005.79 | ... O18: ='BS (MoM)'!AE11 -> 0
B19: Accumilated Depreciation | C19: -19654 | D19: ='BS (MoM)'!T12 -> -20655.06 | E19: ='BS (MoM)'!U12 -> -21744.16 | F19: ='BS (MoM)'!V12 -> -22835.56 | G19: ='BS (MoM)'!W12 -> -23934.75 | H19: ='BS (MoM)'!X12 -> -25025.55 | I19: ='BS (MoM)'!Y12 -> -26189.93 | J19: ='BS (MoM)'!Z12 -> -27342.11 | K19: ='BS (MoM)'!AA12 -> -28494.85 | ... O19: ='BS (MoM)'!AE12 -> 0
B20: Gross Intangible Assets | C20: 740386 | D20: ='BS (MoM)'!T13 -> 740386.28 | E20: ='BS (MoM)'!U13 -> 740386.28 | F20: ='BS (MoM)'!V13 -> 740386.28 | G20: ='BS (MoM)'!W13 -> 740386.28 | H20: ='BS (MoM)'!X13 -> 740386.28 | I20: ='BS (MoM)'!Y13 -> 740386.28 | J20: ='BS (MoM)'!Z13 -> 740386.28 | K20: ='BS (MoM)'!AA13 -> 740386.28 | ... O20: ='BS (MoM)'!AE13 -> 0
A21: 120 | B21: Accumilated Ammortizaion | C21: -586303 | D21: ='BS (MoM)'!T14 -> -606461.87 | E21: ='BS (MoM)'!U14 -> -626639.84 | F21: ='BS (MoM)'!V14 -> -646808.06 | G21: ='BS (MoM)'!W14 -> -666976.28 | H21: ='BS (MoM)'!X14 -> -687144.5 | I21: ='BS (MoM)'!Y14 -> -707312.72 | J21: ='BS (MoM)'!Z14 -> -727478.37 | K21: ='BS (MoM)'!AA14 -> -735219.71 | ... O21: ='BS (MoM)'!AE14 -> 0
A22: 130 | B22: Interco-Receivable Long Term | C22: 2127703 | D22: ='BS (MoM)'!T15 -> 2127702.6 | E22: ='BS (MoM)'!U15 -> 2127702.6 | F22: ='BS (MoM)'!V15 -> 2127702.6 | G22: ='BS (MoM)'!W15 -> 2127702.6 | H22: ='BS (MoM)'!X15 -> 2127702.6 | I22: ='BS (MoM)'!Y15 -> 2127702.6 | J22: ='BS (MoM)'!Z15 -> 2127702.6 | K22: ='BS (MoM)'!AA15 -> 2127702.6 | ... O22: ='BS (MoM)'!AE15 -> 0
A23: 140 | B23: Other Long Term Assets | C23: 19380 | D23: ='BS (MoM)'!T16 -> 19380.33 | E23: ='BS (MoM)'!U16 -> 19380.33 | F23: ='BS (MoM)'!V16 -> 19380.33 | G23: ='BS (MoM)'!W16 -> 19380.33 | H23: ='BS (MoM)'!X16 -> 19380.33 | I23: ='BS (MoM)'!Y16 -> 19380.33 | J23: ='BS (MoM)'!Z16 -> 19380.33 | K23: ='BS (MoM)'!AA16 -> 19380.33 | ... O23: ='BS (MoM)'!AE16 -> 0
A24: 199 | B24: Total Non-Current Assets | C24: 2315860 | D24: =SUM(D18:D23) -> 2297047.1 | E24: =SUM(E18:E23) -> 2280318.8 | F24: =SUM(F18:F23) -> 2263034 | G24: =SUM(G18:G23) -> 2242287.1 | H24: =SUM(H18:H23) -> 2221028.1 | I24: =SUM(I18:I23) -> 2200216 | J24: =SUM(J18:J23) -> 2180654.5 | K24: =SUM(K18:K23) -> 2171760.5 | ... O24: =SUM(O18:O23) -> 0
D25: =D24-'BS (MoM)'!T17 -> 0 | E25: =E24-'BS (MoM)'!U17 -> 0 | F25: =F24-'BS (MoM)'!V17 -> 0 | G25: =G24-'BS (MoM)'!W17 -> 0 | H25: =H24-'BS (MoM)'!X17 -> 0 | I25: =I24-'BS (MoM)'!Y17 -> 0 | J25: =J24-'BS (MoM)'!Z17 -> 0
A26: F1 | B26: TOTAL ASSETS | C26: 4879751 | D26: =D15+D24 -> 5336889.8 | E26: =E15+E24 -> 5566901.1 | F26: =F15+F24 -> 5497370.5 | G26: =G15+G24 -> 5745751.4 | H26: =H15+H24 -> 5897519.2 | I26: =I15+I24 -> 5726041 | J26: =J15+J24 -> 5819460.8 | K26: =K15+K24 -> 5907679.2 | ... O26: =O15+O24 -> 0
D27: =D26-'BS (MoM)'!T19 -> 0 | E27: =E26-'BS (MoM)'!U19 -> 0 | F27: =F26-'BS (MoM)'!V19 -> 0 | G27: =G26-'BS (MoM)'!W19 -> 0 | H27: =H26-'BS (MoM)'!X19 -> 0 | I27: =I26-'BS (MoM)'!Y19 -> 0 | J27: =J26-'BS (MoM)'!Z19 -> 0
B28: LIABILITIES
A29: 200 | B29: Current Liabilities
A30: 210 | B30: Accounts Payable | C30: 210772 | D30: ='BS (MoM)'!T23 -> 211779.54 | E30: ='BS (MoM)'!U23 -> 264518.05 | F30: ='BS (MoM)'!V23 -> 232743.31 | G30: ='BS (MoM)'!W23 -> 238795.28 | H30: ='BS (MoM)'!X23 -> 254436.56 | I30: ='BS (MoM)'!Y23 -> 226911.26 | J30: ='BS (MoM)'!Z23 -> 223287.34 | K30: ='BS (MoM)'!AA23 -> 251091.45 | ... O30: ='BS (MoM)'!AE23 -> 0
A31: 220 | B31: Intercompany Payable | C31: 802096 | D31: ='BS (MoM)'!T24 -> 837980.14 | E31: ='BS (MoM)'!U24 -> 877292.44 | F31: ='BS (MoM)'!V24 -> 889454.08 | G31: ='BS (MoM)'!W24 -> 978004.81 | H31: ='BS (MoM)'!X24 -> 1029008.8 | I31: ='BS (MoM)'!Y24 -> 1048129.6 | J31: ='BS (MoM)'!Z24 -> 1147017.8 | K31: ='BS (MoM)'!AA24 -> 1201727.5 | ... O31: ='BS (MoM)'!AE24 -> 0
A32: 230 | B32: Overdraft / Revolver | C32: 10480 | D32: ='BS (MoM)'!T25 -> 38451.08 | E32: ='BS (MoM)'!U25 -> 36766.55 | F32: ='BS (MoM)'!V25 -> 39566.48 | G32: ='BS (MoM)'!W25 -> 50222.48 | H32: ='BS (MoM)'!X25 -> 62311.74 | I32: ='BS (MoM)'!Y25 -> 53316.19 | J32: ='BS (MoM)'!Z25 -> 47805.79 | K32: ='BS (MoM)'!AA25 -> 47832.43 | ... O32: ='BS (MoM)'!AE25 -> 0
A33: 240 | B33: Customer Deposits | C33: 56935 | D33: ='BS (MoM)'!T26 -> 59745.29 | E33: ='BS (MoM)'!U26 -> 55499.67 | F33: ='BS (MoM)'!V26 -> 44520.22 | G33: ='BS (MoM)'!W26 -> 40256.77 | H33: ='BS (MoM)'!X26 -> 40358.9 | I33: ='BS (MoM)'!Y26 -> 31460.67 | J33: ='BS (MoM)'!Z26 -> 27121.27 | K33: ='BS (MoM)'!AA26 -> 26818.42 | ... O33: ='BS (MoM)'!AE26 -> 0
A34: 250 | B34: Accrued Expenses | C34: 154928 | D34: ='BS (MoM)'!T27 -> 163267.9 | E34: ='BS (MoM)'!U27 -> 167894.01 | F34: ='BS (MoM)'!V27 -> 173427.15 | G34: ='BS (MoM)'!W27 -> 170432.59 | H34: ='BS (MoM)'!X27 -> 160015.16 | I34: ='BS (MoM)'!Y27 -> 142263.18 | J34: ='BS (MoM)'!Z27 -> 127670.45 | K34: ='BS (MoM)'!AA27 -> 114885.19 | ... O34: ='BS (MoM)'!AE27 -> 0
A35: 290 | B35: Total Current Liabilities | C35: 1235211 | D35: =+SUM(D30:D34) -> 1311223.9 | E35: =+SUM(E30:E34) -> 1401970.7 | F35: =+SUM(F30:F34) -> 1379711.2 | G35: =+SUM(G30:G34) -> 1477711.9 | H35: =+SUM(H30:H34) -> 1546131.1 | I35: =+SUM(I30:I34) -> 1502080.9 | J35: =+SUM(J30:J34) -> 1572902.7 | K35: =+SUM(K30:K34) -> 1642355 | ... O35: =+SUM(O30:O34) -> 0
D36: =D35-'BS (MoM)'!T28 -> 0 | E36: =E35-'BS (MoM)'!U28 -> 0 | F36: =F35-'BS (MoM)'!V28 -> 0 | G36: =G35-'BS (MoM)'!W28 -> 0 | H36: =H35-'BS (MoM)'!X28 -> 0 | I36: =I35-'BS (MoM)'!Y28 -> 0 | J36: =J35-'BS (MoM)'!Z28 -> 0
A37: 300 | B37: Non-Current Liabilities
A38: 310 | B38: LT Intercompany Loan | C38: 2246529 | D38: ='BS (MoM)'!T31 -> 2317595 | E38: ='BS (MoM)'!U31 -> 2352226.5 | F38: ='BS (MoM)'!V31 -> 2362682 | G38: ='BS (MoM)'!W31 -> 2362682 | H38: ='BS (MoM)'!X31 -> 2392698.7 | I38: ='BS (MoM)'!Y31 -> 2362681 | J38: ='BS (MoM)'!Z31 -> 2475151.4 | K38: ='BS (MoM)'!AA31 -> 2475151.4 | ... O38: ='BS (MoM)'!AE31 -> 0
A39: 320 | B39: LT Debt | C39: 821021 | D39: ='BS (MoM)'!T32 -> 1681108.4 | E39: ='BS (MoM)'!U32 -> 1881589.2 | F39: ='BS (MoM)'!V32 -> 1901589.2 | G39: ='BS (MoM)'!W32 -> 2151589.2 | H39: ='BS (MoM)'!X32 -> 2301667.3 | I39: ='BS (MoM)'!Y32 -> 2301667.3 | J39: ='BS (MoM)'!Z32 -> 2301667.3 | K39: ='BS (MoM)'!AA32 -> 2402200.4 | ... O39: ='BS (MoM)'!AE32 -> 0
A40: 390 | B40: Total Non-Current Liabilities | C40: 3067550 | D40: =SUM(D38:D39) -> 3998703.5 | E40: =SUM(E38:E39) -> 4233815.6 | F40: =SUM(F38:F39) -> 4264271.2 | G40: =SUM(G38:G39) -> 4514271.2 | H40: =SUM(H38:H39) -> 4694365.9 | I40: =SUM(I38:I39) -> 4664348.3 | J40: =SUM(J38:J39) -> 4776818.7 | K40: =SUM(K38:K39) -> 4877351.8 | ... O40: =SUM(O38:O39) -> 0
D41: =D40-'BS (MoM)'!T33 -> 0 | E41: =E40-'BS (MoM)'!U33 -> 0 | F41: =F40-'BS (MoM)'!V33 -> 0 | G41: =G40-'BS (MoM)'!W33 -> 0 | H41: =H40-'BS (MoM)'!X33 -> 0 | I41: =I40-'BS (MoM)'!Y33 -> 0 | J41: =J40-'BS (MoM)'!Z33 -> 0
A42: 400 | B42: EQUITY
A43: 410 | B43: Share Capital | C43: 4434300 | D43: ='BS (MoM)'!T36 -> 3984299.9 | E43: ='BS (MoM)'!U36 -> 3984299.9 | F43: ='BS (MoM)'!V36 -> 3984299.9 | G43: ='BS (MoM)'!W36 -> 3984299.9 | H43: ='BS (MoM)'!X36 -> 3984334.9 | I43: ='BS (MoM)'!Y36 -> 3984334.9 | J43: ='BS (MoM)'!Z36 -> 3984334.9 | K43: ='BS (MoM)'!AA36 -> 3984334.9 | ... O43: ='BS (MoM)'!AE36 -> 0
A44: 420 | B44: Parent Company Investment in Subsidiary | C44: -8519 | D44: ='BS (MoM)'!T37 -> -8519.07 | E44: ='BS (MoM)'!U37 -> -8519.07 | F44: ='BS (MoM)'!V37 -> -8519.07 | G44: ='BS (MoM)'!W37 -> -8519.07 | H44: ='BS (MoM)'!X37 -> -8519.07 | I44: ='BS (MoM)'!Y37 -> -8519.07 | J44: ='BS (MoM)'!Z37 -> -8519.07 | K44: ='BS (MoM)'!AA37 -> -8519.07 | ... O44: ='BS (MoM)'!AE37 -> 0
A45: 430 | B45: PY Retained Earnings | C45: -891054 | D45: ='BS (MoM)'!T38 -> -891053.5 | E45: ='BS (MoM)'!U38 -> -891053.5 | F45: ='BS (MoM)'!V38 -> -891053.5 | G45: ='BS (MoM)'!W38 -> -891053.5 | H45: ='BS (MoM)'!X38 -> -891053.5 | I45: ='BS (MoM)'!Y38 -> -891053.5 | J45: ='BS (MoM)'!Z38 -> -891053.5 | K45: ='BS (MoM)'!AA38 -> -891053.5 | ... O45: ='BS (MoM)'!AE38 -> 0
A46: 440 | B46: CY Retained Earnings | C46: -2864758 | D46: ='BS (MoM)'!T39 -> -2955381.9 | E46: ='BS (MoM)'!U39 -> -3051196.8 | F46: ='BS (MoM)'!V39 -> -3128884.7 | G46: ='BS (MoM)'!W39 -> -3228485.1 | H46: ='BS (MoM)'!X39 -> -3325250.3 | I46: ='BS (MoM)'!Y39 -> -3422629.4 | J46: ='BS (MoM)'!Z39 -> -3512502 | K46: ='BS (MoM)'!AA39 -> -3594269.3 | ... O46: ='BS (MoM)'!AE39 -> 0
A47: 450 | B47: CY Foreign Currency Transalation | C47: -92979 | D47: ='BS (MoM)'!T40 -> -102383.09 | E47: ='BS (MoM)'!U40 -> -102415.76 | F47: ='BS (MoM)'!V40 -> -102454.64 | G47: ='BS (MoM)'!W40 -> -102473.99 | H47: ='BS (MoM)'!X40 -> -102489.89 | I47: ='BS (MoM)'!Y40 -> -102521.17 | J47: ='BS (MoM)'!Z40 -> -102520.84 | K47: ='BS (MoM)'!AA40 -> -102520.71 | ... O47: ='BS (MoM)'!AE40 -> 0
A48: 499 | B48: Total Equity | C48: 576990 | D48: =SUM(D42:D47) -> 26962.39 | E48: =SUM(E42:E47) -> -68885.25 | F48: =SUM(F42:F47) -> -146611.99 | G48: =SUM(G42:G47) -> -246231.79 | H48: =SUM(H42:H47) -> -342977.81 | I48: =SUM(I42:I47) -> -440388.18 | J48: =SUM(J42:J47) -> -530260.51 | K48: =SUM(K42:K47) -> -612027.66 | ... O48: =SUM(O42:O47) -> 0
A50: F2 | B50: TOTAL LIABILITY & SHAREHOLDER EQUITY | C50: 4879751 | D50: =D35+D40+D48 -> 5336889.8 | E50: =E35+E40+E48 -> 5566901.1 | F50: =F35+F40+F48 -> 5497370.5 | G50: =G35+G40+G48 -> 5745751.4 | H50: =H35+H40+H48 -> 5897519.2 | I50: =I35+I40+I48 -> 5726041 | J50: =J35+J40+J48 -> 5819460.8 | K50: =K35+K40+K48 -> 5907679.2 | ... O50: =O35+O40+O48 -> 0
C53: 0 | D53: =D26-D50 -> 0 | E53: =E26-E50 -> 0 | F53: =F26-F50 -> 0 | G53: =G26-G50 -> 0 | H53: =H26-H50 -> 0 | I53: =I26-I50 -> 0 | J53: =J26-J50 -> 0 | K53: =K26-K50 -> 0 | ... O53: =O26-O50 -> 0
D56: =D46-C46 -> -90623.85 | E56: =E46-D46 -> -95814.97 | F56: =F46-E46 -> -77687.86 | G56: =G46-F46 -> -99600.45 | H56: =H46-G46 -> -96765.16 | I56: =I46-H46 -> -97379.09

Sheet IS_Qrtly
A1: =TableofContent!A1 -> POWER FINANCIAL WELLNESS INC
A2: =TableofContent!A2 -> CONSOLIDATED MANAGEMENT ACCOUNTS
A3: =TableofContent!A3 -> TABLE OF CONTENT
A4: =TableofContent!A4 -> FOR PERIOD ENDED JULY 31, 2025
A5: =TableofContent!A5 -> PREPARED BY: MOSES KIGO
A7: H1 | B7: PROFIT & LOSS STATMENT | C7: Q1 | D7: Q2 | E7: Q3 | F7: Q4 | G7: Total
A9: L11 | B9: Interest Income : Loans | C9: =IS_QRT!T4 -> 93617.54 | D9: =IS_QRT!U4 -> 123446 | E9: =IS_QRT!V4 -> 155737.86 | F9: =IS_QRT!W4 -> 0 | G9: =SUM(C9:F9) -> 372801.4
A10: L12 | B10: Interest Income : Other | C10: =IS_QRT!T5 -> 15946.26 | D10: =IS_QRT!U5 -> 18143.1 | E10: =IS_QRT!V5 -> 19358 | F10: =IS_QRT!W5 -> 0 | G10: =SUM(C10:F10) -> 53447.36
A11: L13 | B11: Interest Expense : Borrowings | C11: =IS_QRT!T6 -> -72218.65 | D11: =IS_QRT!U6 -> -84365.81 | E11: =IS_QRT!V6 -> -101120.98 | F11: =IS_QRT!W6 -> 0 | G11: =SUM(C11:F11) -> -257705.44
A12: F1 | B12: NET INTEREST INCOME | C12: =SUM(C9:C11) -> 37345.15 | D12: =SUM(D9:D11) -> 57223.29 | E12: =SUM(E9:E11) -> 73974.88 | F12: =SUM(F9:F11) -> 0 | G12: =SUM(G9:G11) -> 168543.32
A14: L21 | B14: Fee Income | C14: =IS_QRT!T9 -> 72525.11 | D14: =IS_QRT!U9 -> 81593.76 | E14: =IS_QRT!V9 -> 125169.6 | F14: =IS_QRT!W9 -> 0 | G14: =SUM(C14:F14) -> 279288.47
A15: L22 | B15: Commisions | C15: =IS_QRT!T10 -> 1797.73 | D15: =IS_QRT!U10 -> 2250.06 | E15: =IS_QRT!V10 -> 2696.97 | F15: =IS_QRT!W10 -> 0 | G15: =SUM(C15:F15) -> 6744.76
A16: L23 | B16: Other Fees & Charges | C16: =IS_QRT!T11 -> 37500 | D16: =IS_QRT!U11 -> 37500 | E16: =IS_QRT!V11 -> 9027.74 | F16: =IS_QRT!W11 -> 0 | G16: =SUM(C16:F16) -> 84027.74
A17: F2 | B17: FEES & COMMISIONS | C17: =SUM(C14:C16) -> 111822.84 | D17: =SUM(D14:D16) -> 121343.82 | E17: =SUM(E14:E16) -> 136894.31 | F17: =SUM(F14:F16) -> 0 | G17: =SUM(G14:G16) -> 370060.97
A19: F3 | B19: NET INCOME | C19: =C12+C17 -> 149167.99 | D19: =D12+D17 -> 178567.11 | E19: =E12+E17 -> 210869.19 | F19: =F12+F17 -> 0 | G19: =G12+G17 -> 538604.29
A21: L31 | B21: Loan Impairment | C21: =-IS_QRT!T16 -> -17627.69 | D21: =-IS_QRT!U16 -> -19020.88 | E21: =IS_QRT!V16 -> 32551.74 | F21: =IS_QRT!W16 -> 0 | G21: =SUM(C21:F21) -> -4096.83
A22: L32 | B22: Third Party Charges | C22: =-IS_QRT!T17 -> -3187.61 | D22: =-IS_QRT!U17 -> -3178.77 | E22: =IS_QRT!V17 -> 3999.74 | F22: =IS_QRT!W17 -> 0 | G22: =SUM(C22:F22) -> -2366.64
A23: F4 | B23: TOTAL INDIRECT COSTS | C23: =SUM(C21:C22) -> -20815.3 | D23: =SUM(D21:D22) -> -22199.65 | E23: =SUM(E21:E22) -> 36551.48 | F23: =SUM(F21:F22) -> 0 | G23: =SUM(G21:G22) -> -6463.47
A25: F5 | B25: GROSS MARGINS | C25: =C19+C23 -> 128352.69 | D25: =D19+D23 -> 156367.46 | E25: =E19-E23 -> 174317.71 | F25: =F19-F23 -> 0 | G25: =G19-G23 -> 545067.76
A27: L41 | B27: Sales & Marketing | C27: =-IS_QRT!T22 -> -47535.44 | D27: =-IS_QRT!U22 -> -65341.06 | E27: =IS_QRT!V22 -> 51643.32 | F27: =IS_QRT!W22 -> 0 | G27: =SUM(C27:F27) -> -61233.18
A28: L42 | B28: General & Adminisrative Expenses | C28: =-IS_QRT!T23+IS_QRT!T24 -> -248956.24 | D28: =-IS_QRT!U23+IS_QRT!U24 -> -286842.36 | E28: =IS_QRT!V23 -> 313842.16 | F28: =IS_QRT!W23 -> 0 | G28: =SUM(C28:F28) -> -221956.44
E29: =IS_QRT!V24 -> 43.82 | F29: =IS_QRT!W24 -> 0 | G29: =SUM(C29:F29) -> 43.82
A30: F6 | B30: EBITDAM | C30: =C25+C27+C28-C29 -> -168138.99 | D30: =D25+D27+D28-D29 -> -195815.96 | E30: =E25+E27+E28-E29 -> 539759.37 | F30: =F25+F27+F28-F29 -> 0 | G30: =G25+G27+G28-G29 -> 261834.32
B33: EBITDA | C33: =C30-C32 -> -168138.99 | D33: =D30-D32 -> -195815.96 | E33: =E30-E32 -> 539759.37 | F33: =F30-F32 -> 0 | G33: =SUM(C33:F33) -> 175804.42
A35: L51 | B35: Depreciations | C35: =-IS_QRT!T30 -> -3175.8 | D35: =-IS_QRT!U30 -> -3349.59 | E35: =IS_QRT!V30 -> 3509.08 | F35: =IS_QRT!W30 -> 0 | G35: =SUM(C35:F35) -> -3016.31
A36: L52 | B36: Ammortization | C36: =-IS_QRT!T31 -> -60503.02 | D36: =-IS_QRT!U31 -> -60503.01 | E36: =IS_QRT!V31 -> 28194.69 | F36: =IS_QRT!W31 -> 0 | G36: =SUM(C36:F36) -> -92811.34
A37: L53 | B37: Finance Cost | C37: =-IS_QRT!T32 -> -27960.13 | D37: =-IS_QRT!U32 -> -22176.97 | E37: =IS_QRT!V32 -> 16806.58 | F37: =IS_QRT!W32 -> 0 | G37: =SUM(C37:F37) -> -33330.52
A38: L54 | B38: Head Office Allocation | C38: =-IS_QRT!T33 -> -5384 | D38: =-IS_QRT!U33 -> -11675.6 | E38: =IS_QRT!V33 -> 8716.94 | F38: =IS_QRT!W33 -> 0 | G38: =SUM(C38:F38) -> -8342.66
B40: Earning Before Tax | C40: =C33+SUM(C35:C38) -> -265161.94 | D40: =D33+SUM(D35:D38) -> -293521.13 | E40: =E33-SUM(E35:E38) -> 482532.08 | F40: =F33-SUM(F35:F38) -> 0 | G40: =G33+SUM(G35:G38) -> 38303.59

Sheet IS_12MoM
A1: =TableofContent!A1 -> POWER FINANCIAL WELLNESS INC | O1: =TableofContent!F1 -> USD
A2: =TableofContent!A2 -> CONSOLIDATED MANAGEMENT ACCOUNTS
A3: =TableofContent!A3 -> TABLE OF CONTENT
A4: =TableofContent!A4 -> FOR PERIOD ENDED JULY 31, 2025
A5: =TableofContent!A5 -> PREPARED BY: MOSES KIGO
A8: H1 | B8: PROFIT & LOSS STATMENT | C8: 45658 | D8: =EOMONTH(C8,1) -> 45716 | E8: =EOMONTH(D8,1) -> 45747 | F8: =EOMONTH(E8,1) -> 45777 | G8: =EOMONTH(F8,1) -> 45808 | H8: =EOMONTH(G8,1) -> 45838 | I8: =EOMONTH(H8,1) -> 45869 | J8: =EOMONTH(I8,1) -> 45900 | K8: =EOMONTH(J8,1) -> 45930 | ... N8: =EOMONTH(M8,1) -> 46022 | O8: Total
A10: L11 | B10: Interest Income : Loans | C10: =IS_MOM!U4 -> 28635.54 | D10: =IS_MOM!V4 -> 29287.07 | E10: =IS_MOM!W4 -> 35674.46 | F10: =IS_MOM!X4 -> 40096.28 | G10: =IS_MOM!Y4 -> 42886.19 | H10: =IS_MOM!Z4 -> 40458.8 | I10: =IS_MOM!AA4 -> 51807.68 | J10: =IS_MOM!AB4 -> 52010.58 | ... N10: =IS_MOM!AF4 -> 0 | O10: =SUM(C10:N10) -> 372776.2
A11: L12 | B11: Interest Income : Other | C11: =IS_MOM!U5 -> 4932.24 | D11: =IS_MOM!V5 -> 4938.98 | E11: =IS_MOM!W5 -> 6075.04 | F11: =IS_MOM!X5 -> 4891.52 | G11: =IS_MOM!Y5 -> 5987.87 | H11: =IS_MOM!Z5 -> 7263.71 | I11: =IS_MOM!AA5 -> 8820.37 | J11: =IS_MOM!AB5 -> 5472.76 | ... N11: =IS_MOM!AF5 -> 0 | O11: =SUM(C11:N11) -> 53447.36
A12: L13 | B12: Interest Expense : Borrowings | C12: =IS_MOM!U6 -> -23709.39 | D12: =IS_MOM!V6 -> -22451.36 | E12: =IS_MOM!W6 -> -26057.9 | F12: =IS_MOM!X6 -> -25911.72 | G12: =IS_MOM!Y6 -> -28550.58 | H12: =IS_MOM!Z6 -> -29903.51 | I12: =IS_MOM!AA6 -> -32709.78 | J12: =IS_MOM!AB6 -> -34007.49 | ... N12: =IS_MOM!AF6 -> 0 | O12: =SUM(C12:N12) -> -257705.44
A13: F1 | B13: NET INTEREST INCOME | C13: =SUM(C10:C12) -> 9858.39 | D13: =SUM(D10:D12) -> 11774.69 | E13: =SUM(E10:E12) -> 15691.6 | F13: =SUM(F10:F12) -> 19076.08 | G13: =SUM(G10:G12) -> 20323.48 | H13: =SUM(H10:H12) -> 17819 | I13: =SUM(I10:I12) -> 27918.27 | J13: =SUM(J10:J12) -> 23475.85 | ... O13: =SUM(O10:O12) -> 168518.12
A15: L21 | B15: Fee Income | C15: =IS_MOM!U9 -> 32362.17 | D15: =IS_MOM!V9 -> 29717.12 | E15: =IS_MOM!W9 -> 29960.97 | F15: =IS_MOM!X9 -> 33589.21 | G15: =IS_MOM!Y9 -> 36108.68 | H15: =IS_MOM!Z9 -> 31395.87 | I15: =IS_MOM!AA9 -> 36615.18 | J15: =IS_MOM!AB9 -> 42400.68 | ... N15: =IS_MOM!AF9 -> 0 | O15: =SUM(C15:N15) -> 318303.62
A16: L22 | B16: Commisions | C16: =IS_MOM!U10 -> 658.37 | D16: =IS_MOM!V10 -> 602.98 | E16: =IS_MOM!W10 -> 536.38 | F16: =IS_MOM!X10 -> 852.05 | G16: =IS_MOM!Y10 -> 804.28 | H16: =IS_MOM!Z10 -> 593.73 | I16: =IS_MOM!AA10 -> 910.39 | J16: =IS_MOM!AB10 -> 926.12 | ... N16: =IS_MOM!AF10 -> 0 | O16: =SUM(C16:N16) -> 6744.76
A17: L23 | B17: Other Fees & Charges | C17: =IS_MOM!U11 -> 6507.52 | D17: =IS_MOM!V11 -> 6253.8 | E17: 7226.37 | F17: 6379.02 | G17: =6253.8-2166.94 -> 4086.86 | H17: =6253.8-107.27 -> 6146.53 | I17: =IS_MOM!AA11--'IS_BU(MoM)'!W28 -> 7104.26 | J17: =IS_MOM!AB11 -> 253.8 | K17: =IS_MOM!AC11 -> 2520.14 | L17: =IS_MOM!AD11 -> 0 | M17: =IS_MOM!AE11 -> 0 | N17: =IS_MOM!AF11 -> 0 | O17: =SUM(C17:N17) -> 46478.3
A18: F2 | B18: FEES & COMMISIONS | C18: =SUM(C15:C17) -> 39528.06 | D18: =SUM(D15:D17) -> 36573.9 | E18: =SUM(E15:E17) -> 37723.72 | F18: =SUM(F15:F17) -> 40820.28 | G18: =SUM(G15:G17) -> 40999.82 | H18: =SUM(H15:H17) -> 38136.13 | I18: =SUM(I15:I17) -> 44629.83 | J18: =SUM(J15:J17) -> 43580.6 | ... O18: =SUM(O15:O17) -> 371526.68
A20: F3 | B20: NET INCOME | C20: =C13+C18 -> 49386.45 | D20: =D13+D18 -> 48348.59 | E20: =E13+E18 -> 53415.32 | F20: =F13+F18 -> 59896.36 | G20: =G13+G18 -> 61323.3 | H20: =H13+H18 -> 55955.13 | I20: =I13+I18 -> 72548.1 | J20: =J13+J18 -> 67056.45 | ... O20: =O13+O18 -> 540044.8
A22: L31 | B22: Loan Impairment | C22: =-IS_MOM!U16 -> -5295.01 | D22: =-IS_MOM!V16 -> -4392.29 | E22: =-IS_MOM!W16 -> -7940.39 | F22: =-IS_MOM!X16 -> -6951.63 | G22: =-IS_MOM!Y16 -> -8438.4 | H22: =-IS_MOM!Z16 -> -3630.85 | I22: =-IS_MOM!AA16 -> -8102.46 | J22: =-IS_MOM!AB16 -> -13977.54 | ... N22: =-IS_MOM!AF16 -> 0 | O22: =SUM(C22:N22) -> -69200.31
A23: L32 | B23: Third Party Charges | C23: =-IS_MOM!U17 -> -1170.82 | D23: =-IS_MOM!V17 -> -916.42 | E23: =-IS_MOM!W17 -> -1195.33 | F23: =-IS_MOM!X17 -> -1195.51 | G23: =-IS_MOM!Y17 -> -980.05 | H23: =-IS_MOM!Z17 -> -1332.38 | I23: =-IS_MOM!AA17 -> -1125.94 | J23: =-IS_MOM!AB17 -> -1511.98 | ... N23: =-IS_MOM!AF17 -> 0 | O23: =SUM(C23:N23) -> -10790.25
A24: F4 | B24: TOTAL INDIRECT COSTS | C24: =SUM(C22:C23) -> -6465.83 | D24: =SUM(D22:D23) -> -5308.71 | E24: =SUM(E22:E23) -> -9135.72 | F24: =SUM(F22:F23) -> -8147.14 | G24: =SUM(G22:G23) -> -9418.45 | H24: =SUM(H22:H23) -> -4963.23 | I24: =SUM(I22:I23) -> -9228.4 | J24: =SUM(J22:J23) -> -15489.52 | ... O24: =SUM(O22:O23) -> -79990.56
A26: F5 | B26: GROSS MARGINS | C26: =C20+C24 -> 42920.62 | D26: =D20+D24 -> 43039.88 | E26: =E20+E24 -> 44279.6 | F26: =F20+F24 -> 51749.22 | G26: =G20+G24 -> 51904.85 | H26: =H20+H24 -> 50991.9 | I26: =I20+I24 -> 63319.7 | J26: =J20+J24 -> 51566.93 | ... O26: =O20+O24 -> 460054.24
A28: L41 | B28: Sales & Marketing | C28: =-IS_MOM!U22 -> -14608.31 | D28: =-IS_MOM!V22 -> -15595.01 | E28: =-IS_MOM!W22 -> -17414.68 | F28: =-IS_MOM!X22 -> -24046.41 | G28: =-IS_MOM!Y22 -> -24127.03 | H28: =-IS_MOM!Z22 -> -18558.32 | I28: =-IS_MOM!AA22 -> -17408.22 | J28: =-IS_MOM!AB22 -> -16756.51 | ... N28: =-IS_MOM!AF22 -> 0 | O28: =SUM(C28:N28) -> -165993.08
A29: L42 | B29: General & Adminisrative Expenses | C29: =-IS_MOM!U23+IS_MOM!U24 -> -80728.27 | D29: =-IS_MOM!V23+IS_MOM!V24 -> -82070.28 | E29: =-IS_MOM!W23 -> -87423.47 | F29: =-IS_MOM!X23 -> -94509.03 | G29: =-IS_MOM!Y23 -> -94474.2 | H29: =-IS_MOM!Z23 -> -97817.55 | I29: =-IS_MOM!AA23+IS_MOM!AA24-'IS_BU(MoM)'!W34 -> -99078.58 | J29: =-IS_MOM!AB23+IS_MOM!AB24 -> -104794.6 | K29: =-IS_MOM!AC23+IS_MOM!AC24 -> -110775.62 | L29: =-IS_MOM!AD23+IS_MOM!AD24 -> 0 | M29: =-IS_MOM!AE23+IS_MOM!AE24 -> 0 | N29: =-IS_MOM!AF23+IS_MOM!AF24 -> 0 | O29: =SUM(C29:N29) -> -851671.6
O30: =SUM(C30:N30) -> 0
A31: F6 | B31: EBITDAM | C31: =C26+C28+C29 -> -52415.96 | D31: =D26+D28+D29 -> -54625.41 | E31: =E26+E28+E29 -> -60558.55 | F31: =F26+F28+F29 -> -66806.22 | G31: =G26+G28+G29 -> -66696.38 | H31: =H26+H28+H29 -> -65383.97 | I31: =I26+I28+I29 -> -53167.1 | J31: =J26+J28+J29 -> -69984.18 | ... O31: =O26+O28+O29 -> -557610.44
B34: EBITDA | C34: =C31-C33 -> -52415.96 | D34: =D31-D33 -> -54625.41 | E34: =E31-E33 -> -60558.55 | F34: =F31-F33 -> -66806.22 | G34: =G31-G33 -> -66696.38 | H34: =H31-H33 -> -65383.97 | I34: =I31-I33 -> -53167.1 | J34: =J31-J33 -> -69984.18 | ... N34: =N31-N33 -> 0 | O34: =SUM(C34:N34) -> -557610.44
A36: L51 | B36: Depreciations | C36: =-IS_MOM!U30 -> -999.54 | D36: =-IS_MOM!V30 -> -1087.48 | E36: =-IS_MOM!W30 -> -1089.79 | F36: =-IS_MOM!X30 -> -1097.59 | G36: =-IS_MOM!Y30 -> -1089.21 | H36: =-IS_MOM!Z30 -> -1162.79 | I36: =-IS_MOM!AA30 -> -1152.18 | J36: =-IS_MOM!AB30 -> -1152.74 | ... N36: =-IS_MOM!AF30 -> 0 | O36: =SUM(C36:N36) -> -10035.48
A37: L52 | B37: Ammortization | C37: =-IS_MOM!U31 -> -20157.94 | D37: =-IS_MOM!V31 -> -20177.41 | E37: =-IS_MOM!W31 -> -20167.67 | F37: =-IS_MOM!X31 -> -20167.67 | G37: =-IS_MOM!Y31 -> -20167.67 | H37: =-IS_MOM!Z31 -> -20167.67 | I37: =-IS_MOM!AA31 -> -20165.65 | J37: =-IS_MOM!AB31 -> -7741.34 | ... N37: =-IS_MOM!AF31 -> 0 | O37: =SUM(C37:N37) -> -149200.72
A38: L53 | B38: Finance Cost | C38: =-IS_MOM!U32 -> -8866.64 | D38: =-IS_MOM!V32 -> -9616.99 | E38: =-IS_MOM!W32 -> -9476.5 | F38: =-IS_MOM!X32 -> -7694.2 | G38: =-IS_MOM!Y32 -> -7310.57 | H38: =-IS_MOM!Z32 -> -7172.2 | I38: =-IS_MOM!AA32 -> -5862.85 | J38: =-IS_MOM!AB32 -> -5459.98 | ... N38: =-IS_MOM!AF32 -> 0 | O38: =SUM(C38:N38) -> -66943.68
A39: L54 | B39: Other Income & Expenses | C39: =-IS_MOM!U33 -> -718.7 | D39: =-IS_MOM!V33 -> -1137.51 | E39: =-IS_MOM!W33 -> -3527.35 | F39: =-IS_MOM!X33 -> -3901.47 | G39: =-IS_MOM!Y33 -> -3875.62 | H39: =-IS_MOM!Z33 -> -3898.51 | I39: =-IS_MOM!AA33 -> -9420.3 | J39: =-IS_MOM!AB33 -> 2570.68 | ... N39: =-IS_MOM!AF33 -> 0 | O39: =SUM(C39:N39) -> -25776.1
B41: EARNING BEFORE TAX | C41: =C34+SUM(C36:C39) -> -83158.78 | D41: =D34+SUM(D36:D39) -> -86644.8 | E41: =E34+SUM(E36:E39) -> -94819.86 | F41: =F34+SUM(F36:F39) -> -99667.15 | G41: =G34+SUM(G36:G39) -> -99139.45 | H41: =H34+SUM(H36:H39) -> -97785.14 | I41: =I34+SUM(I36:I39) -> -89768.08 | J41: =J34+SUM(J36:J39) -> -81767.56 | ... O41: =O34+SUM(O36:O39) -> -809566.42

Sheet IS_12Entity_MoM
A1: =TableofContent!A1 -> POWER FINANCIAL WELLNESS INC
A2: =TableofContent!A2 -> CONSOLIDATED MANAGEMENT ACCOUNTS
A3: =TableofContent!A3 -> TABLE OF CONTENT
A4: =TableofContent!A4 -> FOR PERIOD ENDED JULY 31, 2025
A5: =TableofContent!A5 -> PREPARED BY: MOSES KIGO
A8: H1 | B8: PROFIT & LOSS STATMENT | C8: Power Financial Wellnes INC | D8: Frictionless Enterpirse (Kenya) Ltd | E8: PFW Finance India (PVT) Ltd | F8: Power Financial Wellnes Tanzania Ltd | G8: Frictionless Financial Services SMC Ltd | H8: Consolidated Financial Statements
A10: L11 | B10: Interest Income : Loans | C10: ='IS_BU(MoM)'!U4 -> 0 | D10: ='IS_BU(MoM)'!V4 -> 50557.17 | E10: ='IS_BU(MoM)'!W4 -> 0 | F10: ='IS_BU(MoM)'!X4 -> 0 | G10: ='IS_BU(MoM)'!Y4 -> 1362.43 | H10: =SUM(C10:G10) -> 51919.6
A11: L12 | B11: Interest Income : Other | C11: ='IS_BU(MoM)'!U5 -> 359.41 | D11: ='IS_BU(MoM)'!V5 -> 4705.46 | E11: ='IS_BU(MoM)'!W5 -> 0 | F11: ='IS_BU(MoM)'!X5 -> 0 | G11: ='IS_BU(MoM)'!Y5 -> 0 | H11: =SUM(C11:G11) -> 5064.87
A12: L13 | B12: Interest Expense : Borrowings | C12: ='IS_BU(MoM)'!U6 -> 0 | D12: ='IS_BU(MoM)'!V6 -> -34403.71 | E12: ='IS_BU(MoM)'!W6 -> 0 | F12: ='IS_BU(MoM)'!X6 -> 0 | G12: ='IS_BU(MoM)'!Y6 -> 0 | H12: =SUM(C12:G12) -> -34403.71
A13: F1 | B13: NET INTEREST INCOME | C13: =SUM(C10:C12) -> 359.41 | D13: =SUM(D10:D12) -> 20858.92 | E13: =SUM(E10:E12) -> 0 | F13: =SUM(F10:F12) -> 0 | G13: =SUM(G10:G12) -> 1362.43 | H13: =SUM(H10:H12) -> 22580.76
A15: L21 | B15: Fee Income | C15: ='IS_BU(MoM)'!U9 -> 14000 | D15: ='IS_BU(MoM)'!V9 -> 30495.54 | E15: ='IS_BU(MoM)'!W9 -> 0 | F15: ='IS_BU(MoM)'!X9 -> 0 | G15: ='IS_BU(MoM)'!Y9 -> 1658.2 | H15: =SUM(C15:G15) -> 46153.74
A16: L22 | B16: Commisions | C16: ='IS_BU(MoM)'!U10 -> 0 | D16: ='IS_BU(MoM)'!V10 -> 859.46 | E16: ='IS_BU(MoM)'!W10 -> 0 | F16: ='IS_BU(MoM)'!X10 -> 0 | G16: ='IS_BU(MoM)'!Y10 -> 1 | H16: =SUM(C16:G16) -> 860.46
A17: L23 | B17: Other Fees & Charges | C17: ='IS_BU(MoM)'!U11 -> 253.8 | D17: ='IS_BU(MoM)'!V11 -> 2266.34 | E17: ='IS_BU(MoM)'!W11 -> 0 | F17: ='IS_BU(MoM)'!X11 -> 0 | G17: ='IS_BU(MoM)'!Y11 -> 0 | H17: =SUM(C17:G17) -> 2520.14
A18: F2 | B18: FEES & COMMISIONS | C18: =SUM(C15:C17) -> 14253.8 | D18: =SUM(D15:D17) -> 33621.34 | E18: =SUM(E15:E17) -> 0 | F18: =SUM(F15:F17) -> 0 | G18: =SUM(G15:G17) -> 1659.2 | H18: =SUM(H15:H17) -> 49534.34
A20: F3 | B20: NET INCOME | C20: =C13+C18 -> 14613.21 | D20: =D13+D18 -> 54480.26 | E20: =E13+E18 -> 0 | F20: =F13+F18 -> 0 | G20: =G13+G18 -> 3021.63 | H20: =H13+H18 -> 72115.1
A22: L31 | B22: Loan Impairment | C22: =-'IS_BU(MoM)'!U16 -> 0 | D22: =-'IS_BU(MoM)'!V16 -> -10471.74 | E22: =-'IS_BU(MoM)'!W16 -> 0 | F22: =-'IS_BU(MoM)'!X16 -> 0 | G22: =-'IS_BU(MoM)'!Y16 -> 0 | H22: =-'IS_BU(MoM)'!Z16 -> -10471.74
A23: L32 | B23: Third Party Charges | C23: =-'IS_BU(MoM)'!U17 -> 0 | D23: =-'IS_BU(MoM)'!V17 -> -1297.69 | E23: =-'IS_BU(MoM)'!W17 -> 0 | F23: =-'IS_BU(MoM)'!X17 -> 0 | G23: =-'IS_BU(MoM)'!Y17 -> -64.13 | H23: =-'IS_BU(MoM)'!Z17 -> -1361.82
A24: F4 | B24: TOTAL INDIRECT COSTS | C24: =SUM(C22:C23) -> 0 | D24: =SUM(D22:D23) -> -11769.43 | E24: =SUM(E22:E23) -> 0 | F24: =SUM(F22:F23) -> 0 | G24: =SUM(G22:G23) -> -64.13 | H24: =SUM(H22:H23) -> -11833.56
A26: F5 | B26: GROSS MARGINS | C26: =C20+C24 -> 14613.21 | D26: =D20+D24 -> 42710.83 | E26: =E20+E24 -> 0 | F26: =F20+F24 -> 0 | G26: =G20+G24 -> 2957.5 | H26: =H20+H24 -> 60281.54
A28: L41 | B28: Sales & Marketing | C28: =-'IS_BU(MoM)'!U22 -> -4998.31 | D28: =-'IS_BU(MoM)'!V22 -> -8606.86 | E28: =-'IS_BU(MoM)'!W22 -> 0 | F28: =-'IS_BU(MoM)'!X22 -> 0 | G28: =-'IS_BU(MoM)'!Y22 -> -3873.42 | H28: =SUM(C28:G28) -> -17478.59
A29: L42 | B29: General & Adminisrative Expenses | C29: =-'IS_BU(MoM)'!U23-'IS_BU(MoM)'!U24 -> -62880.49 | D29: =-'IS_BU(MoM)'!V23-'IS_BU(MoM)'!V24 -> -42778.06 | E29: =-'IS_BU(MoM)'!W23-'IS_BU(MoM)'!W24 -> 850.46 | F29: =-'IS_BU(MoM)'!X23-'IS_BU(MoM)'!X24 -> -1101.92 | G29: =-'IS_BU(MoM)'!Y23-'IS_BU(MoM)'!Y24 -> -4956.33 | H29: =SUM(C29:G29) -> -110866.34
A31: F6 | B31: EBITDAM | C31: =C26+C28+C29 -> -53265.59 | D31: =D26+D28+D29 -> -8674.09 | E31: =E26+E28+E29 -> 850.46 | F31: =F26+F28+F29 -> -1101.92 | G31: =G26+G28+G29 -> -5872.25 | H31: =SUM(C31:G31) -> -68063.39
B34: EBITDA | C34: =C31-C33 -> -53265.59 | D34: =D31-D33 -> -8674.09 | E34: =E31-E33 -> 850.46 | F34: =F31-F33 -> -1101.92 | G34: =G31-G33 -> -5872.25 | H34: =H31-H33 -> -68063.39
A36: L51 | B36: Depreciations | C36: =-'IS_BU(MoM)'!U30 -> -204.44 | D36: =-'IS_BU(MoM)'!V30 -> -918.32 | E36: =-'IS_BU(MoM)'!W30 -> 0 | F36: =-'IS_BU(MoM)'!X30 -> 0 | G36: =-'IS_BU(MoM)'!Y30 -> -81.4 | H36: =-'IS_BU(MoM)'!Z30 -> -1204.16
A37: L52 | B37: Ammortization | C37: =-'IS_BU(MoM)'!U31 -> 0 | D37: =-'IS_BU(MoM)'!V31 -> -287.7 | E37: =-'IS_BU(MoM)'!W31 -> 0 | F37: =-'IS_BU(MoM)'!X31 -> 0 | G37: =-'IS_BU(MoM)'!Y31 -> 0 | H37: =-'IS_BU(MoM)'!Z31 -> -287.7
A38: L53 | B38: Finance Cost | C38: =-'IS_BU(MoM)'!U32 -> 0 | D38: =-'IS_BU(MoM)'!V32 -> -5483.75 | E38: =-'IS_BU(MoM)'!W32 -> 0 | F38: =-'IS_BU(MoM)'!X32 -> 0 | G38: =-'IS_BU(MoM)'!Y32 -> 0 | H38: =-'IS_BU(MoM)'!Z32 -> -5483.75
A39: L54 | B39: Other Income & Expenses | C39: =-'IS_BU(MoM)'!U33 -> -700 | D39: =-'IS_BU(MoM)'!V33 -> -1167.32 | E39: =-'IS_BU(MoM)'!W33 -> 0 | F39: =-'IS_BU(MoM)'!X33 -> 0 | G39: =-'IS_BU(MoM)'!Y33 -> 0 | H39: =-'IS_BU(MoM)'!Z33 -> -1867.32
B41: EARNING BEFORE TAX | C41: =C34+SUM(C36:C39) -> -54170.03 | D41: =D34+SUM(D36:D39) -> -16531.18 | E41: =E34+SUM(E36:E39) -> 850.46 | F41: =F34+SUM(F36:F39) -> -1101.92 | G41: =G34+SUM(G36:G39) -> -5953.65 | H41: =H34+SUM(H36:H39) -> -76906.32

Sheet Summary
B1: Power Financial Wellness INC | C1: Frictionless EL (Kenya) Ltd | D1: PFW Finance India (PVT) Ltd | E1: Power Financial Wellness Tanzania Ltd | F1: Frictionless Financial Services SMC Ltd | G1: Consolidated Financial Statements
A2: Loss in local currency | B2: =B4*B3 -> -58234.93 | C2: =C4*C3 -> -2087727.9 | D2: =D4*D3 -> -98750.102 | E2: =E4*E3 -> -1464051.9 | F2: =F4*F3 -> -24717913
A3: FX | B3: 1 | C3: =B10 -> 128.5 | D3: =B12 -> 88.84 | E3: =B13 -> 2454.98 | F3: =B11 -> 3543.99
A4: USD Equivalent | B4: -58234.93 | C4: -16246.91 | D4: -1111.55 | E4: -596.36 | F4: -6974.6 | G4: -83164.35
A10: FEL-KE | B10: 128.5
A11: FEL-SMC | B11: 3543.99
A12: PFW-IND | B12: 88.84
A13: PFW-TZ | B13: 2454.98
A14: PFW-USA | B14: 1

Sheet CF_12Months
A1: =TableofContent!A1 -> POWER FINANCIAL WELLNESS INC | O1: =TableofContent!F1 -> USD
A2: =TableofContent!A2 -> CONSOLIDATED MANAGEMENT ACCOUNTS
A3: 12 MONTH CASHFLOW STATEMENT
A4: =TableofContent!A4 -> FOR PERIOD ENDED JULY 31, 2025
A5: =TableofContent!A5 -> PREPARED BY: MOSES KIGO
C6: 2 | D6: =C6+1 -> 3 | E6: =D6+1 -> 4 | F6: =E6+1 -> 5 | G6: =F6+1 -> 6 | H6: =G6+1 -> 7 | I6: =H6+1 -> 8 | J6: =I6+1 -> 9 | K6: =J6+1 -> 10
B8: CASHFLOW STATEMENT | C8: 45658 | D8: =EOMONTH(C8,1) -> 45716 | E8: =EOMONTH(D8,1) -> 45747 | F8: =EOMONTH(E8,1) -> 45777 | G8: =EOMONTH(F8,1) -> 45808 | H8: =EOMONTH(G8,1) -> 45838 | I8: =EOMONTH(H8,1) -> 45869 | J8: =EOMONTH(I8,1) -> 45900 | K8: =EOMONTH(J8,1) -> 45930 | ... N8: =EOMONTH(M8,1) -> 46022 | O8: Total
A10: 010 | B10: Net Income | C10: =BS_12MoM!D46-BS_12MoM!C46 -> -90623.85 | D10: =BS_12MoM!E46-BS_12MoM!D46 -> -95814.97 | E10: =BS_12MoM!F46-BS_12MoM!E46 -> -77687.86 | F10: =BS_12MoM!G46-BS_12MoM!F46 -> -99600.45 | G10: =BS_12MoM!H46-BS_12MoM!G46 -> -96765.16 | H10: =BS_12MoM!I46-BS_12MoM!H46 -> -97379.09 | I10: =BS_12MoM!J46-BS_12MoM!I46 -> -89872.66 | J10: =BS_12MoM!K46-BS_12MoM!J46 -> -81767.28 | K10: =BS_12MoM!L46-BS_12MoM!K46 -> -76906.32 | L10: 0 | M10: 0 | N10: =IS_12MoM!N41 -> 0
A11: 020 | B11: Add Depreciation | C11: =BS_12MoM!C19-BS_12MoM!D19 -> 1001.06 | D11: =BS_12MoM!D19-BS_12MoM!E19 -> 1089.1 | E11: =BS_12MoM!E19-BS_12MoM!F19 -> 1091.4 | F11: =BS_12MoM!F19-BS_12MoM!G19 -> 1099.19 | G11: =BS_12MoM!G19-BS_12MoM!H19 -> 1090.8 | H11: =BS_12MoM!H19-BS_12MoM!I19 -> 1164.38 | I11: =BS_12MoM!I19-BS_12MoM!J19 -> 1152.18 | J11: =BS_12MoM!J19-BS_12MoM!K19 -> 1152.74 | K11: =BS_12MoM!K19-BS_12MoM!L19 -> 1204.16 | L11: 0 | M11: 0 | N11: =BS_12MoM!N19-BS_12MoM!O19 -> 0
A12: 030 | B12: Add Ammortization | C12: =BS_12MoM!C21-BS_12MoM!D21 -> 20158.87 | D12: =BS_12MoM!D21-BS_12MoM!E21 -> 20177.97 | E12: =BS_12MoM!E21-BS_12MoM!F21 -> 20168.22 | F12: =BS_12MoM!F21-BS_12MoM!G21 -> 20168.22 | G12: =BS_12MoM!G21-BS_12MoM!H21 -> 20168.22 | H12: =BS_12MoM!H21-BS_12MoM!I21 -> 20168.22 | I12: =BS_12MoM!I21-BS_12MoM!J21 -> 20165.65 | J12: =BS_12MoM!J21-BS_12MoM!K21 -> 7741.34 | K12: =BS_12MoM!K21-BS_12MoM!L21 -> 287.7 | L12: 0 | M12: 0 | N12: =BS_12MoM!N21-BS_12MoM!O21 -> 0
A13: 040 | B13: Add Finance Cost | C13: =IS_12MoM!C38 -> -8866.64 | D13: =IS_12MoM!D38 -> -9616.99 | E13: =IS_12MoM!E38 -> -9476.5 | F13: =IS_12MoM!F38 -> -7694.2 | G13: =IS_12MoM!G38 -> -7310.57 | H13: =IS_12MoM!H38 -> -7172.2 | I13: =IS_12MoM!I38 -> -5862.85 | J13: =IS_12MoM!J38 -> -5459.98 | K13: =IS_12MoM!K38 -> -5483.75 | L13: 0 | M13: 0 | N13: =IS_12MoM!N38 -> 0
B14: Add Prior Year Adjustment | C14: =BS_12MoM!D45-BS_12MoM!C45 -> 0.5 | D14: =BS_12MoM!E45-BS_12MoM!D45 -> 0 | E14: =BS_12MoM!F45-BS_12MoM!E45 -> 0 | F14: =BS_12MoM!G45-BS_12MoM!F45 -> 0 | G14: =BS_12MoM!H45-BS_12MoM!G45 -> 0 | H14: =BS_12MoM!I45-BS_12MoM!H45 -> 0 | I14: =BS_12MoM!J45-BS_12MoM!I45 -> 0 | J14: =BS_12MoM!K45-BS_12MoM!J45 -> 0 | K14: =BS_12MoM!L45-BS_12MoM!K45 -> 0 | L14: 0 | M14: 0 | N14: =BS_12MoM!O45-BS_12MoM!N45 -> 0
B15: Add Foreign Currency Translation | C15: =BS_12MoM!D47-BS_12MoM!C47 -> -9404.09 | D15: =BS_12MoM!E47-BS_12MoM!D47 -> -32.67 | E15: =BS_12MoM!F47-BS_12MoM!E47 -> -38.88 | F15: =BS_12MoM!G47-BS_12MoM!F47 -> -19.35 | G15: =BS_12MoM!H47-BS_12MoM!G47 -> -15.9 | H15: =BS_12MoM!I47-BS_12MoM!H47 -> -31.28 | I15: =BS_12MoM!J47-BS_12MoM!I47 -> 0.33 | J15: =BS_12MoM!K47-BS_12MoM!J47 -> 0.13 | K15: =BS_12MoM!L47-BS_12MoM!K47 -> 0.13 | L15: 0 | M15: 0 | N15: =BS_12MoM!O47-BS_12MoM!N47 -> 0
A16: 050 | L16: 0 | M16: 0
A17: 099 | B17: Adjusted Net Income | C17: =SUM(C10:C16) -> -87734.15 | D17: =SUM(D10:D16) -> -84197.56 | E17: =SUM(E10:E16) -> -65943.62 | F17: =SUM(F10:F16) -> -86046.59 | G17: =SUM(G10:G16) -> -82832.61 | H17: =SUM(H10:H16) -> -83249.97 | I17: =SUM(I10:I16) -> -74417.35 | J17: =SUM(J10:J16) -> -78333.05 | K17: =SUM(K10:K16) -> -80898.08 | L17: 0 | M17: 0 | N17: =SUM(N10:N16) -> 0
L18: 0 | M18: 0
A19: 100 | B19: =BS_12MoM!B12 -> Net Loan Receivable | C19: =BS_12MoM!C12-BS_12MoM!D12 -> -207069.89 | D19: =BS_12MoM!D12-BS_12MoM!E12 -> -165907.48 | E19: =BS_12MoM!E12-BS_12MoM!F12 -> 5918.03 | F19: =BS_12MoM!F12-BS_12MoM!G12 -> -57124.46 | G19: =BS_12MoM!G12-BS_12MoM!H12 -> -56327.89 | H19: =BS_12MoM!H12-BS_12MoM!I12 -> -82570.86 | I19: =BS_12MoM!I12-BS_12MoM!J12 -> -67006.2 | J19: =BS_12MoM!J12-BS_12MoM!K12 -> -113112.87 | K19: =BS_12MoM!K12-BS_12MoM!L12 -> -97368.46 | L19: 0 | M19: 0 | N19: =BS_12MoM!N12-BS_12MoM!O12 -> 0
B20: =BS_12MoM!B13 -> Interco-Receivable | C20: =BS_12MoM!C13-BS_12MoM!D13 -> -97041.07 | D20: =BS_12MoM!D13-BS_12MoM!E13 -> -124471.89 | E20: =BS_12MoM!E13-BS_12MoM!F13 -> -39620.94 | F20: =BS_12MoM!F13-BS_12MoM!G13 -> -76060.82 | G20: =BS_12MoM!G13-BS_12MoM!H13 -> -78601.38 | H20: =BS_12MoM!H13-BS_12MoM!I13 -> -23602.96 | I20: =BS_12MoM!I13-BS_12MoM!J13 -> -190405.8 | J20: =BS_12MoM!J13-BS_12MoM!K13 -> -50933.16 | K20: =BS_12MoM!K13-BS_12MoM!L13 -> -57750.18 | L20: 0 | M20: 0 | N20: =BS_12MoM!N13-BS_12MoM!O13 -> 0
B21: =BS_12MoM!B14 -> Other Current Assets | C21: =BS_12MoM!C14-BS_12MoM!D14 -> -5466.59 | D21: =BS_12MoM!D14-BS_12MoM!E14 -> 9411.37 | E21: =BS_12MoM!E14-BS_12MoM!F14 -> 15098.11 | F21: =BS_12MoM!F14-BS_12MoM!G14 -> 3407.14 | G21: =BS_12MoM!G14-BS_12MoM!H14 -> 22021.37 | H21: =BS_12MoM!H14-BS_12MoM!I14 -> 21310.99 | I21: =BS_12MoM!I14-BS_12MoM!J14 -> 2775.79 | J21: =BS_12MoM!J14-BS_12MoM!K14 -> 833.26 | K21: =BS_12MoM!K14-BS_12MoM!L14 -> -6079.67 | L21: 0 | M21: 0 | N21: =BS_12MoM!N14-BS_12MoM!O14 -> 0
B22: =BS_12MoM!B30 -> Accounts Payable | C22: =BS_12MoM!D30-BS_12MoM!C30 -> 1007.54 | D22: =BS_12MoM!E30-BS_12MoM!D30 -> 52738.51 | E22: =BS_12MoM!F30-BS_12MoM!E30 -> -31774.74 | F22: =BS_12MoM!G30-BS_12MoM!F30 -> 6051.97 | G22: =BS_12MoM!H30-BS_12MoM!G30 -> 15641.28 | H22: =BS_12MoM!I30-BS_12MoM!H30 -> -27525.3 | I22: =BS_12MoM!J30-BS_12MoM!I30 -> -3623.92 | J22: =BS_12MoM!K30-BS_12MoM!J30 -> 27804.11 | K22: =BS_12MoM!L30-BS_12MoM!K30 -> 11950.81 | L22: 0 | M22: 0 | N22: =BS_12MoM!O30-BS_12MoM!N30 -> 0
B23: =BS_12MoM!B31 -> Intercompany Payable | C23: =BS_12MoM!D31-BS_12MoM!C31 -> 35884.14 | D23: =BS_12MoM!E31-BS_12MoM!D31 -> 39312.3 | E23: =BS_12MoM!F31-BS_12MoM!E31 -> 12161.64 | F23: =BS_12MoM!G31-BS_12MoM!F31 -> 88550.73 | G23: =BS_12MoM!H31-BS_12MoM!G31 -> 51003.94 | H23: =BS_12MoM!I31-BS_12MoM!H31 -> 19120.88 | I23: =BS_12MoM!J31-BS_12MoM!I31 -> 98888.17 | J23: =BS_12MoM!K31-BS_12MoM!J31 -> 54709.71 | K23: =BS_12MoM!L31-BS_12MoM!K31 -> 73534.89 | L23: 0 | M23: 0 | N23: =BS_12MoM!O31-BS_12MoM!N31 -> 0
B24: =BS_12MoM!B33 -> Customer Deposits | C24: =BS_12MoM!D33-BS_12MoM!C33 -> 2810.29 | D24: =BS_12MoM!E33-BS_12MoM!D33 -> -4245.62 | E24: =BS_12MoM!F33-BS_12MoM!E33 -> -10979.45 | F24: =BS_12MoM!G33-BS_12MoM!F33 -> -4263.45 | G24: =BS_12MoM!H33-BS_12MoM!G33 -> 102.13 | H24: =BS_12MoM!I33-BS_12MoM!H33 -> -8898.23 | I24: =BS_12MoM!J33-BS_12MoM!I33 -> -4339.4 | J24: =BS_12MoM!K33-BS_12MoM!J33 -> -302.85 | K24: =BS_12MoM!L33-BS_12MoM!K33 -> -2238.77 | L24: 0 | M24: 0 | N24: =BS_12MoM!O33-BS_12MoM!N33 -> 0
B25: =BS_12MoM!B34 -> Accrued Expenses | C25: =BS_12MoM!D34-BS_12MoM!C34 -> 8339.9 | D25: =BS_12MoM!E34-BS_12MoM!D34 -> 4626.11 | E25: =BS_12MoM!F34-BS_12MoM!E34 -> 5533.14 | F25: =BS_12MoM!G34-BS_12MoM!F34 -> -2994.56 | G25: =BS_12MoM!H34-BS_12MoM!G34 -> -10417.43 | H25: =BS_12MoM!I34-BS_12MoM!H34 -> -17751.98 | I25: =BS_12MoM!J34-BS_12MoM!I34 -> -14592.73 | J25: =BS_12MoM!K34-BS_12MoM!J34 -> -12785.26 | K25: =BS_12MoM!L34-BS_12MoM!K34 -> 4853.77 | L25: 0 | M25: 0 | N25: =BS_12MoM!O34-BS_12MoM!N34 -> 0
B26: Changes In Working Capital | C26: =SUM(C19:C25) -> -261535.68 | D26: =SUM(D19:D25) -> -188536.7 | E26: =SUM(E19:E25) -> -43664.21 | F26: =SUM(F19:F25) -> -42433.45 | G26: =SUM(G19:G25) -> -56577.98 | H26: =SUM(H19:H25) -> -119917.46 | I26: =SUM(I19:I25) -> -178304.09 | J26: =SUM(J19:J25) -> -93787.06 | K26: =SUM(K19:K25) -> -73097.61 | L26: 0 | M26: 0 | N26: =SUM(N19:N25) -> 0
B27: Changes in Other LT Assets/Liabilities | C27: =SUM(BS_12MoM!C22:C23)-SUM(BS_12MoM!D22:D23) -> 0.04 | D27: =SUM(BS_12MoM!D22:D23)-SUM(BS_12MoM!E22:E23) -> 0 | E27: =SUM(BS_12MoM!E22:E23)-SUM(BS_12MoM!F22:F23) -> 0 | F27: =SUM(BS_12MoM!F22:F23)-SUM(BS_12MoM!G22:G23) -> 0 | G27: =SUM(BS_12MoM!G22:G23)-SUM(BS_12MoM!H22:H23) -> 0 | H27: =SUM(BS_12MoM!H22:H23)-SUM(BS_12MoM!I22:I23) -> 0 | I27: =SUM(BS_12MoM!I22:I23)-SUM(BS_12MoM!J22:J23) -> 0 | J27: =SUM(BS_12MoM!J22:J23)-SUM(BS_12MoM!K22:K23) -> 0 | K27: =SUM(BS_12MoM!K22:K23)-SUM(BS_12MoM!L22:L23) -> 0 | L27: 0 | M27: 0 | N27: =SUM(BS_12MoM!N22:N23)-SUM(BS_12MoM!O22:O23) -> 0
L28: 0 | M28: 0
B29: NET INCOME FROM OPERATING ACTIVITIES | C29: =C17+SUM(C26:C28) -> -349269.79 | D29: =D17+SUM(D26:D28) -> -272734.26 | E29: =E17+SUM(E26:E28) -> -109607.83 | F29: =F17+SUM(F26:F28) -> -128480.04 | G29: =G17+SUM(G26:G28) -> -139410.59 | H29: =H17+SUM(H26:H28) -> -203167.43 | I29: =I17+SUM(I26:I28) -> -252721.44 | J29: =J17+SUM(J26:J28) -> -172120.11 | K29: =K17+SUM(K26:K28) -> -153995.69 | L29: 0 | M29: 0 | N29: =N17+SUM(N26:N28) -> 0
A30: F1 | L30: 0 | M30: 0
B31: Capital Addition | C31: =BS_12MoM!C18-BS_12MoM!D18 -> -2346.76 | D31: =BS_12MoM!D18-BS_12MoM!E18 -> -4538.78 | E31: =BS_12MoM!E18-BS_12MoM!F18 -> -3974.8 | F31: =BS_12MoM!F18-BS_12MoM!G18 -> -520.55 | G31: =BS_12MoM!G18-BS_12MoM!H18 -> 0 | H31: =BS_12MoM!H18-BS_12MoM!I18 -> -520.55 | I31: =BS_12MoM!I18-BS_12MoM!J18 -> -1756.35 | J31: =BS_12MoM!J18-BS_12MoM!K18 -> 0 | K31: =BS_12MoM!K18-BS_12MoM!L18 -> -2064.71 | L31: 0 | M31: 0 | N31: =BS_12MoM!N18-BS_12MoM!O18 -> 0
A32: 200 | B32: Intangible Asset additions | C32: =BS_12MoM!C20-BS_12MoM!D20 -> -0.28 | D32: =BS_12MoM!D20-BS_12MoM!E20 -> 0 | E32: =BS_12MoM!E20-BS_12MoM!F20 -> 0 | F32: =BS_12MoM!F20-BS_12MoM!G20 -> 0 | G32: =BS_12MoM!G20-BS_12MoM!H20 -> 0 | H32: =BS_12MoM!H20-BS_12MoM!I20 -> 0 | I32: =BS_12MoM!I20-BS_12MoM!J20 -> 0 | J32: =BS_12MoM!J20-BS_12MoM!K20 -> 0 | K32: =BS_12MoM!K20-BS_12MoM!L20 -> 0 | L32: 0 | M32: 0 | N32: =BS_12MoM!N20-BS_12MoM!O20 -> 0
A33: 210 | L33: 0 | M33: 0
B34: NET CASHFLOW FROM INVESTING ACTIVITIES | C34: =SUM(C31:C32) -> -2347.04 | D34: =SUM(D31:D32) -> -4538.78 | E34: =SUM(E31:E32) -> -3974.8 | F34: =SUM(F31:F32) -> -520.55 | G34: =SUM(G31:G32) -> 0 | H34: =SUM(H31:H32) -> -520.55 | I34: =SUM(I31:I32) -> -1756.35 | J34: =SUM(J31:J32) -> 0 | K34: =SUM(K31:K32) -> -2064.71 | L34: 0 | M34: 0 | N34: =SUM(N31:N32) -> 0
A35: 290 | L35: 0 | M35: 0
B36: Proceeds from Sales Of Ordinary Shares | C36: =BS_12MoM!D43-BS_12MoM!C43 -> -450000.1 | D36: =BS_12MoM!E43-BS_12MoM!D43 -> 0 | E36: =BS_12MoM!F43-BS_12MoM!E43 -> 0 | F36: =BS_12MoM!G43-BS_12MoM!F43 -> 0 | G36: =BS_12MoM!H43-BS_12MoM!G43 -> 35.04 | H36: =BS_12MoM!I43-BS_12MoM!H43 -> 0 | I36: =BS_12MoM!J43-BS_12MoM!I43 -> 0 | J36: =BS_12MoM!K43-BS_12MoM!J43 -> 0 | K36: =BS_12MoM!L43-BS_12MoM!K43 -> 0 | L36: 0 | M36: 0 | N36: =BS_12MoM!O43-BS_12MoM!N43 -> 0
A37: 310 | B37: Proceeds From LT Borrowing | C37: =BS_12MoM!D40-BS_12MoM!C40 -> 931153.5 | D37: =BS_12MoM!E40-BS_12MoM!D40 -> 235112.14 | E37: =BS_12MoM!F40-BS_12MoM!E40 -> 30455.59 | F37: =BS_12MoM!G40-BS_12MoM!F40 -> 250000 | G37: =BS_12MoM!H40-BS_12MoM!G40 -> 180094.7 | H37: =BS_12MoM!I40-BS_12MoM!H40 -> -30017.65 | I37: =BS_12MoM!J40-BS_12MoM!I40 -> 112470.39 | J37: =BS_12MoM!K40-BS_12MoM!J40 -> 100533.14 | K37: =BS_12MoM!L40-BS_12MoM!K40 -> 250000 | L37: 0 | M37: 0 | N37: =BS_12MoM!O40-BS_12MoM!N40 -> 0
A38: 320 | B38: Proceeds from ST Borrowing | C38: =BS_12MoM!D32-BS_12MoM!C32 -> 27971.08 | D38: =BS_12MoM!E32-BS_12MoM!D32 -> -1684.53 | E38: =BS_12MoM!F32-BS_12MoM!E32 -> 2799.93 | F38: =BS_12MoM!G32-BS_12MoM!F32 -> 10656 | G38: =BS_12MoM!H32-BS_12MoM!G32 -> 12089.26 | H38: =BS_12MoM!I32-BS_12MoM!H32 -> -8995.55 | I38: =BS_12MoM!J32-BS_12MoM!I32 -> -5510.4 | J38: =BS_12MoM!K32-BS_12MoM!J32 -> 26.64 | K38: =BS_12MoM!L32-BS_12MoM!K32 -> -6827.17 | L38: 0 | M38: 0 | N38: =BS_12MoM!O32-BS_12MoM!N32 -> 0
B39: Proceeds From IC Borrowing | C39: =BS_12MoM!D44-BS_12MoM!C44 -> -0.07 | D39: =BS_12MoM!E44-BS_12MoM!D44 -> 0 | E39: =BS_12MoM!F44-BS_12MoM!E44 -> 0 | F39: =BS_12MoM!G44-BS_12MoM!F44 -> 0 | G39: =BS_12MoM!H44-BS_12MoM!G44 -> 0 | H39: =BS_12MoM!I44-BS_12MoM!H44 -> 0 | I39: =BS_12MoM!J44-BS_12MoM!I44 -> 0 | J39: =BS_12MoM!K44-BS_12MoM!J44 -> 0 | K39: =BS_12MoM!L44-BS_12MoM!K44 -> 0 | L39: 0 | M39: 0 | N39: =BS_12MoM!O44-BS_12MoM!N44 -> 0
B40: Finance Cost on Borrowing | C40: =-C13 -> 8866.64 | D40: =-D13 -> 9616.99 | E40: =-E13 -> 9476.5 | F40: =-F13 -> 7694.2 | G40: =-G13 -> 7310.57 | H40: =-H13 -> 7172.2 | I40: =-I13 -> 5862.85 | J40: =-J13 -> 5459.98 | K40: =-K13 -> 5483.75 | L40: 0 | M40: 0 | N40: =-N13 -> 0
L41: 0 | M41: 0
B42: NET CASHFLOW FROM FINANCING ACTIVITIES | C42: =SUM(C36:C41) -> 517991.05 | D42: =SUM(D36:D41) -> 243044.6 | E42: =SUM(E36:E41) -> 42732.02 | F42: =SUM(F36:F41) -> 268350.2 | G42: =SUM(G36:G41) -> 199529.57 | H42: =SUM(H36:H41) -> -31841 | I42: =SUM(I36:I41) -> 112822.84 | J42: =SUM(J36:J41) -> 106019.76 | K42: =SUM(K36:K41) -> 248656.58 | L42: 0 | M42: 0 | N42: =SUM(N36:N41) -> 0
A43: 390 | L43: 0 | M43: 0
B44: NET CASHFLOW | C44: =C29+C34+C42 -> 166374.22 | D44: =D29+D34+D42 -> -34228.44 | E44: =E29+E34+E42 -> -70850.61 | F44: =F29+F34+F42 -> 139349.61 | G44: =G29+G34+G42 -> 60118.98 | H44: =H29+H34+H42 -> -235528.98 | I44: =I29+I34+I42 -> -141654.95 | J44: =J29+J34+J42 -> -66100.35 | K44: =K29+K34+K42 -> 92596.18 | L44: 0 | M44: 0 | N44: =N29+N34+N42 -> 0
B45: Cash & Cash Equivalent @ Beginning of period | C45: =BS_12MoM!C11 -> 627920 | D45: =BS_12MoM!D11 -> 794294.22 | E45: =BS_12MoM!E11 -> 760065.78 | F45: =BS_12MoM!F11 -> 689215.17 | G45: =BS_12MoM!G11 -> 828564.78 | H45: =BS_12MoM!H11 -> 888683.76 | I45: =BS_12MoM!I11 -> 653154.78 | J45: =BS_12MoM!J11 -> 511499.83 | K45: =BS_12MoM!K11 -> 445399.48 | L45: 0 | M45: 0 | N45: =M46 -> 0
B46: Cash & Cash Equivaoent at End of Periond | C46: =SUM(C44:C45) -> 794294.22 | D46: =SUM(D44:D45) -> 760065.78 | E46: =SUM(E44:E45) -> 689215.17 | F46: =SUM(F44:F45) -> 828564.78 | G46: =SUM(G44:G45) -> 888683.76 | H46: =SUM(H44:H45) -> 653154.78 | I46: =SUM(I44:I45) -> 511499.83 | J46: =SUM(J44:J45) -> 445399.48 | K46: =SUM(K44:K45) -> 537995.66 | L46: 0 | M46: 0 | N46: =SUM(N44:N45) -> 0
B48: CHECK | C48: =C46-BS_12MoM!D11 -> 0 | D48: =D46-BS_12MoM!E11 -> 0 | E48: =E46-BS_12MoM!F11 -> 0 | F48: =F46-BS_12MoM!G11 -> 0 | G48: =G46-BS_12MoM!H11 -> -9.3132257e-10 | H48: =H46-BS_12MoM!I11 -> 0 | I48: =I46-BS_12MoM!J11 -> 5.2386895e-10 | J48: =J46-BS_12MoM!K11 -> 7.5669959e-10 | K48: =K46-BS_12MoM!L11 -> 0

Sheet CBurn ENtity
A1: =TableofContent!A1 -> POWER FINANCIAL WELLNESS INC
A2: =TableofContent!A2 -> CONSOLIDATED MANAGEMENT ACCOUNTS
A3: 12 MONTH CASHFLOW STATEMENT
A4: =TableofContent!A4 -> FOR PERIOD ENDED JULY 31, 2025
A5: =TableofContent!A5 -> PREPARED BY: MOSES KIGO
B8: COST INCURRED | C8: 45778
B10: =Cburn_Entity!V3 -> Salary & Wages | C10: =Cburn_Entity!W3 -> 0 | D10: =Cburn_Entity!X3 -> 24247.64 | E10: =Cburn_Entity!Y3 -> 7522.36 | F10: =Cburn_Entity!Z3 -> 0 | G10: =Cburn_Entity!AA3 -> 4003.64 | H10: =Cburn_Entity!AB3 -> 35773.64
B11: =Cburn_Entity!V4 -> Consultants | C11: =Cburn_Entity!W4 -> 31994.75 | D11: =Cburn_Entity!X4 -> 1818.21 | E11: =Cburn_Entity!Y4 -> 0 | F11: =Cburn_Entity!Z4 -> 1062.33 | G11: =Cburn_Entity!AA4 -> 0 | H11: =Cburn_Entity!AB4 -> 34875.29
B12: =Cburn_Entity!V5 -> Fringe Benefits | C12: =Cburn_Entity!W5 -> 726.5 | D12: =Cburn_Entity!X5 -> 12052.12 | E12: =Cburn_Entity!Y5 -> 587.8 | F12: =Cburn_Entity!Z5 -> 0 | G12: =Cburn_Entity!AA5 -> 2689.27 | H12: =Cburn_Entity!AB5 -> 16055.69
B13: =Cburn_Entity!V6 -> Rent & Office related expenses | C13: =Cburn_Entity!W6 -> 12590.61 | D13: =Cburn_Entity!X6 -> 1968.13 | E13: =Cburn_Entity!Y6 -> 476.64 | F13: =Cburn_Entity!Z6 -> 0 | G13: =Cburn_Entity!AA6 -> 526.38 | H13: =Cburn_Entity!AB6 -> 15561.76
B14: =Cburn_Entity!V7 -> Utilities | C14: =Cburn_Entity!W7 -> 0 | D14: =Cburn_Entity!X7 -> 132.6 | E14: =Cburn_Entity!Y7 -> 0 | F14: =Cburn_Entity!Z7 -> 0 | G14: =Cburn_Entity!AA7 -> 62.38 | H14: =Cburn_Entity!AB7 -> 194.98
B15: =Cburn_Entity!V8 -> IT Costs | C15: =Cburn_Entity!W8 -> 1456.23 | D15: =Cburn_Entity!X8 -> 3209.13 | E15: =Cburn_Entity!Y8 -> 3107.99 | F15: =Cburn_Entity!Z8 -> 39.59 | G15: =Cburn_Entity!AA8 -> 240.02 | H15: =Cburn_Entity!AB8 -> 8052.96
B16: =Cburn_Entity!V9 -> Outside Servces | C16: =Cburn_Entity!W9 -> 0 | D16: =Cburn_Entity!X9 -> 230.66 | E16: =Cburn_Entity!Y9 -> 0 | F16: =Cburn_Entity!Z9 -> 0 | G16: =Cburn_Entity!AA9 -> 144.76 | H16: =Cburn_Entity!AB9 -> 375.42
B17: =Cburn_Entity!V10 -> Professional Servicess | C17: =Cburn_Entity!W10 -> 6534 | D17: =Cburn_Entity!X10 -> 2753.55 | E17: =Cburn_Entity!Y10 -> 0 | F17: =Cburn_Entity!Z10 -> 0 | G17: =Cburn_Entity!AA10 -> 202.68 | H17: =Cburn_Entity!AB10 -> 9490.23
B18: =Cburn_Entity!V11 -> Selling Expenses | C18: =Cburn_Entity!W11 -> 0 | D18: =Cburn_Entity!X11 -> 2546.05 | E18: =Cburn_Entity!Y11 -> 0 | F18: =Cburn_Entity!Z11 -> 0 | G18: =Cburn_Entity!AA11 -> 122.01 | H18: =Cburn_Entity!AB11 -> 2668.06
B19: =Cburn_Entity!V12 -> Travel & Entertainment | C19: =Cburn_Entity!W12 -> 840 | D19: =Cburn_Entity!X12 -> 0 | E19: =Cburn_Entity!Y12 -> 0 | F19: =Cburn_Entity!Z12 -> 0 | G19: =Cburn_Entity!AA12 -> 0 | H19: =Cburn_Entity!AB12 -> 840
B20: =Cburn_Entity!V13 -> Office Equipment | C20: =Cburn_Entity!W13 -> 0 | D20: =Cburn_Entity!X13 -> 0 | E20: =Cburn_Entity!Y13 -> 0 | F20: =Cburn_Entity!Z13 -> 0 | G20: =Cburn_Entity!AA13 -> 0 | H20: =Cburn_Entity!AB13 -> 0
B21: =Cburn_Entity!V14 -> Auto Expenses | C21: =Cburn_Entity!W14 -> 0 | D21: =Cburn_Entity!X14 -> 546.92 | E21: =Cburn_Entity!Y14 -> 0 | F21: =Cburn_Entity!Z14 -> 0 | G21: =Cburn_Entity!AA14 -> 279.64 | H21: =Cburn_Entity!AB14 -> 826.56
... B24: =Cburn_Entity!V17 -> Other Expenses | C24: =Cburn_Entity!W17 -> 100 | D24: =Cburn_Entity!X17 -> 719.25 | E24: =Cburn_Entity!Y17 -> 0 | F24: =Cburn_Entity!Z17 -> 0 | G24: =Cburn_Entity!AA17 -> 525.44 | H24: =Cburn_Entity!AB17 -> 1344.69
B26: =[2]Burn_MTD!T19 -> TOTAL OPERATING EXPENSES | C26: =SUM(C10:C25) -> 54242.09 | D26: =SUM(D10:D25) -> 53228.85 | E26: =SUM(E10:E25) -> 11694.79 | F26: =SUM(F10:F25) -> 1101.92 | G26: =SUM(G10:G25) -> 8796.22 | H26: =SUM(H10:H25) -> 129063.87
C45: =[2]BS_12Months!D11-C43 -> 0 | D45: =[2]BS_12Months!E11-D43 -> 0

Sheet Cburn YTD
A1: =TableofContent!A1 -> POWER FINANCIAL WELLNESS INC | O1: =[2]TableofContent!I1 -> Tanzania Shilling
A2: =TableofContent!A2 -> CONSOLIDATED MANAGEMENT ACCOUNTS
A3: 12 MONTH CASHFLOW STATEMENT
A4: =TableofContent!A4 -> FOR PERIOD ENDED JULY 31, 2025
A5: =TableofContent!A5 -> PREPARED BY: MOSES KIGO
B8: COST INCURRED | C8: 45658 | D8: =EOMONTH(C8,1) -> 45716 | E8: =EOMONTH(D8,1) -> 45747 | F8: =EOMONTH(E8,1) -> 45777 | G8: =EOMONTH(F8,1) -> 45808 | H8: =EOMONTH(G8,1) -> 45838 | I8: =EOMONTH(H8,1) -> 45869 | J8: =EOMONTH(I8,1) -> 45900 | K8: =EOMONTH(J8,1) -> 45930 | ... N8: =EOMONTH(M8,1) -> 46022 | O8: Total
B10: =CBurn_12Months!V3 -> Salary & Wages | C10: =CBurn_12Months!W3 -> 23081.07 | D10: =CBurn_12Months!X3 -> 25959.19 | E10: =CBurn_12Months!Y3 -> 25780.56 | F10: =CBurn_12Months!Z3 -> 26373.44 | G10: =CBurn_12Months!AA3 -> 30280.34 | H10: =CBurn_12Months!AB3 -> 31906.57 | I10: =CBurn_12Months!AC3 -> 24218.22 | ... N10: =CBurn_12Months!AH3 -> 0 | O10: =SUM(C10:N10) -> 257134.79
B11: =CBurn_12Months!V4 -> Consultants | C11: =CBurn_12Months!W4 -> 28217.15 | D11: =CBurn_12Months!X4 -> 29883.99 | E11: =CBurn_12Months!Y4 -> 29584.99 | F11: =CBurn_12Months!Z4 -> 35157.69 | G11: =CBurn_12Months!AA4 -> 29945.29 | H11: =CBurn_12Months!AB4 -> 34621.65 | I11: =CBurn_12Months!AC4 -> 32262.39 | ... N11: =CBurn_12Months!AH4 -> 0 | O11: =SUM(C11:N11) -> 286945.84
B12: =CBurn_12Months!V5 -> Fringe Benefits | C12: =CBurn_12Months!W5 -> 7303.02 | D12: =CBurn_12Months!X5 -> 8712.94 | E12: =CBurn_12Months!Y5 -> 10141.19 | F12: =CBurn_12Months!Z5 -> 10237.78 | G12: =CBurn_12Months!AA5 -> 11557.12 | H12: =CBurn_12Months!AB5 -> 12790.85 | I12: =CBurn_12Months!AC5 -> 13077.82 | ... N12: =CBurn_12Months!AH5 -> 0 | O12: =SUM(C12:N12) -> 103486.6
B13: =CBurn_12Months!V6 -> Rent & Office related expenses | C13: =CBurn_12Months!W6 -> 11039.74 | D13: =CBurn_12Months!X6 -> 12261.63 | E13: =CBurn_12Months!Y6 -> 11821.84 | F13: =CBurn_12Months!Z6 -> 12830.96 | G13: =CBurn_12Months!AA6 -> 14956.29 | H13: =CBurn_12Months!AB6 -> 15446.32 | I13: =CBurn_12Months!AC6 -> 14744.41 | ... N13: =CBurn_12Months!AH6 -> 0 | O13: =SUM(C13:N13) -> 123974.27
B14: =CBurn_12Months!V7 -> Utilities | C14: =CBurn_12Months!W7 -> 232.59 | D14: =CBurn_12Months!X7 -> 175.64 | E14: =CBurn_12Months!Y7 -> 182.03 | F14: =CBurn_12Months!Z7 -> 184.27 | G14: =CBurn_12Months!AA7 -> 283.41 | H14: =CBurn_12Months!AB7 -> 186.35 | I14: =CBurn_12Months!AC7 -> 212.93 | ... N14: =CBurn_12Months!AH7 -> 0 | O14: =SUM(C14:N14) -> 1927.6
B15: =CBurn_12Months!V8 -> IT Costs | C15: =CBurn_12Months!W8 -> 7138.49 | D15: =CBurn_12Months!X8 -> 6587.16 | E15: =CBurn_12Months!Y8 -> 9142.57 | F15: =CBurn_12Months!Z8 -> 4262.44 | G15: =CBurn_12Months!AA8 -> 10260.18 | H15: =CBurn_12Months!AB8 -> 6198.06 | I15: =CBurn_12Months!AC8 -> 10255.68 | ... N15: =CBurn_12Months!AH8 -> 0 | O15: =SUM(C15:N15) -> 68843.04
B16: =CBurn_12Months!V9 -> Outside Servces | C16: =CBurn_12Months!W9 -> 273.94 | D16: =CBurn_12Months!X9 -> 279.7 | E16: =CBurn_12Months!Y9 -> 290.95 | F16: =CBurn_12Months!Z9 -> 506.86 | G16: =CBurn_12Months!AA9 -> 337.33 | H16: =CBurn_12Months!AB9 -> 151.81 | I16: =CBurn_12Months!AC9 -> 292.92 | ... N16: =CBurn_12Months!AH9 -> 0 | O16: =SUM(C16:N16) -> 2986.62
B17: =CBurn_12Months!V10 -> Professional Servicess | C17: =CBurn_12Months!W10 -> 3654.74 | D17: =CBurn_12Months!X10 -> 2371.45 | E17: =CBurn_12Months!Y10 -> 3434.75 | F17: =CBurn_12Months!Z10 -> 12533.8 | G17: =CBurn_12Months!AA10 -> 3982.42 | H17: =CBurn_12Months!AB10 -> 4942.27 | I17: =CBurn_12Months!AC10 -> 4913.11 | ... N17: =CBurn_12Months!AH10 -> 0 | O17: =SUM(C17:N17) -> 47785.51
B18: =CBurn_12Months!V11 -> Selling Expenses | C18: =CBurn_12Months!W11 -> 2396.58 | D18: =CBurn_12Months!X11 -> 1175.31 | E18: =CBurn_12Months!Y11 -> 3332.11 | F18: =CBurn_12Months!Z11 -> 3376.45 | G18: =CBurn_12Months!AA11 -> 6493.16 | H18: =CBurn_12Months!AB11 -> 2413.92 | I18: =CBurn_12Months!AC11 -> 3630.66 | ... N18: =CBurn_12Months!AH11 -> 0 | O18: =SUM(C18:N18) -> 28218.37
B19: =CBurn_12Months!V12 -> Travel & Entertainment | C19: =CBurn_12Months!W12 -> 397.26 | D19: =CBurn_12Months!X12 -> 135.06 | E19: =CBurn_12Months!Y12 -> 902.64 | F19: =CBurn_12Months!Z12 -> 0 | G19: =CBurn_12Months!AA12 -> 2378.75 | H19: =CBurn_12Months!AB12 -> 536.77 | I19: =CBurn_12Months!AC12 -> 1770.32 | ... N19: =CBurn_12Months!AH12 -> 0 | O19: =SUM(C19:N19) -> 11555.84
B20: =CBurn_12Months!V13 -> Office Equipment | C20: =CBurn_12Months!W13 -> 34.01 | D20: =CBurn_12Months!X13 -> 1.55 | E20: =CBurn_12Months!Y13 -> 71.7 | F20: =CBurn_12Months!Z13 -> 23.19 | G20: =CBurn_12Months!AA13 -> 269.96 | H20: =CBurn_12Months!AB13 -> 0 | I20: =CBurn_12Months!AC13 -> 0 | ... N20: =CBurn_12Months!AH13 -> 0 | O20: =SUM(C20:N20) -> 400.41
B21: =CBurn_12Months!V14 -> Auto Expenses | C21: =CBurn_12Months!W14 -> 507.7 | D21: =CBurn_12Months!X14 -> 853.25 | E21: =CBurn_12Months!Y14 -> 1046.94 | F21: =CBurn_12Months!Z14 -> 504.12 | G21: =CBurn_12Months!AA14 -> 926.61 | H21: =CBurn_12Months!AB14 -> 1659.25 | I21: =CBurn_12Months!AC14 -> 965.23 | ... N21: =CBurn_12Months!AH14 -> 0 | O21: =SUM(C21:N21) -> 8188.9
... B24: =CBurn_12Months!V17 -> Other Expenses | C24: =CBurn_12Months!W17 -> 559.42 | D24: =CBurn_12Months!X17 -> 1303.5 | E24: =CBurn_12Months!Y17 -> 456.18 | F24: =CBurn_12Months!Z17 -> 3670.99 | G24: =CBurn_12Months!AA17 -> 5805.59 | H24: =CBurn_12Months!AB17 -> 4170.46 | I24: =CBurn_12Months!AC17 -> 4342.1 | ... N24: =CBurn_12Months!AH17 -> 0 | O24: =SUM(C24:N24) -> 17962.38
B26: =[2]Burn_MTD!T19 -> TOTAL OPERATING EXPENSES | C26: =SUM(C10:C25) -> 87820.08 | D26: =SUM(D10:D25) -> 92684.74 | E26: =SUM(E10:E25) -> 99172.82 | F26: =SUM(F10:F25) -> 112646.36 | G26: =SUM(G10:G25) -> 120460.82 | H26: =SUM(H10:H25) -> 118008.65 | I26: =SUM(I10:I25) -> 113690.38 | J26: =SUM(J10:J25) -> 112782.44 | ... O26: =SUM(O10:O25) -> 986330.16
C45: =[2]BS_12Months!D11-C43 -> 0 | D45: =[2]BS_12Months!E11-D43 -> 0

Sheet Data --->

Sheet BS(Qrtly(
A1: Financial Report | B1: Name | C1: Description | D1: Row Definition | E1: Column Definition | F1: View by | G1: Date Filter | H1: Show All Lines | I1: Product Filter | J1: Department Filter | K1: Business-Unit Filter | L1: Cost-center Filter | M1: Cost Center Filter | N1: Cost Object Filter | O1: Cash Flow Filter | P1: G/L Budget Filter | Q1: Cost Budget Filter | R1: Row No. | S1: Description1 | T1: Quarter 1 | U1: Quarter 2 | V1: Quarter 3 | W1: Quarter 4 | X1: Total | Z1: 1 | AA1: 2 | AB1: 3 | AC1: 4 | AD1: 5 | AE1: 6 | AF1: 7 | AG1: 8 | AH1: 9
A2: M-BALANCE - Balance Sheet - M-BALANCE - QRT-BAL | B2: M-BALANCE | C2: Balance Sheet | D2: M-BALANCE | E2: QRT-BAL | F2: Year | G2: 01/11/24..30/11/24 | H2: =FALSE() -> FALSE | S2: Assets | T2: 0 | U2: 0 | V2: 0 | W2: 0 | X2: 0 | Y2: 0 | Z2: 0 | AA2: 0 | AB2: 0 | AC2: 0 | AD2: 0 | AE2: 0 | AF2: 0 | AG2: 0 | AH2: 0
A3: M-BALANCE - Balance Sheet - M-BALANCE - QRT-BAL | B3: M-BALANCE | C3: Balance Sheet | D3: M-BALANCE | E3: QRT-BAL | F3: Year | G3: 01/11/24..30/11/24 | H3: =FALSE() -> FALSE | R3: 010 | S3: Current Assets | T3: 0 | U3: 0 | V3: 0 | W3: 0 | X3: 0 | Y3: 0 | Z3: 0 | AA3: 0 | AB3: 0 | AC3: 0 | AD3: 0 | AE3: 0 | AF3: 0 | AG3: 0 | AH3: 0
A4: M-BALANCE - Balance Sheet - M-BALANCE - QRT-BAL | B4: M-BALANCE | C4: Balance Sheet | D4: M-BALANCE | E4: QRT-BAL | F4: Year | G4: 01/11/24..30/11/24 | H4: =FALSE() -> FALSE | R4: 020 | S4: Cash & Cash Equivalents | T4: 689896 | U4: 653836 | V4: 537995.66 | W4: 0 | X4: 794225.58 | Y4: 0 | Z4: 0 | AA4: 0 | AB4: 0 | AC4: 0 | AD4: 0 | AE4: 0 | AF4: 0 | AG4: 0 | AH4: 0
A5: M-BALANCE - Balance Sheet - M-BALANCE - QRT-BAL | B5: M-BALANCE | C5: Balance Sheet | D5: M-BALANCE | E5: QRT-BAL | F5: Year | G5: 01/11/24..30/11/24 | H5: =FALSE() -> FALSE | R5: 030 | S5: Net Loan Receivable | T5: 1172340 | U5: 1368363 | V5: 1645999.1 | W5: 0 | X5: 1010459 | Y5: 0 | Z5: 0 | AA5: 0 | AB5: 0 | AC5: 0 | AD5: 0 | AE5: 0 | AF5: 0 | AG5: 0 | AH5: 0
A6: M-BALANCE - Balance Sheet - M-BALANCE - QRT-BAL | B6: M-BALANCE | C6: Balance Sheet | D6: M-BALANCE | E6: QRT-BAL | F6: Year | G6: 01/11/24..30/11/24 | H6: =FALSE() -> FALSE | R6: 040 | S6: Interco-Receivable | T6: 1146509 | U6: 1324774 | V6: 1623863.2 | W6: 0 | X6: 984666.07 | Y6: 0 | Z6: 0 | AA6: 0 | AB6: 0 | AC6: 0 | AD6: 0 | AE6: 0 | AF6: 0 | AG6: 0 | AH6: 0
A7: M-BALANCE - Balance Sheet - M-BALANCE - QRT-BAL | B7: M-BALANCE | C7: Balance Sheet | D7: M-BALANCE | E7: QRT-BAL | F7: Year | G7: 01/11/24..30/11/24 | H7: =FALSE() -> FALSE | R7: 050 | S7: Other Current Assets | T7: 218927 | U7: 176172 | V7: 181855.23 | W7: 0 | X7: 243756.25 | Y7: 0 | Z7: 0 | AA7: 0 | AB7: 0 | AC7: 0 | AD7: 0 | AE7: 0 | AF7: 0 | AG7: 0 | AH7: 0
A8: M-BALANCE - Balance Sheet - M-BALANCE - QRT-BAL | B8: M-BALANCE | C8: Balance Sheet | D8: M-BALANCE | E8: QRT-BAL | F8: Year | G8: 01/11/24..30/11/24 | H8: =FALSE() -> FALSE | R8: 099 | S8: Total Current Assets | T8: 3227672 | U8: 3523145 | V8: 3989713.2 | W8: 0 | X8: 3033106.9 | Y8: 0 | Z8: 0 | AA8: 0 | AB8: 0 | AC8: 0 | AD8: 0 | AE8: 0 | AF8: 0 | AG8: 0 | AH8: 0
A9: M-BALANCE - Balance Sheet - M-BALANCE - QRT-BAL | B9: M-BALANCE | C9: Balance Sheet | D9: M-BALANCE | E9: QRT-BAL | F9: Year | G9: 01/11/24..30/11/24 | H9: =FALSE() -> FALSE | T9: 0 | U9: 0 | V9: 0 | W9: 0 | X9: 0 | Y9: 0 | Z9: 0 | AA9: 0 | AB9: 0 | AC9: 0 | AD9: 0 | AE9: 0 | AF9: 0 | AG9: 0 | AH9: 0
A10: M-BALANCE - Balance Sheet - M-BALANCE - QRT-BAL | B10: M-BALANCE | C10: Balance Sheet | D10: M-BALANCE | E10: QRT-BAL | F10: Year | G10: 01/11/24..30/11/24 | H10: =FALSE() -> FALSE | R10: 100 | S10: Non-Current Assets | T10: 0 | U10: 0 | V10: 0 | W10: 0 | X10: 0 | Y10: 0 | Z10: 0 | AA10: 0 | AB10: 0 | AC10: 0 | AD10: 0 | AE10: 0 | AF10: 0 | AG10: 0 | AH10: 0
A11: M-BALANCE - Balance Sheet - M-BALANCE - QRT-BAL | B11: M-BALANCE | C11: Balance Sheet | D11: M-BALANCE | E11: QRT-BAL | F11: Year | G11: 01/11/24..30/11/24 | H11: =FALSE() -> FALSE | R11: 110 | S11: Gross Fixed Assets | T11: 45208 | U11: 46249 | V11: 50070.5 | W11: 0 | X11: 36174.87 | Y11: 0 | Z11: 0 | AA11: 0 | AB11: 0 | AC11: 0 | AD11: 0 | AE11: 0 | AF11: 0 | AG11: 0 | AH11: 0
A12: M-BALANCE - Balance Sheet - M-BALANCE - QRT-BAL | B12: M-BALANCE | C12: Balance Sheet | D12: M-BALANCE | E12: QRT-BAL | F12: Year | G12: 01/11/24..30/11/24 | H12: =FALSE() -> FALSE | R12: 111 | S12: Acc. Depreciation | T12: -22835 | U12: -26189 | V12: -29699.01 | W12: 0 | X12: -20449.61 | Y12: 0 | Z12: 0 | AA12: 0 | AB12: 0 | AC12: 0 | AD12: 0 | AE12: 0 | AF12: 0 | AG12: 0 | AH12: 0
A13: M-BALANCE - Balance Sheet - M-BALANCE - QRT-BAL | B13: M-BALANCE | C13: Balance Sheet | D13: M-BALANCE | E13: QRT-BAL | F13: Year | G13: 01/11/24..30/11/24 | H13: =FALSE() -> FALSE | R13: 120 | S13: Gross Intangible Assets | T13: 740386 | U13: 740386 | V13: 740386.28 | W13: 0 | X13: 740386.28 | Y13: 0 | Z13: 0 | AA13: 0 | AB13: 0 | AC13: 0 | AD13: 0 | AE13: 0 | AF13: 0 | AG13: 0 | AH13: 0
A14: M-BALANCE - Balance Sheet - M-BALANCE - QRT-BAL | B14: M-BALANCE | C14: Balance Sheet | D14: M-BALANCE | E14: QRT-BAL | F14: Year | G14: 01/11/24..30/11/24 | H14: =FALSE() -> FALSE | R14: 121 | S14: Acc. Ammortization | T14: -646808 | U14: -707313 | V14: -735507.41 | W14: 0 | X14: -586586.24 | Y14: 0 | Z14: 0 | AA14: 0 | AB14: 0 | AC14: 0 | AD14: 0 | AE14: 0 | AF14: 0 | AG14: 0 | AH14: 0
A15: M-BALANCE - Balance Sheet - M-BALANCE - QRT-BAL | B15: M-BALANCE | C15: Balance Sheet | D15: M-BALANCE | E15: QRT-BAL | F15: Year | G15: 01/11/24..30/11/24 | H15: =FALSE() -> FALSE | R15: 130 | S15: Interco-Receivable Long Term | T15: 2127703 | U15: 2127703 | V15: 2127702.6 | W15: 0 | X15: 2127702.6 | Y15: 0 | Z15: 0 | AA15: 0 | AB15: 0 | AC15: 0 | AD15: 0 | AE15: 0 | AF15: 0 | AG15: 0 | AH15: 0
A16: M-BALANCE - Balance Sheet - M-BALANCE - QRT-BAL | B16: M-BALANCE | C16: Balance Sheet | D16: M-BALANCE | E16: QRT-BAL | F16: Year | G16: 01/11/24..30/11/24 | H16: =FALSE() -> FALSE | R16: 140 | S16: Other Long Term Assets | T16: 19380 | U16: 19380 | V16: 19380.33 | W16: 0 | X16: 19380.33 | Y16: 0 | Z16: 0 | AA16: 0 | AB16: 0 | AC16: 0 | AD16: 0 | AE16: 0 | AF16: 0 | AG16: 0 | AH16: 0
A17: M-BALANCE - Balance Sheet - M-BALANCE - QRT-BAL | B17: M-BALANCE | C17: Balance Sheet | D17: M-BALANCE | E17: QRT-BAL | F17: Year | G17: 01/11/24..30/11/24 | H17: =FALSE() -> FALSE | R17: 199 | S17: Total Non-Current Assets | T17: 2263035 | U17: 2200217 | V17: 2172333.3 | W17: 0 | X17: 2316608.3 | Y17: 0 | Z17: 0 | AA17: 0 | AB17: 0 | AC17: 0 | AD17: 0 | AE17: 0 | AF17: 0 | AG17: 0 | AH17: 0
A18: M-BALANCE - Balance Sheet - M-BALANCE - QRT-BAL | B18: M-BALANCE | C18: Balance Sheet | D18: M-BALANCE | E18: QRT-BAL | F18: Year | G18: 01/11/24..30/11/24 | H18: =FALSE() -> FALSE | T18: 0 | U18: 0 | V18: 0 | W18: 0 | X18: 0 | Y18: 0 | Z18: 0 | AA18: 0 | AB18: 0 | AC18: 0 | AD18: 0 | AE18: 0 | AF18: 0 | AG18: 0 | AH18: 0
A19: M-BALANCE - Balance Sheet - M-BALANCE - QRT-BAL | B19: M-BALANCE | C19: Balance Sheet | D19: M-BALANCE | E19: QRT-BAL | F19: Year | G19: 01/11/24..30/11/24 | H19: =FALSE() -> FALSE | R19: F1 | S19: Total Assets | T19: 5490707 | U19: 5723362 | V19: 6162046.5 | W19: 0 | X19: 5349715.2 | Y19: 0 | Z19: 0 | AA19: 0 | AB19: 0 | AC19: 0 | AD19: 0 | AE19: 0 | AF19: 0 | AG19: 0 | AH19: 0
A20: M-BALANCE - Balance Sheet - M-BALANCE - QRT-BAL | B20: M-BALANCE | C20: Balance Sheet | D20: M-BALANCE | E20: QRT-BAL | F20: Year | G20: 01/11/24..30/11/24 | H20: =FALSE() -> FALSE | T20: 0 | U20: 0 | V20: 0 | W20: 0 | X20: 0 | Y20: 0 | Z20: 0 | AA20: 0 | AB20: 0 | AC20: 0 | AD20: 0 | AE20: 0 | AF20: 0 | AG20: 0 | AH20: 0
A21: M-BALANCE - Balance Sheet - M-BALANCE - QRT-BAL | B21: M-BALANCE | C21: Balance Sheet | D21: M-BALANCE | E21: QRT-BAL | F21: Year | G21: 01/11/24..30/11/24 | H21: =FALSE() -> FALSE | S21: Liabilities | T21: 0 | U21: 0 | V21: 0 | W21: 0 | X21: 0 | Y21: 0 | Z21: 0 | AA21: 0 | AB21: 0 | AC21: 0 | AD21: 0 | AE21: 0 | AF21: 0 | AG21: 0 | AH21: 0
A22: M-BALANCE - Balance Sheet - M-BALANCE - QRT-BAL | B22: M-BALANCE | C22: Balance Sheet | D22: M-BALANCE | E22: QRT-BAL | F22: Year | G22: 01/11/24..30/11/24 | H22: =FALSE() -> FALSE | R22: 200 | S22: Current Liabilities | T22: 0 | U22: 0 | V22: 0 | W22: 0 | X22: 0 | Y22: 0 | Z22: 0 | AA22: 0 | AB22: 0 | AC22: 0 | AD22: 0 | AE22: 0 | AF22: 0 | AG22: 0 | AH22: 0
A23: M-BALANCE - Balance Sheet - M-BALANCE - QRT-BAL | B23: M-BALANCE | C23: Balance Sheet | D23: M-BALANCE | E23: QRT-BAL | F23: Year | G23: 01/11/24..30/11/24 | H23: =FALSE() -> FALSE | R23: 210 | S23: Accounts Payable | T23: 225656 | U23: 227115 | V23: 263042.26 | W23: 0 | X23: 203123.84 | Y23: 0 | Z23: 0 | AA23: 0 | AB23: 0 | AC23: 0 | AD23: 0 | AE23: 0 | AF23: 0 | AG23: 0 | AH23: 0
A24: M-BALANCE - Balance Sheet - M-BALANCE - QRT-BAL | B24: M-BALANCE | C24: Balance Sheet | D24: M-BALANCE | E24: QRT-BAL | F24: Year | G24: 01/11/24..30/11/24 | H24: =FALSE() -> FALSE | R24: 220 | S24: Intercompany Payable | T24: 888576 | U24: 1046101 | V24: 1275262.4 | W24: 0 | X24: 825563.32 | Y24: 0 | Z24: 0 | AA24: 0 | AB24: 0 | AC24: 0 | AD24: 0 | AE24: 0 | AF24: 0 | AG24: 0 | AH24: 0
A25: M-BALANCE - Balance Sheet - M-BALANCE - QRT-BAL | B25: M-BALANCE | C25: Balance Sheet | D25: M-BALANCE | E25: QRT-BAL | F25: Year | G25: 01/11/24..30/11/24 | H25: =FALSE() -> FALSE | R25: 230 | S25: Overdraft / Revolver | T25: 39566 | U25: 53316 | V25: 41005.26 | W25: 0 | X25: 38451.08 | Y25: 0 | Z25: 0 | AA25: 0 | AB25: 0 | AC25: 0 | AD25: 0 | AE25: 0 | AF25: 0 | AG25: 0 | AH25: 0
A26: M-BALANCE - Balance Sheet - M-BALANCE - QRT-BAL | B26: M-BALANCE | C26: Balance Sheet | D26: M-BALANCE | E26: QRT-BAL | F26: Year | G26: 01/11/24..30/11/24 | H26: =FALSE() -> FALSE | R26: 240 | S26: Customer Deposits | T26: 41667 | U26: 28365 | V26: 24579.65 | W26: 0 | X26: 53625.32 | Y26: 0 | Z26: 0 | AA26: 0 | AB26: 0 | AC26: 0 | AD26: 0 | AE26: 0 | AF26: 0 | AG26: 0 | AH26: 0
A27: M-BALANCE - Balance Sheet - M-BALANCE - QRT-BAL | B27: M-BALANCE | C27: Balance Sheet | D27: M-BALANCE | E27: QRT-BAL | F27: Year | G27: 01/11/24..30/11/24 | H27: =FALSE() -> FALSE | R27: 250 | S27: Accrued Expenses | T27: 163075 | U27: 116305 | V27: 119738.96 | W27: 0 | X27: 158726.11 | Y27: 0 | Z27: 0 | AA27: 0 | AB27: 0 | AC27: 0 | AD27: 0 | AE27: 0 | AF27: 0 | AG27: 0 | AH27: 0
A28: M-BALANCE - Balance Sheet - M-BALANCE - QRT-BAL | B28: M-BALANCE | C28: Balance Sheet | D28: M-BALANCE | E28: QRT-BAL | F28: Year | G28: 01/11/24..30/11/24 | H28: =FALSE() -> FALSE | R28: 290 | S28: Total Current Liabilities | T28: 1358540 | U28: 1471203 | V28: 1723628.5 | W28: 0 | X28: 1279489.7 | Y28: 0 | Z28: 0 | AA28: 0 | AB28: 0 | AC28: 0 | AD28: 0 | AE28: 0 | AF28: 0 | AG28: 0 | AH28: 0
A29: M-BALANCE - Balance Sheet - M-BALANCE - QRT-BAL | B29: M-BALANCE | C29: Balance Sheet | D29: M-BALANCE | E29: QRT-BAL | F29: Year | G29: 01/11/24..30/11/24 | H29: =FALSE() -> FALSE | T29: 0 | U29: 0 | V29: 0 | W29: 0 | X29: 0 | Y29: 0 | Z29: 0 | AA29: 0 | AB29: 0 | AC29: 0 | AD29: 0 | AE29: 0 | AF29: 0 | AG29: 0 | AH29: 0
A30: M-BALANCE - Balance Sheet - M-BALANCE - QRT-BAL | B30: M-BALANCE | C30: Balance Sheet | D30: M-BALANCE | E30: QRT-BAL | F30: Year | G30: 01/11/24..30/11/24 | H30: =FALSE() -> FALSE | R30: 300 | S30: Non-Current Liabilities | T30: 0 | U30: 0 | V30: 0 | W30: 0 | X30: 0 | Y30: 0 | Z30: 0 | AA30: 0 | AB30: 0 | AC30: 0 | AD30: 0 | AE30: 0 | AF30: 0 | AG30: 0 | AH30: 0
A31: M-BALANCE - Balance Sheet - M-BALANCE - QRT-BAL | B31: M-BALANCE | C31: Balance Sheet | D31: M-BALANCE | E31: QRT-BAL | F31: Year | G31: 01/11/24..30/11/24 | H31: =FALSE() -> FALSE | R31: 310 | S31: LT Intercompany Loan | T31: 2362682 | U31: 2362681 | V31: 2475151.4 | W31: 0 | X31: 2317595 | Y31: 0 | Z31: 0 | AA31: 0 | AB31: 0 | AC31: 0 | AD31: 0 | AE31: 0 | AF31: 0 | AG31: 0 | AH31: 0
A32: M-BALANCE - Balance Sheet - M-BALANCE - QRT-BAL | B32: M-BALANCE | C32: Balance Sheet | D32: M-BALANCE | E32: QRT-BAL | F32: Year | G32: 01/11/24..30/11/24 | H32: =FALSE() -> FALSE | R32: 320 | S32: LT Debt | T32: 1901589 | U32: 2151589 | V32: 2652200.4 | W32: 0 | X32: 921108.45 | Y32: 0 | Z32: 0 | AA32: 0 | AB32: 0 | AC32: 0 | AD32: 0 | AE32: 0 | AF32: 0 | AG32: 0 | AH32: 0
A33: M-BALANCE - Balance Sheet - M-BALANCE - QRT-BAL | B33: M-BALANCE | C33: Balance Sheet | D33: M-BALANCE | E33: QRT-BAL | F33: Year | G33: 01/11/24..30/11/24 | H33: =FALSE() -> FALSE | R33: 390 | S33: Total Non-Current Liabilities | T33: 3484271 | U33: 3634348 | V33: 5127351.8 | W33: 0 | X33: 3238703.5 | Y33: 0 | Z33: 0 | AA33: 0 | AB33: 0 | AC33: 0 | AD33: 0 | AE33: 0 | AF33: 0 | AG33: 0 | AH33: 0
A34: M-BALANCE - Balance Sheet - M-BALANCE - QRT-BAL | B34: M-BALANCE | C34: Balance Sheet | D34: M-BALANCE | E34: QRT-BAL | F34: Year | G34: 01/11/24..30/11/24 | H34: =FALSE() -> FALSE | T34: 0 | U34: 0 | V34: 0 | W34: 0 | X34: 0 | Y34: 0 | Z34: 0 | AA34: 0 | AB34: 0 | AC34: 0 | AD34: 0 | AE34: 0 | AF34: 0 | AG34: 0 | AH34: 0
A35: M-BALANCE - Balance Sheet - M-BALANCE - QRT-BAL | B35: M-BALANCE | C35: Balance Sheet | D35: M-BALANCE | E35: QRT-BAL | F35: Year | G35: 01/11/24..30/11/24 | H35: =FALSE() -> FALSE | R35: 400 | S35: Equity | T35: 0 | U35: 0 | V35: 0 | W35: 0 | X35: 0 | Y35: 0 | Z35: 0 | AA35: 0 | AB35: 0 | AC35: 0 | AD35: 0 | AE35: 0 | AF35: 0 | AG35: 0 | AH35: 0
A36: M-BALANCE - Balance Sheet - M-BALANCE - QRT-BAL | B36: M-BALANCE | C36: Balance Sheet | D36: M-BALANCE | E36: QRT-BAL | F36: Year | G36: 01/11/24..30/11/24 | H36: =FALSE() -> FALSE | R36: 410 | S36: Share Capital | T36: 3984300 | U36: 3984335 | V36: 3984334.9 | W36: 0 | X36: 3984299.9 | Y36: 0 | Z36: 0 | AA36: 0 | AB36: 0 | AC36: 0 | AD36: 0 | AE36: 0 | AF36: 0 | AG36: 0 | AH36: 0
A37: M-BALANCE - Balance Sheet - M-BALANCE - QRT-BAL | B37: M-BALANCE | C37: Balance Sheet | D37: M-BALANCE | E37: QRT-BAL | F37: Year | G37: 01/11/24..30/11/24 | H37: =FALSE() -> FALSE | R37: 420 | S37: Parent Company Investment in Subsidiary | T37: -8519 | U37: -8519 | V37: -8519.07 | W37: 0 | X37: -8519.07 | Y37: 0 | Z37: 0 | AA37: 0 | AB37: 0 | AC37: 0 | AD37: 0 | AE37: 0 | AF37: 0 | AG37: 0 | AH37: 0
A38: M-BALANCE - Balance Sheet - M-BALANCE - QRT-BAL | B38: M-BALANCE | C38: Balance Sheet | D38: M-BALANCE | E38: QRT-BAL | F38: Year | G38: 01/11/24..30/11/24 | H38: =FALSE() -> FALSE | R38: 430 | S38: PY Retained Earnings | T38: -3740271.1 | U38: -3576720.9 | V38: -891053.5 | W38: 0 | X38: -891053.5 | Y38: 0 | Z38: 0 | AA38: 0 | AB38: 0 | AC38: 0 | AD38: 0 | AE38: 0 | AF38: 0 | AG38: 0 | AH38: 0
A39: M-BALANCE - Balance Sheet - M-BALANCE - QRT-BAL | B39: M-BALANCE | C39: Balance Sheet | D39: M-BALANCE | E39: QRT-BAL | F39: Year | G39: 01/11/24..30/11/24 | H39: =FALSE() -> FALSE | R39: 440 | S39: CY Retained Earnings | T39: -265161.94 | U39: -558683.07 | V39: -3671175.6 | W39: 0 | X39: -2921248.9 | Y39: 0 | Z39: 0 | AA39: 0 | AB39: 0 | AC39: 0 | AD39: 0 | AE39: 0 | AF39: 0 | AG39: 0 | AH39: 0
A40: M-BALANCE - Balance Sheet - M-BALANCE - QRT-BAL | B40: M-BALANCE | C40: Balance Sheet | D40: M-BALANCE | E40: QRT-BAL | F40: Year | G40: 01/11/24..30/11/24 | H40: =FALSE() -> FALSE | R40: 450 | S40: CY Foreign Currency Transalation | T40: -102453 | U40: -102523 | V40: -102520.58 | W40: 0 | X40: -102377.51 | Y40: 0 | Z40: 0 | AA40: 0 | AB40: 0 | AC40: 0 | AD40: 0 | AE40: 0 | AF40: 0 | AG40: 0 | AH40: 0
A41: M-BALANCE - Balance Sheet - M-BALANCE - QRT-BAL | B41: M-BALANCE | C41: Balance Sheet | D41: M-BALANCE | E41: QRT-BAL | F41: Year | G41: 01/11/24..30/11/24 | H41: =FALSE() -> FALSE | R41: 499 | S41: Total Equity | T41: -145174 | U41: -440561 | V41: -688933.85 | W41: 0 | X41: 61100.97 | Y41: 0 | Z41: 0 | AA41: 0 | AB41: 0 | AC41: 0 | AD41: 0 | AE41: 0 | AF41: 0 | AG41: 0 | AH41: 0
A42: M-BALANCE - Balance Sheet - M-BALANCE - QRT-BAL | B42: M-BALANCE | C42: Balance Sheet | D42: M-BALANCE | E42: QRT-BAL | F42: Year | G42: 01/11/24..30/11/24 | H42: =FALSE() -> FALSE | T42: 0 | U42: 0 | V42: 0 | W42: 0 | X42: 0 | Y42: 0 | Z42: 0 | AA42: 0 | AB42: 0 | AC42: 0 | AD42: 0 | AE42: 0 | AF42: 0 | AG42: 0 | AH42: 0
A43: M-BALANCE - Balance Sheet - M-BALANCE - QRT-BAL | B43: M-BALANCE | C43: Balance Sheet | D43: M-BALANCE | E43: QRT-BAL | F43: Year | G43: 01/11/24..30/11/24 | H43: =FALSE() -> FALSE | R43: F2 | S43: Total Equity and Liabilities | T43: 4697637 | U43: 4664990 | V43: 6162046.5 | W43: 0 | X43: 4579294.1 | Y43: 0 | Z43: 0 | AA43: 0 | AB43: 0 | AC43: 0 | AD43: 0 | AE43: 0 | AF43: 0 | AG43: 0 | AH43: 0
A44: M-BALANCE - Balance Sheet - M-BALANCE - QRT-BAL | B44: M-BALANCE | C44: Balance Sheet | D44: M-BALANCE | E44: QRT-BAL | F44: Year | G44: 01/11/24..30/11/24 | H44: =FALSE() -> FALSE | T44: 0 | U44: 0 | V44: 0 | W44: 0 | X44: 0 | Y44: 0 | Z44: 0 | AA44: 0 | AB44: 0 | AC44: 0 | AD44: 0 | AE44: 0 | AF44: 0 | AG44: 0 | AH44: 0
A45: M-BALANCE - Balance Sheet - M-BALANCE - QRT-BAL | B45: M-BALANCE | C45: Balance Sheet | D45: M-BALANCE | E45: QRT-BAL | F45: Year | G45: 01/11/24..30/11/24 | H45: =FALSE() -> FALSE | R45: 999 | S45: Check | T45: 0 | U45: 0 | V45: 0 | W45: 0 | X45: 770421.06 | Y45: 0 | Z45: 0 | AA45: 0 | AB45: 0 | AC45: 0 | AD45: 0 | AE45: 0 | AF45: 0 | AG45: 0 | AH45: 0

Sheet IS_QRT
A1: Financial Report | B1: Name | C1: Description | D1: Row Definition | E1: Column Definition | F1: View by | G1: Date Filter | H1: Show All Lines | I1: Product Filter | J1: Department Filter | K1: Business-Unit Filter | L1: Cost-center Filter | M1: Cost Center Filter | N1: Cost Object Filter | O1: Cash Flow Filter | P1: G/L Budget Filter | Q1: Cost Budget Filter | R1: Row No. | S1: Description1 | T1: Quarter 1 | U1: Quarter 2 | V1: Quarter 3 | W1: Quarter 4 | X1: Total | Z1: 1 | AA1: 2 | AB1: 3 | AC1: 4 | AD1: 5 | AE1: 6 | AF1: 7 | AG1: 8 | AH1: 9
A2: M-INCOME - Income Statement - M-INCOME - MTD-NET | B2: M-INCOME | C2: Income Statement | D2: M-INCOME | E2: QRT-INC | F2: Year | G2: 01/11/24..30/11/24 | H2: =TRUE() -> TRUE | T2: 0 | U2: 0 | V2: 0 | W2: 0 | X2: 0 | Y2: 0 | Z2: 0 | AA2: 0 | AB2: 0 | AC2: 0 | AD2: 0 | AE2: 0 | AF2: 0 | AG2: 0 | AH2: 0
A3: M-INCOME - Income Statement - M-INCOME - MTD-NET | B3: M-INCOME | C3: Income Statement | D3: M-INCOME | E3: QRT-INC | F3: Year | G3: 01/11/24..30/11/24 | H3: =TRUE() -> TRUE | R3: H1 | S3: PROFIT & LOSS STATMENT | T3: 0 | U3: 0 | V3: 0 | W3: 0 | X3: 0 | Y3: 0 | Z3: 0 | AA3: 0 | AB3: 0 | AC3: 0 | AD3: 0 | AE3: 0 | AF3: 0 | AG3: 0 | AH3: 0
A4: M-INCOME - Income Statement - M-INCOME - MTD-NET | B4: M-INCOME | C4: Income Statement | D4: M-INCOME | E4: QRT-INC | F4: Year | G4: 01/11/24..30/11/24 | H4: =TRUE() -> TRUE | R4: L11 | S4: Interest Income : Loans | T4: 93617.54 | U4: 123446 | V4: 155737.86 | W4: 0 | X4: 93698.93 | Y4: 0 | Z4: 0 | AA4: 0 | AB4: 0 | AC4: 0 | AD4: 0 | AE4: 0 | AF4: 0 | AG4: 0 | AH4: 0
A5: M-INCOME - Income Statement - M-INCOME - MTD-NET | B5: M-INCOME | C5: Income Statement | D5: M-INCOME | E5: QRT-INC | F5: Year | G5: 01/11/24..30/11/24 | H5: =TRUE() -> TRUE | R5: L12 | S5: Interest Income : Other | T5: 15946.26 | U5: 18143.1 | V5: 19358 | W5: 0 | X5: 15946.26 | Y5: 0 | Z5: 0 | AA5: 0 | AB5: 0 | AC5: 0 | AD5: 0 | AE5: 0 | AF5: 0 | AG5: 0 | AH5: 0
A6: M-INCOME - Income Statement - M-INCOME - MTD-NET | B6: M-INCOME | C6: Income Statement | D6: M-INCOME | E6: QRT-INC | F6: Year | G6: 01/11/24..30/11/24 | H6: =TRUE() -> TRUE | R6: L13 | S6: Interest Expense : Borrowings | T6: -72218.65 | U6: -84365.81 | V6: -101120.98 | W6: 0 | X6: -72218.65 | Y6: 0 | Z6: 0 | AA6: 0 | AB6: 0 | AC6: 0 | AD6: 0 | AE6: 0 | AF6: 0 | AG6: 0 | AH6: 0
A7: M-INCOME - Income Statement - M-INCOME - MTD-NET | B7: M-INCOME | C7: Income Statement | D7: M-INCOME | E7: QRT-INC | F7: Year | G7: 01/11/24..30/11/24 | H7: =TRUE() -> TRUE | R7: F1 | S7: NET INTEREST INCOME | T7: 37345.15 | U7: 57223.29 | V7: 73974.88 | W7: 0 | X7: 37426.54 | Y7: 0 | Z7: 0 | AA7: 0 | AB7: 0 | AC7: 0 | AD7: 0 | AE7: 0 | AF7: 0 | AG7: 0 | AH7: 0
A8: M-INCOME - Income Statement - M-INCOME - MTD-NET | B8: M-INCOME | C8: Income Statement | D8: M-INCOME | E8: QRT-INC | F8: Year | G8: 01/11/24..30/11/24 | H8: =TRUE() -> TRUE | R8: S0 | T8: 0 | U8: 0 | V8: 0 | W8: 0 | X8: 0 | Y8: 0 | Z8: 0 | AA8: 0 | AB8: 0 | AC8: 0 | AD8: 0 | AE8: 0 | AF8: 0 | AG8: 0 | AH8: 0
A9: M-INCOME - Income Statement - M-INCOME - MTD-NET | B9: M-INCOME | C9: Income Statement | D9: M-INCOME | E9: QRT-INC | F9: Year | G9: 01/11/24..30/11/24 | H9: =TRUE() -> TRUE | R9: L21 | S9: Fee Income | T9: =92025.11-(6500*3) -> 72525.11 | U9: =101093.76-19500 -> 81593.76 | V9: 125169.6 | W9: 0 | X9: 92053.8 | Y9: 0 | Z9: 0 | AA9: 0 | AB9: 0 | AC9: 0 | AD9: 0 | AE9: 0 | AF9: 0 | AG9: 0 | AH9: 0
A10: M-INCOME - Income Statement - M-INCOME - MTD-NET | B10: M-INCOME | C10: Income Statement | D10: M-INCOME | E10: QRT-INC | F10: Year | G10: 01/11/24..30/11/24 | H10: =TRUE() -> TRUE | R10: L22 | S10: Commisions | T10: 1797.73 | U10: 2250.06 | V10: 2696.97 | W10: 0 | X10: 1801.93 | Y10: 0 | Z10: 0 | AA10: 0 | AB10: 0 | AC10: 0 | AD10: 0 | AE10: 0 | AF10: 0 | AG10: 0 | AH10: 0
A11: M-INCOME - Income Statement - M-INCOME - MTD-NET | B11: M-INCOME | C11: Income Statement | D11: M-INCOME | E11: QRT-INC | F11: Year | G11: 01/11/24..30/11/24 | H11: =TRUE() -> TRUE | R11: L23 | S11: Other Income/(Expenses) | T11: =18000+(6500*3) -> 37500 | U11: 37500 | V11: 9027.74 | W11: 0 | X11: 18000 | Y11: 0 | Z11: 0 | AA11: 0 | AB11: 0 | AC11: 0 | AD11: 0 | AE11: 0 | AF11: 0 | AG11: 0 | AH11: 0 | AK11: =Table12[[#This Row],[Quarter 1]]-Table12[[#This Row],[Quarter 2]] -> 0
A12: M-INCOME - Income Statement - M-INCOME - MTD-NET | B12: M-INCOME | C12: Income Statement | D12: M-INCOME | E12: QRT-INC | F12: Year | G12: 01/11/24..30/11/24 | H12: =TRUE() -> TRUE | R12: F2 | S12: FEES & COMMISIONS | T12: 111822.84 | U12: 121343.82 | V12: 136894.31 | W12: 0 | X12: 111855.73 | Y12: 0 | Z12: 0 | AA12: 0 | AB12: 0 | AC12: 0 | AD12: 0 | AE12: 0 | AF12: 0 | AG12: 0 | AH12: 0
A13: M-INCOME - Income Statement - M-INCOME - MTD-NET | B13: M-INCOME | C13: Income Statement | D13: M-INCOME | E13: QRT-INC | F13: Year | G13: 01/11/24..30/11/24 | H13: =TRUE() -> TRUE | R13: S1 | T13: 0 | U13: 0 | V13: 0 | W13: 0 | X13: 0 | Y13: 0 | Z13: 0 | AA13: 0 | AB13: 0 | AC13: 0 | AD13: 0 | AE13: 0 | AF13: 0 | AG13: 0 | AH13: 0
A14: M-INCOME - Income Statement - M-INCOME - MTD-NET | B14: M-INCOME | C14: Income Statement | D14: M-INCOME | E14: QRT-INC | F14: Year | G14: 01/11/24..30/11/24 | H14: =TRUE() -> TRUE | R14: F3 | S14: NET INCOME | T14: 149167.99 | U14: 178567.11 | V14: 210869.19 | W14: 0 | X14: 149282.27 | Y14: 0 | Z14: 0 | AA14: 0 | AB14: 0 | AC14: 0 | AD14: 0 | AE14: 0 | AF14: 0 | AG14: 0 | AH14: 0
A15: M-INCOME - Income Statement - M-INCOME - MTD-NET | B15: M-INCOME | C15: Income Statement | D15: M-INCOME | E15: QRT-INC | F15: Year | G15: 01/11/24..30/11/24 | H15: =TRUE() -> TRUE | R15: S2 | T15: 0 | U15: 0 | V15: 0 | W15: 0 | X15: 0 | Y15: 0 | Z15: 0 | AA15: 0 | AB15: 0 | AC15: 0 | AD15: 0 | AE15: 0 | AF15: 0 | AG15: 0 | AH15: 0
A16: M-INCOME - Income Statement - M-INCOME - MTD-NET | B16: M-INCOME | C16: Income Statement | D16: M-INCOME | E16: QRT-INC | F16: Year | G16: 01/11/24..30/11/24 | H16: =TRUE() -> TRUE | R16: L31 | S16: Loan Impairment | T16: 17627.69 | U16: 19020.88 | V16: 32551.74 | W16: 0 | X16: 17627.69 | Y16: 0 | Z16: 0 | AA16: 0 | AB16: 0 | AC16: 0 | AD16: 0 | AE16: 0 | AF16: 0 | AG16: 0 | AH16: 0
A17: M-INCOME - Income Statement - M-INCOME - MTD-NET | B17: M-INCOME | C17: Income Statement | D17: M-INCOME | E17: QRT-INC | F17: Year | G17: 01/11/24..30/11/24 | H17: =TRUE() -> TRUE | R17: L32 | S17: Third Party Charges | T17: 3187.61 | U17: 3178.77 | V17: 3999.74 | W17: 0 | X17: 3175.3 | Y17: 0 | Z17: 0 | AA17: 0 | AB17: 0 | AC17: 0 | AD17: 0 | AE17: 0 | AF17: 0 | AG17: 0 | AH17: 0
A18: M-INCOME - Income Statement - M-INCOME - MTD-NET | B18: M-INCOME | C18: Income Statement | D18: M-INCOME | E18: QRT-INC | F18: Year | G18: 01/11/24..30/11/24 | H18: =TRUE() -> TRUE | R18: F4 | S18: TOTAL INDIRECT COSTS | T18: 20815.3 | U18: 22199.65 | V18: 36551.48 | W18: 0 | X18: 20802.99 | Y18: 0 | Z18: 0 | AA18: 0 | AB18: 0 | AC18: 0 | AD18: 0 | AE18: 0 | AF18: 0 | AG18: 0 | AH18: 0
A19: M-INCOME - Income Statement - M-INCOME - MTD-NET | B19: M-INCOME | C19: Income Statement | D19: M-INCOME | E19: QRT-INC | F19: Year | G19: 01/11/24..30/11/24 | H19: =TRUE() -> TRUE | R19: S3 | T19: 0 | U19: 0 | V19: 0 | W19: 0 | X19: 0 | Y19: 0 | Z19: 0 | AA19: 0 | AB19: 0 | AC19: 0 | AD19: 0 | AE19: 0 | AF19: 0 | AG19: 0 | AH19: 0
A20: M-INCOME - Income Statement - M-INCOME - MTD-NET | B20: M-INCOME | C20: Income Statement | D20: M-INCOME | E20: QRT-INC | F20: Year | G20: 01/11/24..30/11/24 | H20: =TRUE() -> TRUE | R20: F5 | S20: GROSS MARGINS | T20: 128352.69 | U20: 156367.46 | V20: 174317.71 | W20: 0 | X20: 128479.28 | Y20: 0 | Z20: 0 | AA20: 0 | AB20: 0 | AC20: 0 | AD20: 0 | AE20: 0 | AF20: 0 | AG20: 0 | AH20: 0
A21: M-INCOME - Income Statement - M-INCOME - MTD-NET | B21: M-INCOME | C21: Income Statement | D21: M-INCOME | E21: QRT-INC | F21: Year | G21: 01/11/24..30/11/24 | H21: =TRUE() -> TRUE | R21: S4 | T21: 0 | U21: 0 | V21: 0 | W21: 0 | X21: 0 | Y21: 0 | Z21: 0 | AA21: 0 | AB21: 0 | AC21: 0 | AD21: 0 | AE21: 0 | AF21: 0 | AG21: 0 | AH21: 0
A22: M-INCOME - Income Statement - M-INCOME - MTD-NET | B22: M-INCOME | C22: Income Statement | D22: M-INCOME | E22: QRT-INC | F22: Year | G22: 01/11/24..30/11/24 | H22: =TRUE() -> TRUE | R22: L41 | S22: Sales & Marketing | T22: 47535.44 | U22: 65341.06 | V22: 51643.32 | W22: 0 | X22: 46181.18 | Y22: 0 | Z22: 0 | AA22: 0 | AB22: 0 | AC22: 0 | AD22: 0 | AE22: 0 | AF22: 0 | AG22: 0 | AH22: 0
A23: M-INCOME - Income Statement - M-INCOME - MTD-NET | B23: M-INCOME | C23: Income Statement | D23: M-INCOME | E23: QRT-INC | F23: Year | G23: 01/11/24..30/11/24 | H23: =TRUE() -> TRUE | R23: L42 | S23: General & Adminisrative Expenses | T23: 275097.34 | U23: 320734.51 | V23: 313842.16 | W23: 0 | X23: 277398.1 | Y23: 0 | Z23: 0 | AA23: 0 | AB23: 0 | AC23: 0 | AD23: 0 | AE23: 0 | AF23: 0 | AG23: 0 | AH23: 0
A24: M-INCOME - Income Statement - M-INCOME - MTD-NET | B24: M-INCOME | C24: Income Statement | D24: M-INCOME | E24: QRT-INC | F24: Year | G24: 01/11/24..30/11/24 | H24: =TRUE() -> TRUE | R24: S5 | S24: Interco Purchases | T24: 26141.1 | U24: 33892.15 | V24: 43.82 | W24: 0 | X24: 0 | Y24: 0 | Z24: 0 | AA24: 0 | AB24: 0 | AC24: 0 | AD24: 0 | AE24: 0 | AF24: 0 | AG24: 0 | AH24: 0
A25: M-INCOME - Income Statement - M-INCOME - MTD-NET | B25: M-INCOME | C25: Income Statement | D25: M-INCOME | E25: QRT-INC | F25: Year | G25: 01/11/24..30/11/24 | H25: =TRUE() -> TRUE | R25: F6 | S25: EBITDAM | T25: -168138.99 | U25: -195815.96 | V25: -191211.59 | W25: 0 | X25: -195100 | Y25: 0 | Z25: 0 | AA25: 0 | AB25: 0 | AC25: 0 | AD25: 0 | AE25: 0 | AF25: 0 | AG25: 0 | AH25: 0
A26: M-INCOME - Income Statement - M-INCOME - MTD-NET | B26: M-INCOME | C26: Income Statement | D26: M-INCOME | E26: QRT-INC | F26: Year | G26: 01/11/24..30/11/24 | H26: =TRUE() -> TRUE | R26: S5 | T26: 0 | U26: 0 | V26: 0 | W26: 0 | X26: 0 | Y26: 0 | Z26: 0 | AA26: 0 | AB26: 0 | AC26: 0 | AD26: 0 | AE26: 0 | AF26: 0 | AG26: 0 | AH26: 0
A27: M-INCOME - Income Statement - M-INCOME - MTD-NET | B27: M-INCOME | C27: Income Statement | D27: M-INCOME | E27: QRT-INC | F27: Year | G27: 01/11/24..30/11/24 | H27: =TRUE() -> TRUE | R27: L43 | S27: Head Office | T27: 0 | U27: 0 | V27: 0 | W27: 0 | X27: 0 | Y27: 0 | Z27: 0 | AA27: 0 | AB27: 0 | AC27: 0 | AD27: 0 | AE27: 0 | AF27: 0 | AG27: 0 | AH27: 0
A28: M-INCOME - Income Statement - M-INCOME - MTD-NET | B28: M-INCOME | C28: Income Statement | D28: M-INCOME | E28: QRT-INC | F28: Year | G28: 01/11/24..30/11/24 | H28: =TRUE() -> TRUE | R28: F7 | S28: EBITDA | T28: -168138.99 | U28: -195815.96 | V28: -191211.59 | W28: 0 | X28: -195100 | Y28: 0 | Z28: 0 | AA28: 0 | AB28: 0 | AC28: 0 | AD28: 0 | AE28: 0 | AF28: 0 | AG28: 0 | AH28: 0
A29: M-INCOME - Income Statement - M-INCOME - MTD-NET | B29: M-INCOME | C29: Income Statement | D29: M-INCOME | E29: QRT-INC | F29: Year | G29: 01/11/24..30/11/24 | H29: =TRUE() -> TRUE | R29: S | T29: 0 | U29: 0 | V29: 0 | W29: 0 | X29: 0 | Y29: 0 | Z29: 0 | AA29: 0 | AB29: 0 | AC29: 0 | AD29: 0 | AE29: 0 | AF29: 0 | AG29: 0 | AH29: 0
A30: M-INCOME - Income Statement - M-INCOME - MTD-NET | B30: M-INCOME | C30: Income Statement | D30: M-INCOME | E30: QRT-INC | F30: Year | G30: 01/11/24..30/11/24 | H30: =TRUE() -> TRUE | R30: L51 | S30: Depreciations | T30: 3175.8 | U30: 3349.59 | V30: 3509.08 | W30: 0 | X30: 3172.4 | Y30: 0 | Z30: 0 | AA30: 0 | AB30: 0 | AC30: 0 | AD30: 0 | AE30: 0 | AF30: 0 | AG30: 0 | AH30: 0
A31: M-INCOME - Income Statement - M-INCOME - MTD-NET | B31: M-INCOME | C31: Income Statement | D31: M-INCOME | E31: QRT-INC | F31: Year | G31: 01/11/24..30/11/24 | H31: =TRUE() -> TRUE | R31: L52 | S31: Ammortization | T31: 60503.02 | U31: 60503.01 | V31: 28194.69 | W31: 0 | X31: 60503.02 | Y31: 0 | Z31: 0 | AA31: 0 | AB31: 0 | AC31: 0 | AD31: 0 | AE31: 0 | AF31: 0 | AG31: 0 | AH31: 0
A32: M-INCOME - Income Statement - M-INCOME - MTD-NET | B32: M-INCOME | C32: Income Statement | D32: M-INCOME | E32: QRT-INC | F32: Year | G32: 01/11/24..30/11/24 | H32: =TRUE() -> TRUE | R32: L53 | S32: Finance Cost | T32: 27960.13 | U32: 22176.97 | V32: 16806.58 | W32: 0 | X32: 27960.13 | Y32: 0 | Z32: 0 | AA32: 0 | AB32: 0 | AC32: 0 | AD32: 0 | AE32: 0 | AF32: 0 | AG32: 0 | AH32: 0
A33: M-INCOME - Income Statement - M-INCOME - MTD-NET | B33: M-INCOME | C33: Income Statement | D33: M-INCOME | E33: QRT-INC | F33: Year | G33: 01/11/24..30/11/24 | H33: =TRUE() -> TRUE | R33: L54 | S33: Other Income & Expenses | T33: 5384 | U33: 11675.6 | V33: 8716.94 | W33: 0 | X33: 4684.17 | Y33: 0 | Z33: 0 | AA33: 0 | AB33: 0 | AC33: 0 | AD33: 0 | AE33: 0 | AF33: 0 | AG33: 0 | AH33: 0
A34: M-INCOME - Income Statement - M-INCOME - MTD-NET | B34: M-INCOME | C34: Income Statement | D34: M-INCOME | E34: QRT-INC | F34: Year | G34: 01/11/24..30/11/24 | H34: =TRUE() -> TRUE | S34: EBT | T34: -265161.94 | U34: -293521.13 | V34: -248438.88 | W34: 0 | X34: -291419.72 | Y34: 0 | Z34: 0 | AA34: 0 | AB34: 0 | AC34: 0 | AD34: 0 | AE34: 0 | AF34: 0 | AG34: 0 | AH34: 0

Sheet BS (MoM)
A1: Financial Report | B1: Name | C1: Description | D1: Row Definition | E1: Column Definition | F1: View by | G1: Date Filter | H1: Show All Lines | I1: Product Filter | J1: Department Filter | K1: Business-Unit Filter | L1: Cost-center Filter | M1: Cost Center Filter | N1: Cost Object Filter | O1: Cash Flow Filter | P1: G/L Budget Filter | Q1: Cost Budget Filter | R1: Row No. | S1: Description1 | T1: January | U1: February | V1: March | W1: April | X1: May | Y1: June | Z1: July | AA1: August | AB1: September | AC1: October | AD1: November | AE1: December | AF1: Total | AH1: 1
A2: M-BALANCE - Balance Sheet - M-BALANCE - QRT-BAL | B2: M-BALANCE | C2: Balance Sheet | D2: M-BALANCE | E2: MTD-BAL | F2: Year | G2: 01/11/24..30/11/24 | H2: =FALSE() -> FALSE | S2: Assets | T2: 0 | U2: 0 | V2: 0 | W2: 0 | X2: 0 | Y2: 0 | Z2: 0 | AA2: 0 | AB2: 0 | AC2: 0 | AD2: 0 | AE2: 0 | AF2: 0 | AG2: 0 | AH2: 0
A3: M-BALANCE - Balance Sheet - M-BALANCE - QRT-BAL | B3: M-BALANCE | C3: Balance Sheet | D3: M-BALANCE | E3: MTD-BAL | F3: Year | G3: 01/11/24..30/11/24 | H3: =FALSE() -> FALSE | R3: 010 | S3: Current Assets | T3: 0 | U3: 0 | V3: 0 | W3: 0 | X3: 0 | Y3: 0 | Z3: 0 | AA3: 0 | AB3: 0 | AC3: 0 | AD3: 0 | AE3: 0 | AF3: 0 | AG3: 0 | AH3: 0
A4: M-BALANCE - Balance Sheet - M-BALANCE - QRT-BAL | B4: M-BALANCE | C4: Balance Sheet | D4: M-BALANCE | E4: MTD-BAL | F4: Year | G4: 01/11/24..30/11/24 | H4: =FALSE() -> FALSE | R4: 020 | S4: Cash & Cash Equivalents | T4: 794294.22 | U4: 760065.78 | V4: 689215.17 | W4: 828564.78 | X4: 888683.76 | Y4: 653154.78 | Z4: 511499.83 | AA4: 445399.48 | AB4: 537995.66 | AC4: 0 | AD4: 0 | AE4: 0 | AF4: 794226 | AG4: 0 | AH4: 0
A5: M-BALANCE - Balance Sheet - M-BALANCE - QRT-BAL | B5: M-BALANCE | C5: Balance Sheet | D5: M-BALANCE | E5: MTD-BAL | F5: Year | G5: 01/11/24..30/11/24 | H5: =FALSE() -> FALSE | R5: 030 | S5: Net Loan Receivable | T5: 1012498.9 | U5: 1178406.4 | V5: 1172488.3 | W5: 1229612.8 | X5: 1285940.7 | Y5: 1368511.6 | Z5: 1435517.8 | AA5: 1548630.6 | AB5: 1645999.1 | AC5: 0 | AD5: 0 | AE5: 0 | AF5: 1010459 | AG5: 0 | AH5: 0
A6: M-BALANCE - Balance Sheet - M-BALANCE - QRT-BAL | B6: M-BALANCE | C6: Balance Sheet | D6: M-BALANCE | E6: MTD-BAL | F6: Year | G6: 01/11/24..30/11/24 | H6: =FALSE() -> FALSE | R6: 040 | S6: Interco-Receivable | T6: 982416.07 | U6: 1106888 | V6: 1146508.9 | W6: 1222569.7 | X6: 1301171.1 | Y6: 1324774.1 | Z6: 1515179.9 | AA6: 1566113 | AB6: 1623863.2 | AC6: 0 | AD6: 0 | AE6: 0 | AF6: 984666 | AG6: 0 | AH6: 0
A7: M-BALANCE - Balance Sheet - M-BALANCE - QRT-BAL | B7: M-BALANCE | C7: Balance Sheet | D7: M-BALANCE | E7: MTD-BAL | F7: Year | G7: 01/11/24..30/11/24 | H7: =FALSE() -> FALSE | R7: 050 | S7: Other Current Assets | T7: 250633.59 | U7: 241222.22 | V7: 226124.11 | W7: 222716.97 | X7: 200695.6 | Y7: 179384.61 | Z7: 176608.82 | AA7: 175775.56 | AB7: 181855.23 | AC7: 0 | AD7: 0 | AE7: 0 | AF7: 243756 | AG7: 0 | AH7: 0
A8: M-BALANCE - Balance Sheet - M-BALANCE - QRT-BAL | B8: M-BALANCE | C8: Balance Sheet | D8: M-BALANCE | E8: MTD-BAL | F8: Year | G8: 01/11/24..30/11/24 | H8: =FALSE() -> FALSE | R8: 099 | S8: Total Current Assets | T8: 3039842.8 | U8: 3286582.3 | V8: 3234336.5 | W8: 3503464.3 | X8: 3676491.1 | Y8: 3525825 | Z8: 3638806.3 | AA8: 3735918.7 | AB8: 3989713.2 | AC8: 0 | AD8: 0 | AE8: 0 | AF8: 3033107 | AG8: 0 | AH8: 0
A9: M-BALANCE - Balance Sheet - M-BALANCE - QRT-BAL | B9: M-BALANCE | C9: Balance Sheet | D9: M-BALANCE | E9: MTD-BAL | F9: Year | G9: 01/11/24..30/11/24 | H9: =FALSE() -> FALSE | T9: 0 | U9: 0 | V9: 0 | W9: 0 | X9: 0 | Y9: 0 | Z9: 0 | AA9: 0 | AB9: 0 | AC9: 0 | AD9: 0 | AE9: 0 | AF9: 0 | AG9: 0 | AH9: 0
A10: M-BALANCE - Balance Sheet - M-BALANCE - QRT-BAL | B10: M-BALANCE | C10: Balance Sheet | D10: M-BALANCE | E10: MTD-BAL | F10: Year | G10: 01/11/24..30/11/24 | H10: =FALSE() -> FALSE | R10: 100 | S10: Non-Current Assets | T10: 0 | U10: 0 | V10: 0 | W10: 0 | X10: 0 | Y10: 0 | Z10: 0 | AA10: 0 | AB10: 0 | AC10: 0 | AD10: 0 | AE10: 0 | AF10: 0 | AG10: 0 | AH10: 0
A11: M-BALANCE - Balance Sheet - M-BALANCE - QRT-BAL | B11: M-BALANCE | C11: Balance Sheet | D11: M-BALANCE | E11: MTD-BAL | F11: Year | G11: 01/11/24..30/11/24 | H11: =FALSE() -> FALSE | R11: 110 | S11: Gross Fixed Assets | T11: 36694.76 | U11: 41233.54 | V11: 45208.34 | W11: 45728.89 | X11: 45728.89 | Y11: 46249.44 | Z11: 48005.79 | AA11: 48005.79 | AB11: 50070.5 | AC11: 0 | AD11: 0 | AE11: 0 | AF11: 36175 | AG11: 0 | AH11: 0
A12: M-BALANCE - Balance Sheet - M-BALANCE - QRT-BAL | B12: M-BALANCE | C12: Balance Sheet | D12: M-BALANCE | E12: MTD-BAL | F12: Year | G12: 01/11/24..30/11/24 | H12: =FALSE() -> FALSE | R12: 111 | S12: Acc. Depreciation | T12: -20655.06 | U12: -21744.16 | V12: -22835.56 | W12: -23934.75 | X12: -25025.55 | Y12: -26189.93 | Z12: -27342.11 | AA12: -28494.85 | AB12: -29699.01 | AC12: 0 | AD12: 0 | AE12: 0 | AF12: -20450 | AG12: 0 | AH12: 0
A13: M-BALANCE - Balance Sheet - M-BALANCE - QRT-BAL | B13: M-BALANCE | C13: Balance Sheet | D13: M-BALANCE | E13: MTD-BAL | F13: Year | G13: 01/11/24..30/11/24 | H13: =FALSE() -> FALSE | R13: 120 | S13: Gross Intangible Assets | T13: 740386.28 | U13: 740386.28 | V13: 740386.28 | W13: 740386.28 | X13: 740386.28 | Y13: 740386.28 | Z13: 740386.28 | AA13: 740386.28 | AB13: 740386.28 | AC13: 0 | AD13: 0 | AE13: 0 | AF13: 740386 | AG13: 0 | AH13: 0
A14: M-BALANCE - Balance Sheet - M-BALANCE - QRT-BAL | B14: M-BALANCE | C14: Balance Sheet | D14: M-BALANCE | E14: MTD-BAL | F14: Year | G14: 01/11/24..30/11/24 | H14: =FALSE() -> FALSE | R14: 121 | S14: Acc. Ammortization | T14: -606461.87 | U14: -626639.84 | V14: -646808.06 | W14: -666976.28 | X14: -687144.5 | Y14: -707312.72 | Z14: -727478.37 | AA14: -735219.71 | AB14: -735507.41 | AC14: 0 | AD14: 0 | AE14: 0 | AF14: -586586 | AG14: 0 | AH14: 0
A15: M-BALANCE - Balance Sheet - M-BALANCE - QRT-BAL | B15: M-BALANCE | C15: Balance Sheet | D15: M-BALANCE | E15: MTD-BAL | F15: Year | G15: 01/11/24..30/11/24 | H15: =FALSE() -> FALSE | R15: 130 | S15: Interco-Receivable Long Term | T15: 2127702.6 | U15: 2127702.6 | V15: 2127702.6 | W15: 2127702.6 | X15: 2127702.6 | Y15: 2127702.6 | Z15: 2127702.6 | AA15: 2127702.6 | AB15: 2127702.6 | AC15: 0 | AD15: 0 | AE15: 0 | AF15: 2127703 | AG15: 0 | AH15: 0
A16: M-BALANCE - Balance Sheet - M-BALANCE - QRT-BAL | B16: M-BALANCE | C16: Balance Sheet | D16: M-BALANCE | E16: MTD-BAL | F16: Year | G16: 01/11/24..30/11/24 | H16: =FALSE() -> FALSE | R16: 140 | S16: Other Long Term Assets | T16: 19380.33 | U16: 19380.33 | V16: 19380.33 | W16: 19380.33 | X16: 19380.33 | Y16: 19380.33 | Z16: 19380.33 | AA16: 19380.33 | AB16: 19380.33 | AC16: 0 | AD16: 0 | AE16: 0 | AF16: 19380 | AG16: 0 | AH16: 0
A17: M-BALANCE - Balance Sheet - M-BALANCE - QRT-BAL | B17: M-BALANCE | C17: Balance Sheet | D17: M-BALANCE | E17: MTD-BAL | F17: Year | G17: 01/11/24..30/11/24 | H17: =FALSE() -> FALSE | R17: 199 | S17: Total Non-Current Assets | T17: 2297047.1 | U17: 2280318.8 | V17: 2263034 | W17: 2242287.1 | X17: 2221028.1 | Y17: 2200216 | Z17: 2180654.5 | AA17: 2171760.5 | AB17: 2172333.3 | AC17: 0 | AD17: 0 | AE17: 0 | AF17: 2316608 | AG17: 0 | AH17: 0
A18: M-BALANCE - Balance Sheet - M-BALANCE - QRT-BAL | B18: M-BALANCE | C18: Balance Sheet | D18: M-BALANCE | E18: MTD-BAL | F18: Year | G18: 01/11/24..30/11/24 | H18: =FALSE() -> FALSE | T18: 0 | U18: 0 | V18: 0 | W18: 0 | X18: 0 | Y18: 0 | Z18: 0 | AA18: 0 | AB18: 0 | AC18: 0 | AD18: 0 | AE18: 0 | AF18: 0 | AG18: 0 | AH18: 0
A19: M-BALANCE - Balance Sheet - M-BALANCE - QRT-BAL | B19: M-BALANCE | C19: Balance Sheet | D19: M-BALANCE | E19: MTD-BAL | F19: Year | G19: 01/11/24..30/11/24 | H19: =FALSE() -> FALSE | R19: F1 | S19: Total Assets | T19: 5336889.8 | U19: 5566901.1 | V19: 5497370.5 | W19: 5745751.4 | X19: 5897519.2 | Y19: 5726041 | Z19: 5819460.8 | AA19: 5907679.2 | AB19: 6162046.5 | AC19: 0 | AD19: 0 | AE19: 0 | AF19: 5349715 | AG19: 0 | AH19: 0
A20: M-BALANCE - Balance Sheet - M-BALANCE - QRT-BAL | B20: M-BALANCE | C20: Balance Sheet | D20: M-BALANCE | E20: MTD-BAL | F20: Year | G20: 01/11/24..30/11/24 | H20: =FALSE() -> FALSE | T20: 0 | U20: 0 | V20: 0 | W20: 0 | X20: 0 | Y20: 0 | Z20: 0 | AA20: 0 | AB20: 0 | AC20: 0 | AD20: 0 | AE20: 0 | AF20: 0 | AG20: 0 | AH20: 0
A21: M-BALANCE - Balance Sheet - M-BALANCE - QRT-BAL | B21: M-BALANCE | C21: Balance Sheet | D21: M-BALANCE | E21: MTD-BAL | F21: Year | G21: 01/11/24..30/11/24 | H21: =FALSE() -> FALSE | S21: Liabilities | T21: 0 | U21: 0 | V21: 0 | W21: 0 | X21: 0 | Y21: 0 | Z21: 0 | AA21: 0 | AB21: 0 | AC21: 0 | AD21: 0 | AE21: 0 | AF21: 0 | AG21: 0 | AH21: 0
A22: M-BALANCE - Balance Sheet - M-BALANCE - QRT-BAL | B22: M-BALANCE | C22: Balance Sheet | D22: M-BALANCE | E22: MTD-BAL | F22: Year | G22: 01/11/24..30/11/24 | H22: =FALSE() -> FALSE | R22: 200 | S22: Current Liabilities | T22: 0 | U22: 0 | V22: 0 | W22: 0 | X22: 0 | Y22: 0 | Z22: 0 | AA22: 0 | AB22: 0 | AC22: 0 | AD22: 0 | AE22: 0 | AF22: 0 | AG22: 0 | AH22: 0
A23: M-BALANCE - Balance Sheet - M-BALANCE - QRT-BAL | B23: M-BALANCE | C23: Balance Sheet | D23: M-BALANCE | E23: MTD-BAL | F23: Year | G23: 01/11/24..30/11/24 | H23: =FALSE() -> FALSE | R23: 210 | S23: Accounts Payable | T23: 211779.54 | U23: 264518.05 | V23: 232743.31 | W23: 238795.28 | X23: 254436.56 | Y23: 226911.26 | Z23: 223287.34 | AA23: 251091.45 | AB23: 263042.26 | AC23: 0 | AD23: 0 | AE23: 0 | AF23: 203124 | AG23: 0 | AH23: 0
A24: M-BALANCE - Balance Sheet - M-BALANCE - QRT-BAL | B24: M-BALANCE | C24: Balance Sheet | D24: M-BALANCE | E24: MTD-BAL | F24: Year | G24: 01/11/24..30/11/24 | H24: =FALSE() -> FALSE | R24: 220 | S24: Intercompany Payable | T24: 837980.14 | U24: 877292.44 | V24: 889454.08 | W24: 978004.81 | X24: 1029008.8 | Y24: 1048129.6 | Z24: 1147017.8 | AA24: 1201727.5 | AB24: 1275262.4 | AC24: 0 | AD24: 0 | AE24: 0 | AF24: 825563 | AG24: 0 | AH24: 0
A25: M-BALANCE - Balance Sheet - M-BALANCE - QRT-BAL | B25: M-BALANCE | C25: Balance Sheet | D25: M-BALANCE | E25: MTD-BAL | F25: Year | G25: 01/11/24..30/11/24 | H25: =FALSE() -> FALSE | R25: 230 | S25: Overdraft / Revolver | T25: 38451.08 | U25: 36766.55 | V25: 39566.48 | W25: 50222.48 | X25: 62311.74 | Y25: 53316.19 | Z25: 47805.79 | AA25: 47832.43 | AB25: 41005.26 | AC25: 0 | AD25: 0 | AE25: 0 | AF25: 38451 | AG25: 0 | AH25: 0
A26: M-BALANCE - Balance Sheet - M-BALANCE - QRT-BAL | B26: M-BALANCE | C26: Balance Sheet | D26: M-BALANCE | E26: MTD-BAL | F26: Year | G26: 01/11/24..30/11/24 | H26: =FALSE() -> FALSE | R26: 240 | S26: Customer Deposits | T26: 59745.29 | U26: 55499.67 | V26: 44520.22 | W26: 40256.77 | X26: 40358.9 | Y26: 31460.67 | Z26: 27121.27 | AA26: 26818.42 | AB26: 24579.65 | AC26: 0 | AD26: 0 | AE26: 0 | AF26: 53625 | AG26: 0 | AH26: 0
A27: M-BALANCE - Balance Sheet - M-BALANCE - QRT-BAL | B27: M-BALANCE | C27: Balance Sheet | D27: M-BALANCE | E27: MTD-BAL | F27: Year | G27: 01/11/24..30/11/24 | H27: =FALSE() -> FALSE | R27: 250 | S27: Accrued Expenses | T27: 163267.9 | U27: 167894.01 | V27: 173427.15 | W27: 170432.59 | X27: 160015.16 | Y27: 142263.18 | Z27: 127670.45 | AA27: 114885.19 | AB27: 119738.96 | AC27: 0 | AD27: 0 | AE27: 0 | AF27: 158726 | AG27: 0 | AH27: 0
A28: M-BALANCE - Balance Sheet - M-BALANCE - QRT-BAL | B28: M-BALANCE | C28: Balance Sheet | D28: M-BALANCE | E28: MTD-BAL | F28: Year | G28: 01/11/24..30/11/24 | H28: =FALSE() -> FALSE | R28: 290 | S28: Total Current Liabilities | T28: 1311223.9 | U28: 1401970.7 | V28: 1379711.2 | W28: 1477711.9 | X28: 1546131.1 | Y28: 1502080.9 | Z28: 1572902.6 | AA28: 1642355 | AB28: 1723628.5 | AC28: 0 | AD28: 0 | AE28: 0 | AF28: 1279490 | AG28: 0 | AH28: 0
A29: M-BALANCE - Balance Sheet - M-BALANCE - QRT-BAL | B29: M-BALANCE | C29: Balance Sheet | D29: M-BALANCE | E29: MTD-BAL | F29: Year | G29: 01/11/24..30/11/24 | H29: =FALSE() -> FALSE | T29: 0 | U29: 0 | V29: 0 | W29: 0 | X29: 0 | Y29: 0 | Z29: 0 | AA29: 0 | AB29: 0 | AC29: 0 | AD29: 0 | AE29: 0 | AF29: 0 | AG29: 0 | AH29: 0
A30: M-BALANCE - Balance Sheet - M-BALANCE - QRT-BAL | B30: M-BALANCE | C30: Balance Sheet | D30: M-BALANCE | E30: MTD-BAL | F30: Year | G30: 01/11/24..30/11/24 | H30: =FALSE() -> FALSE | R30: 300 | S30: Non-Current Liabilities | T30: 0 | U30: 0 | V30: 0 | W30: 0 | X30: 0 | Y30: 0 | Z30: 0 | AA30: 0 | AB30: 0 | AC30: 0 | AD30: 0 | AE30: 0 | AF30: 0 | AG30: 0 | AH30: 0
A31: M-BALANCE - Balance Sheet - M-BALANCE - QRT-BAL | B31: M-BALANCE | C31: Balance Sheet | D31: M-BALANCE | E31: MTD-BAL | F31: Year | G31: 01/11/24..30/11/24 | H31: =FALSE() -> FALSE | R31: 310 | S31: LT Intercompany Loan | T31: 2317595 | U31: 2352226.5 | V31: 2362682 | W31: 2362682 | X31: 2392698.7 | Y31: 2362681 | Z31: 2475151.4 | AA31: 2475151.4 | AB31: 2475151.4 | AC31: 0 | AD31: 0 | AE31: 0 | AF31: 2317595 | AG31: 0 | AH31: 0
A32: M-BALANCE - Balance Sheet - M-BALANCE - QRT-BAL | B32: M-BALANCE | C32: Balance Sheet | D32: M-BALANCE | E32: MTD-BAL | F32: Year | G32: 01/11/24..30/11/24 | H32: =FALSE() -> FALSE | R32: 320 | S32: LT Debt | T32: 1681108.4 | U32: 1881589.2 | V32: 1901589.2 | W32: 2151589.2 | X32: 2301667.3 | Y32: 2301667.3 | Z32: 2301667.3 | AA32: 2402200.4 | AB32: 2652200.4 | AC32: 0 | AD32: 0 | AE32: 0 | AF32: 921108 | AG32: 0 | AH32: 0
A33: M-BALANCE - Balance Sheet - M-BALANCE - QRT-BAL | B33: M-BALANCE | C33: Balance Sheet | D33: M-BALANCE | E33: MTD-BAL | F33: Year | G33: 01/11/24..30/11/24 | H33: =FALSE() -> FALSE | R33: 390 | S33: Total Non-Current Liabilities | T33: 3998703.5 | U33: 4233815.6 | V33: 4264271.2 | W33: 4514271.2 | X33: 4694365.9 | Y33: 4664348.3 | Z33: 4776818.7 | AA33: 4877351.8 | AB33: 5127351.8 | AC33: 0 | AD33: 0 | AE33: 0 | AF33: 3238704 | AG33: 0 | AH33: 0
A34: M-BALANCE - Balance Sheet - M-BALANCE - QRT-BAL | B34: M-BALANCE | C34: Balance Sheet | D34: M-BALANCE | E34: MTD-BAL | F34: Year | G34: 01/11/24..30/11/24 | H34: =FALSE() -> FALSE | T34: 0 | U34: 0 | V34: 0 | W34: 0 | X34: 0 | Y34: 0 | Z34: 0 | AA34: 0 | AB34: 0 | AC34: 0 | AD34: 0 | AE34: 0 | AF34: 0 | AG34: 0 | AH34: 0
A35: M-BALANCE - Balance Sheet - M-BALANCE - QRT-BAL | B35: M-BALANCE | C35: Balance Sheet | D35: M-BALANCE | E35: MTD-BAL | F35: Year | G35: 01/11/24..30/11/24 | H35: =FALSE() -> FALSE | R35: 400 | S35: Equity | T35: 0 | U35: 0 | V35: 0 | W35: 0 | X35: 0 | Y35: 0 | Z35: 0 | AA35: 0 | AB35: 0 | AC35: 0 | AD35: 0 | AE35: 0 | AF35: 0 | AG35: 0 | AH35: 0
A36: M-BALANCE - Balance Sheet - M-BALANCE - QRT-BAL | B36: M-BALANCE | C36: Balance Sheet | D36: M-BALANCE | E36: MTD-BAL | F36: Year | G36: 01/11/24..30/11/24 | H36: =FALSE() -> FALSE | R36: 410 | S36: Share Capital | T36: 3984299.9 | U36: 3984299.9 | V36: 3984299.9 | W36: 3984299.9 | X36: 3984334.9 | Y36: 3984334.9 | Z36: 3984334.9 | AA36: 3984334.9 | AB36: 3984334.9 | AC36: 0 | AD36: 0 | AE36: 0 | AF36: 3984300 | AG36: 0 | AH36: 0
A37: M-BALANCE - Balance Sheet - M-BALANCE - QRT-BAL | B37: M-BALANCE | C37: Balance Sheet | D37: M-BALANCE | E37: MTD-BAL | F37: Year | G37: 01/11/24..30/11/24 | H37: =FALSE() -> FALSE | R37: 420 | S37: Parent Company Investment in Subsidiary | T37: -8519.07 | U37: -8519.07 | V37: -8519.07 | W37: -8519.07 | X37: -8519.07 | Y37: -8519.07 | Z37: -8519.07 | AA37: -8519.07 | AB37: -8519.07 | AC37: 0 | AD37: 0 | AE37: 0 | AF37: -8519 | AG37: 0 | AH37: 0
A38: M-BALANCE - Balance Sheet - M-BALANCE - QRT-BAL | B38: M-BALANCE | C38: Balance Sheet | D38: M-BALANCE | E38: MTD-BAL | F38: Year | G38: 01/11/24..30/11/24 | H38: =FALSE() -> FALSE | R38: 430 | S38: PY Retained Earnings | T38: -891053.5 | U38: -891053.5 | V38: -891053.5 | W38: -891053.5 | X38: -891053.5 | Y38: -891053.5 | Z38: -891053.5 | AA38: -891053.5 | AB38: -891053.5 | AC38: 0 | AD38: 0 | AE38: 0 | AF38: -891054 | AG38: 0 | AH38: 0
A39: M-BALANCE - Balance Sheet - M-BALANCE - QRT-BAL | B39: M-BALANCE | C39: Balance Sheet | D39: M-BALANCE | E39: MTD-BAL | F39: Year | G39: 01/11/24..30/11/24 | H39: =FALSE() -> FALSE | R39: 440 | S39: CY Retained Earnings | T39: -2955381.9 | U39: -3051196.8 | V39: -3128884.7 | W39: -3228485.1 | X39: -3325250.3 | Y39: -3422629.4 | Z39: -3512502 | AA39: -3594269.3 | AB39: -3671175.6 | AC39: 0 | AD39: 0 | AE39: 0 | AF39: -2921249 | AG39: 0 | AH39: 0
A40: M-BALANCE - Balance Sheet - M-BALANCE - QRT-BAL | B40: M-BALANCE | C40: Balance Sheet | D40: M-BALANCE | E40: MTD-BAL | F40: Year | G40: 01/11/24..30/11/24 | H40: =FALSE() -> FALSE | R40: 450 | S40: CY Foreign Currency Transalation | T40: -102383.09 | U40: -102415.76 | V40: -102454.64 | W40: -102473.99 | X40: -102489.89 | Y40: -102521.17 | Z40: -102520.84 | AA40: -102520.71 | AB40: -102520.58 | AC40: 0 | AD40: 0 | AE40: 0 | AF40: -102378 | AG40: 0 | AH40: 0
A41: M-BALANCE - Balance Sheet - M-BALANCE - QRT-BAL | B41: M-BALANCE | C41: Balance Sheet | D41: M-BALANCE | E41: MTD-BAL | F41: Year | G41: 01/11/24..30/11/24 | H41: =FALSE() -> FALSE | R41: 499 | S41: Total Equity | T41: 26962.39 | U41: -68885.25 | V41: -146611.99 | W41: -246231.79 | X41: -342977.81 | Y41: -440388.18 | Z41: -530260.51 | AA41: -612027.66 | AB41: -688933.85 | AC41: 0 | AD41: 0 | AE41: 0 | AF41: 61101 | AG41: 0 | AH41: 0
A42: M-BALANCE - Balance Sheet - M-BALANCE - QRT-BAL | B42: M-BALANCE | C42: Balance Sheet | D42: M-BALANCE | E42: MTD-BAL | F42: Year | G42: 01/11/24..30/11/24 | H42: =FALSE() -> FALSE | T42: 0 | U42: 0 | V42: 0 | W42: 0 | X42: 0 | Y42: 0 | Z42: 0 | AA42: 0 | AB42: 0 | AC42: 0 | AD42: 0 | AE42: 0 | AF42: 0 | AG42: 0 | AH42: 0
A43: M-BALANCE - Balance Sheet - M-BALANCE - QRT-BAL | B43: M-BALANCE | C43: Balance Sheet | D43: M-BALANCE | E43: MTD-BAL | F43: Year | G43: 01/11/24..30/11/24 | H43: =FALSE() -> FALSE | R43: F2 | S43: Total Equity and Liabilities | T43: 5336889.8 | U43: 5566901.1 | V43: 5497370.5 | W43: 5745751.4 | X43: 5897519.2 | Y43: 5726041 | Z43: 5819460.8 | AA43: 5907679.2 | AB43: 6162046.5 | AC43: 0 | AD43: 0 | AE43: 0 | AF43: 4579294 | AG43: 0 | AH43: 0
A44: M-BALANCE - Balance Sheet - M-BALANCE - QRT-BAL | B44: M-BALANCE | C44: Balance Sheet | D44: M-BALANCE | E44: MTD-BAL | F44: Year | G44: 01/11/24..30/11/24 | H44: =FALSE() -> FALSE | T44: 0 | U44: 0 | V44: 0 | W44: 0 | X44: 0 | Y44: 0 | Z44: 0 | AA44: 0 | AB44: 0 | AC44: 0 | AD44: 0 | AE44: 0 | AF44: 0 | AG44: 0 | AH44: 0
A45: M-BALANCE - Balance Sheet - M-BALANCE - QRT-BAL | B45: M-BALANCE | C45: Balance Sheet | D45: M-BALANCE | E45: MTD-BAL | F45: Year | G45: 01/11/24..30/11/24 | H45: =FALSE() -> FALSE | R45: 999 | S45: Check | T45: 0 | U45: 0 | V45: 0 | W45: 0 | X45: 0 | Y45: 0 | Z45: 0 | AA45: 0 | AB45: 0 | AC45: 0 | AD45: 0 | AE45: 0 | AF45: 770421 | AG45: 0 | AH45: 0
U48: =U39-T39 -> -95814.97 | V48: =V39-U39 -> -77687.86 | W48: =W39-V39 -> -99600.45 | X48: =X39-W39 -> -96765.16 | Y48: =Y39-X39 -> -97379.09 | Z48: =Z39-Y39 -> -89872.66 | AA48: =AA39-Z39 -> -81767.28
T49: -91323.78 | U49: -95814.97 | V49: -77687.86 | W49: -99600.45 | X49: -96765.16 | Y49: -97379.09 | Z49: -88940.6 | AA49: -83047.26
U50: =U48-IS_MOM!V34 -> -9170.17
T51: -2853637.2 | U51: -2854264.3 | V51: -2850988.4 | W51: -2851493.9 | X51: -2700522.8 | Y51: -2685606.7 | Z51: -3119426.6
T53: -65991.3 | U53: -70402.6 | V53: -79550.23 | W53: -80782.17 | X53: -82687.6 | Y53: -83390.67 | Z53: -76646.49
W55: =W32-X32 -> -150078.08
T57: =T51+T45 -> -2853637.2 | U57: =U51+U45 -> -2854264.3 | V57: =V51+V45 -> -2850988.4 | W57: =W51+W45 -> -2851493.9 | X57: =X51+X45 -> -2700522.8 | Y57: =Y51+Y45 -> -2685606.7 | Z57: =Z51+Z45 -> -3119426.6

Sheet IS_MOM
A1: Financial Report | B1: Name | C1: Description | D1: Row Definition | E1: Column Definition | F1: View by | G1: Date Filter | H1: Show All Lines | I1: Product Filter | J1: Department Filter | K1: Business-Unit Filter | L1: Column1 | M1: Cost-center Filter | N1: Cost Center Filter | O1: Cost Object Filter | P1: Cash Flow Filter | Q1: G/L Budget Filter | R1: Cost Budget Filter | S1: Row No. | T1: Description1 | U1: January | V1: February | W1: March | X1: April | Y1: May | Z1: June | AA1: July | AB1: August | AC1: September | AD1: October | AE1: November | AF1: December | AG1: Total | AI1: 1 | AJ1: 2
A2: M-INCOME - Income Statement - M-INCOME - BSUNIT-IS | B2: M-INCOME | C2: Income Statement | D2: M-INCOME | E2: MTD-NET | F2: Year | G2: 01/09/24..30/09/24 | H2: =TRUE() -> TRUE | U2: 0 | V2: 0 | W2: 0 | X2: 0 | Y2: 0 | Z2: 0 | AA2: 0 | AB2: 0 | AC2: 0 | AD2: 0 | AE2: 0 | AF2: 0 | AG2: 0 | AH2: 0 | AI2: 0
A3: M-INCOME - Income Statement - M-INCOME - BSUNIT-IS | B3: M-INCOME | C3: Income Statement | D3: M-INCOME | E3: MTD-NET | F3: Year | G3: 01/09/24..30/09/24 | H3: =TRUE() -> TRUE | S3: H1 | T3: PROFIT & LOSS STATMENT | U3: 0 | V3: 0 | W3: 0 | X3: 0 | Y3: 0 | Z3: 0 | AA3: 0 | AB3: 0 | AC3: 0 | AD3: 0 | AE3: 0 | AF3: 0 | AG3: 0 | AH3: 0 | AI3: 0
A4: M-INCOME - Income Statement - M-INCOME - BSUNIT-IS | B4: M-INCOME | C4: Income Statement | D4: M-INCOME | E4: MTD-NET | F4: Year | G4: 01/09/24..30/09/24 | H4: =TRUE() -> TRUE | S4: L11 | T4: Interest Income : Loans | U4: 28635.54 | V4: 29287.07 | W4: 35674.46 | X4: 40096.28 | Y4: 42886.19 | Z4: 40458.8 | AA4: 51807.68 | AB4: 52010.58 | AC4: 51919.6 | AD4: 0 | AE4: 0 | AF4: 0 | AG4: 0 | AH4: 0 | AI4: 0
A5: M-INCOME - Income Statement - M-INCOME - BSUNIT-IS | B5: M-INCOME | C5: Income Statement | D5: M-INCOME | E5: MTD-NET | F5: Year | G5: 01/09/24..30/09/24 | H5: =TRUE() -> TRUE | S5: L12 | T5: Interest Income : Other | U5: 4932.24 | V5: 4938.98 | W5: 6075.04 | X5: 4891.52 | Y5: 5987.87 | Z5: 7263.71 | AA5: 8820.37 | AB5: 5472.76 | AC5: 5064.87 | AD5: 0 | AE5: 0 | AF5: 0 | AG5: 0 | AH5: 0 | AI5: 0
A6: M-INCOME - Income Statement - M-INCOME - BSUNIT-IS | B6: M-INCOME | C6: Income Statement | D6: M-INCOME | E6: MTD-NET | F6: Year | G6: 01/09/24..30/09/24 | H6: =TRUE() -> TRUE | S6: L13 | T6: Interest Expense : Borrowings | U6: -23709.39 | V6: -22451.36 | W6: -26057.9 | X6: -25911.72 | Y6: -28550.58 | Z6: -29903.51 | AA6: -32709.78 | AB6: -34007.49 | AC6: -34403.71 | AD6: 0 | AE6: 0 | AF6: 0 | AG6: 0 | AH6: 0 | AI6: 0
A7: M-INCOME - Income Statement - M-INCOME - BSUNIT-IS | B7: M-INCOME | C7: Income Statement | D7: M-INCOME | E7: MTD-NET | F7: Year | G7: 01/09/24..30/09/24 | H7: =TRUE() -> TRUE | S7: F1 | T7: NET INTEREST INCOME | U7: 9858.39 | V7: 11774.69 | W7: 15691.6 | X7: 19076.08 | Y7: 20323.48 | Z7: 17819 | AA7: 27918.27 | AB7: 23475.85 | AC7: 22580.76 | AD7: 0 | AE7: 0 | AF7: 0 | AG7: 0 | AH7: 0 | AI7: 0
A8: M-INCOME - Income Statement - M-INCOME - BSUNIT-IS | B8: M-INCOME | C8: Income Statement | D8: M-INCOME | E8: MTD-NET | F8: Year | G8: 01/09/24..30/09/24 | H8: =TRUE() -> TRUE | S8: S0 | U8: 0 | V8: 0 | W8: 0 | X8: 0 | Y8: 0 | Z8: 0 | AA8: 0 | AB8: 0 | AC8: 0 | AD8: 0 | AE8: 0 | AF8: 0 | AG8: 0 | AH8: 0 | AI8: 0
A9: M-INCOME - Income Statement - M-INCOME - BSUNIT-IS | B9: M-INCOME | C9: Income Statement | D9: M-INCOME | E9: MTD-NET | F9: Year | G9: 01/09/24..30/09/24 | H9: =TRUE() -> TRUE | S9: L21 | T9: Fee Income | U9: 32362.17 | V9: 29717.12 | W9: 29960.97 | X9: 33589.21 | Y9: 36108.68 | Z9: 31395.87 | AA9: 36615.18 | AB9: 42400.68 | AC9: 46153.74 | AD9: 0 | AE9: 0 | AF9: 0 | AG9: 0 | AH9: 0 | AI9: 0
A10: M-INCOME - Income Statement - M-INCOME - BSUNIT-IS | B10: M-INCOME | C10: Income Statement | D10: M-INCOME | E10: MTD-NET | F10: Year | G10: 01/09/24..30/09/24 | H10: =TRUE() -> TRUE | S10: L22 | T10: Commisions | U10: 658.37 | V10: 602.98 | W10: 536.38 | X10: 852.05 | Y10: 804.28 | Z10: 593.73 | AA10: 910.39 | AB10: 926.12 | AC10: 860.46 | AD10: 0 | AE10: 0 | AF10: 0 | AG10: 0 | AH10: 0 | AI10: 0
A11: M-INCOME - Income Statement - M-INCOME - BSUNIT-IS | B11: M-INCOME | C11: Income Statement | D11: M-INCOME | E11: MTD-NET | F11: Year | G11: 01/09/24..30/09/24 | H11: =TRUE() -> TRUE | S11: L23 | T11: Other Income/(Expenses) | U11: 6507.52 | V11: 6253.8 | W11: 6253.8 | X11: 6253.8 | Y11: 6253.8 | Z11: 6253.8 | AA11: 6253.8 | AB11: 253.8 | AC11: 2520.14 | AD11: 0 | AE11: 0 | AF11: 0 | AG11: 0 | AH11: 0 | AI11: 0
A12: M-INCOME - Income Statement - M-INCOME - BSUNIT-IS | B12: M-INCOME | C12: Income Statement | D12: M-INCOME | E12: MTD-NET | F12: Year | G12: 01/09/24..30/09/24 | H12: =TRUE() -> TRUE | S12: F2 | T12: FEES & COMMISIONS | U12: 39528.06 | V12: 36573.9 | W12: 36751.15 | X12: 40695.06 | Y12: 43166.76 | Z12: 38243.4 | AA12: 43779.37 | AB12: 43580.6 | AC12: 49534.34 | AD12: 0 | AE12: 0 | AF12: 0 | AG12: 0 | AH12: 0 | AI12: 0
A13: M-INCOME - Income Statement - M-INCOME - BSUNIT-IS | B13: M-INCOME | C13: Income Statement | D13: M-INCOME | E13: MTD-NET | F13: Year | G13: 01/09/24..30/09/24 | H13: =TRUE() -> TRUE | S13: S1 | U13: 0 | V13: 0 | W13: 0 | X13: 0 | Y13: 0 | Z13: 0 | AA13: 0 | AB13: 0 | AC13: 0 | AD13: 0 | AE13: 0 | AF13: 0 | AG13: 0 | AH13: 0 | AI13: 0
A14: M-INCOME - Income Statement - M-INCOME - BSUNIT-IS | B14: M-INCOME | C14: Income Statement | D14: M-INCOME | E14: MTD-NET | F14: Year | G14: 01/09/24..30/09/24 | H14: =TRUE() -> TRUE | S14: F3 | T14: NET INCOME | U14: 49386.45 | V14: 48348.59 | W14: 52442.75 | X14: 59771.14 | Y14: 63490.24 | Z14: 56062.4 | AA14: 71697.64 | AB14: 67056.45 | AC14: 72115.1 | AD14: 0 | AE14: 0 | AF14: 0 | AG14: 0 | AH14: 0 | AI14: 0
A15: M-INCOME - Income Statement - M-INCOME - BSUNIT-IS | B15: M-INCOME | C15: Income Statement | D15: M-INCOME | E15: MTD-NET | F15: Year | G15: 01/09/24..30/09/24 | H15: =TRUE() -> TRUE | S15: S2 | U15: 0 | V15: 0 | W15: 0 | X15: 0 | Y15: 0 | Z15: 0 | AA15: 0 | AB15: 0 | AC15: 0 | AD15: 0 | AE15: 0 | AF15: 0 | AG15: 0 | AH15: 0 | AI15: 0
A16: M-INCOME - Income Statement - M-INCOME - BSUNIT-IS | B16: M-INCOME | C16: Income Statement | D16: M-INCOME | E16: MTD-NET | F16: Year | G16: 01/09/24..30/09/24 | H16: =TRUE() -> TRUE | S16: L31 | T16: Loan Impairment | U16: 5295.01 | V16: 4392.29 | W16: 7940.39 | X16: 6951.63 | Y16: 8438.4 | Z16: 3630.85 | AA16: 8102.46 | AB16: 13977.54 | AC16: 10471.74 | AD16: 0 | AE16: 0 | AF16: 0 | AG16: 0 | AH16: 0 | AI16: 0
A17: M-INCOME - Income Statement - M-INCOME - BSUNIT-IS | B17: M-INCOME | C17: Income Statement | D17: M-INCOME | E17: MTD-NET | F17: Year | G17: 01/09/24..30/09/24 | H17: =TRUE() -> TRUE | S17: L32 | T17: Third Party Charges | U17: 1170.82 | V17: 916.42 | W17: 1195.33 | X17: 1195.51 | Y17: 980.05 | Z17: 1332.38 | AA17: 1125.94 | AB17: 1511.98 | AC17: 1361.82 | AD17: 0 | AE17: 0 | AF17: 0 | AG17: 0 | AH17: 0 | AI17: 0
A18: M-INCOME - Income Statement - M-INCOME - BSUNIT-IS | B18: M-INCOME | C18: Income Statement | D18: M-INCOME | E18: MTD-NET | F18: Year | G18: 01/09/24..30/09/24 | H18: =TRUE() -> TRUE | S18: F4 | T18: TOTAL INDIRECT COSTS | U18: 6465.83 | V18: 5308.71 | W18: 9135.72 | X18: 8147.14 | Y18: 9418.45 | Z18: 4963.23 | AA18: 9228.4 | AB18: 15489.52 | AC18: 11833.56 | AD18: 0 | AE18: 0 | AF18: 0 | AG18: 0 | AH18: 0 | AI18: 0
A19: M-INCOME - Income Statement - M-INCOME - BSUNIT-IS | B19: M-INCOME | C19: Income Statement | D19: M-INCOME | E19: MTD-NET | F19: Year | G19: 01/09/24..30/09/24 | H19: =TRUE() -> TRUE | S19: S3 | U19: 0 | V19: 0 | W19: 0 | X19: 0 | Y19: 0 | Z19: 0 | AA19: 0 | AB19: 0 | AC19: 0 | AD19: 0 | AE19: 0 | AF19: 0 | AG19: 0 | AH19: 0 | AI19: 0
A20: M-INCOME - Income Statement - M-INCOME - BSUNIT-IS | B20: M-INCOME | C20: Income Statement | D20: M-INCOME | E20: MTD-NET | F20: Year | G20: 01/09/24..30/09/24 | H20: =TRUE() -> TRUE | S20: F5 | T20: GROSS MARGINS | U20: 42920.62 | V20: 43039.88 | W20: 43307.03 | X20: 51624 | Y20: 54071.79 | Z20: 51099.17 | AA20: 62469.24 | AB20: 51566.93 | AC20: 60281.54 | AD20: 0 | AE20: 0 | AF20: 0 | AG20: 0 | AH20: 0 | AI20: 0
A21: M-INCOME - Income Statement - M-INCOME - BSUNIT-IS | B21: M-INCOME | C21: Income Statement | D21: M-INCOME | E21: MTD-NET | F21: Year | G21: 01/09/24..30/09/24 | H21: =TRUE() -> TRUE | S21: S4 | U21: 0 | V21: 0 | W21: 0 | X21: 0 | Y21: 0 | Z21: 0 | AA21: 0 | AB21: 0 | AC21: 0 | AD21: 0 | AE21: 0 | AF21: 0 | AG21: 0 | AH21: 0 | AI21: 0
A22: M-INCOME - Income Statement - M-INCOME - BSUNIT-IS | B22: M-INCOME | C22: Income Statement | D22: M-INCOME | E22: MTD-NET | F22: Year | G22: 01/09/24..30/09/24 | H22: =TRUE() -> TRUE | S22: L41 | T22: Sales & Marketing | U22: 14608.31 | V22: 15595.01 | W22: 17414.68 | X22: 24046.41 | Y22: 24127.03 | Z22: 18558.32 | AA22: 17408.22 | AB22: 16756.51 | AC22: 17478.59 | AD22: 0 | AE22: 0 | AF22: 0 | AG22: 0 | AH22: 0 | AI22: 0
A23: M-INCOME - Income Statement - M-INCOME - BSUNIT-IS | B23: M-INCOME | C23: Income Statement | D23: M-INCOME | E23: MTD-NET | F23: Year | G23: 01/09/24..30/09/24 | H23: =TRUE() -> TRUE | S23: L42 | T23: General & Adminisrative Expenses | U23: 80728.27 | V23: 82070.28 | W23: 87423.47 | X23: 94509.03 | Y23: 94474.2 | Z23: 97817.55 | AA23: 98226.72 | AB23: 104794.46 | AC23: 110820.98 | AD23: 0 | AE23: 0 | AF23: 0 | AG23: 0 | AH23: 0 | AI23: 0
A24: M-INCOME - Income Statement - M-INCOME - BSUNIT-IS | B24: M-INCOME | C24: Income Statement | D24: M-INCOME | E24: MTD-NET | F24: Year | G24: 01/09/24..30/09/24 | H24: =TRUE() -> TRUE | S24: S5 | T24: InterCo Purchases | U24: 0 | V24: 0 | W24: 0 | X24: 0 | Y24: 0 | Z24: 0 | AA24: -1.4 | AB24: -0.14 | AC24: 45.36 | AD24: 0 | AE24: 0 | AF24: 0 | AG24: 0 | AH24: 0 | AI24: 0
A25: M-INCOME - Income Statement - M-INCOME - BSUNIT-IS | B25: M-INCOME | C25: Income Statement | D25: M-INCOME | E25: MTD-NET | F25: Year | G25: 01/09/24..30/09/24 | H25: =TRUE() -> TRUE | S25: F6 | T25: EBITDAM | U25: -52415.96 | V25: -54625.41 | W25: -61531.12 | X25: -66931.44 | Y25: -64529.44 | Z25: -65276.7 | AA25: -53164.3 | AB25: -69983.9 | AC25: -68063.39 | AD25: 0 | AE25: 0 | AF25: 0 | AG25: 0 | AH25: 0 | AI25: 0
A26: M-INCOME - Income Statement - M-INCOME - BSUNIT-IS | B26: M-INCOME | C26: Income Statement | D26: M-INCOME | E26: MTD-NET | F26: Year | G26: 01/09/24..30/09/24 | H26: =TRUE() -> TRUE | S26: S5 | U26: 0 | V26: 0 | W26: 0 | X26: 0 | Y26: 0 | Z26: 0 | AA26: 0 | AB26: 0 | AC26: 0 | AD26: 0 | AE26: 0 | AF26: 0 | AG26: 0 | AH26: 0 | AI26: 0
A27: M-INCOME - Income Statement - M-INCOME - BSUNIT-IS | B27: M-INCOME | C27: Income Statement | D27: M-INCOME | E27: MTD-NET | F27: Year | G27: 01/09/24..30/09/24 | H27: =TRUE() -> TRUE | S27: L43 | T27: Head Office | U27: 0 | V27: 0 | W27: 0 | X27: 0 | Y27: 0 | Z27: 0 | AA27: 0 | AB27: 0 | AC27: 0 | AD27: 0 | AE27: 0 | AF27: 0 | AG27: 0 | AH27: 0 | AI27: 0
A28: M-INCOME - Income Statement - M-INCOME - BSUNIT-IS | B28: M-INCOME | C28: Income Statement | D28: M-INCOME | E28: MTD-NET | F28: Year | G28: 01/09/24..30/09/24 | H28: =TRUE() -> TRUE | S28: F7 | T28: EBITDA | U28: -52415.96 | V28: -54625.41 | W28: -61531.12 | X28: -66931.44 | Y28: -64529.44 | Z28: -65276.7 | AA28: -53164.3 | AB28: -69983.9 | AC28: -68063.39 | AD28: 0 | AE28: 0 | AF28: 0 | AG28: 0 | AH28: 0 | AI28: 0
A29: M-INCOME - Income Statement - M-INCOME - BSUNIT-IS | B29: M-INCOME | C29: Income Statement | D29: M-INCOME | E29: MTD-NET | F29: Year | G29: 01/09/24..30/09/24 | H29: =TRUE() -> TRUE | S29: S | U29: 0 | V29: 0 | W29: 0 | X29: 0 | Y29: 0 | Z29: 0 | AA29: 0 | AB29: 0 | AC29: 0 | AD29: 0 | AE29: 0 | AF29: 0 | AG29: 0 | AH29: 0 | AI29: 0
A30: M-INCOME - Income Statement - M-INCOME - BSUNIT-IS | B30: M-INCOME | C30: Income Statement | D30: M-INCOME | E30: MTD-NET | F30: Year | G30: 01/09/24..30/09/24 | H30: =TRUE() -> TRUE | S30: L51 | T30: Depreciations | U30: 999.54 | V30: 1087.48 | W30: 1089.79 | X30: 1097.59 | Y30: 1089.21 | Z30: 1162.79 | AA30: 1152.18 | AB30: 1152.74 | AC30: 1204.16 | AD30: 0 | AE30: 0 | AF30: 0 | AG30: 0 | AH30: 0 | AI30: 0
A31: M-INCOME - Income Statement - M-INCOME - BSUNIT-IS | B31: M-INCOME | C31: Income Statement | D31: M-INCOME | E31: MTD-NET | F31: Year | G31: 01/09/24..30/09/24 | H31: =TRUE() -> TRUE | S31: L52 | T31: Ammortization | U31: 20157.94 | V31: 20177.41 | W31: 20167.67 | X31: 20167.67 | Y31: 20167.67 | Z31: 20167.67 | AA31: 20165.65 | AB31: 7741.34 | AC31: 287.7 | AD31: 0 | AE31: 0 | AF31: 0 | AG31: 0 | AH31: 0 | AI31: 0
A32: M-INCOME - Income Statement - M-INCOME - BSUNIT-IS | B32: M-INCOME | C32: Income Statement | D32: M-INCOME | E32: MTD-NET | F32: Year | G32: 01/09/24..30/09/24 | H32: =TRUE() -> TRUE | S32: L53 | T32: Finance Cost | U32: 8866.64 | V32: 9616.99 | W32: 9476.5 | X32: 7694.2 | Y32: 7310.57 | Z32: 7172.2 | AA32: 5862.85 | AB32: 5459.98 | AC32: 5483.75 | AD32: 0 | AE32: 0 | AF32: 0 | AG32: 0 | AH32: 0 | AI32: 0
A33: M-INCOME - Income Statement - M-INCOME - BSUNIT-IS | B33: M-INCOME | C33: Income Statement | D33: M-INCOME | E33: MTD-NET | F33: Year | G33: 01/09/24..30/09/24 | H33: =TRUE() -> TRUE | S33: L54 | T33: Other Income & Expenses | U33: 718.7 | V33: 1137.51 | W33: 3527.35 | X33: 3901.47 | Y33: 3875.62 | Z33: 3898.51 | AA33: 9420.3 | AB33: -2570.68 | AC33: 1867.32 | AD33: 0 | AE33: 0 | AF33: 0 | AG33: 0 | AH33: 0 | AI33: 0
A34: M-INCOME - Income Statement - M-INCOME - BSUNIT-IS | B34: M-INCOME | C34: Income Statement | D34: M-INCOME | E34: MTD-NET | F34: Year | G34: 01/09/24..30/09/24 | H34: =TRUE() -> TRUE | T34: EBT | U34: -83158.78 | V34: -86644.8 | W34: -95792.43 | X34: -99792.37 | Y34: -96972.51 | Z34: -97677.87 | AA34: -89765.28 | AB34: -81767.28 | AC34: -76906.32 | AD34: 0 | AE34: 0 | AF34: 0 | AG34: 0 | AH34: 0 | AI34: 0
H35: =TRUE() -> TRUE
U38: =U20-U22-U23 -> -52415.96

Sheet IS_BU(MoM)
A1: Name | B1: Display Title | C1: Row Definition | D1: Column Definition | E1: Negative Amount Format | F1: View by | G1: Date Filter | H1: Show All Lines | I1: Default Excel Layout | J1: Internal Description | K1: IntroductoryParagraph | L1: Product Filter | M1: Department Filter | N1: Cost Center Filter | O1: Cost Object Filter | P1: Cash Flow Filter | Q1: G/L Budget Filter | R1: Cost Budget Filter | S1: Row No. | T1: Description | U1: USA | V1: KENYA | W1: INDIA | X1: TZ | Y1: UGANDA | Z1: CONSOLIDATED | AB1: 1 | AC1: 2 | AD1: 3 | AE1: 4 | AF1: 5 | AG1: 6 | AH1: 7 | AI1: 8 | AJ1: ClosingParagraph
A2: M-INCOME | B2: Income Statement | C2: M-INCOME | D2: BSUNIT-IS | E2: Minus Sign | F2: Year | G2: 01/07/25..31/07/25 | H2: =TRUE() -> TRUE | U2: 0 | V2: 0 | W2: 0 | X2: 0 | Y2: 0 | Z2: 0 | AA2: 0 | AB2: 0 | AC2: 0 | AD2: 0 | AE2: 0 | AF2: 0 | AG2: 0 | AH2: 0 | AI2: 0
A3: M-INCOME | B3: Income Statement | C3: M-INCOME | D3: BSUNIT-IS | E3: Minus Sign | F3: Year | G3: 01/07/25..31/07/25 | H3: =TRUE() -> TRUE | S3: H1 | T3: PROFIT & LOSS STATMENT | U3: 0 | V3: 0 | W3: 0 | X3: 0 | Y3: 0 | Z3: 0 | AA3: 0 | AB3: 0 | AC3: 0 | AD3: 0 | AE3: 0 | AF3: 0 | AG3: 0 | AH3: 0 | AI3: 0
A4: M-INCOME | B4: Income Statement | C4: M-INCOME | D4: BSUNIT-IS | E4: Minus Sign | F4: Year | G4: 01/07/25..31/07/25 | H4: =TRUE() -> TRUE | S4: L11 | T4: Interest Income : Loans | U4: 0 | V4: 50557.17 | W4: 0 | X4: 0 | Y4: 1362.43 | Z4: 51919.6 | AA4: 0 | AB4: 0 | AC4: 0 | AD4: 0 | AE4: 0 | AF4: 0 | AG4: 0 | AH4: 0 | AI4: 0
A5: M-INCOME | B5: Income Statement | C5: M-INCOME | D5: BSUNIT-IS | E5: Minus Sign | F5: Year | G5: 01/07/25..31/07/25 | H5: =TRUE() -> TRUE | S5: L12 | T5: Interest Income : Other | U5: 359.41 | V5: 4705.46 | W5: 0 | X5: 0 | Y5: 0 | Z5: 5064.87 | AA5: 0 | AB5: 0 | AC5: 0 | AD5: 0 | AE5: 0 | AF5: 0 | AG5: 0 | AH5: 0 | AI5: 0
A6: M-INCOME | B6: Income Statement | C6: M-INCOME | D6: BSUNIT-IS | E6: Minus Sign | F6: Year | G6: 01/07/25..31/07/25 | H6: =TRUE() -> TRUE | S6: L13 | T6: Interest Expense : Borrowings | U6: 0 | V6: -34403.71 | W6: 0 | X6: 0 | Y6: 0 | Z6: -34403.71 | AA6: 0 | AB6: 0 | AC6: 0 | AD6: 0 | AE6: 0 | AF6: 0 | AG6: 0 | AH6: 0 | AI6: 0
A7: M-INCOME | B7: Income Statement | C7: M-INCOME | D7: BSUNIT-IS | E7: Minus Sign | F7: Year | G7: 01/07/25..31/07/25 | H7: =TRUE() -> TRUE | S7: F1 | T7: NET INTEREST INCOME | U7: 359.41 | V7: 20858.92 | W7: 0 | X7: 0 | Y7: 1362.43 | Z7: 22580.76 | AA7: 0 | AB7: 0 | AC7: 0 | AD7: 0 | AE7: 0 | AF7: 0 | AG7: 0 | AH7: 0 | AI7: 0
A8: M-INCOME | B8: Income Statement | C8: M-INCOME | D8: BSUNIT-IS | E8: Minus Sign | F8: Year | G8: 01/07/25..31/07/25 | H8: =TRUE() -> TRUE | S8: S0 | U8: 0 | V8: 0 | W8: 0 | X8: 0 | Y8: 0 | Z8: 0 | AA8: 0 | AB8: 0 | AC8: 0 | AD8: 0 | AE8: 0 | AF8: 0 | AG8: 0 | AH8: 0 | AI8: 0
A9: M-INCOME | B9: Income Statement | C9: M-INCOME | D9: BSUNIT-IS | E9: Minus Sign | F9: Year | G9: 01/07/25..31/07/25 | H9: =TRUE() -> TRUE | S9: L21 | T9: Fee Income | U9: 14000 | V9: 30495.54 | W9: 0 | X9: 0 | Y9: 1658.2 | Z9: 46153.74 | AA9: 0 | AB9: 0 | AC9: 0 | AD9: 0 | AE9: 0 | AF9: 0 | AG9: 0 | AH9: 0 | AI9: 0
A10: M-INCOME | B10: Income Statement | C10: M-INCOME | D10: BSUNIT-IS | E10: Minus Sign | F10: Year | G10: 01/07/25..31/07/25 | H10: =TRUE() -> TRUE | S10: L22 | T10: Commisions | U10: 0 | V10: 859.46 | W10: 0 | X10: 0 | Y10: 1 | Z10: 860.46 | AA10: 0 | AB10: 0 | AC10: 0 | AD10: 0 | AE10: 0 | AF10: 0 | AG10: 0 | AH10: 0 | AI10: 0
A11: M-INCOME | B11: Income Statement | C11: M-INCOME | D11: BSUNIT-IS | E11: Minus Sign | F11: Year | G11: 01/07/25..31/07/25 | H11: =TRUE() -> TRUE | S11: L23 | T11: Other Income/(Expenses) | U11: 253.8 | V11: 2266.34 | W11: 0 | X11: 0 | Y11: 0 | Z11: 2520.14 | AA11: 0 | AB11: 0 | AC11: 0 | AD11: 0 | AE11: 0 | AF11: 0 | AG11: 0 | AH11: 0 | AI11: 0
A12: M-INCOME | B12: Income Statement | C12: M-INCOME | D12: BSUNIT-IS | E12: Minus Sign | F12: Year | G12: 01/07/25..31/07/25 | H12: =TRUE() -> TRUE | S12: F2 | T12: FEES & COMMISIONS | U12: 14253.8 | V12: 33621.34 | W12: 0 | X12: 0 | Y12: 1659.2 | Z12: 49534.34 | AA12: 0 | AB12: 0 | AC12: 0 | AD12: 0 | AE12: 0 | AF12: 0 | AG12: 0 | AH12: 0 | AI12: 0
A13: M-INCOME | B13: Income Statement | C13: M-INCOME | D13: BSUNIT-IS | E13: Minus Sign | F13: Year | G13: 01/07/25..31/07/25 | H13: =TRUE() -> TRUE | S13: S1 | U13: 0 | V13: 0 | W13: 0 | X13: 0 | Y13: 0 | Z13: 0 | AA13: 0 | AB13: 0 | AC13: 0 | AD13: 0 | AE13: 0 | AF13: 0 | AG13: 0 | AH13: 0 | AI13: 0
A14: M-INCOME | B14: Income Statement | C14: M-INCOME | D14: BSUNIT-IS | E14: Minus Sign | F14: Year | G14: 01/07/25..31/07/25 | H14: =TRUE() -> TRUE | S14: F3 | T14: NET INCOME | U14: 14613.21 | V14: 54480.26 | W14: 0 | X14: 0 | Y14: 3021.63 | Z14: 72115.1 | AA14: 0 | AB14: 0 | AC14: 0 | AD14: 0 | AE14: 0 | AF14: 0 | AG14: 0 | AH14: 0 | AI14: 0
A15: M-INCOME | B15: Income Statement | C15: M-INCOME | D15: BSUNIT-IS | E15: Minus Sign | F15: Year | G15: 01/07/25..31/07/25 | H15: =TRUE() -> TRUE | S15: S2 | U15: 0 | V15: 0 | W15: 0 | X15: 0 | Y15: 0 | Z15: 0 | AA15: 0 | AB15: 0 | AC15: 0 | AD15: 0 | AE15: 0 | AF15: 0 | AG15: 0 | AH15: 0 | AI15: 0
A16: M-INCOME | B16: Income Statement | C16: M-INCOME | D16: BSUNIT-IS | E16: Minus Sign | F16: Year | G16: 01/07/25..31/07/25 | H16: =TRUE() -> TRUE | S16: L31 | T16: Loan Impairment | U16: 0 | V16: 10471.74 | W16: 0 | X16: 0 | Y16: 0 | Z16: 10471.74 | AA16: 0 | AB16: 0 | AC16: 0 | AD16: 0 | AE16: 0 | AF16: 0 | AG16: 0 | AH16: 0 | AI16: 0
A17: M-INCOME | B17: Income Statement | C17: M-INCOME | D17: BSUNIT-IS | E17: Minus Sign | F17: Year | G17: 01/07/25..31/07/25 | H17: =TRUE() -> TRUE | S17: L32 | T17: Third Party Charges | U17: 0 | V17: 1297.69 | W17: 0 | X17: 0 | Y17: 64.13 | Z17: 1361.82 | AA17: 0 | AB17: 0 | AC17: 0 | AD17: 0 | AE17: 0 | AF17: 0 | AG17: 0 | AH17: 0 | AI17: 0
A18: M-INCOME | B18: Income Statement | C18: M-INCOME | D18: BSUNIT-IS | E18: Minus Sign | F18: Year | G18: 01/07/25..31/07/25 | H18: =TRUE() -> TRUE | S18: F4 | T18: TOTAL INDIRECT COSTS | U18: 0 | V18: 11769.43 | W18: 0 | X18: 0 | Y18: 64.13 | Z18: 11833.56 | AA18: 0 | AB18: 0 | AC18: 0 | AD18: 0 | AE18: 0 | AF18: 0 | AG18: 0 | AH18: 0 | AI18: 0
A19: M-INCOME | B19: Income Statement | C19: M-INCOME | D19: BSUNIT-IS | E19: Minus Sign | F19: Year | G19: 01/07/25..31/07/25 | H19: =TRUE() -> TRUE | S19: S3 | U19: 0 | V19: 0 | W19: 0 | X19: 0 | Y19: 0 | Z19: 0 | AA19: 0 | AB19: 0 | AC19: 0 | AD19: 0 | AE19: 0 | AF19: 0 | AG19: 0 | AH19: 0 | AI19: 0
A20: M-INCOME | B20: Income Statement | C20: M-INCOME | D20: BSUNIT-IS | E20: Minus Sign | F20: Year | G20: 01/07/25..31/07/25 | H20: =TRUE() -> TRUE | S20: F5 | T20: GROSS MARGINS | U20: 14613.21 | V20: 42710.83 | W20: 0 | X20: 0 | Y20: 2957.5 | Z20: 60281.54 | AA20: 0 | AB20: 0 | AC20: 0 | AD20: 0 | AE20: 0 | AF20: 0 | AG20: 0 | AH20: 0 | AI20: 0
A21: M-INCOME | B21: Income Statement | C21: M-INCOME | D21: BSUNIT-IS | E21: Minus Sign | F21: Year | G21: 01/07/25..31/07/25 | H21: =TRUE() -> TRUE | S21: S4 | U21: 0 | V21: 0 | W21: 0 | X21: 0 | Y21: 0 | Z21: 0 | AA21: 0 | AB21: 0 | AC21: 0 | AD21: 0 | AE21: 0 | AF21: 0 | AG21: 0 | AH21: 0 | AI21: 0
A22: M-INCOME | B22: Income Statement | C22: M-INCOME | D22: BSUNIT-IS | E22: Minus Sign | F22: Year | G22: 01/07/25..31/07/25 | H22: =TRUE() -> TRUE | S22: L41 | T22: Sales & Marketing | U22: 4998.31 | V22: 8606.86 | W22: 0 | X22: 0 | Y22: 3873.42 | Z22: 17478.59 | AA22: 0 | AB22: 0 | AC22: 0 | AD22: 0 | AE22: 0 | AF22: 0 | AG22: 0 | AH22: 0 | AI22: 0
A23: M-INCOME | B23: Income Statement | C23: M-INCOME | D23: BSUNIT-IS | E23: Minus Sign | F23: Year | G23: 01/07/25..31/07/25 | H23: =TRUE() -> TRUE | S23: L42 | T23: General & Adminisrative Expenses | U23: 50289.88 | V23: 42778.06 | W23: 11694.79 | X23: 1101.92 | Y23: 4956.33 | Z23: 110820.98 | AA23: 0 | AB23: 0 | AC23: 0 | AD23: 0 | AE23: 0 | AF23: 0 | AG23: 0 | AH23: 0 | AI23: 0
A24: M-INCOME | B24: Income Statement | C24: M-INCOME | D24: BSUNIT-IS | E24: Minus Sign | F24: Year | G24: 01/07/25..31/07/25 | H24: =TRUE() -> TRUE | S24: S5 | T24: InterCo Purchases | U24: 12590.61 | V24: 0 | W24: -12545.25 | X24: 0 | Y24: 0 | Z24: 45.36 | AA24: 0 | AB24: 0 | AC24: 0 | AD24: 0 | AE24: 0 | AF24: 0 | AG24: 0 | AH24: 0 | AI24: 0
A25: M-INCOME | B25: Income Statement | C25: M-INCOME | D25: BSUNIT-IS | E25: Minus Sign | F25: Year | G25: 01/07/25..31/07/25 | H25: =TRUE() -> TRUE | S25: F6 | T25: EBITDAM | U25: -53265.59 | V25: -8674.09 | W25: 850.46 | X25: -1101.92 | Y25: -5872.25 | Z25: -68063.39 | AA25: 0 | AB25: 0 | AC25: 0 | AD25: 0 | AE25: 0 | AF25: 0 | AG25: 0 | AH25: 0 | AI25: 0
A26: M-INCOME | B26: Income Statement | C26: M-INCOME | D26: BSUNIT-IS | E26: Minus Sign | F26: Year | G26: 01/07/25..31/07/25 | H26: =TRUE() -> TRUE | S26: S5 | U26: 0 | V26: 0 | W26: 0 | X26: 0 | Y26: 0 | Z26: 0 | AA26: 0 | AB26: 0 | AC26: 0 | AD26: 0 | AE26: 0 | AF26: 0 | AG26: 0 | AH26: 0 | AI26: 0
A27: M-INCOME | B27: Income Statement | C27: M-INCOME | D27: BSUNIT-IS | E27: Minus Sign | F27: Year | G27: 01/07/25..31/07/25 | H27: =TRUE() -> TRUE | S27: L43 | T27: Head Office | U27: 0 | V27: 0 | W27: 0 | X27: 0 | Y27: 0 | Z27: 0 | AA27: 0 | AB27: 0 | AC27: 0 | AD27: 0 | AE27: 0 | AF27: 0 | AG27: 0 | AH27: 0 | AI27: 0
A28: M-INCOME | B28: Income Statement | C28: M-INCOME | D28: BSUNIT-IS | E28: Minus Sign | F28: Year | G28: 01/07/25..31/07/25 | H28: =TRUE() -> TRUE | S28: F7 | T28: EBITDA | U28: -53265.59 | V28: -8674.09 | W28: 850.46 | X28: -1101.92 | Y28: -5872.25 | Z28: -68063.39 | AA28: 0 | AB28: 0 | AC28: 0 | AD28: 0 | AE28: 0 | AF28: 0 | AG28: 0 | AH28: 0 | AI28: 0
A29: M-INCOME | B29: Income Statement | C29: M-INCOME | D29: BSUNIT-IS | E29: Minus Sign | F29: Year | G29: 01/07/25..31/07/25 | H29: =TRUE() -> TRUE | S29: S | U29: 0 | V29: 0 | W29: 0 | X29: 0 | Y29: 0 | Z29: 0 | AA29: 0 | AB29: 0 | AC29: 0 | AD29: 0 | AE29: 0 | AF29: 0 | AG29: 0 | AH29: 0 | AI29: 0
A30: M-INCOME | B30: Income Statement | C30: M-INCOME | D30: BSUNIT-IS | E30: Minus Sign | F30: Year | G30: 01/07/25..31/07/25 | H30: =TRUE() -> TRUE | S30: L51 | T30: Depreciations | U30: 204.44 | V30: 918.32 | W30: 0 | X30: 0 | Y30: 81.4 | Z30: 1204.16 | AA30: 0 | AB30: 0 | AC30: 0 | AD30: 0 | AE30: 0 | AF30: 0 | AG30: 0 | AH30: 0 | AI30: 0
A31: M-INCOME | B31: Income Statement | C31: M-INCOME | D31: BSUNIT-IS | E31: Minus Sign | F31: Year | G31: 01/07/25..31/07/25 | H31: =TRUE() -> TRUE | S31: L52 | T31: Ammortization | U31: 0 | V31: 287.7 | W31: 0 | X31: 0 | Y31: 0 | Z31: 287.7 | AA31: 0 | AB31: 0 | AC31: 0 | AD31: 0 | AE31: 0 | AF31: 0 | AG31: 0 | AH31: 0 | AI31: 0
A32: M-INCOME | B32: Income Statement | C32: M-INCOME | D32: BSUNIT-IS | E32: Minus Sign | F32: Year | G32: 01/07/25..31/07/25 | H32: =TRUE() -> TRUE | S32: L53 | T32: Finance Cost | U32: 0 | V32: 5483.75 | W32: 0 | X32: 0 | Y32: 0 | Z32: 5483.75 | AA32: 0 | AB32: 0 | AC32: 0 | AD32: 0 | AE32: 0 | AF32: 0 | AG32: 0 | AH32: 0 | AI32: 0
A33: M-INCOME | B33: Income Statement | C33: M-INCOME | D33: BSUNIT-IS | E33: Minus Sign | F33: Year | G33: 01/07/25..31/07/25 | H33: =TRUE() -> TRUE | S33: L54 | T33: Other Income & Expenses | U33: 700 | V33: 1167.32 | W33: 0 | X33: 0 | Y33: 0 | Z33: 1867.32 | AA33: 0 | AB33: 0 | AC33: 0 | AD33: 0 | AE33: 0 | AF33: 0 | AG33: 0 | AH33: 0 | AI33: 0
A34: M-INCOME | B34: Income Statement | C34: M-INCOME | D34: BSUNIT-IS | E34: Minus Sign | F34: Year | G34: 01/07/25..31/07/25 | H34: =TRUE() -> TRUE | T34: EBT | U34: -54170.03 | V34: -16531.18 | W34: 850.46 | X34: -1101.92 | Y34: -5953.65 | Z34: -76906.32 | AA34: 0 | AB34: 0 | AC34: 0 | AD34: 0 | AE34: 0 | AF34: 0 | AG34: 0 | AH34: 0 | AI34: 0

Sheet Cburn_Entity
A1: Name | B1: Display Title | C1: Row Definition | D1: Column Definition | E1: Negative Amount Format | F1: View by | G1: Date Filter | H1: Show All Lines | I1: Default Excel Layout | J1: Internal Description | K1: IntroductoryParagraph | L1: Product Filter | M1: Department Filter | N1: Business-Unit Filter | O1: Cost-center Filter | P1: Cost Center Filter | Q1: Cost Object Filter | R1: Cash Flow Filter | S1: G/L Budget Filter | T1: Cost Budget Filter | U1: Row No. | V1: Description | W1: USA | X1: KENYA | Y1: INDIA | Z1: TZ | AA1: UGANDA | AB1: CONSOLIDATED | AD1: 1 | AE1: 2 | AF1: 3 | AG1: 4 | AH1: 5 | AI1: 6 | AJ1: 7 | AK1: 8 | AL1: ClosingParagraph
A2: CASH BURN | B2: Cost Incurred in Period | C2: OPEX | D2: BSUNIT-IS | E2: Minus Sign | F2: Month | G2: 01/07/25..31/07/25 | H2: =FALSE() -> FALSE | V2: OPERATING EXPENSES | W2: 0 | X2: 0 | Y2: 0 | Z2: 0 | AA2: 0 | AB2: 0 | AC2: 0 | AD2: 0 | AE2: 0 | AF2: 0 | AG2: 0 | AH2: 0 | AI2: 0 | AJ2: 0 | AK2: 0
A3: CASH BURN | B3: Cost Incurred in Period | C3: OPEX | D3: BSUNIT-IS | E3: Minus Sign | F3: Month | G3: 01/07/25..31/07/25 | H3: =FALSE() -> FALSE | U3: 110 | V3: Salary & Wages | W3: 0 | X3: 24247.64 | Y3: 7522.36 | Z3: 0 | AA3: 4003.64 | AB3: 35773.64 | AC3: 0 | AD3: 0 | AE3: 0 | AF3: 0 | AG3: 0 | AH3: 0 | AI3: 0 | AJ3: 0 | AK3: 0
A4: CASH BURN | B4: Cost Incurred in Period | C4: OPEX | D4: BSUNIT-IS | E4: Minus Sign | F4: Month | G4: 01/07/25..31/07/25 | H4: =FALSE() -> FALSE | U4: 120 | V4: Consultants | W4: 31994.75 | X4: 1818.21 | Y4: 0 | Z4: 1062.33 | AA4: 0 | AB4: 34875.29 | AC4: 0 | AD4: 0 | AE4: 0 | AF4: 0 | AG4: 0 | AH4: 0 | AI4: 0 | AJ4: 0 | AK4: 0
A5: CASH BURN | B5: Cost Incurred in Period | C5: OPEX | D5: BSUNIT-IS | E5: Minus Sign | F5: Month | G5: 01/07/25..31/07/25 | H5: =FALSE() -> FALSE | U5: 130 | V5: Fringe Benefits | W5: 726.5 | X5: 12052.12 | Y5: 587.8 | Z5: 0 | AA5: 2689.27 | AB5: 16055.69 | AC5: 0 | AD5: 0 | AE5: 0 | AF5: 0 | AG5: 0 | AH5: 0 | AI5: 0 | AJ5: 0 | AK5: 0
A6: CASH BURN | B6: Cost Incurred in Period | C6: OPEX | D6: BSUNIT-IS | E6: Minus Sign | F6: Month | G6: 01/07/25..31/07/25 | H6: =FALSE() -> FALSE | U6: 210 | V6: Rent & Office related expenses | W6: 12590.61 | X6: 1968.13 | Y6: 476.64 | Z6: 0 | AA6: 526.38 | AB6: 15561.76 | AC6: 0 | AD6: 0 | AE6: 0 | AF6: 0 | AG6: 0 | AH6: 0 | AI6: 0 | AJ6: 0 | AK6: 0
A7: CASH BURN | B7: Cost Incurred in Period | C7: OPEX | D7: BSUNIT-IS | E7: Minus Sign | F7: Month | G7: 01/07/25..31/07/25 | H7: =FALSE() -> FALSE | U7: 220 | V7: Utilities | W7: 0 | X7: 132.6 | Y7: 0 | Z7: 0 | AA7: 62.38 | AB7: 194.98 | AC7: 0 | AD7: 0 | AE7: 0 | AF7: 0 | AG7: 0 | AH7: 0 | AI7: 0 | AJ7: 0 | AK7: 0
A8: CASH BURN | B8: Cost Incurred in Period | C8: OPEX | D8: BSUNIT-IS | E8: Minus Sign | F8: Month | G8: 01/07/25..31/07/25 | H8: =FALSE() -> FALSE | U8: 230 | V8: IT Costs | W8: 1456.23 | X8: 3209.13 | Y8: 3107.99 | Z8: 39.59 | AA8: 240.02 | AB8: 8052.96 | AC8: 0 | AD8: 0 | AE8: 0 | AF8: 0 | AG8: 0 | AH8: 0 | AI8: 0 | AJ8: 0 | AK8: 0
A9: CASH BURN | B9: Cost Incurred in Period | C9: OPEX | D9: BSUNIT-IS | E9: Minus Sign | F9: Month | G9: 01/07/25..31/07/25 | H9: =FALSE() -> FALSE | U9: 240 | V9: Outside Servces | W9: 0 | X9: 230.66 | Y9: 0 | Z9: 0 | AA9: 144.76 | AB9: 375.42 | AC9: 0 | AD9: 0 | AE9: 0 | AF9: 0 | AG9: 0 | AH9: 0 | AI9: 0 | AJ9: 0 | AK9: 0
A10: CASH BURN | B10: Cost Incurred in Period | C10: OPEX | D10: BSUNIT-IS | E10: Minus Sign | F10: Month | G10: 01/07/25..31/07/25 | H10: =FALSE() -> FALSE | U10: 250 | V10: Professional Servicess | W10: 6534 | X10: 2753.55 | Y10: 0 | Z10: 0 | AA10: 202.68 | AB10: 9490.23 | AC10: 0 | AD10: 0 | AE10: 0 | AF10: 0 | AG10: 0 | AH10: 0 | AI10: 0 | AJ10: 0 | AK10: 0
A11: CASH BURN | B11: Cost Incurred in Period | C11: OPEX | D11: BSUNIT-IS | E11: Minus Sign | F11: Month | G11: 01/07/25..31/07/25 | H11: =FALSE() -> FALSE | U11: 260 | V11: Selling Expenses | W11: 0 | X11: 2546.05 | Y11: 0 | Z11: 0 | AA11: 122.01 | AB11: 2668.06 | AC11: 0 | AD11: 0 | AE11: 0 | AF11: 0 | AG11: 0 | AH11: 0 | AI11: 0 | AJ11: 0 | AK11: 0
A12: CASH BURN | B12: Cost Incurred in Period | C12: OPEX | D12: BSUNIT-IS | E12: Minus Sign | F12: Month | G12: 01/07/25..31/07/25 | H12: =FALSE() -> FALSE | U12: 270 | V12: Travel & Entertainment | W12: 840 | X12: 0 | Y12: 0 | Z12: 0 | AA12: 0 | AB12: 840 | AC12: 0 | AD12: 0 | AE12: 0 | AF12: 0 | AG12: 0 | AH12: 0 | AI12: 0 | AJ12: 0 | AK12: 0
A13: CASH BURN | B13: Cost Incurred in Period | C13: OPEX | D13: BSUNIT-IS | E13: Minus Sign | F13: Month | G13: 01/07/25..31/07/25 | H13: =FALSE() -> FALSE | U13: 280 | V13: Office Equipment | W13: 0 | X13: 0 | Y13: 0 | Z13: 0 | AA13: 0 | AB13: 0 | AC13: 0 | AD13: 0 | AE13: 0 | AF13: 0 | AG13: 0 | AH13: 0 | AI13: 0 | AJ13: 0 | AK13: 0
A14: CASH BURN | B14: Cost Incurred in Period | C14: OPEX | D14: BSUNIT-IS | E14: Minus Sign | F14: Month | G14: 01/07/25..31/07/25 | H14: =FALSE() -> FALSE | U14: 290 | V14: Auto Expenses | W14: 0 | X14: 546.92 | Y14: 0 | Z14: 0 | AA14: 279.64 | AB14: 826.56 | AC14: 0 | AD14: 0 | AE14: 0 | AF14: 0 | AG14: 0 | AH14: 0 | AI14: 0 | AJ14: 0 | AK14: 0
... A17: CASH BURN | B17: Cost Incurred in Period | C17: OPEX | D17: BSUNIT-IS | E17: Minus Sign | F17: Month | G17: 01/07/25..31/07/25 | H17: =FALSE() -> FALSE | U17: 320 | V17: Other Expenses | W17: 100 | X17: 719.25 | Y17: 0 | Z17: 0 | AA17: 525.44 | AB17: 1344.69 | AC17: 0 | AD17: 0 | AE17: 0 | AF17: 0 | AG17: 0 | AH17: 0 | AI17: 0 | AJ17: 0 | AK17: 0
A18: CASH BURN | B18: Cost Incurred in Period | C18: OPEX | D18: BSUNIT-IS | E18: Minus Sign | F18: Month | G18: 01/07/25..31/07/25 | H18: =FALSE() -> FALSE | W18: 0 | X18: 0 | Y18: 0 | Z18: 0 | AA18: 0 | AB18: 0 | AC18: 0 | AD18: 0 | AE18: 0 | AF18: 0 | AG18: 0 | AH18: 0 | AI18: 0 | AJ18: 0 | AK18: 0
A19: CASH BURN | B19: Cost Incurred in Period | C19: OPEX | D19: BSUNIT-IS | E19: Minus Sign | F19: Month | G19: 01/07/25..31/07/25 | H19: =FALSE() -> FALSE | U19: F1 | V19: TOTAL OPERATING EXPENSES | W19: 54242.09 | X19: 53228.85 | Y19: 11694.79 | Z19: 1101.92 | AA19: 8796.22 | AB19: 129063.87 | AC19: 0 | AD19: 0 | AE19: 0 | AF19: 0 | AG19: 0 | AH19: 0 | AI19: 0 | AJ19: 0 | AK19: 0

Sheet CBurn_12Months
A1: Name | B1: Display Title | C1: Row Definition | D1: Column Definition | E1: Negative Amount Format | F1: View by | G1: Date Filter | H1: Show All Lines | I1: Default Excel Layout | J1: Internal Description | K1: IntroductoryParagraph | L1: Product Filter | M1: Department Filter | N1: Business-Unit Filter | O1: Cost-center Filter | P1: Cost Center Filter | Q1: Cost Object Filter | R1: Cash Flow Filter | S1: G/L Budget Filter | T1: Cost Budget Filter | U1: Row No. | V1: Description | W1: January | X1: February | Y1: March | Z1: April | AA1: May | AB1: June | AC1: July | AD1: August | AE1: September | AF1: October | AG1: November | AH1: December | AI1: Total | AK1: 1 | AL1: ClosingParagraph
A2: CASH BURN | B2: Cost Incurred in Period | C2: OPEX | D2: MTD-NET | E2: Minus Sign | F2: Month | G2: 01/07/25..31/07/25 | H2: =FALSE() -> FALSE | V2: OPERATING EXPENSES | W2: 0 | X2: 0 | Y2: 0 | Z2: 0 | AA2: 0 | AB2: 0 | AC2: 0 | AD2: 0 | AE2: 0 | AF2: 0 | AG2: 0 | AH2: 0 | AI2: 0 | AJ2: 0 | AK2: 0
A3: CASH BURN | B3: Cost Incurred in Period | C3: OPEX | D3: MTD-NET | E3: Minus Sign | F3: Month | G3: 01/07/25..31/07/25 | H3: =FALSE() -> FALSE | U3: 110 | V3: Salary & Wages | W3: 23081.07 | X3: 25959.19 | Y3: 25780.56 | Z3: 26373.44 | AA3: 30280.34 | AB3: 31906.57 | AC3: 24218.22 | AD3: 33761.76 | AE3: 35773.64 | AF3: 0 | AG3: 0 | AH3: 0 | AI3: 186907.97 | AJ3: 0 | AK3: 0
A4: CASH BURN | B4: Cost Incurred in Period | C4: OPEX | D4: MTD-NET | E4: Minus Sign | F4: Month | G4: 01/07/25..31/07/25 | H4: =FALSE() -> FALSE | U4: 120 | V4: Consultants | W4: 28217.15 | X4: 29883.99 | Y4: 29584.99 | Z4: 35157.69 | AA4: 29945.29 | AB4: 34621.65 | AC4: 32262.39 | AD4: 32397.4 | AE4: 34875.29 | AF4: 0 | AG4: 0 | AH4: 0 | AI4: 219735.32 | AJ4: 0 | AK4: 0
A5: CASH BURN | B5: Cost Incurred in Period | C5: OPEX | D5: MTD-NET | E5: Minus Sign | F5: Month | G5: 01/07/25..31/07/25 | H5: =FALSE() -> FALSE | U5: 130 | V5: Fringe Benefits | W5: 7303.02 | X5: 8712.94 | Y5: 10141.19 | Z5: 10237.78 | AA5: 11557.12 | AB5: 12790.85 | AC5: 13077.82 | AD5: 13610.19 | AE5: 16055.69 | AF5: 0 | AG5: 0 | AH5: 0 | AI5: 73747.75 | AJ5: 0 | AK5: 0
A6: CASH BURN | B6: Cost Incurred in Period | C6: OPEX | D6: MTD-NET | E6: Minus Sign | F6: Month | G6: 01/07/25..31/07/25 | H6: =FALSE() -> FALSE | U6: 210 | V6: Rent & Office related expenses | W6: 11039.74 | X6: 12261.63 | Y6: 11821.84 | Z6: 12830.96 | AA6: 14956.29 | AB6: 15446.32 | AC6: 14744.41 | AD6: 15311.32 | AE6: 15561.76 | AF6: 0 | AG6: 0 | AH6: 0 | AI6: 93072.92 | AJ6: 0 | AK6: 0
A7: CASH BURN | B7: Cost Incurred in Period | C7: OPEX | D7: MTD-NET | E7: Minus Sign | F7: Month | G7: 01/07/25..31/07/25 | H7: =FALSE() -> FALSE | U7: 220 | V7: Utilities | W7: 232.59 | X7: 175.64 | Y7: 182.03 | Z7: 184.27 | AA7: 283.41 | AB7: 186.35 | AC7: 212.93 | AD7: 275.4 | AE7: 194.98 | AF7: 0 | AG7: 0 | AH7: 0 | AI7: 1454.45 | AJ7: 0 | AK7: 0
A8: CASH BURN | B8: Cost Incurred in Period | C8: OPEX | D8: MTD-NET | E8: Minus Sign | F8: Month | G8: 01/07/25..31/07/25 | H8: =FALSE() -> FALSE | U8: 230 | V8: IT Costs | W8: 7138.49 | X8: 6587.16 | Y8: 9142.57 | Z8: 4262.44 | AA8: 10260.18 | AB8: 6198.06 | AC8: 10255.68 | AD8: 6945.5 | AE8: 8052.96 | AF8: 0 | AG8: 0 | AH8: 0 | AI8: 54758.78 | AJ8: 0 | AK8: 0
A9: CASH BURN | B9: Cost Incurred in Period | C9: OPEX | D9: MTD-NET | E9: Minus Sign | F9: Month | G9: 01/07/25..31/07/25 | H9: =FALSE() -> FALSE | U9: 240 | V9: Outside Servces | W9: 273.94 | X9: 279.7 | Y9: 290.95 | Z9: 506.86 | AA9: 337.33 | AB9: 151.81 | AC9: 292.92 | AD9: 477.69 | AE9: 375.42 | AF9: 0 | AG9: 0 | AH9: 0 | AI9: 2131.54 | AJ9: 0 | AK9: 0
A10: CASH BURN | B10: Cost Incurred in Period | C10: OPEX | D10: MTD-NET | E10: Minus Sign | F10: Month | G10: 01/07/25..31/07/25 | H10: =FALSE() -> FALSE | U10: 250 | V10: Professional Servicess | W10: 3654.74 | X10: 2371.45 | Y10: 3434.75 | Z10: 12533.8 | AA10: 3982.42 | AB10: 4942.27 | AC10: 4913.11 | AD10: 2462.74 | AE10: 9490.23 | AF10: 0 | AG10: 0 | AH10: 0 | AI10: 35791.3 | AJ10: 0 | AK10: 0
A11: CASH BURN | B11: Cost Incurred in Period | C11: OPEX | D11: MTD-NET | E11: Minus Sign | F11: Month | G11: 01/07/25..31/07/25 | H11: =FALSE() -> FALSE | U11: 260 | V11: Selling Expenses | W11: 2396.58 | X11: 1175.31 | Y11: 3332.11 | Z11: 3376.45 | AA11: 6493.16 | AB11: 2413.92 | AC11: 3630.66 | AD11: 2732.12 | AE11: 2668.06 | AF11: 0 | AG11: 0 | AH11: 0 | AI11: 21939.85 | AJ11: 0 | AK11: 0
A12: CASH BURN | B12: Cost Incurred in Period | C12: OPEX | D12: MTD-NET | E12: Minus Sign | F12: Month | G12: 01/07/25..31/07/25 | H12: =FALSE() -> FALSE | U12: 270 | V12: Travel & Entertainment | W12: 397.26 | X12: 135.06 | Y12: 902.64 | Z12: 0 | AA12: 2378.75 | AB12: 536.77 | AC12: 1770.32 | AD12: 4595.04 | AE12: 840 | AF12: 0 | AG12: 0 | AH12: 0 | AI12: 6074.14 | AJ12: 0 | AK12: 0
A13: CASH BURN | B13: Cost Incurred in Period | C13: OPEX | D13: MTD-NET | E13: Minus Sign | F13: Month | G13: 01/07/25..31/07/25 | H13: =FALSE() -> FALSE | U13: 280 | V13: Office Equipment | W13: 34.01 | X13: 1.55 | Y13: 71.7 | Z13: 23.19 | AA13: 269.96 | AB13: 0 | AC13: 0 | AD13: 0 | AE13: 0 | AF13: 0 | AG13: 0 | AH13: 0 | AI13: 400.41 | AJ13: 0 | AK13: 0
A14: CASH BURN | B14: Cost Incurred in Period | C14: OPEX | D14: MTD-NET | E14: Minus Sign | F14: Month | G14: 01/07/25..31/07/25 | H14: =FALSE() -> FALSE | U14: 290 | V14: Auto Expenses | W14: 507.7 | X14: 853.25 | Y14: 1046.94 | Z14: 504.12 | AA14: 926.61 | AB14: 1659.25 | AC14: 965.23 | AD14: 899.24 | AE14: 826.56 | AF14: 0 | AG14: 0 | AH14: 0 | AI14: 6447.42 | AJ14: 0 | AK14: 0
... A17: CASH BURN | B17: Cost Incurred in Period | C17: OPEX | D17: MTD-NET | E17: Minus Sign | F17: Month | G17: 01/07/25..31/07/25 | H17: =FALSE() -> FALSE | U17: 320 | V17: Other Expenses | W17: 559.42 | X17: 1303.5 | Y17: 456.18 | Z17: 3670.99 | AA17: 5805.59 | AB17: 4170.46 | AC17: 4342.1 | AD17: -3690.55 | AE17: 1344.69 | AF17: 0 | AG17: 0 | AH17: 0 | AI17: 20271.35 | AJ17: 0 | AK17: 0
A18: CASH BURN | B18: Cost Incurred in Period | C18: OPEX | D18: MTD-NET | E18: Minus Sign | F18: Month | G18: 01/07/25..31/07/25 | H18: =FALSE() -> FALSE | W18: 0 | X18: 0 | Y18: 0 | Z18: 0 | AA18: 0 | AB18: 0 | AC18: 0 | AD18: 0 | AE18: 0 | AF18: 0 | AG18: 0 | AH18: 0 | AI18: 0 | AJ18: 0 | AK18: 0
A19: CASH BURN | B19: Cost Incurred in Period | C19: OPEX | D19: MTD-NET | E19: Minus Sign | F19: Month | G19: 01/07/25..31/07/25 | H19: =FALSE() -> FALSE | U19: F1 | V19: TOTAL OPERATING EXPENSES | W19: 87820.08 | X19: 92684.74 | Y19: 99172.82 | Z19: 112646.36 | AA19: 120460.82 | AB19: 118008.65 | AC19: 113690.38 | AD19: 112782.44 | AE19: 129063.87 | AF19: 0 | AG19: 0 | AH19: 0 | AI19: 743623.79 | AJ19: 0 | AK19: 0
